Workbook
Name CouponRate: 'Intro Notes'!$B$10
Name Date: 'Intro Notes'!$B$5
Name Face_Value: 'Intro Notes'!$B$14
Name InterestRate: 'Intro Notes'!$B$12
Name Term: 'Intro Notes'!$B$9

Sheet Intro Notes
B2: This workbook contains the analysis of the first 6 months of operations for 165WA, the first year, and the first two years.
B4: Recall that on:
B5: 46055
B6: we established 165 Whitney Associates LLC, raised $50,000 cash in exchange for equity in 165 WA and used the $50,000 to buy 30 year U.S Governments bonds that we assume have a:
B8: We assume the bonds have a:
B9: 30 | C9: year Term, and a
B10: 0.04 | C10: coupon, payable semi-annually.
B11: The bonds were priced to yield a semi-annually compounded return of:
B12: 0.0487
B13: Our $50,000 cash bought bonds with a face value of:
B14: 57901.64
B16: We construct financial statements for the first 6 months, the first year
B17: and the second year of 165WA's life:
B19: Balance Sheets
B20: Income Statements
B21: Statements of Changes in Members' Equity
B22: Cash Flow Statements
B23: Reconciliations of Net Income and Cash Flow from Operations
B25: We then explore the effects of changes in interest rates.

Sheet CashFlowMap
A1: Face Value | B1: =Face_Value -> 57901.64
A2: Coupon | B2: =CouponRate -> 0.04 | C2: semi-annual
A3: Term | B3: =Term -> 30 | C3: years
C4: Time | D4: Coupon | E4: Face | F4: CashFlow
C5: 0
C6: 1 | D6: =($B$2/2)*$B$1 -> 1158.0328 | F6: =D6+E6 -> 1158.0328
C7: 2 | D7: =($B$2/2)*$B$1 -> 1158.0328 | F7: =D7+E7 -> 1158.0328
C8: 3 | D8: =($B$2/2)*$B$1 -> 1158.0328 | F8: =D8+E8 -> 1158.0328
C9: 4 | D9: =($B$2/2)*$B$1 -> 1158.0328 | F9: =D9+E9 -> 1158.0328
C10: 5 | D10: =($B$2/2)*$B$1 -> 1158.0328 | F10: =D10+E10 -> 1158.0328
C11: 6 | D11: =($B$2/2)*$B$1 -> 1158.0328 | F11: =D11+E11 -> 1158.0328
C12: 7 | D12: =($B$2/2)*$B$1 -> 1158.0328 | F12: =D12+E12 -> 1158.0328
C13: 8 | D13: =($B$2/2)*$B$1 -> 1158.0328 | F13: =D13+E13 -> 1158.0328
C14: 9 | D14: =($B$2/2)*$B$1 -> 1158.0328 | F14: =D14+E14 -> 1158.0328
C15: 10 | D15: =($B$2/2)*$B$1 -> 1158.0328 | F15: =D15+E15 -> 1158.0328
C16: 11 | D16: =($B$2/2)*$B$1 -> 1158.0328 | F16: =D16+E16 -> 1158.0328
C17: 12 | D17: =($B$2/2)*$B$1 -> 1158.0328 | F17: =D17+E17 -> 1158.0328
... C64: 59 | D64: =($B$2/2)*$B$1 -> 1158.0328 | F64: =D64+E64 -> 1158.0328
C65: 60 | D65: =($B$2/2)*$B$1 -> 1158.0328 | E65: =B1 -> 57901.64 | F65: =D65+E65 -> 59059.673
B66: Total cash | F66: =SUM(F6:F65) -> 127383.61
B67: Repay amt loaned | F67: -50000
B68: Total interest | F68: =F66+F67 -> 77383.608

Sheet Economics of 165WA's investment
A1: Face Value | B1: =Face_Value -> 57901.64 | D1: Date | E1: =Date -> 46055
A2: Term | B2: =Term -> 30 | C2: years
A3: Coupons | B3: =CouponRate -> 0.04 | C3: semi annual | E3: PV at time 0 | F3: =SUM(D8:D67) -> 50000.002
A4: Yield | B4: =InterestRate -> 0.0487 | C4: Comp semi-annually
A6: Time (years) | B6: Coupon | C6: Face | D6: PV of Cash Flow | F6: Time (years) | G6: Bond Value | H6: Interest Income | I6: Check
A7: 0 | F7: 0 | G7: =F3 -> 50000.002
A8: 0.5 | B8: =$B$1*$B$3/2 -> 1158.0328 | D8: =(B8+C8)/(1+$B$4/2)^(2*A8) -> 1130.505 | F8: 0.5 | G8: =G7+H8-B8 -> 50059.469 | H8: =G7*($B$4/2) -> 1217.5 | I8: =G7-B8+H8 -> 50059.469
A9: 1 | B9: =$B$1*$B$3/2 -> 1158.0328 | D9: =(B9+C9)/(1+$B$4/2)^(2*A9) -> 1103.6316 | F9: 1 | G9: =G8+H9-B9 -> 50120.384 | H9: =G8*($B$4/2) -> 1218.9481 | I9: =G8-B9+H9 -> 50120.384
A10: 1.5 | B10: =$B$1*$B$3/2 -> 1158.0328 | D10: =(B10+C10)/(1+$B$4/2)^(2*A10) -> 1077.397 | F10: 1.5 | G10: =G9+H10-B10 -> 50182.783 | H10: =G9*($B$4/2) -> 1220.4314 | I10: =G9-B10+H10 -> 50182.783
A11: 2 | B11: =$B$1*$B$3/2 -> 1158.0328 | D11: =(B11+C11)/(1+$B$4/2)^(2*A11) -> 1051.786 | F11: 2 | G11: =G10+H11-B11 -> 50246.701 | H11: =G10*($B$4/2) -> 1221.9508 | I11: =G10-B11+H11 -> 50246.701
A12: 2.5 | B12: =$B$1*$B$3/2 -> 1158.0328 | D12: =(B12+C12)/(1+$B$4/2)^(2*A12) -> 1026.7838 | F12: 2.5 | G12: =G11+H12-B12 -> 50312.175 | H12: =G11*($B$4/2) -> 1223.5072 | I12: =G11-B12+H12 -> 50312.175
A13: 3 | B13: =$B$1*$B$3/2 -> 1158.0328 | D13: =(B13+C13)/(1+$B$4/2)^(2*A13) -> 1002.3759 | F13: 3 | G13: =G12+H13-B13 -> 50379.244 | H13: =G12*($B$4/2) -> 1225.1015 | I13: =G12-B13+H13 -> 50379.244
A14: 3.5 | B14: =$B$1*$B$3/2 -> 1158.0328 | D14: =(B14+C14)/(1+$B$4/2)^(2*A14) -> 978.54828 | F14: 3.5 | G14: =G13+H14-B14 -> 50447.946 | H14: =G13*($B$4/2) -> 1226.7346 | I14: =G13-B14+H14 -> 50447.946
A15: 4 | B15: =$B$1*$B$3/2 -> 1158.0328 | D15: =(B15+C15)/(1+$B$4/2)^(2*A15) -> 955.28704 | F15: 4 | G15: =G14+H15-B15 -> 50518.32 | H15: =G14*($B$4/2) -> 1228.4075 | I15: =G14-B15+H15 -> 50518.32
A16: 4.5 | B16: =$B$1*$B$3/2 -> 1158.0328 | D16: =(B16+C16)/(1+$B$4/2)^(2*A16) -> 932.57875 | F16: 4.5 | G16: =G15+H16-B16 -> 50590.409 | H16: =G15*($B$4/2) -> 1230.1211 | I16: =G15-B16+H16 -> 50590.409
A17: 5 | B17: =$B$1*$B$3/2 -> 1158.0328 | D17: =(B17+C17)/(1+$B$4/2)^(2*A17) -> 910.41026 | F17: 5 | G17: =G16+H17-B17 -> 50664.252 | H17: =G16*($B$4/2) -> 1231.8765 | I17: =G16-B17+H17 -> 50664.252
A18: 5.5 | B18: =$B$1*$B$3/2 -> 1158.0328 | D18: =(B18+C18)/(1+$B$4/2)^(2*A18) -> 888.76874 | F18: 5.5 | G18: =G17+H18-B18 -> 50739.894 | H18: =G17*($B$4/2) -> 1233.6745 | I18: =G17-B18+H18 -> 50739.894
A19: 6 | B19: =$B$1*$B$3/2 -> 1158.0328 | D19: =(B19+C19)/(1+$B$4/2)^(2*A19) -> 867.64167 | F19: 6 | G19: =G18+H19-B19 -> 50817.378 | H19: =G18*($B$4/2) -> 1235.5164 | I19: =G18-B19+H19 -> 50817.378
... A66: 29.5 | B66: =$B$1*$B$3/2 -> 1158.0328 | D66: =(B66+C66)/(1+$B$4/2)^(2*A66) -> 280.07022 | F66: 29.5 | G66: =G65+H66-B66 -> 57655.755 | H66: =G65*($B$4/2) -> 1398.0727 | I66: =G65-B66+H66 -> 57655.755
A67: 30 | B67: =$B$1*$B$3/2 -> 1158.0328 | C67: =B1 -> 57901.64 | D67: =(B67+C67)/(1+$B$4/2)^(2*A67) -> 13944.044 | F67: 30 | G67: =G66+H67-B67 -> 57901.64 | H67: =G66*($B$4/2) -> 1403.9176 | I67: =G66-B67+H67 -> 57901.64
A68: Total Coupon Payments | C68: =SUM(B8:B67) -> 69481.968 | G68: =G67-C67 -> -1.0113581e-09 | H68: =SUM(H8:H67) -> 77383.606 | I68: Total Interest Revenue
A69: Total Cash Flows | C69: =C67+C68 -> 127383.61
A70: Cost | C70: -50000
A71: Total Interest Revenue | C71: =C69+C70 -> 77383.608

Sheet PVs_thru_Time_Calculations
A1: Face Value | B1: =Face_Value -> 57901.64
A2: Term | B2: =Term -> 30 | C2: years
A3: Coupons | B3: =CouponRate -> 0.04 | C3: semi annual | D3: Time | E3: 0 | F3: 1 | G3: 2 | H3: 3 | I3: 4 | J3: 5 | K3: 6 | L3: 7 | M3: 8 | N3: 9 | O3: 10 | P3: 11 | Q3: 12 | R3: 13 | S3: 14 | T3: 15 | U3: 16 | V3: 17 | W3: 18 | X3: 19 | Y3: 20 | Z3: 21 | AA3: 22 | AB3: 23 | AC3: 24 | AD3: 25 | AE3: 26 | AF3: 27 | AG3: 28 | AH3: 29 | AI3: 30 | AL3: =D3 -> Time | AM3: PV @ Time | AN3: Interest Rate | AO3: Cash in Jar
A4: Yield | B4: =InterestRate -> 0.0487 | D4: PV @ Time | E4: =SUM(E21:E80) -> 50000.002 | F4: =SUM(F21:F80) -> 59206.671 | G4: =SUM(G21:G80) -> 43106.558 | H4: =SUM(H21:H80) -> 50379.244 | I4: =SUM(I21:I80) -> 59128.68 | J4: =SUM(J21:J80) -> 50664.252 | K4: =SUM(K21:K80) -> 50817.378 | L4: =SUM(L21:L80) -> 38828.505 | ... AI4: =SUM(AI21:AI80) -> 57901.64 | AK4: =CHAR(68+ROW(A1)) -> E | AL4: {=INDIRECT($AK4&3)+25} -> 25 | AM4: {=INDIRECT($AK4&4)/1000} -> 50.000002 | AN4: {=INDIRECT($AK4&5)} -> 0.0487 | AO4: =0 -> 0
D5: Interest Rate | E5: {=_xlfn.IFS(C7,E7:AI7,C8,E8:AI8,C9,E9:AI9,C10,E10:AI10,C11,E11:AI11,NOT(OR(C7,C8,C9,C10,C11)),E7:AI7)} -> 0.0487 | F5: 0.0387 | G5: 0.0587 | H5: 0.0487 | I5: 0.0387 | J5: 0.0487 | K5: 0.0487 | L5: 0.0687 | M5: 0.0587 | N5: 0.0687 | O5: 0.0787 | P5: 0.0887 | Q5: 0.0787 | R5: 0.0687 | S5: 0.0787 | T5: 0.0887 | U5: 0.0787 | V5: 0.0887 | W5: 0.0687 | X5: 0.0687 | Y5: 0.0587 | Z5: 0.0487 | AA5: 0.0487 | AB5: 0.0687 | AC5: 0.0587 | AD5: 0.0687 | AE5: 0.0787 | AF5: 0.0887 | AG5: 0.0687 | AH5: 0.0687 | AI5: 0.0587 | AK5: =CHAR(68+ROW(A2)) -> F | AL5: {=INDIRECT($AK5&3)+25} -> 26 | AM5: {=INDIRECT($AK5&4)/1000} -> 59.206671 | AN5: {=INDIRECT($AK5&5)} -> 0.0387 | AO5: =(AO4+(2*$D$21)/1000) -> 2.3160656
AK6: =CHAR(68+ROW(A3)) -> G | AL6: {=INDIRECT($AK6&3)+25} -> 27 | AM6: {=INDIRECT($AK6&4)/1000} -> 43.106558 | AN6: {=INDIRECT($AK6&5)} -> 0.0587 | AO6: =(AO5+(2*$D$21)/1000) -> 4.6321312
C7: FALSE | D7: Constant Rate | E7: =$B$4 -> 0.0487 | F7: =E7 -> 0.0487 | G7: =F7 -> 0.0487 | H7: =G7 -> 0.0487 | I7: =H7 -> 0.0487 | J7: =I7 -> 0.0487 | K7: =J7 -> 0.0487 | L7: =K7 -> 0.0487 | M7: =L7 -> 0.0487 | ... AI7: =AH7 -> 0.0487 | AK7: =CHAR(68+ROW(A4)) -> H | AL7: {=INDIRECT($AK7&3)+25} -> 28 | AM7: {=INDIRECT($AK7&4)/1000} -> 50.379244 | AN7: {=INDIRECT($AK7&5)} -> 0.0487 | AO7: =(AO6+(2*$D$21)/1000) -> 6.9481968
C8: FALSE | D8: One Change (rate increase) | E8: =$B$4 -> 0.0487 | F8: =F7 -> 0.0487 | G8: =G7 -> 0.0487 | H8: =H7+0.04 -> 0.0887 | I8: =I7+0.04 -> 0.0887 | J8: =J7+0.04 -> 0.0887 | K8: =K7+0.04 -> 0.0887 | L8: =L7+0.04 -> 0.0887 | M8: =M7+0.04 -> 0.0887 | N8: =N7+0.04 -> 0.0887 | O8: =O7+0.04 -> 0.0887 | ... AI8: =AI7+0.04 -> 0.0887 | AK8: =CHAR(68+ROW(A5)) -> I | AL8: {=INDIRECT($AK8&3)+25} -> 29 | AM8: {=INDIRECT($AK8&4)/1000} -> 59.12868 | AN8: {=INDIRECT($AK8&5)} -> 0.0387 | AO8: =(AO7+(2*$D$21)/1000) -> 9.2642624
C9: TRUE | D9: Random | E9: =$B$4 -> 0.0487 | F9: =E9+RANDBETWEEN(F14,F15)/100 -> 0.0387 | G9: =F9+RANDBETWEEN(G14,G15)/100 -> 0.0587 | H9: =G9+RANDBETWEEN(H14,H15)/100 -> 0.0487 | I9: =H9+RANDBETWEEN(I14,I15)/100 -> 0.0387 | J9: =I9+RANDBETWEEN(J14,J15)/100 -> 0.0487 | K9: =J9+RANDBETWEEN(K14,K15)/100 -> 0.0487 | L9: =K9+RANDBETWEEN(L14,L15)/100 -> 0.0687 | M9: =L9+RANDBETWEEN(M14,M15)/100 -> 0.0587 | ... AI9: =AH9+RANDBETWEEN(AI14,AI15)/100 -> 0.0587 | AK9: J | AL9: {=INDIRECT($AK9&3)+25} -> 30 | AM9: {=INDIRECT($AK9&4)/1000} -> 50.664252 | AN9: {=INDIRECT($AK9&5)} -> 0.0487 | AO9: =(AO8+(2*$D$21)/1000) -> 11.580328
C10: FALSE | D10: Oscillating | E10: =$B$4 -> 0.0487 | F10: =InterestRate-0.03 -> 0.0187 | G10: =InterestRate+0.03 -> 0.0787 | H10: =InterestRate-0.03 -> 0.0187 | I10: =InterestRate+0.03 -> 0.0787 | J10: =InterestRate-0.03 -> 0.0187 | K10: =InterestRate+0.03 -> 0.0787 | L10: =InterestRate-0.03 -> 0.0187 | M10: =InterestRate+0.03 -> 0.0787 | N10: =InterestRate-0.03 -> 0.0187 | O10: =InterestRate+0.03 -> 0.0787 | P10: =InterestRate-0.03 -> 0.0187 | Q10: =InterestRate+0.03 -> 0.0787 | R10: =InterestRate-0.03 -> 0.0187 | S10: =InterestRate+0.03 -> 0.0787 | T10: =InterestRate-0.03 -> 0.0187 | U10: =InterestRate+0.03 -> 0.0787 | V10: =InterestRate-0.03 -> 0.0187 | W10: =InterestRate+0.03 -> 0.0787 | X10: =InterestRate-0.03 -> 0.0187 | Y10: =InterestRate+0.03 -> 0.0787 | Z10: =InterestRate-0.03 -> 0.0187 | AA10: =InterestRate+0.03 -> 0.0787 | AB10: =InterestRate-0.03 -> 0.0187 | AC10: =InterestRate+0.03 -> 0.0787 | AD10: =InterestRate-0.03 -> 0.0187 | AE10: =InterestRate+0.03 -> 0.0787 | AF10: =InterestRate-0.03 -> 0.0187 | AG10: =InterestRate+0.03 -> 0.0787 | AH10: =InterestRate-0.03 -> 0.0187 | AI10: =InterestRate+0.03 -> 0.0787 | AK10: K | AL10: {=INDIRECT($AK10&3)+25} -> 31 | AM10: {=INDIRECT($AK10&4)/1000} -> 50.817378 | AN10: {=INDIRECT($AK10&5)} -> 0.0487 | AO10: =(AO9+(2*$D$21)/1000) -> 13.896394
C11: FALSE | D11: One Change (rate decrease) | E11: =$B$4 -> 0.0487 | F11: =F7 -> 0.0487 | G11: =G7 -> 0.0487 | H11: =H7-0.01 -> 0.0387 | I11: =I7-0.01 -> 0.0387 | J11: =J7-0.01 -> 0.0387 | K11: =K7-0.01 -> 0.0387 | L11: =L7-0.01 -> 0.0387 | M11: =M7-0.01 -> 0.0387 | N11: =N7-0.01 -> 0.0387 | O11: =O7-0.01 -> 0.0387 | ... AI11: =AI7-0.01 -> 0.0387 | AK11: L | AL11: {=INDIRECT($AK11&3)+25} -> 32 | AM11: {=INDIRECT($AK11&4)/1000} -> 38.828505 | AN11: {=INDIRECT($AK11&5)} -> 0.0687 | AO11: =(AO10+(2*$D$21)/1000) -> 16.212459
AK12: M | AL12: {=INDIRECT($AK12&3)+25} -> 33 | AM12: {=INDIRECT($AK12&4)/1000} -> 44.621556 | AN12: {=INDIRECT($AK12&5)} -> 0.0587 | AO12: =(AO11+(2*$D$21)/1000) -> 18.528525
D13: Parameters for random changes: | AK13: N | AL13: {=INDIRECT($AK13&3)+25} -> 34 | AM13: {=INDIRECT($AK13&4)/1000} -> 39.568464 | AN13: {=INDIRECT($AK13&5)} -> 0.0687 | AO13: =(AO12+(2*$D$21)/1000) -> 20.84459
D14: Decrease | E14: =-(25*$B$4) -> -1.2175 | F14: =-(25*E9) -> -1.2175 | G14: =-(25*F9) -> -0.9675 | H14: =-(25*G9) -> -1.4675 | I14: =-(25*H9) -> -1.2175 | J14: =-(25*I9) -> -0.9675 | K14: =-(25*J9) -> -1.2175 | L14: =-(25*K9) -> -1.2175 | M14: =-(25*L9) -> -1.7175 | ... AI14: =-(25*AH9) -> -1.7175 | AK14: O | AL14: {=INDIRECT($AK14&3)+25} -> 35 | AM14: {=INDIRECT($AK14&4)/1000} -> 35.509752 | AN14: {=INDIRECT($AK14&5)} -> 0.0787 | AO14: =(AO13+(2*$D$21)/1000) -> 23.160656
D15: Increase | E15: =25*B4 -> 1.2175 | F15: =0.1/E9 -> 2.0533881 | G15: =0.1/F9 -> 2.5839793 | H15: =0.1/G9 -> 1.7035775 | I15: =0.1/H9 -> 2.0533881 | J15: =0.1/I9 -> 2.5839793 | K15: =0.1/J9 -> 2.0533881 | L15: =0.1/K9 -> 2.0533881 | M15: =0.1/L9 -> 1.4556041 | ... AI15: =0.1/AH9 -> 1.4556041 | AK15: P | AL15: {=INDIRECT($AK15&3)+25} -> 36 | AM15: {=INDIRECT($AK15&4)/1000} -> 32.222692 | AN15: {=INDIRECT($AK15&5)} -> 0.0887 | AO15: =(AO14+(2*$D$21)/1000) -> 25.476722
AK16: Q | AL16: {=INDIRECT($AK16&3)+25} -> 37 | AM16: {=INDIRECT($AK16&4)/1000} -> 36.524845 | AN16: {=INDIRECT($AK16&5)} -> 0.0787 | AO16: =(AO15+(2*$D$21)/1000) -> 27.792787
AK17: R | AL17: {=INDIRECT($AK17&3)+25} -> 38 | AM17: {=INDIRECT($AK17&4)/1000} -> 41.384954 | AN17: {=INDIRECT($AK17&5)} -> 0.0687 | AO17: =(AO16+(2*$D$21)/1000) -> 30.108853
AK18: S | AL18: {=INDIRECT($AK18&3)+25} -> 39 | AM18: {=INDIRECT($AK18&4)/1000} -> 37.709395 | AN18: {=INDIRECT($AK18&5)} -> 0.0787 | AO18: =(AO17+(2*$D$21)/1000) -> 32.424918
A19: Time (years) | B19: Coupon | C19: Face | D19: Total Cash Flow | AK19: T | AL19: {=INDIRECT($AK19&3)+25} -> 40 | AM19: {=INDIRECT($AK19&4)/1000} -> 34.759192 | AN19: {=INDIRECT($AK19&5)} -> 0.0887 | AO19: =(AO18+(2*$D$21)/1000) -> 34.740984
A20: 0 | AK20: U | AL20: {=INDIRECT($AK20&3)+25} -> 41 | AM20: {=INDIRECT($AK20&4)/1000} -> 39.091689 | AN20: {=INDIRECT($AK20&5)} -> 0.0787 | AO20: =(AO19+(2*$D$21)/1000) -> 37.05705
A21: 0.5 | B21: =$B$1*$B$3/2 -> 1158.0328 | D21: =B21+C21 -> 1158.0328 | E21: =(D21)/(1+$E$5/2)^(2*A21) -> 1130.505 | AK21: V | AL21: {=INDIRECT($AK21&3)+25} -> 42 | AM21: {=INDIRECT($AK21&4)/1000} -> 36.398452 | AN21: {=INDIRECT($AK21&5)} -> 0.0887 | AO21: =(AO20+(2*$D$21)/1000) -> 39.373115
A22: 1 | B22: =$B$1*$B$3/2 -> 1158.0328 | D22: =B22+C22 -> 1158.0328 | E22: =(D22)/(1+$E$5/2)^(2*A22) -> 1103.6316 | AK22: W | AL22: {=INDIRECT($AK22&3)+25} -> 43 | AM22: {=INDIRECT($AK22&4)/1000} -> 44.467378 | AN22: {=INDIRECT($AK22&5)} -> 0.0687 | AO22: =(AO21+(2*$D$21)/1000) -> 41.689181
A23: 1.5 | B23: =$B$1*$B$3/2 -> 1158.0328 | D23: =B23+C23 -> 1158.0328 | E23: =(D23)/(1+$E$5/2)^(2*A23) -> 1077.397 | F23: =($D23)/((1+$F$5/2)^(2*($A23-F$3))) -> 1136.0502 | AK23: X | AL23: {=INDIRECT($AK23&3)+25} -> 44 | AM23: {=INDIRECT($AK23&4)/1000} -> 45.218911 | AN23: {=INDIRECT($AK23&5)} -> 0.0687 | AO23: =(AO22+(2*$D$21)/1000) -> 44.005246
A24: 2 | B24: =$B$1*$B$3/2 -> 1158.0328 | D24: =B24+C24 -> 1158.0328 | E24: =(D24)/(1+$E$5/2)^(2*A24) -> 1051.786 | F24: =($D24)/((1+$F$5/2)^(2*($A24-F$3))) -> 1114.4849 | AK24: Y | AL24: {=INDIRECT($AK24&3)+25} -> 45 | AM24: {=INDIRECT($AK24&4)/1000} -> 49.79865 | AN24: {=INDIRECT($AK24&5)} -> 0.0587 | AO24: =(AO23+(2*$D$21)/1000) -> 46.321312
A25: 2.5 | B25: =$B$1*$B$3/2 -> 1158.0328 | D25: =B25+C25 -> 1158.0328 | E25: =(D25)/(1+$E$5/2)^(2*A25) -> 1026.7838 | F25: =($D25)/((1+$F$5/2)^(2*($A25-F$3))) -> 1093.329 | G25: =($D25)/((1+$G$5/2)^(2*($A25-G$3))) -> 1125.0136 | AK25: Z | AL25: {=INDIRECT($AK25&3)+25} -> 46 | AM25: {=INDIRECT($AK25&4)/1000} -> 54.266084 | AN25: {=INDIRECT($AK25&5)} -> 0.0487 | AO25: =(AO24+(2*$D$21)/1000) -> 48.637378
A26: 3 | B26: =$B$1*$B$3/2 -> 1158.0328 | D26: =B26+C26 -> 1158.0328 | E26: =(D26)/(1+$E$5/2)^(2*A26) -> 1002.3759 | F26: =($D26)/((1+$F$5/2)^(2*($A26-F$3))) -> 1072.5747 | G26: =($D26)/((1+$G$5/2)^(2*($A26-G$3))) -> 1092.936 | AK26: A | AL26: {=INDIRECT("a"&$AK26&3)+25} -> 47 | AM26: {=INDIRECT("a"&$AK26&4)/1000} -> 54.596754 | AN26: {=INDIRECT("a"&$AK26&5)} -> 0.0487 | AO26: =(AO25+(2*$D$21)/1000) -> 50.953443
A27: 3.5 | B27: =$B$1*$B$3/2 -> 1158.0328 | D27: =B27+C27 -> 1158.0328 | E27: =(D27)/(1+$E$5/2)^(2*A27) -> 978.54828 | F27: =($D27)/((1+$F$5/2)^(2*($A27-F$3))) -> 1052.2144 | G27: =($D27)/((1+$G$5/2)^(2*($A27-G$3))) -> 1061.7729 | H27: =($D27)/((1+$H$5/2)^(2*($A27-H$3))) -> 1130.505 | AK27: B | AL27: {=INDIRECT("a"&$AK27&3)+25} -> 48 | AM27: {=INDIRECT("a"&$AK27&4)/1000} -> 48.788212 | AN27: {=INDIRECT("a"&$AK27&5)} -> 0.0687 | AO27: =(AO26+(2*$D$21)/1000) -> 53.269509
A28: 4 | B28: =$B$1*$B$3/2 -> 1158.0328 | D28: =B28+C28 -> 1158.0328 | E28: =(D28)/(1+$E$5/2)^(2*A28) -> 955.28704 | F28: =($D28)/((1+$F$5/2)^(2*($A28-F$3))) -> 1032.2405 | G28: =($D28)/((1+$G$5/2)^(2*($A28-G$3))) -> 1031.4985 | H28: =($D28)/((1+$H$5/2)^(2*($A28-H$3))) -> 1103.6316 | AK28: C | AL28: {=INDIRECT("a"&$AK28&3)+25} -> 49 | AM28: {=INDIRECT("a"&$AK28&4)/1000} -> 52.491768 | AN28: {=INDIRECT("a"&$AK28&5)} -> 0.0587 | AO28: =(AO27+(2*$D$21)/1000) -> 55.585574
A29: 4.5 | B29: =$B$1*$B$3/2 -> 1158.0328 | D29: =B29+C29 -> 1158.0328 | E29: =(D29)/(1+$E$5/2)^(2*A29) -> 932.57875 | F29: =($D29)/((1+$F$5/2)^(2*($A29-F$3))) -> 1012.6458 | G29: =($D29)/((1+$G$5/2)^(2*($A29-G$3))) -> 1002.0872 | H29: =($D29)/((1+$H$5/2)^(2*($A29-H$3))) -> 1077.397 | I29: =($D29)/((1+$I$5/2)^(2*($A29-I$3))) -> 1136.0502 | AK29: D | AL29: {=INDIRECT("a"&$AK29&3)+25} -> 50 | AM29: {=INDIRECT("a"&$AK29&4)/1000} -> 50.968773 | AN29: {=INDIRECT("a"&$AK29&5)} -> 0.0687 | AO29: =(AO28+(2*$D$21)/1000) -> 57.90164
A30: 5 | B30: =$B$1*$B$3/2 -> 1158.0328 | D30: =B30+C30 -> 1158.0328 | E30: =(D30)/(1+$E$5/2)^(2*A30) -> 910.41026 | F30: =($D30)/((1+$F$5/2)^(2*($A30-F$3))) -> 993.42307 | G30: =($D30)/((1+$G$5/2)^(2*($A30-G$3))) -> 973.51455 | H30: =($D30)/((1+$H$5/2)^(2*($A30-H$3))) -> 1051.786 | I30: =($D30)/((1+$I$5/2)^(2*($A30-I$3))) -> 1114.4849 | AK30: E | AL30: {=INDIRECT("a"&$AK30&3)+25} -> 51 | AM30: {=INDIRECT("a"&$AK30&4)/1000} -> 50.338007 | AN30: {=INDIRECT("a"&$AK30&5)} -> 0.0787 | AO30: =(AO29+(2*$D$21)/1000) -> 60.217706
A31: 5.5 | B31: =$B$1*$B$3/2 -> 1158.0328 | D31: =B31+C31 -> 1158.0328 | E31: =(D31)/(1+$E$5/2)^(2*A31) -> 888.76874 | F31: =($D31)/((1+$F$5/2)^(2*($A31-F$3))) -> 974.56524 | G31: =($D31)/((1+$G$5/2)^(2*($A31-G$3))) -> 945.7566 | H31: =($D31)/((1+$H$5/2)^(2*($A31-H$3))) -> 1026.7838 | I31: =($D31)/((1+$I$5/2)^(2*($A31-I$3))) -> 1093.329 | J31: =($D31)/((1+$J$5/2)^(2*($A31-J$3))) -> 1130.505 | AK31: F | AL31: {=INDIRECT("a"&$AK31&3)+25} -> 52 | AM31: {=INDIRECT("a"&$AK31&4)/1000} -> 50.614254 | AN31: {=INDIRECT("a"&$AK31&5)} -> 0.0887 | AO31: =(AO30+(2*$D$21)/1000) -> 62.533771
A32: 6 | B32: =$B$1*$B$3/2 -> 1158.0328 | D32: =B32+C32 -> 1158.0328 | E32: =(D32)/(1+$E$5/2)^(2*A32) -> 867.64167 | F32: =($D32)/((1+$F$5/2)^(2*($A32-F$3))) -> 956.06537 | G32: =($D32)/((1+$G$5/2)^(2*($A32-G$3))) -> 918.79011 | H32: =($D32)/((1+$H$5/2)^(2*($A32-H$3))) -> 1002.3759 | I32: =($D32)/((1+$I$5/2)^(2*($A32-I$3))) -> 1072.5747 | J32: =($D32)/((1+$J$5/2)^(2*($A32-J$3))) -> 1103.6316 | AK32: G | AL32: {=INDIRECT("a"&$AK32&3)+25} -> 53 | AM32: {=INDIRECT("a"&$AK32&4)/1000} -> 54.845005 | AN32: {=INDIRECT("a"&$AK32&5)} -> 0.0687 | AO32: =(AO31+(2*$D$21)/1000) -> 64.849837
A33: 6.5 | B33: =$B$1*$B$3/2 -> 1158.0328 | D33: =B33+C33 -> 1158.0328 | E33: =(D33)/(1+$E$5/2)^(2*A33) -> 847.01681 | F33: =($D33)/((1+$F$5/2)^(2*($A33-F$3))) -> 937.91668 | G33: =($D33)/((1+$G$5/2)^(2*($A33-G$3))) -> 892.59252 | H33: =($D33)/((1+$H$5/2)^(2*($A33-H$3))) -> 978.54828 | I33: =($D33)/((1+$I$5/2)^(2*($A33-I$3))) -> 1052.2144 | J33: =($D33)/((1+$J$5/2)^(2*($A33-J$3))) -> 1077.397 | K33: =($D33)/((1+$K$5/2)^(2*($A33-K$3))) -> 1130.505 | AK33: H | AL33: {=INDIRECT("a"&$AK33&3)+25} -> 54 | AM33: {=INDIRECT("a"&$AK33&4)/1000} -> 56.321726 | AN33: {=INDIRECT("a"&$AK33&5)} -> 0.0687 | AO33: =(AO32+(2*$D$21)/1000) -> 67.165902
A34: 7 | B34: =$B$1*$B$3/2 -> 1158.0328 | D34: =B34+C34 -> 1158.0328 | E34: =(D34)/(1+$E$5/2)^(2*A34) -> 826.88222 | F34: =($D34)/((1+$F$5/2)^(2*($A34-F$3))) -> 920.11251 | G34: =($D34)/((1+$G$5/2)^(2*($A34-G$3))) -> 867.1419 | H34: =($D34)/((1+$H$5/2)^(2*($A34-H$3))) -> 955.28704 | I34: =($D34)/((1+$I$5/2)^(2*($A34-I$3))) -> 1032.2405 | J34: =($D34)/((1+$J$5/2)^(2*($A34-J$3))) -> 1051.786 | K34: =($D34)/((1+$K$5/2)^(2*($A34-K$3))) -> 1103.6316 | AK34: I | AL34: {=INDIRECT("a"&$AK34&3)+25} -> 55 | AM34: {=INDIRECT("a"&$AK34&4)/1000} -> 57.90164 | AN34: {=INDIRECT("a"&$AK34&5)} -> 0.0587 | AO34: =AO33+(2*$D$21+Face_Value)/1000 -> 127.38361
A35: 7.5 | B35: =$B$1*$B$3/2 -> 1158.0328 | D35: =B35+C35 -> 1158.0328 | E35: =(D35)/(1+$E$5/2)^(2*A35) -> 807.22626 | F35: =($D35)/((1+$F$5/2)^(2*($A35-F$3))) -> 902.6463 | G35: =($D35)/((1+$G$5/2)^(2*($A35-G$3))) -> 842.41696 | H35: =($D35)/((1+$H$5/2)^(2*($A35-H$3))) -> 932.57875 | I35: =($D35)/((1+$I$5/2)^(2*($A35-I$3))) -> 1012.6458 | J35: =($D35)/((1+$J$5/2)^(2*($A35-J$3))) -> 1026.7838 | K35: =($D35)/((1+$K$5/2)^(2*($A35-K$3))) -> 1077.397 | L35: =($D35)/((1+$L$5/2)^(2*($A35-L$3))) -> 1119.5754
A36: 8 | B36: =$B$1*$B$3/2 -> 1158.0328 | D36: =B36+C36 -> 1158.0328 | E36: =(D36)/(1+$E$5/2)^(2*A36) -> 788.03755 | F36: =($D36)/((1+$F$5/2)^(2*($A36-F$3))) -> 885.51165 | G36: =($D36)/((1+$G$5/2)^(2*($A36-G$3))) -> 818.39701 | H36: =($D36)/((1+$H$5/2)^(2*($A36-H$3))) -> 910.41026 | I36: =($D36)/((1+$I$5/2)^(2*($A36-I$3))) -> 993.42307 | J36: =($D36)/((1+$J$5/2)^(2*($A36-J$3))) -> 1002.3759 | K36: =($D36)/((1+$K$5/2)^(2*($A36-K$3))) -> 1051.786 | L36: =($D36)/((1+$L$5/2)^(2*($A36-L$3))) -> 1082.3951
A37: 8.5 | B37: =$B$1*$B$3/2 -> 1158.0328 | D37: =B37+C37 -> 1158.0328 | E37: =(D37)/(1+$E$5/2)^(2*A37) -> 769.30497 | F37: =($D37)/((1+$F$5/2)^(2*($A37-F$3))) -> 868.70226 | G37: =($D37)/((1+$G$5/2)^(2*($A37-G$3))) -> 795.06194 | H37: =($D37)/((1+$H$5/2)^(2*($A37-H$3))) -> 888.76874 | I37: =($D37)/((1+$I$5/2)^(2*($A37-I$3))) -> 974.56524 | J37: =($D37)/((1+$J$5/2)^(2*($A37-J$3))) -> 978.54828 | K37: =($D37)/((1+$K$5/2)^(2*($A37-K$3))) -> 1026.7838 | L37: =($D37)/((1+$L$5/2)^(2*($A37-L$3))) -> 1046.4496 | M37: =($D37)/((1+$M$5/2)^(2*($A37-M$3))) -> 1125.0136
A38: 9 | B38: =$B$1*$B$3/2 -> 1158.0328 | D38: =B38+C38 -> 1158.0328 | E38: =(D38)/(1+$E$5/2)^(2*A38) -> 751.01769 | F38: =($D38)/((1+$F$5/2)^(2*($A38-F$3))) -> 852.21196 | G38: =($D38)/((1+$G$5/2)^(2*($A38-G$3))) -> 772.39223 | H38: =($D38)/((1+$H$5/2)^(2*($A38-H$3))) -> 867.64167 | I38: =($D38)/((1+$I$5/2)^(2*($A38-I$3))) -> 956.06537 | J38: =($D38)/((1+$J$5/2)^(2*($A38-J$3))) -> 955.28704 | K38: =($D38)/((1+$K$5/2)^(2*($A38-K$3))) -> 1002.3759 | L38: =($D38)/((1+$L$5/2)^(2*($A38-L$3))) -> 1011.6978 | M38: =($D38)/((1+$M$5/2)^(2*($A38-M$3))) -> 1092.936
A39: 9.5 | B39: =$B$1*$B$3/2 -> 1158.0328 | D39: =B39+C39 -> 1158.0328 | E39: =(D39)/(1+$E$5/2)^(2*A39) -> 733.16512 | F39: =($D39)/((1+$F$5/2)^(2*($A39-F$3))) -> 836.03469 | G39: =($D39)/((1+$G$5/2)^(2*($A39-G$3))) -> 750.3689 | H39: =($D39)/((1+$H$5/2)^(2*($A39-H$3))) -> 847.01681 | I39: =($D39)/((1+$I$5/2)^(2*($A39-I$3))) -> 937.91668 | J39: =($D39)/((1+$J$5/2)^(2*($A39-J$3))) -> 932.57875 | K39: =($D39)/((1+$K$5/2)^(2*($A39-K$3))) -> 978.54828 | L39: =($D39)/((1+$L$5/2)^(2*($A39-L$3))) -> 978.10002 | M39: =($D39)/((1+$M$5/2)^(2*($A39-M$3))) -> 1061.7729 | N39: =($D39)/((1+$N$5/2)^(2*($A39-N$3))) -> 1119.5754
A40: 10 | B40: =$B$1*$B$3/2 -> 1158.0328 | D40: =B40+C40 -> 1158.0328 | E40: =(D40)/(1+$E$5/2)^(2*A40) -> 715.73693 | F40: =($D40)/((1+$F$5/2)^(2*($A40-F$3))) -> 820.1645 | G40: =($D40)/((1+$G$5/2)^(2*($A40-G$3))) -> 728.97353 | H40: =($D40)/((1+$H$5/2)^(2*($A40-H$3))) -> 826.88222 | I40: =($D40)/((1+$I$5/2)^(2*($A40-I$3))) -> 920.11251 | J40: =($D40)/((1+$J$5/2)^(2*($A40-J$3))) -> 910.41026 | K40: =($D40)/((1+$K$5/2)^(2*($A40-K$3))) -> 955.28704 | L40: =($D40)/((1+$L$5/2)^(2*($A40-L$3))) -> 945.61804 | M40: =($D40)/((1+$M$5/2)^(2*($A40-M$3))) -> 1031.4985 | N40: =($D40)/((1+$N$5/2)^(2*($A40-N$3))) -> 1082.3951
A41: 10.5 | B41: =$B$1*$B$3/2 -> 1158.0328 | D41: =B41+C41 -> 1158.0328 | E41: =(D41)/(1+$E$5/2)^(2*A41) -> 698.72302 | F41: =($D41)/((1+$F$5/2)^(2*($A41-F$3))) -> 804.59558 | G41: =($D41)/((1+$G$5/2)^(2*($A41-G$3))) -> 708.18821 | H41: =($D41)/((1+$H$5/2)^(2*($A41-H$3))) -> 807.22626 | I41: =($D41)/((1+$I$5/2)^(2*($A41-I$3))) -> 902.6463 | J41: =($D41)/((1+$J$5/2)^(2*($A41-J$3))) -> 888.76874 | K41: =($D41)/((1+$K$5/2)^(2*($A41-K$3))) -> 932.57875 | L41: =($D41)/((1+$L$5/2)^(2*($A41-L$3))) -> 914.21476 | M41: =($D41)/((1+$M$5/2)^(2*($A41-M$3))) -> 1002.0872 | N41: =($D41)/((1+$N$5/2)^(2*($A41-N$3))) -> 1046.4496 | O41: =($D41)/((1+$O$5/2)^(2*($A41-O$3))) -> 1114.1894
A42: 11 | B42: =$B$1*$B$3/2 -> 1158.0328 | D42: =B42+C42 -> 1158.0328 | E42: =(D42)/(1+$E$5/2)^(2*A42) -> 682.11356 | F42: =($D42)/((1+$F$5/2)^(2*($A42-F$3))) -> 789.3222 | G42: =($D42)/((1+$G$5/2)^(2*($A42-G$3))) -> 687.99554 | H42: =($D42)/((1+$H$5/2)^(2*($A42-H$3))) -> 788.03755 | I42: =($D42)/((1+$I$5/2)^(2*($A42-I$3))) -> 885.51165 | J42: =($D42)/((1+$J$5/2)^(2*($A42-J$3))) -> 867.64167 | K42: =($D42)/((1+$K$5/2)^(2*($A42-K$3))) -> 910.41026 | L42: =($D42)/((1+$L$5/2)^(2*($A42-L$3))) -> 883.85436 | M42: =($D42)/((1+$M$5/2)^(2*($A42-M$3))) -> 973.51455 | N42: =($D42)/((1+$N$5/2)^(2*($A42-N$3))) -> 1011.6978 | O42: =($D42)/((1+$O$5/2)^(2*($A42-O$3))) -> 1072.006
A43: 11.5 | B43: =$B$1*$B$3/2 -> 1158.0328 | D43: =B43+C43 -> 1158.0328 | E43: =(D43)/(1+$E$5/2)^(2*A43) -> 665.89892 | F43: =($D43)/((1+$F$5/2)^(2*($A43-F$3))) -> 774.33874 | G43: =($D43)/((1+$G$5/2)^(2*($A43-G$3))) -> 668.37862 | H43: =($D43)/((1+$H$5/2)^(2*($A43-H$3))) -> 769.30497 | I43: =($D43)/((1+$I$5/2)^(2*($A43-I$3))) -> 868.70226 | J43: =($D43)/((1+$J$5/2)^(2*($A43-J$3))) -> 847.01681 | K43: =($D43)/((1+$K$5/2)^(2*($A43-K$3))) -> 888.76874 | L43: =($D43)/((1+$L$5/2)^(2*($A43-L$3))) -> 854.50221 | M43: =($D43)/((1+$M$5/2)^(2*($A43-M$3))) -> 945.7566 | N43: =($D43)/((1+$N$5/2)^(2*($A43-N$3))) -> 978.10002 | O43: =($D43)/((1+$O$5/2)^(2*($A43-O$3))) -> 1031.4196 | P43: =($D43)/((1+$P$5/2)^(2*($A43-P$3))) -> 1108.8551
A44: 12 | B44: =$B$1*$B$3/2 -> 1158.0328 | D44: =B44+C44 -> 1158.0328 | E44: =(D44)/(1+$E$5/2)^(2*A44) -> 650.06972 | F44: =($D44)/((1+$F$5/2)^(2*($A44-F$3))) -> 759.63971 | G44: =($D44)/((1+$G$5/2)^(2*($A44-G$3))) -> 649.32105 | H44: =($D44)/((1+$H$5/2)^(2*($A44-H$3))) -> 751.01769 | I44: =($D44)/((1+$I$5/2)^(2*($A44-I$3))) -> 852.21196 | J44: =($D44)/((1+$J$5/2)^(2*($A44-J$3))) -> 826.88222 | K44: =($D44)/((1+$K$5/2)^(2*($A44-K$3))) -> 867.64167 | L44: =($D44)/((1+$L$5/2)^(2*($A44-L$3))) -> 826.12482 | M44: =($D44)/((1+$M$5/2)^(2*($A44-M$3))) -> 918.79011 | N44: =($D44)/((1+$N$5/2)^(2*($A44-N$3))) -> 945.61804 | O44: =($D44)/((1+$O$5/2)^(2*($A44-O$3))) -> 992.36989 | P44: =($D44)/((1+$P$5/2)^(2*($A44-P$3))) -> 1061.7658
A45: 12.5 | B45: =$B$1*$B$3/2 -> 1158.0328 | D45: =B45+C45 -> 1158.0328 | E45: =(D45)/(1+$E$5/2)^(2*A45) -> 634.6168 | F45: =($D45)/((1+$F$5/2)^(2*($A45-F$3))) -> 745.21971 | G45: =($D45)/((1+$G$5/2)^(2*($A45-G$3))) -> 630.80687 | H45: =($D45)/((1+$H$5/2)^(2*($A45-H$3))) -> 733.16512 | I45: =($D45)/((1+$I$5/2)^(2*($A45-I$3))) -> 836.03469 | J45: =($D45)/((1+$J$5/2)^(2*($A45-J$3))) -> 807.22626 | K45: =($D45)/((1+$K$5/2)^(2*($A45-K$3))) -> 847.01681 | L45: =($D45)/((1+$L$5/2)^(2*($A45-L$3))) -> 798.68983 | M45: =($D45)/((1+$M$5/2)^(2*($A45-M$3))) -> 892.59252 | N45: =($D45)/((1+$N$5/2)^(2*($A45-N$3))) -> 914.21476 | O45: =($D45)/((1+$O$5/2)^(2*($A45-O$3))) -> 954.79857 | P45: =($D45)/((1+$P$5/2)^(2*($A45-P$3))) -> 1016.6762 | Q45: =($D45)/((1+$Q$5/2)^(2*($A45-Q$3))) -> 1114.1894
A46: 13 | B46: =$B$1*$B$3/2 -> 1158.0328 | D46: =B46+C46 -> 1158.0328 | E46: =(D46)/(1+$E$5/2)^(2*A46) -> 619.53122 | F46: =($D46)/((1+$F$5/2)^(2*($A46-F$3))) -> 731.07344 | G46: =($D46)/((1+$G$5/2)^(2*($A46-G$3))) -> 612.82059 | H46: =($D46)/((1+$H$5/2)^(2*($A46-H$3))) -> 715.73693 | I46: =($D46)/((1+$I$5/2)^(2*($A46-I$3))) -> 820.1645 | J46: =($D46)/((1+$J$5/2)^(2*($A46-J$3))) -> 788.03755 | K46: =($D46)/((1+$K$5/2)^(2*($A46-K$3))) -> 826.88222 | L46: =($D46)/((1+$L$5/2)^(2*($A46-L$3))) -> 772.16593 | M46: =($D46)/((1+$M$5/2)^(2*($A46-M$3))) -> 867.1419 | N46: =($D46)/((1+$N$5/2)^(2*($A46-N$3))) -> 883.85436 | O46: =($D46)/((1+$O$5/2)^(2*($A46-O$3))) -> 918.6497 | P46: =($D46)/((1+$P$5/2)^(2*($A46-P$3))) -> 973.50139 | Q46: =($D46)/((1+$Q$5/2)^(2*($A46-Q$3))) -> 1072.006
A47: 13.5 | B47: =$B$1*$B$3/2 -> 1158.0328 | D47: =B47+C47 -> 1158.0328 | E47: =(D47)/(1+$E$5/2)^(2*A47) -> 604.80423 | F47: =($D47)/((1+$F$5/2)^(2*($A47-F$3))) -> 717.1957 | G47: =($D47)/((1+$G$5/2)^(2*($A47-G$3))) -> 595.34715 | H47: =($D47)/((1+$H$5/2)^(2*($A47-H$3))) -> 698.72302 | I47: =($D47)/((1+$I$5/2)^(2*($A47-I$3))) -> 804.59558 | J47: =($D47)/((1+$J$5/2)^(2*($A47-J$3))) -> 769.30497 | K47: =($D47)/((1+$K$5/2)^(2*($A47-K$3))) -> 807.22626 | L47: =($D47)/((1+$L$5/2)^(2*($A47-L$3))) -> 746.52287 | M47: =($D47)/((1+$M$5/2)^(2*($A47-M$3))) -> 842.41696 | N47: =($D47)/((1+$N$5/2)^(2*($A47-N$3))) -> 854.50221 | O47: =($D47)/((1+$O$5/2)^(2*($A47-O$3))) -> 883.86944 | P47: =($D47)/((1+$P$5/2)^(2*($A47-P$3))) -> 932.16009 | Q47: =($D47)/((1+$Q$5/2)^(2*($A47-Q$3))) -> 1031.4196 | R47: =($D47)/((1+$R$5/2)^(2*($A47-R$3))) -> 1119.5754
A48: 14 | B48: =$B$1*$B$3/2 -> 1158.0328 | D48: =B48+C48 -> 1158.0328 | E48: =(D48)/(1+$E$5/2)^(2*A48) -> 590.42733 | F48: =($D48)/((1+$F$5/2)^(2*($A48-F$3))) -> 703.5814 | G48: =($D48)/((1+$G$5/2)^(2*($A48-G$3))) -> 578.37193 | H48: =($D48)/((1+$H$5/2)^(2*($A48-H$3))) -> 682.11356 | I48: =($D48)/((1+$I$5/2)^(2*($A48-I$3))) -> 789.3222 | J48: =($D48)/((1+$J$5/2)^(2*($A48-J$3))) -> 751.01769 | K48: =($D48)/((1+$K$5/2)^(2*($A48-K$3))) -> 788.03755 | L48: =($D48)/((1+$L$5/2)^(2*($A48-L$3))) -> 721.7314 | M48: =($D48)/((1+$M$5/2)^(2*($A48-M$3))) -> 818.39701 | N48: =($D48)/((1+$N$5/2)^(2*($A48-N$3))) -> 826.12482 | O48: =($D48)/((1+$O$5/2)^(2*($A48-O$3))) -> 850.40596 | P48: =($D48)/((1+$P$5/2)^(2*($A48-P$3))) -> 892.57442 | Q48: =($D48)/((1+$Q$5/2)^(2*($A48-Q$3))) -> 992.36989 | R48: =($D48)/((1+$R$5/2)^(2*($A48-R$3))) -> 1082.3951
A49: 14.5 | B49: =$B$1*$B$3/2 -> 1158.0328 | D49: =B49+C49 -> 1158.0328 | E49: =(D49)/(1+$E$5/2)^(2*A49) -> 576.39218 | F49: =($D49)/((1+$F$5/2)^(2*($A49-F$3))) -> 690.22554 | G49: =($D49)/((1+$G$5/2)^(2*($A49-G$3))) -> 561.88073 | H49: =($D49)/((1+$H$5/2)^(2*($A49-H$3))) -> 665.89892 | I49: =($D49)/((1+$I$5/2)^(2*($A49-I$3))) -> 774.33874 | J49: =($D49)/((1+$J$5/2)^(2*($A49-J$3))) -> 733.16512 | K49: =($D49)/((1+$K$5/2)^(2*($A49-K$3))) -> 769.30497 | L49: =($D49)/((1+$L$5/2)^(2*($A49-L$3))) -> 697.76323 | M49: =($D49)/((1+$M$5/2)^(2*($A49-M$3))) -> 795.06194 | N49: =($D49)/((1+$N$5/2)^(2*($A49-N$3))) -> 798.68983 | O49: =($D49)/((1+$O$5/2)^(2*($A49-O$3))) -> 818.20942 | P49: =($D49)/((1+$P$5/2)^(2*($A49-P$3))) -> 854.66981 | Q49: =($D49)/((1+$Q$5/2)^(2*($A49-Q$3))) -> 954.79857 | R49: =($D49)/((1+$R$5/2)^(2*($A49-R$3))) -> 1046.4496 | S49: =($D49)/((1+$S$5/2)^(2*($A49-S$3))) -> 1114.1894
A50: 15 | B50: =$B$1*$B$3/2 -> 1158.0328 | D50: =B50+C50 -> 1158.0328 | E50: =(D50)/(1+$E$5/2)^(2*A50) -> 562.69066 | F50: =($D50)/((1+$F$5/2)^(2*($A50-F$3))) -> 677.12321 | G50: =($D50)/((1+$G$5/2)^(2*($A50-G$3))) -> 545.85975 | H50: =($D50)/((1+$H$5/2)^(2*($A50-H$3))) -> 650.06972 | I50: =($D50)/((1+$I$5/2)^(2*($A50-I$3))) -> 759.63971 | J50: =($D50)/((1+$J$5/2)^(2*($A50-J$3))) -> 715.73693 | K50: =($D50)/((1+$K$5/2)^(2*($A50-K$3))) -> 751.01769 | L50: =($D50)/((1+$L$5/2)^(2*($A50-L$3))) -> 674.59103 | M50: =($D50)/((1+$M$5/2)^(2*($A50-M$3))) -> 772.39223 | N50: =($D50)/((1+$N$5/2)^(2*($A50-N$3))) -> 772.16593 | O50: =($D50)/((1+$O$5/2)^(2*($A50-O$3))) -> 787.23185 | P50: =($D50)/((1+$P$5/2)^(2*($A50-P$3))) -> 818.37488 | Q50: =($D50)/((1+$Q$5/2)^(2*($A50-Q$3))) -> 918.6497 | R50: =($D50)/((1+$R$5/2)^(2*($A50-R$3))) -> 1011.6978 | S50: =($D50)/((1+$S$5/2)^(2*($A50-S$3))) -> 1072.006
A51: 15.5 | B51: =$B$1*$B$3/2 -> 1158.0328 | D51: =B51+C51 -> 1158.0328 | E51: =(D51)/(1+$E$5/2)^(2*A51) -> 549.31484 | F51: =($D51)/((1+$F$5/2)^(2*($A51-F$3))) -> 664.26959 | G51: =($D51)/((1+$G$5/2)^(2*($A51-G$3))) -> 530.29557 | H51: =($D51)/((1+$H$5/2)^(2*($A51-H$3))) -> 634.6168 | I51: =($D51)/((1+$I$5/2)^(2*($A51-I$3))) -> 745.21971 | J51: =($D51)/((1+$J$5/2)^(2*($A51-J$3))) -> 698.72302 | K51: =($D51)/((1+$K$5/2)^(2*($A51-K$3))) -> 733.16512 | L51: =($D51)/((1+$L$5/2)^(2*($A51-L$3))) -> 652.18836 | M51: =($D51)/((1+$M$5/2)^(2*($A51-M$3))) -> 750.3689 | N51: =($D51)/((1+$N$5/2)^(2*($A51-N$3))) -> 746.52287 | O51: =($D51)/((1+$O$5/2)^(2*($A51-O$3))) -> 757.42709 | P51: =($D51)/((1+$P$5/2)^(2*($A51-P$3))) -> 783.62128 | Q51: =($D51)/((1+$Q$5/2)^(2*($A51-Q$3))) -> 883.86944 | R51: =($D51)/((1+$R$5/2)^(2*($A51-R$3))) -> 978.10002 | S51: =($D51)/((1+$S$5/2)^(2*($A51-S$3))) -> 1031.4196 | T51: =($D51)/((1+$T$5/2)^(2*($A51-T$3))) -> 1108.8551
A52: 16 | B52: =$B$1*$B$3/2 -> 1158.0328 | D52: =B52+C52 -> 1158.0328 | E52: =(D52)/(1+$E$5/2)^(2*A52) -> 536.25699 | F52: =($D52)/((1+$F$5/2)^(2*($A52-F$3))) -> 651.65997 | G52: =($D52)/((1+$G$5/2)^(2*($A52-G$3))) -> 515.17518 | H52: =($D52)/((1+$H$5/2)^(2*($A52-H$3))) -> 619.53122 | I52: =($D52)/((1+$I$5/2)^(2*($A52-I$3))) -> 731.07344 | J52: =($D52)/((1+$J$5/2)^(2*($A52-J$3))) -> 682.11356 | K52: =($D52)/((1+$K$5/2)^(2*($A52-K$3))) -> 715.73693 | L52: =($D52)/((1+$L$5/2)^(2*($A52-L$3))) -> 630.52966 | M52: =($D52)/((1+$M$5/2)^(2*($A52-M$3))) -> 728.97353 | N52: =($D52)/((1+$N$5/2)^(2*($A52-N$3))) -> 721.7314 | O52: =($D52)/((1+$O$5/2)^(2*($A52-O$3))) -> 728.75075 | P52: =($D52)/((1+$P$5/2)^(2*($A52-P$3))) -> 750.34354 | Q52: =($D52)/((1+$Q$5/2)^(2*($A52-Q$3))) -> 850.40596 | R52: =($D52)/((1+$R$5/2)^(2*($A52-R$3))) -> 945.61804 | S52: =($D52)/((1+$S$5/2)^(2*($A52-S$3))) -> 992.36989 | T52: =($D52)/((1+$T$5/2)^(2*($A52-T$3))) -> 1061.7658
A53: 16.5 | B53: =$B$1*$B$3/2 -> 1158.0328 | D53: =B53+C53 -> 1158.0328 | E53: =(D53)/(1+$E$5/2)^(2*A53) -> 523.50953 | F53: =($D53)/((1+$F$5/2)^(2*($A53-F$3))) -> 639.28971 | G53: =($D53)/((1+$G$5/2)^(2*($A53-G$3))) -> 500.48592 | H53: =($D53)/((1+$H$5/2)^(2*($A53-H$3))) -> 604.80423 | I53: =($D53)/((1+$I$5/2)^(2*($A53-I$3))) -> 717.1957 | J53: =($D53)/((1+$J$5/2)^(2*($A53-J$3))) -> 665.89892 | K53: =($D53)/((1+$K$5/2)^(2*($A53-K$3))) -> 698.72302 | L53: =($D53)/((1+$L$5/2)^(2*($A53-L$3))) -> 609.59024 | M53: =($D53)/((1+$M$5/2)^(2*($A53-M$3))) -> 708.18821 | N53: =($D53)/((1+$N$5/2)^(2*($A53-N$3))) -> 697.76323 | O53: =($D53)/((1+$O$5/2)^(2*($A53-O$3))) -> 701.1601 | P53: =($D53)/((1+$P$5/2)^(2*($A53-P$3))) -> 718.479 | Q53: =($D53)/((1+$Q$5/2)^(2*($A53-Q$3))) -> 818.20942 | R53: =($D53)/((1+$R$5/2)^(2*($A53-R$3))) -> 914.21476 | S53: =($D53)/((1+$S$5/2)^(2*($A53-S$3))) -> 954.79857 | T53: =($D53)/((1+$T$5/2)^(2*($A53-T$3))) -> 1016.6762 | U53: =($D53)/((1+$U$5/2)^(2*($A53-U$3))) -> 1114.1894
A54: 17 | B54: =$B$1*$B$3/2 -> 1158.0328 | D54: =B54+C54 -> 1158.0328 | E54: =(D54)/(1+$E$5/2)^(2*A54) -> 511.06509 | F54: =($D54)/((1+$F$5/2)^(2*($A54-F$3))) -> 627.15428 | G54: =($D54)/((1+$G$5/2)^(2*($A54-G$3))) -> 486.21549 | H54: =($D54)/((1+$H$5/2)^(2*($A54-H$3))) -> 590.42733 | I54: =($D54)/((1+$I$5/2)^(2*($A54-I$3))) -> 703.5814 | J54: =($D54)/((1+$J$5/2)^(2*($A54-J$3))) -> 650.06972 | K54: =($D54)/((1+$K$5/2)^(2*($A54-K$3))) -> 682.11356 | L54: =($D54)/((1+$L$5/2)^(2*($A54-L$3))) -> 589.3462 | M54: =($D54)/((1+$M$5/2)^(2*($A54-M$3))) -> 687.99554 | N54: =($D54)/((1+$N$5/2)^(2*($A54-N$3))) -> 674.59103 | O54: =($D54)/((1+$O$5/2)^(2*($A54-O$3))) -> 674.61404 | P54: =($D54)/((1+$P$5/2)^(2*($A54-P$3))) -> 687.96763 | Q54: =($D54)/((1+$Q$5/2)^(2*($A54-Q$3))) -> 787.23185 | R54: =($D54)/((1+$R$5/2)^(2*($A54-R$3))) -> 883.85436 | S54: =($D54)/((1+$S$5/2)^(2*($A54-S$3))) -> 918.6497 | T54: =($D54)/((1+$T$5/2)^(2*($A54-T$3))) -> 973.50139 | U54: =($D54)/((1+$U$5/2)^(2*($A54-U$3))) -> 1072.006
A55: 17.5 | B55: =$B$1*$B$3/2 -> 1158.0328 | D55: =B55+C55 -> 1158.0328 | E55: =(D55)/(1+$E$5/2)^(2*A55) -> 498.91648 | F55: =($D55)/((1+$F$5/2)^(2*($A55-F$3))) -> 615.2492 | G55: =($D55)/((1+$G$5/2)^(2*($A55-G$3))) -> 472.35196 | H55: =($D55)/((1+$H$5/2)^(2*($A55-H$3))) -> 576.39218 | I55: =($D55)/((1+$I$5/2)^(2*($A55-I$3))) -> 690.22554 | J55: =($D55)/((1+$J$5/2)^(2*($A55-J$3))) -> 634.6168 | K55: =($D55)/((1+$K$5/2)^(2*($A55-K$3))) -> 665.89892 | L55: =($D55)/((1+$L$5/2)^(2*($A55-L$3))) -> 569.77444 | M55: =($D55)/((1+$M$5/2)^(2*($A55-M$3))) -> 668.37862 | N55: =($D55)/((1+$N$5/2)^(2*($A55-N$3))) -> 652.18836 | O55: =($D55)/((1+$O$5/2)^(2*($A55-O$3))) -> 649.07302 | P55: =($D55)/((1+$P$5/2)^(2*($A55-P$3))) -> 658.75198 | Q55: =($D55)/((1+$Q$5/2)^(2*($A55-Q$3))) -> 757.42709 | R55: =($D55)/((1+$R$5/2)^(2*($A55-R$3))) -> 854.50221 | S55: =($D55)/((1+$S$5/2)^(2*($A55-S$3))) -> 883.86944 | T55: =($D55)/((1+$T$5/2)^(2*($A55-T$3))) -> 932.16009 | U55: =($D55)/((1+$U$5/2)^(2*($A55-U$3))) -> 1031.4196 | V55: =($D55)/((1+$V$5/2)^(2*($A55-V$3))) -> 1108.8551
A56: 18 | B56: =$B$1*$B$3/2 -> 1158.0328 | D56: =B56+C56 -> 1158.0328 | E56: =(D56)/(1+$E$5/2)^(2*A56) -> 487.05665 | F56: =($D56)/((1+$F$5/2)^(2*($A56-F$3))) -> 603.57012 | G56: =($D56)/((1+$G$5/2)^(2*($A56-G$3))) -> 458.88373 | H56: =($D56)/((1+$H$5/2)^(2*($A56-H$3))) -> 562.69066 | I56: =($D56)/((1+$I$5/2)^(2*($A56-I$3))) -> 677.12321 | J56: =($D56)/((1+$J$5/2)^(2*($A56-J$3))) -> 619.53122 | K56: =($D56)/((1+$K$5/2)^(2*($A56-K$3))) -> 650.06972 | L56: =($D56)/((1+$L$5/2)^(2*($A56-L$3))) -> 550.85266 | M56: =($D56)/((1+$M$5/2)^(2*($A56-M$3))) -> 649.32105 | N56: =($D56)/((1+$N$5/2)^(2*($A56-N$3))) -> 630.52966 | O56: =($D56)/((1+$O$5/2)^(2*($A56-O$3))) -> 624.49898 | P56: =($D56)/((1+$P$5/2)^(2*($A56-P$3))) -> 630.77702 | Q56: =($D56)/((1+$Q$5/2)^(2*($A56-Q$3))) -> 728.75075 | R56: =($D56)/((1+$R$5/2)^(2*($A56-R$3))) -> 826.12482 | S56: =($D56)/((1+$S$5/2)^(2*($A56-S$3))) -> 850.40596 | T56: =($D56)/((1+$T$5/2)^(2*($A56-T$3))) -> 892.57442 | U56: =($D56)/((1+$U$5/2)^(2*($A56-U$3))) -> 992.36989 | V56: =($D56)/((1+$V$5/2)^(2*($A56-V$3))) -> 1061.7658
A57: 18.5 | B57: =$B$1*$B$3/2 -> 1158.0328 | D57: =B57+C57 -> 1158.0328 | E57: =(D57)/(1+$E$5/2)^(2*A57) -> 475.47874 | F57: =($D57)/((1+$F$5/2)^(2*($A57-F$3))) -> 592.11274 | G57: =($D57)/((1+$G$5/2)^(2*($A57-G$3))) -> 445.79951 | H57: =($D57)/((1+$H$5/2)^(2*($A57-H$3))) -> 549.31484 | I57: =($D57)/((1+$I$5/2)^(2*($A57-I$3))) -> 664.26959 | J57: =($D57)/((1+$J$5/2)^(2*($A57-J$3))) -> 604.80423 | K57: =($D57)/((1+$K$5/2)^(2*($A57-K$3))) -> 634.6168 | L57: =($D57)/((1+$L$5/2)^(2*($A57-L$3))) -> 532.55925 | M57: =($D57)/((1+$M$5/2)^(2*($A57-M$3))) -> 630.80687 | N57: =($D57)/((1+$N$5/2)^(2*($A57-N$3))) -> 609.59024 | O57: =($D57)/((1+$O$5/2)^(2*($A57-O$3))) -> 600.85532 | P57: =($D57)/((1+$P$5/2)^(2*($A57-P$3))) -> 603.99006 | Q57: =($D57)/((1+$Q$5/2)^(2*($A57-Q$3))) -> 701.1601 | R57: =($D57)/((1+$R$5/2)^(2*($A57-R$3))) -> 798.68983 | S57: =($D57)/((1+$S$5/2)^(2*($A57-S$3))) -> 818.20942 | T57: =($D57)/((1+$T$5/2)^(2*($A57-T$3))) -> 854.66981 | U57: =($D57)/((1+$U$5/2)^(2*($A57-U$3))) -> 954.79857 | V57: =($D57)/((1+$V$5/2)^(2*($A57-V$3))) -> 1016.6762 | W57: =($D57)/((1+$W$5/2)^(2*($A57-W$3))) -> 1119.5754
A58: 19 | B58: =$B$1*$B$3/2 -> 1158.0328 | D58: =B58+C58 -> 1158.0328 | E58: =(D58)/(1+$E$5/2)^(2*A58) -> 464.17605 | F58: =($D58)/((1+$F$5/2)^(2*($A58-F$3))) -> 580.87285 | G58: =($D58)/((1+$G$5/2)^(2*($A58-G$3))) -> 433.08837 | H58: =($D58)/((1+$H$5/2)^(2*($A58-H$3))) -> 536.25699 | I58: =($D58)/((1+$I$5/2)^(2*($A58-I$3))) -> 651.65997 | J58: =($D58)/((1+$J$5/2)^(2*($A58-J$3))) -> 590.42733 | K58: =($D58)/((1+$K$5/2)^(2*($A58-K$3))) -> 619.53122 | L58: =($D58)/((1+$L$5/2)^(2*($A58-L$3))) -> 514.87335 | M58: =($D58)/((1+$M$5/2)^(2*($A58-M$3))) -> 612.82059 | N58: =($D58)/((1+$N$5/2)^(2*($A58-N$3))) -> 589.3462 | O58: =($D58)/((1+$O$5/2)^(2*($A58-O$3))) -> 578.10682 | P58: =($D58)/((1+$P$5/2)^(2*($A58-P$3))) -> 578.34066 | Q58: =($D58)/((1+$Q$5/2)^(2*($A58-Q$3))) -> 674.61404 | R58: =($D58)/((1+$R$5/2)^(2*($A58-R$3))) -> 772.16593 | S58: =($D58)/((1+$S$5/2)^(2*($A58-S$3))) -> 787.23185 | T58: =($D58)/((1+$T$5/2)^(2*($A58-T$3))) -> 818.37488 | U58: =($D58)/((1+$U$5/2)^(2*($A58-U$3))) -> 918.6497 | V58: =($D58)/((1+$V$5/2)^(2*($A58-V$3))) -> 973.50139 | W58: =($D58)/((1+$W$5/2)^(2*($A58-W$3))) -> 1082.3951
A59: 19.5 | B59: =$B$1*$B$3/2 -> 1158.0328 | D59: =B59+C59 -> 1158.0328 | E59: =(D59)/(1+$E$5/2)^(2*A59) -> 453.14205 | F59: =($D59)/((1+$F$5/2)^(2*($A59-F$3))) -> 569.84633 | G59: =($D59)/((1+$G$5/2)^(2*($A59-G$3))) -> 420.73966 | H59: =($D59)/((1+$H$5/2)^(2*($A59-H$3))) -> 523.50953 | I59: =($D59)/((1+$I$5/2)^(2*($A59-I$3))) -> 639.28971 | J59: =($D59)/((1+$J$5/2)^(2*($A59-J$3))) -> 576.39218 | K59: =($D59)/((1+$K$5/2)^(2*($A59-K$3))) -> 604.80423 | L59: =($D59)/((1+$L$5/2)^(2*($A59-L$3))) -> 497.77478 | M59: =($D59)/((1+$M$5/2)^(2*($A59-M$3))) -> 595.34715 | N59: =($D59)/((1+$N$5/2)^(2*($A59-N$3))) -> 569.77444 | O59: =($D59)/((1+$O$5/2)^(2*($A59-O$3))) -> 556.21958 | P59: =($D59)/((1+$P$5/2)^(2*($A59-P$3))) -> 553.78049 | Q59: =($D59)/((1+$Q$5/2)^(2*($A59-Q$3))) -> 649.07302 | R59: =($D59)/((1+$R$5/2)^(2*($A59-R$3))) -> 746.52287 | S59: =($D59)/((1+$S$5/2)^(2*($A59-S$3))) -> 757.42709 | T59: =($D59)/((1+$T$5/2)^(2*($A59-T$3))) -> 783.62128 | U59: =($D59)/((1+$U$5/2)^(2*($A59-U$3))) -> 883.86944 | V59: =($D59)/((1+$V$5/2)^(2*($A59-V$3))) -> 932.16009 | W59: =($D59)/((1+$W$5/2)^(2*($A59-W$3))) -> 1046.4496 | X59: =($D59)/((1+$X$5/2)^(2*($A59-X$3))) -> 1119.5754
A60: 20 | B60: =$B$1*$B$3/2 -> 1158.0328 | D60: =B60+C60 -> 1158.0328 | E60: =(D60)/(1+$E$5/2)^(2*A60) -> 442.37033 | F60: =($D60)/((1+$F$5/2)^(2*($A60-F$3))) -> 559.02911 | G60: =($D60)/((1+$G$5/2)^(2*($A60-G$3))) -> 408.74305 | H60: =($D60)/((1+$H$5/2)^(2*($A60-H$3))) -> 511.06509 | I60: =($D60)/((1+$I$5/2)^(2*($A60-I$3))) -> 627.15428 | J60: =($D60)/((1+$J$5/2)^(2*($A60-J$3))) -> 562.69066 | K60: =($D60)/((1+$K$5/2)^(2*($A60-K$3))) -> 590.42733 | L60: =($D60)/((1+$L$5/2)^(2*($A60-L$3))) -> 481.24405 | M60: =($D60)/((1+$M$5/2)^(2*($A60-M$3))) -> 578.37193 | N60: =($D60)/((1+$N$5/2)^(2*($A60-N$3))) -> 550.85266 | O60: =($D60)/((1+$O$5/2)^(2*($A60-O$3))) -> 535.161 | P60: =($D60)/((1+$P$5/2)^(2*($A60-P$3))) -> 530.26331 | Q60: =($D60)/((1+$Q$5/2)^(2*($A60-Q$3))) -> 624.49898 | R60: =($D60)/((1+$R$5/2)^(2*($A60-R$3))) -> 721.7314 | S60: =($D60)/((1+$S$5/2)^(2*($A60-S$3))) -> 728.75075 | T60: =($D60)/((1+$T$5/2)^(2*($A60-T$3))) -> 750.34354 | U60: =($D60)/((1+$U$5/2)^(2*($A60-U$3))) -> 850.40596 | V60: =($D60)/((1+$V$5/2)^(2*($A60-V$3))) -> 892.57442 | W60: =($D60)/((1+$W$5/2)^(2*($A60-W$3))) -> 1011.6978 | X60: =($D60)/((1+$X$5/2)^(2*($A60-X$3))) -> 1082.3951
A61: 20.5 | B61: =$B$1*$B$3/2 -> 1158.0328 | D61: =B61+C61 -> 1158.0328 | E61: =(D61)/(1+$E$5/2)^(2*A61) -> 431.85467 | F61: =($D61)/((1+$F$5/2)^(2*($A61-F$3))) -> 548.41724 | G61: =($D61)/((1+$G$5/2)^(2*($A61-G$3))) -> 397.0885 | H61: =($D61)/((1+$H$5/2)^(2*($A61-H$3))) -> 498.91648 | I61: =($D61)/((1+$I$5/2)^(2*($A61-I$3))) -> 615.2492 | J61: =($D61)/((1+$J$5/2)^(2*($A61-J$3))) -> 549.31484 | K61: =($D61)/((1+$K$5/2)^(2*($A61-K$3))) -> 576.39218 | L61: =($D61)/((1+$L$5/2)^(2*($A61-L$3))) -> 465.26229 | M61: =($D61)/((1+$M$5/2)^(2*($A61-M$3))) -> 561.88073 | N61: =($D61)/((1+$N$5/2)^(2*($A61-N$3))) -> 532.55925 | O61: =($D61)/((1+$O$5/2)^(2*($A61-O$3))) -> 514.89969 | P61: =($D61)/((1+$P$5/2)^(2*($A61-P$3))) -> 507.74483 | Q61: =($D61)/((1+$Q$5/2)^(2*($A61-Q$3))) -> 600.85532 | R61: =($D61)/((1+$R$5/2)^(2*($A61-R$3))) -> 697.76323 | S61: =($D61)/((1+$S$5/2)^(2*($A61-S$3))) -> 701.1601 | T61: =($D61)/((1+$T$5/2)^(2*($A61-T$3))) -> 718.479 | U61: =($D61)/((1+$U$5/2)^(2*($A61-U$3))) -> 818.20942 | V61: =($D61)/((1+$V$5/2)^(2*($A61-V$3))) -> 854.66981 | W61: =($D61)/((1+$W$5/2)^(2*($A61-W$3))) -> 978.10002 | X61: =($D61)/((1+$X$5/2)^(2*($A61-X$3))) -> 1046.4496 | Y61: =($D61)/((1+$Y$5/2)^(2*($A61-Y$3))) -> 1125.0136
A62: 21 | B62: =$B$1*$B$3/2 -> 1158.0328 | D62: =B62+C62 -> 1158.0328 | E62: =(D62)/(1+$E$5/2)^(2*A62) -> 421.58898 | F62: =($D62)/((1+$F$5/2)^(2*($A62-F$3))) -> 538.00681 | G62: =($D62)/((1+$G$5/2)^(2*($A62-G$3))) -> 385.76626 | H62: =($D62)/((1+$H$5/2)^(2*($A62-H$3))) -> 487.05665 | I62: =($D62)/((1+$I$5/2)^(2*($A62-I$3))) -> 603.57012 | J62: =($D62)/((1+$J$5/2)^(2*($A62-J$3))) -> 536.25699 | K62: =($D62)/((1+$K$5/2)^(2*($A62-K$3))) -> 562.69066 | L62: =($D62)/((1+$L$5/2)^(2*($A62-L$3))) -> 449.81127 | M62: =($D62)/((1+$M$5/2)^(2*($A62-M$3))) -> 545.85975 | N62: =($D62)/((1+$N$5/2)^(2*($A62-N$3))) -> 514.87335 | O62: =($D62)/((1+$O$5/2)^(2*($A62-O$3))) -> 495.40549 | P62: =($D62)/((1+$P$5/2)^(2*($A62-P$3))) -> 486.18263 | Q62: =($D62)/((1+$Q$5/2)^(2*($A62-Q$3))) -> 578.10682 | R62: =($D62)/((1+$R$5/2)^(2*($A62-R$3))) -> 674.59103 | S62: =($D62)/((1+$S$5/2)^(2*($A62-S$3))) -> 674.61404 | T62: =($D62)/((1+$T$5/2)^(2*($A62-T$3))) -> 687.96763 | U62: =($D62)/((1+$U$5/2)^(2*($A62-U$3))) -> 787.23185 | V62: =($D62)/((1+$V$5/2)^(2*($A62-V$3))) -> 818.37488 | W62: =($D62)/((1+$W$5/2)^(2*($A62-W$3))) -> 945.61804 | X62: =($D62)/((1+$X$5/2)^(2*($A62-X$3))) -> 1011.6978 | Y62: =($D62)/((1+$Y$5/2)^(2*($A62-Y$3))) -> 1092.936
A63: 21.5 | B63: =$B$1*$B$3/2 -> 1158.0328 | D63: =B63+C63 -> 1158.0328 | E63: =(D63)/(1+$E$5/2)^(2*A63) -> 411.56731 | F63: =($D63)/((1+$F$5/2)^(2*($A63-F$3))) -> 527.79399 | G63: =($D63)/((1+$G$5/2)^(2*($A63-G$3))) -> 374.76686 | H63: =($D63)/((1+$H$5/2)^(2*($A63-H$3))) -> 475.47874 | I63: =($D63)/((1+$I$5/2)^(2*($A63-I$3))) -> 592.11274 | J63: =($D63)/((1+$J$5/2)^(2*($A63-J$3))) -> 523.50953 | K63: =($D63)/((1+$K$5/2)^(2*($A63-K$3))) -> 549.31484 | L63: =($D63)/((1+$L$5/2)^(2*($A63-L$3))) -> 434.87337 | M63: =($D63)/((1+$M$5/2)^(2*($A63-M$3))) -> 530.29557 | N63: =($D63)/((1+$N$5/2)^(2*($A63-N$3))) -> 497.77478 | O63: =($D63)/((1+$O$5/2)^(2*($A63-O$3))) -> 476.64934 | P63: =($D63)/((1+$P$5/2)^(2*($A63-P$3))) -> 465.5361 | Q63: =($D63)/((1+$Q$5/2)^(2*($A63-Q$3))) -> 556.21958 | R63: =($D63)/((1+$R$5/2)^(2*($A63-R$3))) -> 652.18836 | S63: =($D63)/((1+$S$5/2)^(2*($A63-S$3))) -> 649.07302 | T63: =($D63)/((1+$T$5/2)^(2*($A63-T$3))) -> 658.75198 | U63: =($D63)/((1+$U$5/2)^(2*($A63-U$3))) -> 757.42709 | V63: =($D63)/((1+$V$5/2)^(2*($A63-V$3))) -> 783.62128 | W63: =($D63)/((1+$W$5/2)^(2*($A63-W$3))) -> 914.21476 | X63: =($D63)/((1+$X$5/2)^(2*($A63-X$3))) -> 978.10002 | Y63: =($D63)/((1+$Y$5/2)^(2*($A63-Y$3))) -> 1061.7729 | Z63: =($D63)/((1+$Z$5/2)^(2*($A63-Z$3))) -> 1130.505
A64: 22 | B64: =$B$1*$B$3/2 -> 1158.0328 | D64: =B64+C64 -> 1158.0328 | E64: =(D64)/(1+$E$5/2)^(2*A64) -> 401.78387 | F64: =($D64)/((1+$F$5/2)^(2*($A64-F$3))) -> 517.77505 | G64: =($D64)/((1+$G$5/2)^(2*($A64-G$3))) -> 364.08108 | H64: =($D64)/((1+$H$5/2)^(2*($A64-H$3))) -> 464.17605 | I64: =($D64)/((1+$I$5/2)^(2*($A64-I$3))) -> 580.87285 | J64: =($D64)/((1+$J$5/2)^(2*($A64-J$3))) -> 511.06509 | K64: =($D64)/((1+$K$5/2)^(2*($A64-K$3))) -> 536.25699 | L64: =($D64)/((1+$L$5/2)^(2*($A64-L$3))) -> 420.43155 | M64: =($D64)/((1+$M$5/2)^(2*($A64-M$3))) -> 515.17518 | N64: =($D64)/((1+$N$5/2)^(2*($A64-N$3))) -> 481.24405 | O64: =($D64)/((1+$O$5/2)^(2*($A64-O$3))) -> 458.6033 | P64: =($D64)/((1+$P$5/2)^(2*($A64-P$3))) -> 445.76637 | Q64: =($D64)/((1+$Q$5/2)^(2*($A64-Q$3))) -> 535.161 | R64: =($D64)/((1+$R$5/2)^(2*($A64-R$3))) -> 630.52966 | S64: =($D64)/((1+$S$5/2)^(2*($A64-S$3))) -> 624.49898 | T64: =($D64)/((1+$T$5/2)^(2*($A64-T$3))) -> 630.77702 | U64: =($D64)/((1+$U$5/2)^(2*($A64-U$3))) -> 728.75075 | V64: =($D64)/((1+$V$5/2)^(2*($A64-V$3))) -> 750.34354 | W64: =($D64)/((1+$W$5/2)^(2*($A64-W$3))) -> 883.85436 | X64: =($D64)/((1+$X$5/2)^(2*($A64-X$3))) -> 945.61804 | Y64: =($D64)/((1+$Y$5/2)^(2*($A64-Y$3))) -> 1031.4985 | Z64: =($D64)/((1+$Z$5/2)^(2*($A64-Z$3))) -> 1103.6316
A65: 22.5 | B65: =$B$1*$B$3/2 -> 1158.0328 | D65: =B65+C65 -> 1158.0328 | E65: =(D65)/(1+$E$5/2)^(2*A65) -> 392.233 | F65: =($D65)/((1+$F$5/2)^(2*($A65-F$3))) -> 507.94629 | G65: =($D65)/((1+$G$5/2)^(2*($A65-G$3))) -> 353.69998 | H65: =($D65)/((1+$H$5/2)^(2*($A65-H$3))) -> 453.14205 | I65: =($D65)/((1+$I$5/2)^(2*($A65-I$3))) -> 569.84633 | J65: =($D65)/((1+$J$5/2)^(2*($A65-J$3))) -> 498.91648 | K65: =($D65)/((1+$K$5/2)^(2*($A65-K$3))) -> 523.50953 | L65: =($D65)/((1+$L$5/2)^(2*($A65-L$3))) -> 406.46933 | M65: =($D65)/((1+$M$5/2)^(2*($A65-M$3))) -> 500.48592 | N65: =($D65)/((1+$N$5/2)^(2*($A65-N$3))) -> 465.26229 | O65: =($D65)/((1+$O$5/2)^(2*($A65-O$3))) -> 441.24048 | P65: =($D65)/((1+$P$5/2)^(2*($A65-P$3))) -> 426.83618 | Q65: =($D65)/((1+$Q$5/2)^(2*($A65-Q$3))) -> 514.89969 | R65: =($D65)/((1+$R$5/2)^(2*($A65-R$3))) -> 609.59024 | S65: =($D65)/((1+$S$5/2)^(2*($A65-S$3))) -> 600.85532 | T65: =($D65)/((1+$T$5/2)^(2*($A65-T$3))) -> 603.99006 | U65: =($D65)/((1+$U$5/2)^(2*($A65-U$3))) -> 701.1601 | V65: =($D65)/((1+$V$5/2)^(2*($A65-V$3))) -> 718.479 | W65: =($D65)/((1+$W$5/2)^(2*($A65-W$3))) -> 854.50221 | X65: =($D65)/((1+$X$5/2)^(2*($A65-X$3))) -> 914.21476 | Y65: =($D65)/((1+$Y$5/2)^(2*($A65-Y$3))) -> 1002.0872 | Z65: =($D65)/((1+$Z$5/2)^(2*($A65-Z$3))) -> 1077.397 | AA65: =($D65)/((1+$AA$5/2)^(2*($A65-AA$3))) -> 1130.505
A66: 23 | B66: =$B$1*$B$3/2 -> 1158.0328 | D66: =B66+C66 -> 1158.0328 | E66: =(D66)/(1+$E$5/2)^(2*A66) -> 382.90916 | F66: =($D66)/((1+$F$5/2)^(2*($A66-F$3))) -> 498.3041 | G66: =($D66)/((1+$G$5/2)^(2*($A66-G$3))) -> 343.61488 | H66: =($D66)/((1+$H$5/2)^(2*($A66-H$3))) -> 442.37033 | I66: =($D66)/((1+$I$5/2)^(2*($A66-I$3))) -> 559.02911 | J66: =($D66)/((1+$J$5/2)^(2*($A66-J$3))) -> 487.05665 | K66: =($D66)/((1+$K$5/2)^(2*($A66-K$3))) -> 511.06509 | L66: =($D66)/((1+$L$5/2)^(2*($A66-L$3))) -> 392.97078 | M66: =($D66)/((1+$M$5/2)^(2*($A66-M$3))) -> 486.21549 | N66: =($D66)/((1+$N$5/2)^(2*($A66-N$3))) -> 449.81127 | O66: =($D66)/((1+$O$5/2)^(2*($A66-O$3))) -> 424.53503 | P66: =($D66)/((1+$P$5/2)^(2*($A66-P$3))) -> 408.7099 | Q66: =($D66)/((1+$Q$5/2)^(2*($A66-Q$3))) -> 495.40549 | R66: =($D66)/((1+$R$5/2)^(2*($A66-R$3))) -> 589.3462 | S66: =($D66)/((1+$S$5/2)^(2*($A66-S$3))) -> 578.10682 | T66: =($D66)/((1+$T$5/2)^(2*($A66-T$3))) -> 578.34066 | U66: =($D66)/((1+$U$5/2)^(2*($A66-U$3))) -> 674.61404 | V66: =($D66)/((1+$V$5/2)^(2*($A66-V$3))) -> 687.96763 | W66: =($D66)/((1+$W$5/2)^(2*($A66-W$3))) -> 826.12482 | X66: =($D66)/((1+$X$5/2)^(2*($A66-X$3))) -> 883.85436 | Y66: =($D66)/((1+$Y$5/2)^(2*($A66-Y$3))) -> 973.51455 | Z66: =($D66)/((1+$Z$5/2)^(2*($A66-Z$3))) -> 1051.786 | AA66: =($D66)/((1+$AA$5/2)^(2*($A66-AA$3))) -> 1103.6316
A67: 23.5 | B67: =$B$1*$B$3/2 -> 1158.0328 | D67: =B67+C67 -> 1158.0328 | E67: =(D67)/(1+$E$5/2)^(2*A67) -> 373.80696 | F67: =($D67)/((1+$F$5/2)^(2*($A67-F$3))) -> 488.84495 | G67: =($D67)/((1+$G$5/2)^(2*($A67-G$3))) -> 333.81735 | H67: =($D67)/((1+$H$5/2)^(2*($A67-H$3))) -> 431.85467 | I67: =($D67)/((1+$I$5/2)^(2*($A67-I$3))) -> 548.41724 | J67: =($D67)/((1+$J$5/2)^(2*($A67-J$3))) -> 475.47874 | K67: =($D67)/((1+$K$5/2)^(2*($A67-K$3))) -> 498.91648 | L67: =($D67)/((1+$L$5/2)^(2*($A67-L$3))) -> 379.92051 | M67: =($D67)/((1+$M$5/2)^(2*($A67-M$3))) -> 472.35196 | N67: =($D67)/((1+$N$5/2)^(2*($A67-N$3))) -> 434.87337 | O67: =($D67)/((1+$O$5/2)^(2*($A67-O$3))) -> 408.46205 | P67: =($D67)/((1+$P$5/2)^(2*($A67-P$3))) -> 391.35338 | Q67: =($D67)/((1+$Q$5/2)^(2*($A67-Q$3))) -> 476.64934 | R67: =($D67)/((1+$R$5/2)^(2*($A67-R$3))) -> 569.77444 | S67: =($D67)/((1+$S$5/2)^(2*($A67-S$3))) -> 556.21958 | T67: =($D67)/((1+$T$5/2)^(2*($A67-T$3))) -> 553.78049 | U67: =($D67)/((1+$U$5/2)^(2*($A67-U$3))) -> 649.07302 | V67: =($D67)/((1+$V$5/2)^(2*($A67-V$3))) -> 658.75198 | W67: =($D67)/((1+$W$5/2)^(2*($A67-W$3))) -> 798.68983 | X67: =($D67)/((1+$X$5/2)^(2*($A67-X$3))) -> 854.50221 | Y67: =($D67)/((1+$Y$5/2)^(2*($A67-Y$3))) -> 945.7566 | Z67: =($D67)/((1+$Z$5/2)^(2*($A67-Z$3))) -> 1026.7838 | AA67: =($D67)/((1+$AA$5/2)^(2*($A67-AA$3))) -> 1077.397 | AB67: =($D67)/((1+$AB$5/2)^(2*($A67-AB$3))) -> 1119.5754
A68: 24 | B68: =$B$1*$B$3/2 -> 1158.0328 | D68: =B68+C68 -> 1158.0328 | E68: =(D68)/(1+$E$5/2)^(2*A68) -> 364.92113 | F68: =($D68)/((1+$F$5/2)^(2*($A68-F$3))) -> 479.56536 | G68: =($D68)/((1+$G$5/2)^(2*($A68-G$3))) -> 324.29917 | H68: =($D68)/((1+$H$5/2)^(2*($A68-H$3))) -> 421.58898 | I68: =($D68)/((1+$I$5/2)^(2*($A68-I$3))) -> 538.00681 | J68: =($D68)/((1+$J$5/2)^(2*($A68-J$3))) -> 464.17605 | K68: =($D68)/((1+$K$5/2)^(2*($A68-K$3))) -> 487.05665 | L68: =($D68)/((1+$L$5/2)^(2*($A68-L$3))) -> 367.30363 | M68: =($D68)/((1+$M$5/2)^(2*($A68-M$3))) -> 458.88373 | N68: =($D68)/((1+$N$5/2)^(2*($A68-N$3))) -> 420.43155 | O68: =($D68)/((1+$O$5/2)^(2*($A68-O$3))) -> 392.99759 | P68: =($D68)/((1+$P$5/2)^(2*($A68-P$3))) -> 374.73393 | Q68: =($D68)/((1+$Q$5/2)^(2*($A68-Q$3))) -> 458.6033 | R68: =($D68)/((1+$R$5/2)^(2*($A68-R$3))) -> 550.85266 | S68: =($D68)/((1+$S$5/2)^(2*($A68-S$3))) -> 535.161 | T68: =($D68)/((1+$T$5/2)^(2*($A68-T$3))) -> 530.26331 | U68: =($D68)/((1+$U$5/2)^(2*($A68-U$3))) -> 624.49898 | V68: =($D68)/((1+$V$5/2)^(2*($A68-V$3))) -> 630.77702 | W68: =($D68)/((1+$W$5/2)^(2*($A68-W$3))) -> 772.16593 | X68: =($D68)/((1+$X$5/2)^(2*($A68-X$3))) -> 826.12482 | Y68: =($D68)/((1+$Y$5/2)^(2*($A68-Y$3))) -> 918.79011 | Z68: =($D68)/((1+$Z$5/2)^(2*($A68-Z$3))) -> 1002.3759 | AA68: =($D68)/((1+$AA$5/2)^(2*($A68-AA$3))) -> 1051.786 | AB68: =($D68)/((1+$AB$5/2)^(2*($A68-AB$3))) -> 1082.3951
A69: 24.5 | B69: =$B$1*$B$3/2 -> 1158.0328 | D69: =B69+C69 -> 1158.0328 | E69: =(D69)/(1+$E$5/2)^(2*A69) -> 356.24653 | F69: =($D69)/((1+$F$5/2)^(2*($A69-F$3))) -> 470.46192 | G69: =($D69)/((1+$G$5/2)^(2*($A69-G$3))) -> 315.05238 | H69: =($D69)/((1+$H$5/2)^(2*($A69-H$3))) -> 411.56731 | I69: =($D69)/((1+$I$5/2)^(2*($A69-I$3))) -> 527.79399 | J69: =($D69)/((1+$J$5/2)^(2*($A69-J$3))) -> 453.14205 | K69: =($D69)/((1+$K$5/2)^(2*($A69-K$3))) -> 475.47874 | L69: =($D69)/((1+$L$5/2)^(2*($A69-L$3))) -> 355.10575 | M69: =($D69)/((1+$M$5/2)^(2*($A69-M$3))) -> 445.79951 | N69: =($D69)/((1+$N$5/2)^(2*($A69-N$3))) -> 406.46933 | O69: =($D69)/((1+$O$5/2)^(2*($A69-O$3))) -> 378.11862 | P69: =($D69)/((1+$P$5/2)^(2*($A69-P$3))) -> 358.82025 | Q69: =($D69)/((1+$Q$5/2)^(2*($A69-Q$3))) -> 441.24048 | R69: =($D69)/((1+$R$5/2)^(2*($A69-R$3))) -> 532.55925 | S69: =($D69)/((1+$S$5/2)^(2*($A69-S$3))) -> 514.89969 | T69: =($D69)/((1+$T$5/2)^(2*($A69-T$3))) -> 507.74483 | U69: =($D69)/((1+$U$5/2)^(2*($A69-U$3))) -> 600.85532 | V69: =($D69)/((1+$V$5/2)^(2*($A69-V$3))) -> 603.99006 | W69: =($D69)/((1+$W$5/2)^(2*($A69-W$3))) -> 746.52287 | X69: =($D69)/((1+$X$5/2)^(2*($A69-X$3))) -> 798.68983 | Y69: =($D69)/((1+$Y$5/2)^(2*($A69-Y$3))) -> 892.59252 | Z69: =($D69)/((1+$Z$5/2)^(2*($A69-Z$3))) -> 978.54828 | AA69: =($D69)/((1+$AA$5/2)^(2*($A69-AA$3))) -> 1026.7838 | AB69: =($D69)/((1+$AB$5/2)^(2*($A69-AB$3))) -> 1046.4496 | AC69: =($D69)/((1+$AC$5/2)^(2*($A69-AC$3))) -> 1125.0136
A70: 25 | B70: =$B$1*$B$3/2 -> 1158.0328 | D70: =B70+C70 -> 1158.0328 | E70: =(D70)/(1+$E$5/2)^(2*A70) -> 347.77813 | F70: =($D70)/((1+$F$5/2)^(2*($A70-F$3))) -> 461.53129 | G70: =($D70)/((1+$G$5/2)^(2*($A70-G$3))) -> 306.06925 | H70: =($D70)/((1+$H$5/2)^(2*($A70-H$3))) -> 401.78387 | I70: =($D70)/((1+$I$5/2)^(2*($A70-I$3))) -> 517.77505 | J70: =($D70)/((1+$J$5/2)^(2*($A70-J$3))) -> 442.37033 | K70: =($D70)/((1+$K$5/2)^(2*($A70-K$3))) -> 464.17605 | L70: =($D70)/((1+$L$5/2)^(2*($A70-L$3))) -> 343.31295 | M70: =($D70)/((1+$M$5/2)^(2*($A70-M$3))) -> 433.08837 | N70: =($D70)/((1+$N$5/2)^(2*($A70-N$3))) -> 392.97078 | O70: =($D70)/((1+$O$5/2)^(2*($A70-O$3))) -> 363.80298 | P70: =($D70)/((1+$P$5/2)^(2*($A70-P$3))) -> 343.58237 | Q70: =($D70)/((1+$Q$5/2)^(2*($A70-Q$3))) -> 424.53503 | R70: =($D70)/((1+$R$5/2)^(2*($A70-R$3))) -> 514.87335 | S70: =($D70)/((1+$S$5/2)^(2*($A70-S$3))) -> 495.40549 | T70: =($D70)/((1+$T$5/2)^(2*($A70-T$3))) -> 486.18263 | U70: =($D70)/((1+$U$5/2)^(2*($A70-U$3))) -> 578.10682 | V70: =($D70)/((1+$V$5/2)^(2*($A70-V$3))) -> 578.34066 | W70: =($D70)/((1+$W$5/2)^(2*($A70-W$3))) -> 721.7314 | X70: =($D70)/((1+$X$5/2)^(2*($A70-X$3))) -> 772.16593 | Y70: =($D70)/((1+$Y$5/2)^(2*($A70-Y$3))) -> 867.1419 | Z70: =($D70)/((1+$Z$5/2)^(2*($A70-Z$3))) -> 955.28704 | AA70: =($D70)/((1+$AA$5/2)^(2*($A70-AA$3))) -> 1002.3759 | AB70: =($D70)/((1+$AB$5/2)^(2*($A70-AB$3))) -> 1011.6978 | AC70: =($D70)/((1+$AC$5/2)^(2*($A70-AC$3))) -> 1092.936
A71: 25.5 | B71: =$B$1*$B$3/2 -> 1158.0328 | D71: =B71+C71 -> 1158.0328 | E71: =(D71)/(1+$E$5/2)^(2*A71) -> 339.51104 | F71: =($D71)/((1+$F$5/2)^(2*($A71-F$3))) -> 452.77019 | G71: =($D71)/((1+$G$5/2)^(2*($A71-G$3))) -> 297.34225 | H71: =($D71)/((1+$H$5/2)^(2*($A71-H$3))) -> 392.233 | I71: =($D71)/((1+$I$5/2)^(2*($A71-I$3))) -> 507.94629 | J71: =($D71)/((1+$J$5/2)^(2*($A71-J$3))) -> 431.85467 | K71: =($D71)/((1+$K$5/2)^(2*($A71-K$3))) -> 453.14205 | L71: =($D71)/((1+$L$5/2)^(2*($A71-L$3))) -> 331.91178 | M71: =($D71)/((1+$M$5/2)^(2*($A71-M$3))) -> 420.73966 | N71: =($D71)/((1+$N$5/2)^(2*($A71-N$3))) -> 379.92051 | O71: =($D71)/((1+$O$5/2)^(2*($A71-O$3))) -> 350.02932 | P71: =($D71)/((1+$P$5/2)^(2*($A71-P$3))) -> 328.99159 | Q71: =($D71)/((1+$Q$5/2)^(2*($A71-Q$3))) -> 408.46205 | R71: =($D71)/((1+$R$5/2)^(2*($A71-R$3))) -> 497.77478 | S71: =($D71)/((1+$S$5/2)^(2*($A71-S$3))) -> 476.64934 | T71: =($D71)/((1+$T$5/2)^(2*($A71-T$3))) -> 465.5361 | U71: =($D71)/((1+$U$5/2)^(2*($A71-U$3))) -> 556.21958 | V71: =($D71)/((1+$V$5/2)^(2*($A71-V$3))) -> 553.78049 | W71: =($D71)/((1+$W$5/2)^(2*($A71-W$3))) -> 697.76323 | X71: =($D71)/((1+$X$5/2)^(2*($A71-X$3))) -> 746.52287 | Y71: =($D71)/((1+$Y$5/2)^(2*($A71-Y$3))) -> 842.41696 | Z71: =($D71)/((1+$Z$5/2)^(2*($A71-Z$3))) -> 932.57875 | AA71: =($D71)/((1+$AA$5/2)^(2*($A71-AA$3))) -> 978.54828 | AB71: =($D71)/((1+$AB$5/2)^(2*($A71-AB$3))) -> 978.10002 | AC71: =($D71)/((1+$AC$5/2)^(2*($A71-AC$3))) -> 1061.7729 | AD71: =($D71)/((1+$AD$5/2)^(2*($A71-AD$3))) -> 1119.5754
A72: 26 | B72: =$B$1*$B$3/2 -> 1158.0328 | D72: =B72+C72 -> 1158.0328 | E72: =(D72)/(1+$E$5/2)^(2*A72) -> 331.44046 | F72: =($D72)/((1+$F$5/2)^(2*($A72-F$3))) -> 444.1754 | G72: =($D72)/((1+$G$5/2)^(2*($A72-G$3))) -> 288.86409 | H72: =($D72)/((1+$H$5/2)^(2*($A72-H$3))) -> 382.90916 | I72: =($D72)/((1+$I$5/2)^(2*($A72-I$3))) -> 498.3041 | J72: =($D72)/((1+$J$5/2)^(2*($A72-J$3))) -> 421.58898 | K72: =($D72)/((1+$K$5/2)^(2*($A72-K$3))) -> 442.37033 | L72: =($D72)/((1+$L$5/2)^(2*($A72-L$3))) -> 320.88923 | M72: =($D72)/((1+$M$5/2)^(2*($A72-M$3))) -> 408.74305 | N72: =($D72)/((1+$N$5/2)^(2*($A72-N$3))) -> 367.30363 | O72: =($D72)/((1+$O$5/2)^(2*($A72-O$3))) -> 336.77714 | P72: =($D72)/((1+$P$5/2)^(2*($A72-P$3))) -> 315.02044 | Q72: =($D72)/((1+$Q$5/2)^(2*($A72-Q$3))) -> 392.99759 | R72: =($D72)/((1+$R$5/2)^(2*($A72-R$3))) -> 481.24405 | S72: =($D72)/((1+$S$5/2)^(2*($A72-S$3))) -> 458.6033 | T72: =($D72)/((1+$T$5/2)^(2*($A72-T$3))) -> 445.76637 | U72: =($D72)/((1+$U$5/2)^(2*($A72-U$3))) -> 535.161 | V72: =($D72)/((1+$V$5/2)^(2*($A72-V$3))) -> 530.26331 | W72: =($D72)/((1+$W$5/2)^(2*($A72-W$3))) -> 674.59103 | X72: =($D72)/((1+$X$5/2)^(2*($A72-X$3))) -> 721.7314 | Y72: =($D72)/((1+$Y$5/2)^(2*($A72-Y$3))) -> 818.39701 | Z72: =($D72)/((1+$Z$5/2)^(2*($A72-Z$3))) -> 910.41026 | AA72: =($D72)/((1+$AA$5/2)^(2*($A72-AA$3))) -> 955.28704 | AB72: =($D72)/((1+$AB$5/2)^(2*($A72-AB$3))) -> 945.61804 | AC72: =($D72)/((1+$AC$5/2)^(2*($A72-AC$3))) -> 1031.4985 | AD72: =($D72)/((1+$AD$5/2)^(2*($A72-AD$3))) -> 1082.3951
A73: 26.5 | B73: =$B$1*$B$3/2 -> 1158.0328 | D73: =B73+C73 -> 1158.0328 | E73: =(D73)/(1+$E$5/2)^(2*A73) -> 323.56174 | F73: =($D73)/((1+$F$5/2)^(2*($A73-F$3))) -> 435.74375 | G73: =($D73)/((1+$G$5/2)^(2*($A73-G$3))) -> 280.62767 | H73: =($D73)/((1+$H$5/2)^(2*($A73-H$3))) -> 373.80696 | I73: =($D73)/((1+$I$5/2)^(2*($A73-I$3))) -> 488.84495 | J73: =($D73)/((1+$J$5/2)^(2*($A73-J$3))) -> 411.56731 | K73: =($D73)/((1+$K$5/2)^(2*($A73-K$3))) -> 431.85467 | L73: =($D73)/((1+$L$5/2)^(2*($A73-L$3))) -> 310.23274 | M73: =($D73)/((1+$M$5/2)^(2*($A73-M$3))) -> 397.0885 | N73: =($D73)/((1+$N$5/2)^(2*($A73-N$3))) -> 355.10575 | O73: =($D73)/((1+$O$5/2)^(2*($A73-O$3))) -> 324.02669 | P73: =($D73)/((1+$P$5/2)^(2*($A73-P$3))) -> 301.64259 | Q73: =($D73)/((1+$Q$5/2)^(2*($A73-Q$3))) -> 378.11862 | R73: =($D73)/((1+$R$5/2)^(2*($A73-R$3))) -> 465.26229 | S73: =($D73)/((1+$S$5/2)^(2*($A73-S$3))) -> 441.24048 | T73: =($D73)/((1+$T$5/2)^(2*($A73-T$3))) -> 426.83618 | U73: =($D73)/((1+$U$5/2)^(2*($A73-U$3))) -> 514.89969 | V73: =($D73)/((1+$V$5/2)^(2*($A73-V$3))) -> 507.74483 | W73: =($D73)/((1+$W$5/2)^(2*($A73-W$3))) -> 652.18836 | X73: =($D73)/((1+$X$5/2)^(2*($A73-X$3))) -> 697.76323 | Y73: =($D73)/((1+$Y$5/2)^(2*($A73-Y$3))) -> 795.06194 | Z73: =($D73)/((1+$Z$5/2)^(2*($A73-Z$3))) -> 888.76874 | AA73: =($D73)/((1+$AA$5/2)^(2*($A73-AA$3))) -> 932.57875 | AB73: =($D73)/((1+$AB$5/2)^(2*($A73-AB$3))) -> 914.21476 | AC73: =($D73)/((1+$AC$5/2)^(2*($A73-AC$3))) -> 1002.0872 | AD73: =($D73)/((1+$AD$5/2)^(2*($A73-AD$3))) -> 1046.4496 | AE73: =($D73)/((1+$AE$5/2)^(2*($A73-AE$3))) -> 1114.1894
A74: 27 | B74: =$B$1*$B$3/2 -> 1158.0328 | D74: =B74+C74 -> 1158.0328 | E74: =(D74)/(1+$E$5/2)^(2*A74) -> 315.87029 | F74: =($D74)/((1+$F$5/2)^(2*($A74-F$3))) -> 427.47217 | G74: =($D74)/((1+$G$5/2)^(2*($A74-G$3))) -> 272.62609 | H74: =($D74)/((1+$H$5/2)^(2*($A74-H$3))) -> 364.92113 | I74: =($D74)/((1+$I$5/2)^(2*($A74-I$3))) -> 479.56536 | J74: =($D74)/((1+$J$5/2)^(2*($A74-J$3))) -> 401.78387 | K74: =($D74)/((1+$K$5/2)^(2*($A74-K$3))) -> 421.58898 | L74: =($D74)/((1+$L$5/2)^(2*($A74-L$3))) -> 299.93014 | M74: =($D74)/((1+$M$5/2)^(2*($A74-M$3))) -> 385.76626 | N74: =($D74)/((1+$N$5/2)^(2*($A74-N$3))) -> 343.31295 | O74: =($D74)/((1+$O$5/2)^(2*($A74-O$3))) -> 311.75898 | P74: =($D74)/((1+$P$5/2)^(2*($A74-P$3))) -> 288.83285 | Q74: =($D74)/((1+$Q$5/2)^(2*($A74-Q$3))) -> 363.80298 | R74: =($D74)/((1+$R$5/2)^(2*($A74-R$3))) -> 449.81127 | S74: =($D74)/((1+$S$5/2)^(2*($A74-S$3))) -> 424.53503 | T74: =($D74)/((1+$T$5/2)^(2*($A74-T$3))) -> 408.7099 | U74: =($D74)/((1+$U$5/2)^(2*($A74-U$3))) -> 495.40549 | V74: =($D74)/((1+$V$5/2)^(2*($A74-V$3))) -> 486.18263 | W74: =($D74)/((1+$W$5/2)^(2*($A74-W$3))) -> 630.52966 | X74: =($D74)/((1+$X$5/2)^(2*($A74-X$3))) -> 674.59103 | Y74: =($D74)/((1+$Y$5/2)^(2*($A74-Y$3))) -> 772.39223 | Z74: =($D74)/((1+$Z$5/2)^(2*($A74-Z$3))) -> 867.64167 | AA74: =($D74)/((1+$AA$5/2)^(2*($A74-AA$3))) -> 910.41026 | AB74: =($D74)/((1+$AB$5/2)^(2*($A74-AB$3))) -> 883.85436 | AC74: =($D74)/((1+$AC$5/2)^(2*($A74-AC$3))) -> 973.51455 | AD74: =($D74)/((1+$AD$5/2)^(2*($A74-AD$3))) -> 1011.6978 | AE74: =($D74)/((1+$AE$5/2)^(2*($A74-AE$3))) -> 1072.006
A75: 27.5 | B75: =$B$1*$B$3/2 -> 1158.0328 | D75: =B75+C75 -> 1158.0328 | E75: =(D75)/(1+$E$5/2)^(2*A75) -> 308.36169 | F75: =($D75)/((1+$F$5/2)^(2*($A75-F$3))) -> 419.3576 | G75: =($D75)/((1+$G$5/2)^(2*($A75-G$3))) -> 264.85267 | H75: =($D75)/((1+$H$5/2)^(2*($A75-H$3))) -> 356.24653 | I75: =($D75)/((1+$I$5/2)^(2*($A75-I$3))) -> 470.46192 | J75: =($D75)/((1+$J$5/2)^(2*($A75-J$3))) -> 392.233 | K75: =($D75)/((1+$K$5/2)^(2*($A75-K$3))) -> 411.56731 | L75: =($D75)/((1+$L$5/2)^(2*($A75-L$3))) -> 289.96968 | M75: =($D75)/((1+$M$5/2)^(2*($A75-M$3))) -> 374.76686 | N75: =($D75)/((1+$N$5/2)^(2*($A75-N$3))) -> 331.91178 | O75: =($D75)/((1+$O$5/2)^(2*($A75-O$3))) -> 299.95572 | P75: =($D75)/((1+$P$5/2)^(2*($A75-P$3))) -> 276.5671 | Q75: =($D75)/((1+$Q$5/2)^(2*($A75-Q$3))) -> 350.02932 | R75: =($D75)/((1+$R$5/2)^(2*($A75-R$3))) -> 434.87337 | S75: =($D75)/((1+$S$5/2)^(2*($A75-S$3))) -> 408.46205 | T75: =($D75)/((1+$T$5/2)^(2*($A75-T$3))) -> 391.35338 | U75: =($D75)/((1+$U$5/2)^(2*($A75-U$3))) -> 476.64934 | V75: =($D75)/((1+$V$5/2)^(2*($A75-V$3))) -> 465.5361 | W75: =($D75)/((1+$W$5/2)^(2*($A75-W$3))) -> 609.59024 | X75: =($D75)/((1+$X$5/2)^(2*($A75-X$3))) -> 652.18836 | Y75: =($D75)/((1+$Y$5/2)^(2*($A75-Y$3))) -> 750.3689 | Z75: =($D75)/((1+$Z$5/2)^(2*($A75-Z$3))) -> 847.01681 | AA75: =($D75)/((1+$AA$5/2)^(2*($A75-AA$3))) -> 888.76874 | AB75: =($D75)/((1+$AB$5/2)^(2*($A75-AB$3))) -> 854.50221 | AC75: =($D75)/((1+$AC$5/2)^(2*($A75-AC$3))) -> 945.7566 | AD75: =($D75)/((1+$AD$5/2)^(2*($A75-AD$3))) -> 978.10002 | AE75: =($D75)/((1+$AE$5/2)^(2*($A75-AE$3))) -> 1031.4196 | AF75: =($D75)/((1+$AF$5/2)^(2*($A75-AF$3))) -> 1108.8551
A76: 28 | B76: =$B$1*$B$3/2 -> 1158.0328 | D76: =B76+C76 -> 1158.0328 | E76: =(D76)/(1+$E$5/2)^(2*A76) -> 301.03157 | F76: =($D76)/((1+$F$5/2)^(2*($A76-F$3))) -> 411.39706 | G76: =($D76)/((1+$G$5/2)^(2*($A76-G$3))) -> 257.30088 | H76: =($D76)/((1+$H$5/2)^(2*($A76-H$3))) -> 347.77813 | I76: =($D76)/((1+$I$5/2)^(2*($A76-I$3))) -> 461.53129 | J76: =($D76)/((1+$J$5/2)^(2*($A76-J$3))) -> 382.90916 | K76: =($D76)/((1+$K$5/2)^(2*($A76-K$3))) -> 401.78387 | L76: =($D76)/((1+$L$5/2)^(2*($A76-L$3))) -> 280.34 | M76: =($D76)/((1+$M$5/2)^(2*($A76-M$3))) -> 364.08108 | N76: =($D76)/((1+$N$5/2)^(2*($A76-N$3))) -> 320.88923 | O76: =($D76)/((1+$O$5/2)^(2*($A76-O$3))) -> 288.59934 | P76: =($D76)/((1+$P$5/2)^(2*($A76-P$3))) -> 264.82223 | Q76: =($D76)/((1+$Q$5/2)^(2*($A76-Q$3))) -> 336.77714 | R76: =($D76)/((1+$R$5/2)^(2*($A76-R$3))) -> 420.43155 | S76: =($D76)/((1+$S$5/2)^(2*($A76-S$3))) -> 392.99759 | T76: =($D76)/((1+$T$5/2)^(2*($A76-T$3))) -> 374.73393 | U76: =($D76)/((1+$U$5/2)^(2*($A76-U$3))) -> 458.6033 | V76: =($D76)/((1+$V$5/2)^(2*($A76-V$3))) -> 445.76637 | W76: =($D76)/((1+$W$5/2)^(2*($A76-W$3))) -> 589.3462 | X76: =($D76)/((1+$X$5/2)^(2*($A76-X$3))) -> 630.52966 | Y76: =($D76)/((1+$Y$5/2)^(2*($A76-Y$3))) -> 728.97353 | Z76: =($D76)/((1+$Z$5/2)^(2*($A76-Z$3))) -> 826.88222 | AA76: =($D76)/((1+$AA$5/2)^(2*($A76-AA$3))) -> 867.64167 | AB76: =($D76)/((1+$AB$5/2)^(2*($A76-AB$3))) -> 826.12482 | AC76: =($D76)/((1+$AC$5/2)^(2*($A76-AC$3))) -> 918.79011 | AD76: =($D76)/((1+$AD$5/2)^(2*($A76-AD$3))) -> 945.61804 | AE76: =($D76)/((1+$AE$5/2)^(2*($A76-AE$3))) -> 992.36989 | AF76: =($D76)/((1+$AF$5/2)^(2*($A76-AF$3))) -> 1061.7658
A77: 28.5 | B77: =$B$1*$B$3/2 -> 1158.0328 | D77: =B77+C77 -> 1158.0328 | E77: =(D77)/(1+$E$5/2)^(2*A77) -> 293.8757 | F77: =($D77)/((1+$F$5/2)^(2*($A77-F$3))) -> 403.58764 | G77: =($D77)/((1+$G$5/2)^(2*($A77-G$3))) -> 249.96443 | H77: =($D77)/((1+$H$5/2)^(2*($A77-H$3))) -> 339.51104 | I77: =($D77)/((1+$I$5/2)^(2*($A77-I$3))) -> 452.77019 | J77: =($D77)/((1+$J$5/2)^(2*($A77-J$3))) -> 373.80696 | K77: =($D77)/((1+$K$5/2)^(2*($A77-K$3))) -> 392.233 | L77: =($D77)/((1+$L$5/2)^(2*($A77-L$3))) -> 271.03012 | M77: =($D77)/((1+$M$5/2)^(2*($A77-M$3))) -> 353.69998 | N77: =($D77)/((1+$N$5/2)^(2*($A77-N$3))) -> 310.23274 | O77: =($D77)/((1+$O$5/2)^(2*($A77-O$3))) -> 277.67291 | P77: =($D77)/((1+$P$5/2)^(2*($A77-P$3))) -> 253.57613 | Q77: =($D77)/((1+$Q$5/2)^(2*($A77-Q$3))) -> 324.02669 | R77: =($D77)/((1+$R$5/2)^(2*($A77-R$3))) -> 406.46933 | S77: =($D77)/((1+$S$5/2)^(2*($A77-S$3))) -> 378.11862 | T77: =($D77)/((1+$T$5/2)^(2*($A77-T$3))) -> 358.82025 | U77: =($D77)/((1+$U$5/2)^(2*($A77-U$3))) -> 441.24048 | V77: =($D77)/((1+$V$5/2)^(2*($A77-V$3))) -> 426.83618 | W77: =($D77)/((1+$W$5/2)^(2*($A77-W$3))) -> 569.77444 | X77: =($D77)/((1+$X$5/2)^(2*($A77-X$3))) -> 609.59024 | Y77: =($D77)/((1+$Y$5/2)^(2*($A77-Y$3))) -> 708.18821 | Z77: =($D77)/((1+$Z$5/2)^(2*($A77-Z$3))) -> 807.22626 | AA77: =($D77)/((1+$AA$5/2)^(2*($A77-AA$3))) -> 847.01681 | AB77: =($D77)/((1+$AB$5/2)^(2*($A77-AB$3))) -> 798.68983 | AC77: =($D77)/((1+$AC$5/2)^(2*($A77-AC$3))) -> 892.59252 | AD77: =($D77)/((1+$AD$5/2)^(2*($A77-AD$3))) -> 914.21476 | AE77: =($D77)/((1+$AE$5/2)^(2*($A77-AE$3))) -> 954.79857 | AF77: =($D77)/((1+$AF$5/2)^(2*($A77-AF$3))) -> 1016.6762 | AG77: =($D77)/((1+$AG$5/2)^(2*($A77-AG$3))) -> 1119.5754
A78: 29 | B78: =$B$1*$B$3/2 -> 1158.0328 | D78: =B78+C78 -> 1158.0328 | E78: =(D78)/(1+$E$5/2)^(2*A78) -> 286.88993 | F78: =($D78)/((1+$F$5/2)^(2*($A78-F$3))) -> 395.92647 | G78: =($D78)/((1+$G$5/2)^(2*($A78-G$3))) -> 242.83716 | H78: =($D78)/((1+$H$5/2)^(2*($A78-H$3))) -> 331.44046 | I78: =($D78)/((1+$I$5/2)^(2*($A78-I$3))) -> 444.1754 | J78: =($D78)/((1+$J$5/2)^(2*($A78-J$3))) -> 364.92113 | K78: =($D78)/((1+$K$5/2)^(2*($A78-K$3))) -> 382.90916 | L78: =($D78)/((1+$L$5/2)^(2*($A78-L$3))) -> 262.02941 | M78: =($D78)/((1+$M$5/2)^(2*($A78-M$3))) -> 343.61488 | N78: =($D78)/((1+$N$5/2)^(2*($A78-N$3))) -> 299.93014 | O78: =($D78)/((1+$O$5/2)^(2*($A78-O$3))) -> 267.16015 | P78: =($D78)/((1+$P$5/2)^(2*($A78-P$3))) -> 242.80761 | Q78: =($D78)/((1+$Q$5/2)^(2*($A78-Q$3))) -> 311.75898 | R78: =($D78)/((1+$R$5/2)^(2*($A78-R$3))) -> 392.97078 | S78: =($D78)/((1+$S$5/2)^(2*($A78-S$3))) -> 363.80298 | T78: =($D78)/((1+$T$5/2)^(2*($A78-T$3))) -> 343.58237 | U78: =($D78)/((1+$U$5/2)^(2*($A78-U$3))) -> 424.53503 | V78: =($D78)/((1+$V$5/2)^(2*($A78-V$3))) -> 408.7099 | W78: =($D78)/((1+$W$5/2)^(2*($A78-W$3))) -> 550.85266 | X78: =($D78)/((1+$X$5/2)^(2*($A78-X$3))) -> 589.3462 | Y78: =($D78)/((1+$Y$5/2)^(2*($A78-Y$3))) -> 687.99554 | Z78: =($D78)/((1+$Z$5/2)^(2*($A78-Z$3))) -> 788.03755 | AA78: =($D78)/((1+$AA$5/2)^(2*($A78-AA$3))) -> 826.88222 | AB78: =($D78)/((1+$AB$5/2)^(2*($A78-AB$3))) -> 772.16593 | AC78: =($D78)/((1+$AC$5/2)^(2*($A78-AC$3))) -> 867.1419 | AD78: =($D78)/((1+$AD$5/2)^(2*($A78-AD$3))) -> 883.85436 | AE78: =($D78)/((1+$AE$5/2)^(2*($A78-AE$3))) -> 918.6497 | AF78: =($D78)/((1+$AF$5/2)^(2*($A78-AF$3))) -> 973.50139 | AG78: =($D78)/((1+$AG$5/2)^(2*($A78-AG$3))) -> 1082.3951
A79: 29.5 | B79: =$B$1*$B$3/2 -> 1158.0328 | D79: =B79+C79 -> 1158.0328 | E79: =(D79)/(1+$E$5/2)^(2*A79) -> 280.07022 | F79: =($D79)/((1+$F$5/2)^(2*($A79-F$3))) -> 388.41072 | G79: =($D79)/((1+$G$5/2)^(2*($A79-G$3))) -> 235.91311 | H79: =($D79)/((1+$H$5/2)^(2*($A79-H$3))) -> 323.56174 | I79: =($D79)/((1+$I$5/2)^(2*($A79-I$3))) -> 435.74375 | J79: =($D79)/((1+$J$5/2)^(2*($A79-J$3))) -> 356.24653 | K79: =($D79)/((1+$K$5/2)^(2*($A79-K$3))) -> 373.80696 | L79: =($D79)/((1+$L$5/2)^(2*($A79-L$3))) -> 253.3276 | M79: =($D79)/((1+$M$5/2)^(2*($A79-M$3))) -> 333.81735 | N79: =($D79)/((1+$N$5/2)^(2*($A79-N$3))) -> 289.96968 | O79: =($D79)/((1+$O$5/2)^(2*($A79-O$3))) -> 257.04542 | P79: =($D79)/((1+$P$5/2)^(2*($A79-P$3))) -> 232.4964 | Q79: =($D79)/((1+$Q$5/2)^(2*($A79-Q$3))) -> 299.95572 | R79: =($D79)/((1+$R$5/2)^(2*($A79-R$3))) -> 379.92051 | S79: =($D79)/((1+$S$5/2)^(2*($A79-S$3))) -> 350.02932 | T79: =($D79)/((1+$T$5/2)^(2*($A79-T$3))) -> 328.99159 | U79: =($D79)/((1+$U$5/2)^(2*($A79-U$3))) -> 408.46205 | V79: =($D79)/((1+$V$5/2)^(2*($A79-V$3))) -> 391.35338 | W79: =($D79)/((1+$W$5/2)^(2*($A79-W$3))) -> 532.55925 | X79: =($D79)/((1+$X$5/2)^(2*($A79-X$3))) -> 569.77444 | Y79: =($D79)/((1+$Y$5/2)^(2*($A79-Y$3))) -> 668.37862 | Z79: =($D79)/((1+$Z$5/2)^(2*($A79-Z$3))) -> 769.30497 | AA79: =($D79)/((1+$AA$5/2)^(2*($A79-AA$3))) -> 807.22626 | AB79: =($D79)/((1+$AB$5/2)^(2*($A79-AB$3))) -> 746.52287 | AC79: =($D79)/((1+$AC$5/2)^(2*($A79-AC$3))) -> 842.41696 | AD79: =($D79)/((1+$AD$5/2)^(2*($A79-AD$3))) -> 854.50221 | AE79: =($D79)/((1+$AE$5/2)^(2*($A79-AE$3))) -> 883.86944 | AF79: =($D79)/((1+$AF$5/2)^(2*($A79-AF$3))) -> 932.16009 | AG79: =($D79)/((1+$AG$5/2)^(2*($A79-AG$3))) -> 1046.4496 | AH79: =($D79)/((1+$AH$5/2)^(2*($A79-AH$3))) -> 1119.5754
A80: 30 | B80: =$B$1*$B$3/2 -> 1158.0328 | C80: =B1 -> 57901.64 | D80: =B80+C80 -> 59059.673 | E80: =(D80)/(1+$E$5/2)^(2*A80) -> 13944.044 | F80: =($D80)/((1+$F$5/2)^(2*($A80-F$3))) -> 19432.92 | G80: =($D80)/((1+$G$5/2)^(2*($A80-G$3))) -> 11688.511 | H80: =($D80)/((1+$H$5/2)^(2*($A80-H$3))) -> 16109.385 | I80: =($D80)/((1+$I$5/2)^(2*($A80-I$3))) -> 21801.081 | J80: =($D80)/((1+$J$5/2)^(2*($A80-J$3))) -> 17736.685 | K80: =($D80)/((1+$K$5/2)^(2*($A80-K$3))) -> 18610.978 | L80: =($D80)/((1+$L$5/2)^(2*($A80-L$3))) -> 12490.654 | M80: =($D80)/((1+$M$5/2)^(2*($A80-M$3))) -> 16539.257 | N80: =($D80)/((1+$N$5/2)^(2*($A80-N$3))) -> 14297.34 | O80: =($D80)/((1+$O$5/2)^(2*($A80-O$3))) -> 12612.995 | P80: =($D80)/((1+$P$5/2)^(2*($A80-P$3))) -> 11353.776 | Q80: =($D80)/((1+$Q$5/2)^(2*($A80-Q$3))) -> 14718.566 | R80: =($D80)/((1+$R$5/2)^(2*($A80-R$3))) -> 18732.485 | S80: =($D80)/((1+$S$5/2)^(2*($A80-S$3))) -> 17175.634 | T80: =($D80)/((1+$T$5/2)^(2*($A80-T$3))) -> 16066.042 | U80: =($D80)/((1+$U$5/2)^(2*($A80-U$3))) -> 20042.877 | V80: =($D80)/((1+$V$5/2)^(2*($A80-V$3))) -> 19111.43 | W80: =($D80)/((1+$W$5/2)^(2*($A80-W$3))) -> 26258.541 | X80: =($D80)/((1+$X$5/2)^(2*($A80-X$3))) -> 28093.485 | Y80: =($D80)/((1+$Y$5/2)^(2*($A80-Y$3))) -> 33115.374 | Z80: =($D80)/((1+$Z$5/2)^(2*($A80-Z$3))) -> 38301.902 | AA80: =($D80)/((1+$AA$5/2)^(2*($A80-AA$3))) -> 40189.915 | AB80: =($D80)/((1+$AB$5/2)^(2*($A80-AB$3))) -> 36808.301 | AC80: =($D80)/((1+$AC$5/2)^(2*($A80-AC$3))) -> 41738.248 | AD80: =($D80)/((1+$AD$5/2)^(2*($A80-AD$3))) -> 42132.366 | AE80: =($D80)/((1+$AE$5/2)^(2*($A80-AE$3))) -> 43370.704 | AF80: =($D80)/((1+$AF$5/2)^(2*($A80-AF$3))) -> 45521.295 | AG80: =($D80)/((1+$AG$5/2)^(2*($A80-AG$3))) -> 51596.585 | AH80: =($D80)/((1+$AH$5/2)^(2*($A80-AH$3))) -> 55202.151 | AI80: =C80 -> 57901.64

Sheet Bal sheets on Day 1
B6: 165 Whitney Associates LLC
B7: Balance Sheet
B8: as of Open of Business on
B9: =Date -> 46055
B10: Assets | D10: Liabilities
B11: Cash | C11: 0 | D11: Payables | E11: 0
D12: Equities | E12: 0
B13: Total assets | C13: 0 | D13: Total Liab & Equities | E13: 0
B19: 165 Whitney Associates LLC
B20: Balance Sheet
B21: as of 9:30 am on
B22: =Date -> 46055
B23: Assets | D23: Liabilities
B24: Cash | C24: 50000 | D24: Payables | E24: 0
D25: Equities | E25: 50000
B26: Total assets | C26: =SUM(C24:C25) -> 50000 | D26: Total Liab & Equities | E26: =SUM(E24:E25) -> 50000
B32: 165 Whitney Associates LLC
B33: Balance Sheet
B34: as of Close of Business on
B35: =Date -> 46055
B36: Assets | D36: Liabilities
B37: Cash | C37: 0 | D37: Payables | E37: 0
B38: U.S Govt 30 year Bonds | C38: 50000 | D38: Equities | E38: 50000
B39: Total assets | C39: =SUM(C37:C38) -> 50000 | D39: Total Liab & Equities | E39: =SUM(E37:E38) -> 50000

Sheet 6 Months Later
A1: Question 1: How much interest did 165WA earn over this first six months? | F1: Accounting statements:
A3: Interest revenue | F3: 165 Whitney Associates LLC
B4: Amount of investment at beg of period: | C4: 50000 | F4: Balance Sheets
B5: Interest rate: | C5: =InterestRate -> 0.0487 | F5: as of Close of Business on
B6: Semi-annual factor | C6: 2
B7: Interest earned | C7: =C4*(C5/2) -> 1217.5 | G7: =TEXT(DATE(YEAR(Date),MONTH(Date)+6,DAY(Date)),"mmmm dd, yyyy") -> August 02, 2026 | H7: =TEXT(DATE(YEAR(Date),MONTH(Date),DAY(Date)-1),"mmmm dd, yyyy") -> February 01, 2026
F8: Assets
A9: Question 2: How much cash did 165WA get? | F9: Cash | G9: =C16 -> 1158.0328 | H9: 0
F10: U.S. Govt 30 Year Bonds | G10: =C24 -> 50059.467 | H10: 0
A11: Coupon payment | F11: Total Assets | G11: =SUM(G9:G10) -> 51217.5 | H11: =SUM(H9:H10) -> 0
B13: Face value of bonds | C13: ='Economics of 165WA''s investment'!B1 -> 57901.64 | F13: Liabilites | G13: 0 | H13: 0
B14: Coupon rate | C14: =CouponRate -> 0.04
B15: Semi-annual factor | C15: 2 | F15: Equity
B16: Cash received | C16: =C13*(C14/C15) -> 1158.0328 | F16: Contributed | G16: =50000 -> 50000 | H16: 0
F17: Retained Earnings | G17: =H17+G29 -> 1217.5 | H17: 0
G18: =SUM(G16:G17) -> 51217.5 | H18: =SUM(H16:H17) -> 0
A19: Question 3: How did the value of the bond change over these 6 months?
F20: 165 Whitney Associates LLC
B21: ="Value at "&TEXT(Date,"mmmm dd, yyyy") -> Value at February 02, 2026 | C21: 50000 | F21: Income Statement
B22: Coupon payment | C22: =-C16 -> -1158.0328 | F22: For the Six Months Ended
B23: Interest earned | C23: =C7 -> 1217.5 | F23: =DATE(YEAR(Date),MONTH(Date)+6,DAY(Date)) -> 46236
B24: ="Value at "&TEXT(DATE(YEAR(Date),MONTH(Date)+6,DAY(Date)),"mmmm dd, yyyy") -> Value at August 02, 2026 | C24: =SUM(C21:C23) -> 50059.467
F25: Revenues
B26: Change in value | C26: =C24-C21 -> 59.4672 | F26: Interest income | G26: =C7 -> 1217.5
A28: Alternatively: | F28: Expenses | G28: 0
B29: PV of remaining cash flows at: | F29: Net Income | G29: =SUM(G26:G28) -> 1217.5
B30: =DATE(YEAR(Date),MONTH(Date)+6,DAY(Date)) -> 46236 | C30: =C24 -> 50059.467
B31: =Date -> 46055 | C31: 50000 | F31: 165 Whitney Associates LLC
B32: Change in value | C32: =C30-C31 -> 59.4672 | F32: Statement of Changes in Members' Equity
F33: For the Six Months Ended
F34: =DATE(YEAR(Date),MONTH(Date)+6,DAY(Date)) -> 46236
G36: Contributed | H36: Earned and Retained | I36: Total
F37: ="Balance on "&TEXT(Date,"mmmm dd, yyyy") -> Balance on February 02, 2026 | G37: 0 | H37: 0 | I37: =SUM(G37:H37) -> 0
F38: Issued equity to members | G38: 50000 | I38: =SUM(G38:H38) -> 50000
F39: Net income | H39: =G29 -> 1217.5 | I39: =SUM(G39:H39) -> 1217.5
F40: ="Balance on "&TEXT(DATE(YEAR(Date),MONTH(Date)+6,DAY(Date)),"mmmm dd, yyyy") -> Balance on August 02, 2026 | G40: =SUM(G37:G39) -> 50000 | H40: =SUM(H37:H39) -> 1217.5 | I40: =SUM(I37:I39) -> 51217.5
F43: 165 Whitney Associates LLC
F44: Cash Flow Statement (Direct Method)
F45: For the Six Months Ended
F46: =DATE(YEAR(Date),MONTH(Date)+6,DAY(Date)) -> 46236
F48: Operations
F49: Coupon payment | G49: =C16 -> 1158.0328
F51: Investing
F52: Bought bonds | G52: -50000
F54: Financing
F55: Issued shares | G55: 50000
F57: Total cash flows | G57: =SUM(G49:G56) -> 1158.0328
E58: Cash at | F58: =Date -> 46055 | G58: 0
E59: Cash at | F59: =DATE(YEAR(Date),MONTH(Date)+6,DAY(Date)) -> 46236 | G59: =SUM(G57:G58) -> 1158.0328
F61: 165 Whitney Associates LLC
F62: Reconciliation of Net Income and Cash Flow from Operations
F63: For the Six Months Ended
F64: =DATE(YEAR(Date),MONTH(Date)+6,DAY(Date)) -> 46236
F66: Net income | G66: =C7 -> 1217.5
F67: Amortization of bond discount | G67: =-C32 -> -59.4672
F68: Cash flow from operations | G68: =SUM(G66:G67) -> 1158.0328

Sheet 1 Year Later
A1: Now we zoom ahead another six months to the end of the day on | D1: =DATE(YEAR(Date)+1,MONTH(Date),DAY(Date)) -> 46420 | H1: Accounting statements:
A3: Question 3: How much interest revenue did 165WA earn over the second six months? | H3: 165 Whitney Associates LLC
H4: Balance Sheets
A5: First, what about the cash of: | C5: ='6 Months Later'!G9 -> 1158.0328 | H5: as of Close of Business on
A6: Assume it is held in a jar in the Dean's office. I.e., it is not earning anything.
I7: =DATE(YEAR(Date)+1,MONTH(Date),DAY(Date)) -> 46420 | J7: =DATE(YEAR(Date),MONTH(Date),DAY(Date)-1) -> 46054
B8: Amount of investment at beg of period: | C8: ='6 Months Later'!C24 -> 50059.467 | H8: Assets
B9: Interest rate: | C9: =InterestRate -> 0.0487 | H9: Cash | I9: =C18*2 -> 2316.0656 | J9: 0
B10: Semi-annual factor | C10: 2 | H10: U.S. Govt 30 Year Bonds | I10: =C25 -> 50120.382 | J10: 0
B11: Interest earned | C11: =C8*(C9/C10) -> 1218.948 | H11: Total Assets | I11: =SUM(I9:I10) -> 52436.448 | J11: =SUM(J9:J10) -> 0
A13: Question 4: How much cash did 165WA receive during the second six months? | H13: Liabilites | I13: 0 | J13: 0
B15: Face value of bonds | C15: ='Economics of 165WA''s investment'!B1 -> 57901.64 | H15: Equity
B16: Coupon rate | C16: =CouponRate -> 0.04 | H16: Contributed | I16: 50000 | J16: 0
B17: Semi-annual adjustment factor | C17: 2 | H17: Retained Earnings | I17: =J17+I29 -> 2436.448 | J17: 0
B18: Payment received | C18: =C15*(C16/C17) -> 1158.0328 | I18: =SUM(I16:I17) -> 52436.448 | J18: =SUM(J16:J17) -> 0
A20: Question 5: By how much did the value of the bonds change over these 6 months? | H20: 165 Whitney Associates LLC
H21: Income Statement
B22: Value at the beginning | C22: =C8 -> 50059.467 | H22: For the Year Ended
B23: Coupon payment | C23: =-C18 -> -1158.0328 | H23: =DATE(YEAR(Date)+1,MONTH(Date),DAY(Date)) -> 46420
B24: Interest earned | C24: =C11 -> 1218.948
B25: Value of bond at end of year | C25: =SUM(C22:C24) -> 50120.382 | H25: Revenues
H26: Interest income | I26: ='6 Months Later'!C7+C24 -> 2436.448
B27: Change in value | C27: =C25-C22 -> 60.915226
H28: Expenses | I28: 0
B29: Alternatively | H29: Net Income | I29: =SUM(I26:I28) -> 2436.448
B30: Present value of remaining cash flows on:
B31: =DATE(YEAR(Date)+1,MONTH(Date),DAY(Date)) -> 46420 | C31: =C25 -> 50120.382 | H31: 165 Whitney Associates LLC
B32: =DATE(YEAR(Date),MONTH(Date)+6,DAY(Date)) -> 46236 | C32: =C22 -> 50059.467 | H32: Statement of Changes in Members' Equity
B33: Increase in value | C33: =-C32+C31 -> 60.915226 | H33: For the Year Ended
H34: =DATE(YEAR(Date)+1,MONTH(Date),DAY(Date)) -> 46420
I36: Contributed | J36: Earned and Retained | K36: Total
H37: ="Balance on "&TEXT(Date,"mmmm dd, yyyy") -> Balance on February 02, 2026 | I37: 0 | J37: 0 | K37: 0
H38: Issued equity to members | I38: 50000 | K38: 50000
H39: Net income | J39: =I29 -> 2436.448 | K39: 1197.5
H40: ="Balance on "&TEXT(DATE(YEAR(Date)+1,MONTH(Date),DAY(Date)),"mmmm dd, yyyy") -> Balance on February 02, 2027 | I40: 50000 | J40: 1197.5 | K40: 51197.5
H43: 165 Whitney Associates LLC
H44: Cash Flow Statement (Direct Method)
H45: For the Year Ended
H46: =DATE(YEAR(Date)+1,MONTH(Date),DAY(Date)) -> 46420
H48: Operations
H49: Coupon payments | I49: =2*C18 -> 2316.0656
H51: Investing
H52: Bought bonds | I52: -50000
H54: Financing
H55: Issued equity | I55: 50000
H57: Total cash flows | I57: =SUM(I49:I56) -> 2316.0656
G58: Cash on | H58: =Date -> 46055 | I58: 0
G59: Cash on | H59: =DATE(YEAR(Date)+1,MONTH(Date),DAY(Date)) -> 46420 | I59: =SUM(I57:I58) -> 2316.0656
H61: 165 Whitney Associates LLC
H62: Reconciliation of Net Income and Cash Flow from Operations
H63: For the Year Ended
H64: =DATE(YEAR(Date)+1,MONTH(Date),DAY(Date)) -> 46420
H67: Net income | I67: =I29 -> 2436.448
H68: Amortization of bond discount | I68: =-('6 Months Later'!C26+'1 Year Later'!C27) -> -120.38243
H69: Cash flow from operations | I69: =SUM(I67:I68) -> 2316.0656

Sheet 2 Years Later
A1: Now we zoom ahead one year to the end of the day on | C1: =DATE(YEAR(Date)+2,MONTH(Date),DAY(Date)) -> 46785 | E1: Accounting statements:
A3: Question 6: How much interest revenue did 165WA earn over the second year? | E3: 165 Whitney Associates LLC
E4: Balance Sheets
A5: First half of Yr | B5: Amount of investment at beg of period: | C5: ='1 Year Later'!I10 -> 50120.382 | E5: as of
B6: Interest rate: | C6: =InterestRate -> 0.0487
B7: Semi-annual factor | C7: 2 | F7: =DATE(YEAR(Date)+2,MONTH(Date),DAY(Date)) -> 46785 | G7: =DATE(YEAR(Date)+1,MONTH(Date),DAY(Date)) -> 46420
B8: Interest earned | C8: =C5*(C6/C7) -> 1220.4313 | E8: Assets
E9: Cash | F9: =G9+C25 -> 4632.1312 | G9: ='1 Year Later'!I9 -> 2316.0656
A10: Second half of Yr | B10: Amount of investment at beg of period: | C10: =C5+C8-C23 -> 50182.781 | E10: U.S. Govt 30 Year Bonds | F10: =C33 -> 50246.699 | G10: =C5 -> 50120.382
B11: Interest rate: | C11: =InterestRate -> 0.0487 | E11: Total Assets | F11: =SUM(F9:F10) -> 54878.83 | G11: =SUM(G9:G10) -> 52436.448
B12: Semi-annual factor | C12: 2
B13: Interest earned | C13: =C10*(C11/C12) -> 1221.9507 | E13: Liabilites | F13: 0 | G13: 0
A15: Total over the year | C15: =C8+C13 -> 2442.382 | E15: Equity
E16: Contributed | F16: 50000 | G16: ='1 Year Later'!I16 -> 50000
E17: Retained Earnings | F17: ='1 Year Later'!I17+C32 -> 4878.8301 | G17: ='1 Year Later'!I17 -> 2436.448
A18: Question 7: How much cash did 165WA receive during the year? | F18: =SUM(F16:F17) -> 54878.83 | G18: =SUM(G16:G17) -> 52436.448
B20: Face value of bonds | C20: ='Economics of 165WA''s investment'!B1 -> 57901.64 | E20: 165 Whitney Associates LLC
B21: Coupon rate | C21: =CouponRate -> 0.04 | E21: Income Statement
B22: Semi-annual adjustment factor | C22: 2 | E22: For the Year Ended
B23: Payment received each 6 months | C23: =C20*(C21/C22) -> 1158.0328 | E23: =DATE(YEAR(Date)+2,MONTH(Date),DAY(Date)) -> 46785
B24: Number of coupon payments | C24: 2
B25: Cash received during year | C25: =C23*C24 -> 2316.0656 | E25: Revenues
E26: Interest income | F26: =C32 -> 2442.382
A28: Question 8: By how much did the value of the bonds change over the year? | E28: Expenses | F28: 0
E29: Net Income | F29: =SUM(F26:F28) -> 2442.382
B30: Value at the beginning | C30: =C5 -> 50120.382
B31: Coupon payments | C31: =-C25 -> -2316.0656 | E31: 165 Whitney Associates LLC
B32: Interest earned | C32: =C15 -> 2442.382 | E32: Statement of Changes in Members' Equity
B33: Value of bond at end of year | C33: =SUM(C30:C32) -> 50246.699 | E33: For the Year Ended
E34: =DATE(YEAR(Date)+2,MONTH(Date),DAY(Date)) -> 46785
B35: Change | C35: =C33-C30 -> 126.31643
F36: Contributed | G36: Earned and Retained | H36: Total
E37: ="Balance on "&TEXT(DATE(YEAR(Date)+1,MONTH(Date),DAY(Date)),"mmmm dd, yyyy") -> Balance on February 02, 2027 | F37: ='1 Year Later'!I16 -> 50000 | G37: =G17 -> 2436.448 | H37: =SUM(F37:G37) -> 52436.448
E38: Issued equity to members | F38: 0 | G38: 0 | H38: =SUM(F38:G38) -> 0
E39: Net income | G39: =F29 -> 2442.382 | H39: =SUM(F39:G39) -> 2442.382
E40: ="Balance on "&TEXT(DATE(YEAR(Date)+2,MONTH(Date),DAY(Date)),"mmmm dd, yyyy") -> Balance on February 02, 2028 | F40: =SUM(F37:F39) -> 50000 | G40: =SUM(G37:G39) -> 4878.8301 | H40: =SUM(H37:H39) -> 54878.83
E43: 165 Whitney Associates LLC
E44: Cash Flow Statement (Direct method)
E45: For the Year Ended
E46: =DATE(YEAR(Date)+2,MONTH(Date),DAY(Date)) -> 46785
E48: Operations
E49: Coupon payments | F49: =2*C23 -> 2316.0656
E51: Investing
E53: Financing
E56: Total cash flows | F56: =SUM(F49:F55) -> 2316.0656
D57: Cash on | E57: =DATE(YEAR(Date)+1,MONTH(Date),DAY(Date)) -> 46420 | F57: =G9 -> 2316.0656
D58: Cash on | E58: =DATE(YEAR(Date)+2,MONTH(Date),DAY(Date)) -> 46785 | F58: =SUM(F56:F57) -> 4632.1312
E60: 165 Whitney Associates LLC
E61: Reconciliation of Net Income and Cash Flow from Operations
E62: For the Year Ended
E63: =DATE(YEAR(Date)+2,MONTH(Date),DAY(Date)) -> 46785
E65: Net Income | F65: =F29 -> 2442.382
E66: Bond discount amortization | F66: =-C35 -> -126.31643
E67: Cash flow from operations | F67: =F65+F66 -> 2316.0656

Sheet 3 Years Later
A1: Now we zoom ahead one year to the end of the day on | C1: =DATE(YEAR(Date)+3,MONTH(Date),DAY(Date)) -> 47151 | E1: Accounting statements:
A3: Question 9: How much interest revenue did 165WA earn over the second year? | E3: 165 Whitney Associates LLC | J3: 165 Whitney Associates LLC
E4: Balance Sheets | J4: Balance Sheets
A5: First half of Yr | B5: Amount of investment at beg of period: | C5: ='2 Years Later'!F10 -> 50246.699 | E5: as of | J5: as of
B6: Interest rate: | C6: =InterestRate -> 0.0487
B7: Semi-annual factor | C7: 2 | F7: =DATE(YEAR(Date)+3,MONTH(Date),DAY(Date)) -> 47151 | G7: =DATE(YEAR(Date)+2,MONTH(Date),DAY(Date)) -> 46785 | K7: =DATE(YEAR(Date)+3,MONTH(Date),DAY(Date)) -> 47151 | L7: =DATE(YEAR(Date)+2,MONTH(Date),DAY(Date)) -> 46785
B8: Interest earned | C8: =C5*(C6/C7) -> 1223.5071 | E8: Assets | J8: Assets
E9: Cash | F9: =G9+C25 -> 6948.1968 | G9: ='2 Years Later'!$F$9 -> 4632.1312 | J9: Cash | K9: =L9+C25 -> 6948.1968 | L9: ='2 Years Later'!$F$9 -> 4632.1312
A10: Second half of Yr | B10: Amount of investment at beg of period: | C10: =C5+C8-C23 -> 50312.173 | E10: U.S. Govt 30 Year Bonds | F10: =C33 -> 50379.242 | G10: =$C$5 -> 50246.699 | J10: U.S. Govt 30 Year Bonds | K10: =PVs_thru_Time_Calculations!H4 -> 50379.244 | L10: =$C$5 -> 50246.699
B11: Interest rate: | C11: =InterestRate -> 0.0487 | E11: Total Assets | F11: =SUM(F9:F10) -> 57327.439 | G11: =SUM(G9:G10) -> 54878.83 | J11: Total Assets | K11: =SUM(K9:K10) -> 57327.441 | L11: =SUM(L9:L10) -> 54878.83
B12: Semi-annual factor | C12: 2
B13: Interest earned | C13: =C10*(C11/C12) -> 1225.1014 | E13: Liabilites | F13: 0 | G13: 0 | J13: Liabilites | K13: 0 | L13: 0
A15: Total over the year | C15: =C8+C13 -> 2448.6085 | E15: Equity | J15: Equity
E16: Contributed | F16: 50000 | G16: ='2 Years Later'!$F$16 -> 50000 | J16: Contributed | K16: 50000 | L16: ='2 Years Later'!$F$16 -> 50000
E17: Retained Earnings | F17: =G17+F29 -> 7327.4386 | G17: ='2 Years Later'!$F$17 -> 4878.8301 | J17: Retained Earnings | K17: =L17+K29 -> 7327.4386 | L17: ='2 Years Later'!$F$17 -> 4878.8301
A18: Question 10: How much cash did 165WA receive during the year? | F18: =SUM(F16:F17) -> 57327.439 | G18: =SUM(G16:G17) -> 54878.83 | K18: =SUM(K16:K17) -> 57327.439 | L18: =SUM(L16:L17) -> 54878.83
B20: Face value of bonds | C20: ='Economics of 165WA''s investment'!B1 -> 57901.64 | E20: 165 Whitney Associates LLC
B21: Coupon rate | C21: =CouponRate -> 0.04 | E21: Income Statement
B22: Semi-annual adjustment factor | C22: 2 | E22: For the Year Ended | J22: 165 Whitney Associates LLC
B23: Payment received each 6 months | C23: =C20*(C21/C22) -> 1158.0328 | E23: =DATE(YEAR(Date)+3,MONTH(Date),DAY(Date)) -> 47151 | J23: Income Statement
B24: Number of coupon payments | C24: 2 | J24: For the Year Ended
B25: Cash received during year | C25: =C23*C24 -> 2316.0656 | E25: Revenues | J25: =DATE(YEAR(Date)+3,MONTH(Date),DAY(Date)) -> 47151
E26: Interest income | F26: =$C$32 -> 2448.6085
J27: Interest income | K27: =$C$32 -> 2448.6085
A28: Question 11: By how much did the value of the bonds change over the year? | E28: Expenses | F28: 0 | J28: Holding gain (loss) on U.S. Govt 30 Year Bonds | K28: =ROUND($K$10-$C$33,2) -> 0
E29: Net Income | F29: =SUM(F26:F28) -> 2448.6085 | J29: Net Income (Loss) | K29: =SUM(K27:K28) -> 2448.6085
B30: Value at the beginning | C30: =C5 -> 50246.699
B31: Coupon payments | C31: =-C25 -> -2316.0656 | E31: 165 Whitney Associates LLC
B32: Interest earned | C32: =C15 -> 2448.6085 | E32: Statement of Changes in Members' Equity
B33: Value of bond at end of year | C33: =SUM(C30:C32) -> 50379.242 | E33: For the Year Ended | J33: 165 Whitney Associates LLC
E34: =DATE(YEAR(Date)+3,MONTH(Date),DAY(Date)) -> 47151 | J34: Cash Flow Statement
B35: Change | C35: =C33-C30 -> 132.54293 | J35: For the Year Ended
F36: Contributed | G36: Earned and Retained | H36: Total | J36: =DATE(YEAR(Date)+3,MONTH(Date),DAY(Date)) -> 47151
E37: ="Balance on "&TEXT(DATE(YEAR(Date)+2,MONTH(Date),DAY(Date)),"mmmm dd, yyyy") -> Balance on February 02, 2028 | F37: ='2 Years Later'!$F$40 -> 50000 | G37: =$G$17 -> 4878.8301 | H37: =SUM(F37:G37) -> 54878.83
E38: Issued equity to members | F38: 0 | H38: =SUM(F38:G38) -> 0 | J38: Coupon payments | K38: =2*$C$23 -> 2316.0656
E39: Net income | G39: =F29 -> 2448.6085 | H39: =SUM(F39:G39) -> 2448.6085 | J39: Cash at the beginning of the period | K39: =L9 -> 4632.1312
E40: ="Balance on "&TEXT(DATE(YEAR(Date)+3,MONTH(Date),DAY(Date)),"mmmm dd, yyyy") -> Balance on February 02, 2029 | F40: =SUM(F37:F39) -> 50000 | G40: =SUM(G37:G39) -> 7327.4386 | H40: =SUM(H37:H39) -> 57327.439 | J40: Cash at the end of the period | K40: =SUM(K38:K39) -> 6948.1968
E43: 165 Whitney Associates LLC
E44: Cash Flow Statement (Direct method) | J44: 165 Whitney Associates LLC
E45: For the Year Ended | J45: Reconciliation of Net Income and Cash Flow from Operations
E46: =DATE(YEAR(Date)+3,MONTH(Date),DAY(Date)) -> 47151 | J46: For the Year Ended
J47: =DATE(YEAR(Date)+2,MONTH(Date),DAY(Date)) -> 46785
E48: Operations
E49: Coupon payments | F49: =2*$C$23 -> 2316.0656 | J49: Net Income | K49: =K29 -> 2448.6085
J50: Bond discount amortization | K50: =-$C$35 -> -132.54293
E51: Investing | J51: Holding (Gain) Loss on U.S. Govt 30 year bonds | K51: =-ROUND($K$10-$C$33,2) -> 0
J52: Cash flow from operations | K52: =SUM(K49:K51) -> 2316.0656
E53: Financing
E56: Total cash flows | F56: =SUM(F49:F55) -> 2316.0656
E57: Cash at the beginning of the period | F57: =G9 -> 4632.1312
E58: Cash at the end of the period | F58: =SUM(F56:F57) -> 6948.1968
E60: 165 Whitney Associates LLC
E61: Reconciliation of Net Income and Cash Flow from Operations
E62: For the Year Ended
E63: =DATE(YEAR(Date)+2,MONTH(Date),DAY(Date)) -> 46785
E65: Net Income | F65: =F29 -> 2448.6085
E66: Bond discount amortization | F66: =-$C$35 -> -132.54293
E67: Cash flow from operations | F67: =F65+F66 -> 2316.0656

Sheet Values thru time @Constant Rate
A1: Face Value | B1: =Face_Value -> 57901.64
A2: Term | B2: =Term -> 30 | C2: years | E2: Present value of cash flow at time
A3: Coupons | B3: =CouponRate -> 0.04 | C3: semi annual | E3: 0 | F3: 1 | G3: 2 | H3: 3 | I3: 4 | J3: 5 | K3: 6 | L3: 7 | M3: 8 | N3: 9 | O3: 10 | P3: 11 | Q3: 12 | R3: 13 | S3: 14 | T3: 15 | U3: 16 | V3: 17 | W3: 18 | X3: 19 | Y3: 20 | Z3: 21 | AA3: 22 | AB3: 23 | AC3: 24 | AD3: 25 | AE3: 26 | AF3: 27 | AG3: 28 | AH3: 29 | AI3: 30
A4: Yield | B4: =InterestRate -> 0.0487 | E4: =SUM(E8:E67) -> 50000.002 | F4: =SUM(F8:F67) -> 50120.384 | G4: =SUM(G8:G67) -> 50246.701 | H4: =SUM(H8:H67) -> 50379.244 | I4: =SUM(I8:I67) -> 50518.32 | J4: =SUM(J8:J67) -> 50664.252 | K4: =SUM(K8:K67) -> 50817.378 | L4: =SUM(L8:L67) -> 50978.051 | ... AI4: =SUM(AI8:AI67) -> 57901.64
A6: Time (years) | B6: Coupon | C6: Face | D6: Total Cash Flow
A7: 0
A8: 0.5 | B8: =$B$1*$B$3/2 -> 1158.0328 | D8: =B8+C8 -> 1158.0328 | E8: =(D8)/(1+$B$4/2)^(2*A8) -> 1130.505
A9: 1 | B9: =$B$1*$B$3/2 -> 1158.0328 | D9: =B9+C9 -> 1158.0328 | E9: =(D9)/(1+$B$4/2)^(2*A9) -> 1103.6316
A10: 1.5 | B10: =$B$1*$B$3/2 -> 1158.0328 | D10: =B10+C10 -> 1158.0328 | E10: =(D10)/(1+$B$4/2)^(2*A10) -> 1077.397 | F10: =($D10)/((1+$B$4/2)^(2*($A10-F$3))) -> 1130.505
A11: 2 | B11: =$B$1*$B$3/2 -> 1158.0328 | D11: =B11+C11 -> 1158.0328 | E11: =(D11)/(1+$B$4/2)^(2*A11) -> 1051.786 | F11: =($D11)/((1+$B$4/2)^(2*($A11-F$3))) -> 1103.6316
A12: 2.5 | B12: =$B$1*$B$3/2 -> 1158.0328 | D12: =B12+C12 -> 1158.0328 | E12: =(D12)/(1+$B$4/2)^(2*A12) -> 1026.7838 | F12: =($D12)/((1+$B$4/2)^(2*($A12-F$3))) -> 1077.397 | G12: =($D12)/((1+$B$4/2)^(2*($A12-G$3))) -> 1130.505
A13: 3 | B13: =$B$1*$B$3/2 -> 1158.0328 | D13: =B13+C13 -> 1158.0328 | E13: =(D13)/(1+$B$4/2)^(2*A13) -> 1002.3759 | F13: =($D13)/((1+$B$4/2)^(2*($A13-F$3))) -> 1051.786 | G13: =($D13)/((1+$B$4/2)^(2*($A13-G$3))) -> 1103.6316
A14: 3.5 | B14: =$B$1*$B$3/2 -> 1158.0328 | D14: =B14+C14 -> 1158.0328 | E14: =(D14)/(1+$B$4/2)^(2*A14) -> 978.54828 | F14: =($D14)/((1+$B$4/2)^(2*($A14-F$3))) -> 1026.7838 | G14: =($D14)/((1+$B$4/2)^(2*($A14-G$3))) -> 1077.397 | H14: =($D14)/((1+$B$4/2)^(2*($A14-H$3))) -> 1130.505
A15: 4 | B15: =$B$1*$B$3/2 -> 1158.0328 | D15: =B15+C15 -> 1158.0328 | E15: =(D15)/(1+$B$4/2)^(2*A15) -> 955.28704 | F15: =($D15)/((1+$B$4/2)^(2*($A15-F$3))) -> 1002.3759 | G15: =($D15)/((1+$B$4/2)^(2*($A15-G$3))) -> 1051.786 | H15: =($D15)/((1+$B$4/2)^(2*($A15-H$3))) -> 1103.6316
A16: 4.5 | B16: =$B$1*$B$3/2 -> 1158.0328 | D16: =B16+C16 -> 1158.0328 | E16: =(D16)/(1+$B$4/2)^(2*A16) -> 932.57875 | F16: =($D16)/((1+$B$4/2)^(2*($A16-F$3))) -> 978.54828 | G16: =($D16)/((1+$B$4/2)^(2*($A16-G$3))) -> 1026.7838 | H16: =($D16)/((1+$B$4/2)^(2*($A16-H$3))) -> 1077.397 | I16: =($D16)/((1+$B$4/2)^(2*($A16-I$3))) -> 1130.505
A17: 5 | B17: =$B$1*$B$3/2 -> 1158.0328 | D17: =B17+C17 -> 1158.0328 | E17: =(D17)/(1+$B$4/2)^(2*A17) -> 910.41026 | F17: =($D17)/((1+$B$4/2)^(2*($A17-F$3))) -> 955.28704 | G17: =($D17)/((1+$B$4/2)^(2*($A17-G$3))) -> 1002.3759 | H17: =($D17)/((1+$B$4/2)^(2*($A17-H$3))) -> 1051.786 | I17: =($D17)/((1+$B$4/2)^(2*($A17-I$3))) -> 1103.6316
A18: 5.5 | B18: =$B$1*$B$3/2 -> 1158.0328 | D18: =B18+C18 -> 1158.0328 | E18: =(D18)/(1+$B$4/2)^(2*A18) -> 888.76874 | F18: =($D18)/((1+$B$4/2)^(2*($A18-F$3))) -> 932.57875 | G18: =($D18)/((1+$B$4/2)^(2*($A18-G$3))) -> 978.54828 | H18: =($D18)/((1+$B$4/2)^(2*($A18-H$3))) -> 1026.7838 | I18: =($D18)/((1+$B$4/2)^(2*($A18-I$3))) -> 1077.397 | J18: =($D18)/((1+$B$4/2)^(2*($A18-J$3))) -> 1130.505
A19: 6 | B19: =$B$1*$B$3/2 -> 1158.0328 | D19: =B19+C19 -> 1158.0328 | E19: =(D19)/(1+$B$4/2)^(2*A19) -> 867.64167 | F19: =($D19)/((1+$B$4/2)^(2*($A19-F$3))) -> 910.41026 | G19: =($D19)/((1+$B$4/2)^(2*($A19-G$3))) -> 955.28704 | H19: =($D19)/((1+$B$4/2)^(2*($A19-H$3))) -> 1002.3759 | I19: =($D19)/((1+$B$4/2)^(2*($A19-I$3))) -> 1051.786 | J19: =($D19)/((1+$B$4/2)^(2*($A19-J$3))) -> 1103.6316
A20: 6.5 | B20: =$B$1*$B$3/2 -> 1158.0328 | D20: =B20+C20 -> 1158.0328 | E20: =(D20)/(1+$B$4/2)^(2*A20) -> 847.01681 | F20: =($D20)/((1+$B$4/2)^(2*($A20-F$3))) -> 888.76874 | G20: =($D20)/((1+$B$4/2)^(2*($A20-G$3))) -> 932.57875 | H20: =($D20)/((1+$B$4/2)^(2*($A20-H$3))) -> 978.54828 | I20: =($D20)/((1+$B$4/2)^(2*($A20-I$3))) -> 1026.7838 | J20: =($D20)/((1+$B$4/2)^(2*($A20-J$3))) -> 1077.397 | K20: =($D20)/((1+$B$4/2)^(2*($A20-K$3))) -> 1130.505
A21: 7 | B21: =$B$1*$B$3/2 -> 1158.0328 | D21: =B21+C21 -> 1158.0328 | E21: =(D21)/(1+$B$4/2)^(2*A21) -> 826.88222 | F21: =($D21)/((1+$B$4/2)^(2*($A21-F$3))) -> 867.64167 | G21: =($D21)/((1+$B$4/2)^(2*($A21-G$3))) -> 910.41026 | H21: =($D21)/((1+$B$4/2)^(2*($A21-H$3))) -> 955.28704 | I21: =($D21)/((1+$B$4/2)^(2*($A21-I$3))) -> 1002.3759 | J21: =($D21)/((1+$B$4/2)^(2*($A21-J$3))) -> 1051.786 | K21: =($D21)/((1+$B$4/2)^(2*($A21-K$3))) -> 1103.6316
A22: 7.5 | B22: =$B$1*$B$3/2 -> 1158.0328 | D22: =B22+C22 -> 1158.0328 | E22: =(D22)/(1+$B$4/2)^(2*A22) -> 807.22626 | F22: =($D22)/((1+$B$4/2)^(2*($A22-F$3))) -> 847.01681 | G22: =($D22)/((1+$B$4/2)^(2*($A22-G$3))) -> 888.76874 | H22: =($D22)/((1+$B$4/2)^(2*($A22-H$3))) -> 932.57875 | I22: =($D22)/((1+$B$4/2)^(2*($A22-I$3))) -> 978.54828 | J22: =($D22)/((1+$B$4/2)^(2*($A22-J$3))) -> 1026.7838 | K22: =($D22)/((1+$B$4/2)^(2*($A22-K$3))) -> 1077.397 | L22: =($D22)/((1+$B$4/2)^(2*($A22-L$3))) -> 1130.505
A23: 8 | B23: =$B$1*$B$3/2 -> 1158.0328 | D23: =B23+C23 -> 1158.0328 | E23: =(D23)/(1+$B$4/2)^(2*A23) -> 788.03755 | F23: =($D23)/((1+$B$4/2)^(2*($A23-F$3))) -> 826.88222 | G23: =($D23)/((1+$B$4/2)^(2*($A23-G$3))) -> 867.64167 | H23: =($D23)/((1+$B$4/2)^(2*($A23-H$3))) -> 910.41026 | I23: =($D23)/((1+$B$4/2)^(2*($A23-I$3))) -> 955.28704 | J23: =($D23)/((1+$B$4/2)^(2*($A23-J$3))) -> 1002.3759 | K23: =($D23)/((1+$B$4/2)^(2*($A23-K$3))) -> 1051.786 | L23: =($D23)/((1+$B$4/2)^(2*($A23-L$3))) -> 1103.6316
A24: 8.5 | B24: =$B$1*$B$3/2 -> 1158.0328 | D24: =B24+C24 -> 1158.0328 | E24: =(D24)/(1+$B$4/2)^(2*A24) -> 769.30497 | F24: =($D24)/((1+$B$4/2)^(2*($A24-F$3))) -> 807.22626 | G24: =($D24)/((1+$B$4/2)^(2*($A24-G$3))) -> 847.01681 | H24: =($D24)/((1+$B$4/2)^(2*($A24-H$3))) -> 888.76874 | I24: =($D24)/((1+$B$4/2)^(2*($A24-I$3))) -> 932.57875 | J24: =($D24)/((1+$B$4/2)^(2*($A24-J$3))) -> 978.54828 | K24: =($D24)/((1+$B$4/2)^(2*($A24-K$3))) -> 1026.7838 | L24: =($D24)/((1+$B$4/2)^(2*($A24-L$3))) -> 1077.397 | M24: =($D24)/((1+$B$4/2)^(2*($A24-M$3))) -> 1130.505
A25: 9 | B25: =$B$1*$B$3/2 -> 1158.0328 | D25: =B25+C25 -> 1158.0328 | E25: =(D25)/(1+$B$4/2)^(2*A25) -> 751.01769 | F25: =($D25)/((1+$B$4/2)^(2*($A25-F$3))) -> 788.03755 | G25: =($D25)/((1+$B$4/2)^(2*($A25-G$3))) -> 826.88222 | H25: =($D25)/((1+$B$4/2)^(2*($A25-H$3))) -> 867.64167 | I25: =($D25)/((1+$B$4/2)^(2*($A25-I$3))) -> 910.41026 | J25: =($D25)/((1+$B$4/2)^(2*($A25-J$3))) -> 955.28704 | K25: =($D25)/((1+$B$4/2)^(2*($A25-K$3))) -> 1002.3759 | L25: =($D25)/((1+$B$4/2)^(2*($A25-L$3))) -> 1051.786 | M25: =($D25)/((1+$B$4/2)^(2*($A25-M$3))) -> 1103.6316
A26: 9.5 | B26: =$B$1*$B$3/2 -> 1158.0328 | D26: =B26+C26 -> 1158.0328 | E26: =(D26)/(1+$B$4/2)^(2*A26) -> 733.16512 | F26: =($D26)/((1+$B$4/2)^(2*($A26-F$3))) -> 769.30497 | G26: =($D26)/((1+$B$4/2)^(2*($A26-G$3))) -> 807.22626 | H26: =($D26)/((1+$B$4/2)^(2*($A26-H$3))) -> 847.01681 | I26: =($D26)/((1+$B$4/2)^(2*($A26-I$3))) -> 888.76874 | J26: =($D26)/((1+$B$4/2)^(2*($A26-J$3))) -> 932.57875 | K26: =($D26)/((1+$B$4/2)^(2*($A26-K$3))) -> 978.54828 | L26: =($D26)/((1+$B$4/2)^(2*($A26-L$3))) -> 1026.7838 | M26: =($D26)/((1+$B$4/2)^(2*($A26-M$3))) -> 1077.397 | N26: =($D26)/((1+$B$4/2)^(2*($A26-N$3))) -> 1130.505
A27: 10 | B27: =$B$1*$B$3/2 -> 1158.0328 | D27: =B27+C27 -> 1158.0328 | E27: =(D27)/(1+$B$4/2)^(2*A27) -> 715.73693 | F27: =($D27)/((1+$B$4/2)^(2*($A27-F$3))) -> 751.01769 | G27: =($D27)/((1+$B$4/2)^(2*($A27-G$3))) -> 788.03755 | H27: =($D27)/((1+$B$4/2)^(2*($A27-H$3))) -> 826.88222 | I27: =($D27)/((1+$B$4/2)^(2*($A27-I$3))) -> 867.64167 | J27: =($D27)/((1+$B$4/2)^(2*($A27-J$3))) -> 910.41026 | K27: =($D27)/((1+$B$4/2)^(2*($A27-K$3))) -> 955.28704 | L27: =($D27)/((1+$B$4/2)^(2*($A27-L$3))) -> 1002.3759 | M27: =($D27)/((1+$B$4/2)^(2*($A27-M$3))) -> 1051.786 | N27: =($D27)/((1+$B$4/2)^(2*($A27-N$3))) -> 1103.6316
A28: 10.5 | B28: =$B$1*$B$3/2 -> 1158.0328 | D28: =B28+C28 -> 1158.0328 | E28: =(D28)/(1+$B$4/2)^(2*A28) -> 698.72302 | F28: =($D28)/((1+$B$4/2)^(2*($A28-F$3))) -> 733.16512 | G28: =($D28)/((1+$B$4/2)^(2*($A28-G$3))) -> 769.30497 | H28: =($D28)/((1+$B$4/2)^(2*($A28-H$3))) -> 807.22626 | I28: =($D28)/((1+$B$4/2)^(2*($A28-I$3))) -> 847.01681 | J28: =($D28)/((1+$B$4/2)^(2*($A28-J$3))) -> 888.76874 | K28: =($D28)/((1+$B$4/2)^(2*($A28-K$3))) -> 932.57875 | L28: =($D28)/((1+$B$4/2)^(2*($A28-L$3))) -> 978.54828 | M28: =($D28)/((1+$B$4/2)^(2*($A28-M$3))) -> 1026.7838 | ... O28: =($D28)/((1+$B$4/2)^(2*($A28-O$3))) -> 1130.505
A29: 11 | B29: =$B$1*$B$3/2 -> 1158.0328 | D29: =B29+C29 -> 1158.0328 | E29: =(D29)/(1+$B$4/2)^(2*A29) -> 682.11356 | F29: =($D29)/((1+$B$4/2)^(2*($A29-F$3))) -> 715.73693 | G29: =($D29)/((1+$B$4/2)^(2*($A29-G$3))) -> 751.01769 | H29: =($D29)/((1+$B$4/2)^(2*($A29-H$3))) -> 788.03755 | I29: =($D29)/((1+$B$4/2)^(2*($A29-I$3))) -> 826.88222 | J29: =($D29)/((1+$B$4/2)^(2*($A29-J$3))) -> 867.64167 | K29: =($D29)/((1+$B$4/2)^(2*($A29-K$3))) -> 910.41026 | L29: =($D29)/((1+$B$4/2)^(2*($A29-L$3))) -> 955.28704 | M29: =($D29)/((1+$B$4/2)^(2*($A29-M$3))) -> 1002.3759 | ... O29: =($D29)/((1+$B$4/2)^(2*($A29-O$3))) -> 1103.6316
A30: 11.5 | B30: =$B$1*$B$3/2 -> 1158.0328 | D30: =B30+C30 -> 1158.0328 | E30: =(D30)/(1+$B$4/2)^(2*A30) -> 665.89892 | F30: =($D30)/((1+$B$4/2)^(2*($A30-F$3))) -> 698.72302 | G30: =($D30)/((1+$B$4/2)^(2*($A30-G$3))) -> 733.16512 | H30: =($D30)/((1+$B$4/2)^(2*($A30-H$3))) -> 769.30497 | I30: =($D30)/((1+$B$4/2)^(2*($A30-I$3))) -> 807.22626 | J30: =($D30)/((1+$B$4/2)^(2*($A30-J$3))) -> 847.01681 | K30: =($D30)/((1+$B$4/2)^(2*($A30-K$3))) -> 888.76874 | L30: =($D30)/((1+$B$4/2)^(2*($A30-L$3))) -> 932.57875 | M30: =($D30)/((1+$B$4/2)^(2*($A30-M$3))) -> 978.54828 | ... P30: =($D30)/((1+$B$4/2)^(2*($A30-P$3))) -> 1130.505
A31: 12 | B31: =$B$1*$B$3/2 -> 1158.0328 | D31: =B31+C31 -> 1158.0328 | E31: =(D31)/(1+$B$4/2)^(2*A31) -> 650.06972 | F31: =($D31)/((1+$B$4/2)^(2*($A31-F$3))) -> 682.11356 | G31: =($D31)/((1+$B$4/2)^(2*($A31-G$3))) -> 715.73693 | H31: =($D31)/((1+$B$4/2)^(2*($A31-H$3))) -> 751.01769 | I31: =($D31)/((1+$B$4/2)^(2*($A31-I$3))) -> 788.03755 | J31: =($D31)/((1+$B$4/2)^(2*($A31-J$3))) -> 826.88222 | K31: =($D31)/((1+$B$4/2)^(2*($A31-K$3))) -> 867.64167 | L31: =($D31)/((1+$B$4/2)^(2*($A31-L$3))) -> 910.41026 | M31: =($D31)/((1+$B$4/2)^(2*($A31-M$3))) -> 955.28704 | ... P31: =($D31)/((1+$B$4/2)^(2*($A31-P$3))) -> 1103.6316
A32: 12.5 | B32: =$B$1*$B$3/2 -> 1158.0328 | D32: =B32+C32 -> 1158.0328 | E32: =(D32)/(1+$B$4/2)^(2*A32) -> 634.6168 | F32: =($D32)/((1+$B$4/2)^(2*($A32-F$3))) -> 665.89892 | G32: =($D32)/((1+$B$4/2)^(2*($A32-G$3))) -> 698.72302 | H32: =($D32)/((1+$B$4/2)^(2*($A32-H$3))) -> 733.16512 | I32: =($D32)/((1+$B$4/2)^(2*($A32-I$3))) -> 769.30497 | J32: =($D32)/((1+$B$4/2)^(2*($A32-J$3))) -> 807.22626 | K32: =($D32)/((1+$B$4/2)^(2*($A32-K$3))) -> 847.01681 | L32: =($D32)/((1+$B$4/2)^(2*($A32-L$3))) -> 888.76874 | M32: =($D32)/((1+$B$4/2)^(2*($A32-M$3))) -> 932.57875 | ... Q32: =($D32)/((1+$B$4/2)^(2*($A32-Q$3))) -> 1130.505
A33: 13 | B33: =$B$1*$B$3/2 -> 1158.0328 | D33: =B33+C33 -> 1158.0328 | E33: =(D33)/(1+$B$4/2)^(2*A33) -> 619.53122 | F33: =($D33)/((1+$B$4/2)^(2*($A33-F$3))) -> 650.06972 | G33: =($D33)/((1+$B$4/2)^(2*($A33-G$3))) -> 682.11356 | H33: =($D33)/((1+$B$4/2)^(2*($A33-H$3))) -> 715.73693 | I33: =($D33)/((1+$B$4/2)^(2*($A33-I$3))) -> 751.01769 | J33: =($D33)/((1+$B$4/2)^(2*($A33-J$3))) -> 788.03755 | K33: =($D33)/((1+$B$4/2)^(2*($A33-K$3))) -> 826.88222 | L33: =($D33)/((1+$B$4/2)^(2*($A33-L$3))) -> 867.64167 | M33: =($D33)/((1+$B$4/2)^(2*($A33-M$3))) -> 910.41026 | ... Q33: =($D33)/((1+$B$4/2)^(2*($A33-Q$3))) -> 1103.6316
A34: 13.5 | B34: =$B$1*$B$3/2 -> 1158.0328 | D34: =B34+C34 -> 1158.0328 | E34: =(D34)/(1+$B$4/2)^(2*A34) -> 604.80423 | F34: =($D34)/((1+$B$4/2)^(2*($A34-F$3))) -> 634.6168 | G34: =($D34)/((1+$B$4/2)^(2*($A34-G$3))) -> 665.89892 | H34: =($D34)/((1+$B$4/2)^(2*($A34-H$3))) -> 698.72302 | I34: =($D34)/((1+$B$4/2)^(2*($A34-I$3))) -> 733.16512 | J34: =($D34)/((1+$B$4/2)^(2*($A34-J$3))) -> 769.30497 | K34: =($D34)/((1+$B$4/2)^(2*($A34-K$3))) -> 807.22626 | L34: =($D34)/((1+$B$4/2)^(2*($A34-L$3))) -> 847.01681 | M34: =($D34)/((1+$B$4/2)^(2*($A34-M$3))) -> 888.76874 | ... R34: =($D34)/((1+$B$4/2)^(2*($A34-R$3))) -> 1130.505
A35: 14 | B35: =$B$1*$B$3/2 -> 1158.0328 | D35: =B35+C35 -> 1158.0328 | E35: =(D35)/(1+$B$4/2)^(2*A35) -> 590.42733 | F35: =($D35)/((1+$B$4/2)^(2*($A35-F$3))) -> 619.53122 | G35: =($D35)/((1+$B$4/2)^(2*($A35-G$3))) -> 650.06972 | H35: =($D35)/((1+$B$4/2)^(2*($A35-H$3))) -> 682.11356 | I35: =($D35)/((1+$B$4/2)^(2*($A35-I$3))) -> 715.73693 | J35: =($D35)/((1+$B$4/2)^(2*($A35-J$3))) -> 751.01769 | K35: =($D35)/((1+$B$4/2)^(2*($A35-K$3))) -> 788.03755 | L35: =($D35)/((1+$B$4/2)^(2*($A35-L$3))) -> 826.88222 | M35: =($D35)/((1+$B$4/2)^(2*($A35-M$3))) -> 867.64167 | ... R35: =($D35)/((1+$B$4/2)^(2*($A35-R$3))) -> 1103.6316
A36: 14.5 | B36: =$B$1*$B$3/2 -> 1158.0328 | D36: =B36+C36 -> 1158.0328 | E36: =(D36)/(1+$B$4/2)^(2*A36) -> 576.39218 | F36: =($D36)/((1+$B$4/2)^(2*($A36-F$3))) -> 604.80423 | G36: =($D36)/((1+$B$4/2)^(2*($A36-G$3))) -> 634.6168 | H36: =($D36)/((1+$B$4/2)^(2*($A36-H$3))) -> 665.89892 | I36: =($D36)/((1+$B$4/2)^(2*($A36-I$3))) -> 698.72302 | J36: =($D36)/((1+$B$4/2)^(2*($A36-J$3))) -> 733.16512 | K36: =($D36)/((1+$B$4/2)^(2*($A36-K$3))) -> 769.30497 | L36: =($D36)/((1+$B$4/2)^(2*($A36-L$3))) -> 807.22626 | M36: =($D36)/((1+$B$4/2)^(2*($A36-M$3))) -> 847.01681 | ... S36: =($D36)/((1+$B$4/2)^(2*($A36-S$3))) -> 1130.505
A37: 15 | B37: =$B$1*$B$3/2 -> 1158.0328 | D37: =B37+C37 -> 1158.0328 | E37: =(D37)/(1+$B$4/2)^(2*A37) -> 562.69066 | F37: =($D37)/((1+$B$4/2)^(2*($A37-F$3))) -> 590.42733 | G37: =($D37)/((1+$B$4/2)^(2*($A37-G$3))) -> 619.53122 | H37: =($D37)/((1+$B$4/2)^(2*($A37-H$3))) -> 650.06972 | I37: =($D37)/((1+$B$4/2)^(2*($A37-I$3))) -> 682.11356 | J37: =($D37)/((1+$B$4/2)^(2*($A37-J$3))) -> 715.73693 | K37: =($D37)/((1+$B$4/2)^(2*($A37-K$3))) -> 751.01769 | L37: =($D37)/((1+$B$4/2)^(2*($A37-L$3))) -> 788.03755 | M37: =($D37)/((1+$B$4/2)^(2*($A37-M$3))) -> 826.88222 | ... S37: =($D37)/((1+$B$4/2)^(2*($A37-S$3))) -> 1103.6316
A38: 15.5 | B38: =$B$1*$B$3/2 -> 1158.0328 | D38: =B38+C38 -> 1158.0328 | E38: =(D38)/(1+$B$4/2)^(2*A38) -> 549.31484 | F38: =($D38)/((1+$B$4/2)^(2*($A38-F$3))) -> 576.39218 | G38: =($D38)/((1+$B$4/2)^(2*($A38-G$3))) -> 604.80423 | H38: =($D38)/((1+$B$4/2)^(2*($A38-H$3))) -> 634.6168 | I38: =($D38)/((1+$B$4/2)^(2*($A38-I$3))) -> 665.89892 | J38: =($D38)/((1+$B$4/2)^(2*($A38-J$3))) -> 698.72302 | K38: =($D38)/((1+$B$4/2)^(2*($A38-K$3))) -> 733.16512 | L38: =($D38)/((1+$B$4/2)^(2*($A38-L$3))) -> 769.30497 | M38: =($D38)/((1+$B$4/2)^(2*($A38-M$3))) -> 807.22626 | ... T38: =($D38)/((1+$B$4/2)^(2*($A38-T$3))) -> 1130.505
A39: 16 | B39: =$B$1*$B$3/2 -> 1158.0328 | D39: =B39+C39 -> 1158.0328 | E39: =(D39)/(1+$B$4/2)^(2*A39) -> 536.25699 | F39: =($D39)/((1+$B$4/2)^(2*($A39-F$3))) -> 562.69066 | G39: =($D39)/((1+$B$4/2)^(2*($A39-G$3))) -> 590.42733 | H39: =($D39)/((1+$B$4/2)^(2*($A39-H$3))) -> 619.53122 | I39: =($D39)/((1+$B$4/2)^(2*($A39-I$3))) -> 650.06972 | J39: =($D39)/((1+$B$4/2)^(2*($A39-J$3))) -> 682.11356 | K39: =($D39)/((1+$B$4/2)^(2*($A39-K$3))) -> 715.73693 | L39: =($D39)/((1+$B$4/2)^(2*($A39-L$3))) -> 751.01769 | M39: =($D39)/((1+$B$4/2)^(2*($A39-M$3))) -> 788.03755 | ... T39: =($D39)/((1+$B$4/2)^(2*($A39-T$3))) -> 1103.6316
A40: 16.5 | B40: =$B$1*$B$3/2 -> 1158.0328 | D40: =B40+C40 -> 1158.0328 | E40: =(D40)/(1+$B$4/2)^(2*A40) -> 523.50953 | F40: =($D40)/((1+$B$4/2)^(2*($A40-F$3))) -> 549.31484 | G40: =($D40)/((1+$B$4/2)^(2*($A40-G$3))) -> 576.39218 | H40: =($D40)/((1+$B$4/2)^(2*($A40-H$3))) -> 604.80423 | I40: =($D40)/((1+$B$4/2)^(2*($A40-I$3))) -> 634.6168 | J40: =($D40)/((1+$B$4/2)^(2*($A40-J$3))) -> 665.89892 | K40: =($D40)/((1+$B$4/2)^(2*($A40-K$3))) -> 698.72302 | L40: =($D40)/((1+$B$4/2)^(2*($A40-L$3))) -> 733.16512 | M40: =($D40)/((1+$B$4/2)^(2*($A40-M$3))) -> 769.30497 | ... U40: =($D40)/((1+$B$4/2)^(2*($A40-U$3))) -> 1130.505
A41: 17 | B41: =$B$1*$B$3/2 -> 1158.0328 | D41: =B41+C41 -> 1158.0328 | E41: =(D41)/(1+$B$4/2)^(2*A41) -> 511.06509 | F41: =($D41)/((1+$B$4/2)^(2*($A41-F$3))) -> 536.25699 | G41: =($D41)/((1+$B$4/2)^(2*($A41-G$3))) -> 562.69066 | H41: =($D41)/((1+$B$4/2)^(2*($A41-H$3))) -> 590.42733 | I41: =($D41)/((1+$B$4/2)^(2*($A41-I$3))) -> 619.53122 | J41: =($D41)/((1+$B$4/2)^(2*($A41-J$3))) -> 650.06972 | K41: =($D41)/((1+$B$4/2)^(2*($A41-K$3))) -> 682.11356 | L41: =($D41)/((1+$B$4/2)^(2*($A41-L$3))) -> 715.73693 | M41: =($D41)/((1+$B$4/2)^(2*($A41-M$3))) -> 751.01769 | ... U41: =($D41)/((1+$B$4/2)^(2*($A41-U$3))) -> 1103.6316
A42: 17.5 | B42: =$B$1*$B$3/2 -> 1158.0328 | D42: =B42+C42 -> 1158.0328 | E42: =(D42)/(1+$B$4/2)^(2*A42) -> 498.91648 | F42: =($D42)/((1+$B$4/2)^(2*($A42-F$3))) -> 523.50953 | G42: =($D42)/((1+$B$4/2)^(2*($A42-G$3))) -> 549.31484 | H42: =($D42)/((1+$B$4/2)^(2*($A42-H$3))) -> 576.39218 | I42: =($D42)/((1+$B$4/2)^(2*($A42-I$3))) -> 604.80423 | J42: =($D42)/((1+$B$4/2)^(2*($A42-J$3))) -> 634.6168 | K42: =($D42)/((1+$B$4/2)^(2*($A42-K$3))) -> 665.89892 | L42: =($D42)/((1+$B$4/2)^(2*($A42-L$3))) -> 698.72302 | M42: =($D42)/((1+$B$4/2)^(2*($A42-M$3))) -> 733.16512 | ... V42: =($D42)/((1+$B$4/2)^(2*($A42-V$3))) -> 1130.505
A43: 18 | B43: =$B$1*$B$3/2 -> 1158.0328 | D43: =B43+C43 -> 1158.0328 | E43: =(D43)/(1+$B$4/2)^(2*A43) -> 487.05665 | F43: =($D43)/((1+$B$4/2)^(2*($A43-F$3))) -> 511.06509 | G43: =($D43)/((1+$B$4/2)^(2*($A43-G$3))) -> 536.25699 | H43: =($D43)/((1+$B$4/2)^(2*($A43-H$3))) -> 562.69066 | I43: =($D43)/((1+$B$4/2)^(2*($A43-I$3))) -> 590.42733 | J43: =($D43)/((1+$B$4/2)^(2*($A43-J$3))) -> 619.53122 | K43: =($D43)/((1+$B$4/2)^(2*($A43-K$3))) -> 650.06972 | L43: =($D43)/((1+$B$4/2)^(2*($A43-L$3))) -> 682.11356 | M43: =($D43)/((1+$B$4/2)^(2*($A43-M$3))) -> 715.73693 | ... V43: =($D43)/((1+$B$4/2)^(2*($A43-V$3))) -> 1103.6316
A44: 18.5 | B44: =$B$1*$B$3/2 -> 1158.0328 | D44: =B44+C44 -> 1158.0328 | E44: =(D44)/(1+$B$4/2)^(2*A44) -> 475.47874 | F44: =($D44)/((1+$B$4/2)^(2*($A44-F$3))) -> 498.91648 | G44: =($D44)/((1+$B$4/2)^(2*($A44-G$3))) -> 523.50953 | H44: =($D44)/((1+$B$4/2)^(2*($A44-H$3))) -> 549.31484 | I44: =($D44)/((1+$B$4/2)^(2*($A44-I$3))) -> 576.39218 | J44: =($D44)/((1+$B$4/2)^(2*($A44-J$3))) -> 604.80423 | K44: =($D44)/((1+$B$4/2)^(2*($A44-K$3))) -> 634.6168 | L44: =($D44)/((1+$B$4/2)^(2*($A44-L$3))) -> 665.89892 | M44: =($D44)/((1+$B$4/2)^(2*($A44-M$3))) -> 698.72302 | ... W44: =($D44)/((1+$B$4/2)^(2*($A44-W$3))) -> 1130.505
A45: 19 | B45: =$B$1*$B$3/2 -> 1158.0328 | D45: =B45+C45 -> 1158.0328 | E45: =(D45)/(1+$B$4/2)^(2*A45) -> 464.17605 | F45: =($D45)/((1+$B$4/2)^(2*($A45-F$3))) -> 487.05665 | G45: =($D45)/((1+$B$4/2)^(2*($A45-G$3))) -> 511.06509 | H45: =($D45)/((1+$B$4/2)^(2*($A45-H$3))) -> 536.25699 | I45: =($D45)/((1+$B$4/2)^(2*($A45-I$3))) -> 562.69066 | J45: =($D45)/((1+$B$4/2)^(2*($A45-J$3))) -> 590.42733 | K45: =($D45)/((1+$B$4/2)^(2*($A45-K$3))) -> 619.53122 | L45: =($D45)/((1+$B$4/2)^(2*($A45-L$3))) -> 650.06972 | M45: =($D45)/((1+$B$4/2)^(2*($A45-M$3))) -> 682.11356 | ... W45: =($D45)/((1+$B$4/2)^(2*($A45-W$3))) -> 1103.6316
A46: 19.5 | B46: =$B$1*$B$3/2 -> 1158.0328 | D46: =B46+C46 -> 1158.0328 | E46: =(D46)/(1+$B$4/2)^(2*A46) -> 453.14205 | F46: =($D46)/((1+$B$4/2)^(2*($A46-F$3))) -> 475.47874 | G46: =($D46)/((1+$B$4/2)^(2*($A46-G$3))) -> 498.91648 | H46: =($D46)/((1+$B$4/2)^(2*($A46-H$3))) -> 523.50953 | I46: =($D46)/((1+$B$4/2)^(2*($A46-I$3))) -> 549.31484 | J46: =($D46)/((1+$B$4/2)^(2*($A46-J$3))) -> 576.39218 | K46: =($D46)/((1+$B$4/2)^(2*($A46-K$3))) -> 604.80423 | L46: =($D46)/((1+$B$4/2)^(2*($A46-L$3))) -> 634.6168 | M46: =($D46)/((1+$B$4/2)^(2*($A46-M$3))) -> 665.89892 | ... X46: =($D46)/((1+$B$4/2)^(2*($A46-X$3))) -> 1130.505
A47: 20 | B47: =$B$1*$B$3/2 -> 1158.0328 | D47: =B47+C47 -> 1158.0328 | E47: =(D47)/(1+$B$4/2)^(2*A47) -> 442.37033 | F47: =($D47)/((1+$B$4/2)^(2*($A47-F$3))) -> 464.17605 | G47: =($D47)/((1+$B$4/2)^(2*($A47-G$3))) -> 487.05665 | H47: =($D47)/((1+$B$4/2)^(2*($A47-H$3))) -> 511.06509 | I47: =($D47)/((1+$B$4/2)^(2*($A47-I$3))) -> 536.25699 | J47: =($D47)/((1+$B$4/2)^(2*($A47-J$3))) -> 562.69066 | K47: =($D47)/((1+$B$4/2)^(2*($A47-K$3))) -> 590.42733 | L47: =($D47)/((1+$B$4/2)^(2*($A47-L$3))) -> 619.53122 | M47: =($D47)/((1+$B$4/2)^(2*($A47-M$3))) -> 650.06972 | ... X47: =($D47)/((1+$B$4/2)^(2*($A47-X$3))) -> 1103.6316
A48: 20.5 | B48: =$B$1*$B$3/2 -> 1158.0328 | D48: =B48+C48 -> 1158.0328 | E48: =(D48)/(1+$B$4/2)^(2*A48) -> 431.85467 | F48: =($D48)/((1+$B$4/2)^(2*($A48-F$3))) -> 453.14205 | G48: =($D48)/((1+$B$4/2)^(2*($A48-G$3))) -> 475.47874 | H48: =($D48)/((1+$B$4/2)^(2*($A48-H$3))) -> 498.91648 | I48: =($D48)/((1+$B$4/2)^(2*($A48-I$3))) -> 523.50953 | J48: =($D48)/((1+$B$4/2)^(2*($A48-J$3))) -> 549.31484 | K48: =($D48)/((1+$B$4/2)^(2*($A48-K$3))) -> 576.39218 | L48: =($D48)/((1+$B$4/2)^(2*($A48-L$3))) -> 604.80423 | M48: =($D48)/((1+$B$4/2)^(2*($A48-M$3))) -> 634.6168 | ... Y48: =($D48)/((1+$B$4/2)^(2*($A48-Y$3))) -> 1130.505
A49: 21 | B49: =$B$1*$B$3/2 -> 1158.0328 | D49: =B49+C49 -> 1158.0328 | E49: =(D49)/(1+$B$4/2)^(2*A49) -> 421.58898 | F49: =($D49)/((1+$B$4/2)^(2*($A49-F$3))) -> 442.37033 | G49: =($D49)/((1+$B$4/2)^(2*($A49-G$3))) -> 464.17605 | H49: =($D49)/((1+$B$4/2)^(2*($A49-H$3))) -> 487.05665 | I49: =($D49)/((1+$B$4/2)^(2*($A49-I$3))) -> 511.06509 | J49: =($D49)/((1+$B$4/2)^(2*($A49-J$3))) -> 536.25699 | K49: =($D49)/((1+$B$4/2)^(2*($A49-K$3))) -> 562.69066 | L49: =($D49)/((1+$B$4/2)^(2*($A49-L$3))) -> 590.42733 | M49: =($D49)/((1+$B$4/2)^(2*($A49-M$3))) -> 619.53122 | ... Y49: =($D49)/((1+$B$4/2)^(2*($A49-Y$3))) -> 1103.6316
A50: 21.5 | B50: =$B$1*$B$3/2 -> 1158.0328 | D50: =B50+C50 -> 1158.0328 | E50: =(D50)/(1+$B$4/2)^(2*A50) -> 411.56731 | F50: =($D50)/((1+$B$4/2)^(2*($A50-F$3))) -> 431.85467 | G50: =($D50)/((1+$B$4/2)^(2*($A50-G$3))) -> 453.14205 | H50: =($D50)/((1+$B$4/2)^(2*($A50-H$3))) -> 475.47874 | I50: =($D50)/((1+$B$4/2)^(2*($A50-I$3))) -> 498.91648 | J50: =($D50)/((1+$B$4/2)^(2*($A50-J$3))) -> 523.50953 | K50: =($D50)/((1+$B$4/2)^(2*($A50-K$3))) -> 549.31484 | L50: =($D50)/((1+$B$4/2)^(2*($A50-L$3))) -> 576.39218 | M50: =($D50)/((1+$B$4/2)^(2*($A50-M$3))) -> 604.80423 | ... Z50: =($D50)/((1+$B$4/2)^(2*($A50-Z$3))) -> 1130.505
A51: 22 | B51: =$B$1*$B$3/2 -> 1158.0328 | D51: =B51+C51 -> 1158.0328 | E51: =(D51)/(1+$B$4/2)^(2*A51) -> 401.78387 | F51: =($D51)/((1+$B$4/2)^(2*($A51-F$3))) -> 421.58898 | G51: =($D51)/((1+$B$4/2)^(2*($A51-G$3))) -> 442.37033 | H51: =($D51)/((1+$B$4/2)^(2*($A51-H$3))) -> 464.17605 | I51: =($D51)/((1+$B$4/2)^(2*($A51-I$3))) -> 487.05665 | J51: =($D51)/((1+$B$4/2)^(2*($A51-J$3))) -> 511.06509 | K51: =($D51)/((1+$B$4/2)^(2*($A51-K$3))) -> 536.25699 | L51: =($D51)/((1+$B$4/2)^(2*($A51-L$3))) -> 562.69066 | M51: =($D51)/((1+$B$4/2)^(2*($A51-M$3))) -> 590.42733 | ... Z51: =($D51)/((1+$B$4/2)^(2*($A51-Z$3))) -> 1103.6316
A52: 22.5 | B52: =$B$1*$B$3/2 -> 1158.0328 | D52: =B52+C52 -> 1158.0328 | E52: =(D52)/(1+$B$4/2)^(2*A52) -> 392.233 | F52: =($D52)/((1+$B$4/2)^(2*($A52-F$3))) -> 411.56731 | G52: =($D52)/((1+$B$4/2)^(2*($A52-G$3))) -> 431.85467 | H52: =($D52)/((1+$B$4/2)^(2*($A52-H$3))) -> 453.14205 | I52: =($D52)/((1+$B$4/2)^(2*($A52-I$3))) -> 475.47874 | J52: =($D52)/((1+$B$4/2)^(2*($A52-J$3))) -> 498.91648 | K52: =($D52)/((1+$B$4/2)^(2*($A52-K$3))) -> 523.50953 | L52: =($D52)/((1+$B$4/2)^(2*($A52-L$3))) -> 549.31484 | M52: =($D52)/((1+$B$4/2)^(2*($A52-M$3))) -> 576.39218 | ... AA52: =($D52)/((1+$B$4/2)^(2*($A52-AA$3))) -> 1130.505
A53: 23 | B53: =$B$1*$B$3/2 -> 1158.0328 | D53: =B53+C53 -> 1158.0328 | E53: =(D53)/(1+$B$4/2)^(2*A53) -> 382.90916 | F53: =($D53)/((1+$B$4/2)^(2*($A53-F$3))) -> 401.78387 | G53: =($D53)/((1+$B$4/2)^(2*($A53-G$3))) -> 421.58898 | H53: =($D53)/((1+$B$4/2)^(2*($A53-H$3))) -> 442.37033 | I53: =($D53)/((1+$B$4/2)^(2*($A53-I$3))) -> 464.17605 | J53: =($D53)/((1+$B$4/2)^(2*($A53-J$3))) -> 487.05665 | K53: =($D53)/((1+$B$4/2)^(2*($A53-K$3))) -> 511.06509 | L53: =($D53)/((1+$B$4/2)^(2*($A53-L$3))) -> 536.25699 | M53: =($D53)/((1+$B$4/2)^(2*($A53-M$3))) -> 562.69066 | ... AA53: =($D53)/((1+$B$4/2)^(2*($A53-AA$3))) -> 1103.6316
A54: 23.5 | B54: =$B$1*$B$3/2 -> 1158.0328 | D54: =B54+C54 -> 1158.0328 | E54: =(D54)/(1+$B$4/2)^(2*A54) -> 373.80696 | F54: =($D54)/((1+$B$4/2)^(2*($A54-F$3))) -> 392.233 | G54: =($D54)/((1+$B$4/2)^(2*($A54-G$3))) -> 411.56731 | H54: =($D54)/((1+$B$4/2)^(2*($A54-H$3))) -> 431.85467 | I54: =($D54)/((1+$B$4/2)^(2*($A54-I$3))) -> 453.14205 | J54: =($D54)/((1+$B$4/2)^(2*($A54-J$3))) -> 475.47874 | K54: =($D54)/((1+$B$4/2)^(2*($A54-K$3))) -> 498.91648 | L54: =($D54)/((1+$B$4/2)^(2*($A54-L$3))) -> 523.50953 | M54: =($D54)/((1+$B$4/2)^(2*($A54-M$3))) -> 549.31484 | ... AB54: =($D54)/((1+$B$4/2)^(2*($A54-AB$3))) -> 1130.505
A55: 24 | B55: =$B$1*$B$3/2 -> 1158.0328 | D55: =B55+C55 -> 1158.0328 | E55: =(D55)/(1+$B$4/2)^(2*A55) -> 364.92113 | F55: =($D55)/((1+$B$4/2)^(2*($A55-F$3))) -> 382.90916 | G55: =($D55)/((1+$B$4/2)^(2*($A55-G$3))) -> 401.78387 | H55: =($D55)/((1+$B$4/2)^(2*($A55-H$3))) -> 421.58898 | I55: =($D55)/((1+$B$4/2)^(2*($A55-I$3))) -> 442.37033 | J55: =($D55)/((1+$B$4/2)^(2*($A55-J$3))) -> 464.17605 | K55: =($D55)/((1+$B$4/2)^(2*($A55-K$3))) -> 487.05665 | L55: =($D55)/((1+$B$4/2)^(2*($A55-L$3))) -> 511.06509 | M55: =($D55)/((1+$B$4/2)^(2*($A55-M$3))) -> 536.25699 | ... AB55: =($D55)/((1+$B$4/2)^(2*($A55-AB$3))) -> 1103.6316
A56: 24.5 | B56: =$B$1*$B$3/2 -> 1158.0328 | D56: =B56+C56 -> 1158.0328 | E56: =(D56)/(1+$B$4/2)^(2*A56) -> 356.24653 | F56: =($D56)/((1+$B$4/2)^(2*($A56-F$3))) -> 373.80696 | G56: =($D56)/((1+$B$4/2)^(2*($A56-G$3))) -> 392.233 | H56: =($D56)/((1+$B$4/2)^(2*($A56-H$3))) -> 411.56731 | I56: =($D56)/((1+$B$4/2)^(2*($A56-I$3))) -> 431.85467 | J56: =($D56)/((1+$B$4/2)^(2*($A56-J$3))) -> 453.14205 | K56: =($D56)/((1+$B$4/2)^(2*($A56-K$3))) -> 475.47874 | L56: =($D56)/((1+$B$4/2)^(2*($A56-L$3))) -> 498.91648 | M56: =($D56)/((1+$B$4/2)^(2*($A56-M$3))) -> 523.50953 | ... AC56: =($D56)/((1+$B$4/2)^(2*($A56-AC$3))) -> 1130.505
A57: 25 | B57: =$B$1*$B$3/2 -> 1158.0328 | D57: =B57+C57 -> 1158.0328 | E57: =(D57)/(1+$B$4/2)^(2*A57) -> 347.77813 | F57: =($D57)/((1+$B$4/2)^(2*($A57-F$3))) -> 364.92113 | G57: =($D57)/((1+$B$4/2)^(2*($A57-G$3))) -> 382.90916 | H57: =($D57)/((1+$B$4/2)^(2*($A57-H$3))) -> 401.78387 | I57: =($D57)/((1+$B$4/2)^(2*($A57-I$3))) -> 421.58898 | J57: =($D57)/((1+$B$4/2)^(2*($A57-J$3))) -> 442.37033 | K57: =($D57)/((1+$B$4/2)^(2*($A57-K$3))) -> 464.17605 | L57: =($D57)/((1+$B$4/2)^(2*($A57-L$3))) -> 487.05665 | M57: =($D57)/((1+$B$4/2)^(2*($A57-M$3))) -> 511.06509 | ... AC57: =($D57)/((1+$B$4/2)^(2*($A57-AC$3))) -> 1103.6316
A58: 25.5 | B58: =$B$1*$B$3/2 -> 1158.0328 | D58: =B58+C58 -> 1158.0328 | E58: =(D58)/(1+$B$4/2)^(2*A58) -> 339.51104 | F58: =($D58)/((1+$B$4/2)^(2*($A58-F$3))) -> 356.24653 | G58: =($D58)/((1+$B$4/2)^(2*($A58-G$3))) -> 373.80696 | H58: =($D58)/((1+$B$4/2)^(2*($A58-H$3))) -> 392.233 | I58: =($D58)/((1+$B$4/2)^(2*($A58-I$3))) -> 411.56731 | J58: =($D58)/((1+$B$4/2)^(2*($A58-J$3))) -> 431.85467 | K58: =($D58)/((1+$B$4/2)^(2*($A58-K$3))) -> 453.14205 | L58: =($D58)/((1+$B$4/2)^(2*($A58-L$3))) -> 475.47874 | M58: =($D58)/((1+$B$4/2)^(2*($A58-M$3))) -> 498.91648 | ... AD58: =($D58)/((1+$B$4/2)^(2*($A58-AD$3))) -> 1130.505
A59: 26 | B59: =$B$1*$B$3/2 -> 1158.0328 | D59: =B59+C59 -> 1158.0328 | E59: =(D59)/(1+$B$4/2)^(2*A59) -> 331.44046 | F59: =($D59)/((1+$B$4/2)^(2*($A59-F$3))) -> 347.77813 | G59: =($D59)/((1+$B$4/2)^(2*($A59-G$3))) -> 364.92113 | H59: =($D59)/((1+$B$4/2)^(2*($A59-H$3))) -> 382.90916 | I59: =($D59)/((1+$B$4/2)^(2*($A59-I$3))) -> 401.78387 | J59: =($D59)/((1+$B$4/2)^(2*($A59-J$3))) -> 421.58898 | K59: =($D59)/((1+$B$4/2)^(2*($A59-K$3))) -> 442.37033 | L59: =($D59)/((1+$B$4/2)^(2*($A59-L$3))) -> 464.17605 | M59: =($D59)/((1+$B$4/2)^(2*($A59-M$3))) -> 487.05665 | ... AD59: =($D59)/((1+$B$4/2)^(2*($A59-AD$3))) -> 1103.6316
A60: 26.5 | B60: =$B$1*$B$3/2 -> 1158.0328 | D60: =B60+C60 -> 1158.0328 | E60: =(D60)/(1+$B$4/2)^(2*A60) -> 323.56174 | F60: =($D60)/((1+$B$4/2)^(2*($A60-F$3))) -> 339.51104 | G60: =($D60)/((1+$B$4/2)^(2*($A60-G$3))) -> 356.24653 | H60: =($D60)/((1+$B$4/2)^(2*($A60-H$3))) -> 373.80696 | I60: =($D60)/((1+$B$4/2)^(2*($A60-I$3))) -> 392.233 | J60: =($D60)/((1+$B$4/2)^(2*($A60-J$3))) -> 411.56731 | K60: =($D60)/((1+$B$4/2)^(2*($A60-K$3))) -> 431.85467 | L60: =($D60)/((1+$B$4/2)^(2*($A60-L$3))) -> 453.14205 | M60: =($D60)/((1+$B$4/2)^(2*($A60-M$3))) -> 475.47874 | ... AE60: =($D60)/((1+$B$4/2)^(2*($A60-AE$3))) -> 1130.505
A61: 27 | B61: =$B$1*$B$3/2 -> 1158.0328 | D61: =B61+C61 -> 1158.0328 | E61: =(D61)/(1+$B$4/2)^(2*A61) -> 315.87029 | F61: =($D61)/((1+$B$4/2)^(2*($A61-F$3))) -> 331.44046 | G61: =($D61)/((1+$B$4/2)^(2*($A61-G$3))) -> 347.77813 | H61: =($D61)/((1+$B$4/2)^(2*($A61-H$3))) -> 364.92113 | I61: =($D61)/((1+$B$4/2)^(2*($A61-I$3))) -> 382.90916 | J61: =($D61)/((1+$B$4/2)^(2*($A61-J$3))) -> 401.78387 | K61: =($D61)/((1+$B$4/2)^(2*($A61-K$3))) -> 421.58898 | L61: =($D61)/((1+$B$4/2)^(2*($A61-L$3))) -> 442.37033 | M61: =($D61)/((1+$B$4/2)^(2*($A61-M$3))) -> 464.17605 | ... AE61: =($D61)/((1+$B$4/2)^(2*($A61-AE$3))) -> 1103.6316
A62: 27.5 | B62: =$B$1*$B$3/2 -> 1158.0328 | D62: =B62+C62 -> 1158.0328 | E62: =(D62)/(1+$B$4/2)^(2*A62) -> 308.36169 | F62: =($D62)/((1+$B$4/2)^(2*($A62-F$3))) -> 323.56174 | G62: =($D62)/((1+$B$4/2)^(2*($A62-G$3))) -> 339.51104 | H62: =($D62)/((1+$B$4/2)^(2*($A62-H$3))) -> 356.24653 | I62: =($D62)/((1+$B$4/2)^(2*($A62-I$3))) -> 373.80696 | J62: =($D62)/((1+$B$4/2)^(2*($A62-J$3))) -> 392.233 | K62: =($D62)/((1+$B$4/2)^(2*($A62-K$3))) -> 411.56731 | L62: =($D62)/((1+$B$4/2)^(2*($A62-L$3))) -> 431.85467 | M62: =($D62)/((1+$B$4/2)^(2*($A62-M$3))) -> 453.14205 | ... AF62: =($D62)/((1+$B$4/2)^(2*($A62-AF$3))) -> 1130.505
A63: 28 | B63: =$B$1*$B$3/2 -> 1158.0328 | D63: =B63+C63 -> 1158.0328 | E63: =(D63)/(1+$B$4/2)^(2*A63) -> 301.03157 | F63: =($D63)/((1+$B$4/2)^(2*($A63-F$3))) -> 315.87029 | G63: =($D63)/((1+$B$4/2)^(2*($A63-G$3))) -> 331.44046 | H63: =($D63)/((1+$B$4/2)^(2*($A63-H$3))) -> 347.77813 | I63: =($D63)/((1+$B$4/2)^(2*($A63-I$3))) -> 364.92113 | J63: =($D63)/((1+$B$4/2)^(2*($A63-J$3))) -> 382.90916 | K63: =($D63)/((1+$B$4/2)^(2*($A63-K$3))) -> 401.78387 | L63: =($D63)/((1+$B$4/2)^(2*($A63-L$3))) -> 421.58898 | M63: =($D63)/((1+$B$4/2)^(2*($A63-M$3))) -> 442.37033 | ... AF63: =($D63)/((1+$B$4/2)^(2*($A63-AF$3))) -> 1103.6316
A64: 28.5 | B64: =$B$1*$B$3/2 -> 1158.0328 | D64: =B64+C64 -> 1158.0328 | E64: =(D64)/(1+$B$4/2)^(2*A64) -> 293.8757 | F64: =($D64)/((1+$B$4/2)^(2*($A64-F$3))) -> 308.36169 | G64: =($D64)/((1+$B$4/2)^(2*($A64-G$3))) -> 323.56174 | H64: =($D64)/((1+$B$4/2)^(2*($A64-H$3))) -> 339.51104 | I64: =($D64)/((1+$B$4/2)^(2*($A64-I$3))) -> 356.24653 | J64: =($D64)/((1+$B$4/2)^(2*($A64-J$3))) -> 373.80696 | K64: =($D64)/((1+$B$4/2)^(2*($A64-K$3))) -> 392.233 | L64: =($D64)/((1+$B$4/2)^(2*($A64-L$3))) -> 411.56731 | M64: =($D64)/((1+$B$4/2)^(2*($A64-M$3))) -> 431.85467 | ... AG64: =($D64)/((1+$B$4/2)^(2*($A64-AG$3))) -> 1130.505
A65: 29 | B65: =$B$1*$B$3/2 -> 1158.0328 | D65: =B65+C65 -> 1158.0328 | E65: =(D65)/(1+$B$4/2)^(2*A65) -> 286.88993 | F65: =($D65)/((1+$B$4/2)^(2*($A65-F$3))) -> 301.03157 | G65: =($D65)/((1+$B$4/2)^(2*($A65-G$3))) -> 315.87029 | H65: =($D65)/((1+$B$4/2)^(2*($A65-H$3))) -> 331.44046 | I65: =($D65)/((1+$B$4/2)^(2*($A65-I$3))) -> 347.77813 | J65: =($D65)/((1+$B$4/2)^(2*($A65-J$3))) -> 364.92113 | K65: =($D65)/((1+$B$4/2)^(2*($A65-K$3))) -> 382.90916 | L65: =($D65)/((1+$B$4/2)^(2*($A65-L$3))) -> 401.78387 | M65: =($D65)/((1+$B$4/2)^(2*($A65-M$3))) -> 421.58898 | ... AG65: =($D65)/((1+$B$4/2)^(2*($A65-AG$3))) -> 1103.6316
A66: 29.5 | B66: =$B$1*$B$3/2 -> 1158.0328 | D66: =B66+C66 -> 1158.0328 | E66: =(D66)/(1+$B$4/2)^(2*A66) -> 280.07022 | F66: =($D66)/((1+$B$4/2)^(2*($A66-F$3))) -> 293.8757 | G66: =($D66)/((1+$B$4/2)^(2*($A66-G$3))) -> 308.36169 | H66: =($D66)/((1+$B$4/2)^(2*($A66-H$3))) -> 323.56174 | I66: =($D66)/((1+$B$4/2)^(2*($A66-I$3))) -> 339.51104 | J66: =($D66)/((1+$B$4/2)^(2*($A66-J$3))) -> 356.24653 | K66: =($D66)/((1+$B$4/2)^(2*($A66-K$3))) -> 373.80696 | L66: =($D66)/((1+$B$4/2)^(2*($A66-L$3))) -> 392.233 | M66: =($D66)/((1+$B$4/2)^(2*($A66-M$3))) -> 411.56731 | ... AH66: =($D66)/((1+$B$4/2)^(2*($A66-AH$3))) -> 1130.505
A67: 30 | B67: =$B$1*$B$3/2 -> 1158.0328 | C67: =B1 -> 57901.64 | D67: =B67+C67 -> 59059.673 | E67: =(D67)/(1+$B$4/2)^(2*A67) -> 13944.044 | F67: =($D67)/((1+$B$4/2)^(2*($A67-F$3))) -> 14631.386 | G67: =($D67)/((1+$B$4/2)^(2*($A67-G$3))) -> 15352.61 | H67: =($D67)/((1+$B$4/2)^(2*($A67-H$3))) -> 16109.385 | I67: =($D67)/((1+$B$4/2)^(2*($A67-I$3))) -> 16903.464 | J67: =($D67)/((1+$B$4/2)^(2*($A67-J$3))) -> 17736.685 | K67: =($D67)/((1+$B$4/2)^(2*($A67-K$3))) -> 18610.978 | L67: =($D67)/((1+$B$4/2)^(2*($A67-L$3))) -> 19528.367 | M67: =($D67)/((1+$B$4/2)^(2*($A67-M$3))) -> 20490.978 | ... AH67: =($D67)/((1+$B$4/2)^(2*($A67-AH$3))) -> 56285.21 | AI67: =C67 -> 57901.64
