Workbook
Name _1_29_2020: 'Value of Bonds at Purchase Date'!$B$1:$B$6
Name Amount_to_Spend: 'Value of Bonds at Purchase Date'!$B$6
Name Coupon_rate: 'Value of Bonds at Purchase Date'!$B$3
Name Face_Value: 'Value of Bonds at Purchase Date'!$B$1
Name Interest_rate: 'Value of Bonds at Purchase Date'!$B$5
Name One_Period_Equals: 'Value of Bonds at Purchase Date'!$B$4
Name Start_date: 'Value of Bonds at Purchase Date'!$B$7
Name Term: 'Value of Bonds at Purchase Date'!$B$2

Sheet Instructions

Sheet Value of Bonds at Purchase Date
A1: Face_Value | B1: 57901.64 | E1: Date | F1: PV at Date
A2: Term | B2: 30 | C2: years | E2: =Start_date -> 46055 | F2: =SUM(F11:F70) -> 50000.002
A3: Coupon_rate | B3: 0.04 | C3: Paid semi-annually
A4: One_Period_Equals | B4: 0.5 | C4: years
A5: Interest_rate | B5: 0.0487 | C5: Compounded semi-annually
A6: Amount_to_Spend | B6: 50000
A7: Start_date | B7: 46055
A9: Date | B9: Time | C9: Coupon | D9: Face | E9: Total Cash Flow | F9: PV of cash flow
A10: =Start_date -> 46055 | B10: 0
A11: =EDATE(Start_date,6) -> 46236 | B11: 1 | C11: =Face_Value*Coupon_rate/2 -> 1158.0328 | E11: =SUM(C11:D11) -> 1158.0328 | F11: =E11/(1+Interest_rate/2)^(B11-0) -> 1130.505
A12: =EDATE(A11,6) -> 46420 | B12: 2 | C12: =Face_Value*Coupon_rate/2 -> 1158.0328 | E12: =SUM(C12:D12) -> 1158.0328 | F12: =E12/(1+Interest_rate/2)^(B12-0) -> 1103.6316
A13: =EDATE(A12,6) -> 46601 | B13: 3 | C13: =Face_Value*Coupon_rate/2 -> 1158.0328 | E13: =SUM(C13:D13) -> 1158.0328 | F13: =E13/(1+Interest_rate/2)^(B13-0) -> 1077.397
A14: =EDATE(A13,6) -> 46785 | B14: 4 | C14: =Face_Value*Coupon_rate/2 -> 1158.0328 | E14: =SUM(C14:D14) -> 1158.0328 | F14: =E14/(1+Interest_rate/2)^(B14-0) -> 1051.786
A15: =EDATE(A14,6) -> 46967 | B15: 5 | C15: =Face_Value*Coupon_rate/2 -> 1158.0328 | E15: =SUM(C15:D15) -> 1158.0328 | F15: =E15/(1+Interest_rate/2)^(B15-0) -> 1026.7838
A16: =EDATE(A15,6) -> 47151 | B16: 6 | C16: =Face_Value*Coupon_rate/2 -> 1158.0328 | E16: =SUM(C16:D16) -> 1158.0328 | F16: =E16/(1+Interest_rate/2)^(B16-0) -> 1002.3759
A17: =EDATE(A16,6) -> 47332 | B17: 7 | C17: =Face_Value*Coupon_rate/2 -> 1158.0328 | E17: =SUM(C17:D17) -> 1158.0328 | F17: =E17/(1+Interest_rate/2)^(B17-0) -> 978.54828
A18: =EDATE(A17,6) -> 47516 | B18: 8 | C18: =Face_Value*Coupon_rate/2 -> 1158.0328 | E18: =SUM(C18:D18) -> 1158.0328 | F18: =E18/(1+Interest_rate/2)^(B18-0) -> 955.28704
A19: =EDATE(A18,6) -> 47697 | B19: 9 | C19: =Face_Value*Coupon_rate/2 -> 1158.0328 | E19: =SUM(C19:D19) -> 1158.0328 | F19: =E19/(1+Interest_rate/2)^(B19-0) -> 932.57875
A20: =EDATE(A19,6) -> 47881 | B20: 10 | C20: =Face_Value*Coupon_rate/2 -> 1158.0328 | E20: =SUM(C20:D20) -> 1158.0328 | F20: =E20/(1+Interest_rate/2)^(B20-0) -> 910.41026
A21: =EDATE(A20,6) -> 48062 | B21: 11 | C21: =Face_Value*Coupon_rate/2 -> 1158.0328 | E21: =SUM(C21:D21) -> 1158.0328 | F21: =E21/(1+Interest_rate/2)^(B21-0) -> 888.76874
A22: =EDATE(A21,6) -> 48246 | B22: 12 | C22: =Face_Value*Coupon_rate/2 -> 1158.0328 | E22: =SUM(C22:D22) -> 1158.0328 | F22: =E22/(1+Interest_rate/2)^(B22-0) -> 867.64167
A23: =EDATE(A22,6) -> 48428 | B23: 13 | C23: =Face_Value*Coupon_rate/2 -> 1158.0328 | E23: =SUM(C23:D23) -> 1158.0328 | F23: =E23/(1+Interest_rate/2)^(B23-0) -> 847.01681
... A69: =EDATE(A68,6) -> 56828 | B69: 59 | C69: =Face_Value*Coupon_rate/2 -> 1158.0328 | E69: =SUM(C69:D69) -> 1158.0328 | F69: =E69/(1+Interest_rate/2)^(B69-0) -> 280.07022
A70: =EDATE(A69,6) -> 57012 | B70: 60 | C70: =Face_Value*Coupon_rate/2 -> 1158.0328 | D70: =Face_Value -> 57901.64 | E70: =SUM(C70:D70) -> 59059.673 | F70: =E70/(1+Interest_rate/2)^(B70-0) -> 13944.044
B71: Total | E71: =SUM(E11:E70) -> 127383.61 | F71: =SUM(F11:F70) -> 50000.002

Sheet Value of Bonds 6 mos later
A1: Face_Value | B1: =Face_Value -> 57901.64 | E1: Date | F1: PV at Date
A2: Term | B2: =Term-0.5 -> 29.5 | C2: years remaining | E2: =EDATE(Start_date,6) -> 46236 | F2: =SUM(F11:F70) -> 50059.469
A3: Coupon_rate | B3: 0.0425
A4: One_Period_Equals | B4: 0.5 | C4: years
A5: Interest_rate | B5: =Interest_rate -> 0.0487
A6: Amount_to_Spend | B6: 50000
A7: Start_date | B7: =Start_date -> 46055
A9: Date | B9: Time | C9: Coupon | D9: Face | E9: Total Cash Flow | F9: ="PV of cash flow @ "&TEXT(E2,"d-mmm-yy") -> PV of cash flow @ 2-Aug-26
A10: =Start_date -> 46055 | B10: 0
A11: =EDATE(Start_date,6) -> 46236 | B11: 1 | C11: Paid
A12: =EDATE(A11,6) -> 46420 | B12: 2 | C12: =Face_Value*Coupon_rate/2 -> 1158.0328 | E12: =SUM(C12:D12) -> 1158.0328 | F12: =E12/(1+Interest_rate/2)^(B12-1) -> 1130.505
A13: =EDATE(A12,6) -> 46601 | B13: 3 | C13: =Face_Value*Coupon_rate/2 -> 1158.0328 | E13: =SUM(C13:D13) -> 1158.0328 | F13: =E13/(1+Interest_rate/2)^(B13-1) -> 1103.6316
A14: =EDATE(A13,6) -> 46785 | B14: 4 | C14: =Face_Value*Coupon_rate/2 -> 1158.0328 | E14: =SUM(C14:D14) -> 1158.0328 | F14: =E14/(1+Interest_rate/2)^(B14-1) -> 1077.397
A15: =EDATE(A14,6) -> 46967 | B15: 5 | C15: =Face_Value*Coupon_rate/2 -> 1158.0328 | E15: =SUM(C15:D15) -> 1158.0328 | F15: =E15/(1+Interest_rate/2)^(B15-1) -> 1051.786
A16: =EDATE(A15,6) -> 47151 | B16: 6 | C16: =Face_Value*Coupon_rate/2 -> 1158.0328 | E16: =SUM(C16:D16) -> 1158.0328 | F16: =E16/(1+Interest_rate/2)^(B16-1) -> 1026.7838
A17: =EDATE(A16,6) -> 47332 | B17: 7 | C17: =Face_Value*Coupon_rate/2 -> 1158.0328 | E17: =SUM(C17:D17) -> 1158.0328 | F17: =E17/(1+Interest_rate/2)^(B17-1) -> 1002.3759
A18: =EDATE(A17,6) -> 47516 | B18: 8 | C18: =Face_Value*Coupon_rate/2 -> 1158.0328 | E18: =SUM(C18:D18) -> 1158.0328 | F18: =E18/(1+Interest_rate/2)^(B18-1) -> 978.54828
A19: =EDATE(A18,6) -> 47697 | B19: 9 | C19: =Face_Value*Coupon_rate/2 -> 1158.0328 | E19: =SUM(C19:D19) -> 1158.0328 | F19: =E19/(1+Interest_rate/2)^(B19-1) -> 955.28704
A20: =EDATE(A19,6) -> 47881 | B20: 10 | C20: =Face_Value*Coupon_rate/2 -> 1158.0328 | E20: =SUM(C20:D20) -> 1158.0328 | F20: =E20/(1+Interest_rate/2)^(B20-1) -> 932.57875
A21: =EDATE(A20,6) -> 48062 | B21: 11 | C21: =Face_Value*Coupon_rate/2 -> 1158.0328 | E21: =SUM(C21:D21) -> 1158.0328 | F21: =E21/(1+Interest_rate/2)^(B21-1) -> 910.41026
A22: =EDATE(A21,6) -> 48246 | B22: 12 | C22: =Face_Value*Coupon_rate/2 -> 1158.0328 | E22: =SUM(C22:D22) -> 1158.0328 | F22: =E22/(1+Interest_rate/2)^(B22-1) -> 888.76874
A23: =EDATE(A22,6) -> 48428 | B23: 13 | C23: =Face_Value*Coupon_rate/2 -> 1158.0328 | E23: =SUM(C23:D23) -> 1158.0328 | F23: =E23/(1+Interest_rate/2)^(B23-1) -> 867.64167
... A69: =EDATE(A68,6) -> 56828 | B69: 59 | C69: =Face_Value*Coupon_rate/2 -> 1158.0328 | E69: =SUM(C69:D69) -> 1158.0328 | F69: =E69/(1+Interest_rate/2)^(B69-1) -> 286.88993
A70: =EDATE(A69,6) -> 57012 | B70: 60 | C70: =Face_Value*Coupon_rate/2 -> 1158.0328 | D70: =Face_Value -> 57901.64 | E70: =SUM(C70:D70) -> 59059.673 | F70: =E70/(1+Interest_rate/2)^(B70-1) -> 14283.581
B71: Total | E71: =SUM(E11:E70) -> 126225.58 | F71: =SUM(F11:F70) -> 50059.469

Sheet Value of Bonds 1 yr later
A1: Face_Value | B1: =Face_Value -> 57901.64 | E1: =EDATE(Start_date,12) -> 46420 | F1: =SUM(F11:F70) -> 0
A2: Term | B2: =Term-1 -> 29 | C2: years remaining
A3: Coupon_rate | B3: =Coupon_rate -> 0.04
A4: One_Period_Equals | B4: =One_Period_Equals -> 0.5 | C4: years
A5: Interest_rate | B5: =Interest_rate -> 0.0487
A6: Amount_to_Spend | B6: =Amount_to_Spend -> 50000 | F6: FALSE
A7: Start_date | B7: =Start_date -> 46055
A9: Date | B9: Time | C9: Coupon | D9: Face | E9: Total Cash Flow | F9: ="PV of cash flow @ "&TEXT(E1,"d-mmm-yy") -> PV of cash flow @ 2-Feb-27
A10: =Start_date -> 46055
A11: =EDATE(Start_date,6) -> 46236 | B11: 1 | C11: Paid
A12: =EDATE(A11,6) -> 46420 | B12: 2 | C12: Paid
A13: =EDATE(A12,6) -> 46601 | B13: 3 | C13: ='Value of Bonds 6 mos later'!C12 -> 1158.0328 | E13: =SUM(C13:D13) -> 1158.0328
A14: =EDATE(A13,6) -> 46785 | B14: 4 | C14: ='Value of Bonds 6 mos later'!C13 -> 1158.0328 | E14: =SUM(C14:D14) -> 1158.0328
A15: =EDATE(A14,6) -> 46967 | B15: 5 | C15: ='Value of Bonds 6 mos later'!C14 -> 1158.0328 | E15: =SUM(C15:D15) -> 1158.0328
A16: =EDATE(A15,6) -> 47151 | B16: 6 | C16: ='Value of Bonds 6 mos later'!C15 -> 1158.0328 | E16: =SUM(C16:D16) -> 1158.0328
A17: =EDATE(A16,6) -> 47332 | B17: 7 | C17: ='Value of Bonds 6 mos later'!C16 -> 1158.0328 | E17: =SUM(C17:D17) -> 1158.0328
A18: =EDATE(A17,6) -> 47516 | B18: 8 | C18: ='Value of Bonds 6 mos later'!C17 -> 1158.0328 | E18: =SUM(C18:D18) -> 1158.0328
A19: =EDATE(A18,6) -> 47697 | B19: 9 | C19: ='Value of Bonds 6 mos later'!C18 -> 1158.0328 | E19: =SUM(C19:D19) -> 1158.0328
A20: =EDATE(A19,6) -> 47881 | B20: 10 | C20: ='Value of Bonds 6 mos later'!C19 -> 1158.0328 | E20: =SUM(C20:D20) -> 1158.0328
A21: =EDATE(A20,6) -> 48062 | B21: 11 | C21: ='Value of Bonds 6 mos later'!C20 -> 1158.0328 | E21: =SUM(C21:D21) -> 1158.0328
A22: =EDATE(A21,6) -> 48246 | B22: 12 | C22: ='Value of Bonds 6 mos later'!C21 -> 1158.0328 | E22: =SUM(C22:D22) -> 1158.0328
A23: =EDATE(A22,6) -> 48428 | B23: 13 | C23: ='Value of Bonds 6 mos later'!C22 -> 1158.0328 | E23: =SUM(C23:D23) -> 1158.0328
A24: =EDATE(A23,6) -> 48612 | B24: 14 | C24: ='Value of Bonds 6 mos later'!C23 -> 1158.0328 | E24: =SUM(C24:D24) -> 1158.0328
... A69: =EDATE(A68,6) -> 56828 | B69: 59 | C69: ='Value of Bonds 6 mos later'!C68 -> 1158.0328 | E69: =SUM(C69:D69) -> 1158.0328
A70: =EDATE(A69,6) -> 57012 | B70: 60 | C70: ='Value of Bonds 6 mos later'!C69 -> 1158.0328 | D70: ='Value of Bonds 6 mos later'!D70 -> 57901.64 | E70: =SUM(C70:D70) -> 59059.673
B71: Total | E71: =SUM(E11:E70) -> 125067.54 | F71: =SUM(F11:F70) -> 0

Sheet Ans1
A1: Face_Value | B1: =Face_Value -> 57901.64 | E1: =EDATE(Start_date,12) -> 46420 | F1: =SUM(F11:F70) -> 50120.384
A2: Term | B2: =Term-1 -> 29 | C2: years remaining
A3: Coupon_rate | B3: =Coupon_rate -> 0.04
A4: One_Period_Equals | B4: =One_Period_Equals -> 0.5 | C4: years
A5: Interest_rate | B5: =Interest_rate -> 0.0487
A6: Amount_to_Spend | B6: =Amount_to_Spend -> 50000
A7: Start_date | B7: =Start_date -> 46055
A9: Date | B9: Time | C9: Coupon | D9: Face | E9: Total Cash Flow | F9: ="PV of cash flow @ "&TEXT(E1,"d-mmm-yy") -> PV of cash flow @ 2-Feb-27
A10: =Start_date -> 46055
A11: =EDATE(Start_date,6) -> 46236 | B11: 1 | C11: Paid
A12: =EDATE(A11,6) -> 46420 | B12: 2 | C12: Paid
A13: =EDATE(A12,6) -> 46601 | B13: 3 | C13: ='Value of Bonds 6 mos later'!C12 -> 1158.0328 | E13: =SUM(C13:D13) -> 1158.0328 | F13: =E13/(1+Interest_rate/2)^(B13-2) -> 1130.505
A14: =EDATE(A13,6) -> 46785 | B14: 4 | C14: ='Value of Bonds 6 mos later'!C13 -> 1158.0328 | E14: =SUM(C14:D14) -> 1158.0328 | F14: =E14/(1+Interest_rate/2)^(B14-2) -> 1103.6316
A15: =EDATE(A14,6) -> 46967 | B15: 5 | C15: ='Value of Bonds 6 mos later'!C14 -> 1158.0328 | E15: =SUM(C15:D15) -> 1158.0328 | F15: =E15/(1+Interest_rate/2)^(B15-2) -> 1077.397
A16: =EDATE(A15,6) -> 47151 | B16: 6 | C16: ='Value of Bonds 6 mos later'!C15 -> 1158.0328 | E16: =SUM(C16:D16) -> 1158.0328 | F16: =E16/(1+Interest_rate/2)^(B16-2) -> 1051.786
A17: =EDATE(A16,6) -> 47332 | B17: 7 | C17: ='Value of Bonds 6 mos later'!C16 -> 1158.0328 | E17: =SUM(C17:D17) -> 1158.0328 | F17: =E17/(1+Interest_rate/2)^(B17-2) -> 1026.7838
A18: =EDATE(A17,6) -> 47516 | B18: 8 | C18: ='Value of Bonds 6 mos later'!C17 -> 1158.0328 | E18: =SUM(C18:D18) -> 1158.0328 | F18: =E18/(1+Interest_rate/2)^(B18-2) -> 1002.3759
A19: =EDATE(A18,6) -> 47697 | B19: 9 | C19: ='Value of Bonds 6 mos later'!C18 -> 1158.0328 | E19: =SUM(C19:D19) -> 1158.0328 | F19: =E19/(1+Interest_rate/2)^(B19-2) -> 978.54828
A20: =EDATE(A19,6) -> 47881 | B20: 10 | C20: ='Value of Bonds 6 mos later'!C19 -> 1158.0328 | E20: =SUM(C20:D20) -> 1158.0328 | F20: =E20/(1+Interest_rate/2)^(B20-2) -> 955.28704
A21: =EDATE(A20,6) -> 48062 | B21: 11 | C21: ='Value of Bonds 6 mos later'!C20 -> 1158.0328 | E21: =SUM(C21:D21) -> 1158.0328 | F21: =E21/(1+Interest_rate/2)^(B21-2) -> 932.57875
A22: =EDATE(A21,6) -> 48246 | B22: 12 | C22: ='Value of Bonds 6 mos later'!C21 -> 1158.0328 | E22: =SUM(C22:D22) -> 1158.0328 | F22: =E22/(1+Interest_rate/2)^(B22-2) -> 910.41026
A23: =EDATE(A22,6) -> 48428 | B23: 13 | C23: ='Value of Bonds 6 mos later'!C22 -> 1158.0328 | E23: =SUM(C23:D23) -> 1158.0328 | F23: =E23/(1+Interest_rate/2)^(B23-2) -> 888.76874
A24: =EDATE(A23,6) -> 48612 | B24: 14 | C24: ='Value of Bonds 6 mos later'!C23 -> 1158.0328 | E24: =SUM(C24:D24) -> 1158.0328 | F24: =E24/(1+Interest_rate/2)^(B24-2) -> 867.64167
... A69: =EDATE(A68,6) -> 56828 | B69: 59 | C69: ='Value of Bonds 6 mos later'!C68 -> 1158.0328 | E69: =SUM(C69:D69) -> 1158.0328 | F69: =E69/(1+Interest_rate/2)^(B69-2) -> 293.8757
A70: =EDATE(A69,6) -> 57012 | B70: 60 | C70: ='Value of Bonds 6 mos later'!C69 -> 1158.0328 | D70: ='Value of Bonds 6 mos later'!D70 -> 57901.64 | E70: =SUM(C70:D70) -> 59059.673 | F70: =E70/(1+Interest_rate/2)^(B70-2) -> 14631.386
B71: Total | E71: =SUM(E11:E70) -> 125067.54 | F71: =SUM(F11:F70) -> 50120.384

Sheet Interest Earned vs Coupon Pymnt
C2: Date
A3: Amount of initial loan to US Government | B3: 50000 | C3: =TEXT(Start_date,"d-mmm-yy") -> 2-Feb-26
A4: Interest over 1st 6 months | B4: =B3*Interest_rate/2 -> 1217.5
A5: Value of bonds immediately before the 1st coupon payment | B5: =SUM(B3:B4) -> 51217.5
A6: 1st Coupon Payment | B6: =-Face_Value*Coupon_rate/2 -> -1158.0328
A7: Value of bonds immediately after the 1st payment | B7: =SUM(B5:B6) -> 50059.467 | C7: =TEXT(EDATE(Start_date,6),"d-mmm-yy") -> 2-Aug-26
A8: Interest over 2nd 6 months
A9: Value of bonds immediately before the 2nd coupon payment | B9: =SUM(B7:B8) -> 50059.467
A10: 2nd Coupon Payment
A11: Total amount owed by US Gov't immediately after the 2nd coupon payment | B11: =SUM(B9:B10) -> 50059.467 | C11: =TEXT(EDATE(Start_date,12),"d-mmm-yy") -> 2-Feb-27
A12: Interest over 3rd 6 months
A13: Total amount owed by US Gov't immediately before the 3rd coupon payment | B13: =SUM(B11:B12) -> 50059.467
A14: 3rd Coupon Payment
A15: Total amount owed by US Gov't immediately after the 3rd coupon payment | B15: =SUM(B13:B14) -> 50059.467 | C15: =TEXT(EDATE(Start_date,18),"d-mmm-yy") -> 2-Aug-27
A16: Can you see the pattern of the calculations?
B18: FALSE

Sheet Ans2
C2: Date
A3: Amount of initial loan to US Government | B3: 50000 | C3: =TEXT(Start_date,"d-mmm-yy") -> 2-Feb-26
A4: Interest over 1st 6 months | B4: =B3*Interest_rate/2 -> 1217.5
A5: Value of bonds immediately before the 1st coupon payment | B5: =SUM(B3:B4) -> 51217.5
A6: 1st Coupon Payment | B6: =-Face_Value*Coupon_rate/2 -> -1158.0328
A7: Value of bonds immediately after the 1st payment | B7: =SUM(B5:B6) -> 50059.467 | C7: =TEXT(EDATE(Start_date,6),"d-mmm-yy") -> 2-Aug-26
A8: Interest over 2nd 6 months | B8: =B7*Interest_rate/2 -> 1218.948
A9: Value of bonds immediately before the 2nd coupon payment | B9: =SUM(B7:B8) -> 51278.415
A10: 2nd Coupon Payment | B10: =-Face_Value*Coupon_rate/2 -> -1158.0328
A11: Total amount owed by US Gov't immediately after the 2nd coupon payment | B11: =SUM(B9:B10) -> 50120.382 | C11: =TEXT(EDATE(Start_date,12),"d-mmm-yy") -> 2-Feb-27
A12: Interest over 3rd 6 months | B12: =B11*Interest_rate/2 -> 1220.4313
A13: Total amount owed by US Gov't immediately before the 3rd coupon payment | B13: =SUM(B11:B12) -> 51340.814
A14: 3rd Coupon Payment | B14: =-Face_Value*Coupon_rate/2 -> -1158.0328
A15: Total amount owed by US Gov't immediately after the 3rd coupon payment | B15: =SUM(B13:B14) -> 50182.781 | C15: =TEXT(EDATE(Start_date,18),"d-mmm-yy") -> 2-Aug-27
A16: Can you see the pattern of the calculations? | B16: YES

Sheet Grading
A1: ProblemType | B1: WorksheetName | C1: Range | D1: Comparison | E1: Grade | F1: IncorrectFeedback | G1: CorrectFeedback
A2: CELL | B2: Value of Bonds 6 mos later | C2: F2 | D2: MOEValue(0.1) | E2: 0 | F2: Incorrect PV | G2: Got it!
A3: CELL | B3: Value of Bonds 6 mos later | C3: C12 | D3: MOEValue(0.1) | E3: 0 | F3: Incorrect coupon payment | G3: Got it!
A4: CELL | B4: Value of Bonds 6 mos later | C4: C13 | D4: MOEValue(0.1) | E4: 0 | F4: Incorrect coupon payment | G4: Got it!
A5: CELL | B5: Value of Bonds 6 mos later | C5: C14 | D5: MOEValue(0.1) | E5: 0 | F5: Incorrect coupon payment | G5: Got it!
A6: CELL | B6: Value of Bonds 6 mos later | C6: C15 | D6: MOEValue(0.1) | E6: 0 | F6: Incorrect coupon payment | G6: Got it!
A7: CELL | B7: Value of Bonds 6 mos later | C7: C16 | D7: MOEValue(0.1) | E7: 0 | F7: Incorrect coupon payment | G7: Got it!
A8: CELL | B8: Value of Bonds 6 mos later | C8: C17 | D8: MOEValue(0.1) | E8: 0 | F8: Incorrect coupon payment | G8: Got it!
A9: CELL | B9: Value of Bonds 6 mos later | C9: C18 | D9: MOEValue(0.1) | E9: 0 | F9: Incorrect coupon payment | G9: Got it!
A10: CELL | B10: Value of Bonds 6 mos later | C10: C19 | D10: MOEValue(0.1) | E10: 0 | F10: Incorrect coupon payment | G10: Got it!
A11: CELL | B11: Value of Bonds 6 mos later | C11: C20 | D11: MOEValue(0.1) | E11: 0 | F11: Incorrect coupon payment | G11: Got it!
A12: CELL | B12: Value of Bonds 6 mos later | C12: C21 | D12: MOEValue(0.1) | E12: 0 | F12: Incorrect coupon payment | G12: Got it!
A13: CELL | B13: Value of Bonds 6 mos later | C13: C22 | D13: MOEValue(0.1) | E13: 0 | F13: Incorrect coupon payment | G13: Got it!
... A185: CELL | B185: Interest Earned vs Coupon Pymnt | C185: B16 | D185: MOEValue(0.1) | E185: 0 | F185: See TA or Instructor | G185: GREAT!
