Workbook
Name AccountTypesUsed: _xlfn.ANCHORARRAY(MasterData!$L$5)
Name AssetUsed: _xlfn.ANCHORARRAY(MasterData!$L$56)
Name BB_Inbalance: Financial_Statement_Builder!$E$559
Name BegDate: ProblemData!$E$64
Name Begin: MasterData!$F$669:$F$688
Name Begin: MasterData!$F$669:$F$688
Name CFO_NI_Recon_NI: FSConstruction!$BA$7:$BE$7
Name DeprMethod: ProblemData!$E$72
Name End: MasterData!$G$669:$G$688
Name End: MasterData!$G$669:$G$688
Name EndDate: ProblemData!$E$65
Name Entity: ProblemData!$E$61
Name EntityActivity: ProblemData!$E$63
Name EntityType: ProblemData!$E$62
Name EquityUsed: _xlfn.ANCHORARRAY(MasterData!$L$116)
Name ExpenseUsed: _xlfn.ANCHORARRAY(MasterData!$L$149)
Name FS_IssueDate: ProblemData!$E$66
Name GainUsed: _xlfn.ANCHORARRAY(MasterData!$L$171)
Name InventoryMethod: ProblemData!$E$73
Name Issue_Date: ProblemData!$E$66
Name LiabilityUsed: _xlfn.ANCHORARRAY(MasterData!$L$83)
Name LossUsed: _xlfn.ANCHORARRAY(MasterData!$L$185)
Name ParValue: ProblemData!$E$70
Name Period: ProblemData!$E$67
Name PurposesUsed: _xlfn.ANCHORARRAY(MasterData!$F$512)
Name RevenueUsed: _xlfn.ANCHORARRAY(MasterData!$L$135)
Name RevRec: ProblemData!$E$74
Name ShrsOut: ProblemData!$E$69
Name TreasShrs: ProblemData!$E$71
Name Units: ProblemData!$E$68
Name ZZZ: FSConstruction!$BA$7:$BE$7

Sheet Tables and Columns
A1: Table Name | B1: Column Names
A2: MD_Account_Type_Labels | B2: ACCOUNT TYPE LABELS, Used
A3: MD_CF_Labels | B3: CASH FLOW STATEMENT LABELS, Used
A4: MD_Assets | B4: Account Name, Abbreviation, BalType, C/NC, Num, Definition, Used
A5: MD_Liabilities | B5: Account Name, Abbr, BalType, C/NC, Num, Definition, Used
A6: MD_Equities | B6: Account Name, Abbr, BalType, C/NC, Num, Definition, Used
A7: MD_Revenues | B7: Account Name, Abbr, BalType, C/NC, Num, Definition, Used
A8: MD_Expenses | B8: Account Name, Abbr, BalType, C/NC, Num, Definition, Used
A9: MD_Gains | B9: Account Name, Abbr, BalType, C/NC, Num, Definition, Used
A10: MD_Losses | B10: Account Name, Abbr, BalType, C/NC, Num, Definition, Used
A11: CashFlow_Codes | B11: Cash Flow Code
A12: Investing | B12: Transaction Description, Involve Cash, Abbr
... A34: Journal | B34: Transaction #, Accnt Type, Debit Account, Credit Account, Dr Amt, Cr Amt, Cash Flow, Movement #, Cash, ref1, ref2

Sheet FSFormattingCodes
B2: 1 | C2: Financial Statement Title
B3: 2 | C3: Main Heading
B4: 3 | C4: Main Heading Total
B5: 4 | C5: Subheading
B6: 5 | C6: Subheading Total
B7: 6 | C7: First Account Title or Explanation after Heading or Subheading
B8: 7 | C8: Not the First Account Title or Explanation after Heading or Subheading
B9: 8 | C9: Blank Line not in the Statement
B10: 9 | C10: Blank Line in the Statement
B11: 10 | C11: Units
B12: 11 | C12: Line not in the Statement
C15: Main Headings
C16: Assets
C17: Liabilities
C18: Equities
C21: Subheadings
C22: Revenues
C23: Expenses
C24: Account Abbreviations
C25: Operating
C26: Investing
C27: Financing
C28: Net Income (Loss)

Sheet MasterData
B2: Labels
C4: ACCOUNT TYPE LABELS | D4: Used | F4: ="MD_Account_Type_Labels[ACCOUNT TYPE LABELS]" -> MD_Account_Type_Labels[ACCOUNT TYPE LABELS] | L4: Account Types Used
C5: Asset | D5: =IF(MD_Account_Type_Labels[[#This Row],[ACCOUNT TYPE LABELS]]="","",IFERROR(IF(SEARCH(MD_Account_Type_Labels[[#This Row],[ACCOUNT TYPE LABELS]],ProblemData!$E$241)>0,1,0),"")) -> 1 | L5: {=IFERROR(_xlfn._xlws.FILTER(MD_Account_Type_Labels[ACCOUNT TYPE LABELS],MD_Account_Type_Labels[Used]=1),"")} -> Asset
C6: Liability | D6: =IF(MD_Account_Type_Labels[[#This Row],[ACCOUNT TYPE LABELS]]="","",IFERROR(IF(SEARCH(MD_Account_Type_Labels[[#This Row],[ACCOUNT TYPE LABELS]],ProblemData!$E$241)>0,1,0),"")) -> 1 | L6: Liability
C7: Equity | D7: =IF(MD_Account_Type_Labels[[#This Row],[ACCOUNT TYPE LABELS]]="","",IFERROR(IF(SEARCH(MD_Account_Type_Labels[[#This Row],[ACCOUNT TYPE LABELS]],ProblemData!$E$241)>0,1,0),"")) -> 1 | L7: Equity
C8: Revenue | D8: =IF(MD_Account_Type_Labels[[#This Row],[ACCOUNT TYPE LABELS]]="","",IFERROR(IF(SEARCH(MD_Account_Type_Labels[[#This Row],[ACCOUNT TYPE LABELS]],ProblemData!$E$241)>0,1,0),"")) -> 1 | L8: Revenue
C9: Expense | D9: =IF(MD_Account_Type_Labels[[#This Row],[ACCOUNT TYPE LABELS]]="","",IFERROR(IF(SEARCH(MD_Account_Type_Labels[[#This Row],[ACCOUNT TYPE LABELS]],ProblemData!$E$241)>0,1,0),"")) -> 1 | L9: Expense
C10: Gain | D10: =IF(MD_Account_Type_Labels[[#This Row],[ACCOUNT TYPE LABELS]]="","",IFERROR(IF(SEARCH(MD_Account_Type_Labels[[#This Row],[ACCOUNT TYPE LABELS]],ProblemData!$E$241)>0,1,0),"")) | L10: Loss
C11: Loss | D11: =IF(MD_Account_Type_Labels[[#This Row],[ACCOUNT TYPE LABELS]]="","",IFERROR(IF(SEARCH(MD_Account_Type_Labels[[#This Row],[ACCOUNT TYPE LABELS]],ProblemData!$E$241)>0,1,0),"")) -> 1
C14: CASH FLOW STATEMENT LABELS | D14: Used | E14: Include on Student List if Used | K14: CFS Labels Used for Students | L14: All CFS Labels Used
C15: Operating | D15: =IF(MD_CF_Labels[[#This Row],[CASH FLOW STATEMENT LABELS]]="","",IFERROR(IF(SEARCH(MD_CF_Labels[[#This Row],[CASH FLOW STATEMENT LABELS]],ProblemData!$E$242)>0,1,0),"")) -> 1 | E15: 1 | K15: {=IFERROR(_xlfn._xlws.FILTER(MD_CF_Labels[CASH FLOW STATEMENT LABELS],(MD_CF_Labels[Used]=1)*MD_CF_Labels[Include on Student List if Used]=1),"")} -> Operating | L15: {=IFERROR(_xlfn._xlws.FILTER(MD_CF_Labels[CASH FLOW STATEMENT LABELS],MD_CF_Labels[Used]=1),"")} -> Operating
C16: Investing | D16: =IF(MD_CF_Labels[[#This Row],[CASH FLOW STATEMENT LABELS]]="","",IFERROR(IF(SEARCH(MD_CF_Labels[[#This Row],[CASH FLOW STATEMENT LABELS]],ProblemData!$E$242)>0,1,0),"")) -> 1 | E16: 1 | K16: Investing | L16: Investing
C17: Financing | D17: =IF(MD_CF_Labels[[#This Row],[CASH FLOW STATEMENT LABELS]]="","",IFERROR(IF(SEARCH(MD_CF_Labels[[#This Row],[CASH FLOW STATEMENT LABELS]],ProblemData!$E$242)>0,1,0),"")) -> 1 | E17: 1 | K17: Financing | L17: Financing
C18: Noncash_Investing | D18: =IF(MD_CF_Labels[[#This Row],[CASH FLOW STATEMENT LABELS]]="","",IFERROR(IF(SEARCH(MD_CF_Labels[[#This Row],[CASH FLOW STATEMENT LABELS]],ProblemData!$E$242)>0,1,0),"")) -> 1 | E18: 0 | L18: Noncash_Investing
C19: Noncash_Financing | D19: =IF(MD_CF_Labels[[#This Row],[CASH FLOW STATEMENT LABELS]]="","",IFERROR(IF(SEARCH(MD_CF_Labels[[#This Row],[CASH FLOW STATEMENT LABELS]],ProblemData!$E$242)>0,1,0),"")) -> 1 | E19: 0 | L19: Noncash_Financing
C20: Noncash_Investing/Financing | D20: =IF(MD_CF_Labels[[#This Row],[CASH FLOW STATEMENT LABELS]]="","",IFERROR(IF(SEARCH(MD_CF_Labels[[#This Row],[CASH FLOW STATEMENT LABELS]],ProblemData!$E$242)>0,1,0),"")) | E20: 0
B24: Automation
C26: LEVELS OF FINANCIAL STATEMENT AUTOMATION | D26: Selected | F26: ="MD_FS_Automation[LEVELS OF FINANCIAL STATEMENT AUTOMATION]" -> MD_FS_Automation[LEVELS OF FINANCIAL STATEMENT AUTOMATION]
C27: None | D27: =IF(ProblemData!$E$3=MD_FS_Automation[[#This Row],[LEVELS OF FINANCIAL STATEMENT AUTOMATION]],1,"")
C28: Balance Sheets | D28: =IF(ProblemData!$E$3=MD_FS_Automation[[#This Row],[LEVELS OF FINANCIAL STATEMENT AUTOMATION]],1,"")
C29: Balance Sheets and Income Statement | D29: =IF(ProblemData!$E$3=MD_FS_Automation[[#This Row],[LEVELS OF FINANCIAL STATEMENT AUTOMATION]],1,"")
C30: Balance Sheets, Income Statement and Statement of Shareholders' Equity | D30: =IF(ProblemData!$E$3=MD_FS_Automation[[#This Row],[LEVELS OF FINANCIAL STATEMENT AUTOMATION]],1,"")
C31: Balance Sheets, Income Statement, Statement of Shareholders' Equity and Cash Flow Statement | D31: =IF(ProblemData!$E$3=MD_FS_Automation[[#This Row],[LEVELS OF FINANCIAL STATEMENT AUTOMATION]],1,"")
C32: All | D32: =IF(ProblemData!$E$3=MD_FS_Automation[[#This Row],[LEVELS OF FINANCIAL STATEMENT AUTOMATION]],1,"")
B34: Feedback
C36: LEVELS OF FEEDBACK | D36: Selected | F36: ="MD_Feedback[LEVELS OF FEEDBACK]" -> MD_Feedback[LEVELS OF FEEDBACK]
C37: None | D37: =IF(ProblemData!$E$10=MD_Feedback[[#This Row],[LEVELS OF FEEDBACK]],1,"")
C38: Journal Entry Tool in Analysis Help Only | D38: =IF(ProblemData!$E$10=MD_Feedback[[#This Row],[LEVELS OF FEEDBACK]],1,"")
C39: Journal Entry Tool in Analysis Help and Journal Entry Checker | D39: =IF(ProblemData!$E$10=MD_Feedback[[#This Row],[LEVELS OF FEEDBACK]],1,"")
C40: Journal Entry Tool in Analysis Help, Journal Entry Checker and Journal | D40: =IF(ProblemData!$E$10=MD_Feedback[[#This Row],[LEVELS OF FEEDBACK]],1,"")
D41: =IF(ProblemData!$E$10=MD_Feedback[[#This Row],[LEVELS OF FEEDBACK]],1,"")
D42: =IF(ProblemData!$E$10=MD_Feedback[[#This Row],[LEVELS OF FEEDBACK]],1,"")
D43: =IF(ProblemData!$E$10=MD_Feedback[[#This Row],[LEVELS OF FEEDBACK]],1,"")
D44: =IF(ProblemData!$E$10=MD_Feedback[[#This Row],[LEVELS OF FEEDBACK]],1,"")
D45: =IF(ProblemData!$E$10=MD_Feedback[[#This Row],[LEVELS OF FEEDBACK]],1,"")
D46: =IF(ProblemData!$E$10=MD_Feedback[[#This Row],[LEVELS OF FEEDBACK]],1,"")
D47: =IF(ProblemData!$E$10=MD_Feedback[[#This Row],[LEVELS OF FEEDBACK]],1,"")
B50: Accounts Taxonomy
B52: Balance Sheet Accounts
C54: Assets | AD54: {=_xlfn._xlws.FILTER(INDIRECT(J54,FALSE),INDIRECT(J54,FALSE)<>"")} -> #REF!
C55: Account Name | D55: Abbr | E55: IncreasedBy | F55: C/NC | G55: Num | H55: Definition | I55: Used | J55: NI_CFO_Recon | L55: AssetUsed | N55: AllAcctsUsed
I56: =IF(MD_Asset[[#This Row],[Account Name]]="","",IFERROR(IF(SEARCH(MD_Asset[[#This Row],[Account Name]],ProblemData!$E$241)>0,1,0),"")) | J56: =IF(MD_Asset[[#This Row],[Abbr]]="","",IFERROR(IF(SEARCH(MD_Asset[[#This Row],[Abbr]],ProblemData!$E$241)>0,1,0),"")) | K56: ROW INTENTIONALLY LEFT BLANK | L56: {=IFERROR(_xlfn._xlws.FILTER(MD_Asset[[#All],[Account Name]],MD_Asset[[#All],[Used]]=1),"")} -> Cash | N56: {=_xlfn.VSTACK(AssetUsed,LiabilityUsed,EquityUsed,RevenueUsed,ExpenseUsed)} -> Cash | O56: {=_xlfn.SORTBY(_xlfn.ANCHORARRAY(N56), _xlfn.RANDARRAY(ROWS(_xlfn.ANCHORARRAY(N56))))} -> Cash
C57: Cash | D57: CSH | E57: Debit | F57: C | G57: 1 | H57: Rights to settle debts and acquire goods and services. These rights are, by definition, the most liquid of assets, meaning cash is readily converted into other assets or used to extinguish debts. | I57: =IF(MD_Asset[[#This Row],[Account Name]]="","",IFERROR(IF(SEARCH(MD_Asset[[#This Row],[Account Name]],ProblemData!$E$241)>0,1,0),"")) -> 1 | L57: Accounts Receivable | N57: Accounts Receivable | O57: Accounts Payable
C58: Accounts Receivable | D58: AR | E58: Debit | F58: C | G58: =G57+1 -> 2 | H58: The amounts due from customers in payment for goods delivered or services performed by the entity. | I58: =IF(MD_Asset[[#This Row],[Account Name]]="","",IFERROR(IF(SEARCH(MD_Asset[[#This Row],[Account Name]],ProblemData!$E$241)>0,1,0),"")) -> 1 | J58: 1 | L58: Inventories | N58: Inventories | O58: Common Stock
C59: Allowance for Doubtful Accounts | D59: ADA | E59: Credit | F59: C | G59: =G58+1 -> 3 | H59: A contra-asset account holding the estimated amount of uncollectible Accounts Receivable. | I59: =IF(MD_Asset[[#This Row],[Account Name]]="","",IFERROR(IF(SEARCH(MD_Asset[[#This Row],[Account Name]],ProblemData!$E$241)>0,1,0),"")) | J59: 1 | L59: Property, Plant & Equipment | N59: Property, Plant & Equipment | O59: Property, Plant & Equipment
C60: Marketable Securities | D60: MS | E60: Debit | F60: C | G60: =G59+1 -> 4 | H60: Investments in financial assets, such as shares of stocks and bonds. | I60: =IF(MD_Asset[[#This Row],[Account Name]]="","",IFERROR(IF(SEARCH(MD_Asset[[#This Row],[Account Name]],ProblemData!$E$241)>0,1,0),"")) | L60: Land | N60: Land | O60: Inventories
C61: Inventories | D61: Inv | E61: Debit | F61: C | G61: =G60+1 -> 5 | H61: Goods held for sale in a retailer. Manufacturing firms also have Raw Materials, Work-in-Process, and Finished Goods inventories. | I61: =IF(MD_Asset[[#This Row],[Account Name]]="","",IFERROR(IF(SEARCH(MD_Asset[[#This Row],[Account Name]],ProblemData!$E$241)>0,1,0),"")) -> 1 | J61: 1 | N61: Accounts Payable | O61: Loans Payable
C62: Prepaid Expenses | D62: PrePE | E62: Debit | F62: C | G62: =G61+1 -> 6 | H62: An asset account, these are goods and services for which payment has been made but which will not be consumed until some time in the future. | I62: =IF(MD_Asset[[#This Row],[Account Name]]="","",IFERROR(IF(SEARCH(MD_Asset[[#This Row],[Account Name]],ProblemData!$E$241)>0,1,0),"")) | J62: 1 | N62: Dividends Payable | O62: Retained Earnings
C63: Prepaid Rent | D63: PrePR | E63: Debit | F63: C | G63: =G62+1 -> 7 | H63: The right to occupy space for which payment has been made. | I63: =IF(MD_Asset[[#This Row],[Account Name]]="","",IFERROR(IF(SEARCH(MD_Asset[[#This Row],[Account Name]],ProblemData!$E$241)>0,1,0),"")) | J63: 1 | N63: Unearned Revenue | O63: Sales
C64: Other Current Assets | D64: OCA | E64: Debit | F64: C | G64: =G63+1 -> 8 | H64: Current assets not shown in any other category. | I64: =IF(MD_Asset[[#This Row],[Account Name]]="","",IFERROR(IF(SEARCH(MD_Asset[[#This Row],[Account Name]],ProblemData!$E$241)>0,1,0),"")) | J64: 1 | N64: Loans Payable | O64: Unearned Revenue
C65: Property, Plant & Equipment | D65: PPE | E65: Debit | F65: NC | G65: =G64+1 -> 9 | H65: The land, buildings, manufacturing machines, delivery vehicles, etc., that entities hold for use over several periods. | I65: =IF(MD_Asset[[#This Row],[Account Name]]="","",IFERROR(IF(SEARCH(MD_Asset[[#This Row],[Account Name]],ProblemData!$E$241)>0,1,0),"")) -> 1 | N65: Common Stock | O65: Cost of Goods Sold
C66: Accumulated Depreciation | D66: AccDepr | E66: Credit | F66: NC | G66: =G65+1 -> 10 | H66: A contra-asset account holding the accumulated amount of depreciation expense taken on tangible assets. Depreciation is the process of systematically allocating the cost of an asset to the periods that it benefits. | I66: =IF(MD_Asset[[#This Row],[Account Name]]="","",IFERROR(IF(SEARCH(MD_Asset[[#This Row],[Account Name]],ProblemData!$E$241)>0,1,0),"")) | N66: Retained Earnings | O66: Accounts Receivable
C67: Intangibles | D67: Intang | E67: Debit | F67: NC | G67: =G66+1 -> 11 | H67: Assets that have no physical existent, such as patents, brands, and copyrights. | I67: =IF(MD_Asset[[#This Row],[Account Name]]="","",IFERROR(IF(SEARCH(MD_Asset[[#This Row],[Account Name]],ProblemData!$E$241)>0,1,0),"")) | N67: Sales | O67: Dividends Payable
C68: Goodwill | D68: Gdwll | E68: Debit | F68: NC | G68: =G67+1 -> 12 | H68: The excess of the acquisition cost of a company over the net fair value of its identifiable assets and liabilities at the time of the acquisition. | I68: =IF(MD_Asset[[#This Row],[Account Name]]="","",IFERROR(IF(SEARCH(MD_Asset[[#This Row],[Account Name]],ProblemData!$E$241)>0,1,0),"")) | N68: Cost of Goods Sold | O68: Land
C69: Other Noncurrent Assets | D69: ONCA | E69: Debit | F69: NC | G69: =G68+1 -> 13 | H69: Noncurrent assts not shown in any other category. | I69: =IF(MD_Asset[[#This Row],[Account Name]]="","",IFERROR(IF(SEARCH(MD_Asset[[#This Row],[Account Name]],ProblemData!$E$241)>0,1,0),"")) | J69: 1
C70: Deferred Tax Assets | D70: DefTxA | E70: Debit | F70: NC | G70: =G69+1 -> 14 | H70: Debits arising from temporary differences between financial accounting records and tax accounting records. | I70: =IF(MD_Asset[[#This Row],[Account Name]]="","",IFERROR(IF(SEARCH(MD_Asset[[#This Row],[Account Name]],ProblemData!$E$241)>0,1,0),""))
C71: Accumulated Amortization | D71: AccAmort | E71: Credit | F71: NC | G71: =G70+1 -> 15 | H71: A contra-asset account holding the accumulated amount of amortization expense taken on finite-lived intangible assets. Amortization is the process of systematically writing off an intangible asset over time, and is conceptually identical to depreciation for tangible assets. | I71: =IF(MD_Asset[[#This Row],[Account Name]]="","",IFERROR(IF(SEARCH(MD_Asset[[#This Row],[Account Name]],ProblemData!$E$241)>0,1,0),""))
C72: Land | D72: LND | E72: Debit | F72: NC | G72: =G71+1 -> 16 | H72: Land held for use, not resale. | I72: =IF(MD_Asset[[#This Row],[Account Name]]="","",IFERROR(IF(SEARCH(MD_Asset[[#This Row],[Account Name]],ProblemData!$E$241)>0,1,0),"")) -> 1
G73: =G72+1 -> 17 | I73: =IF(MD_Asset[[#This Row],[Account Name]]="","",IFERROR(IF(SEARCH(MD_Asset[[#This Row],[Account Name]],ProblemData!$E$241)>0,1,0),""))
G74: =G73+1 -> 18 | I74: =IF(MD_Asset[[#This Row],[Account Name]]="","",IFERROR(IF(SEARCH(MD_Asset[[#This Row],[Account Name]],ProblemData!$E$241)>0,1,0),""))
G75: =G74+1 -> 19 | I75: =IF(MD_Asset[[#This Row],[Account Name]]="","",IFERROR(IF(SEARCH(MD_Asset[[#This Row],[Account Name]],ProblemData!$E$241)>0,1,0),""))
G76: =G75+1 -> 20 | I76: =IF(MD_Asset[[#This Row],[Account Name]]="","",IFERROR(IF(SEARCH(MD_Asset[[#This Row],[Account Name]],ProblemData!$E$241)>0,1,0),""))
G77: =G76+1 -> 21 | I77: =IF(MD_Asset[[#This Row],[Account Name]]="","",IFERROR(IF(SEARCH(MD_Asset[[#This Row],[Account Name]],ProblemData!$E$241)>0,1,0),""))
G78: =G77+1 -> 22 | I78: =IF(MD_Asset[[#This Row],[Account Name]]="","",IFERROR(IF(SEARCH(MD_Asset[[#This Row],[Account Name]],ProblemData!$E$241)>0,1,0),""))
C81: Liabilities
C82: Account Name | D82: Abbr | E82: IncreasedBy | F82: C/NC | G82: Num | H82: Definition | I82: Used | J82: NI_CFO_Recon | L82: LiabilityUsed
C83: Accounts Payable | D83: AP | E83: Credit | F83: C | G83: 1 | H83: Amounts owed for purchases from vendors. | I83: =IF(MD_Liability[[#This Row],[Account Name]]="","",IFERROR(IF(SEARCH(MD_Liability[[#This Row],[Account Name]],ProblemData!$E$241)>0,1,0),"")) -> 1 | J83: 1 | K83: ROW INTENTIONALLY LEFT BLANK | L83: {=IFERROR(_xlfn._xlws.FILTER(MD_Liability[[#All],[Account Name]],MD_Liability[[#All],[Used]]=1),"")} -> Accounts Payable
C84: Accrued Expenses | D84: AccExp | E84: Credit | F84: C | G84: =G83+1 -> 2 | H84: Amounts owed for consumption of goods and services . | I84: =IF(MD_Liability[[#This Row],[Account Name]]="","",IFERROR(IF(SEARCH(MD_Liability[[#This Row],[Account Name]],ProblemData!$E$241)>0,1,0),"")) | J84: 1 | L84: Dividends Payable
C85: Interest Payable | D85: IP | E85: Credit | F85: C | G85: =G84+1 -> 3 | H85: Amounts owed for interest on borrowed funds. | I85: =IF(MD_Liability[[#This Row],[Account Name]]="","",IFERROR(IF(SEARCH(MD_Liability[[#This Row],[Account Name]],ProblemData!$E$241)>0,1,0),"")) | J85: 1 | L85: Unearned Revenue
C86: Dividends Payable | D86: DP | E86: Credit | F86: C | G86: =G85+1 -> 4 | H86: Amounts owed for dividends that have been declared but not yet paid. | I86: =IF(MD_Liability[[#This Row],[Account Name]]="","",IFERROR(IF(SEARCH(MD_Liability[[#This Row],[Account Name]],ProblemData!$E$241)>0,1,0),"")) -> 1 | L86: Loans Payable
C87: Taxes Payable | D87: TxP | E87: Credit | F87: C | G87: =G86+1 -> 5 | H87: Amounts owed for taxes. | I87: =IF(MD_Liability[[#This Row],[Account Name]]="","",IFERROR(IF(SEARCH(MD_Liability[[#This Row],[Account Name]],ProblemData!$E$241)>0,1,0),"")) | J87: 1
C88: Deferred Tax Liabilities | D88: DefTxL | E88: Credit | F88: C | G88: =G87+1 -> 6 | H88: Debits arising from temporary differences between financial accounting records and tax accounting records. | I88: =IF(MD_Liability[[#This Row],[Account Name]]="","",IFERROR(IF(SEARCH(MD_Liability[[#This Row],[Account Name]],ProblemData!$E$241)>0,1,0),"")) | J88: 1
C89: Unearned Revenue | D89: UR | E89: Credit | F89: C | G89: =G88+1 -> 7 | H89: Amounts received for goods to be delivered or services to be performed in the future. | I89: =IF(MD_Liability[[#This Row],[Account Name]]="","",IFERROR(IF(SEARCH(MD_Liability[[#This Row],[Account Name]],ProblemData!$E$241)>0,1,0),"")) -> 1 | J89: 1
C90: Salaries & Wages Payable | D90: SWP | E90: Credit | F90: C | G90: =G89+1 -> 8 | H90: Amounts owed to employees for services rendered. | I90: =IF(MD_Liability[[#This Row],[Account Name]]="","",IFERROR(IF(SEARCH(MD_Liability[[#This Row],[Account Name]],ProblemData!$E$241)>0,1,0),"")) | J90: 1
C91: Rent Payable | D91: RP | E91: Credit | F91: C | G91: =G90+1 -> 9 | H91: Amonts owed to landlords for rent. | I91: =IF(MD_Liability[[#This Row],[Account Name]]="","",IFERROR(IF(SEARCH(MD_Liability[[#This Row],[Account Name]],ProblemData!$E$241)>0,1,0),"")) | J91: 1
C92: 180-day Note Payable | D92: 180NP | E92: Credit | F92: C | G92: =G91+1 -> 10 | H92: Debt arising from issuance of a note with a maturity date 180 days from its issuance. | I92: =IF(MD_Liability[[#This Row],[Account Name]]="","",IFERROR(IF(SEARCH(MD_Liability[[#This Row],[Account Name]],ProblemData!$E$241)>0,1,0),""))
C93: Accounts Payable (Inventory) | D93: APInv | E93: Credit | F93: C | G93: =G92+1 -> 11 | H93: Amounts owed for purchases from suppliers of inventory. | I93: =IF(MD_Liability[[#This Row],[Account Name]]="","",IFERROR(IF(SEARCH(MD_Liability[[#This Row],[Account Name]],ProblemData!$E$241)>0,1,0),"")) | J93: 1
C94: Accounts Payable (Other) | D94: APOth | E94: Credit | F94: C | G94: =G93+1 -> 12 | H94: Amounts owed for purchases of goods or services other than merchandise inventory. | I94: =IF(MD_Liability[[#This Row],[Account Name]]="","",IFERROR(IF(SEARCH(MD_Liability[[#This Row],[Account Name]],ProblemData!$E$241)>0,1,0),"")) | J94: 1
C95: Interest Payable - Current | D95: IPCur | E95: Credit | F95: C | G95: =G94+1 -> 13 | H95: Amounts due within one year for interest on borrowed funds. | I95: =IF(MD_Liability[[#This Row],[Account Name]]="","",IFERROR(IF(SEARCH(MD_Liability[[#This Row],[Account Name]],ProblemData!$E$241)>0,1,0),"")) | J95: 1
C96: Other Accrued Expenses | D96: OAE | E96: Credit | F96: C | G96: =G95+1 -> 14 | H96: Amounts owed for consumption of goods and services . | I96: =IF(MD_Liability[[#This Row],[Account Name]]="","",IFERROR(IF(SEARCH(MD_Liability[[#This Row],[Account Name]],ProblemData!$E$241)>0,1,0),"")) | J96: 1
C97: Note Payable - Current | D97: NPCur | E97: Credit | F97: C | G97: =G96+1 -> 15 | H97: Amounts due within one year under the terms of a note. | I97: =IF(MD_Liability[[#This Row],[Account Name]]="","",IFERROR(IF(SEARCH(MD_Liability[[#This Row],[Account Name]],ProblemData!$E$241)>0,1,0),""))
C98: Bonds Payable | D98: BP | E98: Credit | F98: NC | G98: =G97+1 -> 16 | H98: Debt arising from the issuance of bonds. | I98: =IF(MD_Liability[[#This Row],[Account Name]]="","",IFERROR(IF(SEARCH(MD_Liability[[#This Row],[Account Name]],ProblemData!$E$241)>0,1,0),""))
C99: Notes Payable | D99: NP | E99: Credit | F99: NC | G99: =G98+1 -> 17 | H99: Debt arising from the issuance of promissory notes | I99: =IF(MD_Liability[[#This Row],[Account Name]]="","",IFERROR(IF(SEARCH(MD_Liability[[#This Row],[Account Name]],ProblemData!$E$241)>0,1,0),""))
C100: Senior Debt | D100: SenDbt | E100: Credit | F100: NC | G100: =G99+1 -> 18 | H100: Long-term debt that has high priority in bankruptcy. | I100: =IF(MD_Liability[[#This Row],[Account Name]]="","",IFERROR(IF(SEARCH(MD_Liability[[#This Row],[Account Name]],ProblemData!$E$241)>0,1,0),""))
C101: Subordinated Debt | D101: SubDbt | E101: Credit | F101: NC | G101: =G100+1 -> 19 | H101: Long-term debt that has low priority in bankruptcy. | I101: =IF(MD_Liability[[#This Row],[Account Name]]="","",IFERROR(IF(SEARCH(MD_Liability[[#This Row],[Account Name]],ProblemData!$E$241)>0,1,0),""))
C102: Interest Payable - Noncurrent | D102: IPNCur | E102: Credit | F102: NC | G102: =G101+1 -> 20 | H102: Amounts due beyond one year for interest on borrowed funds. | I102: =IF(MD_Liability[[#This Row],[Account Name]]="","",IFERROR(IF(SEARCH(MD_Liability[[#This Row],[Account Name]],ProblemData!$E$241)>0,1,0),"")) | J102: 1
C103: Loans Payable | D103: LP | E103: Credit | F103: NC | G103: =G102+1 -> 21 | H103: Debt arising from taking out a loan. | I103: =IF(MD_Liability[[#This Row],[Account Name]]="","",IFERROR(IF(SEARCH(MD_Liability[[#This Row],[Account Name]],ProblemData!$E$241)>0,1,0),"")) -> 1
C104: Long-term Bonds Payable | D104: LTBP | E104: Credit | F104: NC | G104: =G103+1 -> 22 | H104: Debt arising from the issuance of bonds. | I104: =IF(MD_Liability[[#This Row],[Account Name]]="","",IFERROR(IF(SEARCH(MD_Liability[[#This Row],[Account Name]],ProblemData!$E$241)>0,1,0),""))
C105: Other Long-term Liabilities | D105: OLTL | E105: Credit | F105: NC | G105: =G104+1 -> 23 | H105: Noncurrent liabilities not shown in any other category. | I105: =IF(MD_Liability[[#This Row],[Account Name]]="","",IFERROR(IF(SEARCH(MD_Liability[[#This Row],[Account Name]],ProblemData!$E$241)>0,1,0),""))
C106: No current liabilities | D106: NoCL | E106: Credit | F106: C | G106: =G105+1 -> 24 | I106: =IF(MD_Liability[[#This Row],[Account Name]]="","",IFERROR(IF(SEARCH(MD_Liability[[#This Row],[Account Name]],ProblemData!$E$241)>0,1,0),""))
C107: No noncurrent liabilities | D107: NoNCL | E107: Credit | F107: NC | G107: =G106+1 -> 25 | I107: =IF(MD_Liability[[#This Row],[Account Name]]="","",IFERROR(IF(SEARCH(MD_Liability[[#This Row],[Account Name]],ProblemData!$E$241)>0,1,0),""))
G108: =G107+1 -> 26 | I108: =IF(MD_Liability[[#This Row],[Account Name]]="","",IFERROR(IF(SEARCH(MD_Liability[[#This Row],[Account Name]],ProblemData!$E$241)>0,1,0),""))
G109: =G108+1 -> 27 | I109: =IF(MD_Liability[[#This Row],[Account Name]]="","",IFERROR(IF(SEARCH(MD_Liability[[#This Row],[Account Name]],ProblemData!$E$241)>0,1,0),""))
G110: =G109+1 -> 28 | I110: =IF(MD_Liability[[#This Row],[Account Name]]="","",IFERROR(IF(SEARCH(MD_Liability[[#This Row],[Account Name]],ProblemData!$E$241)>0,1,0),""))
G111: =G110+1 -> 29 | I111: =IF(MD_Liability[[#This Row],[Account Name]]="","",IFERROR(IF(SEARCH(MD_Liability[[#This Row],[Account Name]],ProblemData!$E$241)>0,1,0),"")) | K111: Equities
C114: Equities
C115: Account Name | D115: Abbr | E115: IncreasedBy | F115: C/NC | G115: Num | H115: Definition | I115: Used | J115: NI_CFO_Recon | L115: EquityUsed | N115: AllISAcctsUsed
K116: ROW INTENTIONALLY LEFT BLANK | L116: {=IFERROR(_xlfn._xlws.FILTER(MD_Equity[[#All],[Account Name]],MD_Equity[[#All],[Used]]=1),"")} -> Common Stock | N116: {=_xlfn.VSTACK(RevenueUsed,ExpenseUsed,GainUsed,LossUsed)} -> Sales
C117: Preferred Stock | D117: PrefStk | E117: Credit | G117: 1 | H117: Stock with higher priority for the receipt of dividends than common stock. Typically, the control rights of its owners are limited. | I117: =IF(MD_Equity[[#This Row],[Account Name]]="","",IFERROR(IF(SEARCH(MD_Equity[[#This Row],[Account Name]],ProblemData!$E$241)>0,1,0),"")) | L117: Retained Earnings | N117: Cost of Goods Sold
C118: Common Stock | D118: CS | E118: Credit | G118: =G117+1 -> 2 | H118: For common stocks with a par value, this account holds the total par value of common stock issued. For common stocks with no par value, it holds the total amount raised by the issuance of common stock. | I118: =IF(MD_Equity[[#This Row],[Account Name]]="","",IFERROR(IF(SEARCH(MD_Equity[[#This Row],[Account Name]],ProblemData!$E$241)>0,1,0),"")) -> 1
...

Sheet ProblemData
B1: Problem Parameters, Requirements and Purposes
D3: Item | E3: Allow Automation?
D4: All Entity Information, Units, Dates, … | E4: TRUE
D5: Entity Name | E5: FALSE
D6: Units | E6: FALSE
D7: Beginning Balance Sheet Date | E7: FALSE
D8: Ending Balance Sheet Date | E8: FALSE
D9: Period | E9: FALSE
D10: Beginning Balance Sheet | E10: TRUE
D11: Income Statement | E11: TRUE
D12: Statement of Comprehensive Income | E12: TRUE
D13: Statement of Changes in Shareholders' Equity | E13: TRUE
D14: Cash Flow Statement | E14: TRUE
D15: Reconciliation of NI and CFO | E15: TRUE
... D17: Ending Balance Sheet | E17: TRUE
D19: Feedback | E19: Allow?
D26: Purposes of Problem
D27: 1 | E27: Expand your financial vocabulary. | H27: 1
D28: 2 | E28: Use the Accounting Identity to analyze transactions. | H28: 1
D29: 3 | E29: Learn how to use the Analysis_Help | H29: 1
D30: 4 | H30: 1
D31: 5 | H31: 1
D33: Requirements
D34: Item | E34: Tab | F34: Action
D35: Chart of Accounts | E35: Instructions | F35: Omit
D36: Notes to the Financial Statements | E36: Notes_to_FSs | F36: Omit
D37: Beginning Balance Sheet | E37: Financial Statements | F37: Omit
D38: Journal entries for transactions and events of the period | E38: Journal | F38: Omit
D39: Journal entry to close temporary accounts | E39: Journal | F39: Omit
D40: Income Statement | E40: Financial Statements | F40: Omit
D41: Statement of Comprehensive Income | E41: Financial Statements | F41: Omit
D42: Statement of Shareholders' Equity | E42: Financial Statements | F42: Omit
D43: Cash flow statement labels in Column I of Journal | E43: Journal | F43: Omit
D44: Statement of Cash Flows | E44: Financial Statements | F44: Omit
D45: Net Income - Cash Flow from Operations Reconciliation Worksheet | E45: Reconciliation Worksheet | F45: Omit
... D50: Accounting Identity | E50: Analysis_Help | F50: Enter
B58: Entity Information
D60: Entity Information
D61: Entity | E61: Accounting Identity LLC
D62: Entity Type | E62: For-profit corporation
D63: Nature of Activity | E63: Service
D64: Begin Date | E64: 12/31/20x0
D65: End Date | E65: 12/31/20x1
D66: Issue Date | E66: 0
D67: Period | E67: Year
D68: Units | E68: Dollars in Thousands
D69: Begin Date Comm Shares Outstanding | E69: 1000
D70: Par Value per Share | E70: 0
D71: Shares held as Treasury Stock | E71: 0
D72: Depreciation Method | E72: Straight-line
D73: Inventory Method | E73: First-in, first-out (FIFO)
D74: Revenue Recognition | E74: when these criteria are met: (1) There is persuasive evidence of an arrangement with a customer/client; (2) Goods have been delivered or services have been provided; (3) The price to the customer/client is fixed or determinable; (4) There is sreasonable assurance that the price will be paid - i.e., that any related receivables will be collected.
B76: Transactions, Events and Answers
D78: Transaction Code | E78: 1 | F78: 2 | G78: 3 | H78: 4 | I78: 5 | J78: 6 | K78: 7 | L78: 8 | M78: 9 | N78: 10 | O78: 11 | P78: 12 | Q78: 13 | R78: 14 | S78: 15 | T78: 16 | U78: 17 | V78: 18 | W78: 19 | X78: 20 | Y78: 21 | Z78: 22 | AA78: 23 | AB78: 24 | AC78: 25 | AD78: 26 | AE78: 27 | AF78: 28 | AG78: 29 | AH78: 30 | AI78: 31 | AJ78: 32 | AK78: 33 | AL78: 34 | AM78: 35 | AN78: Entry Number
D79: Transaction Info | E79: Receives $50k in cash from its shareholders in exchange for issuing common stock. | F79: Receives $50k from a bank in exchange for making a promise to repay the bank with interest. | G79: Receives $50k from a customer in exchange for the performance of services. | H79: Receives a building to house its administration that is valued at $50k in exchange for issuing common stock to the building's existing owners. | I79: Receives a building to house its administration that is valued at $50k in exchange for making a promise to pay the existing owners (with interest). | J79: Pays $18k to suppliers for goods it intends to resell and takes delivery of those goods. | K79: Promises to pay $18k to suppliers for goods it intends to resell and takes delivery of the goods. | L79: Paid $17k to suppliers for goods it had purchased on credit. | M79: Pays $17k in cash and promises to pay another $1k next month to suppliers in exchange for goods it intends to resell and takes delivery of the goods. | N79: Received $8k in cash from customers and delivered those goods to those customers. | O79: Received $8k in cash from customers in exchange for a promise to deliver goods to those customers in the future. | P79: Received a call from a past customer during which the customer promised to buy $8k of goods next month. | Q79: Determined that the goods valued at their cost of $6k in its inventory accounts had been sold to customers. | R79: Determined that goods valued at their cost of $6k in its inventory accounts were accidentally destroyed. | S79: The entity announced its intention to bid for a contract to provide services to the city of New Haven, CT. | T79: Put in a bid of $15k for a contract to provide services to the city of New Haven, CT. | U79: Was informed that its bid of $15K to provide services to the city of New Haven, CT had made it to the final round of consideration. | V79: Was informed that its bid of $15K to provide services to the city of New Haven, CT had been accepted. | W79: Performed services to the city of New Haven under a contract. The contract calls for New Haven to pay $15k for these services. | X79: Received payment of $15k from the city of New Haven in response to a bill for services rendered. | Y79: Announced its intention to pay its shareholders a dividend. | Z79: Issued a formal declaration of its intention to pay a total of $2k in dividends to its shareholders of record as of 5 pm on October 10 of next year. | AA79: Paid cash of $2k for previously declared dividends to its shareholders.
D80: Recognition Yes/No | E80: Yes | F80: Yes | G80: Yes | H80: Yes | I80: Yes | J80: Yes | K80: Yes | L80: Yes | M80: Yes | N80: Yes | O80: Yes | P80: No | Q80: Yes | R80: Yes | S80: No | T80: No | U80: No | V80: No | W80: Yes | X80: Yes | Y80: No | Z80: Yes | AA80: Yes
D81: Recognition Explanation | E81: An asset (cash) has been received (i.e., it is now owned or controlled by the entity) and must be recognized. | F81: An asset (cash) has been received (i.e., it is now owned or controlled by the entity) and must be recognized. A liability (obligation to pay) has been created, and this also must be recognized. | G81: An asset (cash) has been received (i.e., it is now owned or controlled by the entity) and must be recognized. | H81: An asset (building) has been received (i.e., it is now owned or controlled by the entity) and must be recognized. | I81: An asset (building) has been received (i.e., it is now owned or controlled by the entity) and must be recognized. | J81: An asset (goods to resell) has been received (i.e., it is now owned or controlled by the entity) and must be recognized. Another asset (cash) is no longer owned or controlled by the entity and this also must be recognized. | K81: An asset (the right to collect cash) has been created and should be recognized. | L81: An asset (goods to resell) has been received (i.e., it is now owned or controlled by the entity) and must be recognized. A liability (obligation to pay) has been created, and this also must be recognized. | M81: An asset (goods to resell) has been received (i.e., it is now owned or controlled by the entity) and must be recognized. Another asset (cash) is no longer owned or controlled by the entity and this must be recognized. A liability (obligation to pay) has been created, and this also must be recognized. | N81: On asset (cash) has been received and another (the right to collect cash) no longer exists. Either must be recognized. | O81: An asset (cash) has been received and this must be recognized. Also, an obligation to perform services (a future sacrifice) has been created, and this also requires recognition. | P81: Although it is (perhaps) good news, no asset has been been created or received and no obligations have been incurred. This will not be recognized in the accounts. | Q81: This is evidence that an asset (inventory) is no longer owned or controlled by the entity. This must be recognized. | R81: This is evidence that an asset (inventory) is no longer owned or controlled by the entity. This must be recognized. | S81: Although it is (perhaps) good news, no asset has been been created or received and no obligations have been incurred. This will not be recognized in the accounts. | T81: Although it is (perhaps) good news, no asset has been been created or received and no obligations have been incurred. This will not be recognized in the accounts. | U81: Although it is (perhaps) good news, no asset has been been created or received and no obligations have been incurred. This will not be recognized in the accounts. | V81: Although it is (perhaps) good news, no asset has been been created or received and no obligations have been incurred. This will not be recognized in the accounts. | W81: An asset (the right to collect cash) has been created by the performance of services and should be recognized. | X81: One asset (cash) has been received and another (the right to collect cash) no longer exists. Either must be recognized. | Y81: Announcing an intention, without any accompanying formalities, does not create an obligation to pay. This will not be recognized in the accounts. | Z81: The formal declaration of dividends does, at least in the United States, create an obligation to pay them. This will be recognized in the accounts. | AA81: An asset (cash) is no longer owned or controlled by the entity. An obligation has been fulfilled. Either requires recognition.
D82: Cash Flow/Noncash trans CODE | E82: Financing | F82: Financing | G82: Operating | H82: Noncash_Investing_Financing | I82: Noncash_Investing_Financing | J82: Operating | K82: Noncash_Operating | L82: Operating | M82: Operating | N82: Operating | O82: Operating | Q82: Noncash_Operating | R82: Noncash_Financing | W82: Noncash_Operating | X82: Operating | Z82: Noncash_Financing | AA82: Financing
D83: Description if CODE is used | E83: Issued common stock | F83: Got a loan from a bank | G83: Collected from customers | H83: Acquired PP&E with Common Stock | I83: Acquired PP&E by incurring a liability | J83: Paid suppliers | L83: Paid suppliers | M83: Paid suppliers | N83: Collected from customers | O83: Collected from customers | X83: Collected from customers | AA83: Pay dividends
B84: Movement # | C84: Entry Number | D84: Safety Check: #Fields Filled Out | E84: =IF(E237=0,"",IF(E237=INT(E237),"All 4 Fields Nonempty","Make Sure each movement has the 4 fields filled out")) -> All 4 Fields Nonempty | F84: =IF(F237=0,"",IF(F237=INT(F237),"All 4 Fields Nonempty","Make Sure each movement has the 4 fields filled out")) -> All 4 Fields Nonempty | G84: =IF(G237=0,"",IF(G237=INT(G237),"All 4 Fields Nonempty","Make Sure each movement has the 4 fields filled out")) -> All 4 Fields Nonempty | H84: =IF(H237=0,"",IF(H237=INT(H237),"All 4 Fields Nonempty","Make Sure each movement has the 4 fields filled out")) -> All 4 Fields Nonempty | I84: =IF(I237=0,"",IF(I237=INT(I237),"All 4 Fields Nonempty","Make Sure each movement has the 4 fields filled out")) -> All 4 Fields Nonempty | J84: =IF(J237=0,"",IF(J237=INT(J237),"All 4 Fields Nonempty","Make Sure each movement has the 4 fields filled out")) -> All 4 Fields Nonempty | K84: =IF(K237=0,"",IF(K237=INT(K237),"All 4 Fields Nonempty","Make Sure each movement has the 4 fields filled out")) -> All 4 Fields Nonempty | L84: =IF(L237=0,"",IF(L237=INT(L237),"All 4 Fields Nonempty","Make Sure each movement has the 4 fields filled out")) -> All 4 Fields Nonempty | ... AM84: =IF(AM237=0,"",IF(AM237=INT(AM237),"All 4 Fields Nonempty","Make Sure each movement has the 4 fields filled out"))
D85: Safety Check: Debits - Credits | E85: {=IF(ROUND(SUM(IF((E86:E145="Debit")*(ISNUMBER(E87:E146)),E87:E146,0))-SUM(IF((E86:E145="Credit")*(ISNUMBER(E87:E146)),E87:E146,0)),2)=0,0,ROUND(SUM(IF((E86:E145="Debit")*(ISNUMBER(E87:E146)),E87:E146,0))-SUM(IF((E86:E145="Credit")*(ISNUMBER(E87:E146)),E87:E146,0)),2))} -> 0 | F85: {=IF(ROUND(SUM(IF((F86:F145="Debit")*(ISNUMBER(F87:F146)),F87:F146,0))-SUM(IF((F86:F145="Credit")*(ISNUMBER(F87:F146)),F87:F146,0)),2)=0,0,ROUND(SUM(IF((F86:F145="Debit")*(ISNUMBER(F87:F146)),F87:F146,0))-SUM(IF((F86:F145="Credit")*(ISNUMBER(F87:F146)),F87:F146,0)),2))} -> 0 | G85: {=IF(ROUND(SUM(IF((G86:G145="Debit")*(ISNUMBER(G87:G146)),G87:G146,0))-SUM(IF((G86:G145="Credit")*(ISNUMBER(G87:G146)),G87:G146,0)),2)=0,0,ROUND(SUM(IF((G86:G145="Debit")*(ISNUMBER(G87:G146)),G87:G146,0))-SUM(IF((G86:G145="Credit")*(ISNUMBER(G87:G146)),G87:G146,0)),2))} -> 0 | H85: {=IF(ROUND(SUM(IF((H86:H145="Debit")*(ISNUMBER(H87:H146)),H87:H146,0))-SUM(IF((H86:H145="Credit")*(ISNUMBER(H87:H146)),H87:H146,0)),2)=0,0,ROUND(SUM(IF((H86:H145="Debit")*(ISNUMBER(H87:H146)),H87:H146,0))-SUM(IF((H86:H145="Credit")*(ISNUMBER(H87:H146)),H87:H146,0)),2))} -> 0 | I85: {=IF(ROUND(SUM(IF((I86:I145="Debit")*(ISNUMBER(I87:I146)),I87:I146,0))-SUM(IF((I86:I145="Credit")*(ISNUMBER(I87:I146)),I87:I146,0)),2)=0,0,ROUND(SUM(IF((I86:I145="Debit")*(ISNUMBER(I87:I146)),I87:I146,0))-SUM(IF((I86:I145="Credit")*(ISNUMBER(I87:I146)),I87:I146,0)),2))} -> 0 | J85: {=IF(ROUND(SUM(IF((J86:J145="Debit")*(ISNUMBER(J87:J146)),J87:J146,0))-SUM(IF((J86:J145="Credit")*(ISNUMBER(J87:J146)),J87:J146,0)),2)=0,0,ROUND(SUM(IF((J86:J145="Debit")*(ISNUMBER(J87:J146)),J87:J146,0))-SUM(IF((J86:J145="Credit")*(ISNUMBER(J87:J146)),J87:J146,0)),2))} -> 0 | K85: {=IF(ROUND(SUM(IF((K86:K145="Debit")*(ISNUMBER(K87:K146)),K87:K146,0))-SUM(IF((K86:K145="Credit")*(ISNUMBER(K87:K146)),K87:K146,0)),2)=0,0,ROUND(SUM(IF((K86:K145="Debit")*(ISNUMBER(K87:K146)),K87:K146,0))-SUM(IF((K86:K145="Credit")*(ISNUMBER(K87:K146)),K87:K146,0)),2))} -> 0 | L85: {=IF(ROUND(SUM(IF((L86:L145="Debit")*(ISNUMBER(L87:L146)),L87:L146,0))-SUM(IF((L86:L145="Credit")*(ISNUMBER(L87:L146)),L87:L146,0)),2)=0,0,ROUND(SUM(IF((L86:L145="Debit")*(ISNUMBER(L87:L146)),L87:L146,0))-SUM(IF((L86:L145="Credit")*(ISNUMBER(L87:L146)),L87:L146,0)),2))} -> 0 | ... AM85: {=IF(ROUND(SUM(IF((AM86:AM145="Debit")*(ISNUMBER(AM87:AM146)),AM87:AM146,0))-SUM(IF((AM86:AM145="Credit")*(ISNUMBER(AM87:AM146)),AM87:AM146,0)),2)=0,0,ROUND(SUM(IF((AM86:AM145="Debit")*(ISNUMBER(AM87:AM146)),AM87:AM146,0))-SUM(IF((AM86:AM145="Credit")*(ISNUMBER(AM87:AM146)),AM87:AM146,0)),2))} -> 0
B86: 1 | C86: 1.1 | D86: Account Type | E86: Asset | F86: Asset | G86: Asset | H86: Asset | I86: Asset | J86: Asset | K86: Asset | L86: Liability | M86: Asset | N86: Asset | O86: Asset | Q86: Expense | R86: Loss | W86: Asset | X86: Asset | Z86: Equity | AA86: Liability | AN86: =C86 -> 1.1
B87: 1 | C87: 1.2 | D87: Account Name | E87: Cash | F87: Cash | G87: Cash | H87: Property, Plant & Equipment | I87: Property, Plant & Equipment | J87: Inventories | K87: Inventories | L87: Accounts Payable | M87: Inventories | N87: Cash | O87: Cash | Q87: Cost of Goods Sold | R87: Loss from Accidental Destruction of Inventory | W87: Accounts Receivable | X87: Cash | Z87: Retained Earnings | AA87: Dividends Payable | AN87: =C87 -> 1.2
B88: 1 | C88: 1.3 | D88: Debit/Credit | E88: Debit | F88: Debit | G88: Debit | H88: Debit | I88: Debit | J88: Debit | K88: Debit | L88: Debit | M88: Debit | N88: Debit | O88: Debit | Q88: Debit | R88: Debit | W88: Debit | X88: Debit | Z88: Debit | AA88: Debit | AN88: =C88 -> 1.3
B89: 1 | C89: 1.4 | D89: Amount | E89: 50 | F89: 50 | G89: 50 | H89: 50 | I89: 50 | J89: 18 | K89: 18 | L89: 17 | M89: 18 | N89: 18 | O89: 8 | Q89: 6 | R89: 6 | W89: 15 | X89: 15 | Z89: 2 | AA89: 2 | AN89: =C89 -> 1.4
B90: 2 | C90: 2.1 | D90: Account Type | E90: Equity | F90: Liability | G90: Revenue | H90: Equity | I90: Liability | J90: Asset | K90: Liability | L90: Asset | M90: Asset | N90: Revenue | O90: Liability | Q90: Asset | R90: Asset | W90: Revenue | X90: Asset | Z90: Liability | AA90: Asset | AN90: =C90 -> 2.1
B91: 2 | C91: 2.2 | D91: Account Name | E91: Common Stock | F91: Loans Payable | G91: Revenue from Services | H91: Common Stock | I91: Loans Payable | J91: Cash | K91: Accounts Payable | L91: Cash | M91: Cash | N91: Sales | O91: Unearned Revenue | Q91: Inventories | R91: Inventories | W91: Revenue from Services | X91: Accounts Receivable | Z91: Dividends Payable | AA91: Cash | AN91: =C91 -> 2.2
B92: 2 | C92: 2.3 | D92: Debit/Credit | E92: Credit | F92: Credit | G92: Credit | H92: Credit | I92: Credit | J92: Credit | K92: Credit | L92: Credit | M92: Credit | N92: Credit | O92: Credit | Q92: Credit | R92: Credit | W92: Credit | X92: Credit | Z92: Credit | AA92: Credit | AN92: =C92 -> 2.3
B93: 2 | C93: 2.4 | D93: Amount | E93: 50 | F93: 50 | G93: 50 | H93: 50 | I93: 50 | J93: 18 | K93: 18 | L93: 17 | M93: 17 | N93: 18 | O93: 8 | Q93: 6 | R93: 6 | W93: 15 | X93: 15 | Z93: 2 | AA93: 2 | AN93: =C93 -> 2.4
B94: 3 | C94: 3.1 | D94: Account Type | M94: Liability | AN94: =C94 -> 3.1
B95: 3 | C95: 3.2 | D95: Account Name | M95: Accounts Payable | AN95: =C95 -> 3.2
B96: 3 | C96: 3.3 | D96: Debit/Credit | M96: Credit | AN96: =C96 -> 3.3
B97: 3 | C97: 3.4 | D97: Amount | M97: 1 | AN97: =C97 -> 3.4
B98: 4 | C98: 4.1 | D98: Account Type | AN98: =C98 -> 4.1
B99: 4 | C99: 4.2 | D99: Account Name | AN99: =C99 -> 4.2
B100: 4 | C100: 4.3 | D100: Debit/Credit | AN100: =C100 -> 4.3
B101: 4 | C101: 4.4 | D101: Amount | AN101: =C101 -> 4.4
B102: 5 | C102: 5.1 | D102: Account Type | AN102: =C102 -> 5.1
B103: 5 | C103: 5.2 | D103: Account Name | AN103: =C103 -> 5.2
B104: 5 | C104: 5.3 | D104: Debit/Credit | AN104: =C104 -> 5.3
B105: 5 | C105: 5.4 | D105: Amount | AN105: =C105 -> 5.4
B106: 6 | C106: 6.1 | D106: Account Type | AN106: =C106 -> 6.1
B107: 6 | C107: 6.2 | D107: Account Name | AN107: =C107 -> 6.2
B108: 6 | C108: 6.3 | D108: Debit/Credit | AN108: =C108 -> 6.3
B109: 6 | C109: 6.4 | D109: Amount | AN109: =C109 -> 6.4
... B145: 15 | C145: 15.4 | D145: Amount | AN145: =C145 -> 15.4
B150: Beginning Balance Sheet and Unchanged Balance Sheet Accounts
E153: Assets | K153: ASSETS used anywhere
D154: ASSETS on BS but not used in an entry | E154: Account | F154: Amount | G154: IncreasedBy | H154: Num | I154: Current/Non-Current | J154: Abbr | K154: {=AssetUsed} -> Cash
D155: Land | E155: Cash | F155: 0 | G155: =IF(BegBalanceSheet_Assets[[#This Row],[Account]]="","",_xlfn.XLOOKUP(BegBalanceSheet_Assets[[#This Row],[Account]],MD_Asset[Account Name],MD_Asset[IncreasedBy])) -> Debit | H155: 1 | I155: =IF(BegBalanceSheet_Assets[[#This Row],[Account]]="","",_xlfn.XLOOKUP(BegBalanceSheet_Assets[[#This Row],[Account]],MD_Asset[Account Name],MD_Asset[C/NC])) -> C | J155: =IF(BegBalanceSheet_Assets[[#This Row],[Account]]="","",_xlfn.XLOOKUP(BegBalanceSheet_Assets[[#This Row],[Account]],MD_Asset[Account Name],MD_Asset[Abbr])) -> CSH | K155: Accounts Receivable
E156: Accounts Receivable | F156: 0 | G156: =IF(BegBalanceSheet_Assets[[#This Row],[Account]]="","",_xlfn.XLOOKUP(BegBalanceSheet_Assets[[#This Row],[Account]],MD_Asset[Account Name],MD_Asset[IncreasedBy])) -> Debit | H156: 2 | I156: =IF(BegBalanceSheet_Assets[[#This Row],[Account]]="","",_xlfn.XLOOKUP(BegBalanceSheet_Assets[[#This Row],[Account]],MD_Asset[Account Name],MD_Asset[C/NC])) -> C | J156: =IF(BegBalanceSheet_Assets[[#This Row],[Account]]="","",_xlfn.XLOOKUP(BegBalanceSheet_Assets[[#This Row],[Account]],MD_Asset[Account Name],MD_Asset[Abbr])) -> AR | K156: Inventories
E157: Inventories | F157: 0 | G157: =IF(BegBalanceSheet_Assets[[#This Row],[Account]]="","",_xlfn.XLOOKUP(BegBalanceSheet_Assets[[#This Row],[Account]],MD_Asset[Account Name],MD_Asset[IncreasedBy])) -> Debit | H157: 3 | I157: =IF(BegBalanceSheet_Assets[[#This Row],[Account]]="","",_xlfn.XLOOKUP(BegBalanceSheet_Assets[[#This Row],[Account]],MD_Asset[Account Name],MD_Asset[C/NC])) -> C | J157: =IF(BegBalanceSheet_Assets[[#This Row],[Account]]="","",_xlfn.XLOOKUP(BegBalanceSheet_Assets[[#This Row],[Account]],MD_Asset[Account Name],MD_Asset[Abbr])) -> Inv | K157: Property, Plant & Equipment
E158: Property, Plant & Equipment | F158: 0 | G158: =IF(BegBalanceSheet_Assets[[#This Row],[Account]]="","",_xlfn.XLOOKUP(BegBalanceSheet_Assets[[#This Row],[Account]],MD_Asset[Account Name],MD_Asset[IncreasedBy])) -> Debit | H158: 4 | I158: =IF(BegBalanceSheet_Assets[[#This Row],[Account]]="","",_xlfn.XLOOKUP(BegBalanceSheet_Assets[[#This Row],[Account]],MD_Asset[Account Name],MD_Asset[C/NC])) -> NC | J158: =IF(BegBalanceSheet_Assets[[#This Row],[Account]]="","",_xlfn.XLOOKUP(BegBalanceSheet_Assets[[#This Row],[Account]],MD_Asset[Account Name],MD_Asset[Abbr])) -> PPE | K158: Land
E159: Land | F159: 0 | G159: =IF(BegBalanceSheet_Assets[[#This Row],[Account]]="","",_xlfn.XLOOKUP(BegBalanceSheet_Assets[[#This Row],[Account]],MD_Asset[Account Name],MD_Asset[IncreasedBy])) -> Debit | H159: 5 | I159: =IF(BegBalanceSheet_Assets[[#This Row],[Account]]="","",_xlfn.XLOOKUP(BegBalanceSheet_Assets[[#This Row],[Account]],MD_Asset[Account Name],MD_Asset[C/NC])) -> NC | J159: =IF(BegBalanceSheet_Assets[[#This Row],[Account]]="","",_xlfn.XLOOKUP(BegBalanceSheet_Assets[[#This Row],[Account]],MD_Asset[Account Name],MD_Asset[Abbr])) -> LND
G160: =IF(BegBalanceSheet_Assets[[#This Row],[Account]]="","",_xlfn.XLOOKUP(BegBalanceSheet_Assets[[#This Row],[Account]],MD_Asset[Account Name],MD_Asset[IncreasedBy])) | H160: 6 | I160: =IF(BegBalanceSheet_Assets[[#This Row],[Account]]="","",_xlfn.XLOOKUP(BegBalanceSheet_Assets[[#This Row],[Account]],MD_Asset[Account Name],MD_Asset[C/NC])) | J160: =IF(BegBalanceSheet_Assets[[#This Row],[Account]]="","",_xlfn.XLOOKUP(BegBalanceSheet_Assets[[#This Row],[Account]],MD_Asset[Account Name],MD_Asset[Abbr]))
G161: =IF(BegBalanceSheet_Assets[[#This Row],[Account]]="","",_xlfn.XLOOKUP(BegBalanceSheet_Assets[[#This Row],[Account]],MD_Asset[Account Name],MD_Asset[IncreasedBy])) | H161: 7 | I161: =IF(BegBalanceSheet_Assets[[#This Row],[Account]]="","",_xlfn.XLOOKUP(BegBalanceSheet_Assets[[#This Row],[Account]],MD_Asset[Account Name],MD_Asset[C/NC])) | J161: =IF(BegBalanceSheet_Assets[[#This Row],[Account]]="","",_xlfn.XLOOKUP(BegBalanceSheet_Assets[[#This Row],[Account]],MD_Asset[Account Name],MD_Asset[Abbr]))
G162: =IF(BegBalanceSheet_Assets[[#This Row],[Account]]="","",_xlfn.XLOOKUP(BegBalanceSheet_Assets[[#This Row],[Account]],MD_Asset[Account Name],MD_Asset[IncreasedBy])) | H162: 8 | I162: =IF(BegBalanceSheet_Assets[[#This Row],[Account]]="","",_xlfn.XLOOKUP(BegBalanceSheet_Assets[[#This Row],[Account]],MD_Asset[Account Name],MD_Asset[C/NC])) | J162: =IF(BegBalanceSheet_Assets[[#This Row],[Account]]="","",_xlfn.XLOOKUP(BegBalanceSheet_Assets[[#This Row],[Account]],MD_Asset[Account Name],MD_Asset[Abbr]))
G163: =IF(BegBalanceSheet_Assets[[#This Row],[Account]]="","",_xlfn.XLOOKUP(BegBalanceSheet_Assets[[#This Row],[Account]],MD_Asset[Account Name],MD_Asset[IncreasedBy])) | H163: 9 | I163: =IF(BegBalanceSheet_Assets[[#This Row],[Account]]="","",_xlfn.XLOOKUP(BegBalanceSheet_Assets[[#This Row],[Account]],MD_Asset[Account Name],MD_Asset[C/NC])) | J163: =IF(BegBalanceSheet_Assets[[#This Row],[Account]]="","",_xlfn.XLOOKUP(BegBalanceSheet_Assets[[#This Row],[Account]],MD_Asset[Account Name],MD_Asset[Abbr]))
G164: =IF(BegBalanceSheet_Assets[[#This Row],[Account]]="","",_xlfn.XLOOKUP(BegBalanceSheet_Assets[[#This Row],[Account]],MD_Asset[Account Name],MD_Asset[IncreasedBy])) | H164: 10 | I164: =IF(BegBalanceSheet_Assets[[#This Row],[Account]]="","",_xlfn.XLOOKUP(BegBalanceSheet_Assets[[#This Row],[Account]],MD_Asset[Account Name],MD_Asset[C/NC])) | J164: =IF(BegBalanceSheet_Assets[[#This Row],[Account]]="","",_xlfn.XLOOKUP(BegBalanceSheet_Assets[[#This Row],[Account]],MD_Asset[Account Name],MD_Asset[Abbr]))
G165: =IF(BegBalanceSheet_Assets[[#This Row],[Account]]="","",_xlfn.XLOOKUP(BegBalanceSheet_Assets[[#This Row],[Account]],MD_Asset[Account Name],MD_Asset[IncreasedBy])) | H165: 11 | I165: =IF(BegBalanceSheet_Assets[[#This Row],[Account]]="","",_xlfn.XLOOKUP(BegBalanceSheet_Assets[[#This Row],[Account]],MD_Asset[Account Name],MD_Asset[C/NC])) | J165: =IF(BegBalanceSheet_Assets[[#This Row],[Account]]="","",_xlfn.XLOOKUP(BegBalanceSheet_Assets[[#This Row],[Account]],MD_Asset[Account Name],MD_Asset[Abbr]))
...

Sheet JournalAnswer
C2: Transaction # | D2: 32
C3: Transaction Description | L3: X
C4: {=INDEX(ProblemData!D78:AN79,2,D2+1)} -> 0 | L4: X
L5: X
L6: X
L7: X
C9: Journal Entries | G9: Drs | H9: Crs | I9: Diff
G10: =SUM(JournalAnswer[Dr Amt]) -> 393 | H10: =SUM(JournalAnswer[Cr Amt]) -> 393 | I10: =ROUND(G10-H10,2) -> 0
C11: Transaction # | D11: Accnt Type | E11: Debit Account | F11: Credit Account | G11: Dr Amt | H11: Cr Amt | I11: Cash Flow | J11: Movement # | K11: Cash | L11: ref1 | M11: ref2 | N11: ref3
B12: {=_xlfn._xlws.FILTER(ProblemData!$G$284:$G$808,ProblemData!$G$284:$G$808<>0)} -> 1 | C12: =IF(B12="","",B12) -> 1 | D12: =IFERROR(_xlfn.IFNA(INDEX(ProblemData!$C$78:$AM$145,MATCH(J12+0.1,ProblemData!$C$78:$C$145,0),MATCH(C12,ProblemData!$C$78:$AM$78,0)),""),"") -> Asset | E12: =IFERROR(_xlfn.IFNA(IF(INDEX(ProblemData!$C$78:$AM$145,MATCH(J12+0.3,ProblemData!$C$78:$C$145,0),MATCH(C12,ProblemData!$C$78:$AM$78,0))="Debit",INDEX(ProblemData!$C$78:$AM$145,MATCH(J12+0.2,ProblemData!$C$78:$C$145,0),MATCH(C12,ProblemData!$C$78:$AM$78,0)),""),""),"") -> Cash | F12: =IFERROR(_xlfn.IFNA(IF(INDEX(ProblemData!$C$78:$AM$145,MATCH(J12+0.3,ProblemData!$C$78:$C$145,0),MATCH(C12,ProblemData!$C$78:$AM$78,0))="Credit",INDEX(ProblemData!$C$78:$AM$145,MATCH(J12+0.2,ProblemData!$C$78:$C$145,0),MATCH(C12,ProblemData!$C$78:$AM$78,0)),""),""),"") | G12: =_xlfn.IFNA(IF(JournalAnswer[[#This Row],[Debit Account]]<>"",INDEX(ProblemData!$C$78:$AM$145,MATCH(J12+0.4,ProblemData!$C$78:$C$145,0),MATCH(C12,ProblemData!$C$78:$AM$78,0)),""),"") -> 50 | H12: =_xlfn.IFNA(IF(JournalAnswer[[#This Row],[Credit Account]]<>"",INDEX(ProblemData!$C$78:$AM$145,MATCH(J12+0.4,ProblemData!$C$78:$C$145,0),MATCH(C12,ProblemData!$C$78:$AM$78,0)),""),"") | I12: {=IF(JournalAnswer[[#This Row],[Debit Account]]="Cash",INDEX(ProblemData!$E$238:$AM$238,1,JournalAnswer[[#This Row],[Transaction '#]]),IF(JournalAnswer[[#This Row],[Credit Account]]="Cash",INDEX(ProblemData!$E$238:$AM$238,1,JournalAnswer[[#This Row],[Transaction '#]]),""))} -> Financing | J12: =IF(JournalAnswer[[#This Row],[Transaction '#]]="","",IF(JournalAnswer[[#This Row],[Transaction '#]]=C11,J11+1,1)) -> 1 | K12: {=IFERROR(_xlfn.IFS(JournalAnswer[[#This Row],[Debit Account]]="Cash",JournalAnswer[[#This Row],[Dr Amt]],JournalAnswer[[#This Row],[Credit Account]]="Cash",-JournalAnswer[[#This Row],[Cr Amt]]),0)} -> 50 | L12: {=IFERROR(INDEX(ProblemData!$E$239:$AM$239,1,JournalAnswer[[#This Row],[Transaction '#]]),"")} -> ICS | M12: =IF(JournalAnswer[[#This Row],[ref1]]="","",IF(NOT(ISBLANK(JournalAnswer[[#This Row],[Transaction '#]])),JournalAnswer[[#This Row],[ref1]]&JournalAnswer[[#This Row],[Movement '#]],"")) -> ICS1 | N12: =OR(JournalAnswer[[#This Row],[ref1]]="",ISNUMBER(MATCH(JournalAnswer[[#This Row],[ref1]], Operating[Abbr], 0)), "Found", "Not Found"="Found") -> FALSE
B13: 1 | C13: =IF(B13="","",B13) -> 1 | D13: =IFERROR(_xlfn.IFNA(INDEX(ProblemData!$C$78:$AM$145,MATCH(J13+0.1,ProblemData!$C$78:$C$145,0),MATCH(C13,ProblemData!$C$78:$AM$78,0)),""),"") -> Equity | E13: =IFERROR(_xlfn.IFNA(IF(INDEX(ProblemData!$C$78:$AM$145,MATCH(J13+0.3,ProblemData!$C$78:$C$145,0),MATCH(C13,ProblemData!$C$78:$AM$78,0))="Debit",INDEX(ProblemData!$C$78:$AM$145,MATCH(J13+0.2,ProblemData!$C$78:$C$145,0),MATCH(C13,ProblemData!$C$78:$AM$78,0)),""),""),"") | F13: =IFERROR(_xlfn.IFNA(IF(INDEX(ProblemData!$C$78:$AM$145,MATCH(J13+0.3,ProblemData!$C$78:$C$145,0),MATCH(C13,ProblemData!$C$78:$AM$78,0))="Credit",INDEX(ProblemData!$C$78:$AM$145,MATCH(J13+0.2,ProblemData!$C$78:$C$145,0),MATCH(C13,ProblemData!$C$78:$AM$78,0)),""),""),"") -> Common Stock | G13: =_xlfn.IFNA(IF(JournalAnswer[[#This Row],[Debit Account]]<>"",INDEX(ProblemData!$C$78:$AM$145,MATCH(J13+0.4,ProblemData!$C$78:$C$145,0),MATCH(C13,ProblemData!$C$78:$AM$78,0)),""),"") | H13: =_xlfn.IFNA(IF(JournalAnswer[[#This Row],[Credit Account]]<>"",INDEX(ProblemData!$C$78:$AM$145,MATCH(J13+0.4,ProblemData!$C$78:$C$145,0),MATCH(C13,ProblemData!$C$78:$AM$78,0)),""),"") -> 50 | I13: {=IF(JournalAnswer[[#This Row],[Debit Account]]="Cash",INDEX(ProblemData!$E$238:$AM$238,1,JournalAnswer[[#This Row],[Transaction '#]]),IF(JournalAnswer[[#This Row],[Credit Account]]="Cash",INDEX(ProblemData!$E$238:$AM$238,1,JournalAnswer[[#This Row],[Transaction '#]]),""))} | J13: =IF(JournalAnswer[[#This Row],[Transaction '#]]="","",IF(JournalAnswer[[#This Row],[Transaction '#]]=C12,J12+1,1)) -> 2 | K13: {=IFERROR(_xlfn.IFS(JournalAnswer[[#This Row],[Debit Account]]="Cash",JournalAnswer[[#This Row],[Dr Amt]],JournalAnswer[[#This Row],[Credit Account]]="Cash",-JournalAnswer[[#This Row],[Cr Amt]]),0)} -> 0 | L13: {=IFERROR(INDEX(ProblemData!$E$239:$AM$239,1,JournalAnswer[[#This Row],[Transaction '#]]),"")} -> ICS | M13: =IF(JournalAnswer[[#This Row],[ref1]]="","",IF(NOT(ISBLANK(JournalAnswer[[#This Row],[Transaction '#]])),JournalAnswer[[#This Row],[ref1]]&JournalAnswer[[#This Row],[Movement '#]],"")) -> ICS2 | N13: =OR(JournalAnswer[[#This Row],[ref1]]="",ISNUMBER(MATCH(JournalAnswer[[#This Row],[ref1]], Operating[Abbr], 0)), "Found", "Not Found"="Found") -> FALSE
B14: 2 | C14: =IF(B14="","",B14) -> 2 | D14: =IFERROR(_xlfn.IFNA(INDEX(ProblemData!$C$78:$AM$145,MATCH(J14+0.1,ProblemData!$C$78:$C$145,0),MATCH(C14,ProblemData!$C$78:$AM$78,0)),""),"") -> Asset | E14: =IFERROR(_xlfn.IFNA(IF(INDEX(ProblemData!$C$78:$AM$145,MATCH(J14+0.3,ProblemData!$C$78:$C$145,0),MATCH(C14,ProblemData!$C$78:$AM$78,0))="Debit",INDEX(ProblemData!$C$78:$AM$145,MATCH(J14+0.2,ProblemData!$C$78:$C$145,0),MATCH(C14,ProblemData!$C$78:$AM$78,0)),""),""),"") -> Cash | F14: =IFERROR(_xlfn.IFNA(IF(INDEX(ProblemData!$C$78:$AM$145,MATCH(J14+0.3,ProblemData!$C$78:$C$145,0),MATCH(C14,ProblemData!$C$78:$AM$78,0))="Credit",INDEX(ProblemData!$C$78:$AM$145,MATCH(J14+0.2,ProblemData!$C$78:$C$145,0),MATCH(C14,ProblemData!$C$78:$AM$78,0)),""),""),"") | G14: =_xlfn.IFNA(IF(JournalAnswer[[#This Row],[Debit Account]]<>"",INDEX(ProblemData!$C$78:$AM$145,MATCH(J14+0.4,ProblemData!$C$78:$C$145,0),MATCH(C14,ProblemData!$C$78:$AM$78,0)),""),"") -> 50 | H14: =_xlfn.IFNA(IF(JournalAnswer[[#This Row],[Credit Account]]<>"",INDEX(ProblemData!$C$78:$AM$145,MATCH(J14+0.4,ProblemData!$C$78:$C$145,0),MATCH(C14,ProblemData!$C$78:$AM$78,0)),""),"") | I14: {=IF(JournalAnswer[[#This Row],[Debit Account]]="Cash",INDEX(ProblemData!$E$238:$AM$238,1,JournalAnswer[[#This Row],[Transaction '#]]),IF(JournalAnswer[[#This Row],[Credit Account]]="Cash",INDEX(ProblemData!$E$238:$AM$238,1,JournalAnswer[[#This Row],[Transaction '#]]),""))} -> Financing | J14: =IF(JournalAnswer[[#This Row],[Transaction '#]]="","",IF(JournalAnswer[[#This Row],[Transaction '#]]=C13,J13+1,1)) -> 1 | K14: {=IFERROR(_xlfn.IFS(JournalAnswer[[#This Row],[Debit Account]]="Cash",JournalAnswer[[#This Row],[Dr Amt]],JournalAnswer[[#This Row],[Credit Account]]="Cash",-JournalAnswer[[#This Row],[Cr Amt]]),0)} -> 50 | L14: {=IFERROR(INDEX(ProblemData!$E$239:$AM$239,1,JournalAnswer[[#This Row],[Transaction '#]]),"")} -> GL | M14: =IF(JournalAnswer[[#This Row],[ref1]]="","",IF(NOT(ISBLANK(JournalAnswer[[#This Row],[Transaction '#]])),JournalAnswer[[#This Row],[ref1]]&JournalAnswer[[#This Row],[Movement '#]],"")) -> GL1 | N14: =OR(JournalAnswer[[#This Row],[ref1]]="",ISNUMBER(MATCH(JournalAnswer[[#This Row],[ref1]], Operating[Abbr], 0)), "Found", "Not Found"="Found") -> FALSE
B15: 2 | C15: =IF(B15="","",B15) -> 2 | D15: =IFERROR(_xlfn.IFNA(INDEX(ProblemData!$C$78:$AM$145,MATCH(J15+0.1,ProblemData!$C$78:$C$145,0),MATCH(C15,ProblemData!$C$78:$AM$78,0)),""),"") -> Liability | E15: =IFERROR(_xlfn.IFNA(IF(INDEX(ProblemData!$C$78:$AM$145,MATCH(J15+0.3,ProblemData!$C$78:$C$145,0),MATCH(C15,ProblemData!$C$78:$AM$78,0))="Debit",INDEX(ProblemData!$C$78:$AM$145,MATCH(J15+0.2,ProblemData!$C$78:$C$145,0),MATCH(C15,ProblemData!$C$78:$AM$78,0)),""),""),"") | F15: =IFERROR(_xlfn.IFNA(IF(INDEX(ProblemData!$C$78:$AM$145,MATCH(J15+0.3,ProblemData!$C$78:$C$145,0),MATCH(C15,ProblemData!$C$78:$AM$78,0))="Credit",INDEX(ProblemData!$C$78:$AM$145,MATCH(J15+0.2,ProblemData!$C$78:$C$145,0),MATCH(C15,ProblemData!$C$78:$AM$78,0)),""),""),"") -> Loans Payable | G15: =_xlfn.IFNA(IF(JournalAnswer[[#This Row],[Debit Account]]<>"",INDEX(ProblemData!$C$78:$AM$145,MATCH(J15+0.4,ProblemData!$C$78:$C$145,0),MATCH(C15,ProblemData!$C$78:$AM$78,0)),""),"") | H15: =_xlfn.IFNA(IF(JournalAnswer[[#This Row],[Credit Account]]<>"",INDEX(ProblemData!$C$78:$AM$145,MATCH(J15+0.4,ProblemData!$C$78:$C$145,0),MATCH(C15,ProblemData!$C$78:$AM$78,0)),""),"") -> 50 | I15: {=IF(JournalAnswer[[#This Row],[Debit Account]]="Cash",INDEX(ProblemData!$E$238:$AM$238,1,JournalAnswer[[#This Row],[Transaction '#]]),IF(JournalAnswer[[#This Row],[Credit Account]]="Cash",INDEX(ProblemData!$E$238:$AM$238,1,JournalAnswer[[#This Row],[Transaction '#]]),""))} | J15: =IF(JournalAnswer[[#This Row],[Transaction '#]]="","",IF(JournalAnswer[[#This Row],[Transaction '#]]=C14,J14+1,1)) -> 2 | K15: {=IFERROR(_xlfn.IFS(JournalAnswer[[#This Row],[Debit Account]]="Cash",JournalAnswer[[#This Row],[Dr Amt]],JournalAnswer[[#This Row],[Credit Account]]="Cash",-JournalAnswer[[#This Row],[Cr Amt]]),0)} -> 0 | L15: {=IFERROR(INDEX(ProblemData!$E$239:$AM$239,1,JournalAnswer[[#This Row],[Transaction '#]]),"")} -> GL | M15: =IF(JournalAnswer[[#This Row],[ref1]]="","",IF(NOT(ISBLANK(JournalAnswer[[#This Row],[Transaction '#]])),JournalAnswer[[#This Row],[ref1]]&JournalAnswer[[#This Row],[Movement '#]],"")) -> GL2 | N15: =OR(JournalAnswer[[#This Row],[ref1]]="",ISNUMBER(MATCH(JournalAnswer[[#This Row],[ref1]], Operating[Abbr], 0)), "Found", "Not Found"="Found") -> FALSE
B16: 3 | C16: =IF(B16="","",B16) -> 3 | D16: =IFERROR(_xlfn.IFNA(INDEX(ProblemData!$C$78:$AM$145,MATCH(J16+0.1,ProblemData!$C$78:$C$145,0),MATCH(C16,ProblemData!$C$78:$AM$78,0)),""),"") -> Asset | E16: =IFERROR(_xlfn.IFNA(IF(INDEX(ProblemData!$C$78:$AM$145,MATCH(J16+0.3,ProblemData!$C$78:$C$145,0),MATCH(C16,ProblemData!$C$78:$AM$78,0))="Debit",INDEX(ProblemData!$C$78:$AM$145,MATCH(J16+0.2,ProblemData!$C$78:$C$145,0),MATCH(C16,ProblemData!$C$78:$AM$78,0)),""),""),"") -> Cash | F16: =IFERROR(_xlfn.IFNA(IF(INDEX(ProblemData!$C$78:$AM$145,MATCH(J16+0.3,ProblemData!$C$78:$C$145,0),MATCH(C16,ProblemData!$C$78:$AM$78,0))="Credit",INDEX(ProblemData!$C$78:$AM$145,MATCH(J16+0.2,ProblemData!$C$78:$C$145,0),MATCH(C16,ProblemData!$C$78:$AM$78,0)),""),""),"") | G16: =_xlfn.IFNA(IF(JournalAnswer[[#This Row],[Debit Account]]<>"",INDEX(ProblemData!$C$78:$AM$145,MATCH(J16+0.4,ProblemData!$C$78:$C$145,0),MATCH(C16,ProblemData!$C$78:$AM$78,0)),""),"") -> 50 | H16: =_xlfn.IFNA(IF(JournalAnswer[[#This Row],[Credit Account]]<>"",INDEX(ProblemData!$C$78:$AM$145,MATCH(J16+0.4,ProblemData!$C$78:$C$145,0),MATCH(C16,ProblemData!$C$78:$AM$78,0)),""),"") | I16: {=IF(JournalAnswer[[#This Row],[Debit Account]]="Cash",INDEX(ProblemData!$E$238:$AM$238,1,JournalAnswer[[#This Row],[Transaction '#]]),IF(JournalAnswer[[#This Row],[Credit Account]]="Cash",INDEX(ProblemData!$E$238:$AM$238,1,JournalAnswer[[#This Row],[Transaction '#]]),""))} -> Operating | J16: =IF(JournalAnswer[[#This Row],[Transaction '#]]="","",IF(JournalAnswer[[#This Row],[Transaction '#]]=C15,J15+1,1)) -> 1 | K16: {=IFERROR(_xlfn.IFS(JournalAnswer[[#This Row],[Debit Account]]="Cash",JournalAnswer[[#This Row],[Dr Amt]],JournalAnswer[[#This Row],[Credit Account]]="Cash",-JournalAnswer[[#This Row],[Cr Amt]]),0)} -> 50 | L16: {=IFERROR(INDEX(ProblemData!$E$239:$AM$239,1,JournalAnswer[[#This Row],[Transaction '#]]),"")} -> ColC | M16: =IF(JournalAnswer[[#This Row],[ref1]]="","",IF(NOT(ISBLANK(JournalAnswer[[#This Row],[Transaction '#]])),JournalAnswer[[#This Row],[ref1]]&JournalAnswer[[#This Row],[Movement '#]],"")) -> ColC1 | N16: =OR(JournalAnswer[[#This Row],[ref1]]="",ISNUMBER(MATCH(JournalAnswer[[#This Row],[ref1]], Operating[Abbr], 0)), "Found", "Not Found"="Found") -> TRUE
B17: 3 | C17: =IF(B17="","",B17) -> 3 | D17: =IFERROR(_xlfn.IFNA(INDEX(ProblemData!$C$78:$AM$145,MATCH(J17+0.1,ProblemData!$C$78:$C$145,0),MATCH(C17,ProblemData!$C$78:$AM$78,0)),""),"") -> Revenue | E17: =IFERROR(_xlfn.IFNA(IF(INDEX(ProblemData!$C$78:$AM$145,MATCH(J17+0.3,ProblemData!$C$78:$C$145,0),MATCH(C17,ProblemData!$C$78:$AM$78,0))="Debit",INDEX(ProblemData!$C$78:$AM$145,MATCH(J17+0.2,ProblemData!$C$78:$C$145,0),MATCH(C17,ProblemData!$C$78:$AM$78,0)),""),""),"") | F17: =IFERROR(_xlfn.IFNA(IF(INDEX(ProblemData!$C$78:$AM$145,MATCH(J17+0.3,ProblemData!$C$78:$C$145,0),MATCH(C17,ProblemData!$C$78:$AM$78,0))="Credit",INDEX(ProblemData!$C$78:$AM$145,MATCH(J17+0.2,ProblemData!$C$78:$C$145,0),MATCH(C17,ProblemData!$C$78:$AM$78,0)),""),""),"") -> Revenue from Services | G17: =_xlfn.IFNA(IF(JournalAnswer[[#This Row],[Debit Account]]<>"",INDEX(ProblemData!$C$78:$AM$145,MATCH(J17+0.4,ProblemData!$C$78:$C$145,0),MATCH(C17,ProblemData!$C$78:$AM$78,0)),""),"") | H17: =_xlfn.IFNA(IF(JournalAnswer[[#This Row],[Credit Account]]<>"",INDEX(ProblemData!$C$78:$AM$145,MATCH(J17+0.4,ProblemData!$C$78:$C$145,0),MATCH(C17,ProblemData!$C$78:$AM$78,0)),""),"") -> 50 | I17: {=IF(JournalAnswer[[#This Row],[Debit Account]]="Cash",INDEX(ProblemData!$E$238:$AM$238,1,JournalAnswer[[#This Row],[Transaction '#]]),IF(JournalAnswer[[#This Row],[Credit Account]]="Cash",INDEX(ProblemData!$E$238:$AM$238,1,JournalAnswer[[#This Row],[Transaction '#]]),""))} | J17: =IF(JournalAnswer[[#This Row],[Transaction '#]]="","",IF(JournalAnswer[[#This Row],[Transaction '#]]=C16,J16+1,1)) -> 2 | K17: {=IFERROR(_xlfn.IFS(JournalAnswer[[#This Row],[Debit Account]]="Cash",JournalAnswer[[#This Row],[Dr Amt]],JournalAnswer[[#This Row],[Credit Account]]="Cash",-JournalAnswer[[#This Row],[Cr Amt]]),0)} -> 0 | L17: {=IFERROR(INDEX(ProblemData!$E$239:$AM$239,1,JournalAnswer[[#This Row],[Transaction '#]]),"")} -> ColC | M17: =IF(JournalAnswer[[#This Row],[ref1]]="","",IF(NOT(ISBLANK(JournalAnswer[[#This Row],[Transaction '#]])),JournalAnswer[[#This Row],[ref1]]&JournalAnswer[[#This Row],[Movement '#]],"")) -> ColC2 | N17: =OR(JournalAnswer[[#This Row],[ref1]]="",ISNUMBER(MATCH(JournalAnswer[[#This Row],[ref1]], Operating[Abbr], 0)), "Found", "Not Found"="Found") -> TRUE
B18: 4 | C18: =IF(B18="","",B18) -> 4 | D18: =IFERROR(_xlfn.IFNA(INDEX(ProblemData!$C$78:$AM$145,MATCH(J18+0.1,ProblemData!$C$78:$C$145,0),MATCH(C18,ProblemData!$C$78:$AM$78,0)),""),"") -> Asset | E18: =IFERROR(_xlfn.IFNA(IF(INDEX(ProblemData!$C$78:$AM$145,MATCH(J18+0.3,ProblemData!$C$78:$C$145,0),MATCH(C18,ProblemData!$C$78:$AM$78,0))="Debit",INDEX(ProblemData!$C$78:$AM$145,MATCH(J18+0.2,ProblemData!$C$78:$C$145,0),MATCH(C18,ProblemData!$C$78:$AM$78,0)),""),""),"") -> Property, Plant & Equipment | F18: =IFERROR(_xlfn.IFNA(IF(INDEX(ProblemData!$C$78:$AM$145,MATCH(J18+0.3,ProblemData!$C$78:$C$145,0),MATCH(C18,ProblemData!$C$78:$AM$78,0))="Credit",INDEX(ProblemData!$C$78:$AM$145,MATCH(J18+0.2,ProblemData!$C$78:$C$145,0),MATCH(C18,ProblemData!$C$78:$AM$78,0)),""),""),"") | G18: =_xlfn.IFNA(IF(JournalAnswer[[#This Row],[Debit Account]]<>"",INDEX(ProblemData!$C$78:$AM$145,MATCH(J18+0.4,ProblemData!$C$78:$C$145,0),MATCH(C18,ProblemData!$C$78:$AM$78,0)),""),"") -> 50 | H18: =_xlfn.IFNA(IF(JournalAnswer[[#This Row],[Credit Account]]<>"",INDEX(ProblemData!$C$78:$AM$145,MATCH(J18+0.4,ProblemData!$C$78:$C$145,0),MATCH(C18,ProblemData!$C$78:$AM$78,0)),""),"") | I18: {=IF(JournalAnswer[[#This Row],[Debit Account]]="Cash",INDEX(ProblemData!$E$238:$AM$238,1,JournalAnswer[[#This Row],[Transaction '#]]),IF(JournalAnswer[[#This Row],[Credit Account]]="Cash",INDEX(ProblemData!$E$238:$AM$238,1,JournalAnswer[[#This Row],[Transaction '#]]),""))} | J18: =IF(JournalAnswer[[#This Row],[Transaction '#]]="","",IF(JournalAnswer[[#This Row],[Transaction '#]]=C17,J17+1,1)) -> 1 | K18: {=IFERROR(_xlfn.IFS(JournalAnswer[[#This Row],[Debit Account]]="Cash",JournalAnswer[[#This Row],[Dr Amt]],JournalAnswer[[#This Row],[Credit Account]]="Cash",-JournalAnswer[[#This Row],[Cr Amt]]),0)} -> 0 | L18: {=IFERROR(INDEX(ProblemData!$E$239:$AM$239,1,JournalAnswer[[#This Row],[Transaction '#]]),"")} -> PPEfCS | M18: =IF(JournalAnswer[[#This Row],[ref1]]="","",IF(NOT(ISBLANK(JournalAnswer[[#This Row],[Transaction '#]])),JournalAnswer[[#This Row],[ref1]]&JournalAnswer[[#This Row],[Movement '#]],"")) -> PPEfCS1 | N18: =OR(JournalAnswer[[#This Row],[ref1]]="",ISNUMBER(MATCH(JournalAnswer[[#This Row],[ref1]], Operating[Abbr], 0)), "Found", "Not Found"="Found") -> FALSE
B19: 4 | C19: =IF(B19="","",B19) -> 4 | D19: =IFERROR(_xlfn.IFNA(INDEX(ProblemData!$C$78:$AM$145,MATCH(J19+0.1,ProblemData!$C$78:$C$145,0),MATCH(C19,ProblemData!$C$78:$AM$78,0)),""),"") -> Equity | E19: =IFERROR(_xlfn.IFNA(IF(INDEX(ProblemData!$C$78:$AM$145,MATCH(J19+0.3,ProblemData!$C$78:$C$145,0),MATCH(C19,ProblemData!$C$78:$AM$78,0))="Debit",INDEX(ProblemData!$C$78:$AM$145,MATCH(J19+0.2,ProblemData!$C$78:$C$145,0),MATCH(C19,ProblemData!$C$78:$AM$78,0)),""),""),"") | F19: =IFERROR(_xlfn.IFNA(IF(INDEX(ProblemData!$C$78:$AM$145,MATCH(J19+0.3,ProblemData!$C$78:$C$145,0),MATCH(C19,ProblemData!$C$78:$AM$78,0))="Credit",INDEX(ProblemData!$C$78:$AM$145,MATCH(J19+0.2,ProblemData!$C$78:$C$145,0),MATCH(C19,ProblemData!$C$78:$AM$78,0)),""),""),"") -> Common Stock | G19: =_xlfn.IFNA(IF(JournalAnswer[[#This Row],[Debit Account]]<>"",INDEX(ProblemData!$C$78:$AM$145,MATCH(J19+0.4,ProblemData!$C$78:$C$145,0),MATCH(C19,ProblemData!$C$78:$AM$78,0)),""),"") | H19: =_xlfn.IFNA(IF(JournalAnswer[[#This Row],[Credit Account]]<>"",INDEX(ProblemData!$C$78:$AM$145,MATCH(J19+0.4,ProblemData!$C$78:$C$145,0),MATCH(C19,ProblemData!$C$78:$AM$78,0)),""),"") -> 50 | I19: {=IF(JournalAnswer[[#This Row],[Debit Account]]="Cash",INDEX(ProblemData!$E$238:$AM$238,1,JournalAnswer[[#This Row],[Transaction '#]]),IF(JournalAnswer[[#This Row],[Credit Account]]="Cash",INDEX(ProblemData!$E$238:$AM$238,1,JournalAnswer[[#This Row],[Transaction '#]]),""))} | J19: =IF(JournalAnswer[[#This Row],[Transaction '#]]="","",IF(JournalAnswer[[#This Row],[Transaction '#]]=C18,J18+1,1)) -> 2 | K19: {=IFERROR(_xlfn.IFS(JournalAnswer[[#This Row],[Debit Account]]="Cash",JournalAnswer[[#This Row],[Dr Amt]],JournalAnswer[[#This Row],[Credit Account]]="Cash",-JournalAnswer[[#This Row],[Cr Amt]]),0)} -> 0 | L19: {=IFERROR(INDEX(ProblemData!$E$239:$AM$239,1,JournalAnswer[[#This Row],[Transaction '#]]),"")} -> PPEfCS | M19: =IF(JournalAnswer[[#This Row],[ref1]]="","",IF(NOT(ISBLANK(JournalAnswer[[#This Row],[Transaction '#]])),JournalAnswer[[#This Row],[ref1]]&JournalAnswer[[#This Row],[Movement '#]],"")) -> PPEfCS2 | N19: =OR(JournalAnswer[[#This Row],[ref1]]="",ISNUMBER(MATCH(JournalAnswer[[#This Row],[ref1]], Operating[Abbr], 0)), "Found", "Not Found"="Found") -> FALSE
B20: 5 | C20: =IF(B20="","",B20) -> 5 | D20: =IFERROR(_xlfn.IFNA(INDEX(ProblemData!$C$78:$AM$145,MATCH(J20+0.1,ProblemData!$C$78:$C$145,0),MATCH(C20,ProblemData!$C$78:$AM$78,0)),""),"") -> Asset | E20: =IFERROR(_xlfn.IFNA(IF(INDEX(ProblemData!$C$78:$AM$145,MATCH(J20+0.3,ProblemData!$C$78:$C$145,0),MATCH(C20,ProblemData!$C$78:$AM$78,0))="Debit",INDEX(ProblemData!$C$78:$AM$145,MATCH(J20+0.2,ProblemData!$C$78:$C$145,0),MATCH(C20,ProblemData!$C$78:$AM$78,0)),""),""),"") -> Property, Plant & Equipment | F20: =IFERROR(_xlfn.IFNA(IF(INDEX(ProblemData!$C$78:$AM$145,MATCH(J20+0.3,ProblemData!$C$78:$C$145,0),MATCH(C20,ProblemData!$C$78:$AM$78,0))="Credit",INDEX(ProblemData!$C$78:$AM$145,MATCH(J20+0.2,ProblemData!$C$78:$C$145,0),MATCH(C20,ProblemData!$C$78:$AM$78,0)),""),""),"") | G20: =_xlfn.IFNA(IF(JournalAnswer[[#This Row],[Debit Account]]<>"",INDEX(ProblemData!$C$78:$AM$145,MATCH(J20+0.4,ProblemData!$C$78:$C$145,0),MATCH(C20,ProblemData!$C$78:$AM$78,0)),""),"") -> 50 | H20: =_xlfn.IFNA(IF(JournalAnswer[[#This Row],[Credit Account]]<>"",INDEX(ProblemData!$C$78:$AM$145,MATCH(J20+0.4,ProblemData!$C$78:$C$145,0),MATCH(C20,ProblemData!$C$78:$AM$78,0)),""),"") | I20: {=IF(JournalAnswer[[#This Row],[Debit Account]]="Cash",INDEX(ProblemData!$E$238:$AM$238,1,JournalAnswer[[#This Row],[Transaction '#]]),IF(JournalAnswer[[#This Row],[Credit Account]]="Cash",INDEX(ProblemData!$E$238:$AM$238,1,JournalAnswer[[#This Row],[Transaction '#]]),""))} | J20: =IF(JournalAnswer[[#This Row],[Transaction '#]]="","",IF(JournalAnswer[[#This Row],[Transaction '#]]=C19,J19+1,1)) -> 1 | K20: {=IFERROR(_xlfn.IFS(JournalAnswer[[#This Row],[Debit Account]]="Cash",JournalAnswer[[#This Row],[Dr Amt]],JournalAnswer[[#This Row],[Credit Account]]="Cash",-JournalAnswer[[#This Row],[Cr Amt]]),0)} -> 0 | L20: {=IFERROR(INDEX(ProblemData!$E$239:$AM$239,1,JournalAnswer[[#This Row],[Transaction '#]]),"")} -> PPEfL | M20: =IF(JournalAnswer[[#This Row],[ref1]]="","",IF(NOT(ISBLANK(JournalAnswer[[#This Row],[Transaction '#]])),JournalAnswer[[#This Row],[ref1]]&JournalAnswer[[#This Row],[Movement '#]],"")) -> PPEfL1 | N20: =OR(JournalAnswer[[#This Row],[ref1]]="",ISNUMBER(MATCH(JournalAnswer[[#This Row],[ref1]], Operating[Abbr], 0)), "Found", "Not Found"="Found") -> FALSE
B21: 5 | C21: =IF(B21="","",B21) -> 5 | D21: =IFERROR(_xlfn.IFNA(INDEX(ProblemData!$C$78:$AM$145,MATCH(J21+0.1,ProblemData!$C$78:$C$145,0),MATCH(C21,ProblemData!$C$78:$AM$78,0)),""),"") -> Liability | E21: =IFERROR(_xlfn.IFNA(IF(INDEX(ProblemData!$C$78:$AM$145,MATCH(J21+0.3,ProblemData!$C$78:$C$145,0),MATCH(C21,ProblemData!$C$78:$AM$78,0))="Debit",INDEX(ProblemData!$C$78:$AM$145,MATCH(J21+0.2,ProblemData!$C$78:$C$145,0),MATCH(C21,ProblemData!$C$78:$AM$78,0)),""),""),"") | F21: =IFERROR(_xlfn.IFNA(IF(INDEX(ProblemData!$C$78:$AM$145,MATCH(J21+0.3,ProblemData!$C$78:$C$145,0),MATCH(C21,ProblemData!$C$78:$AM$78,0))="Credit",INDEX(ProblemData!$C$78:$AM$145,MATCH(J21+0.2,ProblemData!$C$78:$C$145,0),MATCH(C21,ProblemData!$C$78:$AM$78,0)),""),""),"") -> Loans Payable | G21: =_xlfn.IFNA(IF(JournalAnswer[[#This Row],[Debit Account]]<>"",INDEX(ProblemData!$C$78:$AM$145,MATCH(J21+0.4,ProblemData!$C$78:$C$145,0),MATCH(C21,ProblemData!$C$78:$AM$78,0)),""),"") | H21: =_xlfn.IFNA(IF(JournalAnswer[[#This Row],[Credit Account]]<>"",INDEX(ProblemData!$C$78:$AM$145,MATCH(J21+0.4,ProblemData!$C$78:$C$145,0),MATCH(C21,ProblemData!$C$78:$AM$78,0)),""),"") -> 50 | I21: {=IF(JournalAnswer[[#This Row],[Debit Account]]="Cash",INDEX(ProblemData!$E$238:$AM$238,1,JournalAnswer[[#This Row],[Transaction '#]]),IF(JournalAnswer[[#This Row],[Credit Account]]="Cash",INDEX(ProblemData!$E$238:$AM$238,1,JournalAnswer[[#This Row],[Transaction '#]]),""))} | J21: =IF(JournalAnswer[[#This Row],[Transaction '#]]="","",IF(JournalAnswer[[#This Row],[Transaction '#]]=C20,J20+1,1)) -> 2 | K21: {=IFERROR(_xlfn.IFS(JournalAnswer[[#This Row],[Debit Account]]="Cash",JournalAnswer[[#This Row],[Dr Amt]],JournalAnswer[[#This Row],[Credit Account]]="Cash",-JournalAnswer[[#This Row],[Cr Amt]]),0)} -> 0 | L21: {=IFERROR(INDEX(ProblemData!$E$239:$AM$239,1,JournalAnswer[[#This Row],[Transaction '#]]),"")} -> PPEfL | M21: =IF(JournalAnswer[[#This Row],[ref1]]="","",IF(NOT(ISBLANK(JournalAnswer[[#This Row],[Transaction '#]])),JournalAnswer[[#This Row],[ref1]]&JournalAnswer[[#This Row],[Movement '#]],"")) -> PPEfL2 | N21: =OR(JournalAnswer[[#This Row],[ref1]]="",ISNUMBER(MATCH(JournalAnswer[[#This Row],[ref1]], Operating[Abbr], 0)), "Found", "Not Found"="Found") -> FALSE
B22: 6 | C22: =IF(B22="","",B22) -> 6 | D22: =IFERROR(_xlfn.IFNA(INDEX(ProblemData!$C$78:$AM$145,MATCH(J22+0.1,ProblemData!$C$78:$C$145,0),MATCH(C22,ProblemData!$C$78:$AM$78,0)),""),"") -> Asset | E22: =IFERROR(_xlfn.IFNA(IF(INDEX(ProblemData!$C$78:$AM$145,MATCH(J22+0.3,ProblemData!$C$78:$C$145,0),MATCH(C22,ProblemData!$C$78:$AM$78,0))="Debit",INDEX(ProblemData!$C$78:$AM$145,MATCH(J22+0.2,ProblemData!$C$78:$C$145,0),MATCH(C22,ProblemData!$C$78:$AM$78,0)),""),""),"") -> Inventories | F22: =IFERROR(_xlfn.IFNA(IF(INDEX(ProblemData!$C$78:$AM$145,MATCH(J22+0.3,ProblemData!$C$78:$C$145,0),MATCH(C22,ProblemData!$C$78:$AM$78,0))="Credit",INDEX(ProblemData!$C$78:$AM$145,MATCH(J22+0.2,ProblemData!$C$78:$C$145,0),MATCH(C22,ProblemData!$C$78:$AM$78,0)),""),""),"") | G22: =_xlfn.IFNA(IF(JournalAnswer[[#This Row],[Debit Account]]<>"",INDEX(ProblemData!$C$78:$AM$145,MATCH(J22+0.4,ProblemData!$C$78:$C$145,0),MATCH(C22,ProblemData!$C$78:$AM$78,0)),""),"") -> 18 | H22: =_xlfn.IFNA(IF(JournalAnswer[[#This Row],[Credit Account]]<>"",INDEX(ProblemData!$C$78:$AM$145,MATCH(J22+0.4,ProblemData!$C$78:$C$145,0),MATCH(C22,ProblemData!$C$78:$AM$78,0)),""),"") | I22: {=IF(JournalAnswer[[#This Row],[Debit Account]]="Cash",INDEX(ProblemData!$E$238:$AM$238,1,JournalAnswer[[#This Row],[Transaction '#]]),IF(JournalAnswer[[#This Row],[Credit Account]]="Cash",INDEX(ProblemData!$E$238:$AM$238,1,JournalAnswer[[#This Row],[Transaction '#]]),""))} | J22: =IF(JournalAnswer[[#This Row],[Transaction '#]]="","",IF(JournalAnswer[[#This Row],[Transaction '#]]=C21,J21+1,1)) -> 1 | K22: {=IFERROR(_xlfn.IFS(JournalAnswer[[#This Row],[Debit Account]]="Cash",JournalAnswer[[#This Row],[Dr Amt]],JournalAnswer[[#This Row],[Credit Account]]="Cash",-JournalAnswer[[#This Row],[Cr Amt]]),0)} -> 0 | L22: {=IFERROR(INDEX(ProblemData!$E$239:$AM$239,1,JournalAnswer[[#This Row],[Transaction '#]]),"")} -> PdS | M22: =IF(JournalAnswer[[#This Row],[ref1]]="","",IF(NOT(ISBLANK(JournalAnswer[[#This Row],[Transaction '#]])),JournalAnswer[[#This Row],[ref1]]&JournalAnswer[[#This Row],[Movement '#]],"")) -> PdS1 | N22: =OR(JournalAnswer[[#This Row],[ref1]]="",ISNUMBER(MATCH(JournalAnswer[[#This Row],[ref1]], Operating[Abbr], 0)), "Found", "Not Found"="Found") -> TRUE
B23: 6 | C23: =IF(B23="","",B23) -> 6 | D23: =IFERROR(_xlfn.IFNA(INDEX(ProblemData!$C$78:$AM$145,MATCH(J23+0.1,ProblemData!$C$78:$C$145,0),MATCH(C23,ProblemData!$C$78:$AM$78,0)),""),"") -> Asset | E23: =IFERROR(_xlfn.IFNA(IF(INDEX(ProblemData!$C$78:$AM$145,MATCH(J23+0.3,ProblemData!$C$78:$C$145,0),MATCH(C23,ProblemData!$C$78:$AM$78,0))="Debit",INDEX(ProblemData!$C$78:$AM$145,MATCH(J23+0.2,ProblemData!$C$78:$C$145,0),MATCH(C23,ProblemData!$C$78:$AM$78,0)),""),""),"") | F23: =IFERROR(_xlfn.IFNA(IF(INDEX(ProblemData!$C$78:$AM$145,MATCH(J23+0.3,ProblemData!$C$78:$C$145,0),MATCH(C23,ProblemData!$C$78:$AM$78,0))="Credit",INDEX(ProblemData!$C$78:$AM$145,MATCH(J23+0.2,ProblemData!$C$78:$C$145,0),MATCH(C23,ProblemData!$C$78:$AM$78,0)),""),""),"") -> Cash | G23: =_xlfn.IFNA(IF(JournalAnswer[[#This Row],[Debit Account]]<>"",INDEX(ProblemData!$C$78:$AM$145,MATCH(J23+0.4,ProblemData!$C$78:$C$145,0),MATCH(C23,ProblemData!$C$78:$AM$78,0)),""),"") | H23: =_xlfn.IFNA(IF(JournalAnswer[[#This Row],[Credit Account]]<>"",INDEX(ProblemData!$C$78:$AM$145,MATCH(J23+0.4,ProblemData!$C$78:$C$145,0),MATCH(C23,ProblemData!$C$78:$AM$78,0)),""),"") -> 18 | I23: {=IF(JournalAnswer[[#This Row],[Debit Account]]="Cash",INDEX(ProblemData!$E$238:$AM$238,1,JournalAnswer[[#This Row],[Transaction '#]]),IF(JournalAnswer[[#This Row],[Credit Account]]="Cash",INDEX(ProblemData!$E$238:$AM$238,1,JournalAnswer[[#This Row],[Transaction '#]]),""))} -> Operating | J23: =IF(JournalAnswer[[#This Row],[Transaction '#]]="","",IF(JournalAnswer[[#This Row],[Transaction '#]]=C22,J22+1,1)) -> 2 | K23: {=IFERROR(_xlfn.IFS(JournalAnswer[[#This Row],[Debit Account]]="Cash",JournalAnswer[[#This Row],[Dr Amt]],JournalAnswer[[#This Row],[Credit Account]]="Cash",-JournalAnswer[[#This Row],[Cr Amt]]),0)} -> -18 | L23: {=IFERROR(INDEX(ProblemData!$E$239:$AM$239,1,JournalAnswer[[#This Row],[Transaction '#]]),"")} -> PdS | M23: =IF(JournalAnswer[[#This Row],[ref1]]="","",IF(NOT(ISBLANK(JournalAnswer[[#This Row],[Transaction '#]])),JournalAnswer[[#This Row],[ref1]]&JournalAnswer[[#This Row],[Movement '#]],"")) -> PdS2 | N23: =OR(JournalAnswer[[#This Row],[ref1]]="",ISNUMBER(MATCH(JournalAnswer[[#This Row],[ref1]], Operating[Abbr], 0)), "Found", "Not Found"="Found") -> TRUE
B24: 7 | C24: =IF(B24="","",B24) -> 7 | D24: =IFERROR(_xlfn.IFNA(INDEX(ProblemData!$C$78:$AM$145,MATCH(J24+0.1,ProblemData!$C$78:$C$145,0),MATCH(C24,ProblemData!$C$78:$AM$78,0)),""),"") -> Asset | E24: =IFERROR(_xlfn.IFNA(IF(INDEX(ProblemData!$C$78:$AM$145,MATCH(J24+0.3,ProblemData!$C$78:$C$145,0),MATCH(C24,ProblemData!$C$78:$AM$78,0))="Debit",INDEX(ProblemData!$C$78:$AM$145,MATCH(J24+0.2,ProblemData!$C$78:$C$145,0),MATCH(C24,ProblemData!$C$78:$AM$78,0)),""),""),"") -> Inventories | F24: =IFERROR(_xlfn.IFNA(IF(INDEX(ProblemData!$C$78:$AM$145,MATCH(J24+0.3,ProblemData!$C$78:$C$145,0),MATCH(C24,ProblemData!$C$78:$AM$78,0))="Credit",INDEX(ProblemData!$C$78:$AM$145,MATCH(J24+0.2,ProblemData!$C$78:$C$145,0),MATCH(C24,ProblemData!$C$78:$AM$78,0)),""),""),"") | G24: =_xlfn.IFNA(IF(JournalAnswer[[#This Row],[Debit Account]]<>"",INDEX(ProblemData!$C$78:$AM$145,MATCH(J24+0.4,ProblemData!$C$78:$C$145,0),MATCH(C24,ProblemData!$C$78:$AM$78,0)),""),"") -> 18 | H24: =_xlfn.IFNA(IF(JournalAnswer[[#This Row],[Credit Account]]<>"",INDEX(ProblemData!$C$78:$AM$145,MATCH(J24+0.4,ProblemData!$C$78:$C$145,0),MATCH(C24,ProblemData!$C$78:$AM$78,0)),""),"") | I24: {=IF(JournalAnswer[[#This Row],[Debit Account]]="Cash",INDEX(ProblemData!$E$238:$AM$238,1,JournalAnswer[[#This Row],[Transaction '#]]),IF(JournalAnswer[[#This Row],[Credit Account]]="Cash",INDEX(ProblemData!$E$238:$AM$238,1,JournalAnswer[[#This Row],[Transaction '#]]),""))} | J24: =IF(JournalAnswer[[#This Row],[Transaction '#]]="","",IF(JournalAnswer[[#This Row],[Transaction '#]]=C23,J23+1,1)) -> 1 | K24: {=IFERROR(_xlfn.IFS(JournalAnswer[[#This Row],[Debit Account]]="Cash",JournalAnswer[[#This Row],[Dr Amt]],JournalAnswer[[#This Row],[Credit Account]]="Cash",-JournalAnswer[[#This Row],[Cr Amt]]),0)} -> 0 | L24: {=IFERROR(INDEX(ProblemData!$E$239:$AM$239,1,JournalAnswer[[#This Row],[Transaction '#]]),"")} | M24: =IF(JournalAnswer[[#This Row],[ref1]]="","",IF(NOT(ISBLANK(JournalAnswer[[#This Row],[Transaction '#]])),JournalAnswer[[#This Row],[ref1]]&JournalAnswer[[#This Row],[Movement '#]],"")) | N24: =OR(JournalAnswer[[#This Row],[ref1]]="",ISNUMBER(MATCH(JournalAnswer[[#This Row],[ref1]], Operating[Abbr], 0)), "Found", "Not Found"="Found") -> TRUE
... B46: 23 | C46: =IF(B46="","",B46) -> 23 | D46: =IFERROR(_xlfn.IFNA(INDEX(ProblemData!$C$78:$AM$145,MATCH(J46+0.1,ProblemData!$C$78:$C$145,0),MATCH(C46,ProblemData!$C$78:$AM$78,0)),""),"") -> Asset | E46: =IFERROR(_xlfn.IFNA(IF(INDEX(ProblemData!$C$78:$AM$145,MATCH(J46+0.3,ProblemData!$C$78:$C$145,0),MATCH(C46,ProblemData!$C$78:$AM$78,0))="Debit",INDEX(ProblemData!$C$78:$AM$145,MATCH(J46+0.2,ProblemData!$C$78:$C$145,0),MATCH(C46,ProblemData!$C$78:$AM$78,0)),""),""),"") | F46: =IFERROR(_xlfn.IFNA(IF(INDEX(ProblemData!$C$78:$AM$145,MATCH(J46+0.3,ProblemData!$C$78:$C$145,0),MATCH(C46,ProblemData!$C$78:$AM$78,0))="Credit",INDEX(ProblemData!$C$78:$AM$145,MATCH(J46+0.2,ProblemData!$C$78:$C$145,0),MATCH(C46,ProblemData!$C$78:$AM$78,0)),""),""),"") -> Cash | G46: =_xlfn.IFNA(IF(JournalAnswer[[#This Row],[Debit Account]]<>"",INDEX(ProblemData!$C$78:$AM$145,MATCH(J46+0.4,ProblemData!$C$78:$C$145,0),MATCH(C46,ProblemData!$C$78:$AM$78,0)),""),"") | H46: =_xlfn.IFNA(IF(JournalAnswer[[#This Row],[Credit Account]]<>"",INDEX(ProblemData!$C$78:$AM$145,MATCH(J46+0.4,ProblemData!$C$78:$C$145,0),MATCH(C46,ProblemData!$C$78:$AM$78,0)),""),"") -> 2 | I46: {=IF(JournalAnswer[[#This Row],[Debit Account]]="Cash",INDEX(ProblemData!$E$238:$AM$238,1,JournalAnswer[[#This Row],[Transaction '#]]),IF(JournalAnswer[[#This Row],[Credit Account]]="Cash",INDEX(ProblemData!$E$238:$AM$238,1,JournalAnswer[[#This Row],[Transaction '#]]),""))} -> Financing | J46: =IF(JournalAnswer[[#This Row],[Transaction '#]]="","",IF(JournalAnswer[[#This Row],[Transaction '#]]=C45,J45+1,1)) -> 2 | K46: {=IFERROR(_xlfn.IFS(JournalAnswer[[#This Row],[Debit Account]]="Cash",JournalAnswer[[#This Row],[Dr Amt]],JournalAnswer[[#This Row],[Credit Account]]="Cash",-JournalAnswer[[#This Row],[Cr Amt]]),0)} -> -2 | L46: {=IFERROR(INDEX(ProblemData!$E$239:$AM$239,1,JournalAnswer[[#This Row],[Transaction '#]]),"")} | M46: =IF(JournalAnswer[[#This Row],[ref1]]="","",IF(NOT(ISBLANK(JournalAnswer[[#This Row],[Transaction '#]])),JournalAnswer[[#This Row],[ref1]]&JournalAnswer[[#This Row],[Movement '#]],"")) | N46: =OR(JournalAnswer[[#This Row],[ref1]]="",ISNUMBER(MATCH(JournalAnswer[[#This Row],[ref1]], Operating[Abbr], 0)), "Found", "Not Found"="Found") -> TRUE
C47: =IF(B47="","",B47) | D47: =IFERROR(_xlfn.IFNA(INDEX(ProblemData!$C$78:$AM$145,MATCH(J47+0.1,ProblemData!$C$78:$C$145,0),MATCH(C47,ProblemData!$C$78:$AM$78,0)),""),"") | E47: =IFERROR(_xlfn.IFNA(IF(INDEX(ProblemData!$C$78:$AM$145,MATCH(J47+0.3,ProblemData!$C$78:$C$145,0),MATCH(C47,ProblemData!$C$78:$AM$78,0))="Debit",INDEX(ProblemData!$C$78:$AM$145,MATCH(J47+0.2,ProblemData!$C$78:$C$145,0),MATCH(C47,ProblemData!$C$78:$AM$78,0)),""),""),"") | F47: =IFERROR(_xlfn.IFNA(IF(INDEX(ProblemData!$C$78:$AM$145,MATCH(J47+0.3,ProblemData!$C$78:$C$145,0),MATCH(C47,ProblemData!$C$78:$AM$78,0))="Credit",INDEX(ProblemData!$C$78:$AM$145,MATCH(J47+0.2,ProblemData!$C$78:$C$145,0),MATCH(C47,ProblemData!$C$78:$AM$78,0)),""),""),"") | G47: =_xlfn.IFNA(IF(JournalAnswer[[#This Row],[Debit Account]]<>"",INDEX(ProblemData!$C$78:$AM$145,MATCH(J47+0.4,ProblemData!$C$78:$C$145,0),MATCH(C47,ProblemData!$C$78:$AM$78,0)),""),"") | H47: =_xlfn.IFNA(IF(JournalAnswer[[#This Row],[Credit Account]]<>"",INDEX(ProblemData!$C$78:$AM$145,MATCH(J47+0.4,ProblemData!$C$78:$C$145,0),MATCH(C47,ProblemData!$C$78:$AM$78,0)),""),"") | I47: {=IF(JournalAnswer[[#This Row],[Debit Account]]="Cash",INDEX(ProblemData!$E$238:$AM$238,1,JournalAnswer[[#This Row],[Transaction '#]]),IF(JournalAnswer[[#This Row],[Credit Account]]="Cash",INDEX(ProblemData!$E$238:$AM$238,1,JournalAnswer[[#This Row],[Transaction '#]]),""))} | J47: =IF(JournalAnswer[[#This Row],[Transaction '#]]="","",IF(JournalAnswer[[#This Row],[Transaction '#]]=C46,J46+1,1)) | K47: {=IFERROR(_xlfn.IFS(JournalAnswer[[#This Row],[Debit Account]]="Cash",JournalAnswer[[#This Row],[Dr Amt]],JournalAnswer[[#This Row],[Credit Account]]="Cash",-JournalAnswer[[#This Row],[Cr Amt]]),0)} -> 0 | L47: {=IFERROR(INDEX(ProblemData!$E$239:$AM$239,1,JournalAnswer[[#This Row],[Transaction '#]]),"")} | M47: =IF(JournalAnswer[[#This Row],[ref1]]="","",IF(NOT(ISBLANK(JournalAnswer[[#This Row],[Transaction '#]])),JournalAnswer[[#This Row],[ref1]]&JournalAnswer[[#This Row],[Movement '#]],"")) | N47: =OR(JournalAnswer[[#This Row],[ref1]]="",ISNUMBER(MATCH(JournalAnswer[[#This Row],[ref1]], Operating[Abbr], 0)), "Found", "Not Found"="Found") -> TRUE
C48: =IF(B48="","",B48) | D48: =IFERROR(_xlfn.IFNA(INDEX(ProblemData!$C$78:$AM$145,MATCH(J48+0.1,ProblemData!$C$78:$C$145,0),MATCH(C48,ProblemData!$C$78:$AM$78,0)),""),"") | E48: =IFERROR(_xlfn.IFNA(IF(INDEX(ProblemData!$C$78:$AM$145,MATCH(J48+0.3,ProblemData!$C$78:$C$145,0),MATCH(C48,ProblemData!$C$78:$AM$78,0))="Debit",INDEX(ProblemData!$C$78:$AM$145,MATCH(J48+0.2,ProblemData!$C$78:$C$145,0),MATCH(C48,ProblemData!$C$78:$AM$78,0)),""),""),"") | F48: =IFERROR(_xlfn.IFNA(IF(INDEX(ProblemData!$C$78:$AM$145,MATCH(J48+0.3,ProblemData!$C$78:$C$145,0),MATCH(C48,ProblemData!$C$78:$AM$78,0))="Credit",INDEX(ProblemData!$C$78:$AM$145,MATCH(J48+0.2,ProblemData!$C$78:$C$145,0),MATCH(C48,ProblemData!$C$78:$AM$78,0)),""),""),"") | G48: =_xlfn.IFNA(IF(JournalAnswer[[#This Row],[Debit Account]]<>"",INDEX(ProblemData!$C$78:$AM$145,MATCH(J48+0.4,ProblemData!$C$78:$C$145,0),MATCH(C48,ProblemData!$C$78:$AM$78,0)),""),"") | H48: =_xlfn.IFNA(IF(JournalAnswer[[#This Row],[Credit Account]]<>"",INDEX(ProblemData!$C$78:$AM$145,MATCH(J48+0.4,ProblemData!$C$78:$C$145,0),MATCH(C48,ProblemData!$C$78:$AM$78,0)),""),"") | I48: {=IF(JournalAnswer[[#This Row],[Debit Account]]="Cash",INDEX(ProblemData!$E$238:$AM$238,1,JournalAnswer[[#This Row],[Transaction '#]]),IF(JournalAnswer[[#This Row],[Credit Account]]="Cash",INDEX(ProblemData!$E$238:$AM$238,1,JournalAnswer[[#This Row],[Transaction '#]]),""))} | J48: =IF(JournalAnswer[[#This Row],[Transaction '#]]="","",IF(JournalAnswer[[#This Row],[Transaction '#]]=C47,J47+1,1)) | K48: {=IFERROR(_xlfn.IFS(JournalAnswer[[#This Row],[Debit Account]]="Cash",JournalAnswer[[#This Row],[Dr Amt]],JournalAnswer[[#This Row],[Credit Account]]="Cash",-JournalAnswer[[#This Row],[Cr Amt]]),0)} -> 0 | L48: {=IFERROR(INDEX(ProblemData!$E$239:$AM$239,1,JournalAnswer[[#This Row],[Transaction '#]]),"")} | M48: =IF(JournalAnswer[[#This Row],[ref1]]="","",IF(NOT(ISBLANK(JournalAnswer[[#This Row],[Transaction '#]])),JournalAnswer[[#This Row],[ref1]]&JournalAnswer[[#This Row],[Movement '#]],"")) | N48: =OR(JournalAnswer[[#This Row],[ref1]]="",ISNUMBER(MATCH(JournalAnswer[[#This Row],[ref1]], Operating[Abbr], 0)), "Found", "Not Found"="Found") -> TRUE
C49: =IF(B49="","",B49) | D49: =IFERROR(_xlfn.IFNA(INDEX(ProblemData!$C$78:$AM$145,MATCH(J49+0.1,ProblemData!$C$78:$C$145,0),MATCH(C49,ProblemData!$C$78:$AM$78,0)),""),"") | E49: =IFERROR(_xlfn.IFNA(IF(INDEX(ProblemData!$C$78:$AM$145,MATCH(J49+0.3,ProblemData!$C$78:$C$145,0),MATCH(C49,ProblemData!$C$78:$AM$78,0))="Debit",INDEX(ProblemData!$C$78:$AM$145,MATCH(J49+0.2,ProblemData!$C$78:$C$145,0),MATCH(C49,ProblemData!$C$78:$AM$78,0)),""),""),"") | F49: =IFERROR(_xlfn.IFNA(IF(INDEX(ProblemData!$C$78:$AM$145,MATCH(J49+0.3,ProblemData!$C$78:$C$145,0),MATCH(C49,ProblemData!$C$78:$AM$78,0))="Credit",INDEX(ProblemData!$C$78:$AM$145,MATCH(J49+0.2,ProblemData!$C$78:$C$145,0),MATCH(C49,ProblemData!$C$78:$AM$78,0)),""),""),"") | G49: =_xlfn.IFNA(IF(JournalAnswer[[#This Row],[Debit Account]]<>"",INDEX(ProblemData!$C$78:$AM$145,MATCH(J49+0.4,ProblemData!$C$78:$C$145,0),MATCH(C49,ProblemData!$C$78:$AM$78,0)),""),"") | H49: =_xlfn.IFNA(IF(JournalAnswer[[#This Row],[Credit Account]]<>"",INDEX(ProblemData!$C$78:$AM$145,MATCH(J49+0.4,ProblemData!$C$78:$C$145,0),MATCH(C49,ProblemData!$C$78:$AM$78,0)),""),"") | I49: {=IF(JournalAnswer[[#This Row],[Debit Account]]="Cash",INDEX(ProblemData!$E$238:$AM$238,1,JournalAnswer[[#This Row],[Transaction '#]]),IF(JournalAnswer[[#This Row],[Credit Account]]="Cash",INDEX(ProblemData!$E$238:$AM$238,1,JournalAnswer[[#This Row],[Transaction '#]]),""))} | J49: =IF(JournalAnswer[[#This Row],[Transaction '#]]="","",IF(JournalAnswer[[#This Row],[Transaction '#]]=C48,J48+1,1)) | K49: {=IFERROR(_xlfn.IFS(JournalAnswer[[#This Row],[Debit Account]]="Cash",JournalAnswer[[#This Row],[Dr Amt]],JournalAnswer[[#This Row],[Credit Account]]="Cash",-JournalAnswer[[#This Row],[Cr Amt]]),0)} -> 0 | L49: {=IFERROR(INDEX(ProblemData!$E$239:$AM$239,1,JournalAnswer[[#This Row],[Transaction '#]]),"")} | M49: =IF(JournalAnswer[[#This Row],[ref1]]="","",IF(NOT(ISBLANK(JournalAnswer[[#This Row],[Transaction '#]])),JournalAnswer[[#This Row],[ref1]]&JournalAnswer[[#This Row],[Movement '#]],"")) | N49: =OR(JournalAnswer[[#This Row],[ref1]]="",ISNUMBER(MATCH(JournalAnswer[[#This Row],[ref1]], Operating[Abbr], 0)), "Found", "Not Found"="Found") -> TRUE
C50: =IF(B50="","",B50) | D50: =IFERROR(_xlfn.IFNA(INDEX(ProblemData!$C$78:$AM$145,MATCH(J50+0.1,ProblemData!$C$78:$C$145,0),MATCH(C50,ProblemData!$C$78:$AM$78,0)),""),"") | E50: =IFERROR(_xlfn.IFNA(IF(INDEX(ProblemData!$C$78:$AM$145,MATCH(J50+0.3,ProblemData!$C$78:$C$145,0),MATCH(C50,ProblemData!$C$78:$AM$78,0))="Debit",INDEX(ProblemData!$C$78:$AM$145,MATCH(J50+0.2,ProblemData!$C$78:$C$145,0),MATCH(C50,ProblemData!$C$78:$AM$78,0)),""),""),"") | F50: =IFERROR(_xlfn.IFNA(IF(INDEX(ProblemData!$C$78:$AM$145,MATCH(J50+0.3,ProblemData!$C$78:$C$145,0),MATCH(C50,ProblemData!$C$78:$AM$78,0))="Credit",INDEX(ProblemData!$C$78:$AM$145,MATCH(J50+0.2,ProblemData!$C$78:$C$145,0),MATCH(C50,ProblemData!$C$78:$AM$78,0)),""),""),"") | G50: =_xlfn.IFNA(IF(JournalAnswer[[#This Row],[Debit Account]]<>"",INDEX(ProblemData!$C$78:$AM$145,MATCH(J50+0.4,ProblemData!$C$78:$C$145,0),MATCH(C50,ProblemData!$C$78:$AM$78,0)),""),"") | H50: =_xlfn.IFNA(IF(JournalAnswer[[#This Row],[Credit Account]]<>"",INDEX(ProblemData!$C$78:$AM$145,MATCH(J50+0.4,ProblemData!$C$78:$C$145,0),MATCH(C50,ProblemData!$C$78:$AM$78,0)),""),"") | I50: {=IF(JournalAnswer[[#This Row],[Debit Account]]="Cash",INDEX(ProblemData!$E$238:$AM$238,1,JournalAnswer[[#This Row],[Transaction '#]]),IF(JournalAnswer[[#This Row],[Credit Account]]="Cash",INDEX(ProblemData!$E$238:$AM$238,1,JournalAnswer[[#This Row],[Transaction '#]]),""))} | J50: =IF(JournalAnswer[[#This Row],[Transaction '#]]="","",IF(JournalAnswer[[#This Row],[Transaction '#]]=C49,J49+1,1)) | K50: {=IFERROR(_xlfn.IFS(JournalAnswer[[#This Row],[Debit Account]]="Cash",JournalAnswer[[#This Row],[Dr Amt]],JournalAnswer[[#This Row],[Credit Account]]="Cash",-JournalAnswer[[#This Row],[Cr Amt]]),0)} -> 0 | L50: {=IFERROR(INDEX(ProblemData!$E$239:$AM$239,1,JournalAnswer[[#This Row],[Transaction '#]]),"")} | M50: =IF(JournalAnswer[[#This Row],[ref1]]="","",IF(NOT(ISBLANK(JournalAnswer[[#This Row],[Transaction '#]])),JournalAnswer[[#This Row],[ref1]]&JournalAnswer[[#This Row],[Movement '#]],"")) | N50: =OR(JournalAnswer[[#This Row],[ref1]]="",ISNUMBER(MATCH(JournalAnswer[[#This Row],[ref1]], Operating[Abbr], 0)), "Found", "Not Found"="Found") -> TRUE
C51: =IF(B51="","",B51) | D51: =IFERROR(_xlfn.IFNA(INDEX(ProblemData!$C$78:$AM$145,MATCH(J51+0.1,ProblemData!$C$78:$C$145,0),MATCH(C51,ProblemData!$C$78:$AM$78,0)),""),"") | E51: =IFERROR(_xlfn.IFNA(IF(INDEX(ProblemData!$C$78:$AM$145,MATCH(J51+0.3,ProblemData!$C$78:$C$145,0),MATCH(C51,ProblemData!$C$78:$AM$78,0))="Debit",INDEX(ProblemData!$C$78:$AM$145,MATCH(J51+0.2,ProblemData!$C$78:$C$145,0),MATCH(C51,ProblemData!$C$78:$AM$78,0)),""),""),"") | F51: =IFERROR(_xlfn.IFNA(IF(INDEX(ProblemData!$C$78:$AM$145,MATCH(J51+0.3,ProblemData!$C$78:$C$145,0),MATCH(C51,ProblemData!$C$78:$AM$78,0))="Credit",INDEX(ProblemData!$C$78:$AM$145,MATCH(J51+0.2,ProblemData!$C$78:$C$145,0),MATCH(C51,ProblemData!$C$78:$AM$78,0)),""),""),"") | G51: =_xlfn.IFNA(IF(JournalAnswer[[#This Row],[Debit Account]]<>"",INDEX(ProblemData!$C$78:$AM$145,MATCH(J51+0.4,ProblemData!$C$78:$C$145,0),MATCH(C51,ProblemData!$C$78:$AM$78,0)),""),"") | H51: =_xlfn.IFNA(IF(JournalAnswer[[#This Row],[Credit Account]]<>"",INDEX(ProblemData!$C$78:$AM$145,MATCH(J51+0.4,ProblemData!$C$78:$C$145,0),MATCH(C51,ProblemData!$C$78:$AM$78,0)),""),"") | I51: {=IF(JournalAnswer[[#This Row],[Debit Account]]="Cash",INDEX(ProblemData!$E$238:$AM$238,1,JournalAnswer[[#This Row],[Transaction '#]]),IF(JournalAnswer[[#This Row],[Credit Account]]="Cash",INDEX(ProblemData!$E$238:$AM$238,1,JournalAnswer[[#This Row],[Transaction '#]]),""))} | J51: =IF(JournalAnswer[[#This Row],[Transaction '#]]="","",IF(JournalAnswer[[#This Row],[Transaction '#]]=C50,J50+1,1)) | K51: {=IFERROR(_xlfn.IFS(JournalAnswer[[#This Row],[Debit Account]]="Cash",JournalAnswer[[#This Row],[Dr Amt]],JournalAnswer[[#This Row],[Credit Account]]="Cash",-JournalAnswer[[#This Row],[Cr Amt]]),0)} -> 0 | L51: {=IFERROR(INDEX(ProblemData!$E$239:$AM$239,1,JournalAnswer[[#This Row],[Transaction '#]]),"")} | M51: =IF(JournalAnswer[[#This Row],[ref1]]="","",IF(NOT(ISBLANK(JournalAnswer[[#This Row],[Transaction '#]])),JournalAnswer[[#This Row],[ref1]]&JournalAnswer[[#This Row],[Movement '#]],"")) | N51: =OR(JournalAnswer[[#This Row],[ref1]]="",ISNUMBER(MATCH(JournalAnswer[[#This Row],[ref1]], Operating[Abbr], 0)), "Found", "Not Found"="Found") -> TRUE
C52: =IF(B52="","",B52) | D52: =IFERROR(_xlfn.IFNA(INDEX(ProblemData!$C$78:$AM$145,MATCH(J52+0.1,ProblemData!$C$78:$C$145,0),MATCH(C52,ProblemData!$C$78:$AM$78,0)),""),"") | E52: =IFERROR(_xlfn.IFNA(IF(INDEX(ProblemData!$C$78:$AM$145,MATCH(J52+0.3,ProblemData!$C$78:$C$145,0),MATCH(C52,ProblemData!$C$78:$AM$78,0))="Debit",INDEX(ProblemData!$C$78:$AM$145,MATCH(J52+0.2,ProblemData!$C$78:$C$145,0),MATCH(C52,ProblemData!$C$78:$AM$78,0)),""),""),"") | F52: =IFERROR(_xlfn.IFNA(IF(INDEX(ProblemData!$C$78:$AM$145,MATCH(J52+0.3,ProblemData!$C$78:$C$145,0),MATCH(C52,ProblemData!$C$78:$AM$78,0))="Credit",INDEX(ProblemData!$C$78:$AM$145,MATCH(J52+0.2,ProblemData!$C$78:$C$145,0),MATCH(C52,ProblemData!$C$78:$AM$78,0)),""),""),"") | G52: =_xlfn.IFNA(IF(JournalAnswer[[#This Row],[Debit Account]]<>"",INDEX(ProblemData!$C$78:$AM$145,MATCH(J52+0.4,ProblemData!$C$78:$C$145,0),MATCH(C52,ProblemData!$C$78:$AM$78,0)),""),"") | H52: =_xlfn.IFNA(IF(JournalAnswer[[#This Row],[Credit Account]]<>"",INDEX(ProblemData!$C$78:$AM$145,MATCH(J52+0.4,ProblemData!$C$78:$C$145,0),MATCH(C52,ProblemData!$C$78:$AM$78,0)),""),"") | I52: {=IF(JournalAnswer[[#This Row],[Debit Account]]="Cash",INDEX(ProblemData!$E$238:$AM$238,1,JournalAnswer[[#This Row],[Transaction '#]]),IF(JournalAnswer[[#This Row],[Credit Account]]="Cash",INDEX(ProblemData!$E$238:$AM$238,1,JournalAnswer[[#This Row],[Transaction '#]]),""))} | J52: =IF(JournalAnswer[[#This Row],[Transaction '#]]="","",IF(JournalAnswer[[#This Row],[Transaction '#]]=C51,J51+1,1)) | K52: {=IFERROR(_xlfn.IFS(JournalAnswer[[#This Row],[Debit Account]]="Cash",JournalAnswer[[#This Row],[Dr Amt]],JournalAnswer[[#This Row],[Credit Account]]="Cash",-JournalAnswer[[#This Row],[Cr Amt]]),0)} -> 0 | L52: {=IFERROR(INDEX(ProblemData!$E$239:$AM$239,1,JournalAnswer[[#This Row],[Transaction '#]]),"")} | M52: =IF(JournalAnswer[[#This Row],[ref1]]="","",IF(NOT(ISBLANK(JournalAnswer[[#This Row],[Transaction '#]])),JournalAnswer[[#This Row],[ref1]]&JournalAnswer[[#This Row],[Movement '#]],"")) | N52: =OR(JournalAnswer[[#This Row],[ref1]]="",ISNUMBER(MATCH(JournalAnswer[[#This Row],[ref1]], Operating[Abbr], 0)), "Found", "Not Found"="Found") -> TRUE
C53: =IF(B53="","",B53) | D53: =IFERROR(_xlfn.IFNA(INDEX(ProblemData!$C$78:$AM$145,MATCH(J53+0.1,ProblemData!$C$78:$C$145,0),MATCH(C53,ProblemData!$C$78:$AM$78,0)),""),"") | E53: =IFERROR(_xlfn.IFNA(IF(INDEX(ProblemData!$C$78:$AM$145,MATCH(J53+0.3,ProblemData!$C$78:$C$145,0),MATCH(C53,ProblemData!$C$78:$AM$78,0))="Debit",INDEX(ProblemData!$C$78:$AM$145,MATCH(J53+0.2,ProblemData!$C$78:$C$145,0),MATCH(C53,ProblemData!$C$78:$AM$78,0)),""),""),"") | F53: =IFERROR(_xlfn.IFNA(IF(INDEX(ProblemData!$C$78:$AM$145,MATCH(J53+0.3,ProblemData!$C$78:$C$145,0),MATCH(C53,ProblemData!$C$78:$AM$78,0))="Credit",INDEX(ProblemData!$C$78:$AM$145,MATCH(J53+0.2,ProblemData!$C$78:$C$145,0),MATCH(C53,ProblemData!$C$78:$AM$78,0)),""),""),"") | G53: =_xlfn.IFNA(IF(JournalAnswer[[#This Row],[Debit Account]]<>"",INDEX(ProblemData!$C$78:$AM$145,MATCH(J53+0.4,ProblemData!$C$78:$C$145,0),MATCH(C53,ProblemData!$C$78:$AM$78,0)),""),"") | H53: =_xlfn.IFNA(IF(JournalAnswer[[#This Row],[Credit Account]]<>"",INDEX(ProblemData!$C$78:$AM$145,MATCH(J53+0.4,ProblemData!$C$78:$C$145,0),MATCH(C53,ProblemData!$C$78:$AM$78,0)),""),"") | I53: {=IF(JournalAnswer[[#This Row],[Debit Account]]="Cash",INDEX(ProblemData!$E$238:$AM$238,1,JournalAnswer[[#This Row],[Transaction '#]]),IF(JournalAnswer[[#This Row],[Credit Account]]="Cash",INDEX(ProblemData!$E$238:$AM$238,1,JournalAnswer[[#This Row],[Transaction '#]]),""))} | J53: =IF(JournalAnswer[[#This Row],[Transaction '#]]="","",IF(JournalAnswer[[#This Row],[Transaction '#]]=C52,J52+1,1)) | K53: {=IFERROR(_xlfn.IFS(JournalAnswer[[#This Row],[Debit Account]]="Cash",JournalAnswer[[#This Row],[Dr Amt]],JournalAnswer[[#This Row],[Credit Account]]="Cash",-JournalAnswer[[#This Row],[Cr Amt]]),0)} -> 0 | L53: {=IFERROR(INDEX(ProblemData!$E$239:$AM$239,1,JournalAnswer[[#This Row],[Transaction '#]]),"")} | M53: =IF(JournalAnswer[[#This Row],[ref1]]="","",IF(NOT(ISBLANK(JournalAnswer[[#This Row],[Transaction '#]])),JournalAnswer[[#This Row],[ref1]]&JournalAnswer[[#This Row],[Movement '#]],"")) | N53: =OR(JournalAnswer[[#This Row],[ref1]]="",ISNUMBER(MATCH(JournalAnswer[[#This Row],[ref1]], Operating[Abbr], 0)), "Found", "Not Found"="Found") -> TRUE
C54: =IF(B54="","",B54) | D54: =IFERROR(_xlfn.IFNA(INDEX(ProblemData!$C$78:$AM$145,MATCH(J54+0.1,ProblemData!$C$78:$C$145,0),MATCH(C54,ProblemData!$C$78:$AM$78,0)),""),"") | E54: =IFERROR(_xlfn.IFNA(IF(INDEX(ProblemData!$C$78:$AM$145,MATCH(J54+0.3,ProblemData!$C$78:$C$145,0),MATCH(C54,ProblemData!$C$78:$AM$78,0))="Debit",INDEX(ProblemData!$C$78:$AM$145,MATCH(J54+0.2,ProblemData!$C$78:$C$145,0),MATCH(C54,ProblemData!$C$78:$AM$78,0)),""),""),"") | F54: =IFERROR(_xlfn.IFNA(IF(INDEX(ProblemData!$C$78:$AM$145,MATCH(J54+0.3,ProblemData!$C$78:$C$145,0),MATCH(C54,ProblemData!$C$78:$AM$78,0))="Credit",INDEX(ProblemData!$C$78:$AM$145,MATCH(J54+0.2,ProblemData!$C$78:$C$145,0),MATCH(C54,ProblemData!$C$78:$AM$78,0)),""),""),"") | G54: =_xlfn.IFNA(IF(JournalAnswer[[#This Row],[Debit Account]]<>"",INDEX(ProblemData!$C$78:$AM$145,MATCH(J54+0.4,ProblemData!$C$78:$C$145,0),MATCH(C54,ProblemData!$C$78:$AM$78,0)),""),"") | H54: =_xlfn.IFNA(IF(JournalAnswer[[#This Row],[Credit Account]]<>"",INDEX(ProblemData!$C$78:$AM$145,MATCH(J54+0.4,ProblemData!$C$78:$C$145,0),MATCH(C54,ProblemData!$C$78:$AM$78,0)),""),"") | I54: {=IF(JournalAnswer[[#This Row],[Debit Account]]="Cash",INDEX(ProblemData!$E$238:$AM$238,1,JournalAnswer[[#This Row],[Transaction '#]]),IF(JournalAnswer[[#This Row],[Credit Account]]="Cash",INDEX(ProblemData!$E$238:$AM$238,1,JournalAnswer[[#This Row],[Transaction '#]]),""))} | J54: =IF(JournalAnswer[[#This Row],[Transaction '#]]="","",IF(JournalAnswer[[#This Row],[Transaction '#]]=C53,J53+1,1)) | K54: {=IFERROR(_xlfn.IFS(JournalAnswer[[#This Row],[Debit Account]]="Cash",JournalAnswer[[#This Row],[Dr Amt]],JournalAnswer[[#This Row],[Credit Account]]="Cash",-JournalAnswer[[#This Row],[Cr Amt]]),0)} -> 0 | L54: {=IFERROR(INDEX(ProblemData!$E$239:$AM$239,1,JournalAnswer[[#This Row],[Transaction '#]]),"")} | M54: =IF(JournalAnswer[[#This Row],[ref1]]="","",IF(NOT(ISBLANK(JournalAnswer[[#This Row],[Transaction '#]])),JournalAnswer[[#This Row],[ref1]]&JournalAnswer[[#This Row],[Movement '#]],"")) | N54: =OR(JournalAnswer[[#This Row],[ref1]]="",ISNUMBER(MATCH(JournalAnswer[[#This Row],[ref1]], Operating[Abbr], 0)), "Found", "Not Found"="Found") -> TRUE
C55: =IF(B55="","",B55) | D55: =IFERROR(_xlfn.IFNA(INDEX(ProblemData!$C$78:$AM$145,MATCH(J55+0.1,ProblemData!$C$78:$C$145,0),MATCH(C55,ProblemData!$C$78:$AM$78,0)),""),"") | E55: =IFERROR(_xlfn.IFNA(IF(INDEX(ProblemData!$C$78:$AM$145,MATCH(J55+0.3,ProblemData!$C$78:$C$145,0),MATCH(C55,ProblemData!$C$78:$AM$78,0))="Debit",INDEX(ProblemData!$C$78:$AM$145,MATCH(J55+0.2,ProblemData!$C$78:$C$145,0),MATCH(C55,ProblemData!$C$78:$AM$78,0)),""),""),"") | F55: =IFERROR(_xlfn.IFNA(IF(INDEX(ProblemData!$C$78:$AM$145,MATCH(J55+0.3,ProblemData!$C$78:$C$145,0),MATCH(C55,ProblemData!$C$78:$AM$78,0))="Credit",INDEX(ProblemData!$C$78:$AM$145,MATCH(J55+0.2,ProblemData!$C$78:$C$145,0),MATCH(C55,ProblemData!$C$78:$AM$78,0)),""),""),"") | G55: =_xlfn.IFNA(IF(JournalAnswer[[#This Row],[Debit Account]]<>"",INDEX(ProblemData!$C$78:$AM$145,MATCH(J55+0.4,ProblemData!$C$78:$C$145,0),MATCH(C55,ProblemData!$C$78:$AM$78,0)),""),"") | H55: =_xlfn.IFNA(IF(JournalAnswer[[#This Row],[Credit Account]]<>"",INDEX(ProblemData!$C$78:$AM$145,MATCH(J55+0.4,ProblemData!$C$78:$C$145,0),MATCH(C55,ProblemData!$C$78:$AM$78,0)),""),"") | I55: {=IF(JournalAnswer[[#This Row],[Debit Account]]="Cash",INDEX(ProblemData!$E$238:$AM$238,1,JournalAnswer[[#This Row],[Transaction '#]]),IF(JournalAnswer[[#This Row],[Credit Account]]="Cash",INDEX(ProblemData!$E$238:$AM$238,1,JournalAnswer[[#This Row],[Transaction '#]]),""))} | J55: =IF(JournalAnswer[[#This Row],[Transaction '#]]="","",IF(JournalAnswer[[#This Row],[Transaction '#]]=C54,J54+1,1)) | K55: {=IFERROR(_xlfn.IFS(JournalAnswer[[#This Row],[Debit Account]]="Cash",JournalAnswer[[#This Row],[Dr Amt]],JournalAnswer[[#This Row],[Credit Account]]="Cash",-JournalAnswer[[#This Row],[Cr Amt]]),0)} -> 0 | L55: {=IFERROR(INDEX(ProblemData!$E$239:$AM$239,1,JournalAnswer[[#This Row],[Transaction '#]]),"")} | M55: =IF(JournalAnswer[[#This Row],[ref1]]="","",IF(NOT(ISBLANK(JournalAnswer[[#This Row],[Transaction '#]])),JournalAnswer[[#This Row],[ref1]]&JournalAnswer[[#This Row],[Movement '#]],"")) | N55: =OR(JournalAnswer[[#This Row],[ref1]]="",ISNUMBER(MATCH(JournalAnswer[[#This Row],[ref1]], Operating[Abbr], 0)), "Found", "Not Found"="Found") -> TRUE
C56: =IF(B56="","",B56) | D56: =IFERROR(_xlfn.IFNA(INDEX(ProblemData!$C$78:$AM$145,MATCH(J56+0.1,ProblemData!$C$78:$C$145,0),MATCH(C56,ProblemData!$C$78:$AM$78,0)),""),"") | E56: =IFERROR(_xlfn.IFNA(IF(INDEX(ProblemData!$C$78:$AM$145,MATCH(J56+0.3,ProblemData!$C$78:$C$145,0),MATCH(C56,ProblemData!$C$78:$AM$78,0))="Debit",INDEX(ProblemData!$C$78:$AM$145,MATCH(J56+0.2,ProblemData!$C$78:$C$145,0),MATCH(C56,ProblemData!$C$78:$AM$78,0)),""),""),"") | F56: =IFERROR(_xlfn.IFNA(IF(INDEX(ProblemData!$C$78:$AM$145,MATCH(J56+0.3,ProblemData!$C$78:$C$145,0),MATCH(C56,ProblemData!$C$78:$AM$78,0))="Credit",INDEX(ProblemData!$C$78:$AM$145,MATCH(J56+0.2,ProblemData!$C$78:$C$145,0),MATCH(C56,ProblemData!$C$78:$AM$78,0)),""),""),"") | G56: =_xlfn.IFNA(IF(JournalAnswer[[#This Row],[Debit Account]]<>"",INDEX(ProblemData!$C$78:$AM$145,MATCH(J56+0.4,ProblemData!$C$78:$C$145,0),MATCH(C56,ProblemData!$C$78:$AM$78,0)),""),"") | H56: =_xlfn.IFNA(IF(JournalAnswer[[#This Row],[Credit Account]]<>"",INDEX(ProblemData!$C$78:$AM$145,MATCH(J56+0.4,ProblemData!$C$78:$C$145,0),MATCH(C56,ProblemData!$C$78:$AM$78,0)),""),"") | I56: {=IF(JournalAnswer[[#This Row],[Debit Account]]="Cash",INDEX(ProblemData!$E$238:$AM$238,1,JournalAnswer[[#This Row],[Transaction '#]]),IF(JournalAnswer[[#This Row],[Credit Account]]="Cash",INDEX(ProblemData!$E$238:$AM$238,1,JournalAnswer[[#This Row],[Transaction '#]]),""))} | J56: =IF(JournalAnswer[[#This Row],[Transaction '#]]="","",IF(JournalAnswer[[#This Row],[Transaction '#]]=C55,J55+1,1)) | K56: {=IFERROR(_xlfn.IFS(JournalAnswer[[#This Row],[Debit Account]]="Cash",JournalAnswer[[#This Row],[Dr Amt]],JournalAnswer[[#This Row],[Credit Account]]="Cash",-JournalAnswer[[#This Row],[Cr Amt]]),0)} -> 0 | L56: {=IFERROR(INDEX(ProblemData!$E$239:$AM$239,1,JournalAnswer[[#This Row],[Transaction '#]]),"")} | M56: =IF(JournalAnswer[[#This Row],[ref1]]="","",IF(NOT(ISBLANK(JournalAnswer[[#This Row],[Transaction '#]])),JournalAnswer[[#This Row],[ref1]]&JournalAnswer[[#This Row],[Movement '#]],"")) | N56: =OR(JournalAnswer[[#This Row],[ref1]]="",ISNUMBER(MATCH(JournalAnswer[[#This Row],[ref1]], Operating[Abbr], 0)), "Found", "Not Found"="Found") -> TRUE
C57: =IF(B57="","",B57) | D57: =IFERROR(_xlfn.IFNA(INDEX(ProblemData!$C$78:$AM$145,MATCH(J57+0.1,ProblemData!$C$78:$C$145,0),MATCH(C57,ProblemData!$C$78:$AM$78,0)),""),"") | E57: =IFERROR(_xlfn.IFNA(IF(INDEX(ProblemData!$C$78:$AM$145,MATCH(J57+0.3,ProblemData!$C$78:$C$145,0),MATCH(C57,ProblemData!$C$78:$AM$78,0))="Debit",INDEX(ProblemData!$C$78:$AM$145,MATCH(J57+0.2,ProblemData!$C$78:$C$145,0),MATCH(C57,ProblemData!$C$78:$AM$78,0)),""),""),"") | F57: =IFERROR(_xlfn.IFNA(IF(INDEX(ProblemData!$C$78:$AM$145,MATCH(J57+0.3,ProblemData!$C$78:$C$145,0),MATCH(C57,ProblemData!$C$78:$AM$78,0))="Credit",INDEX(ProblemData!$C$78:$AM$145,MATCH(J57+0.2,ProblemData!$C$78:$C$145,0),MATCH(C57,ProblemData!$C$78:$AM$78,0)),""),""),"") | G57: =_xlfn.IFNA(IF(JournalAnswer[[#This Row],[Debit Account]]<>"",INDEX(ProblemData!$C$78:$AM$145,MATCH(J57+0.4,ProblemData!$C$78:$C$145,0),MATCH(C57,ProblemData!$C$78:$AM$78,0)),""),"") | H57: =_xlfn.IFNA(IF(JournalAnswer[[#This Row],[Credit Account]]<>"",INDEX(ProblemData!$C$78:$AM$145,MATCH(J57+0.4,ProblemData!$C$78:$C$145,0),MATCH(C57,ProblemData!$C$78:$AM$78,0)),""),"") | I57: {=IF(JournalAnswer[[#This Row],[Debit Account]]="Cash",INDEX(ProblemData!$E$238:$AM$238,1,JournalAnswer[[#This Row],[Transaction '#]]),IF(JournalAnswer[[#This Row],[Credit Account]]="Cash",INDEX(ProblemData!$E$238:$AM$238,1,JournalAnswer[[#This Row],[Transaction '#]]),""))} | J57: =IF(JournalAnswer[[#This Row],[Transaction '#]]="","",IF(JournalAnswer[[#This Row],[Transaction '#]]=C56,J56+1,1)) | K57: {=IFERROR(_xlfn.IFS(JournalAnswer[[#This Row],[Debit Account]]="Cash",JournalAnswer[[#This Row],[Dr Amt]],JournalAnswer[[#This Row],[Credit Account]]="Cash",-JournalAnswer[[#This Row],[Cr Amt]]),0)} -> 0 | L57: {=IFERROR(INDEX(ProblemData!$E$239:$AM$239,1,JournalAnswer[[#This Row],[Transaction '#]]),"")} | M57: =IF(JournalAnswer[[#This Row],[ref1]]="","",IF(NOT(ISBLANK(JournalAnswer[[#This Row],[Transaction '#]])),JournalAnswer[[#This Row],[ref1]]&JournalAnswer[[#This Row],[Movement '#]],"")) | N57: =OR(JournalAnswer[[#This Row],[ref1]]="",ISNUMBER(MATCH(JournalAnswer[[#This Row],[ref1]], Operating[Abbr], 0)), "Found", "Not Found"="Found") -> TRUE
C58: =IF(B58="","",B58) | D58: =IFERROR(_xlfn.IFNA(INDEX(ProblemData!$C$78:$AM$145,MATCH(J58+0.1,ProblemData!$C$78:$C$145,0),MATCH(C58,ProblemData!$C$78:$AM$78,0)),""),"") | E58: =IFERROR(_xlfn.IFNA(IF(INDEX(ProblemData!$C$78:$AM$145,MATCH(J58+0.3,ProblemData!$C$78:$C$145,0),MATCH(C58,ProblemData!$C$78:$AM$78,0))="Debit",INDEX(ProblemData!$C$78:$AM$145,MATCH(J58+0.2,ProblemData!$C$78:$C$145,0),MATCH(C58,ProblemData!$C$78:$AM$78,0)),""),""),"") | F58: =IFERROR(_xlfn.IFNA(IF(INDEX(ProblemData!$C$78:$AM$145,MATCH(J58+0.3,ProblemData!$C$78:$C$145,0),MATCH(C58,ProblemData!$C$78:$AM$78,0))="Credit",INDEX(ProblemData!$C$78:$AM$145,MATCH(J58+0.2,ProblemData!$C$78:$C$145,0),MATCH(C58,ProblemData!$C$78:$AM$78,0)),""),""),"") | G58: =_xlfn.IFNA(IF(JournalAnswer[[#This Row],[Debit Account]]<>"",INDEX(ProblemData!$C$78:$AM$145,MATCH(J58+0.4,ProblemData!$C$78:$C$145,0),MATCH(C58,ProblemData!$C$78:$AM$78,0)),""),"") | H58: =_xlfn.IFNA(IF(JournalAnswer[[#This Row],[Credit Account]]<>"",INDEX(ProblemData!$C$78:$AM$145,MATCH(J58+0.4,ProblemData!$C$78:$C$145,0),MATCH(C58,ProblemData!$C$78:$AM$78,0)),""),"") | I58: {=IF(JournalAnswer[[#This Row],[Debit Account]]="Cash",INDEX(ProblemData!$E$238:$AM$238,1,JournalAnswer[[#This Row],[Transaction '#]]),IF(JournalAnswer[[#This Row],[Credit Account]]="Cash",INDEX(ProblemData!$E$238:$AM$238,1,JournalAnswer[[#This Row],[Transaction '#]]),""))} | J58: =IF(JournalAnswer[[#This Row],[Transaction '#]]="","",IF(JournalAnswer[[#This Row],[Transaction '#]]=C57,J57+1,1)) | K58: {=IFERROR(_xlfn.IFS(JournalAnswer[[#This Row],[Debit Account]]="Cash",JournalAnswer[[#This Row],[Dr Amt]],JournalAnswer[[#This Row],[Credit Account]]="Cash",-JournalAnswer[[#This Row],[Cr Amt]]),0)} -> 0 | L58: {=IFERROR(INDEX(ProblemData!$E$239:$AM$239,1,JournalAnswer[[#This Row],[Transaction '#]]),"")} | M58: =IF(JournalAnswer[[#This Row],[ref1]]="","",IF(NOT(ISBLANK(JournalAnswer[[#This Row],[Transaction '#]])),JournalAnswer[[#This Row],[ref1]]&JournalAnswer[[#This Row],[Movement '#]],"")) | N58: =OR(JournalAnswer[[#This Row],[ref1]]="",ISNUMBER(MATCH(JournalAnswer[[#This Row],[ref1]], Operating[Abbr], 0)), "Found", "Not Found"="Found") -> TRUE
... C197: =IF(B197="","",B197) | D197: =IFERROR(_xlfn.IFNA(INDEX(ProblemData!$C$78:$AM$145,MATCH(J197+0.1,ProblemData!$C$78:$C$145,0),MATCH(C197,ProblemData!$C$78:$AM$78,0)),""),"") | E197: =IFERROR(_xlfn.IFNA(IF(INDEX(ProblemData!$C$78:$AM$145,MATCH(J197+0.3,ProblemData!$C$78:$C$145,0),MATCH(C197,ProblemData!$C$78:$AM$78,0))="Debit",INDEX(ProblemData!$C$78:$AM$145,MATCH(J197+0.2,ProblemData!$C$78:$C$145,0),MATCH(C197,ProblemData!$C$78:$AM$78,0)),""),""),"") | F197: =IFERROR(_xlfn.IFNA(IF(INDEX(ProblemData!$C$78:$AM$145,MATCH(J197+0.3,ProblemData!$C$78:$C$145,0),MATCH(C197,ProblemData!$C$78:$AM$78,0))="Credit",INDEX(ProblemData!$C$78:$AM$145,MATCH(J197+0.2,ProblemData!$C$78:$C$145,0),MATCH(C197,ProblemData!$C$78:$AM$78,0)),""),""),"") | G197: =_xlfn.IFNA(IF(JournalAnswer[[#This Row],[Debit Account]]<>"",INDEX(ProblemData!$C$78:$AM$145,MATCH(J197+0.4,ProblemData!$C$78:$C$145,0),MATCH(C197,ProblemData!$C$78:$AM$78,0)),""),"") | H197: =_xlfn.IFNA(IF(JournalAnswer[[#This Row],[Credit Account]]<>"",INDEX(ProblemData!$C$78:$AM$145,MATCH(J197+0.4,ProblemData!$C$78:$C$145,0),MATCH(C197,ProblemData!$C$78:$AM$78,0)),""),"") | I197: {=IF(JournalAnswer[[#This Row],[Debit Account]]="Cash",INDEX(ProblemData!$E$238:$AM$238,1,JournalAnswer[[#This Row],[Transaction '#]]),IF(JournalAnswer[[#This Row],[Credit Account]]="Cash",INDEX(ProblemData!$E$238:$AM$238,1,JournalAnswer[[#This Row],[Transaction '#]]),""))} | J197: =IF(JournalAnswer[[#This Row],[Transaction '#]]="","",IF(JournalAnswer[[#This Row],[Transaction '#]]=C196,J196+1,1)) | K197: {=IFERROR(_xlfn.IFS(JournalAnswer[[#This Row],[Debit Account]]="Cash",JournalAnswer[[#This Row],[Dr Amt]],JournalAnswer[[#This Row],[Credit Account]]="Cash",-JournalAnswer[[#This Row],[Cr Amt]]),0)} -> 0 | L197: {=IFERROR(INDEX(ProblemData!$E$239:$AM$239,1,JournalAnswer[[#This Row],[Transaction '#]]),"")} | M197: =IF(JournalAnswer[[#This Row],[ref1]]="","",IF(NOT(ISBLANK(JournalAnswer[[#This Row],[Transaction '#]])),JournalAnswer[[#This Row],[ref1]]&JournalAnswer[[#This Row],[Movement '#]],"")) | N197: =OR(JournalAnswer[[#This Row],[ref1]]="",ISNUMBER(MATCH(JournalAnswer[[#This Row],[ref1]], Operating[Abbr], 0)), "Found", "Not Found"="Found") -> TRUE

Sheet FSAnswers
A1: 1 | C1: =Entity -> Accounting Identity LLC
A2: 2 | C2: =Units -> Dollars in Thousands
A3: Show OCI
A4: Direct CFO | C4: =BegDate -> 12/31/20x0 | H4: Explanations of Changes Made over the Year | T4: =EndDate -> 12/31/20x1
A5: Show NCIF
A6: Show NI CFO Recon | B6: 1 | C6: Balance Sheet | G6: 1 | H6: Income Statement | K6: 1 | L6: Statement of Changes in Shareholders' Equity | O6: 1 | P6: Cash Flow Statement | S6: 1 | T6: Balance Sheet
B7: {=_xlfn.VSTACK(_xlfn.ANCHORARRAY(B235),{"","",""},_xlfn.ANCHORARRAY(B236),{"","",""},_xlfn.ANCHORARRAY(B246),_xlfn.ANCHORARRAY(B255),{"","",""},_xlfn.ANCHORARRAY(B256),{"","",""},_xlfn.ANCHORARRAY(B258),{"","",""},_xlfn.ANCHORARRAY(B260),{"","",""},_xlfn.ANCHORARRAY(B270),_xlfn.ANCHORARRAY(B280),{"","",""},_xlfn.ANCHORARRAY(B282),{"","",""},_xlfn.ANCHORARRAY(B284),_xlfn.ANCHORARRAY(B290),{"","",""},_xlfn.ANCHORARRAY(B292))} -> 2 | C7: ASSETS | G7: {=IF(OR(J190=1,J200=1),_xlfn.VSTACK(_xlfn.ANCHORARRAY(G235),{"","",""},_xlfn.ANCHORARRAY(G236),_xlfn.ANCHORARRAY(G245),{"","",""},_xlfn.ANCHORARRAY(G246),{"","",""},_xlfn.ANCHORARRAY(G247),_xlfn.ANCHORARRAY(G269),{"","",""},_xlfn.ANCHORARRAY(G270),_xlfn.ANCHORARRAY(G271),_xlfn.ANCHORARRAY(G279),{"","",""},_xlfn.ANCHORARRAY(G280),_xlfn.ANCHORARRAY(G281),_xlfn.ANCHORARRAY(G289),{"","",""},_xlfn.ANCHORARRAY(G290)),_xlfn.VSTACK(_xlfn.ANCHORARRAY(G235),{"","",""},_xlfn.ANCHORARRAY(G236),_xlfn.ANCHORARRAY(G245),{"","",""},_xlfn.ANCHORARRAY(G246),{"","",""},_xlfn.ANCHORARRAY(G247),_xlfn.ANCHORARRAY(G269),{"","",""},_xlfn.ANCHORARRAY(G290)))} -> 2 | H7: REVENUES | L7: {=IF($M$224=1,_xlfn.ANCHORARRAY(L230))} -> FALSE | O7: {=_xlfn.VSTACK(_xlfn.ANCHORARRAY(O316),{"","",""},_xlfn.ANCHORARRAY(O317),{"","",""},_xlfn.ANCHORARRAY(O335),{"","",""},_xlfn.ANCHORARRAY(O336),{"","",""},_xlfn.ANCHORARRAY(O351),{"","",""},_xlfn.ANCHORARRAY(O352),{"","",""},_xlfn.ANCHORARRAY(O365),{"","",""},_xlfn.ANCHORARRAY(O367))} -> 2 | P7: Operating Activities | S7: {=_xlfn.VSTACK(_xlfn.ANCHORARRAY(S235),{"","",""},_xlfn.ANCHORARRAY(S236),{"","",""},_xlfn.ANCHORARRAY(S246),_xlfn.ANCHORARRAY(S255),{"","",""},_xlfn.ANCHORARRAY(S256),{"","",""},_xlfn.ANCHORARRAY(S258),{"","",""},_xlfn.ANCHORARRAY(S260),{"","",""},_xlfn.ANCHORARRAY(S270),_xlfn.ANCHORARRAY(S280),{"","",""},_xlfn.ANCHORARRAY(S282),{"","",""},_xlfn.ANCHORARRAY(S284),_xlfn.ANCHORARRAY(S290),{"","",""},_xlfn.ANCHORARRAY(S292))} -> 2 | T7: ASSETS | V7: 0
V8: 0
G9: 6 | H9: Sales | I9: 18 | O9: 6 | P9: Collections from customers | Q9: 91 | S9: 4 | T9: Current Assets: | V9: 0
G10: 5 | H10: Total Revenues | I10: 18 | O10: 7 | P10: Payments to suppliers | Q10: -52 | S10: 6 | T10: Cash | U10: 137 | V10: 0
S11: 7 | T11: Accounts Receivable | U11: 0 | V11: 0
B12: 5 | C12: Total Noncurrent Assets | D12: 0 | G12: 2 | H12: EXPENSES | O12: 3 | P12: Total Cash Flow from Operating Activities | Q12: 39 | S12: 7 | T12: Inventories | U12: 42 | V12: 0
S13: 5 | T13: Total Current Assets | U13: 179 | V13: 0
B14: 3 | C14: Total Assets | D14: 0 | G14: 6 | H14: Cost of Goods Sold | I14: 6 | O14: 2 | P14: Investing Activities | V14: 0
G15: 5 | H15: Total Expenses | I15: 6 | S15: 4 | T15: Noncurrent Assets: | V15: 0
B16: 2 | C16: LIABILITIES | O16: 2 | P16: Financing Activities | S16: 6 | T16: Property, Plant & Equipment | U16: 100 | V16: 0
G17: 3 | H17: Net Income | I17: 12 | S17: 7 | T17: Land | U17: 0 | V17: 0
O18: 6 | P18: Issued common stock | Q18: 50 | S18: 5 | T18: Total Noncurrent Assets | U18: 100 | V18: 0
O19: 7 | P19: Got a loan from a bank | Q19: 50 | V19: 0
S20: 3 | T20: Total Assets | U20: 279 | V20: 0
O21: 3 | P21: Total Cash Flow from Financing Activities | Q21: 100 | V21: 0
S22: 2 | T22: LIABILITIES | V22: 0
B23: 2 | C23: EQUITIES | O23: 3 | P23: Increase (decrease) in cash | Q23: 139 | V23: 0
O24: 5 | P24: Cash @ 12/31/20x1 | Q24: 139 | S24: 4 | T24: Current Liabilities: | V24: 0
B25: 6 | C25: Common Stock | D25: 0 | S25: 6 | T25: Accounts Payable | U25: 2 | V25: 0
B26: 7 | C26: Retained Earnings | D26: 0 | S26: 7 | T26: Dividends Payable | U26: 0 | V26: #NAME?
B27: 3 | C27: Total Equities | D27: 0 | J27: 0 | S27: 7 | T27: Unearned Revenue | U27: 8 | V27: 0
J28: 0 | S28: 5 | T28: Total Current Liabilities | U28: 10 | V28: 0
J29: 0 | V29: 0
J30: 0 | S30: 4 | T30: Noncurrent Liabilities: | V30: 0
J31: =IF(H31<>"",COUNTIFS(#REF!,H31),0) -> 0 | S31: 6 | T31: Loans Payable | U31: 100
J32: =IF(H32<>"",COUNTIFS(#REF!,H32),0) -> 0 | S32: 5 | T32: Total Noncurrent Liabilities | U32: 100
J33: =IF(H33<>"",COUNTIFS(#REF!,H33),0) -> 0 | S33: 3 | T33: Total Liabilities | U33: 110
J34: =IF(H34<>"",COUNTIFS(#REF!,H34),0) -> 0
J35: =IF(H35<>"",COUNTIFS(#REF!,H35),0) -> 0 | S35: 2 | T35: EQUITIES
J36: =IF(H36<>"",COUNTIFS(#REF!,H36),0) -> 0
J37: =IF(H37<>"",COUNTIFS(#REF!,H37),0) -> 0 | S37: 6 | T37: Common Stock | U37: 100
J38: =IF(H38<>"",COUNTIFS(#REF!,H38),0) -> 0 | S38: 7 | T38: Retained Earnings | U38: -2
J39: =IF(H39<>"",COUNTIFS(#REF!,H39),0) -> 0 | S39: 3 | T39: Total Equities | U39: 98
J40: =IF(H40<>"",COUNTIFS(#REF!,H40),0) -> 0
J41: =IF(H41<>"",COUNTIFS(#REF!,H41),0) -> 0 | S41: 3 | T41: Total Liabilities and Equities | U41: 208
J42: =IF(H42<>"",COUNTIFS(#REF!,H42),0) -> 0
J43: =IF(H43<>"",COUNTIFS(#REF!,H43),0) -> 0
J44: =IF(H44<>"",COUNTIFS(#REF!,H44),0) -> 0
J45: =IF(H45<>"",COUNTIFS(#REF!,H45),0) -> 0
J46: =IF(H46<>"",COUNTIFS(#REF!,H46),0) -> 0
J47: =IF(H47<>"",COUNTIFS(#REF!,H47),0) -> 0
J48: =IF(H48<>"",COUNTIFS(#REF!,H48),0) -> 0
J49: =IF(H49<>"",COUNTIFS(#REF!,H49),0) -> 0
J50: =IF(H50<>"",COUNTIFS(#REF!,H50),0) -> 0
J51: =IF(H51<>"",COUNTIFS(#REF!,H51),0) -> 0
J52: =IF(H52<>"",COUNTIFS(#REF!,H52),0) -> 0
J53: =IF(H53<>"",COUNTIFS(#REF!,H53),0) -> 0
... J60: =IF(H60<>"",COUNTIFS(#REF!,H60),0) -> 0
C99: At least one line in student answer disagrees? | D99: =ISNUMBER(MATCH(FALSE,D100:D154,0)) -> TRUE | H99: At least one line in student answer disagrees? | I99: =ISNUMBER(MATCH(FALSE,I100:I154,0)) -> TRUE | L99: At least one line in student answer disagrees? | M99: =ISNUMBER(MATCH(FALSE,M100:M154,0)) -> TRUE | P99: At least one line in student answer disagrees? | Q99: =ISNUMBER(MATCH(FALSE,Q100:Q154,0)) -> TRUE | T99: At least one disagrees: | U99: =ISNUMBER(MATCH(FALSE,U100:U154,0)) -> TRUE
C100: =C7&D7 -> ASSETS | D100: =ISNUMBER(MATCH(C100,Financial_Statement_Builder!$J$405:$J$488,0)) -> TRUE | H100: =H7&I7 -> REVENUES | I100: =ISNUMBER(MATCH(H100,Financial_Statement_Builder!$M$405:$M$488,0)) -> TRUE | L100: =_xlfn.CONCAT(L7:M7) -> FALSE | M100: =ISNUMBER(MATCH(L100,Financial_Statement_Builder!$Q$405:$Q$488,0)) -> FALSE | P100: =P7&Q7 -> Operating Activities | Q100: =ISNUMBER(MATCH(P100,Financial_Statement_Builder!$T$405:$T$488,0)) -> TRUE | T100: =T7&U7 -> ASSETS | U100: =ISNUMBER(MATCH(T100,Financial_Statement_Builder!$X$405:$X$488,0)) -> TRUE
C101: =C8&D8 | D101: =ISNUMBER(MATCH(C101,Financial_Statement_Builder!$J$405:$J$488,0)) -> TRUE | H101: =H8&I8 | I101: =ISNUMBER(MATCH(H101,Financial_Statement_Builder!$M$405:$M$488,0)) -> TRUE | L101: =_xlfn.CONCAT(L8:M8) | M101: =ISNUMBER(MATCH(L101,Financial_Statement_Builder!$Q$405:$Q$488,0)) -> TRUE | P101: =P8&Q8 | Q101: =ISNUMBER(MATCH(P101,Financial_Statement_Builder!$T$405:$T$488,0)) -> TRUE | T101: =T8&U8 | U101: =ISNUMBER(MATCH(T101,Financial_Statement_Builder!$X$405:$X$488,0)) -> TRUE
C102: =C9&D9 | D102: =ISNUMBER(MATCH(C102,Financial_Statement_Builder!$J$405:$J$488,0)) -> TRUE | H102: =H9&I9 -> Sales18 | I102: =ISNUMBER(MATCH(H102,Financial_Statement_Builder!$M$405:$M$488,0)) -> FALSE | L102: =_xlfn.CONCAT(L9:M9) | M102: =ISNUMBER(MATCH(L102,Financial_Statement_Builder!$Q$405:$Q$488,0)) -> TRUE | P102: =P9&Q9 -> Collections from customers91 | Q102: =ISNUMBER(MATCH(P102,Financial_Statement_Builder!$T$405:$T$488,0)) -> FALSE | T102: =T9&U9 -> Current Assets: | U102: =ISNUMBER(MATCH(T102,Financial_Statement_Builder!$X$405:$X$488,0)) -> TRUE
C103: =C10&D10 | D103: =ISNUMBER(MATCH(C103,Financial_Statement_Builder!$J$405:$J$488,0)) -> TRUE | H103: =H10&I10 -> Total Revenues18 | I103: =ISNUMBER(MATCH(H103,Financial_Statement_Builder!$M$405:$M$488,0)) -> FALSE | L103: =_xlfn.CONCAT(L10:M10) | M103: =ISNUMBER(MATCH(L103,Financial_Statement_Builder!$Q$405:$Q$488,0)) -> TRUE | P103: =P10&Q10 -> Payments to suppliers-52 | Q103: =ISNUMBER(MATCH(P103,Financial_Statement_Builder!$T$405:$T$488,0)) -> FALSE | T103: =T10&U10 -> Cash137 | U103: =ISNUMBER(MATCH(T103,Financial_Statement_Builder!$X$405:$X$488,0)) -> FALSE
C104: =C11&D11 | D104: =ISNUMBER(MATCH(C104,Financial_Statement_Builder!$J$405:$J$488,0)) -> TRUE | H104: =H11&I11 | I104: =ISNUMBER(MATCH(H104,Financial_Statement_Builder!$M$405:$M$488,0)) -> TRUE | L104: =_xlfn.CONCAT(L11:M11) | M104: =ISNUMBER(MATCH(L104,Financial_Statement_Builder!$Q$405:$Q$488,0)) -> TRUE | P104: =P11&Q11 | Q104: =ISNUMBER(MATCH(P104,Financial_Statement_Builder!$T$405:$T$488,0)) -> TRUE | T104: =T11&U11 -> Accounts Receivable0 | U104: =ISNUMBER(MATCH(T104,Financial_Statement_Builder!$X$405:$X$488,0)) -> TRUE
C105: =C12&D12 -> Total Noncurrent Assets0 | D105: =ISNUMBER(MATCH(C105,Financial_Statement_Builder!$J$405:$J$488,0)) -> FALSE | H105: =H12&I12 -> EXPENSES | I105: =ISNUMBER(MATCH(H105,Financial_Statement_Builder!$M$405:$M$488,0)) -> TRUE | L105: =_xlfn.CONCAT(L12:M12) | M105: =ISNUMBER(MATCH(L105,Financial_Statement_Builder!$Q$405:$Q$488,0)) -> TRUE | P105: =P12&Q12 -> Total Cash Flow from Operating Activities39 | Q105: =ISNUMBER(MATCH(P105,Financial_Statement_Builder!$T$405:$T$488,0)) -> FALSE | T105: =T12&U12 -> Inventories42 | U105: =ISNUMBER(MATCH(T105,Financial_Statement_Builder!$X$405:$X$488,0)) -> FALSE
C106: =C13&D13 | D106: =ISNUMBER(MATCH(C106,Financial_Statement_Builder!$J$405:$J$488,0)) -> TRUE | H106: =H13&I13 | I106: =ISNUMBER(MATCH(H106,Financial_Statement_Builder!$M$405:$M$488,0)) -> TRUE | L106: =_xlfn.CONCAT(L13:M13) | M106: =ISNUMBER(MATCH(L106,Financial_Statement_Builder!$Q$405:$Q$488,0)) -> TRUE | P106: =P13&Q13 | Q106: =ISNUMBER(MATCH(P106,Financial_Statement_Builder!$T$405:$T$488,0)) -> TRUE | T106: =T13&U13 -> Total Current Assets179 | U106: =ISNUMBER(MATCH(T106,Financial_Statement_Builder!$X$405:$X$488,0)) -> FALSE
C107: =C14&D14 -> Total Assets0 | D107: =ISNUMBER(MATCH(C107,Financial_Statement_Builder!$J$405:$J$488,0)) -> FALSE | H107: =H14&I14 -> Cost of Goods Sold6 | I107: =ISNUMBER(MATCH(H107,Financial_Statement_Builder!$M$405:$M$488,0)) -> FALSE | L107: =_xlfn.CONCAT(L14:M14) | M107: =ISNUMBER(MATCH(L107,Financial_Statement_Builder!$Q$405:$Q$488,0)) -> TRUE | P107: =P14&Q14 -> Investing Activities | Q107: =ISNUMBER(MATCH(P107,Financial_Statement_Builder!$T$405:$T$488,0)) -> TRUE | T107: =T14&U14 | U107: =ISNUMBER(MATCH(T107,Financial_Statement_Builder!$X$405:$X$488,0)) -> TRUE
C108: =C15&D15 | D108: =ISNUMBER(MATCH(C108,Financial_Statement_Builder!$J$405:$J$488,0)) -> TRUE | H108: =H15&I15 -> Total Expenses6 | I108: =ISNUMBER(MATCH(H108,Financial_Statement_Builder!$M$405:$M$488,0)) -> FALSE | L108: =_xlfn.CONCAT(L15:M15) | M108: =ISNUMBER(MATCH(L108,Financial_Statement_Builder!$Q$405:$Q$488,0)) -> TRUE | P108: =P15&Q15 | Q108: =ISNUMBER(MATCH(P108,Financial_Statement_Builder!$T$405:$T$488,0)) -> TRUE | T108: =T15&U15 -> Noncurrent Assets: | U108: =ISNUMBER(MATCH(T108,Financial_Statement_Builder!$X$405:$X$488,0)) -> TRUE
C109: =C16&D16 -> LIABILITIES | D109: =ISNUMBER(MATCH(C109,Financial_Statement_Builder!$J$405:$J$488,0)) -> TRUE | H109: =H16&I16 | I109: =ISNUMBER(MATCH(H109,Financial_Statement_Builder!$M$405:$M$488,0)) -> TRUE | L109: =_xlfn.CONCAT(L16:M16) | M109: =ISNUMBER(MATCH(L109,Financial_Statement_Builder!$Q$405:$Q$488,0)) -> TRUE | P109: =P16&Q16 -> Financing Activities | Q109: =ISNUMBER(MATCH(P109,Financial_Statement_Builder!$T$405:$T$488,0)) -> TRUE | T109: =T16&U16 -> Property, Plant & Equipment100 | U109: =ISNUMBER(MATCH(T109,Financial_Statement_Builder!$X$405:$X$488,0)) -> FALSE
C110: =C17&D17 | D110: =ISNUMBER(MATCH(C110,Financial_Statement_Builder!$J$405:$J$488,0)) -> TRUE | H110: =H17&I17 -> Net Income12 | I110: =ISNUMBER(MATCH(H110,Financial_Statement_Builder!$M$405:$M$488,0)) -> FALSE | L110: =_xlfn.CONCAT(L17:M17) | M110: =ISNUMBER(MATCH(L110,Financial_Statement_Builder!$Q$405:$Q$488,0)) -> TRUE | P110: =P17&Q17 | Q110: =ISNUMBER(MATCH(P110,Financial_Statement_Builder!$T$405:$T$488,0)) -> TRUE | T110: =T17&U17 -> Land0 | U110: =ISNUMBER(MATCH(T110,Financial_Statement_Builder!$X$405:$X$488,0)) -> TRUE
C111: =C18&D18 | D111: =ISNUMBER(MATCH(C111,Financial_Statement_Builder!$J$405:$J$488,0)) -> TRUE | H111: =H18&I18 | I111: =ISNUMBER(MATCH(H111,Financial_Statement_Builder!$M$405:$M$488,0)) -> TRUE | L111: =_xlfn.CONCAT(L18:M18) | M111: =ISNUMBER(MATCH(L111,Financial_Statement_Builder!$Q$405:$Q$488,0)) -> TRUE | P111: =P18&Q18 -> Issued common stock50 | Q111: =ISNUMBER(MATCH(P111,Financial_Statement_Builder!$T$405:$T$488,0)) -> FALSE | T111: =T18&U18 -> Total Noncurrent Assets100 | U111: =ISNUMBER(MATCH(T111,Financial_Statement_Builder!$X$405:$X$488,0)) -> FALSE
... C154: =C61&D61 | D154: =ISNUMBER(MATCH(C154,Financial_Statement_Builder!$J$405:$J$488,0)) -> TRUE | H154: =H61&I61 | I154: =ISNUMBER(MATCH(H154,Financial_Statement_Builder!$M$405:$M$488,0)) -> TRUE | L154: =_xlfn.CONCAT(L61:M61) | M154: =ISNUMBER(MATCH(L154,Financial_Statement_Builder!$Q$405:$Q$488,0)) -> TRUE | P154: =P61&Q61 | Q154: =ISNUMBER(MATCH(P154,Financial_Statement_Builder!$T$405:$T$488,0)) -> TRUE | T154: =T61&U61 | U154: =ISNUMBER(MATCH(T154,Financial_Statement_Builder!$X$405:$X$488,0)) -> TRUE
H155: =H62&I62
H156: =H63&I63
H158: =COUNTIF(Journal!$D$7:$D$179,"Gain")>0 -> FALSE
E159: Absolute value | F159: Category active? | P159: Operating - Direct | V159: Absolute value | W159: Category active?
B160: 6 | C160: {=_xlfn._xlws.FILTER(CHOOSE({1,2},BCurrAssets[Account],BCurrAssets[Amt]),BCurrAssets[Used]=1,"")} -> Cash | D160: 0 | E160: =ABS(D160) -> 0 | F160: =SUM(E160:E169)>0.000001 -> FALSE | G160: 6 | H160: {=IF(J160,_xlfn._xlws.FILTER(CHOOSE({1,2},IS_Revenues[Account],IS_Revenues[AmtAnswer]),IS_Revenues[UsedAnswer]=1,""),{"",""})} -> Sales | I160: 18 | J160: =COUNTIF(JournalAnswer[Accnt Type],"Revenue")>0 -> TRUE | L160: Issued preferred stock | O160: 6 | P160: {=_xlfn._xlws.FILTER(CHOOSE({1,2},CFS_CFO[Account],CFS_CFO[AmtAnswer]),CFS_CFO[UsedAnswer]=1,"")} -> Collections from customers | Q160: 91 | S160: 6 | T160: {=_xlfn._xlws.FILTER(CHOOSE({1,2},ECurrAssets[Account],ECurrAssets[AmtAnswer]),ECurrAssets[Used]=1,"")} -> Cash | U160: 137 | V160: =ABS(U160) -> 137 | W160: =SUM(V160:V169)>0.000001 -> TRUE
B161: 7 | C161: Accounts Receivable | D161: 0 | E161: =ABS(D161) -> 0 | G161: 7 | L161: Issued common stock | O161: 7 | P161: Payments to suppliers | Q161: -52 | S161: 7 | T161: Accounts Receivable | U161: 0 | V161: =ABS(U161) -> 0
B162: 7 | C162: Inventories | D162: 0 | E162: =ABS(D162) -> 0 | G162: 7 | L162: Declared Dividends | O162: 7 | S162: 7 | T162: Inventories | U162: 42 | V162: =ABS(U162) -> 42
B163: 7 | E163: =ABS(D163) -> 0 | G163: 7 | L163: Net Income (Loss) | O163: 7 | S163: 7 | V163: =ABS(U163) -> 0
B164: 7 | E164: =ABS(D164) -> 0 | G164: 7 | L164: Purchased treasury stock | O164: 7 | S164: 7 | V164: =ABS(U164) -> 0
B165: 7 | E165: =ABS(D165) -> 0 | G165: 7 | L165: Sold treasury stock | O165: 7 | S165: 7 | V165: =ABS(U165) -> 0
B166: 7 | E166: =ABS(D166) -> 0 | G166: 7 | L166: Other Comprehensive Income (Loss) | O166: 7 | S166: 7 | V166: =ABS(U166) -> 0
B167: 7 | E167: =ABS(D167) -> 0 | G167: 7 | L167: Issued common stock for building | O167: 7 | S167: 7 | V167: =ABS(U167) -> 0
B168: 7 | E168: =ABS(D168) -> 0 | G168: 7 | L168: Stock-based compensation | O168: 7 | S168: 7 | V168: =ABS(U168) -> 0
B169: 7 | E169: =ABS(D169) -> 0 | G169: 7 | O169: 7 | S169: 7 | V169: =ABS(U169) -> 0
B170: 6 | C170: {=_xlfn._xlws.FILTER(CHOOSE({1,2},BNonCurrAssets[Account],BNonCurrAssets[Amt]),BNonCurrAssets[Used]=1,"")} -> Property, Plant & Equipment | D170: 0 | E170: =ABS(D170) -> 0 | F170: =SUM(E170:E179)>0.000001 -> FALSE | G170: 6 | H170: {=IF(J170,_xlfn._xlws.FILTER(CHOOSE({1,2},IS_Expenses[Account],IS_Expenses[AmtAnswer]),IS_Expenses[UsedAnswer]=1,""),{"",""})} -> Cost of Goods Sold | I170: 6 | J170: =COUNTIF(JournalAnswer[Accnt Type],"Expense")>0 -> TRUE | L170: Statement of Changes in Shareholders' Equity | O170: 7 | S170: 6 | T170: {=_xlfn._xlws.FILTER(CHOOSE({1,2},ENonCurrAssets[Account],ENonCurrAssets[AmtAnswer]),ENonCurrAssets[Used]=1,"")} -> Property, Plant & Equipment | U170: 100 | V170: =ABS(U170) -> 100 | W170: =SUM(V170:V179)>0.000001 -> TRUE
B171: 7 | C171: Land | D171: 0 | E171: =ABS(D171) -> 0 | G171: 7 | L171: Preferred Stock | M171: =IF(ABS(MAX(M172:M174)>0),1,0) -> 0 | O171: 7 | S171: 7 | T171: Land | U171: 0 | V171: =ABS(U171) -> 0
B172: 7 | E172: =ABS(D172) -> 0 | G172: 7 | K172: 5 | L172: ="Balance @ "&BegDate -> Balance @ 12/31/20x0 | M172: {=_xlfn._xlws.FILTER(BegBalanceSheet_Equities[Amount],BegBalanceSheet_Equities[Account]=L171,0)} -> 0 | O172: 7 | S172: 7 | V172: =ABS(U172) -> 0
B173: 7 | E173: =ABS(D173) -> 0 | G173: 7 | K173: 7 | L173: Issued Preferred Stock | M173: =FSConstruction!AG9 -> 0 | O173: 7 | S173: 7 | V173: =ABS(U173) -> 0
B174: 7 | E174: =ABS(D174) -> 0 | G174: 7 | K174: 5 | L174: ="Balance @ "&EndDate -> Balance @ 12/31/20x1 | M174: {=_xlfn._xlws.FILTER(EEquities[AmtAnswer],(EEquities[UsedAnswer]=1)*(EEquities[Account]=L171),0)} -> 0 | O174: 7 | S174: 7 | V174: =ABS(U174) -> 0
B175: 7 | E175: =ABS(D175) -> 0 | G175: 7 | K175: 8 | O175: 7 | S175: 7 | V175: =ABS(U175) -> 0
B176: 7 | E176: =ABS(D176) -> 0 | G176: 7 | L176: Common Stock | M176: =IF(ABS(MAX(M177:M181)>0),1,0) -> 1 | O176: 7 | S176: 7 | V176: =ABS(U176) -> 0
B177: 7 | E177: =ABS(D177) -> 0 | G177: 7 | K177: 5 | L177: ="Balance @ "&BegDate -> Balance @ 12/31/20x0 | M177: {=_xlfn._xlws.FILTER(BegBalanceSheet_Equities[Amount],BegBalanceSheet_Equities[Account]=L176,0)} -> 0 | N177: 1 | O177: 7 | S177: 7 | V177: =ABS(U177) -> 0
B178: 7 | E178: =ABS(D178) -> 0 | G178: 7 | K178: 7 | L178: Issued Common Stock | M178: =FSConstruction!AG10 -> 50 | N178: =IF(M178="",0,1) -> 1 | O178: 7 | S178: 7 | V178: =ABS(U178) -> 0
B179: 7 | E179: =ABS(D179) -> 0 | G179: 7 | K179: 7 | L179: Issued Common Stock for PP&E | M179: =FSConstruction!AG17 -> 50 | N179: =IF(M179="",0,1) -> 1 | P179: Investing | S179: 7 | V179: =ABS(U179) -> 0
B180: 6 | C180: {=_xlfn._xlws.FILTER(CHOOSE({1,2},BCurrLiabs[Account],BCurrLiabs[Amt]),BCurrLiabs[Used]=1,"")} -> Accounts Payable | D180: 0 | E180: =ABS(D180) -> 0 | F180: =SUM(E180:E189)>0.000001 -> FALSE | G180: 7 | K180: 7 | L180: Stock-based compensation | M180: =FSConstruction!AG19 -> 0 | N180: =IF(M180="",0,1) -> 1 | O180: 6 | P180: {=_xlfn._xlws.FILTER(CHOOSE({1,2},CFS_CFI[Account],CFS_CFI[AmtAnswer]),CFS_CFI[UsedAnswer]=1,"")} | S180: 6 | T180: {=_xlfn._xlws.FILTER(CHOOSE({1,2},ECurrLiabs[Account],ECurrLiabs[AmtAnswer]),ECurrLiabs[Used]=1,"")} -> Accounts Payable | U180: 2 | V180: =ABS(U180) -> 2 | W180: =SUM(V180:V189)>0.000001 -> TRUE
B181: 7 | C181: Dividends Payable | D181: 0 | E181: =ABS(D181) -> 0 | G181: 7 | K181: 5 | L181: ="Balance @ "&EndDate -> Balance @ 12/31/20x1 | M181: {=_xlfn._xlws.FILTER(EEquities[AmtAnswer],(EEquities[UsedAnswer]=1)*(EEquities[Account]=L176),0)} -> 100 | N181: 1 | O181: 7 | S181: 7 | T181: Dividends Payable | U181: 0 | V181: =ABS(U181) -> 0
B182: 7 | C182: Unearned Revenue | D182: 0 | E182: =ABS(D182) -> 0 | G182: 7 | K182: 8 | N182: 1 | O182: 7 | S182: 7 | T182: Unearned Revenue | U182: 8 | V182: =ABS(U182) -> 8
B183: 7 | E183: =ABS(D183) -> 0 | G183: 7 | L183: Additional Paid-in Capital | M183: =IF(ABS(MAX(M184:M188)>0),1,0) -> 1 | O183: 7 | S183: 7 | V183: =ABS(U183) -> 0
B184: 7 | E184: =ABS(D184) -> 0 | G184: 7 | K184: 5 | L184: ="Balance @ "&BegDate -> Balance @ 12/31/20x0 | M184: {=_xlfn._xlws.FILTER(BegBalanceSheet_Equities[Amount],BegBalanceSheet_Equities[Account]=L183,0)} -> 0 | N184: 1 | O184: 7 | S184: 7 | V184: =ABS(U184) -> 0
B185: 7 | E185: =ABS(D185) -> 0 | G185: 7 | K185: 7 | L185: Issued Common Stock - APIC | M185: =FSConstruction!AG11 -> 0 | N185: =IF(M185="",0,1) -> 1 | O185: 7 | S185: 7 | V185: =ABS(U185) -> 0
B186: 7 | E186: =ABS(D186) -> 0 | G186: 7 | K186: 7 | L186: Issued Common Stock for PP&E - APIC | M186: =FSConstruction!AG17 -> 50 | N186: =IF(M186="",0,1) -> 1 | O186: 7 | S186: 7 | V186: =ABS(U186) -> 0
B187: 7 | E187: =ABS(D187) -> 0 | G187: 7 | K187: 7 | L187: Stock-based compensation - APIC | M187: =FSConstruction!AG20 -> 0 | N187: =IF(M187="",0,1) -> 1 | O187: 7 | S187: 7 | V187: =ABS(U187) -> 0
...

Sheet FSData
C2: Dollars in Thousands
C4: 12/31/20x4 | F4: Explanations of Changes Made Using the Accounting Indentity over the Year | Y4: 12/31/20x5
AD5: Assets
C6: Balance Sheet | E6: 1 | F6: Income Statement | I6: 1 | J6: Statement of Changes in Shareholders' Equity | T6: 1 | U6: Cash Flow Statement | X6: 1 | Y6: Balance Sheet | AD6: None | AH6: None | AL6: None | AP6: None | AT6: None
C7: Assets | E7: 2 | F7: Revenues | H7: 0 | I7: 2 | J7: Equity Accounts | K7: CS | L7: Total | T7: 2 | U7: Operating | X7: 2 | Y7: Assets | AA7: 0 | AC7: BB | AD7: 0 | AE7: 0 | AF7: BB | AG7: BB | AH7: 0 | AI7: 0 | AJ7: BB | AK7: BB | AL7: 0 | AM7: 0 | AN7: BB | AO7: BB | AP7: 0 | AQ7: 0 | AR7: BB | AS7: BB | AT7: 0 | AU7: 0 | AV7: BB
C8: Current Assets | H8: 0 | I8: 3 | J8: Balance as of 12/31/20x4 | K8: 60 | L8: 60 | N8: 0 | O8: 0 | P8: 0 | Q8: 0 | R8: 0 | X8: 4 | Y8: Current Assets | AA8: 0 | AD8: 0 | AE8: 0 | AH8: 0 | AI8: 0 | AL8: 0 | AM8: 0 | AP8: 0 | AQ8: 0 | AT8: 0 | AU8: 0
C9: Cash | D9: 55 | H9: 0 | I9: 3 | J9: Balance as of 12/31/20x5 | K9: 60 | L9: 60 | N9: 0 | O9: 0 | P9: 0 | Q9: 0 | R9: 0 | X9: 6 | Y9: Cash | Z9: 55 | AA9: 0
C10: Inventories | D10: 0 | H10: 0 | T10: 2 | U10: Investing | X10: 7 | Y10: Inventories | Z10: 0 | AA10: 0
C11: Total Current Assets | D11: 55 | E11: 2 | F11: Expenses | H11: 0 | X11: 5 | Y11: Total Current Assets | Z11: 55 | AA11: 0
C12: Noncurrent Assets | H12: 0 | X12: 4 | Y12: Noncurrent Assets | AA12: 0
C13: Land | D13: 5 | H13: 0 | T13: 2 | U13: Financing | X13: 6 | Y13: Land | Z13: 5 | AA13: 0
C14: Total Noncurrent Assets | D14: 5 | H14: 0 | X14: 5 | Y14: Total Noncurrent Assets | Z14: 5 | AA14: 0
C15: Total Assets | D15: 60 | H15: 0 | X15: 3 | Y15: Total Assets | Z15: 60 | AA15: 0
C16: Liabilities | E16: 3 | F16: Net Income (Loss) | G16: 0 | H16: 0 | T16: 5 | U16: Cash @ 12/31/20x4 | V16: 55 | X16: 2 | Y16: Liabilities | AA16: 0
C17: Current Liabilities | H17: 0 | T17: 5 | U17: Cash @ 12/31/20x5 | V17: 55 | X17: 4 | Y17: Current Liabilities | AA17: 0
C18: No current liabilities | D18: 0 | H18: 0 | X18: 6 | Y18: No Current Liabilities | Z18: 0 | AA18: 0
C19: Total Current Liabilities | D19: 0 | H19: 0 | X19: 5 | Y19: Total Current Liabilities | Z19: 0 | AA19: 0 | AZ19: 1
C20: NonCurrent Liabilities | H20: 0 | T20: 1 | U20: Reconciliation of NI and CFO | X20: 4 | Y20: NonCurrent Liabilities | AA20: 0 | AC20: EB | AD20: 0 | AE20: 0 | AF20: EB | AG20: EB | AH20: 0 | AI20: 0 | AJ20: EB | AK20: EB | AL20: 0 | AM20: 0 | AN20: EB | AO20: EB | AP20: 0 | AQ20: 0 | AR20: EB | AS20: EB | AT20: 0 | AU20: 0 | AV20: EB
C21: No noncurrent liabilities | D21: 0 | H21: 0 | T21: 3 | U21: Net Income | V21: 0 | X21: 6 | Y21: No Noncurrent Liabilities | Z21: 0 | AA21: 0 | AD21: Liabilities
C22: Total Noncurrent Liabilities | D22: 0 | H22: 0 | T22: 4 | U22: Adjustments | X22: 5 | Y22: Total Noncurrent Liabilities | Z22: 0 | AA22: 0 | AD22: None | AH22: None | AL22: None | AP22: None | AT22: None
C23: Total Liabilities | D23: 0 | H23: 0 | X23: 3 | Y23: Total Liabilities | Z23: 0 | AA23: 0 | AC23: BB | AD23: 0 | AE23: 0 | AF23: BB | AG23: BB | AH23: 0 | AI23: 0 | AJ23: BB | AK23: BB | AL23: 0 | AM23: 0 | AN23: BB | AO23: BB | AP23: 0 | AQ23: 0 | AR23: BB | AS23: BB | AT23: 0 | AU23: 0 | AV23: BB
C24: Equities | H24: 0 | T24: 4 | U24: Changes in Assets and Liabilities Due to Operations | X24: 2 | Y24: Equities | AA24: 0 | AD24: 0 | AE24: 0 | AH24: 0 | AI24: 0 | AL24: 0 | AM24: 0 | AP24: 0 | AQ24: 0 | AT24: 0 | AU24: 0
C25: Common Stock | D25: 60 | H25: 0 | X25: 6 | Y25: Common Stock | Z25: 60 | AA25: 0
C26: Retained Earnings | D26: 0 | H26: 0 | T26: 3 | U26: Cash Flow from Operations | V26: 0 | X26: 7 | Y26: Retained Earnings | Z26: 0 | AA26: 0
C27: Total Equities | D27: 60 | H27: 0 | X27: 3 | Y27: Total Equities | Z27: 60 | AA27: 0
C28: Total Liabilities & Equities | D28: 60 | H28: 0 | X28: 3 | Y28: Total Liabilities & Equities | Z28: 60 | AA28: 0
H29: 0 | AA29: 0
H30: 0 | AA30: 0 | AC30: EB | AD30: 0 | AE30: 0 | AF30: EB | AG30: EB | AH30: 0 | AI30: 0 | AJ30: EB | AK30: EB | AL30: 0 | AM30: 0 | AN30: EB | AO30: EB | AP30: 0 | AQ30: 0 | AR30: EB | AS30: EB | AT30: 0 | AU30: 0 | AV30: EB
H31: 0 | AA31: 0 | AD31: Equities
H32: 0 | AA32: 0 | AD32: None | AH32: None | AL32: None | AP32: None | AT32: None
H33: 0 | AA33: 0 | AC33: BB | AD33: 0 | AE33: 0 | AF33: BB | AG33: BB | AH33: 0 | AI33: 0 | AJ33: BB | AK33: BB | AL33: 0 | AM33: 0 | AN33: BB | AO33: BB | AP33: 0 | AQ33: 0 | AR33: BB | AS33: BB | AT33: 0 | AU33: 0 | AV33: BB
H34: 0 | AA34: 0 | AD34: 0 | AE34: 0 | AH34: 0 | AI34: 0 | AL34: 0 | AM34: 0 | AP34: 0 | AQ34: 0 | AT34: 0 | AU34: 0
H35: 0 | AA35: 0
H36: 0 | AA36: 0
H37: 0 | AA37: 0
H38: 0 | AA38: 0
H39: 0 | AA39: 0
H40: 0 | AA40: 0 | AC40: EB | AD40: 0 | AE40: 0 | AF40: EB | AG40: EB | AH40: 0 | AI40: 0 | AJ40: EB | AK40: EB | AL40: 0 | AM40: 0 | AN40: EB | AO40: EB | AP40: 0 | AQ40: 0 | AR40: EB | AS40: EB | AT40: 0 | AU40: 0 | AV40: EB
H41: 0 | AA41: 0 | AD41: Revenues and Gains
H42: 0 | AA42: 0 | AD42: None | AH42: None | AL42: None | AP42: None | AT42: None
H43: 0 | AA43: 0 | AD43: 0 | AE43: 0 | AH43: 0 | AI43: 0 | AL43: 0 | AM43: 0 | AP43: 0 | AQ43: 0 | AT43: 0 | AU43: 0
H44: 0 | AA44: 0
H45: 0 | AA45: 0
H46: 0 | AA46: 0
H47: 0 | AA47: 0
H48: 0 | AA48: 0
H49: 0 | AA49: 0
H50: 0 | AA50: 0 | AC50: EB | AD50: 0 | AE50: 0 | AF50: EB | AG50: EB | AH50: 0 | AI50: 0 | AJ50: EB | AK50: EB | AL50: 0 | AM50: 0 | AN50: EB | AO50: EB | AP50: 0 | AQ50: 0 | AR50: EB | AS50: EB | AT50: 0 | AU50: 0 | AV50: EB
H51: 0 | AA51: 0 | AD51: Expenses and Losses
H52: 0 | AA52: 0 | AD52: None | AH52: None | AL52: None | AP52: None | AT52: None
H53: 0 | AA53: 0 | AD53: 0 | AE53: 0 | AH53: 0 | AI53: 0 | AL53: 0 | AM53: 0 | AP53: 0 | AQ53: 0 | AT53: 0 | AU53: 0
H54: 0 | AA54: 0
H55: 0 | AA55: 0
H56: 0 | AA56: 0
H57: 0 | AA57: 0
H58: 0 | AA58: 0
H59: 0 | AA59: 0
H60: 0 | AA60: 0
AA61: 0
AA62: 0
AA63: 0
AA64: 0
C100: Assets | F100: Revenues | G100: TRUE | J100: Equity AccountsCSTotal | K100: TRUE | U100: Operating | V100: TRUE | Y100: Assets | Z100: NotFound | AS100: Type | AT100: Account | AU100: Order (1st is index 0)
C101: Current Assets | G101: FALSE | J101: Balance as of 12/31/20x4606000000 | K101: TRUE | V101: FALSE | Y101: Current Assets | Z101: NotFound | AQ101: Indicator for use of a Temporary Account | AR101: 0 | AU101: 0
C102: Cash55 | G102: FALSE | J102: Balance as of 12/31/20x5606000000 | K102: TRUE | V102: FALSE | Y102: Cash55 | Z102: NotFound | AQ102: Revenue | AU102: 1
C103: Inventories0 | G103: FALSE | K103: NotFound | U103: Investing | V103: TRUE | Y103: Inventories0 | Z103: NotFound | AQ103: Expense
C104: Total Current Assets55 | F104: Expenses | G104: TRUE | K104: NotFound | V104: FALSE | Y104: Total Current Assets55 | Z104: NotFound | AQ104: Gain
C105: Noncurrent Assets | G105: FALSE | K105: NotFound | V105: FALSE | Y105: Noncurrent Assets | Z105: NotFound | AQ105: Loss
C106: Land5 | G106: FALSE | K106: NotFound | U106: Financing | V106: TRUE | Y106: Land5 | Z106: NotFound
C107: Total Noncurrent Assets5 | G107: FALSE | K107: NotFound | V107: FALSE | Y107: Total Noncurrent Assets5 | Z107: NotFound
C108: Total Assets60 | G108: FALSE | K108: NotFound | V108: FALSE | Y108: Total Assets60 | Z108: NotFound
C109: Liabilities | F109: Net Income (Loss)0 | G109: TRUE | K109: NotFound | U109: Cash @ 12/31/20x455 | V109: TRUE | Y109: Liabilities | Z109: NotFound
C110: Current Liabilities | G110: FALSE | K110: NotFound | U110: Cash @ 12/31/20x555 | V110: TRUE | Y110: Current Liabilities | Z110: NotFound
C111: No current liabilities0 | G111: FALSE | K111: NotFound | V111: FALSE | Y111: No Current Liabilities0 | Z111: NotFound
C112: Total Current Liabilities0 | G112: FALSE | K112: NotFound | V112: FALSE | Y112: Total Current Liabilities0 | Z112: NotFound
C113: NonCurrent Liabilities | G113: FALSE | K113: NotFound | U113: Reconciliation of NI and CFO | V113: TRUE | Y113: NonCurrent Liabilities | Z113: NotFound
C114: No noncurrent liabilities0 | G114: FALSE | K114: NotFound | U114: Net Income0 | V114: TRUE | Y114: No Noncurrent Liabilities0 | Z114: NotFound
C115: Total Noncurrent Liabilities0 | G115: FALSE | K115: NotFound | U115: Adjustments | V115: TRUE | Y115: Total Noncurrent Liabilities0 | Z115: NotFound
C116: Total Liabilities0 | G116: FALSE | K116: NotFound | V116: FALSE | Y116: Total Liabilities0 | Z116: NotFound
C117: Equities | G117: FALSE | K117: NotFound | U117: Changes in Assets and Liabilities Due to Operations | V117: TRUE | Y117: Equities | Z117: NotFound
C118: Common Stock60 | G118: FALSE | K118: NotFound | V118: FALSE | Y118: Common Stock60 | Z118: NotFound
C119: Retained Earnings0 | G119: FALSE | K119: NotFound | U119: Cash Flow from Operations0 | V119: TRUE | Y119: Retained Earnings0 | Z119: NotFound
C120: Total Equities60 | G120: FALSE | K120: NotFound | V120: FALSE | Y120: Total Equities60 | Z120: NotFound
C121: =C28&D28 -> Total Liabilities & Equities60 | F121: =F28&G28 | I121: =_xlfn.CONCAT(I28:Q28) | S121: =_xlfn.CONCAT(S28:T28) | U121: =_xlfn.CONCAT(U28:V28) | V121: =_xlfn.CONCAT(V28:W28)
C122: =C29&D29 | F122: =F29&G29 | I122: =_xlfn.CONCAT(I29:Q29) | S122: =_xlfn.CONCAT(S29:T29) | U122: =_xlfn.CONCAT(U29:V29) | V122: =_xlfn.CONCAT(V29:W29)
C123: =C30&D30 | F123: =F30&G30 | I123: =_xlfn.CONCAT(I30:Q30) | S123: =_xlfn.CONCAT(S30:T30) | U123: =_xlfn.CONCAT(U30:V30)
C124: =C31&D31 | F124: =F31&G31 | I124: =_xlfn.CONCAT(I31:Q31) | S124: =_xlfn.CONCAT(S31:T31) | U124: =_xlfn.CONCAT(U31:V31)
C125: =C32&D32 | F125: =F32&G32 | I125: =_xlfn.CONCAT(I32:Q32) | S125: =_xlfn.CONCAT(S32:T32) | U125: =_xlfn.CONCAT(U32:V32)
C126: =C33&D33 | F126: =F33&G33 | I126: =_xlfn.CONCAT(I33:Q33) | S126: =_xlfn.CONCAT(S33:T33) | U126: =_xlfn.CONCAT(U33:V33)
C127: =C34&D34 | F127: =F34&G34 | I127: =_xlfn.CONCAT(I34:Q34) | S127: =_xlfn.CONCAT(S34:T34) | U127: =_xlfn.CONCAT(U34:V34) | V127: =_xlfn.CONCAT(V34:W34)
C128: =C35&D35 | F128: =F35&G35 | I128: =_xlfn.CONCAT(I35:Q35) | S128: =_xlfn.CONCAT(S35:T35) | U128: =_xlfn.CONCAT(U35:V35) | V128: =_xlfn.CONCAT(V35:W35)
C129: =C36&D36 | F129: =F36&G36 | I129: =_xlfn.CONCAT(I36:Q36) | S129: =_xlfn.CONCAT(S36:T36) | U129: =_xlfn.CONCAT(U36:V36) | V129: =_xlfn.CONCAT(V36:W36)
C130: =C37&D37 | F130: =F37&G37 | I130: =_xlfn.CONCAT(I37:Q37) | S130: =_xlfn.CONCAT(S37:T37) | U130: =_xlfn.CONCAT(U37:V37) | V130: =_xlfn.CONCAT(V37:W37)
C131: =C38&D38 | F131: =F38&G38 | I131: =_xlfn.CONCAT(I38:Q38) | S131: =_xlfn.CONCAT(S38:T38) | U131: =_xlfn.CONCAT(U38:V38) | V131: =_xlfn.CONCAT(V38:W38)
C132: =C39&D39 | F132: =F39&G39 | I132: =_xlfn.CONCAT(I39:Q39) | S132: =_xlfn.CONCAT(S39:T39) | U132: =_xlfn.CONCAT(U39:V39) | V132: =_xlfn.CONCAT(V39:W39)
C133: =C40&D40 | F133: =F40&G40 | I133: =_xlfn.CONCAT(I40:Q40) | S133: =_xlfn.CONCAT(S40:T40) | U133: =_xlfn.CONCAT(U40:V40) | V133: =_xlfn.CONCAT(V40:W40)
C134: =C41&D41 | F134: =F41&G41 | I134: =_xlfn.CONCAT(I41:Q41) | S134: =_xlfn.CONCAT(S41:T41) | U134: =_xlfn.CONCAT(U41:V41) | V134: =_xlfn.CONCAT(V41:W41)
C135: =C42&D42 | F135: =F42&G42 | I135: =_xlfn.CONCAT(I42:Q42) | S135: =_xlfn.CONCAT(S42:T42) | U135: =_xlfn.CONCAT(U42:V42) | V135: =_xlfn.CONCAT(V42:W42)
C136: =C43&D43 | F136: =F43&G43 | I136: =_xlfn.CONCAT(I43:Q43) | S136: =_xlfn.CONCAT(S43:T43) | U136: =_xlfn.CONCAT(U43:V43) | V136: =_xlfn.CONCAT(V43:W43)
C137: =C44&D44 | F137: =F44&G44 | I137: =_xlfn.CONCAT(I44:Q44) | S137: =_xlfn.CONCAT(S44:T44) | U137: =_xlfn.CONCAT(U44:V44) | V137: =_xlfn.CONCAT(V44:W44)
...

Sheet Instructions
B2: Basic Information
B3: Entity
B4: Entity: | C4: =IF(ProblemData!E61="","",ProblemData!E61) -> Accounting Identity LLC
B5: Type: | C5: =IF(ProblemData!E62="","",ProblemData!E62) -> For-profit corporation
B6: Activity: | C6: =IF(ProblemData!E63="","",ProblemData!E63) -> Service
B7: Dates and Period
B8: Period Beginning: | C8: =IF(ProblemData!E64="","",ProblemData!E64) -> 12/31/20x0
B9: Period Ending: | C9: =IF(ProblemData!E65="","",ProblemData!E65) -> 12/31/20x1
B10: Period Length: | C10: =IF(ProblemData!E67="","",ProblemData!E67) -> Year
B11: Units and Shares
B12: Units: | C12: =IF(ProblemData!E68="","",ProblemData!E68) -> Dollars in Thousands
B13: Shares Outstanding: | C13: =IF(ProblemData!E69="","",ProblemData!E69) -> 1000
B14: Par Value per Share: | C14: =IF(ProblemData!E70="","",ProblemData!E70) -> 0
B18: Requirements:
B19: Number | C19: Action: | D19: Item: | H19: Location:
B20: #1 | C20: {=_xlfn._xlws.FILTER(RequirementsChosen[Action],RequirementsChosen[Action]<>"Omit")} -> Enter | D20: {=_xlfn._xlws.FILTER(RequirementsChosen[Item],RequirementsChosen[Action]<>"Omit")} -> Accounting Identity | H20: {=_xlfn._xlws.FILTER(RequirementsChosen[Tab],RequirementsChosen[Action]<>"Omit")} -> Analysis_Help
B21: #2
B22: #3
B23: #4
B24: #5
B25: #6
B26: #7
B27: #8
B28: #9
B29: #10
B30: #11
B31: #12
B33: Chart of Accounts
B35: Permanent Accounts | C35: Assets | E35: Liabilities | G35: Equities
C36: {=IFERROR(_xlfn._xlws.FILTER(MD_Asset[[#All],[Account Name]],MD_Asset[[#All],[Used]]=1),"")} -> Cash | E36: {=IFERROR(_xlfn._xlws.FILTER(MD_Liability[[#All],[Account Name]],MD_Liability[[#All],[Used]]=1),"")} -> Accounts Payable | G36: {=IFERROR(_xlfn._xlws.FILTER(MD_Equity[[#All],[Account Name]],MD_Equity[[#All],[Used]]=1),"")} -> Common Stock
C37: Accounts Receivable | E37: Dividends Payable | G37: Retained Earnings
C38: Inventories | E38: Unearned Revenue
C39: Property, Plant & Equipment | E39: Loans Payable
C40: Land
B49: Temporary Accounts | C49: Revenues | E49: Expenses | G49: Gains | I49: Losses
C50: {=IFERROR(_xlfn._xlws.FILTER(MD_Revenue[[#All],[Account Name]],MD_Revenue[[#All],[Used]]=1),"")} -> Sales | E50: {=IFERROR(_xlfn._xlws.FILTER(MD_Expense[[#All],[Account Name]],MD_Expense[[#All],[Used]]=1),"")} -> Cost of Goods Sold | G50: {=IFERROR(_xlfn._xlws.FILTER(MD_Gain[[#All],[Account Name]],MD_Gain[[#All],[Used]]=1),"")} | I50: {=IFERROR(_xlfn._xlws.FILTER(MD_Loss[[#All],[Account Name]],MD_Loss[[#All],[Used]]=1),"")}
B64: This problem will help you:
B65: #1 | C65: {=PurposesUsed} -> Expand your financial vocabulary.
B66: #2 | C66: Use the Accounting Identity to analyze transactions.
B67: #3 | C67: Learn how to use the Analysis_Help
B68: #4
B69: #5

Sheet Journal
C2: Transaction # | D2: 1
C3: Transaction Description | L3: X
C4: {=INDEX(ProblemData!D78:AN79,2,D2+1)} -> Receives $50k in cash from its shareholders in exchange for issuing common stock. | L4: X
L5: X
L6: X
L7: X
C9: ="Journal for "&BegDate&" to "&EndDate -> Journal for 12/31/20x0 to 12/31/20x1 | I9: Balance?
I10: =IF(ROUND(SUM(Journal[Dr Amt])-SUM(Journal[Cr Amt]),2)=0,"YES",ROUND(SUM(Journal[Dr Amt])-SUM(Journal[Cr Amt]),2)) -> YES
C11: Transaction # | D11: Accnt Type | E11: Debit Account | F11: Credit Account | G11: Dr Amt | H11: Cr Amt | I11: Cash Flow | J11: Movement # | K11: Cash | L11: ref1 | M11: ref2 | N11: ref3
J12: =IF(Journal[[#This Row],[Transaction '#]]="","",IF(Journal[[#This Row],[Transaction '#]]=C11,J11+1,1)) | K12: {=IFERROR(_xlfn.IFS(Journal[[#This Row],[Debit Account]]="Cash",Journal[[#This Row],[Dr Amt]],Journal[[#This Row],[Credit Account]]="Cash",-Journal[[#This Row],[Cr Amt]]),0)} -> 0 | L12: {=IF(Journal[[#This Row],[Transaction '#]]<>"",IFERROR(INDEX(ProblemData!$E$239:$AM$239,1,Journal[[#This Row],[Transaction '#]]),""),"")} | M12: =IF(Journal[[#This Row],[ref1]]="","",IF(NOT(ISBLANK(Journal[[#This Row],[Transaction '#]])),Journal[[#This Row],[ref1]]&Journal[[#This Row],[Movement '#]],"")) | N12: =OR(Journal[[#This Row],[ref1]]="",ISNUMBER(MATCH(Journal[[#This Row],[ref1]], Operating[Abbr], 0)), "Found", "Not Found"="Found") -> TRUE | P12: =Journal[[#This Row],[Accnt Type]]&"Used" -> Used
J13: =IF(Journal[[#This Row],[Transaction '#]]="","",IF(Journal[[#This Row],[Transaction '#]]=C12,J12+1,1)) | K13: {=IFERROR(_xlfn.IFS(Journal[[#This Row],[Debit Account]]="Cash",Journal[[#This Row],[Dr Amt]],Journal[[#This Row],[Credit Account]]="Cash",-Journal[[#This Row],[Cr Amt]]),0)} -> 0 | L13: {=IF(Journal[[#This Row],[Transaction '#]]<>"",IFERROR(INDEX(ProblemData!$E$239:$AM$239,1,Journal[[#This Row],[Transaction '#]]),""),"")} | M13: =IF(Journal[[#This Row],[ref1]]="","",IF(NOT(ISBLANK(Journal[[#This Row],[Transaction '#]])),Journal[[#This Row],[ref1]]&Journal[[#This Row],[Movement '#]],"")) | N13: =OR(Journal[[#This Row],[ref1]]="",ISNUMBER(MATCH(Journal[[#This Row],[ref1]], Operating[Abbr], 0)), "Found", "Not Found"="Found") -> TRUE | P13: =Journal[[#This Row],[Accnt Type]]&"Used" -> Used
J14: =IF(Journal[[#This Row],[Transaction '#]]="","",IF(Journal[[#This Row],[Transaction '#]]=C13,J13+1,1)) | K14: {=IFERROR(_xlfn.IFS(Journal[[#This Row],[Debit Account]]="Cash",Journal[[#This Row],[Dr Amt]],Journal[[#This Row],[Credit Account]]="Cash",-Journal[[#This Row],[Cr Amt]]),0)} -> 0 | L14: {=IF(Journal[[#This Row],[Transaction '#]]<>"",IFERROR(INDEX(ProblemData!$E$239:$AM$239,1,Journal[[#This Row],[Transaction '#]]),""),"")} | M14: =IF(Journal[[#This Row],[ref1]]="","",IF(NOT(ISBLANK(Journal[[#This Row],[Transaction '#]])),Journal[[#This Row],[ref1]]&Journal[[#This Row],[Movement '#]],"")) | N14: =OR(Journal[[#This Row],[ref1]]="",ISNUMBER(MATCH(Journal[[#This Row],[ref1]], Operating[Abbr], 0)), "Found", "Not Found"="Found") -> TRUE | P14: =Journal[[#This Row],[Accnt Type]]&"Used" -> Used
J15: =IF(Journal[[#This Row],[Transaction '#]]="","",IF(Journal[[#This Row],[Transaction '#]]=C14,J14+1,1)) | K15: {=IFERROR(_xlfn.IFS(Journal[[#This Row],[Debit Account]]="Cash",Journal[[#This Row],[Dr Amt]],Journal[[#This Row],[Credit Account]]="Cash",-Journal[[#This Row],[Cr Amt]]),0)} -> 0 | L15: {=IF(Journal[[#This Row],[Transaction '#]]<>"",IFERROR(INDEX(ProblemData!$E$239:$AM$239,1,Journal[[#This Row],[Transaction '#]]),""),"")} | M15: =IF(Journal[[#This Row],[ref1]]="","",IF(NOT(ISBLANK(Journal[[#This Row],[Transaction '#]])),Journal[[#This Row],[ref1]]&Journal[[#This Row],[Movement '#]],"")) | N15: =OR(Journal[[#This Row],[ref1]]="",ISNUMBER(MATCH(Journal[[#This Row],[ref1]], Operating[Abbr], 0)), "Found", "Not Found"="Found") -> TRUE | P15: =Journal[[#This Row],[Accnt Type]]&"Used" -> Used
J16: =IF(Journal[[#This Row],[Transaction '#]]="","",IF(Journal[[#This Row],[Transaction '#]]=C15,J15+1,1)) | K16: {=IFERROR(_xlfn.IFS(Journal[[#This Row],[Debit Account]]="Cash",Journal[[#This Row],[Dr Amt]],Journal[[#This Row],[Credit Account]]="Cash",-Journal[[#This Row],[Cr Amt]]),0)} -> 0 | L16: {=IF(Journal[[#This Row],[Transaction '#]]<>"",IFERROR(INDEX(ProblemData!$E$239:$AM$239,1,Journal[[#This Row],[Transaction '#]]),""),"")} | M16: =IF(Journal[[#This Row],[ref1]]="","",IF(NOT(ISBLANK(Journal[[#This Row],[Transaction '#]])),Journal[[#This Row],[ref1]]&Journal[[#This Row],[Movement '#]],"")) | N16: =OR(Journal[[#This Row],[ref1]]="",ISNUMBER(MATCH(Journal[[#This Row],[ref1]], Operating[Abbr], 0)), "Found", "Not Found"="Found") -> TRUE | P16: =Journal[[#This Row],[Accnt Type]]&"Used" -> Used
J17: =IF(Journal[[#This Row],[Transaction '#]]="","",IF(Journal[[#This Row],[Transaction '#]]=C16,J16+1,1)) | K17: {=IFERROR(_xlfn.IFS(Journal[[#This Row],[Debit Account]]="Cash",Journal[[#This Row],[Dr Amt]],Journal[[#This Row],[Credit Account]]="Cash",-Journal[[#This Row],[Cr Amt]]),0)} -> 0 | L17: {=IF(Journal[[#This Row],[Transaction '#]]<>"",IFERROR(INDEX(ProblemData!$E$239:$AM$239,1,Journal[[#This Row],[Transaction '#]]),""),"")} | M17: =IF(Journal[[#This Row],[ref1]]="","",IF(NOT(ISBLANK(Journal[[#This Row],[Transaction '#]])),Journal[[#This Row],[ref1]]&Journal[[#This Row],[Movement '#]],"")) | N17: =OR(Journal[[#This Row],[ref1]]="",ISNUMBER(MATCH(Journal[[#This Row],[ref1]], Operating[Abbr], 0)), "Found", "Not Found"="Found") -> TRUE | P17: =Journal[[#This Row],[Accnt Type]]&"Used" -> Used
J18: =IF(Journal[[#This Row],[Transaction '#]]="","",IF(Journal[[#This Row],[Transaction '#]]=C17,J17+1,1)) | K18: {=IFERROR(_xlfn.IFS(Journal[[#This Row],[Debit Account]]="Cash",Journal[[#This Row],[Dr Amt]],Journal[[#This Row],[Credit Account]]="Cash",-Journal[[#This Row],[Cr Amt]]),0)} -> 0 | L18: {=IF(Journal[[#This Row],[Transaction '#]]<>"",IFERROR(INDEX(ProblemData!$E$239:$AM$239,1,Journal[[#This Row],[Transaction '#]]),""),"")} | M18: =IF(Journal[[#This Row],[ref1]]="","",IF(NOT(ISBLANK(Journal[[#This Row],[Transaction '#]])),Journal[[#This Row],[ref1]]&Journal[[#This Row],[Movement '#]],"")) | N18: =OR(Journal[[#This Row],[ref1]]="",ISNUMBER(MATCH(Journal[[#This Row],[ref1]], Operating[Abbr], 0)), "Found", "Not Found"="Found") -> TRUE | P18: =Journal[[#This Row],[Accnt Type]]&"Used" -> Used
J19: =IF(Journal[[#This Row],[Transaction '#]]="","",IF(Journal[[#This Row],[Transaction '#]]=C18,J18+1,1)) | K19: {=IFERROR(_xlfn.IFS(Journal[[#This Row],[Debit Account]]="Cash",Journal[[#This Row],[Dr Amt]],Journal[[#This Row],[Credit Account]]="Cash",-Journal[[#This Row],[Cr Amt]]),0)} -> 0 | L19: {=IF(Journal[[#This Row],[Transaction '#]]<>"",IFERROR(INDEX(ProblemData!$E$239:$AM$239,1,Journal[[#This Row],[Transaction '#]]),""),"")} | M19: =IF(Journal[[#This Row],[ref1]]="","",IF(NOT(ISBLANK(Journal[[#This Row],[Transaction '#]])),Journal[[#This Row],[ref1]]&Journal[[#This Row],[Movement '#]],"")) | N19: =OR(Journal[[#This Row],[ref1]]="",ISNUMBER(MATCH(Journal[[#This Row],[ref1]], Operating[Abbr], 0)), "Found", "Not Found"="Found") -> TRUE | P19: =Journal[[#This Row],[Accnt Type]]&"Used" -> Used
J20: =IF(Journal[[#This Row],[Transaction '#]]="","",IF(Journal[[#This Row],[Transaction '#]]=C19,J19+1,1)) | K20: {=IFERROR(_xlfn.IFS(Journal[[#This Row],[Debit Account]]="Cash",Journal[[#This Row],[Dr Amt]],Journal[[#This Row],[Credit Account]]="Cash",-Journal[[#This Row],[Cr Amt]]),0)} -> 0 | L20: {=IF(Journal[[#This Row],[Transaction '#]]<>"",IFERROR(INDEX(ProblemData!$E$239:$AM$239,1,Journal[[#This Row],[Transaction '#]]),""),"")} | M20: =IF(Journal[[#This Row],[ref1]]="","",IF(NOT(ISBLANK(Journal[[#This Row],[Transaction '#]])),Journal[[#This Row],[ref1]]&Journal[[#This Row],[Movement '#]],"")) | N20: =OR(Journal[[#This Row],[ref1]]="",ISNUMBER(MATCH(Journal[[#This Row],[ref1]], Operating[Abbr], 0)), "Found", "Not Found"="Found") -> TRUE | P20: =Journal[[#This Row],[Accnt Type]]&"Used" -> Used
J21: =IF(Journal[[#This Row],[Transaction '#]]="","",IF(Journal[[#This Row],[Transaction '#]]=C20,J20+1,1)) | K21: {=IFERROR(_xlfn.IFS(Journal[[#This Row],[Debit Account]]="Cash",Journal[[#This Row],[Dr Amt]],Journal[[#This Row],[Credit Account]]="Cash",-Journal[[#This Row],[Cr Amt]]),0)} -> 0 | L21: {=IF(Journal[[#This Row],[Transaction '#]]<>"",IFERROR(INDEX(ProblemData!$E$239:$AM$239,1,Journal[[#This Row],[Transaction '#]]),""),"")} | M21: =IF(Journal[[#This Row],[ref1]]="","",IF(NOT(ISBLANK(Journal[[#This Row],[Transaction '#]])),Journal[[#This Row],[ref1]]&Journal[[#This Row],[Movement '#]],"")) | N21: =OR(Journal[[#This Row],[ref1]]="",ISNUMBER(MATCH(Journal[[#This Row],[ref1]], Operating[Abbr], 0)), "Found", "Not Found"="Found") -> TRUE | P21: =Journal[[#This Row],[Accnt Type]]&"Used" -> Used
J22: =IF(Journal[[#This Row],[Transaction '#]]="","",IF(Journal[[#This Row],[Transaction '#]]=C21,J21+1,1)) | K22: {=IFERROR(_xlfn.IFS(Journal[[#This Row],[Debit Account]]="Cash",Journal[[#This Row],[Dr Amt]],Journal[[#This Row],[Credit Account]]="Cash",-Journal[[#This Row],[Cr Amt]]),0)} -> 0 | L22: {=IF(Journal[[#This Row],[Transaction '#]]<>"",IFERROR(INDEX(ProblemData!$E$239:$AM$239,1,Journal[[#This Row],[Transaction '#]]),""),"")} | M22: =IF(Journal[[#This Row],[ref1]]="","",IF(NOT(ISBLANK(Journal[[#This Row],[Transaction '#]])),Journal[[#This Row],[ref1]]&Journal[[#This Row],[Movement '#]],"")) | N22: =OR(Journal[[#This Row],[ref1]]="",ISNUMBER(MATCH(Journal[[#This Row],[ref1]], Operating[Abbr], 0)), "Found", "Not Found"="Found") -> TRUE | P22: =Journal[[#This Row],[Accnt Type]]&"Used" -> Used
J23: =IF(Journal[[#This Row],[Transaction '#]]="","",IF(Journal[[#This Row],[Transaction '#]]=C22,J22+1,1)) | K23: {=IFERROR(_xlfn.IFS(Journal[[#This Row],[Debit Account]]="Cash",Journal[[#This Row],[Dr Amt]],Journal[[#This Row],[Credit Account]]="Cash",-Journal[[#This Row],[Cr Amt]]),0)} -> 0 | L23: {=IF(Journal[[#This Row],[Transaction '#]]<>"",IFERROR(INDEX(ProblemData!$E$239:$AM$239,1,Journal[[#This Row],[Transaction '#]]),""),"")} | M23: =IF(Journal[[#This Row],[ref1]]="","",IF(NOT(ISBLANK(Journal[[#This Row],[Transaction '#]])),Journal[[#This Row],[ref1]]&Journal[[#This Row],[Movement '#]],"")) | N23: =OR(Journal[[#This Row],[ref1]]="",ISNUMBER(MATCH(Journal[[#This Row],[ref1]], Operating[Abbr], 0)), "Found", "Not Found"="Found") -> TRUE | P23: =Journal[[#This Row],[Accnt Type]]&"Used" -> Used
... J197: =IF(Journal[[#This Row],[Transaction '#]]="","",IF(Journal[[#This Row],[Transaction '#]]=C196,J196+1,1)) | K197: {=IFERROR(_xlfn.IFS(Journal[[#This Row],[Debit Account]]="Cash",Journal[[#This Row],[Dr Amt]],Journal[[#This Row],[Credit Account]]="Cash",-Journal[[#This Row],[Cr Amt]]),0)} -> 0 | L197: {=IF(Journal[[#This Row],[Transaction '#]]<>"",IFERROR(INDEX(ProblemData!$E$239:$AM$239,1,Journal[[#This Row],[Transaction '#]]),""),"")} | M197: =IF(Journal[[#This Row],[ref1]]="","",IF(NOT(ISBLANK(Journal[[#This Row],[Transaction '#]])),Journal[[#This Row],[ref1]]&Journal[[#This Row],[Movement '#]],"")) | N197: =OR(Journal[[#This Row],[ref1]]="",ISNUMBER(MATCH(Journal[[#This Row],[ref1]], Operating[Abbr], 0)), "Found", "Not Found"="Found") -> TRUE | P197: =Journal[[#This Row],[Accnt Type]]&"Used" -> Used

Sheet FSConstruction
A1: =Entity -> Accounting Identity LLC
A2: Note: If you add an account in MasterData, you must copy and paste the account titles into the statement pieces as appropriate. | AE2: Statement of Changes in Shareholders' Equity | AP2: Cash Flow Statement
B3: ="Balance Sheet" -> Balance Sheet | H3: Income Statement | S3: Statement of Comprehensive Income | AE3: ="for the "&Period&" Ended " -> for the Year Ended | AP3: ="for the "&Period&" Ended " -> for the Year Ended | BL3: ="Balance Sheet" -> Balance Sheet
B4: ="as of " -> as of | H4: ="for the "&Period&" Ended " -> for the Year Ended | S4: ="for the "&Period&" Ended " -> for the Year Ended | AE4: =EndDate -> 12/31/20x1 | AP4: =EndDate -> 12/31/20x1 | BL4: ="as of " -> as of
B5: =BegDate -> 12/31/20x0 | H5: =EndDate -> 12/31/20x1 | S5: =EndDate -> 12/31/20x1 | AE5: =Units -> Dollars in Thousands | AP5: =Units -> Dollars in Thousands | BL5: =EndDate -> 12/31/20x1
B6: =Units -> Dollars in Thousands | H6: =Units -> Dollars in Thousands | S6: =Units -> Dollars in Thousands | BA6: Reconciliation of Net Income and Cash Flow from Operations | BL6: =Units -> Dollars in Thousands
AP7: Cash Flow from Operations | BA7: 3 | BB7: Net Income | BE7: =L54 -> 0 | BF7: =M54 -> 12 | BG7: =N54 -> 0 | BL7: Assets
B8: Assets | H8: Revenues | S8: Other Comprehensive Income (Loss), net of tax | AE8: Item | AF8: AmtJournal | AG8: AmtAnswer | AP8: FC | AQ8: Account | AR8: Used | AS8: Order | AT8: AmtJournal | AU8: AmtAnswer | AV8: AmtFSBuilder | AW8: UsedJournal | AX8: UsedAnswer | AY8: UsedFSBuilder | BA8: Adjustments needed to reconcile NI to CFO: | BL8: Current Assets
B9: Current Assets | H9: FC | I9: Account | J9: Used | K9: Order | L9: AmtJournal | M9: AmtAnswer | N9: AmtFSBuilder | O9: UsedJournal | P9: UsedAnswer | Q9: UsedFSBuilder | S9: FC | T9: Account | U9: Used | V9: Order | W9: AmtJournal | X9: AmtAnswer | Y9: AmtFSBuilder | Z9: UsedJournal | AA9: UsedAnswer | AB9: UsedFSBuilder | AE9: Issued preferred stock | AF9: =SUMIFS(Journal[Cr Amt],Journal[ref1],"IPS",Journal[Credit Account],"Preferred Stock") -> 0 | AG9: =SUMIFS(JournalAnswer[Cr Amt],JournalAnswer[ref1],"IPS",JournalAnswer[Credit Account],"Preferred Stock") -> 0 | AP9: {=_xlfn.IFS(AND(CFS_CFO[[#This Row],[Used]]=1,CFS_CFO[[#This Row],[Order]]=1),6,AND(CFS_CFO[[#This Row],[Used]]=1,CFS_CFO[[#This Row],[Order]]>1),7,CFS_CFO[[#This Row],[Used]]=0,8)} -> 6 | AQ9: Collections from customers | AR9: =IF(MAX(CFS_CFO[[#This Row],[AmtJournal]],CFS_CFO[[#This Row],[AmtAnswer]],CFS_CFO[[#This Row],[AmtFSBuilder]])>0,1,0) -> 1 | AS9: =CFS_CFO[[#This Row],[Used]] -> 1 | AT9: =SUMIFS(Journal[Dr Amt],Journal[ref1],"ColC",Journal[Debit Account],"Cash") -> 0 | AU9: =SUMIFS(JournalAnswer[Dr Amt],JournalAnswer[ref1],"ColC",JournalAnswer[Debit Account],"Cash") -> 91 | AV9: {=IF(CFS_CFO[[#This Row],[Account]]<>"",_xlfn._xlws.FILTER(FSBuilder[Amount],FSBuilder[Account or Explanation]=CFS_CFO[[#This Row],[Account]],0),"")} -> 0 | AW9: =IF(CFS_CFO[[#This Row],[AmtJournal]]<>0,1,0) -> 0 | AX9: =IF(CFS_CFO[[#This Row],[AmtAnswer]]<>0,1,0) -> 1 | AY9: =IF(CFS_CFO[[#This Row],[AmtFSBuilder]]<>0,1,0) -> 0 | BA9: Gains | BL9: FC | BM9: Account | BN9: Used | BO9: Order | BP9: AmtJournal | BQ9: AmtAnswer | BR9: AmtFSBuilder | BS9: UsedJournal | BT9: UsedAnswer | BU9: UsedFSBuilder
B10: FC | C10: Account | D10: Used | E10: Order | F10: Amt | H10: {=_xlfn.IFS(AND(IS_Revenues[[#This Row],[Used]]=1,IS_Revenues[[#This Row],[Order]]=1),6,AND(IS_Revenues[[#This Row],[Used]]=1,IS_Revenues[[#This Row],[Order]]>1),7,IS_Revenues[[#This Row],[Used]]=0,8)} -> 6 | I10: Sales | J10: =IF(ISNUMBER(_xlfn.XLOOKUP(IS_Revenues[[#This Row],[Account]],MD_Revenue[Account Name],MD_Revenue[Used])),_xlfn.XLOOKUP(IS_Revenues[[#This Row],[Account]],MD_Revenue[Account Name],MD_Revenue[Used]),0) -> 1 | K10: =IS_Revenues[[#This Row],[Used]] -> 1 | L10: =SUMIFS(Journal[Cr Amt],Journal[Credit Account],I10,Journal[ref1],"<>CL") -> 0 | M10: =SUMIFS(JournalAnswer[Cr Amt],JournalAnswer[Credit Account],I10,JournalAnswer[ref1],"<>CL") -> 18 | N10: {=IF(IS_Revenues[[#This Row],[Account]]<>"",_xlfn._xlws.FILTER(FSBuilder[Amount],FSBuilder[Account or Explanation]=IS_Revenues[[#This Row],[Account]],0),"")} -> 0 | O10: =IS_Revenues[[#This Row],[Used]]*(IS_Revenues[[#This Row],[AmtJournal]]<>0) -> 0 | P10: =IS_Revenues[[#This Row],[Used]]*(IS_Revenues[[#This Row],[AmtAnswer]]<>0) -> 1 | Q10: =IS_Revenues[[#This Row],[Used]]*(IS_Revenues[[#This Row],[AmtFSBuilder]]<>0)*Financial_Statement_Builder!$K$121 -> 0 | S10: 7 | T10: Change in fair value of marketable debt securities | U10: =IF(ABS(OCI[[#This Row],[AmtJournal]])>0,1,0) -> 0 | V10: 1 | W10: =SUMIFS(Journal[Cr Amt],Journal[ref1],"OCI",Journal[Credit Account],"Accumulated Other Comprehensive Income (Loss)")-SUMIFS(Journal[Dr Amt],Journal[ref1],"OCI",Journal[Debit Account],"Accumulated Other Comprehensive Income (Loss)") -> 0 | X10: =SUMIFS(JournalAnswer[Cr Amt],JournalAnswer[ref1],"OCI",JournalAnswer[Credit Account],"Accumulated Other Comprehensive Income (Loss)")-SUMIFS(JournalAnswer[Dr Amt],JournalAnswer[ref1],"OCI",JournalAnswer[Debit Account],"Accumulated Other Comprehensive Income (Loss)") -> 0 | Y10: {=IF(OCI[[#This Row],[Account]]<>"",_xlfn._xlws.FILTER(FSBuilder[Amount],FSBuilder[Account or Explanation]=OCI[[#This Row],[Account]],0),"")} -> 0 | Z10: =OCI[[#This Row],[Used]]*(OCI[[#This Row],[AmtJournal]]<>0) -> 0 | AA10: =OCI[[#This Row],[Used]]*(OCI[[#This Row],[AmtAnswer]]<>0) -> 0 | AB10: =OCI[[#This Row],[Used]]*(OCI[[#This Row],[AmtFSBuilder]]<>0) -> 0 | AE10: Issued common stock | AF10: =SUMIFS(Journal[Cr Amt],Journal[ref1],"ICS",Journal[Credit Account],"Common Stock") -> 0 | AG10: =SUMIFS(JournalAnswer[Cr Amt],JournalAnswer[ref1],"ICS",JournalAnswer[Credit Account],"Common Stock") -> 50 | AP10: 7 | AQ10: Payments to suppliers | AR10: =IF(ABS(CFS_CFO[[#This Row],[AmtJournal]])>0,1,0) -> 0 | AS10: =IF(CFS_CFO[[#This Row],[Used]]>0,CFS_CFO[[#This Row],[Used]]+AR9,0) -> 0 | AT10: =-SUMIFS(Journal[Cr Amt],Journal[ref1],"PdS",Journal[Credit Account],"Cash") -> 0 | AU10: =-SUMIFS(JournalAnswer[Cr Amt],JournalAnswer[ref1],"PdS",JournalAnswer[Credit Account],"Cash") -> -52 | AV10: {=IF(CFS_CFO[[#This Row],[Account]]<>"",_xlfn._xlws.FILTER(FSBuilder[Amount],FSBuilder[Account or Explanation]=CFS_CFO[[#This Row],[Account]],0),"")} -> 0 | AW10: =IF(CFS_CFO[[#This Row],[AmtJournal]]<>0,1,0) -> 0 | AX10: =IF(CFS_CFO[[#This Row],[AmtAnswer]]<>0,1,0) -> 1 | AY10: =IF(CFS_CFO[[#This Row],[AmtFSBuilder]]<>0,1,0) -> 0 | BA10: FC | BB10: Account | BC10: Used | BD10: Order | BE10: AmtJournal | BF10: AmtAnswer | BG10: AmtFSBuilder | BH10: UsedJournal | BI10: UsedAnswer | BJ10: UsedFSBuilder | BL10: {=_xlfn.IFS(AND(ECurrAssets[[#This Row],[Used]]=1,ECurrAssets[[#This Row],[Order]]=1),6,AND(ECurrAssets[[#This Row],[Used]]=1,ECurrAssets[[#This Row],[Order]]>1),7,ECurrAssets[[#This Row],[Used]]=0,8)} -> 6 | BM10: Cash | BN10: =IF(ISNUMBER(_xlfn.XLOOKUP(ECurrAssets[[#This Row],[Account]],MD_Asset[Account Name],MD_Asset[Used])),_xlfn.XLOOKUP(ECurrAssets[[#This Row],[Account]],MD_Asset[Account Name],MD_Asset[Used]),0) -> 1 | BO10: =ECurrAssets[[#This Row],[Used]] -> 1 | BP10: =_xlfn.IFNA((_xlfn.XLOOKUP(ECurrAssets[[#This Row],[Account]],BegBalanceSheet_Assets[Account],BegBalanceSheet_Assets[Amount]))+SUMIF(Journal[Debit Account],ECurrAssets[[#This Row],[Account]],Journal[Dr Amt])-SUMIF(Journal[Credit Account],ECurrAssets[[#This Row],[Account]],Journal[Cr Amt]),0) -> 0 | BQ10: =_xlfn.IFNA((_xlfn.XLOOKUP(ECurrAssets[[#This Row],[Account]],BegBalanceSheet_Assets[Account],BegBalanceSheet_Assets[Amount]))+SUMIF(JournalAnswer[Debit Account],ECurrAssets[[#This Row],[Account]],JournalAnswer[Dr Amt])-SUMIF(JournalAnswer[Credit Account],ECurrAssets[[#This Row],[Account]],JournalAnswer[Cr Amt]),0) -> 137 | BR10: {=IF(ECurrAssets[[#This Row],[Account]]<>"",_xlfn._xlws.FILTER(FSBuilder[Amount],(FSBuilder[Account or Explanation]=ECurrAssets[[#This Row],[Account]])*(FSBuilder[Statement]="Ending Balance Sheet"),0),0)} -> 0 | BS10: =ECurrAssets[[#This Row],[Used]]*(ECurrAssets[[#This Row],[AmtJournal]]<>0) -> 0 | BT10: =ECurrAssets[[#This Row],[Used]]*(ECurrAssets[[#This Row],[AmtAnswer]]<>0) -> 1 | BU10: =ECurrAssets[[#This Row],[Used]]*(ECurrAssets[[#This Row],[AmtFSBuilder]]<>0) -> 0
B11: {=_xlfn.IFS(AND(BCurrAssets[[#This Row],[Used]]=1,BCurrAssets[[#This Row],[Order]]=1),6,AND(BCurrAssets[[#This Row],[Used]]=1,BCurrAssets[[#This Row],[Order]]>1),7,BCurrAssets[[#This Row],[Used]]=0,8)} -> 6 | C11: Cash | D11: =IF(ISNUMBER(_xlfn.XLOOKUP(BCurrAssets[[#This Row],[Account]],MD_Asset[Account Name],MD_Asset[Used])),_xlfn.XLOOKUP(BCurrAssets[[#This Row],[Account]],MD_Asset[Account Name],MD_Asset[Used]),0) -> 1 | E11: =BCurrAssets[[#This Row],[Used]] -> 1 | F11: =_xlfn.IFNA(_xlfn.XLOOKUP(C11,BegBalanceSheet_Assets[Account],BegBalanceSheet_Assets[Amount]),0) -> 0 | H11: {=_xlfn.IFS(AND(IS_Revenues[[#This Row],[Used]]=1,IS_Revenues[[#This Row],[Order]]=1),6,AND(IS_Revenues[[#This Row],[Used]]=1,IS_Revenues[[#This Row],[Order]]>1),7,IS_Revenues[[#This Row],[Used]]=0,8)} -> 8 | I11: Consulting Revenue | J11: =IF(ISNUMBER(_xlfn.XLOOKUP(IS_Revenues[[#This Row],[Account]],MD_Revenue[Account Name],MD_Revenue[Used])),_xlfn.XLOOKUP(IS_Revenues[[#This Row],[Account]],MD_Revenue[Account Name],MD_Revenue[Used]),0) -> 0 | K11: =IF(IS_Revenues[[#This Row],[Used]]=1,IS_Revenues[[#This Row],[Used]]+J10,0) -> 0 | L11: =SUMIFS(Journal[Cr Amt],Journal[Credit Account],I11,Journal[ref1],"<>CL") -> 0 | M11: =SUMIFS(JournalAnswer[Cr Amt],JournalAnswer[Credit Account],I11,JournalAnswer[ref1],"<>CL") -> 0 | N11: {=IF(IS_Revenues[[#This Row],[Account]]<>"",_xlfn._xlws.FILTER(FSBuilder[Amount],FSBuilder[Account or Explanation]=IS_Revenues[[#This Row],[Account]],0),"")} -> 0 | O11: =IS_Revenues[[#This Row],[Used]]*(IS_Revenues[[#This Row],[AmtJournal]]<>0) -> 0 | P11: =IS_Revenues[[#This Row],[Used]]*(IS_Revenues[[#This Row],[AmtAnswer]]<>0) -> 0 | Q11: =IS_Revenues[[#This Row],[Used]]*(IS_Revenues[[#This Row],[AmtFSBuilder]]<>0)*Financial_Statement_Builder!$K$121 -> 0 | W11: =SUMIFS(Journal[Cr Amt],Journal[ref1],"OCI",Journal[Credit Account],"Accumulated Other Comprehensive Income (Loss)")-SUMIFS(Journal[Dr Amt],Journal[ref1],"OCI",Journal[Debit Account],"Accumulated Other Comprehensive Income (Loss)") -> 0 | X11: =SUMIFS(JournalAnswer[Cr Amt],JournalAnswer[ref1],"OCI",JournalAnswer[Credit Account],"Accumulated Other Comprehensive Income (Loss)")-SUMIFS(JournalAnswer[Dr Amt],JournalAnswer[ref1],"OCI",JournalAnswer[Debit Account],"Accumulated Other Comprehensive Income (Loss)") -> 0 | Y11: {=IF(OCI[[#This Row],[Account]]<>"",_xlfn._xlws.FILTER(FSBuilder[Amount],FSBuilder[Account or Explanation]=OCI[[#This Row],[Account]],0),"")} | Z11: =OCI[[#This Row],[Used]]*(OCI[[#This Row],[AmtJournal]]<>0) -> 0 | AA11: =OCI[[#This Row],[Used]]*(OCI[[#This Row],[AmtAnswer]]<>0) -> 0 | AB11: =OCI[[#This Row],[Used]]*(OCI[[#This Row],[AmtFSBuilder]]<>0) -> 0 | AE11: Issued common stock APIC | AF11: =SUMIFS(Journal[Cr Amt],Journal[ref1],"ICS",Journal[Credit Account],"Additional Paid-n Capital") -> 0 | AG11: =SUMIFS(JournalAnswer[Cr Amt],JournalAnswer[ref1],"ICS",JournalAnswer[Credit Account],"Additional Paid-in Capital") -> 0 | AP11: {=_xlfn.IFS(AND(CFS_CFO[[#This Row],[Used]]=1,CFS_CFO[[#This Row],[Order]]=1),6,AND(CFS_CFO[[#This Row],[Used]]=1,CFS_CFO[[#This Row],[Order]]>1),7,CFS_CFO[[#This Row],[Used]]=0,8)} -> 8 | AQ11: Payments to employees | AR11: =IF(ABS(CFS_CFO[[#This Row],[AmtJournal]])>0,1,0) -> 0 | AS11: =IF(CFS_CFO[[#This Row],[Used]]=1,CFS_CFO[[#This Row],[Used]]+SUM(AR9:AR10),0) -> 0 | AT11: =-SUMIFS(Journal[Cr Amt],Journal[ref1],"PdSW",Journal[Credit Account],"Cash") -> 0 | AU11: =-SUMIFS(JournalAnswer[Cr Amt],JournalAnswer[ref1],"PdSW",JournalAnswer[Credit Account],"Cash") -> 0 | AV11: {=IF(CFS_CFO[[#This Row],[Account]]<>"",_xlfn._xlws.FILTER(FSBuilder[Amount],FSBuilder[Account or Explanation]=CFS_CFO[[#This Row],[Account]],0),"")} -> 0 | AW11: =IF(CFS_CFO[[#This Row],[AmtJournal]]<>0,1,0) -> 0 | AX11: =IF(CFS_CFO[[#This Row],[AmtAnswer]]<>0,1,0) -> 0 | AY11: =IF(CFS_CFO[[#This Row],[AmtFSBuilder]]<>0,1,0) -> 0 | BA11: =IF(NI_CFO_Recon_Gains[[#This Row],[Used]]=1,7,8) -> 8 | BB11: Gain on Sale of PP&E | BC11: =IF(ABS(NI_CFO_Recon_Gains[[#This Row],[AmtJournal]])>0,1,0) -> 0 | BD11: =NI_CFO_Recon_Gains[[#This Row],[Used]] -> 0 | BE11: =-SUMIF(Journal[Credit Account],BB11,Journal[Cr Amt]) -> 0 | BF11: =-SUMIF(JournalAnswer[Credit Account],#REF!,JournalAnswer[Cr Amt]) -> 0 | BG11: {=IF(NI_CFO_Recon_Gains[[#This Row],[Account]]<>"",_xlfn._xlws.FILTER(FSBuilder[Amount],(FSBuilder[Account or Explanation]=NI_CFO_Recon_Gains[[#This Row],[Account]])*(FSBuilder[Statement]="Cash Flow Statement"),0),0)} -> 0 | BH11: =IF(ABS(NI_CFO_Recon_Gains[[#This Row],[AmtJournal]])>0,1,0) -> 0 | BI11: =IF(ABS(NI_CFO_Recon_Gains[[#This Row],[AmtAnswer]])>0,1,0) -> 0 | BJ11: =IF(ABS(NI_CFO_Recon_Gains[[#This Row],[AmtFSBuilder]])>0,1,0) -> 0 | BL11: {=_xlfn.IFS(AND(ECurrAssets[[#This Row],[Used]]=1,ECurrAssets[[#This Row],[Order]]=1),6,AND(ECurrAssets[[#This Row],[Used]]=1,ECurrAssets[[#This Row],[Order]]>1),7,ECurrAssets[[#This Row],[Used]]=0,8)} -> 7 | BM11: Accounts Receivable | BN11: =IF(ISNUMBER(_xlfn.XLOOKUP(ECurrAssets[[#This Row],[Account]],MD_Asset[Account Name],MD_Asset[Used])),_xlfn.XLOOKUP(ECurrAssets[[#This Row],[Account]],MD_Asset[Account Name],MD_Asset[Used]),0) -> 1 | BO11: =IF(ECurrAssets[[#This Row],[Used]]=1,ECurrAssets[[#This Row],[Used]]+BN10,0) -> 2 | BP11: =_xlfn.IFNA((_xlfn.XLOOKUP(ECurrAssets[[#This Row],[Account]],BegBalanceSheet_Assets[Account],BegBalanceSheet_Assets[Amount]))+SUMIF(Journal[Debit Account],ECurrAssets[[#This Row],[Account]],Journal[Dr Amt])-SUMIF(Journal[Credit Account],ECurrAssets[[#This Row],[Account]],Journal[Cr Amt]),0) -> 0 | BQ11: =_xlfn.IFNA((_xlfn.XLOOKUP(ECurrAssets[[#This Row],[Account]],BegBalanceSheet_Assets[Account],BegBalanceSheet_Assets[Amount]))+SUMIF(JournalAnswer[Debit Account],ECurrAssets[[#This Row],[Account]],JournalAnswer[Dr Amt])-SUMIF(JournalAnswer[Credit Account],ECurrAssets[[#This Row],[Account]],JournalAnswer[Cr Amt]),0) -> 0 | BR11: {=IF(ECurrAssets[[#This Row],[Account]]<>"",_xlfn._xlws.FILTER(FSBuilder[Amount],(FSBuilder[Account or Explanation]=ECurrAssets[[#This Row],[Account]])*(FSBuilder[Statement]="Ending Balance Sheet"),0),0)} -> 0 | BS11: =ECurrAssets[[#This Row],[Used]]*(ECurrAssets[[#This Row],[AmtJournal]]<>0) -> 0 | BT11: =ECurrAssets[[#This Row],[Used]]*(ECurrAssets[[#This Row],[AmtAnswer]]<>0) -> 0 | BU11: =ECurrAssets[[#This Row],[Used]]*(ECurrAssets[[#This Row],[AmtFSBuilder]]<>0) -> 0
B12: {=_xlfn.IFS(AND(BCurrAssets[[#This Row],[Used]]=1,BCurrAssets[[#This Row],[Order]]=1),6,AND(BCurrAssets[[#This Row],[Used]]=1,BCurrAssets[[#This Row],[Order]]>1),7,BCurrAssets[[#This Row],[Used]]=0,8)} -> 7 | C12: Accounts Receivable | D12: =IF(ISNUMBER(_xlfn.XLOOKUP(BCurrAssets[[#This Row],[Account]],MD_Asset[Account Name],MD_Asset[Used])),_xlfn.XLOOKUP(BCurrAssets[[#This Row],[Account]],MD_Asset[Account Name],MD_Asset[Used]),0) -> 1 | E12: =IF(BCurrAssets[[#This Row],[Used]]=1,BCurrAssets[[#This Row],[Used]]+D11,0) -> 2 | F12: =_xlfn.IFNA(_xlfn.XLOOKUP(C12,BegBalanceSheet_Assets[Account],BegBalanceSheet_Assets[Amount]),0) -> 0 | H12: {=_xlfn.IFS(AND(IS_Revenues[[#This Row],[Used]]=1,IS_Revenues[[#This Row],[Order]]=1),6,AND(IS_Revenues[[#This Row],[Used]]=1,IS_Revenues[[#This Row],[Order]]>1),7,IS_Revenues[[#This Row],[Used]]=0,8)} -> 8 | I12: Interest Revenue | J12: =IF(ISNUMBER(_xlfn.XLOOKUP(IS_Revenues[[#This Row],[Account]],MD_Revenue[Account Name],MD_Revenue[Used])),_xlfn.XLOOKUP(IS_Revenues[[#This Row],[Account]],MD_Revenue[Account Name],MD_Revenue[Used]),0) -> 0 | K12: =IF(IS_Revenues[[#This Row],[Used]]=1,IS_Revenues[[#This Row],[Used]]+SUM(J10:J11),0) -> 0 | L12: =SUMIFS(Journal[Cr Amt],Journal[Credit Account],I12,Journal[ref1],"<>CL") -> 0 | M12: =SUMIFS(JournalAnswer[Cr Amt],JournalAnswer[Credit Account],I12,JournalAnswer[ref1],"<>CL") -> 0 | N12: {=IF(IS_Revenues[[#This Row],[Account]]<>"",_xlfn._xlws.FILTER(FSBuilder[Amount],FSBuilder[Account or Explanation]=IS_Revenues[[#This Row],[Account]],0),"")} -> 0 | O12: =IS_Revenues[[#This Row],[Used]]*(IS_Revenues[[#This Row],[AmtJournal]]<>0) -> 0 | P12: =IS_Revenues[[#This Row],[Used]]*(IS_Revenues[[#This Row],[AmtAnswer]]<>0) -> 0 | Q12: =IS_Revenues[[#This Row],[Used]]*(IS_Revenues[[#This Row],[AmtFSBuilder]]<>0)*Financial_Statement_Builder!$K$121 -> 0 | W12: =SUMIFS(Journal[Cr Amt],Journal[ref1],"OCI",Journal[Credit Account],"Accumulated Other Comprehensive Income (Loss)")-SUMIFS(Journal[Dr Amt],Journal[ref1],"OCI",Journal[Debit Account],"Accumulated Other Comprehensive Income (Loss)") -> 0 | X12: =SUMIFS(JournalAnswer[Cr Amt],JournalAnswer[ref1],"OCI",JournalAnswer[Credit Account],"Accumulated Other Comprehensive Income (Loss)")-SUMIFS(JournalAnswer[Dr Amt],JournalAnswer[ref1],"OCI",JournalAnswer[Debit Account],"Accumulated Other Comprehensive Income (Loss)") -> 0 | Y12: {=IF(OCI[[#This Row],[Account]]<>"",_xlfn._xlws.FILTER(FSBuilder[Amount],FSBuilder[Account or Explanation]=OCI[[#This Row],[Account]],0),"")} | Z12: =OCI[[#This Row],[Used]]*(OCI[[#This Row],[AmtJournal]]<>0) -> 0 | AA12: =OCI[[#This Row],[Used]]*(OCI[[#This Row],[AmtAnswer]]<>0) -> 0 | AB12: =OCI[[#This Row],[Used]]*(OCI[[#This Row],[AmtFSBuilder]]<>0) -> 0 | AE12: Declared Dividends | AF12: =-SUMIFS(Journal[Dr Amt],Journal[ref1],"DD",Journal[Debit Account],"Retained Earnings") -> 0 | AG12: =-SUMIFS(JournalAnswer[Dr Amt],JournalAnswer[ref1],"DD",JournalAnswer[Debit Account],"Retained Earnings") -> 0 | AP12: {=_xlfn.IFS(AND(CFS_CFO[[#This Row],[Used]]=1,CFS_CFO[[#This Row],[Order]]=1),6,AND(CFS_CFO[[#This Row],[Used]]=1,CFS_CFO[[#This Row],[Order]]>1),7,CFS_CFO[[#This Row],[Used]]=0,8)} -> 8 | AQ12: Payments for taxes | AR12: =IF(ABS(CFS_CFO[[#This Row],[AmtJournal]])>0,1,0) -> 0 | AS12: =IF(CFS_CFO[[#This Row],[Used]]=1,CFS_CFO[[#This Row],[Used]]+SUM(AR9:AR11),0) -> 0 | AT12: =-SUMIFS(Journal[Cr Amt],Journal[ref1],"PdTx",Journal[Credit Account],"Cash") -> 0 | AU12: =-SUMIFS(JournalAnswer[Cr Amt],JournalAnswer[ref1],"PdTx",JournalAnswer[Credit Account],"Cash") -> 0 | AV12: {=IF(CFS_CFO[[#This Row],[Account]]<>"",_xlfn._xlws.FILTER(FSBuilder[Amount],FSBuilder[Account or Explanation]=CFS_CFO[[#This Row],[Account]],0),"")} -> 0 | AW12: =IF(CFS_CFO[[#This Row],[AmtJournal]]<>0,1,0) -> 0 | AX12: =IF(CFS_CFO[[#This Row],[AmtAnswer]]<>0,1,0) -> 0 | AY12: =IF(CFS_CFO[[#This Row],[AmtFSBuilder]]<>0,1,0) -> 0 | BA12: =IF(NI_CFO_Recon_Gains[[#This Row],[Used]]=1,7,8) -> 8 | BB12: Gain on Sale of Subsidiary | BC12: =IF(ABS(NI_CFO_Recon_Gains[[#This Row],[AmtJournal]])>0,1,0) -> 0 | BD12: =NI_CFO_Recon_Gains[[#This Row],[Used]]+BC11 -> 0 | BE12: =-SUMIF(Journal[Credit Account],BB12,Journal[Cr Amt]) -> 0 | BF12: =-SUMIF(JournalAnswer[Credit Account],#REF!,JournalAnswer[Cr Amt]) -> 0 | BG12: {=IF(NI_CFO_Recon_Gains[[#This Row],[Account]]<>"",_xlfn._xlws.FILTER(FSBuilder[Amount],(FSBuilder[Account or Explanation]=NI_CFO_Recon_Gains[[#This Row],[Account]])*(FSBuilder[Statement]="Cash Flow Statement"),0),0)} -> 0 | BH12: =IF(ABS(NI_CFO_Recon_Gains[[#This Row],[AmtJournal]])>0,1,0) -> 0 | BI12: =IF(ABS(NI_CFO_Recon_Gains[[#This Row],[AmtAnswer]])>0,1,0) -> 0 | BJ12: =IF(ABS(NI_CFO_Recon_Gains[[#This Row],[AmtFSBuilder]])>0,1,0) -> 0 | BL12: {=_xlfn.IFS(AND(ECurrAssets[[#This Row],[Used]]=1,ECurrAssets[[#This Row],[Order]]=1),6,AND(ECurrAssets[[#This Row],[Used]]=1,ECurrAssets[[#This Row],[Order]]>1),7,ECurrAssets[[#This Row],[Used]]=0,8)} -> 8 | BM12: Allowance for Doubtful Accounts | BN12: =IF(ISNUMBER(_xlfn.XLOOKUP(ECurrAssets[[#This Row],[Account]],MD_Asset[Account Name],MD_Asset[Used])),_xlfn.XLOOKUP(ECurrAssets[[#This Row],[Account]],MD_Asset[Account Name],MD_Asset[Used]),0) -> 0 | BO12: =IF(ECurrAssets[[#This Row],[Used]]=1,ECurrAssets[[#This Row],[Used]]+SUM(BN10:BN11),0) -> 0 | BP12: =_xlfn.IFNA(-(_xlfn.XLOOKUP(ECurrAssets[[#This Row],[Account]],BegBalanceSheet_Assets[Account],BegBalanceSheet_Assets[Amount]))-SUMIF(Journal[Debit Account],ECurrAssets[[#This Row],[Account]],Journal[Dr Amt])+SUMIF(Journal[Credit Account],ECurrAssets[[#This Row],[Account]],Journal[Cr Amt]),0) -> 0 | BQ12: =_xlfn.IFNA(-(_xlfn.XLOOKUP(ECurrAssets[[#This Row],[Account]],BegBalanceSheet_Assets[Account],BegBalanceSheet_Assets[Amount]))-SUMIF(JournalAnswer[Debit Account],ECurrAssets[[#This Row],[Account]],JournalAnswer[Dr Amt])+SUMIF(JournalAnswer[Credit Account],ECurrAssets[[#This Row],[Account]],JournalAnswer[Cr Amt]),0) -> 0 | BR12: {=IF(ECurrAssets[[#This Row],[Account]]<>"",_xlfn._xlws.FILTER(FSBuilder[Amount],(FSBuilder[Account or Explanation]=ECurrAssets[[#This Row],[Account]])*(FSBuilder[Statement]="Ending Balance Sheet"),0),0)} -> 0 | BS12: =ECurrAssets[[#This Row],[Used]]*(ECurrAssets[[#This Row],[AmtJournal]]<>0) -> 0 | BT12: =ECurrAssets[[#This Row],[Used]]*(ECurrAssets[[#This Row],[AmtAnswer]]<>0) -> 0 | BU12: =ECurrAssets[[#This Row],[Used]]*(ECurrAssets[[#This Row],[AmtFSBuilder]]<>0) -> 0
B13: {=_xlfn.IFS(AND(BCurrAssets[[#This Row],[Used]]=1,BCurrAssets[[#This Row],[Order]]=1),6,AND(BCurrAssets[[#This Row],[Used]]=1,BCurrAssets[[#This Row],[Order]]>1),7,BCurrAssets[[#This Row],[Used]]=0,8)} -> 8 | C13: Allowance for Doubtful Accounts | D13: =IF(ISNUMBER(_xlfn.XLOOKUP(BCurrAssets[[#This Row],[Account]],MD_Asset[Account Name],MD_Asset[Used])),_xlfn.XLOOKUP(BCurrAssets[[#This Row],[Account]],MD_Asset[Account Name],MD_Asset[Used]),0) -> 0 | E13: =IF(BCurrAssets[[#This Row],[Used]]=1,BCurrAssets[[#This Row],[Used]]+SUM(D11:D12),0) -> 0 | F13: =_xlfn.IFNA(_xlfn.XLOOKUP(C13,BegBalanceSheet_Assets[Account],BegBalanceSheet_Assets[Amount]),0) -> 0 | H13: {=_xlfn.IFS(AND(IS_Revenues[[#This Row],[Used]]=1,IS_Revenues[[#This Row],[Order]]=1),6,AND(IS_Revenues[[#This Row],[Used]]=1,IS_Revenues[[#This Row],[Order]]>1),7,IS_Revenues[[#This Row],[Used]]=0,8)} -> 8 | I13: Sales of Office Furniture | J13: =IF(ISNUMBER(_xlfn.XLOOKUP(IS_Revenues[[#This Row],[Account]],MD_Revenue[Account Name],MD_Revenue[Used])),_xlfn.XLOOKUP(IS_Revenues[[#This Row],[Account]],MD_Revenue[Account Name],MD_Revenue[Used]),0) -> 0 | K13: =IF(IS_Revenues[[#This Row],[Used]]=1,IS_Revenues[[#This Row],[Used]]+SUM(J10:J12),0) -> 0 | L13: =SUMIFS(Journal[Cr Amt],Journal[Credit Account],I13,Journal[ref1],"<>CL") -> 0 | M13: =SUMIFS(JournalAnswer[Cr Amt],JournalAnswer[Credit Account],I13,JournalAnswer[ref1],"<>CL") -> 0 | N13: {=IF(IS_Revenues[[#This Row],[Account]]<>"",_xlfn._xlws.FILTER(FSBuilder[Amount],FSBuilder[Account or Explanation]=IS_Revenues[[#This Row],[Account]],0),"")} -> 0 | O13: =IS_Revenues[[#This Row],[Used]]*(IS_Revenues[[#This Row],[AmtJournal]]<>0) -> 0 | P13: =IS_Revenues[[#This Row],[Used]]*(IS_Revenues[[#This Row],[AmtAnswer]]<>0) -> 0 | Q13: =IS_Revenues[[#This Row],[Used]]*(IS_Revenues[[#This Row],[AmtFSBuilder]]<>0)*Financial_Statement_Builder!$K$121 -> 0 | W13: =SUMIFS(Journal[Cr Amt],Journal[ref1],"OCI",Journal[Credit Account],"Accumulated Other Comprehensive Income (Loss)")-SUMIFS(Journal[Dr Amt],Journal[ref1],"OCI",Journal[Debit Account],"Accumulated Other Comprehensive Income (Loss)") -> 0 | X13: =SUMIFS(JournalAnswer[Cr Amt],JournalAnswer[ref1],"OCI",JournalAnswer[Credit Account],"Accumulated Other Comprehensive Income (Loss)")-SUMIFS(JournalAnswer[Dr Amt],JournalAnswer[ref1],"OCI",JournalAnswer[Debit Account],"Accumulated Other Comprehensive Income (Loss)") -> 0 | Y13: {=IF(OCI[[#This Row],[Account]]<>"",_xlfn._xlws.FILTER(FSBuilder[Amount],FSBuilder[Account or Explanation]=OCI[[#This Row],[Account]],0),"")} | Z13: =OCI[[#This Row],[Used]]*(OCI[[#This Row],[AmtJournal]]<>0) -> 0 | AA13: =OCI[[#This Row],[Used]]*(OCI[[#This Row],[AmtAnswer]]<>0) -> 0 | AB13: =OCI[[#This Row],[Used]]*(OCI[[#This Row],[AmtFSBuilder]]<>0) -> 0 | AE13: Net Income (Loss) | AF13: =L54 -> 0 | AG13: =M54 -> 12 | AP13: {=_xlfn.IFS(AND(CFS_CFO[[#This Row],[Used]]=1,CFS_CFO[[#This Row],[Order]]=1),6,AND(CFS_CFO[[#This Row],[Used]]=1,CFS_CFO[[#This Row],[Order]]>1),7,CFS_CFO[[#This Row],[Used]]=0,8)} -> 8 | AQ13: Payments for interest | AR13: =IF(ABS(CFS_CFO[[#This Row],[AmtJournal]])>0,1,0) -> 0 | AS13: =IF(CFS_CFO[[#This Row],[Used]]=1,CFS_CFO[[#This Row],[Used]]+SUM(AR9:AR12),0) -> 0 | AT13: =-SUMIFS(Journal[Cr Amt],Journal[ref1],"PdInt",Journal[Credit Account],"Cash") -> 0 | AU13: =-SUMIFS(JournalAnswer[Cr Amt],JournalAnswer[ref1],"PdInt",JournalAnswer[Credit Account],"Cash") -> 0 | AV13: {=IF(CFS_CFO[[#This Row],[Account]]<>"",_xlfn._xlws.FILTER(FSBuilder[Amount],FSBuilder[Account or Explanation]=CFS_CFO[[#This Row],[Account]],0),"")} -> 0 | AW13: =IF(CFS_CFO[[#This Row],[AmtJournal]]<>0,1,0) -> 0 | AX13: =IF(CFS_CFO[[#This Row],[AmtAnswer]]<>0,1,0) -> 0 | AY13: =IF(CFS_CFO[[#This Row],[AmtFSBuilder]]<>0,1,0) -> 0 | BA13: =IF(NI_CFO_Recon_Gains[[#This Row],[Used]]=1,7,8) -> 8 | BB13: Gain on Retirement of Debt | BC13: =IF(ABS(NI_CFO_Recon_Gains[[#This Row],[AmtJournal]])>0,1,0) -> 0 | BD13: =NI_CFO_Recon_Gains[[#This Row],[Used]]+SUM(BC11:BC12) -> 0 | BE13: =-SUMIF(Journal[Credit Account],BB13,Journal[Cr Amt]) -> 0 | BF13: =-SUMIF(JournalAnswer[Credit Account],#REF!,JournalAnswer[Cr Amt]) -> 0 | BG13: {=IF(NI_CFO_Recon_Gains[[#This Row],[Account]]<>"",_xlfn._xlws.FILTER(FSBuilder[Amount],(FSBuilder[Account or Explanation]=NI_CFO_Recon_Gains[[#This Row],[Account]])*(FSBuilder[Statement]="Cash Flow Statement"),0),0)} -> 0 | BH13: =IF(ABS(NI_CFO_Recon_Gains[[#This Row],[AmtJournal]])>0,1,0) -> 0 | BI13: =IF(ABS(NI_CFO_Recon_Gains[[#This Row],[AmtAnswer]])>0,1,0) -> 0 | BJ13: =IF(ABS(NI_CFO_Recon_Gains[[#This Row],[AmtFSBuilder]])>0,1,0) -> 0 | BL13: {=_xlfn.IFS(AND(ECurrAssets[[#This Row],[Used]]=1,ECurrAssets[[#This Row],[Order]]=1),6,AND(ECurrAssets[[#This Row],[Used]]=1,ECurrAssets[[#This Row],[Order]]>1),7,ECurrAssets[[#This Row],[Used]]=0,8)} -> 8 | BM13: Marketable Securities | BN13: =IF(ISNUMBER(_xlfn.XLOOKUP(ECurrAssets[[#This Row],[Account]],MD_Asset[Account Name],MD_Asset[Used])),_xlfn.XLOOKUP(ECurrAssets[[#This Row],[Account]],MD_Asset[Account Name],MD_Asset[Used]),0) -> 0 | BO13: =IF(ECurrAssets[[#This Row],[Used]]=1,ECurrAssets[[#This Row],[Used]]+SUM(BN10:BN12),0) -> 0 | BP13: =_xlfn.IFNA((_xlfn.XLOOKUP(ECurrAssets[[#This Row],[Account]],BegBalanceSheet_Assets[Account],BegBalanceSheet_Assets[Amount]))+SUMIF(Journal[Debit Account],ECurrAssets[[#This Row],[Account]],Journal[Dr Amt])-SUMIF(Journal[Credit Account],ECurrAssets[[#This Row],[Account]],Journal[Cr Amt]),0) -> 0 | BQ13: =_xlfn.IFNA((_xlfn.XLOOKUP(ECurrAssets[[#This Row],[Account]],BegBalanceSheet_Assets[Account],BegBalanceSheet_Assets[Amount]))+SUMIF(JournalAnswer[Debit Account],ECurrAssets[[#This Row],[Account]],JournalAnswer[Dr Amt])-SUMIF(JournalAnswer[Credit Account],ECurrAssets[[#This Row],[Account]],JournalAnswer[Cr Amt]),0) -> 0 | BR13: {=IF(ECurrAssets[[#This Row],[Account]]<>"",_xlfn._xlws.FILTER(FSBuilder[Amount],(FSBuilder[Account or Explanation]=ECurrAssets[[#This Row],[Account]])*(FSBuilder[Statement]="Ending Balance Sheet"),0),0)} -> 0 | BS13: =ECurrAssets[[#This Row],[Used]]*(ECurrAssets[[#This Row],[AmtJournal]]<>0) -> 0 | BT13: =ECurrAssets[[#This Row],[Used]]*(ECurrAssets[[#This Row],[AmtAnswer]]<>0) -> 0 | BU13: =ECurrAssets[[#This Row],[Used]]*(ECurrAssets[[#This Row],[AmtFSBuilder]]<>0) -> 0
B14: {=_xlfn.IFS(AND(BCurrAssets[[#This Row],[Used]]=1,BCurrAssets[[#This Row],[Order]]=1),6,AND(BCurrAssets[[#This Row],[Used]]=1,BCurrAssets[[#This Row],[Order]]>1),7,BCurrAssets[[#This Row],[Used]]=0,8)} -> 8 | C14: Marketable Securities | D14: =IF(ISNUMBER(_xlfn.XLOOKUP(BCurrAssets[[#This Row],[Account]],MD_Asset[Account Name],MD_Asset[Used])),_xlfn.XLOOKUP(BCurrAssets[[#This Row],[Account]],MD_Asset[Account Name],MD_Asset[Used]),0) -> 0 | E14: =IF(BCurrAssets[[#This Row],[Used]]=1,BCurrAssets[[#This Row],[Used]]+SUM(D11:D13),0) -> 0 | F14: =_xlfn.IFNA(_xlfn.XLOOKUP(C14,BegBalanceSheet_Assets[Account],BegBalanceSheet_Assets[Amount]),0) -> 0 | H14: {=_xlfn.IFS(AND(IS_Revenues[[#This Row],[Used]]=1,IS_Revenues[[#This Row],[Order]]=1),6,AND(IS_Revenues[[#This Row],[Used]]=1,IS_Revenues[[#This Row],[Order]]>1),7,IS_Revenues[[#This Row],[Used]]=0,8)} -> 8 | J14: =IF(ISNUMBER(_xlfn.XLOOKUP(IS_Revenues[[#This Row],[Account]],MD_Revenue[Account Name],MD_Revenue[Used])),_xlfn.XLOOKUP(IS_Revenues[[#This Row],[Account]],MD_Revenue[Account Name],MD_Revenue[Used]),0) -> 0 | K14: =IF(IS_Revenues[[#This Row],[Used]]=1,IS_Revenues[[#This Row],[Used]]+SUM(J10:J13),0) -> 0 | L14: =SUMIFS(Journal[Cr Amt],Journal[Credit Account],I14,Journal[ref1],"<>CL") -> 0 | M14: =SUMIFS(JournalAnswer[Cr Amt],JournalAnswer[Credit Account],I14,JournalAnswer[ref1],"<>CL") -> 0 | N14: {=IF(IS_Revenues[[#This Row],[Account]]<>"",_xlfn._xlws.FILTER(FSBuilder[Amount],FSBuilder[Account or Explanation]=IS_Revenues[[#This Row],[Account]],0),"")} | O14: =IS_Revenues[[#This Row],[Used]]*(IS_Revenues[[#This Row],[AmtJournal]]<>0) -> 0 | P14: =IS_Revenues[[#This Row],[Used]]*(IS_Revenues[[#This Row],[AmtAnswer]]<>0) -> 0 | Q14: =IS_Revenues[[#This Row],[Used]]*(IS_Revenues[[#This Row],[AmtFSBuilder]]<>0)*Financial_Statement_Builder!$K$121 -> 0 | W14: =SUMIFS(Journal[Cr Amt],Journal[ref1],"OCI",Journal[Credit Account],"Accumulated Other Comprehensive Income (Loss)")-SUMIFS(Journal[Dr Amt],Journal[ref1],"OCI",Journal[Debit Account],"Accumulated Other Comprehensive Income (Loss)") -> 0 | X14: =SUMIFS(JournalAnswer[Cr Amt],JournalAnswer[ref1],"OCI",JournalAnswer[Credit Account],"Accumulated Other Comprehensive Income (Loss)")-SUMIFS(JournalAnswer[Dr Amt],JournalAnswer[ref1],"OCI",JournalAnswer[Debit Account],"Accumulated Other Comprehensive Income (Loss)") -> 0 | Y14: {=IF(OCI[[#This Row],[Account]]<>"",_xlfn._xlws.FILTER(FSBuilder[Amount],FSBuilder[Account or Explanation]=OCI[[#This Row],[Account]],0),"")} | Z14: =OCI[[#This Row],[Used]]*(OCI[[#This Row],[AmtJournal]]<>0) -> 0 | AA14: =OCI[[#This Row],[Used]]*(OCI[[#This Row],[AmtAnswer]]<>0) -> 0 | AB14: =OCI[[#This Row],[Used]]*(OCI[[#This Row],[AmtFSBuilder]]<>0) -> 0 | AE14: Purchased treasury stock | AF14: =-SUMIFS(Journal[Dr Amt],Journal[ref1],"PTS",Journal[Debit Account],"Treasury Stock") -> 0 | AG14: =-SUMIFS(JournalAnswer[Dr Amt],JournalAnswer[ref1],"PTS",JournalAnswer[Debit Account],"Treasury Stock") -> 0 | AP14: {=_xlfn.IFS(AND(CFS_CFO[[#This Row],[Used]]=1,CFS_CFO[[#This Row],[Order]]=1),6,AND(CFS_CFO[[#This Row],[Used]]=1,CFS_CFO[[#This Row],[Order]]>1),7,CFS_CFO[[#This Row],[Used]]=0,8)} -> 8 | AQ14: Payments for prepaid expenses | AR14: =IF(ABS(CFS_CFO[[#This Row],[AmtJournal]])>0,1,0) -> 0 | AS14: =IF(CFS_CFO[[#This Row],[Used]]=1,CFS_CFO[[#This Row],[Used]]+SUM(AR9:AR13),0) -> 0 | AT14: =-SUMIFS(Journal[Cr Amt],Journal[ref1],"PdPPd",Journal[Credit Account],"Cash") -> 0 | AU14: =-SUMIFS(JournalAnswer[Cr Amt],JournalAnswer[ref1],"PdPPd",JournalAnswer[Credit Account],"Cash") -> 0 | AV14: {=IF(CFS_CFO[[#This Row],[Account]]<>"",_xlfn._xlws.FILTER(FSBuilder[Amount],FSBuilder[Account or Explanation]=CFS_CFO[[#This Row],[Account]],0),"")} -> 0 | AW14: =IF(CFS_CFO[[#This Row],[AmtJournal]]<>0,1,0) -> 0 | AX14: =IF(CFS_CFO[[#This Row],[AmtAnswer]]<>0,1,0) -> 0 | AY14: =IF(CFS_CFO[[#This Row],[AmtFSBuilder]]<>0,1,0) -> 0 | BA14: =IF(NI_CFO_Recon_Gains[[#This Row],[Used]]=1,7,8) -> 8 | BB14: Holding Gain on Marketable Securities | BC14: =IF(ABS(NI_CFO_Recon_Gains[[#This Row],[AmtJournal]])>0,1,0) -> 0 | BD14: =NI_CFO_Recon_Gains[[#This Row],[Used]]+SUM(BC11:BC13) -> 0 | BE14: =-SUMIF(Journal[Credit Account],BB14,Journal[Cr Amt]) -> 0 | BF14: =-SUMIF(JournalAnswer[Credit Account],#REF!,JournalAnswer[Cr Amt]) -> 0 | BG14: {=IF(NI_CFO_Recon_Gains[[#This Row],[Account]]<>"",_xlfn._xlws.FILTER(FSBuilder[Amount],(FSBuilder[Account or Explanation]=NI_CFO_Recon_Gains[[#This Row],[Account]])*(FSBuilder[Statement]="Cash Flow Statement"),0),0)} -> 0 | BH14: =IF(ABS(NI_CFO_Recon_Gains[[#This Row],[AmtJournal]])>0,1,0) -> 0 | BI14: =IF(ABS(NI_CFO_Recon_Gains[[#This Row],[AmtAnswer]])>0,1,0) -> 0 | BJ14: =IF(ABS(NI_CFO_Recon_Gains[[#This Row],[AmtFSBuilder]])>0,1,0) -> 0 | BL14: {=_xlfn.IFS(AND(ECurrAssets[[#This Row],[Used]]=1,ECurrAssets[[#This Row],[Order]]=1),6,AND(ECurrAssets[[#This Row],[Used]]=1,ECurrAssets[[#This Row],[Order]]>1),7,ECurrAssets[[#This Row],[Used]]=0,8)} -> 7 | BM14: Inventories | BN14: =IF(ISNUMBER(_xlfn.XLOOKUP(ECurrAssets[[#This Row],[Account]],MD_Asset[Account Name],MD_Asset[Used])),_xlfn.XLOOKUP(ECurrAssets[[#This Row],[Account]],MD_Asset[Account Name],MD_Asset[Used]),0) -> 1 | BO14: =IF(ECurrAssets[[#This Row],[Used]]=1,ECurrAssets[[#This Row],[Used]]+SUM(BN10:BN13),0) -> 3 | BP14: =_xlfn.IFNA((_xlfn.XLOOKUP(ECurrAssets[[#This Row],[Account]],BegBalanceSheet_Assets[Account],BegBalanceSheet_Assets[Amount]))+SUMIF(Journal[Debit Account],ECurrAssets[[#This Row],[Account]],Journal[Dr Amt])-SUMIF(Journal[Credit Account],ECurrAssets[[#This Row],[Account]],Journal[Cr Amt]),0) -> 0 | BQ14: =_xlfn.IFNA((_xlfn.XLOOKUP(ECurrAssets[[#This Row],[Account]],BegBalanceSheet_Assets[Account],BegBalanceSheet_Assets[Amount]))+SUMIF(JournalAnswer[Debit Account],ECurrAssets[[#This Row],[Account]],JournalAnswer[Dr Amt])-SUMIF(JournalAnswer[Credit Account],ECurrAssets[[#This Row],[Account]],JournalAnswer[Cr Amt]),0) -> 42 | BR14: {=IF(ECurrAssets[[#This Row],[Account]]<>"",_xlfn._xlws.FILTER(FSBuilder[Amount],(FSBuilder[Account or Explanation]=ECurrAssets[[#This Row],[Account]])*(FSBuilder[Statement]="Ending Balance Sheet"),0),0)} -> 0 | BS14: =ECurrAssets[[#This Row],[Used]]*(ECurrAssets[[#This Row],[AmtJournal]]<>0) -> 0 | BT14: =ECurrAssets[[#This Row],[Used]]*(ECurrAssets[[#This Row],[AmtAnswer]]<>0) -> 1 | BU14: =ECurrAssets[[#This Row],[Used]]*(ECurrAssets[[#This Row],[AmtFSBuilder]]<>0) -> 0
B15: {=_xlfn.IFS(AND(BCurrAssets[[#This Row],[Used]]=1,BCurrAssets[[#This Row],[Order]]=1),6,AND(BCurrAssets[[#This Row],[Used]]=1,BCurrAssets[[#This Row],[Order]]>1),7,BCurrAssets[[#This Row],[Used]]=0,8)} -> 7 | C15: Inventories | D15: =IF(ISNUMBER(_xlfn.XLOOKUP(BCurrAssets[[#This Row],[Account]],MD_Asset[Account Name],MD_Asset[Used])),_xlfn.XLOOKUP(BCurrAssets[[#This Row],[Account]],MD_Asset[Account Name],MD_Asset[Used]),0) -> 1 | E15: =IF(BCurrAssets[[#This Row],[Used]]=1,BCurrAssets[[#This Row],[Used]]+SUM(D11:D14),0) -> 3 | F15: =_xlfn.IFNA(_xlfn.XLOOKUP(C15,BegBalanceSheet_Assets[Account],BegBalanceSheet_Assets[Amount]),0) -> 0 | H15: 5 | I15: Total Revenues | L15: =SUBTOTAL(9,L10:L14) -> 0 | M15: =SUBTOTAL(9,M10:M14) -> 18 | N15: =SUBTOTAL(9,N10:N14) -> 0 | O15: =SUBTOTAL(9,O10:O14) -> 0 | W15: =SUMIFS(Journal[Cr Amt],Journal[ref1],"OCI",Journal[Credit Account],"Accumulated Other Comprehensive Income (Loss)")-SUMIFS(Journal[Dr Amt],Journal[ref1],"OCI",Journal[Debit Account],"Accumulated Other Comprehensive Income (Loss)") -> 0 | X15: =SUMIFS(JournalAnswer[Cr Amt],JournalAnswer[ref1],"OCI",JournalAnswer[Credit Account],"Accumulated Other Comprehensive Income (Loss)")-SUMIFS(JournalAnswer[Dr Amt],JournalAnswer[ref1],"OCI",JournalAnswer[Debit Account],"Accumulated Other Comprehensive Income (Loss)") -> 0 | Y15: {=IF(OCI[[#This Row],[Account]]<>"",_xlfn._xlws.FILTER(FSBuilder[Amount],FSBuilder[Account or Explanation]=OCI[[#This Row],[Account]],0),"")} | Z15: =OCI[[#This Row],[Used]]*(OCI[[#This Row],[AmtJournal]]<>0) -> 0 | AA15: =OCI[[#This Row],[Used]]*(OCI[[#This Row],[AmtAnswer]]<>0) -> 0 | AB15: =OCI[[#This Row],[Used]]*(OCI[[#This Row],[AmtFSBuilder]]<>0) -> 0 | AE15: Sold treasury stock | AF15: =-SUMIFS(Journal[Cr Amt],Journal[ref1],"STS",Journal[Credit Account],"Treasury Stock") -> 0 | AG15: =-SUMIFS(JournalAnswer[Cr Amt],JournalAnswer[ref1],"STS",JournalAnswer[Credit Account],"Treasury Stock") -> 0 | AP15: {=_xlfn.IFS(AND(CFS_CFO[[#This Row],[Used]]=1,CFS_CFO[[#This Row],[Order]]=1),6,AND(CFS_CFO[[#This Row],[Used]]=1,CFS_CFO[[#This Row],[Order]]>1),7,CFS_CFO[[#This Row],[Used]]=0,8)} -> 8 | AQ15: Payments for accrued expenses | AR15: =IF(ABS(CFS_CFO[[#This Row],[AmtJournal]])>0,1,0) -> 0 | AS15: =IF(CFS_CFO[[#This Row],[Used]]=1,CFS_CFO[[#This Row],[Used]]+SUM(AR9:AR14),0) -> 0 | AT15: =-SUMIFS(Journal[Cr Amt],Journal[ref1],"PdACCEx",Journal[Credit Account],"Cash") -> 0 | AU15: =-SUMIFS(JournalAnswer[Cr Amt],JournalAnswer[ref1],"PdACCEx",JournalAnswer[Credit Account],"Cash") -> 0 | AV15: {=IF(CFS_CFO[[#This Row],[Account]]<>"",_xlfn._xlws.FILTER(FSBuilder[Amount],FSBuilder[Account or Explanation]=CFS_CFO[[#This Row],[Account]],0),"")} -> 0 | AW15: =IF(CFS_CFO[[#This Row],[AmtJournal]]<>0,1,0) -> 0 | AX15: =IF(CFS_CFO[[#This Row],[AmtAnswer]]<>0,1,0) -> 0 | AY15: =IF(CFS_CFO[[#This Row],[AmtFSBuilder]]<>0,1,0) -> 0 | BA15: =IF(NI_CFO_Recon_Gains[[#This Row],[Used]]=1,7,8) -> 8 | BB15: Realized Gain on Marketable Securities | BC15: =IF(ABS(NI_CFO_Recon_Gains[[#This Row],[AmtJournal]])>0,1,0) -> 0 | BD15: =NI_CFO_Recon_Gains[[#This Row],[Used]]+SUM(BC11:BC14) -> 0 | BE15: =-SUMIF(Journal[Credit Account],BB15,Journal[Cr Amt]) -> 0 | BF15: =-SUMIF(JournalAnswer[Credit Account],#REF!,JournalAnswer[Cr Amt]) -> 0 | BG15: {=IF(NI_CFO_Recon_Gains[[#This Row],[Account]]<>"",_xlfn._xlws.FILTER(FSBuilder[Amount],(FSBuilder[Account or Explanation]=NI_CFO_Recon_Gains[[#This Row],[Account]])*(FSBuilder[Statement]="Cash Flow Statement"),0),0)} -> 0 | BH15: =IF(ABS(NI_CFO_Recon_Gains[[#This Row],[AmtJournal]])>0,1,0) -> 0 | BI15: =IF(ABS(NI_CFO_Recon_Gains[[#This Row],[AmtAnswer]])>0,1,0) -> 0 | BJ15: =IF(ABS(NI_CFO_Recon_Gains[[#This Row],[AmtFSBuilder]])>0,1,0) -> 0 | BL15: {=_xlfn.IFS(AND(ECurrAssets[[#This Row],[Used]]=1,ECurrAssets[[#This Row],[Order]]=1),6,AND(ECurrAssets[[#This Row],[Used]]=1,ECurrAssets[[#This Row],[Order]]>1),7,ECurrAssets[[#This Row],[Used]]=0,8)} -> 8 | BM15: Prepaid Expenses | BN15: =IF(ISNUMBER(_xlfn.XLOOKUP(ECurrAssets[[#This Row],[Account]],MD_Asset[Account Name],MD_Asset[Used])),_xlfn.XLOOKUP(ECurrAssets[[#This Row],[Account]],MD_Asset[Account Name],MD_Asset[Used]),0) -> 0 | BO15: =IF(ECurrAssets[[#This Row],[Used]]=1,ECurrAssets[[#This Row],[Used]]+SUM(BN10:BN14),0) -> 0 | BP15: =_xlfn.IFNA((_xlfn.XLOOKUP(ECurrAssets[[#This Row],[Account]],BegBalanceSheet_Assets[Account],BegBalanceSheet_Assets[Amount]))+SUMIF(Journal[Debit Account],ECurrAssets[[#This Row],[Account]],Journal[Dr Amt])-SUMIF(Journal[Credit Account],ECurrAssets[[#This Row],[Account]],Journal[Cr Amt]),0) -> 0 | BQ15: =_xlfn.IFNA((_xlfn.XLOOKUP(ECurrAssets[[#This Row],[Account]],BegBalanceSheet_Assets[Account],BegBalanceSheet_Assets[Amount]))+SUMIF(JournalAnswer[Debit Account],ECurrAssets[[#This Row],[Account]],JournalAnswer[Dr Amt])-SUMIF(JournalAnswer[Credit Account],ECurrAssets[[#This Row],[Account]],JournalAnswer[Cr Amt]),0) -> 0 | BR15: {=IF(ECurrAssets[[#This Row],[Account]]<>"",_xlfn._xlws.FILTER(FSBuilder[Amount],(FSBuilder[Account or Explanation]=ECurrAssets[[#This Row],[Account]])*(FSBuilder[Statement]="Ending Balance Sheet"),0),0)} -> 0 | BS15: =ECurrAssets[[#This Row],[Used]]*(ECurrAssets[[#This Row],[AmtJournal]]<>0) -> 0 | BT15: =ECurrAssets[[#This Row],[Used]]*(ECurrAssets[[#This Row],[AmtAnswer]]<>0) -> 0 | BU15: =ECurrAssets[[#This Row],[Used]]*(ECurrAssets[[#This Row],[AmtFSBuilder]]<>0) -> 0
