Workbook
Name AccountTypesUsed: _xlfn.ANCHORARRAY([1]MasterData!$L$5)
Name AccountTypesUsed: _xlfn.ANCHORARRAY(MasterData!$L$5)
Name AssetUsed: _xlfn.ANCHORARRAY([1]MasterData!$L$56)
Name AssetUsed: _xlfn.ANCHORARRAY(MasterData!$L$56)
Name BB_Inbalance: Financial_Statements_Builder!$E$559
Name BegDate: [1]ProblemData!$E$64
Name BegDate: ProblemData!$E$64
Name Begin: MasterData!$F$684:$F$703
Name Begin: MasterData!$F$684:$F$703
Name CFO_NI_Recon_NI: FSConstruction!$BA$7:$BE$7
Name DeprMethod: ProblemData!$E$72
Name End: MasterData!$G$684:$G$703
Name End: MasterData!$G$684:$G$703
Name EndDate: [1]ProblemData!$E$65
Name EndDate: ProblemData!$E$65
Name Entity: [1]ProblemData!$E$61
Name Entity: ProblemData!$E$61
Name EntityActivity: [1]ProblemData!$E$63
Name EntityActivity: ProblemData!$E$63
Name EntityType: [1]ProblemData!$E$62
Name EntityType: ProblemData!$E$62
Name EquityUsed: _xlfn.ANCHORARRAY([1]MasterData!$L$116)
Name EquityUsed: _xlfn.ANCHORARRAY(MasterData!$L$116)
Name ExpenseUsed: _xlfn.ANCHORARRAY([1]MasterData!$L$149)
Name ExpenseUsed: _xlfn.ANCHORARRAY(MasterData!$L$149)
Name FS_IssueDate: ProblemData!$E$66
Name FSBuilderAccnts: [1]MasterData!$X$56:$X$90
Name FSBuilderAccnts: MasterData!$X$71:$X$90
Name GainUsed: _xlfn.ANCHORARRAY([1]MasterData!$L$171)
Name GainUsed: _xlfn.ANCHORARRAY(MasterData!$L$171)
Name InventoryMethod: [1]ProblemData!$E$73
Name InventoryMethod: ProblemData!$E$73
Name Issue_Date: [1]ProblemData!$E$66
Name Issue_Date: ProblemData!$E$66
Name LiabilityUsed: _xlfn.ANCHORARRAY([1]MasterData!$L$83)
Name LiabilityUsed: _xlfn.ANCHORARRAY(MasterData!$L$83)
Name LossUsed: _xlfn.ANCHORARRAY([1]MasterData!$L$185)
Name LossUsed: _xlfn.ANCHORARRAY(MasterData!$L$185)
Name Net_Income: FSConstruction!$L$54
Name ParValue: ProblemData!$E$70
Name Period: [1]ProblemData!$E$67
Name Period: ProblemData!$E$67
Name PurposesUsed: _xlfn.ANCHORARRAY([1]MasterData!$F$515)
Name PurposesUsed: _xlfn.ANCHORARRAY(MasterData!$F$515)
Name RevenueUsed: _xlfn.ANCHORARRAY([1]MasterData!$L$135)
Name RevenueUsed: _xlfn.ANCHORARRAY(MasterData!$L$135)
Name RevRec: [1]ProblemData!$E$74
Name RevRec: ProblemData!$E$74
Name ShrsOut: ProblemData!$E$69
Name TreasShrs: ProblemData!$E$71
Name Units: [1]ProblemData!$E$68
Name Units: ProblemData!$E$68
Name ZZZ: FSConstruction!$BA$7:$BE$7

Sheet Instructions
B2: Basic Information
B3: Entity
B4: Entity: | C4: =IF(ProblemData!E61="","",ProblemData!E61) -> Miloslav's Magazines
B5: Type: | C5: =IF(ProblemData!E62="","",ProblemData!E62) -> For-profit corporation
B6: Activity: | C6: =IF(ProblemData!E63="","",ProblemData!E63) -> Retail
B7: Dates and Period
B8: Period Beginning: | C8: =IF(ProblemData!E64="","",ProblemData!E64) -> 12/31/20x3
B9: Period Ending: | C9: =IF(ProblemData!E65="","",ProblemData!E65) -> 12/31/20x4
B10: Period Length: | C10: =IF(ProblemData!E67="","",ProblemData!E67) -> Year
B11: Units and Shares
B12: Units: | C12: =IF(ProblemData!E68="","",ProblemData!E68) -> Dollars in Thousands
B13: Shares Outstanding: | C13: =IF(ProblemData!E69="","",ProblemData!E69) -> 0
B14: Par Value per Share: | C14: =IF(ProblemData!E70="","",ProblemData!E70) -> 0
B18: Requirements:
B19: Number | C19: Action: | D19: Item: | G19: Completed? | H19: Location:
B20: #1 | C20: {=_xlfn._xlws.FILTER(RequirementsChosen[Action],RequirementsChosen[Action]<>"Omit")} -> Review | D20: {=_xlfn._xlws.FILTER(RequirementsChosen[Item],RequirementsChosen[Action]<>"Omit")} -> Chart of Accounts | G20: TRUE | H20: {=_xlfn._xlws.FILTER(RequirementsChosen[Tab],RequirementsChosen[Action]<>"Omit")} -> Instructions
B21: #2 | C21: Review | D21: Notes to the Financial Statements | G21: TRUE | H21: Notes_to_FSs
B22: #3 | C22: Prepare | D22: Beginning Balance Sheet | G22: TRUE | H22: Financial_Statements_Builder
B23: #4 | C23: Prepare | D23: Journal entries for transactions and events of the period | G23: FALSE | H23: Journal
B24: #5 | C24: Prepare | D24: Journal entry to close temporary accounts | G24: FALSE | H24: Journal
B25: #6 | C25: Prepare | D25: Ending Balance Sheet | G25: FALSE | H25: Financial_Statements_Builder
B26: #7 | C26: Prepare | D26: Income Statement | G26: FALSE | H26: Financial_Statements_Builder
B27: #8 | C27: Prepare | D27: Statement of Shareholders' Equity | G27: FALSE | H27: Financial_Statements_Builder
B28: #9 | G28: FALSE
B29: #10 | G29: FALSE
B30: #11 | G30: FALSE
B31: #12 | G31: FALSE
B32: #13 | G32: FALSE
B33: #14 | G33: FALSE
B34: #15 | G34: FALSE
B36: Chart of Accounts
B38: Permanent Accounts | C38: Assets | E38: Liabilities | G38: Equities
C39: Name | D39: Current/Noncurrent | E39: Name | F39: Current/Noncurrent
C40: {=IFERROR(_xlfn._xlws.FILTER(MD_Asset[[#All],[Account Name]],MD_Asset[[#All],[Used]]=1),"")} -> Cash | D40: =IF(NOT(ISBLANK(C40)),_xlfn.XLOOKUP(C40,MD_Asset[Account Name],MD_Asset[C/NC],""),"") -> C | E40: {=IFERROR(_xlfn._xlws.FILTER(MD_Liability[[#All],[Account Name]],MD_Liability[[#All],[Used]]=1),"")} -> Interest Payable | F40: =IF(NOT(ISBLANK(E40)),_xlfn.XLOOKUP(E40,MD_Liability[Account Name],MD_Liability[C/NC],""),"") -> C | G40: {=IFERROR(_xlfn._xlws.FILTER(MD_Equity[[#All],[Account Name]],MD_Equity[[#All],[Used]]=1),"")} -> Common Stock
C41: Accounts Receivable | D41: =IF(NOT(ISBLANK(C41)),_xlfn.XLOOKUP(C41,MD_Asset[Account Name],MD_Asset[C/NC],""),"") -> C | E41: Dividends Payable | F41: =IF(NOT(ISBLANK(E41)),_xlfn.XLOOKUP(E41,MD_Liability[Account Name],MD_Liability[C/NC],""),"") -> C | G41: Retained Earnings
C42: Inventories | D42: =IF(NOT(ISBLANK(C42)),_xlfn.XLOOKUP(C42,MD_Asset[Account Name],MD_Asset[C/NC],""),"") -> C | E42: Notes Payable | F42: =IF(NOT(ISBLANK(E42)),_xlfn.XLOOKUP(E42,MD_Liability[Account Name],MD_Liability[C/NC],""),"") -> NC
C43: Property, Plant & Equipment | D43: =IF(NOT(ISBLANK(C43)),_xlfn.XLOOKUP(C43,MD_Asset[Account Name],MD_Asset[C/NC],""),"") -> NC | F43: =IF(NOT(ISBLANK(E43)),_xlfn.XLOOKUP(E43,MD_Liability[Account Name],MD_Liability[C/NC],""),"")
C44: Accumulated Depreciation | D44: =IF(NOT(ISBLANK(C44)),_xlfn.XLOOKUP(C44,MD_Asset[Account Name],MD_Asset[C/NC],""),"") -> NC | F44: =IF(NOT(ISBLANK(E44)),_xlfn.XLOOKUP(E44,MD_Liability[Account Name],MD_Liability[C/NC],""),"")
D45: =IF(NOT(ISBLANK(C45)),_xlfn.XLOOKUP(C45,MD_Asset[Account Name],MD_Asset[C/NC],""),"") | F45: =IF(NOT(ISBLANK(E45)),_xlfn.XLOOKUP(E45,MD_Liability[Account Name],MD_Liability[C/NC],""),"")
D46: =IF(NOT(ISBLANK(C46)),_xlfn.XLOOKUP(C46,MD_Asset[Account Name],MD_Asset[C/NC],""),"") | F46: =IF(NOT(ISBLANK(E46)),_xlfn.XLOOKUP(E46,MD_Liability[Account Name],MD_Liability[C/NC],""),"")
D47: =IF(NOT(ISBLANK(C47)),_xlfn.XLOOKUP(C47,MD_Asset[Account Name],MD_Asset[C/NC],""),"") | F47: =IF(NOT(ISBLANK(E47)),_xlfn.XLOOKUP(E47,MD_Liability[Account Name],MD_Liability[C/NC],""),"")
D48: =IF(NOT(ISBLANK(C48)),_xlfn.XLOOKUP(C48,MD_Asset[Account Name],MD_Asset[C/NC],""),"") | F48: =IF(NOT(ISBLANK(E48)),_xlfn.XLOOKUP(E48,MD_Liability[Account Name],MD_Liability[C/NC],""),"")
D49: =IF(NOT(ISBLANK(C49)),_xlfn.XLOOKUP(C49,MD_Asset[Account Name],MD_Asset[C/NC],""),"") | F49: =IF(NOT(ISBLANK(E49)),_xlfn.XLOOKUP(E49,MD_Liability[Account Name],MD_Liability[C/NC],""),"")
D50: =IF(NOT(ISBLANK(C50)),_xlfn.XLOOKUP(C50,MD_Asset[Account Name],MD_Asset[C/NC],""),"") | F50: =IF(NOT(ISBLANK(E50)),_xlfn.XLOOKUP(E50,MD_Liability[Account Name],MD_Liability[C/NC],""),"")
D51: =IF(NOT(ISBLANK(C51)),_xlfn.XLOOKUP(C51,MD_Asset[Account Name],MD_Asset[C/NC],""),"") | F51: =IF(NOT(ISBLANK(E51)),_xlfn.XLOOKUP(E51,MD_Liability[Account Name],MD_Liability[C/NC],""),"")
B54: Temporary Accounts | C54: Revenues | E54: Expenses | G54: Gains | I54: Losses
C55: {=IFERROR(_xlfn._xlws.FILTER(MD_Revenue[[#All],[Account Name]],MD_Revenue[[#All],[Used]]=1),"")} -> Sales | E55: {=IFERROR(_xlfn._xlws.FILTER(MD_Expense[[#All],[Account Name]],MD_Expense[[#All],[Used]]=1),"")} -> Cost of Goods Sold | G55: {=IFERROR(_xlfn._xlws.FILTER(MD_Gain[[#All],[Account Name]],MD_Gain[[#All],[Used]]=1),"")} | I55: {=IFERROR(_xlfn._xlws.FILTER(MD_Loss[[#All],[Account Name]],MD_Loss[[#All],[Used]]=1),"")}
E56: Interest Expense
E57: Depreciation Expense
E58: Salaries & Wages Expense
B69: This problem will help you:
B70: #1 | C70: {=PurposesUsed} -> Expand your financial vocabulary.
B71: #2 | C71: Use the Accounting Identity to analyze transactions.
B72: #3 | C72: Practice journal entry notation for analyzing/recording transactions.
B73: #4 | C73: Better understand the nature of accounting equities.
B74: #5 | C74: Become familiar with Gains and Losses accounts.

Sheet Journal
C2: Transaction # | D2: 14 | E2: =Entity&" Journal for "&BegDate&" to "&EndDate -> Miloslav's Magazines Journal for 12/31/20x3 to 12/31/20x4 | H2: Balance? | I2: =IF(ROUND(SUM(Journal[Dr Amt])-SUM(Journal[Cr Amt]),2)=0,"YES",ROUND(SUM(Journal[Dr Amt])-SUM(Journal[Cr Amt]),2)) -> YES
L3: X
C4: {=INDEX(ProblemData!D78:AN79,2,D2+1)} -> Close temporary accounts | L4: X
L5: X
L6: X
L7: X
C8: Transaction # | D8: Accnt Type | E8: Debit Account | F8: Credit Account | G8: Dr Amt | H8: Cr Amt | I8: Cash Flow | J8: Movement # | K8: Cash | L8: ref1 | M8: ref2 | N8: ref3
C9: 1 | D9: Asset | E9: Cash | G9: 3 | J9: =IF(Journal[[#This Row],[Transaction '#]]="","",IF(Journal[[#This Row],[Transaction '#]]=C8,J8+1,1)) -> 1 | K9: {=IFERROR(_xlfn.IFS(Journal[[#This Row],[Debit Account]]="Cash",Journal[[#This Row],[Dr Amt]],Journal[[#This Row],[Credit Account]]="Cash",-Journal[[#This Row],[Cr Amt]]),0)} -> 3 | L9: {=IF(Journal[[#This Row],[Transaction '#]]<>"",IFERROR(INDEX(ProblemData!$E$240:$AM$240,1,Journal[[#This Row],[Transaction '#]]),""),"")} -> ICS | M9: =IF(Journal[[#This Row],[ref1]]="","",IF(NOT(ISBLANK(Journal[[#This Row],[Transaction '#]])),Journal[[#This Row],[ref1]]&Journal[[#This Row],[Movement '#]],"")) -> ICS1 | N9: =OR(Journal[[#This Row],[ref1]]="",ISNUMBER(MATCH(Journal[[#This Row],[ref1]],Operating[Abbr], 0))) -> FALSE | P9: =Journal[[#This Row],[Accnt Type]]&"Used" -> AssetUsed
C10: 1 | D10: Equity | F10: Common Stock | H10: 3 | J10: =IF(Journal[[#This Row],[Transaction '#]]="","",IF(Journal[[#This Row],[Transaction '#]]=C9,J9+1,1)) -> 2 | K10: {=IFERROR(_xlfn.IFS(Journal[[#This Row],[Debit Account]]="Cash",Journal[[#This Row],[Dr Amt]],Journal[[#This Row],[Credit Account]]="Cash",-Journal[[#This Row],[Cr Amt]]),0)} -> 0 | L10: {=IF(Journal[[#This Row],[Transaction '#]]<>"",IFERROR(INDEX(ProblemData!$E$240:$AM$240,1,Journal[[#This Row],[Transaction '#]]),""),"")} -> ICS | M10: =IF(Journal[[#This Row],[ref1]]="","",IF(NOT(ISBLANK(Journal[[#This Row],[Transaction '#]])),Journal[[#This Row],[ref1]]&Journal[[#This Row],[Movement '#]],"")) -> ICS2 | N10: =OR(Journal[[#This Row],[ref1]]="",ISNUMBER(MATCH(Journal[[#This Row],[ref1]],Operating[Abbr], 0))) -> FALSE | P10: =Journal[[#This Row],[Accnt Type]]&"Used" -> EquityUsed
J11: =IF(Journal[[#This Row],[Transaction '#]]="","",IF(Journal[[#This Row],[Transaction '#]]=C10,J10+1,1)) | K11: {=IFERROR(_xlfn.IFS(Journal[[#This Row],[Debit Account]]="Cash",Journal[[#This Row],[Dr Amt]],Journal[[#This Row],[Credit Account]]="Cash",-Journal[[#This Row],[Cr Amt]]),0)} -> 0 | L11: {=IF(Journal[[#This Row],[Transaction '#]]<>"",IFERROR(INDEX(ProblemData!$E$240:$AM$240,1,Journal[[#This Row],[Transaction '#]]),""),"")} | M11: =IF(Journal[[#This Row],[ref1]]="","",IF(NOT(ISBLANK(Journal[[#This Row],[Transaction '#]])),Journal[[#This Row],[ref1]]&Journal[[#This Row],[Movement '#]],"")) | N11: =OR(Journal[[#This Row],[ref1]]="",ISNUMBER(MATCH(Journal[[#This Row],[ref1]],Operating[Abbr], 0))) -> TRUE | P11: =Journal[[#This Row],[Accnt Type]]&"Used" -> Used
C12: 2 | D12: Asset | E12: Cash | G12: 20 | J12: =IF(Journal[[#This Row],[Transaction '#]]="","",IF(Journal[[#This Row],[Transaction '#]]=C11,J11+1,1)) -> 1 | K12: {=IFERROR(_xlfn.IFS(Journal[[#This Row],[Debit Account]]="Cash",Journal[[#This Row],[Dr Amt]],Journal[[#This Row],[Credit Account]]="Cash",-Journal[[#This Row],[Cr Amt]]),0)} -> 20 | L12: {=IF(Journal[[#This Row],[Transaction '#]]<>"",IFERROR(INDEX(ProblemData!$E$240:$AM$240,1,Journal[[#This Row],[Transaction '#]]),""),"")} -> IN | M12: =IF(Journal[[#This Row],[ref1]]="","",IF(NOT(ISBLANK(Journal[[#This Row],[Transaction '#]])),Journal[[#This Row],[ref1]]&Journal[[#This Row],[Movement '#]],"")) -> IN1 | N12: =OR(Journal[[#This Row],[ref1]]="",ISNUMBER(MATCH(Journal[[#This Row],[ref1]],Operating[Abbr], 0))) -> FALSE | P12: =Journal[[#This Row],[Accnt Type]]&"Used" -> AssetUsed
C13: 2 | D13: Liability | F13: Notes Payable | H13: 20 | J13: =IF(Journal[[#This Row],[Transaction '#]]="","",IF(Journal[[#This Row],[Transaction '#]]=C12,J12+1,1)) -> 2 | K13: {=IFERROR(_xlfn.IFS(Journal[[#This Row],[Debit Account]]="Cash",Journal[[#This Row],[Dr Amt]],Journal[[#This Row],[Credit Account]]="Cash",-Journal[[#This Row],[Cr Amt]]),0)} -> 0 | L13: {=IF(Journal[[#This Row],[Transaction '#]]<>"",IFERROR(INDEX(ProblemData!$E$240:$AM$240,1,Journal[[#This Row],[Transaction '#]]),""),"")} -> IN | M13: =IF(Journal[[#This Row],[ref1]]="","",IF(NOT(ISBLANK(Journal[[#This Row],[Transaction '#]])),Journal[[#This Row],[ref1]]&Journal[[#This Row],[Movement '#]],"")) -> IN2 | N13: =OR(Journal[[#This Row],[ref1]]="",ISNUMBER(MATCH(Journal[[#This Row],[ref1]],Operating[Abbr], 0))) -> FALSE | P13: =Journal[[#This Row],[Accnt Type]]&"Used" -> LiabilityUsed
J14: =IF(Journal[[#This Row],[Transaction '#]]="","",IF(Journal[[#This Row],[Transaction '#]]=C13,J13+1,1)) | K14: {=IFERROR(_xlfn.IFS(Journal[[#This Row],[Debit Account]]="Cash",Journal[[#This Row],[Dr Amt]],Journal[[#This Row],[Credit Account]]="Cash",-Journal[[#This Row],[Cr Amt]]),0)} -> 0 | L14: {=IF(Journal[[#This Row],[Transaction '#]]<>"",IFERROR(INDEX(ProblemData!$E$240:$AM$240,1,Journal[[#This Row],[Transaction '#]]),""),"")} | M14: =IF(Journal[[#This Row],[ref1]]="","",IF(NOT(ISBLANK(Journal[[#This Row],[Transaction '#]])),Journal[[#This Row],[ref1]]&Journal[[#This Row],[Movement '#]],"")) | N14: =OR(Journal[[#This Row],[ref1]]="",ISNUMBER(MATCH(Journal[[#This Row],[ref1]],Operating[Abbr], 0))) -> TRUE | P14: =Journal[[#This Row],[Accnt Type]]&"Used" -> Used
C15: 3 | D15: Asset | E15: Property, Plant & Equipment | G15: 1 | J15: =IF(Journal[[#This Row],[Transaction '#]]="","",IF(Journal[[#This Row],[Transaction '#]]=C14,J14+1,1)) -> 1 | K15: {=IFERROR(_xlfn.IFS(Journal[[#This Row],[Debit Account]]="Cash",Journal[[#This Row],[Dr Amt]],Journal[[#This Row],[Credit Account]]="Cash",-Journal[[#This Row],[Cr Amt]]),0)} -> 0 | L15: {=IF(Journal[[#This Row],[Transaction '#]]<>"",IFERROR(INDEX(ProblemData!$E$240:$AM$240,1,Journal[[#This Row],[Transaction '#]]),""),"")} -> PPPE | M15: =IF(Journal[[#This Row],[ref1]]="","",IF(NOT(ISBLANK(Journal[[#This Row],[Transaction '#]])),Journal[[#This Row],[ref1]]&Journal[[#This Row],[Movement '#]],"")) -> PPPE1 | N15: =OR(Journal[[#This Row],[ref1]]="",ISNUMBER(MATCH(Journal[[#This Row],[ref1]],Operating[Abbr], 0))) -> FALSE | P15: =Journal[[#This Row],[Accnt Type]]&"Used" -> AssetUsed
C16: 3 | D16: Asset | F16: Cash | H16: 1 | J16: =IF(Journal[[#This Row],[Transaction '#]]="","",IF(Journal[[#This Row],[Transaction '#]]=C15,J15+1,1)) -> 2 | K16: {=IFERROR(_xlfn.IFS(Journal[[#This Row],[Debit Account]]="Cash",Journal[[#This Row],[Dr Amt]],Journal[[#This Row],[Credit Account]]="Cash",-Journal[[#This Row],[Cr Amt]]),0)} -> -1 | L16: {=IF(Journal[[#This Row],[Transaction '#]]<>"",IFERROR(INDEX(ProblemData!$E$240:$AM$240,1,Journal[[#This Row],[Transaction '#]]),""),"")} -> PPPE | M16: =IF(Journal[[#This Row],[ref1]]="","",IF(NOT(ISBLANK(Journal[[#This Row],[Transaction '#]])),Journal[[#This Row],[ref1]]&Journal[[#This Row],[Movement '#]],"")) -> PPPE2 | N16: =OR(Journal[[#This Row],[ref1]]="",ISNUMBER(MATCH(Journal[[#This Row],[ref1]],Operating[Abbr], 0))) -> FALSE | P16: =Journal[[#This Row],[Accnt Type]]&"Used" -> AssetUsed
J17: =IF(Journal[[#This Row],[Transaction '#]]="","",IF(Journal[[#This Row],[Transaction '#]]=C16,J16+1,1)) | K17: {=IFERROR(_xlfn.IFS(Journal[[#This Row],[Debit Account]]="Cash",Journal[[#This Row],[Dr Amt]],Journal[[#This Row],[Credit Account]]="Cash",-Journal[[#This Row],[Cr Amt]]),0)} -> 0 | L17: {=IF(Journal[[#This Row],[Transaction '#]]<>"",IFERROR(INDEX(ProblemData!$E$240:$AM$240,1,Journal[[#This Row],[Transaction '#]]),""),"")} | M17: =IF(Journal[[#This Row],[ref1]]="","",IF(NOT(ISBLANK(Journal[[#This Row],[Transaction '#]])),Journal[[#This Row],[ref1]]&Journal[[#This Row],[Movement '#]],"")) | N17: =OR(Journal[[#This Row],[ref1]]="",ISNUMBER(MATCH(Journal[[#This Row],[ref1]],Operating[Abbr], 0))) -> TRUE | P17: =Journal[[#This Row],[Accnt Type]]&"Used" -> Used
C18: 4 | D18: Asset | E18: Inventories | G18: 20 | J18: =IF(Journal[[#This Row],[Transaction '#]]="","",IF(Journal[[#This Row],[Transaction '#]]=C17,J17+1,1)) -> 1 | K18: {=IFERROR(_xlfn.IFS(Journal[[#This Row],[Debit Account]]="Cash",Journal[[#This Row],[Dr Amt]],Journal[[#This Row],[Credit Account]]="Cash",-Journal[[#This Row],[Cr Amt]]),0)} -> 0 | L18: {=IF(Journal[[#This Row],[Transaction '#]]<>"",IFERROR(INDEX(ProblemData!$E$240:$AM$240,1,Journal[[#This Row],[Transaction '#]]),""),"")} -> PdS | M18: =IF(Journal[[#This Row],[ref1]]="","",IF(NOT(ISBLANK(Journal[[#This Row],[Transaction '#]])),Journal[[#This Row],[ref1]]&Journal[[#This Row],[Movement '#]],"")) -> PdS1 | N18: =OR(Journal[[#This Row],[ref1]]="",ISNUMBER(MATCH(Journal[[#This Row],[ref1]],Operating[Abbr], 0))) -> TRUE | P18: =Journal[[#This Row],[Accnt Type]]&"Used" -> AssetUsed
C19: 4 | D19: Asset | F19: Cash | H19: 20 | J19: =IF(Journal[[#This Row],[Transaction '#]]="","",IF(Journal[[#This Row],[Transaction '#]]=C18,J18+1,1)) -> 2 | K19: {=IFERROR(_xlfn.IFS(Journal[[#This Row],[Debit Account]]="Cash",Journal[[#This Row],[Dr Amt]],Journal[[#This Row],[Credit Account]]="Cash",-Journal[[#This Row],[Cr Amt]]),0)} -> -20 | L19: {=IF(Journal[[#This Row],[Transaction '#]]<>"",IFERROR(INDEX(ProblemData!$E$240:$AM$240,1,Journal[[#This Row],[Transaction '#]]),""),"")} -> PdS | M19: =IF(Journal[[#This Row],[ref1]]="","",IF(NOT(ISBLANK(Journal[[#This Row],[Transaction '#]])),Journal[[#This Row],[ref1]]&Journal[[#This Row],[Movement '#]],"")) -> PdS2 | N19: =OR(Journal[[#This Row],[ref1]]="",ISNUMBER(MATCH(Journal[[#This Row],[ref1]],Operating[Abbr], 0))) -> TRUE | P19: =Journal[[#This Row],[Accnt Type]]&"Used" -> AssetUsed
J20: =IF(Journal[[#This Row],[Transaction '#]]="","",IF(Journal[[#This Row],[Transaction '#]]=C19,J19+1,1)) | K20: {=IFERROR(_xlfn.IFS(Journal[[#This Row],[Debit Account]]="Cash",Journal[[#This Row],[Dr Amt]],Journal[[#This Row],[Credit Account]]="Cash",-Journal[[#This Row],[Cr Amt]]),0)} -> 0 | L20: {=IF(Journal[[#This Row],[Transaction '#]]<>"",IFERROR(INDEX(ProblemData!$E$240:$AM$240,1,Journal[[#This Row],[Transaction '#]]),""),"")} | M20: =IF(Journal[[#This Row],[ref1]]="","",IF(NOT(ISBLANK(Journal[[#This Row],[Transaction '#]])),Journal[[#This Row],[ref1]]&Journal[[#This Row],[Movement '#]],"")) | N20: =OR(Journal[[#This Row],[ref1]]="",ISNUMBER(MATCH(Journal[[#This Row],[ref1]],Operating[Abbr], 0))) -> TRUE | P20: =Journal[[#This Row],[Accnt Type]]&"Used" -> Used
C21: 5 | D21: Asset | E21: Accounts Receivable | G21: 25 | J21: =IF(Journal[[#This Row],[Transaction '#]]="","",IF(Journal[[#This Row],[Transaction '#]]=C20,J20+1,1)) -> 1 | K21: {=IFERROR(_xlfn.IFS(Journal[[#This Row],[Debit Account]]="Cash",Journal[[#This Row],[Dr Amt]],Journal[[#This Row],[Credit Account]]="Cash",-Journal[[#This Row],[Cr Amt]]),0)} -> 0 | L21: {=IF(Journal[[#This Row],[Transaction '#]]<>"",IFERROR(INDEX(ProblemData!$E$240:$AM$240,1,Journal[[#This Row],[Transaction '#]]),""),"")} | M21: =IF(Journal[[#This Row],[ref1]]="","",IF(NOT(ISBLANK(Journal[[#This Row],[Transaction '#]])),Journal[[#This Row],[ref1]]&Journal[[#This Row],[Movement '#]],"")) | N21: =OR(Journal[[#This Row],[ref1]]="",ISNUMBER(MATCH(Journal[[#This Row],[ref1]],Operating[Abbr], 0))) -> TRUE | P21: =Journal[[#This Row],[Accnt Type]]&"Used" -> AssetUsed
C22: 5 | D22: Revenue | F22: Sales | H22: 25 | J22: =IF(Journal[[#This Row],[Transaction '#]]="","",IF(Journal[[#This Row],[Transaction '#]]=C21,J21+1,1)) -> 2 | K22: {=IFERROR(_xlfn.IFS(Journal[[#This Row],[Debit Account]]="Cash",Journal[[#This Row],[Dr Amt]],Journal[[#This Row],[Credit Account]]="Cash",-Journal[[#This Row],[Cr Amt]]),0)} -> 0 | L22: {=IF(Journal[[#This Row],[Transaction '#]]<>"",IFERROR(INDEX(ProblemData!$E$240:$AM$240,1,Journal[[#This Row],[Transaction '#]]),""),"")} | M22: =IF(Journal[[#This Row],[ref1]]="","",IF(NOT(ISBLANK(Journal[[#This Row],[Transaction '#]])),Journal[[#This Row],[ref1]]&Journal[[#This Row],[Movement '#]],"")) | N22: =OR(Journal[[#This Row],[ref1]]="",ISNUMBER(MATCH(Journal[[#This Row],[ref1]],Operating[Abbr], 0))) -> TRUE | P22: =Journal[[#This Row],[Accnt Type]]&"Used" -> RevenueUsed
J23: =IF(Journal[[#This Row],[Transaction '#]]="","",IF(Journal[[#This Row],[Transaction '#]]=C22,J22+1,1)) | K23: {=IFERROR(_xlfn.IFS(Journal[[#This Row],[Debit Account]]="Cash",Journal[[#This Row],[Dr Amt]],Journal[[#This Row],[Credit Account]]="Cash",-Journal[[#This Row],[Cr Amt]]),0)} -> 0 | L23: {=IF(Journal[[#This Row],[Transaction '#]]<>"",IFERROR(INDEX(ProblemData!$E$240:$AM$240,1,Journal[[#This Row],[Transaction '#]]),""),"")} | M23: =IF(Journal[[#This Row],[ref1]]="","",IF(NOT(ISBLANK(Journal[[#This Row],[Transaction '#]])),Journal[[#This Row],[ref1]]&Journal[[#This Row],[Movement '#]],"")) | N23: =OR(Journal[[#This Row],[ref1]]="",ISNUMBER(MATCH(Journal[[#This Row],[ref1]],Operating[Abbr], 0))) -> TRUE | P23: =Journal[[#This Row],[Accnt Type]]&"Used" -> Used
C24: 6 | D24: Asset | E24: Cash | G24: 20.5 | J24: =IF(Journal[[#This Row],[Transaction '#]]="","",IF(Journal[[#This Row],[Transaction '#]]=C23,J23+1,1)) -> 1 | K24: {=IFERROR(_xlfn.IFS(Journal[[#This Row],[Debit Account]]="Cash",Journal[[#This Row],[Dr Amt]],Journal[[#This Row],[Credit Account]]="Cash",-Journal[[#This Row],[Cr Amt]]),0)} -> 20.5 | L24: {=IF(Journal[[#This Row],[Transaction '#]]<>"",IFERROR(INDEX(ProblemData!$E$240:$AM$240,1,Journal[[#This Row],[Transaction '#]]),""),"")} -> ColC | M24: =IF(Journal[[#This Row],[ref1]]="","",IF(NOT(ISBLANK(Journal[[#This Row],[Transaction '#]])),Journal[[#This Row],[ref1]]&Journal[[#This Row],[Movement '#]],"")) -> ColC1 | N24: =OR(Journal[[#This Row],[ref1]]="",ISNUMBER(MATCH(Journal[[#This Row],[ref1]],Operating[Abbr], 0))) -> TRUE | P24: =Journal[[#This Row],[Accnt Type]]&"Used" -> AssetUsed
C25: 6 | D25: Asset | F25: Accounts Receivable | H25: 20.5 | J25: =IF(Journal[[#This Row],[Transaction '#]]="","",IF(Journal[[#This Row],[Transaction '#]]=C24,J24+1,1)) -> 2 | K25: {=IFERROR(_xlfn.IFS(Journal[[#This Row],[Debit Account]]="Cash",Journal[[#This Row],[Dr Amt]],Journal[[#This Row],[Credit Account]]="Cash",-Journal[[#This Row],[Cr Amt]]),0)} -> 0 | L25: {=IF(Journal[[#This Row],[Transaction '#]]<>"",IFERROR(INDEX(ProblemData!$E$240:$AM$240,1,Journal[[#This Row],[Transaction '#]]),""),"")} -> ColC | M25: =IF(Journal[[#This Row],[ref1]]="","",IF(NOT(ISBLANK(Journal[[#This Row],[Transaction '#]])),Journal[[#This Row],[ref1]]&Journal[[#This Row],[Movement '#]],"")) -> ColC2 | N25: =OR(Journal[[#This Row],[ref1]]="",ISNUMBER(MATCH(Journal[[#This Row],[ref1]],Operating[Abbr], 0))) -> TRUE | P25: =Journal[[#This Row],[Accnt Type]]&"Used" -> AssetUsed
J26: =IF(Journal[[#This Row],[Transaction '#]]="","",IF(Journal[[#This Row],[Transaction '#]]=C25,J25+1,1)) | K26: {=IFERROR(_xlfn.IFS(Journal[[#This Row],[Debit Account]]="Cash",Journal[[#This Row],[Dr Amt]],Journal[[#This Row],[Credit Account]]="Cash",-Journal[[#This Row],[Cr Amt]]),0)} -> 0 | L26: {=IF(Journal[[#This Row],[Transaction '#]]<>"",IFERROR(INDEX(ProblemData!$E$240:$AM$240,1,Journal[[#This Row],[Transaction '#]]),""),"")} | M26: =IF(Journal[[#This Row],[ref1]]="","",IF(NOT(ISBLANK(Journal[[#This Row],[Transaction '#]])),Journal[[#This Row],[ref1]]&Journal[[#This Row],[Movement '#]],"")) | N26: =OR(Journal[[#This Row],[ref1]]="",ISNUMBER(MATCH(Journal[[#This Row],[ref1]],Operating[Abbr], 0))) -> TRUE | P26: =Journal[[#This Row],[Accnt Type]]&"Used" -> Used
C27: 7 | D27: Expense | E27: Salaries & Wages Expense | G27: 3 | J27: =IF(Journal[[#This Row],[Transaction '#]]="","",IF(Journal[[#This Row],[Transaction '#]]=C26,J26+1,1)) -> 1 | K27: {=IFERROR(_xlfn.IFS(Journal[[#This Row],[Debit Account]]="Cash",Journal[[#This Row],[Dr Amt]],Journal[[#This Row],[Credit Account]]="Cash",-Journal[[#This Row],[Cr Amt]]),0)} -> 0 | L27: {=IF(Journal[[#This Row],[Transaction '#]]<>"",IFERROR(INDEX(ProblemData!$E$240:$AM$240,1,Journal[[#This Row],[Transaction '#]]),""),"")} -> PdSW | M27: =IF(Journal[[#This Row],[ref1]]="","",IF(NOT(ISBLANK(Journal[[#This Row],[Transaction '#]])),Journal[[#This Row],[ref1]]&Journal[[#This Row],[Movement '#]],"")) -> PdSW1 | N27: =OR(Journal[[#This Row],[ref1]]="",ISNUMBER(MATCH(Journal[[#This Row],[ref1]],Operating[Abbr], 0))) -> TRUE | P27: =Journal[[#This Row],[Accnt Type]]&"Used" -> ExpenseUsed
C28: 7 | D28: Asset | F28: Cash | H28: 3 | J28: =IF(Journal[[#This Row],[Transaction '#]]="","",IF(Journal[[#This Row],[Transaction '#]]=C27,J27+1,1)) -> 2 | K28: {=IFERROR(_xlfn.IFS(Journal[[#This Row],[Debit Account]]="Cash",Journal[[#This Row],[Dr Amt]],Journal[[#This Row],[Credit Account]]="Cash",-Journal[[#This Row],[Cr Amt]]),0)} -> -3 | L28: {=IF(Journal[[#This Row],[Transaction '#]]<>"",IFERROR(INDEX(ProblemData!$E$240:$AM$240,1,Journal[[#This Row],[Transaction '#]]),""),"")} -> PdSW | M28: =IF(Journal[[#This Row],[ref1]]="","",IF(NOT(ISBLANK(Journal[[#This Row],[Transaction '#]])),Journal[[#This Row],[ref1]]&Journal[[#This Row],[Movement '#]],"")) -> PdSW2 | N28: =OR(Journal[[#This Row],[ref1]]="",ISNUMBER(MATCH(Journal[[#This Row],[ref1]],Operating[Abbr], 0))) -> TRUE | P28: =Journal[[#This Row],[Accnt Type]]&"Used" -> AssetUsed
J29: =IF(Journal[[#This Row],[Transaction '#]]="","",IF(Journal[[#This Row],[Transaction '#]]=C28,J28+1,1)) | K29: {=IFERROR(_xlfn.IFS(Journal[[#This Row],[Debit Account]]="Cash",Journal[[#This Row],[Dr Amt]],Journal[[#This Row],[Credit Account]]="Cash",-Journal[[#This Row],[Cr Amt]]),0)} -> 0 | L29: {=IF(Journal[[#This Row],[Transaction '#]]<>"",IFERROR(INDEX(ProblemData!$E$240:$AM$240,1,Journal[[#This Row],[Transaction '#]]),""),"")} | M29: =IF(Journal[[#This Row],[ref1]]="","",IF(NOT(ISBLANK(Journal[[#This Row],[Transaction '#]])),Journal[[#This Row],[ref1]]&Journal[[#This Row],[Movement '#]],"")) | N29: =OR(Journal[[#This Row],[ref1]]="",ISNUMBER(MATCH(Journal[[#This Row],[ref1]],Operating[Abbr], 0))) -> TRUE | P29: =Journal[[#This Row],[Accnt Type]]&"Used" -> Used
C30: 8 | D30: Equity | E30: Retained Earnings | G30: 0.05 | J30: =IF(Journal[[#This Row],[Transaction '#]]="","",IF(Journal[[#This Row],[Transaction '#]]=C29,J29+1,1)) -> 1 | K30: {=IFERROR(_xlfn.IFS(Journal[[#This Row],[Debit Account]]="Cash",Journal[[#This Row],[Dr Amt]],Journal[[#This Row],[Credit Account]]="Cash",-Journal[[#This Row],[Cr Amt]]),0)} -> 0 | L30: {=IF(Journal[[#This Row],[Transaction '#]]<>"",IFERROR(INDEX(ProblemData!$E$240:$AM$240,1,Journal[[#This Row],[Transaction '#]]),""),"")} -> DD | M30: =IF(Journal[[#This Row],[ref1]]="","",IF(NOT(ISBLANK(Journal[[#This Row],[Transaction '#]])),Journal[[#This Row],[ref1]]&Journal[[#This Row],[Movement '#]],"")) -> DD1 | N30: =OR(Journal[[#This Row],[ref1]]="",ISNUMBER(MATCH(Journal[[#This Row],[ref1]],Operating[Abbr], 0))) -> FALSE | P30: =Journal[[#This Row],[Accnt Type]]&"Used" -> EquityUsed
C31: 8 | D31: Liability | F31: Dividends Payable | H31: 0.05 | J31: =IF(Journal[[#This Row],[Transaction '#]]="","",IF(Journal[[#This Row],[Transaction '#]]=C30,J30+1,1)) -> 2 | K31: {=IFERROR(_xlfn.IFS(Journal[[#This Row],[Debit Account]]="Cash",Journal[[#This Row],[Dr Amt]],Journal[[#This Row],[Credit Account]]="Cash",-Journal[[#This Row],[Cr Amt]]),0)} -> 0 | L31: {=IF(Journal[[#This Row],[Transaction '#]]<>"",IFERROR(INDEX(ProblemData!$E$240:$AM$240,1,Journal[[#This Row],[Transaction '#]]),""),"")} -> DD | M31: =IF(Journal[[#This Row],[ref1]]="","",IF(NOT(ISBLANK(Journal[[#This Row],[Transaction '#]])),Journal[[#This Row],[ref1]]&Journal[[#This Row],[Movement '#]],"")) -> DD2 | N31: =OR(Journal[[#This Row],[ref1]]="",ISNUMBER(MATCH(Journal[[#This Row],[ref1]],Operating[Abbr], 0))) -> FALSE | P31: =Journal[[#This Row],[Accnt Type]]&"Used" -> LiabilityUsed
J32: =IF(Journal[[#This Row],[Transaction '#]]="","",IF(Journal[[#This Row],[Transaction '#]]=C31,J31+1,1)) | K32: {=IFERROR(_xlfn.IFS(Journal[[#This Row],[Debit Account]]="Cash",Journal[[#This Row],[Dr Amt]],Journal[[#This Row],[Credit Account]]="Cash",-Journal[[#This Row],[Cr Amt]]),0)} -> 0 | L32: {=IF(Journal[[#This Row],[Transaction '#]]<>"",IFERROR(INDEX(ProblemData!$E$240:$AM$240,1,Journal[[#This Row],[Transaction '#]]),""),"")} | M32: =IF(Journal[[#This Row],[ref1]]="","",IF(NOT(ISBLANK(Journal[[#This Row],[Transaction '#]])),Journal[[#This Row],[ref1]]&Journal[[#This Row],[Movement '#]],"")) | N32: =OR(Journal[[#This Row],[ref1]]="",ISNUMBER(MATCH(Journal[[#This Row],[ref1]],Operating[Abbr], 0))) -> TRUE | P32: =Journal[[#This Row],[Accnt Type]]&"Used" -> Used
C33: 9 | D33: Liability | E33: Dividends Payable | G33: 0.05 | J33: =IF(Journal[[#This Row],[Transaction '#]]="","",IF(Journal[[#This Row],[Transaction '#]]=C32,J32+1,1)) -> 1 | K33: {=IFERROR(_xlfn.IFS(Journal[[#This Row],[Debit Account]]="Cash",Journal[[#This Row],[Dr Amt]],Journal[[#This Row],[Credit Account]]="Cash",-Journal[[#This Row],[Cr Amt]]),0)} -> 0 | L33: {=IF(Journal[[#This Row],[Transaction '#]]<>"",IFERROR(INDEX(ProblemData!$E$240:$AM$240,1,Journal[[#This Row],[Transaction '#]]),""),"")} -> PD | M33: =IF(Journal[[#This Row],[ref1]]="","",IF(NOT(ISBLANK(Journal[[#This Row],[Transaction '#]])),Journal[[#This Row],[ref1]]&Journal[[#This Row],[Movement '#]],"")) -> PD1 | N33: =OR(Journal[[#This Row],[ref1]]="",ISNUMBER(MATCH(Journal[[#This Row],[ref1]],Operating[Abbr], 0))) -> FALSE | P33: =Journal[[#This Row],[Accnt Type]]&"Used" -> LiabilityUsed
C34: 9 | D34: Asset | F34: Cash | H34: 0.05 | J34: =IF(Journal[[#This Row],[Transaction '#]]="","",IF(Journal[[#This Row],[Transaction '#]]=C33,J33+1,1)) -> 2 | K34: {=IFERROR(_xlfn.IFS(Journal[[#This Row],[Debit Account]]="Cash",Journal[[#This Row],[Dr Amt]],Journal[[#This Row],[Credit Account]]="Cash",-Journal[[#This Row],[Cr Amt]]),0)} -> -0.05 | L34: {=IF(Journal[[#This Row],[Transaction '#]]<>"",IFERROR(INDEX(ProblemData!$E$240:$AM$240,1,Journal[[#This Row],[Transaction '#]]),""),"")} -> PD | M34: =IF(Journal[[#This Row],[ref1]]="","",IF(NOT(ISBLANK(Journal[[#This Row],[Transaction '#]])),Journal[[#This Row],[ref1]]&Journal[[#This Row],[Movement '#]],"")) -> PD2 | N34: =OR(Journal[[#This Row],[ref1]]="",ISNUMBER(MATCH(Journal[[#This Row],[ref1]],Operating[Abbr], 0))) -> FALSE | P34: =Journal[[#This Row],[Accnt Type]]&"Used" -> AssetUsed
J35: =IF(Journal[[#This Row],[Transaction '#]]="","",IF(Journal[[#This Row],[Transaction '#]]=C34,J34+1,1)) | K35: {=IFERROR(_xlfn.IFS(Journal[[#This Row],[Debit Account]]="Cash",Journal[[#This Row],[Dr Amt]],Journal[[#This Row],[Credit Account]]="Cash",-Journal[[#This Row],[Cr Amt]]),0)} -> 0 | L35: {=IF(Journal[[#This Row],[Transaction '#]]<>"",IFERROR(INDEX(ProblemData!$E$240:$AM$240,1,Journal[[#This Row],[Transaction '#]]),""),"")} | M35: =IF(Journal[[#This Row],[ref1]]="","",IF(NOT(ISBLANK(Journal[[#This Row],[Transaction '#]])),Journal[[#This Row],[ref1]]&Journal[[#This Row],[Movement '#]],"")) | N35: =OR(Journal[[#This Row],[ref1]]="",ISNUMBER(MATCH(Journal[[#This Row],[ref1]],Operating[Abbr], 0))) -> TRUE | P35: =Journal[[#This Row],[Accnt Type]]&"Used" -> Used
J36: =IF(Journal[[#This Row],[Transaction '#]]="","",IF(Journal[[#This Row],[Transaction '#]]=C35,J35+1,1)) | K36: {=IFERROR(_xlfn.IFS(Journal[[#This Row],[Debit Account]]="Cash",Journal[[#This Row],[Dr Amt]],Journal[[#This Row],[Credit Account]]="Cash",-Journal[[#This Row],[Cr Amt]]),0)} -> 0 | L36: {=IF(Journal[[#This Row],[Transaction '#]]<>"",IFERROR(INDEX(ProblemData!$E$240:$AM$240,1,Journal[[#This Row],[Transaction '#]]),""),"")} | M36: =IF(Journal[[#This Row],[ref1]]="","",IF(NOT(ISBLANK(Journal[[#This Row],[Transaction '#]])),Journal[[#This Row],[ref1]]&Journal[[#This Row],[Movement '#]],"")) | N36: =OR(Journal[[#This Row],[ref1]]="",ISNUMBER(MATCH(Journal[[#This Row],[ref1]],Operating[Abbr], 0))) -> TRUE | P36: =Journal[[#This Row],[Accnt Type]]&"Used" -> Used
C37: 10 | D37: Expense | E37: Interest Expense | G37: 1.87 | J37: =IF(Journal[[#This Row],[Transaction '#]]="","",IF(Journal[[#This Row],[Transaction '#]]=C36,J36+1,1)) -> 1 | K37: {=IFERROR(_xlfn.IFS(Journal[[#This Row],[Debit Account]]="Cash",Journal[[#This Row],[Dr Amt]],Journal[[#This Row],[Credit Account]]="Cash",-Journal[[#This Row],[Cr Amt]]),0)} -> 0 | L37: {=IF(Journal[[#This Row],[Transaction '#]]<>"",IFERROR(INDEX(ProblemData!$E$240:$AM$240,1,Journal[[#This Row],[Transaction '#]]),""),"")} | M37: =IF(Journal[[#This Row],[ref1]]="","",IF(NOT(ISBLANK(Journal[[#This Row],[Transaction '#]])),Journal[[#This Row],[ref1]]&Journal[[#This Row],[Movement '#]],"")) | N37: =OR(Journal[[#This Row],[ref1]]="",ISNUMBER(MATCH(Journal[[#This Row],[ref1]],Operating[Abbr], 0))) -> TRUE | P37: =Journal[[#This Row],[Accnt Type]]&"Used" -> ExpenseUsed
C38: 10 | D38: Liability | F38: Interest Payable | H38: 1.87 | J38: =IF(Journal[[#This Row],[Transaction '#]]="","",IF(Journal[[#This Row],[Transaction '#]]=C37,J37+1,1)) -> 2 | K38: {=IFERROR(_xlfn.IFS(Journal[[#This Row],[Debit Account]]="Cash",Journal[[#This Row],[Dr Amt]],Journal[[#This Row],[Credit Account]]="Cash",-Journal[[#This Row],[Cr Amt]]),0)} -> 0 | L38: {=IF(Journal[[#This Row],[Transaction '#]]<>"",IFERROR(INDEX(ProblemData!$E$240:$AM$240,1,Journal[[#This Row],[Transaction '#]]),""),"")} | M38: =IF(Journal[[#This Row],[ref1]]="","",IF(NOT(ISBLANK(Journal[[#This Row],[Transaction '#]])),Journal[[#This Row],[ref1]]&Journal[[#This Row],[Movement '#]],"")) | N38: =OR(Journal[[#This Row],[ref1]]="",ISNUMBER(MATCH(Journal[[#This Row],[ref1]],Operating[Abbr], 0))) -> TRUE | P38: =Journal[[#This Row],[Accnt Type]]&"Used" -> LiabilityUsed
J39: =IF(Journal[[#This Row],[Transaction '#]]="","",IF(Journal[[#This Row],[Transaction '#]]=C38,J38+1,1)) | K39: {=IFERROR(_xlfn.IFS(Journal[[#This Row],[Debit Account]]="Cash",Journal[[#This Row],[Dr Amt]],Journal[[#This Row],[Credit Account]]="Cash",-Journal[[#This Row],[Cr Amt]]),0)} -> 0 | L39: {=IF(Journal[[#This Row],[Transaction '#]]<>"",IFERROR(INDEX(ProblemData!$E$240:$AM$240,1,Journal[[#This Row],[Transaction '#]]),""),"")} | M39: =IF(Journal[[#This Row],[ref1]]="","",IF(NOT(ISBLANK(Journal[[#This Row],[Transaction '#]])),Journal[[#This Row],[ref1]]&Journal[[#This Row],[Movement '#]],"")) | N39: =OR(Journal[[#This Row],[ref1]]="",ISNUMBER(MATCH(Journal[[#This Row],[ref1]],Operating[Abbr], 0))) -> TRUE | P39: =Journal[[#This Row],[Accnt Type]]&"Used" -> Used
C40: 11 | D40: Liability | E40: Interest Payable | G40: 1.87 | J40: =IF(Journal[[#This Row],[Transaction '#]]="","",IF(Journal[[#This Row],[Transaction '#]]=C39,J39+1,1)) -> 1 | K40: {=IFERROR(_xlfn.IFS(Journal[[#This Row],[Debit Account]]="Cash",Journal[[#This Row],[Dr Amt]],Journal[[#This Row],[Credit Account]]="Cash",-Journal[[#This Row],[Cr Amt]]),0)} -> 0 | L40: {=IF(Journal[[#This Row],[Transaction '#]]<>"",IFERROR(INDEX(ProblemData!$E$240:$AM$240,1,Journal[[#This Row],[Transaction '#]]),""),"")} -> PdInt | M40: =IF(Journal[[#This Row],[ref1]]="","",IF(NOT(ISBLANK(Journal[[#This Row],[Transaction '#]])),Journal[[#This Row],[ref1]]&Journal[[#This Row],[Movement '#]],"")) -> PdInt1 | N40: =OR(Journal[[#This Row],[ref1]]="",ISNUMBER(MATCH(Journal[[#This Row],[ref1]],Operating[Abbr], 0))) -> TRUE | P40: =Journal[[#This Row],[Accnt Type]]&"Used" -> LiabilityUsed
C41: 11 | D41: Asset | F41: Cash | H41: 1.87 | J41: =IF(Journal[[#This Row],[Transaction '#]]="","",IF(Journal[[#This Row],[Transaction '#]]=C40,J40+1,1)) -> 2 | K41: {=IFERROR(_xlfn.IFS(Journal[[#This Row],[Debit Account]]="Cash",Journal[[#This Row],[Dr Amt]],Journal[[#This Row],[Credit Account]]="Cash",-Journal[[#This Row],[Cr Amt]]),0)} -> -1.87 | L41: {=IF(Journal[[#This Row],[Transaction '#]]<>"",IFERROR(INDEX(ProblemData!$E$240:$AM$240,1,Journal[[#This Row],[Transaction '#]]),""),"")} -> PdInt | M41: =IF(Journal[[#This Row],[ref1]]="","",IF(NOT(ISBLANK(Journal[[#This Row],[Transaction '#]])),Journal[[#This Row],[ref1]]&Journal[[#This Row],[Movement '#]],"")) -> PdInt2 | N41: =OR(Journal[[#This Row],[ref1]]="",ISNUMBER(MATCH(Journal[[#This Row],[ref1]],Operating[Abbr], 0))) -> TRUE | P41: =Journal[[#This Row],[Accnt Type]]&"Used" -> AssetUsed
J42: =IF(Journal[[#This Row],[Transaction '#]]="","",IF(Journal[[#This Row],[Transaction '#]]=C41,J41+1,1)) | K42: {=IFERROR(_xlfn.IFS(Journal[[#This Row],[Debit Account]]="Cash",Journal[[#This Row],[Dr Amt]],Journal[[#This Row],[Credit Account]]="Cash",-Journal[[#This Row],[Cr Amt]]),0)} -> 0 | L42: {=IF(Journal[[#This Row],[Transaction '#]]<>"",IFERROR(INDEX(ProblemData!$E$240:$AM$240,1,Journal[[#This Row],[Transaction '#]]),""),"")} | M42: =IF(Journal[[#This Row],[ref1]]="","",IF(NOT(ISBLANK(Journal[[#This Row],[Transaction '#]])),Journal[[#This Row],[ref1]]&Journal[[#This Row],[Movement '#]],"")) | N42: =OR(Journal[[#This Row],[ref1]]="",ISNUMBER(MATCH(Journal[[#This Row],[ref1]],Operating[Abbr], 0))) -> TRUE | P42: =Journal[[#This Row],[Accnt Type]]&"Used" -> Used
C43: 12 | D43: Expense | E43: Cost of Goods Sold | G43: 18 | J43: =IF(Journal[[#This Row],[Transaction '#]]="","",IF(Journal[[#This Row],[Transaction '#]]=C42,J42+1,1)) -> 1 | K43: {=IFERROR(_xlfn.IFS(Journal[[#This Row],[Debit Account]]="Cash",Journal[[#This Row],[Dr Amt]],Journal[[#This Row],[Credit Account]]="Cash",-Journal[[#This Row],[Cr Amt]]),0)} -> 0 | L43: {=IF(Journal[[#This Row],[Transaction '#]]<>"",IFERROR(INDEX(ProblemData!$E$240:$AM$240,1,Journal[[#This Row],[Transaction '#]]),""),"")} | M43: =IF(Journal[[#This Row],[ref1]]="","",IF(NOT(ISBLANK(Journal[[#This Row],[Transaction '#]])),Journal[[#This Row],[ref1]]&Journal[[#This Row],[Movement '#]],"")) | N43: =OR(Journal[[#This Row],[ref1]]="",ISNUMBER(MATCH(Journal[[#This Row],[ref1]],Operating[Abbr], 0))) -> TRUE | P43: =Journal[[#This Row],[Accnt Type]]&"Used" -> ExpenseUsed
C44: 12 | D44: Asset | F44: Inventories | H44: 18 | J44: =IF(Journal[[#This Row],[Transaction '#]]="","",IF(Journal[[#This Row],[Transaction '#]]=C43,J43+1,1)) -> 2 | K44: {=IFERROR(_xlfn.IFS(Journal[[#This Row],[Debit Account]]="Cash",Journal[[#This Row],[Dr Amt]],Journal[[#This Row],[Credit Account]]="Cash",-Journal[[#This Row],[Cr Amt]]),0)} -> 0 | L44: {=IF(Journal[[#This Row],[Transaction '#]]<>"",IFERROR(INDEX(ProblemData!$E$240:$AM$240,1,Journal[[#This Row],[Transaction '#]]),""),"")} | M44: =IF(Journal[[#This Row],[ref1]]="","",IF(NOT(ISBLANK(Journal[[#This Row],[Transaction '#]])),Journal[[#This Row],[ref1]]&Journal[[#This Row],[Movement '#]],"")) | N44: =OR(Journal[[#This Row],[ref1]]="",ISNUMBER(MATCH(Journal[[#This Row],[ref1]],Operating[Abbr], 0))) -> TRUE | P44: =Journal[[#This Row],[Accnt Type]]&"Used" -> AssetUsed
J45: =IF(Journal[[#This Row],[Transaction '#]]="","",IF(Journal[[#This Row],[Transaction '#]]=C44,J44+1,1)) | K45: {=IFERROR(_xlfn.IFS(Journal[[#This Row],[Debit Account]]="Cash",Journal[[#This Row],[Dr Amt]],Journal[[#This Row],[Credit Account]]="Cash",-Journal[[#This Row],[Cr Amt]]),0)} -> 0 | L45: {=IF(Journal[[#This Row],[Transaction '#]]<>"",IFERROR(INDEX(ProblemData!$E$240:$AM$240,1,Journal[[#This Row],[Transaction '#]]),""),"")} | M45: =IF(Journal[[#This Row],[ref1]]="","",IF(NOT(ISBLANK(Journal[[#This Row],[Transaction '#]])),Journal[[#This Row],[ref1]]&Journal[[#This Row],[Movement '#]],"")) | N45: =OR(Journal[[#This Row],[ref1]]="",ISNUMBER(MATCH(Journal[[#This Row],[ref1]],Operating[Abbr], 0))) -> TRUE | P45: =Journal[[#This Row],[Accnt Type]]&"Used" -> Used
C46: 13 | D46: Expense | E46: Depreciation Expense | G46: 0.2 | J46: =IF(Journal[[#This Row],[Transaction '#]]="","",IF(Journal[[#This Row],[Transaction '#]]=C45,J45+1,1)) -> 1 | K46: {=IFERROR(_xlfn.IFS(Journal[[#This Row],[Debit Account]]="Cash",Journal[[#This Row],[Dr Amt]],Journal[[#This Row],[Credit Account]]="Cash",-Journal[[#This Row],[Cr Amt]]),0)} -> 0 | L46: {=IF(Journal[[#This Row],[Transaction '#]]<>"",IFERROR(INDEX(ProblemData!$E$240:$AM$240,1,Journal[[#This Row],[Transaction '#]]),""),"")} -> RecDeprExp | M46: =IF(Journal[[#This Row],[ref1]]="","",IF(NOT(ISBLANK(Journal[[#This Row],[Transaction '#]])),Journal[[#This Row],[ref1]]&Journal[[#This Row],[Movement '#]],"")) -> RecDeprExp1 | N46: =OR(Journal[[#This Row],[ref1]]="",ISNUMBER(MATCH(Journal[[#This Row],[ref1]],Operating[Abbr], 0))) -> FALSE | P46: =Journal[[#This Row],[Accnt Type]]&"Used" -> ExpenseUsed
C47: 13 | D47: Asset | F47: Accumulated Depreciation | H47: 0.2 | J47: =IF(Journal[[#This Row],[Transaction '#]]="","",IF(Journal[[#This Row],[Transaction '#]]=C46,J46+1,1)) -> 2 | K47: {=IFERROR(_xlfn.IFS(Journal[[#This Row],[Debit Account]]="Cash",Journal[[#This Row],[Dr Amt]],Journal[[#This Row],[Credit Account]]="Cash",-Journal[[#This Row],[Cr Amt]]),0)} -> 0 | L47: {=IF(Journal[[#This Row],[Transaction '#]]<>"",IFERROR(INDEX(ProblemData!$E$240:$AM$240,1,Journal[[#This Row],[Transaction '#]]),""),"")} -> RecDeprExp | M47: =IF(Journal[[#This Row],[ref1]]="","",IF(NOT(ISBLANK(Journal[[#This Row],[Transaction '#]])),Journal[[#This Row],[ref1]]&Journal[[#This Row],[Movement '#]],"")) -> RecDeprExp2 | N47: =OR(Journal[[#This Row],[ref1]]="",ISNUMBER(MATCH(Journal[[#This Row],[ref1]],Operating[Abbr], 0))) -> FALSE | P47: =Journal[[#This Row],[Accnt Type]]&"Used" -> AssetUsed
J48: =IF(Journal[[#This Row],[Transaction '#]]="","",IF(Journal[[#This Row],[Transaction '#]]=C47,J47+1,1)) | K48: {=IFERROR(_xlfn.IFS(Journal[[#This Row],[Debit Account]]="Cash",Journal[[#This Row],[Dr Amt]],Journal[[#This Row],[Credit Account]]="Cash",-Journal[[#This Row],[Cr Amt]]),0)} -> 0 | L48: {=IF(Journal[[#This Row],[Transaction '#]]<>"",IFERROR(INDEX(ProblemData!$E$240:$AM$240,1,Journal[[#This Row],[Transaction '#]]),""),"")} | M48: =IF(Journal[[#This Row],[ref1]]="","",IF(NOT(ISBLANK(Journal[[#This Row],[Transaction '#]])),Journal[[#This Row],[ref1]]&Journal[[#This Row],[Movement '#]],"")) | N48: =OR(Journal[[#This Row],[ref1]]="",ISNUMBER(MATCH(Journal[[#This Row],[ref1]],Operating[Abbr], 0))) -> TRUE | P48: =Journal[[#This Row],[Accnt Type]]&"Used" -> Used
C49: 14 | D49: Revenue | E49: Sales | G49: 25 | J49: =IF(Journal[[#This Row],[Transaction '#]]="","",IF(Journal[[#This Row],[Transaction '#]]=C48,J48+1,1)) -> 1 | K49: {=IFERROR(_xlfn.IFS(Journal[[#This Row],[Debit Account]]="Cash",Journal[[#This Row],[Dr Amt]],Journal[[#This Row],[Credit Account]]="Cash",-Journal[[#This Row],[Cr Amt]]),0)} -> 0 | L49: {=IF(Journal[[#This Row],[Transaction '#]]<>"",IFERROR(INDEX(ProblemData!$E$240:$AM$240,1,Journal[[#This Row],[Transaction '#]]),""),"")} -> CL | M49: =IF(Journal[[#This Row],[ref1]]="","",IF(NOT(ISBLANK(Journal[[#This Row],[Transaction '#]])),Journal[[#This Row],[ref1]]&Journal[[#This Row],[Movement '#]],"")) -> CL1 | N49: =OR(Journal[[#This Row],[ref1]]="",ISNUMBER(MATCH(Journal[[#This Row],[ref1]],Operating[Abbr], 0))) -> FALSE | P49: =Journal[[#This Row],[Accnt Type]]&"Used" -> RevenueUsed
C50: 14 | D50: Expense | F50: Cost of Goods Sold | H50: 18 | J50: =IF(Journal[[#This Row],[Transaction '#]]="","",IF(Journal[[#This Row],[Transaction '#]]=C49,J49+1,1)) -> 2 | K50: {=IFERROR(_xlfn.IFS(Journal[[#This Row],[Debit Account]]="Cash",Journal[[#This Row],[Dr Amt]],Journal[[#This Row],[Credit Account]]="Cash",-Journal[[#This Row],[Cr Amt]]),0)} -> 0 | L50: {=IF(Journal[[#This Row],[Transaction '#]]<>"",IFERROR(INDEX(ProblemData!$E$240:$AM$240,1,Journal[[#This Row],[Transaction '#]]),""),"")} -> CL | M50: =IF(Journal[[#This Row],[ref1]]="","",IF(NOT(ISBLANK(Journal[[#This Row],[Transaction '#]])),Journal[[#This Row],[ref1]]&Journal[[#This Row],[Movement '#]],"")) -> CL2 | N50: =OR(Journal[[#This Row],[ref1]]="",ISNUMBER(MATCH(Journal[[#This Row],[ref1]],Operating[Abbr], 0))) -> FALSE | P50: =Journal[[#This Row],[Accnt Type]]&"Used" -> ExpenseUsed
C51: 14 | D51: Expense | F51: Interest Expense | H51: 1.87 | J51: =IF(Journal[[#This Row],[Transaction '#]]="","",IF(Journal[[#This Row],[Transaction '#]]=C50,J50+1,1)) -> 3 | K51: {=IFERROR(_xlfn.IFS(Journal[[#This Row],[Debit Account]]="Cash",Journal[[#This Row],[Dr Amt]],Journal[[#This Row],[Credit Account]]="Cash",-Journal[[#This Row],[Cr Amt]]),0)} -> 0 | L51: {=IF(Journal[[#This Row],[Transaction '#]]<>"",IFERROR(INDEX(ProblemData!$E$240:$AM$240,1,Journal[[#This Row],[Transaction '#]]),""),"")} -> CL | M51: =IF(Journal[[#This Row],[ref1]]="","",IF(NOT(ISBLANK(Journal[[#This Row],[Transaction '#]])),Journal[[#This Row],[ref1]]&Journal[[#This Row],[Movement '#]],"")) -> CL3 | N51: =OR(Journal[[#This Row],[ref1]]="",ISNUMBER(MATCH(Journal[[#This Row],[ref1]],Operating[Abbr], 0))) -> FALSE | P51: =Journal[[#This Row],[Accnt Type]]&"Used" -> ExpenseUsed
C52: 14 | D52: Expense | F52: Depreciation Expense | H52: 0.2 | J52: =IF(Journal[[#This Row],[Transaction '#]]="","",IF(Journal[[#This Row],[Transaction '#]]=C51,J51+1,1)) -> 4 | K52: {=IFERROR(_xlfn.IFS(Journal[[#This Row],[Debit Account]]="Cash",Journal[[#This Row],[Dr Amt]],Journal[[#This Row],[Credit Account]]="Cash",-Journal[[#This Row],[Cr Amt]]),0)} -> 0 | L52: {=IF(Journal[[#This Row],[Transaction '#]]<>"",IFERROR(INDEX(ProblemData!$E$240:$AM$240,1,Journal[[#This Row],[Transaction '#]]),""),"")} -> CL | M52: =IF(Journal[[#This Row],[ref1]]="","",IF(NOT(ISBLANK(Journal[[#This Row],[Transaction '#]])),Journal[[#This Row],[ref1]]&Journal[[#This Row],[Movement '#]],"")) -> CL4 | N52: =OR(Journal[[#This Row],[ref1]]="",ISNUMBER(MATCH(Journal[[#This Row],[ref1]],Operating[Abbr], 0))) -> FALSE | P52: =Journal[[#This Row],[Accnt Type]]&"Used" -> ExpenseUsed
C53: 14 | D53: Expense | F53: Salaries & Wages Expense | H53: 3 | J53: =IF(Journal[[#This Row],[Transaction '#]]="","",IF(Journal[[#This Row],[Transaction '#]]=C52,J52+1,1)) -> 5 | K53: {=IFERROR(_xlfn.IFS(Journal[[#This Row],[Debit Account]]="Cash",Journal[[#This Row],[Dr Amt]],Journal[[#This Row],[Credit Account]]="Cash",-Journal[[#This Row],[Cr Amt]]),0)} -> 0 | L53: {=IF(Journal[[#This Row],[Transaction '#]]<>"",IFERROR(INDEX(ProblemData!$E$240:$AM$240,1,Journal[[#This Row],[Transaction '#]]),""),"")} -> CL | M53: =IF(Journal[[#This Row],[ref1]]="","",IF(NOT(ISBLANK(Journal[[#This Row],[Transaction '#]])),Journal[[#This Row],[ref1]]&Journal[[#This Row],[Movement '#]],"")) -> CL5 | N53: =OR(Journal[[#This Row],[ref1]]="",ISNUMBER(MATCH(Journal[[#This Row],[ref1]],Operating[Abbr], 0))) -> FALSE | P53: =Journal[[#This Row],[Accnt Type]]&"Used" -> ExpenseUsed
C54: 14 | D54: Equity | F54: Retained Earnings | H54: 1.93 | J54: =IF(Journal[[#This Row],[Transaction '#]]="","",IF(Journal[[#This Row],[Transaction '#]]=C53,J53+1,1)) -> 6 | K54: {=IFERROR(_xlfn.IFS(Journal[[#This Row],[Debit Account]]="Cash",Journal[[#This Row],[Dr Amt]],Journal[[#This Row],[Credit Account]]="Cash",-Journal[[#This Row],[Cr Amt]]),0)} -> 0 | L54: {=IF(Journal[[#This Row],[Transaction '#]]<>"",IFERROR(INDEX(ProblemData!$E$240:$AM$240,1,Journal[[#This Row],[Transaction '#]]),""),"")} -> CL | M54: =IF(Journal[[#This Row],[ref1]]="","",IF(NOT(ISBLANK(Journal[[#This Row],[Transaction '#]])),Journal[[#This Row],[ref1]]&Journal[[#This Row],[Movement '#]],"")) -> CL6 | N54: =OR(Journal[[#This Row],[ref1]]="",ISNUMBER(MATCH(Journal[[#This Row],[ref1]],Operating[Abbr], 0))) -> FALSE | P54: =Journal[[#This Row],[Accnt Type]]&"Used" -> EquityUsed
J55: =IF(Journal[[#This Row],[Transaction '#]]="","",IF(Journal[[#This Row],[Transaction '#]]=C54,J54+1,1)) | K55: {=IFERROR(_xlfn.IFS(Journal[[#This Row],[Debit Account]]="Cash",Journal[[#This Row],[Dr Amt]],Journal[[#This Row],[Credit Account]]="Cash",-Journal[[#This Row],[Cr Amt]]),0)} -> 0 | L55: {=IF(Journal[[#This Row],[Transaction '#]]<>"",IFERROR(INDEX(ProblemData!$E$240:$AM$240,1,Journal[[#This Row],[Transaction '#]]),""),"")} | M55: =IF(Journal[[#This Row],[ref1]]="","",IF(NOT(ISBLANK(Journal[[#This Row],[Transaction '#]])),Journal[[#This Row],[ref1]]&Journal[[#This Row],[Movement '#]],"")) | N55: =OR(Journal[[#This Row],[ref1]]="",ISNUMBER(MATCH(Journal[[#This Row],[ref1]],Operating[Abbr], 0))) -> TRUE | P55: =Journal[[#This Row],[Accnt Type]]&"Used" -> Used
J56: =IF(Journal[[#This Row],[Transaction '#]]="","",IF(Journal[[#This Row],[Transaction '#]]=C55,J55+1,1)) | K56: {=IFERROR(_xlfn.IFS(Journal[[#This Row],[Debit Account]]="Cash",Journal[[#This Row],[Dr Amt]],Journal[[#This Row],[Credit Account]]="Cash",-Journal[[#This Row],[Cr Amt]]),0)} -> 0 | L56: {=IF(Journal[[#This Row],[Transaction '#]]<>"",IFERROR(INDEX(ProblemData!$E$240:$AM$240,1,Journal[[#This Row],[Transaction '#]]),""),"")} | M56: =IF(Journal[[#This Row],[ref1]]="","",IF(NOT(ISBLANK(Journal[[#This Row],[Transaction '#]])),Journal[[#This Row],[ref1]]&Journal[[#This Row],[Movement '#]],"")) | N56: =OR(Journal[[#This Row],[ref1]]="",ISNUMBER(MATCH(Journal[[#This Row],[ref1]],Operating[Abbr], 0))) -> TRUE | P56: =Journal[[#This Row],[Accnt Type]]&"Used" -> Used
J57: =IF(Journal[[#This Row],[Transaction '#]]="","",IF(Journal[[#This Row],[Transaction '#]]=C56,J56+1,1)) | K57: {=IFERROR(_xlfn.IFS(Journal[[#This Row],[Debit Account]]="Cash",Journal[[#This Row],[Dr Amt]],Journal[[#This Row],[Credit Account]]="Cash",-Journal[[#This Row],[Cr Amt]]),0)} -> 0 | L57: {=IF(Journal[[#This Row],[Transaction '#]]<>"",IFERROR(INDEX(ProblemData!$E$240:$AM$240,1,Journal[[#This Row],[Transaction '#]]),""),"")} | M57: =IF(Journal[[#This Row],[ref1]]="","",IF(NOT(ISBLANK(Journal[[#This Row],[Transaction '#]])),Journal[[#This Row],[ref1]]&Journal[[#This Row],[Movement '#]],"")) | N57: =OR(Journal[[#This Row],[ref1]]="",ISNUMBER(MATCH(Journal[[#This Row],[ref1]],Operating[Abbr], 0))) -> TRUE | P57: =Journal[[#This Row],[Accnt Type]]&"Used" -> Used
J58: =IF(Journal[[#This Row],[Transaction '#]]="","",IF(Journal[[#This Row],[Transaction '#]]=C57,J57+1,1)) | K58: {=IFERROR(_xlfn.IFS(Journal[[#This Row],[Debit Account]]="Cash",Journal[[#This Row],[Dr Amt]],Journal[[#This Row],[Credit Account]]="Cash",-Journal[[#This Row],[Cr Amt]]),0)} -> 0 | L58: {=IF(Journal[[#This Row],[Transaction '#]]<>"",IFERROR(INDEX(ProblemData!$E$240:$AM$240,1,Journal[[#This Row],[Transaction '#]]),""),"")} | M58: =IF(Journal[[#This Row],[ref1]]="","",IF(NOT(ISBLANK(Journal[[#This Row],[Transaction '#]])),Journal[[#This Row],[ref1]]&Journal[[#This Row],[Movement '#]],"")) | N58: =OR(Journal[[#This Row],[ref1]]="",ISNUMBER(MATCH(Journal[[#This Row],[ref1]],Operating[Abbr], 0))) -> TRUE | P58: =Journal[[#This Row],[Accnt Type]]&"Used" -> Used
J59: =IF(Journal[[#This Row],[Transaction '#]]="","",IF(Journal[[#This Row],[Transaction '#]]=C58,J58+1,1)) | K59: {=IFERROR(_xlfn.IFS(Journal[[#This Row],[Debit Account]]="Cash",Journal[[#This Row],[Dr Amt]],Journal[[#This Row],[Credit Account]]="Cash",-Journal[[#This Row],[Cr Amt]]),0)} -> 0 | L59: {=IF(Journal[[#This Row],[Transaction '#]]<>"",IFERROR(INDEX(ProblemData!$E$240:$AM$240,1,Journal[[#This Row],[Transaction '#]]),""),"")} | M59: =IF(Journal[[#This Row],[ref1]]="","",IF(NOT(ISBLANK(Journal[[#This Row],[Transaction '#]])),Journal[[#This Row],[ref1]]&Journal[[#This Row],[Movement '#]],"")) | N59: =OR(Journal[[#This Row],[ref1]]="",ISNUMBER(MATCH(Journal[[#This Row],[ref1]],Operating[Abbr], 0))) -> TRUE | P59: =Journal[[#This Row],[Accnt Type]]&"Used" -> Used
J60: =IF(Journal[[#This Row],[Transaction '#]]="","",IF(Journal[[#This Row],[Transaction '#]]=C59,J59+1,1)) | K60: {=IFERROR(_xlfn.IFS(Journal[[#This Row],[Debit Account]]="Cash",Journal[[#This Row],[Dr Amt]],Journal[[#This Row],[Credit Account]]="Cash",-Journal[[#This Row],[Cr Amt]]),0)} -> 0 | L60: {=IF(Journal[[#This Row],[Transaction '#]]<>"",IFERROR(INDEX(ProblemData!$E$240:$AM$240,1,Journal[[#This Row],[Transaction '#]]),""),"")} | M60: =IF(Journal[[#This Row],[ref1]]="","",IF(NOT(ISBLANK(Journal[[#This Row],[Transaction '#]])),Journal[[#This Row],[ref1]]&Journal[[#This Row],[Movement '#]],"")) | N60: =OR(Journal[[#This Row],[ref1]]="",ISNUMBER(MATCH(Journal[[#This Row],[ref1]],Operating[Abbr], 0))) -> TRUE | P60: =Journal[[#This Row],[Accnt Type]]&"Used" -> Used
J61: =IF(Journal[[#This Row],[Transaction '#]]="","",IF(Journal[[#This Row],[Transaction '#]]=C60,J60+1,1)) | K61: {=IFERROR(_xlfn.IFS(Journal[[#This Row],[Debit Account]]="Cash",Journal[[#This Row],[Dr Amt]],Journal[[#This Row],[Credit Account]]="Cash",-Journal[[#This Row],[Cr Amt]]),0)} -> 0 | L61: {=IF(Journal[[#This Row],[Transaction '#]]<>"",IFERROR(INDEX(ProblemData!$E$240:$AM$240,1,Journal[[#This Row],[Transaction '#]]),""),"")} | M61: =IF(Journal[[#This Row],[ref1]]="","",IF(NOT(ISBLANK(Journal[[#This Row],[Transaction '#]])),Journal[[#This Row],[ref1]]&Journal[[#This Row],[Movement '#]],"")) | N61: =OR(Journal[[#This Row],[ref1]]="",ISNUMBER(MATCH(Journal[[#This Row],[ref1]],Operating[Abbr], 0))) -> TRUE | P61: =Journal[[#This Row],[Accnt Type]]&"Used" -> Used
J62: =IF(Journal[[#This Row],[Transaction '#]]="","",IF(Journal[[#This Row],[Transaction '#]]=C61,J61+1,1)) | K62: {=IFERROR(_xlfn.IFS(Journal[[#This Row],[Debit Account]]="Cash",Journal[[#This Row],[Dr Amt]],Journal[[#This Row],[Credit Account]]="Cash",-Journal[[#This Row],[Cr Amt]]),0)} -> 0 | L62: {=IF(Journal[[#This Row],[Transaction '#]]<>"",IFERROR(INDEX(ProblemData!$E$240:$AM$240,1,Journal[[#This Row],[Transaction '#]]),""),"")} | M62: =IF(Journal[[#This Row],[ref1]]="","",IF(NOT(ISBLANK(Journal[[#This Row],[Transaction '#]])),Journal[[#This Row],[ref1]]&Journal[[#This Row],[Movement '#]],"")) | N62: =OR(Journal[[#This Row],[ref1]]="",ISNUMBER(MATCH(Journal[[#This Row],[ref1]],Operating[Abbr], 0))) -> TRUE | P62: =Journal[[#This Row],[Accnt Type]]&"Used" -> Used
J63: =IF(Journal[[#This Row],[Transaction '#]]="","",IF(Journal[[#This Row],[Transaction '#]]=C62,J62+1,1)) | K63: {=IFERROR(_xlfn.IFS(Journal[[#This Row],[Debit Account]]="Cash",Journal[[#This Row],[Dr Amt]],Journal[[#This Row],[Credit Account]]="Cash",-Journal[[#This Row],[Cr Amt]]),0)} -> 0 | L63: {=IF(Journal[[#This Row],[Transaction '#]]<>"",IFERROR(INDEX(ProblemData!$E$240:$AM$240,1,Journal[[#This Row],[Transaction '#]]),""),"")} | M63: =IF(Journal[[#This Row],[ref1]]="","",IF(NOT(ISBLANK(Journal[[#This Row],[Transaction '#]])),Journal[[#This Row],[ref1]]&Journal[[#This Row],[Movement '#]],"")) | N63: =OR(Journal[[#This Row],[ref1]]="",ISNUMBER(MATCH(Journal[[#This Row],[ref1]],Operating[Abbr], 0))) -> TRUE | P63: =Journal[[#This Row],[Accnt Type]]&"Used" -> Used
J64: =IF(Journal[[#This Row],[Transaction '#]]="","",IF(Journal[[#This Row],[Transaction '#]]=C63,J63+1,1)) | K64: {=IFERROR(_xlfn.IFS(Journal[[#This Row],[Debit Account]]="Cash",Journal[[#This Row],[Dr Amt]],Journal[[#This Row],[Credit Account]]="Cash",-Journal[[#This Row],[Cr Amt]]),0)} -> 0 | L64: {=IF(Journal[[#This Row],[Transaction '#]]<>"",IFERROR(INDEX(ProblemData!$E$240:$AM$240,1,Journal[[#This Row],[Transaction '#]]),""),"")} | M64: =IF(Journal[[#This Row],[ref1]]="","",IF(NOT(ISBLANK(Journal[[#This Row],[Transaction '#]])),Journal[[#This Row],[ref1]]&Journal[[#This Row],[Movement '#]],"")) | N64: =OR(Journal[[#This Row],[ref1]]="",ISNUMBER(MATCH(Journal[[#This Row],[ref1]],Operating[Abbr], 0))) -> TRUE | P64: =Journal[[#This Row],[Accnt Type]]&"Used" -> Used
J65: =IF(Journal[[#This Row],[Transaction '#]]="","",IF(Journal[[#This Row],[Transaction '#]]=C64,J64+1,1)) | K65: {=IFERROR(_xlfn.IFS(Journal[[#This Row],[Debit Account]]="Cash",Journal[[#This Row],[Dr Amt]],Journal[[#This Row],[Credit Account]]="Cash",-Journal[[#This Row],[Cr Amt]]),0)} -> 0 | L65: {=IF(Journal[[#This Row],[Transaction '#]]<>"",IFERROR(INDEX(ProblemData!$E$240:$AM$240,1,Journal[[#This Row],[Transaction '#]]),""),"")} | M65: =IF(Journal[[#This Row],[ref1]]="","",IF(NOT(ISBLANK(Journal[[#This Row],[Transaction '#]])),Journal[[#This Row],[ref1]]&Journal[[#This Row],[Movement '#]],"")) | N65: =OR(Journal[[#This Row],[ref1]]="",ISNUMBER(MATCH(Journal[[#This Row],[ref1]],Operating[Abbr], 0))) -> TRUE | P65: =Journal[[#This Row],[Accnt Type]]&"Used" -> Used
J66: =IF(Journal[[#This Row],[Transaction '#]]="","",IF(Journal[[#This Row],[Transaction '#]]=C65,J65+1,1)) | K66: {=IFERROR(_xlfn.IFS(Journal[[#This Row],[Debit Account]]="Cash",Journal[[#This Row],[Dr Amt]],Journal[[#This Row],[Credit Account]]="Cash",-Journal[[#This Row],[Cr Amt]]),0)} -> 0 | L66: {=IF(Journal[[#This Row],[Transaction '#]]<>"",IFERROR(INDEX(ProblemData!$E$240:$AM$240,1,Journal[[#This Row],[Transaction '#]]),""),"")} | M66: =IF(Journal[[#This Row],[ref1]]="","",IF(NOT(ISBLANK(Journal[[#This Row],[Transaction '#]])),Journal[[#This Row],[ref1]]&Journal[[#This Row],[Movement '#]],"")) | N66: =OR(Journal[[#This Row],[ref1]]="",ISNUMBER(MATCH(Journal[[#This Row],[ref1]],Operating[Abbr], 0))) -> TRUE | P66: =Journal[[#This Row],[Accnt Type]]&"Used" -> Used
... J194: =IF(Journal[[#This Row],[Transaction '#]]="","",IF(Journal[[#This Row],[Transaction '#]]=C193,J193+1,1)) | K194: {=IFERROR(_xlfn.IFS(Journal[[#This Row],[Debit Account]]="Cash",Journal[[#This Row],[Dr Amt]],Journal[[#This Row],[Credit Account]]="Cash",-Journal[[#This Row],[Cr Amt]]),0)} -> 0 | L194: {=IF(Journal[[#This Row],[Transaction '#]]<>"",IFERROR(INDEX(ProblemData!$E$240:$AM$240,1,Journal[[#This Row],[Transaction '#]]),""),"")} | M194: =IF(Journal[[#This Row],[ref1]]="","",IF(NOT(ISBLANK(Journal[[#This Row],[Transaction '#]])),Journal[[#This Row],[ref1]]&Journal[[#This Row],[Movement '#]],"")) | N194: =OR(Journal[[#This Row],[ref1]]="",ISNUMBER(MATCH(Journal[[#This Row],[ref1]],Operating[Abbr], 0))) -> TRUE | P194: =Journal[[#This Row],[Accnt Type]]&"Used" -> Used

Sheet Financial_Statements_Builder
C1: Financial Statement Builder | J1: =IF(D4<>"",D4,"") -> Miloslav's Magazines | P1: =IF(N1<>"",COUNTIFS($AK$183:$AK$200,N1),0) -> 0
J2: =IF(D5<>"",D5,"") -> Dollars in Thousands | P2: =IF(N2<>"",COUNTIFS($AK$183:$AK$200,N2),0) -> 0
C3: Item | D3: Selection | N3: Presentation Mode | O3: TRUE
C4: Entity | D4: =Entity -> Miloslav's Magazines | J4: =IF(D6<>"",D6,"") -> 12/31/20x3 | N4: =IF(D8<>"","Explanations of Changes over the "&D8,"") -> Explanations of Changes over the Year | Y4: =IF(D7<>"",D7,"") -> 12/31/20x4
C5: Units | D5: =Units -> Dollars in Thousands
C6: Beginning Balance Sheet Date | D6: =BegDate -> 12/31/20x3 | J6: =IF(OR(E101,F101),"Balance Sheet","") -> Balance Sheet | L6: 1 | N6: =IF(S111,"Income Statement","") -> Income Statement | Q6: 1 | R6: =IF($S$118,"Statement of Changes in Shareholders' Equity","") -> Statement of Changes in Shareholders' Equity | T6: 1 | U6: =IF($S$126,"Cash Flow Statement","") -> Cash Flow Statement | X6: 1 | Y6: =IF($S$146,"Balance Sheet","") -> Balance Sheet
C7: Ending Balance Sheet Date | D7: =EndDate -> 12/31/20x4 | I7: {=_xlfn.VSTACK(_xlfn.ANCHORARRAY(B609),{"","",""},_xlfn.ANCHORARRAY(B689),{"","",""},_xlfn.ANCHORARRAY(B744))} -> 2 | J7: Assets | M7: {=_xlfn.VSTACK(_xlfn.IFS(L564,_xlfn.ANCHORARRAY(I719),L565,_xlfn.ANCHORARRAY(I764),L566,_xlfn.ANCHORARRAY(I799),L567,_xlfn.ANCHORARRAY(I839),L568,{"","",""}),{"","",""},{"","",""},{"","",""},{"","",""},_xlfn.ANCHORARRAY(M557),{"","",""},_xlfn.ANCHORARRAY(M558),_xlfn.ANCHORARRAY(M559),_xlfn.ANCHORARRAY(M560),_xlfn.ANCHORARRAY(M562))} -> 2 | N7: Revenues | Q7: {=_xlfn.IFS(S566=1,_xlfn.ANCHORARRAY(Q653),S566=2,_xlfn.ANCHORARRAY(Q688),S566=3,_xlfn.ANCHORARRAY(Q728),S566=4,_xlfn.ANCHORARRAY(Q778))} -> 2 | R7: Total Shareholders' Equity @ 12/31/20x3 | S7: 0 | T7: {=_xlfn.VSTACK(_xlfn.ANCHORARRAY(T567),{"","",""},_xlfn.ANCHORARRAY(T569),_xlfn.ANCHORARRAY(T571),_xlfn.ANCHORARRAY(T594),_xlfn.ANCHORARRAY(T596),_xlfn.ANCHORARRAY(T614),_xlfn.ANCHORARRAY(T616),_xlfn.ANCHORARRAY(T627),{"","",""},_xlfn.ANCHORARRAY(T629),{"","",""},{"","",""},{"","",""},{"","",""},_xlfn.ANCHORARRAY(T635),{"","",""},{"","",""},{"","",""},{"","",""},_xlfn.ANCHORARRAY(T652),{"","",""},_xlfn.ANCHORARRAY(T654),{"","",""},_xlfn.ANCHORARRAY(T656),_xlfn.ANCHORARRAY(T657),{"","",""},_xlfn.ANCHORARRAY(T670),_xlfn.ANCHORARRAY(T671),{"","",""},_xlfn.ANCHORARRAY(T685))} -> 2 | U7: Cash @ 12/31/20x3 | V7: 0 | X7: {=_xlfn.VSTACK(_xlfn.ANCHORARRAY(AB609),{"","",""},_xlfn.ANCHORARRAY(AB689),{"","",""},_xlfn.ANCHORARRAY(AB744))} -> 2 | Y7: Assets | AC7: Income Statement | AF7: Statement of Changes in Shareholders' Equity | AJ7: Cash Flow Statement | AN7: Ending Balance Sheet
C8: Period | D8: =Period -> Year | AC8: Line in Statement before the latest entry? | AD8: Line not a total or Net Income | AE8: Highlight line | AF8: Line in Statement before the latest entry? | AG8: Line not a total or Balance | AH8: Highlight line | AJ8: Line in Statement before? | AK8: Line not Total or Increase (Derease) | AL8: Highlight | AN8: Line in Statement before? | AO8: Line not Total or Increase (Derease) | AP8: Highlight
C9: Income Statement | D9: ="for the "&D8&" ended "&D7 -> for the Year ended 12/31/20x4 | I9: 4 | J9: Current Assets: | M9: 6 | N9: Sales | O9: 25 | Q9: 3 | R9: Common Stock | X9: 4 | Y9: Current Assets: | AC9: =ISNUMBER(MATCH(N9&O9,FSData!$V$7:$V$95,0)) -> TRUE | AD9: =OR(ISNUMBER(SEARCH("Total",N9,1)),ISNUMBER(SEARCH("Net Income",N9,1))) -> FALSE | AE9: =AND(NOT(AC9),NOT(AD9)) -> FALSE | AF9: =ISNUMBER(MATCH(R9&S9,FSData!$X$7:$X$95,0)) -> TRUE | AG9: =OR(ISNUMBER(SEARCH("Total",R9,1)),ISNUMBER(SEARCH("Balance",R9,1))) -> FALSE | AH9: =AND(NOT(AF9),NOT(AG9)) -> FALSE | AJ9: =ISNUMBER(MATCH(U9&V9,FSData!$Z$7:$Z$95,0)) -> TRUE | AK9: =OR(ISNUMBER(SEARCH("Total",U9,1)),ISNUMBER(SEARCH("Increase (decrease)",U9,1)),ISNUMBER(SEARCH("Operating Activities",U9,1)),ISNUMBER(SEARCH("Investing Activities",U9,1)),ISNUMBER(SEARCH("Financing Activities",U9,1)),ISNUMBER(SEARCH("Cash @",U9,1)),ISNUMBER(SEARCH("Net Income",U9,1)),ISNUMBER(SEARCH("Cash Flow from Operations",U9,1))) -> FALSE | AL9: =AND(NOT(AJ9),NOT(AK9)) -> FALSE | AN9: =ISNUMBER(MATCH(Y9&Z9,FSData!$AB$7:$AB$95,0)) -> TRUE | AO9: =OR(ISNUMBER(SEARCH("Total",Y9,1))) -> FALSE | AP9: =AND(NOT(AN9),NOT(AO9)) -> FALSE
C10: Statement of Changes in Shareholders' Equity | D10: ="for the "&D8&" ended "&D7 -> for the Year ended 12/31/20x4 | I10: 6 | J10: Cash | K10: 0 | M10: 5 | N10: Total Revenues | O10: 25 | Q10: 5 | R10: Balance @ 12/31/20x3 | S10: 0 | X10: 6 | Y10: Cash | Z10: 17.58 | AC10: =ISNUMBER(MATCH(N10&O10,FSData!$V$7:$V$95,0)) -> TRUE | AD10: =OR(ISNUMBER(SEARCH("Total",N10,1)),ISNUMBER(SEARCH("Net Income",N10,1))) -> TRUE | AE10: =AND(NOT(AC10),NOT(AD10)) -> FALSE | AF10: =ISNUMBER(MATCH(R10&S10,FSData!$X$7:$X$95,0)) -> TRUE | AG10: =OR(ISNUMBER(SEARCH("Total",R10,1)),ISNUMBER(SEARCH("Balance",R10,1))) -> TRUE | AH10: =AND(NOT(AF10),NOT(AG10)) -> FALSE | AJ10: =ISNUMBER(MATCH(U10&V10,FSData!$Z$7:$Z$95,0)) -> TRUE | AK10: =OR(ISNUMBER(SEARCH("Total",U10,1)),ISNUMBER(SEARCH("Increase (decrease)",U10,1)),ISNUMBER(SEARCH("Operating Activities",U10,1)),ISNUMBER(SEARCH("Investing Activities",U10,1)),ISNUMBER(SEARCH("Financing Activities",U10,1)),ISNUMBER(SEARCH("Cash @",U10,1)),ISNUMBER(SEARCH("Net Income",U10,1)),ISNUMBER(SEARCH("Cash Flow from Operations",U10,1))) -> FALSE | AL10: =AND(NOT(AJ10),NOT(AK10)) -> FALSE | AN10: =ISNUMBER(MATCH(Y10&Z10,FSData!$AB$7:$AB$95,0)) -> TRUE | AO10: =OR(ISNUMBER(SEARCH("Total",Y10,1))) -> FALSE | AP10: =AND(NOT(AN10),NOT(AO10)) -> FALSE
C11: Cash Flow Statement | D11: ="for the "&D8&" ended "&D7 -> for the Year ended 12/31/20x4 | I11: 7 | J11: Accounts Receivable | K11: 0 | Q11: 7 | R11: Issued common stock | S11: 3 | X11: 7 | Y11: Accounts Receivable | Z11: 4.5 | AC11: =ISNUMBER(MATCH(N11&O11,FSData!$V$7:$V$95,0)) -> TRUE | AD11: =OR(ISNUMBER(SEARCH("Total",N11,1)),ISNUMBER(SEARCH("Net Income",N11,1))) -> FALSE | AE11: =AND(NOT(AC11),NOT(AD11)) -> FALSE | AF11: =ISNUMBER(MATCH(R11&S11,FSData!$X$7:$X$95,0)) -> TRUE | AG11: =OR(ISNUMBER(SEARCH("Total",R11,1)),ISNUMBER(SEARCH("Balance",R11,1))) -> FALSE | AH11: =AND(NOT(AF11),NOT(AG11)) -> FALSE | AJ11: =ISNUMBER(MATCH(U11&V11,FSData!$Z$7:$Z$95,0)) -> TRUE | AK11: =OR(ISNUMBER(SEARCH("Total",U11,1)),ISNUMBER(SEARCH("Increase (decrease)",U11,1)),ISNUMBER(SEARCH("Operating Activities",U11,1)),ISNUMBER(SEARCH("Investing Activities",U11,1)),ISNUMBER(SEARCH("Financing Activities",U11,1)),ISNUMBER(SEARCH("Cash @",U11,1)),ISNUMBER(SEARCH("Net Income",U11,1)),ISNUMBER(SEARCH("Cash Flow from Operations",U11,1))) -> FALSE | AL11: =AND(NOT(AJ11),NOT(AK11)) -> FALSE | AN11: =ISNUMBER(MATCH(Y11&Z11,FSData!$AB$7:$AB$95,0)) -> TRUE | AO11: =OR(ISNUMBER(SEARCH("Total",Y11,1))) -> FALSE | AP11: =AND(NOT(AN11),NOT(AO11)) -> FALSE
I12: 7 | J12: Inventories | K12: 0 | M12: 2 | N12: Expenses | Q12: 5 | R12: Balance @ 12/31/20x4 | S12: 3 | X12: 7 | Y12: Inventories | Z12: 2 | AC12: =ISNUMBER(MATCH(N12&O12,FSData!$V$7:$V$95,0)) -> TRUE | AD12: =OR(ISNUMBER(SEARCH("Total",N12,1)),ISNUMBER(SEARCH("Net Income",N12,1))) -> FALSE | AE12: =AND(NOT(AC12),NOT(AD12)) -> FALSE | AF12: =ISNUMBER(MATCH(R12&S12,FSData!$X$7:$X$95,0)) -> TRUE | AG12: =OR(ISNUMBER(SEARCH("Total",R12,1)),ISNUMBER(SEARCH("Balance",R12,1))) -> TRUE | AH12: =AND(NOT(AF12),NOT(AG12)) -> FALSE | AJ12: =ISNUMBER(MATCH(U12&V12,FSData!$Z$7:$Z$95,0)) -> TRUE | AK12: =OR(ISNUMBER(SEARCH("Total",U12,1)),ISNUMBER(SEARCH("Increase (decrease)",U12,1)),ISNUMBER(SEARCH("Operating Activities",U12,1)),ISNUMBER(SEARCH("Investing Activities",U12,1)),ISNUMBER(SEARCH("Financing Activities",U12,1)),ISNUMBER(SEARCH("Cash @",U12,1)),ISNUMBER(SEARCH("Net Income",U12,1)),ISNUMBER(SEARCH("Cash Flow from Operations",U12,1))) -> FALSE | AL12: =AND(NOT(AJ12),NOT(AK12)) -> FALSE | AN12: =ISNUMBER(MATCH(Y12&Z12,FSData!$AB$7:$AB$95,0)) -> TRUE | AO12: =OR(ISNUMBER(SEARCH("Total",Y12,1))) -> FALSE | AP12: =AND(NOT(AN12),NOT(AO12)) -> FALSE
C13: Financial Statement | D13: Automate? | I13: 5 | J13: Total Current Assets | K13: 0 | Q13: 3 | R13: Retained Earnings | X13: 5 | Y13: Total Current Assets | Z13: 24.08 | AC13: =ISNUMBER(MATCH(N13&O13,FSData!$V$7:$V$95,0)) -> TRUE | AD13: =OR(ISNUMBER(SEARCH("Total",N13,1)),ISNUMBER(SEARCH("Net Income",N13,1))) -> FALSE | AE13: =AND(NOT(AC13),NOT(AD13)) -> FALSE | AF13: =ISNUMBER(MATCH(R13&S13,FSData!$X$7:$X$95,0)) -> TRUE | AG13: =OR(ISNUMBER(SEARCH("Total",R13,1)),ISNUMBER(SEARCH("Balance",R13,1))) -> FALSE | AH13: =AND(NOT(AF13),NOT(AG13)) -> FALSE | AJ13: =ISNUMBER(MATCH(U13&V13,FSData!$Z$7:$Z$95,0)) -> TRUE | AK13: =OR(ISNUMBER(SEARCH("Total",U13,1)),ISNUMBER(SEARCH("Increase (decrease)",U13,1)),ISNUMBER(SEARCH("Operating Activities",U13,1)),ISNUMBER(SEARCH("Investing Activities",U13,1)),ISNUMBER(SEARCH("Financing Activities",U13,1)),ISNUMBER(SEARCH("Cash @",U13,1)),ISNUMBER(SEARCH("Net Income",U13,1)),ISNUMBER(SEARCH("Cash Flow from Operations",U13,1))) -> FALSE | AL13: =AND(NOT(AJ13),NOT(AK13)) -> FALSE | AN13: =ISNUMBER(MATCH(Y13&Z13,FSData!$AB$7:$AB$95,0)) -> TRUE | AO13: =OR(ISNUMBER(SEARCH("Total",Y13,1))) -> TRUE | AP13: =AND(NOT(AN13),NOT(AO13)) -> FALSE
C14: {=IFERROR(_xlfn._xlws.FILTER(ProblemData!D10:D17,ProblemData!E10:E17),"")} -> Beginning Balance Sheet | D14: TRUE | M14: 6 | N14: Cost of Goods Sold | O14: 18 | Q14: 5 | R14: Balance @ 12/31/20x3 | S14: 0 | AC14: =ISNUMBER(MATCH(N14&O14,FSData!$V$7:$V$95,0)) -> TRUE | AD14: =OR(ISNUMBER(SEARCH("Total",N14,1)),ISNUMBER(SEARCH("Net Income",N14,1))) -> FALSE | AE14: =AND(NOT(AC14),NOT(AD14)) -> FALSE | AF14: =ISNUMBER(MATCH(R14&S14,FSData!$X$7:$X$95,0)) -> TRUE | AG14: =OR(ISNUMBER(SEARCH("Total",R14,1)),ISNUMBER(SEARCH("Balance",R14,1))) -> TRUE | AH14: =AND(NOT(AF14),NOT(AG14)) -> FALSE | AJ14: =ISNUMBER(MATCH(U14&V14,FSData!$Z$7:$Z$95,0)) -> TRUE | AK14: =OR(ISNUMBER(SEARCH("Total",U14,1)),ISNUMBER(SEARCH("Increase (decrease)",U14,1)),ISNUMBER(SEARCH("Operating Activities",U14,1)),ISNUMBER(SEARCH("Investing Activities",U14,1)),ISNUMBER(SEARCH("Financing Activities",U14,1)),ISNUMBER(SEARCH("Cash @",U14,1)),ISNUMBER(SEARCH("Net Income",U14,1)),ISNUMBER(SEARCH("Cash Flow from Operations",U14,1))) -> FALSE | AL14: =AND(NOT(AJ14),NOT(AK14)) -> FALSE | AN14: =ISNUMBER(MATCH(Y14&Z14,FSData!$AB$7:$AB$95,0)) -> TRUE | AO14: =OR(ISNUMBER(SEARCH("Total",Y14,1))) -> FALSE | AP14: =AND(NOT(AN14),NOT(AO14)) -> FALSE
C15: Income Statement | D15: TRUE | I15: 4 | J15: Noncurrent Assets: | M15: 7 | N15: Interest Expense | O15: 1.87 | Q15: 7 | R15: Declared Dividends | S15: -0.05 | X15: 4 | Y15: Noncurrent Assets: | AC15: =ISNUMBER(MATCH(N15&O15,FSData!$V$7:$V$95,0)) -> TRUE | AD15: =OR(ISNUMBER(SEARCH("Total",N15,1)),ISNUMBER(SEARCH("Net Income",N15,1))) -> FALSE | AE15: =AND(NOT(AC15),NOT(AD15)) -> FALSE | AF15: =ISNUMBER(MATCH(R15&S15,FSData!$X$7:$X$95,0)) -> TRUE | AG15: =OR(ISNUMBER(SEARCH("Total",R15,1)),ISNUMBER(SEARCH("Balance",R15,1))) -> FALSE | AH15: =AND(NOT(AF15),NOT(AG15)) -> FALSE | AJ15: =ISNUMBER(MATCH(U15&V15,FSData!$Z$7:$Z$95,0)) -> TRUE | AK15: =OR(ISNUMBER(SEARCH("Total",U15,1)),ISNUMBER(SEARCH("Increase (decrease)",U15,1)),ISNUMBER(SEARCH("Operating Activities",U15,1)),ISNUMBER(SEARCH("Investing Activities",U15,1)),ISNUMBER(SEARCH("Financing Activities",U15,1)),ISNUMBER(SEARCH("Cash @",U15,1)),ISNUMBER(SEARCH("Net Income",U15,1)),ISNUMBER(SEARCH("Cash Flow from Operations",U15,1))) -> FALSE | AL15: =AND(NOT(AJ15),NOT(AK15)) -> FALSE | AN15: =ISNUMBER(MATCH(Y15&Z15,FSData!$AB$7:$AB$95,0)) -> TRUE | AO15: =OR(ISNUMBER(SEARCH("Total",Y15,1))) -> FALSE | AP15: =AND(NOT(AN15),NOT(AO15)) -> FALSE
C16: Statement of Changes in Shareholders' Equity | D16: TRUE | I16: 6 | J16: Property, Plant & Equipment | K16: 0 | M16: 7 | N16: Depreciation Expense | O16: 0.2 | Q16: 7 | R16: Net Income (Loss) | S16: 1.93 | X16: 6 | Y16: Property, Plant & Equipment | Z16: 1 | AC16: =ISNUMBER(MATCH(N16&O16,FSData!$V$7:$V$95,0)) -> TRUE | AD16: =OR(ISNUMBER(SEARCH("Total",N16,1)),ISNUMBER(SEARCH("Net Income",N16,1))) -> FALSE | AE16: =AND(NOT(AC16),NOT(AD16)) -> FALSE | AF16: =ISNUMBER(MATCH(R16&S16,FSData!$X$7:$X$95,0)) -> TRUE | AG16: =OR(ISNUMBER(SEARCH("Total",R16,1)),ISNUMBER(SEARCH("Balance",R16,1))) -> FALSE | AH16: =AND(NOT(AF16),NOT(AG16)) -> FALSE | AJ16: =ISNUMBER(MATCH(U16&V16,FSData!$Z$7:$Z$95,0)) -> TRUE | AK16: =OR(ISNUMBER(SEARCH("Total",U16,1)),ISNUMBER(SEARCH("Increase (decrease)",U16,1)),ISNUMBER(SEARCH("Operating Activities",U16,1)),ISNUMBER(SEARCH("Investing Activities",U16,1)),ISNUMBER(SEARCH("Financing Activities",U16,1)),ISNUMBER(SEARCH("Cash @",U16,1)),ISNUMBER(SEARCH("Net Income",U16,1)),ISNUMBER(SEARCH("Cash Flow from Operations",U16,1))) -> FALSE | AL16: =AND(NOT(AJ16),NOT(AK16)) -> FALSE | AN16: =ISNUMBER(MATCH(Y16&Z16,FSData!$AB$7:$AB$95,0)) -> TRUE | AO16: =OR(ISNUMBER(SEARCH("Total",Y16,1))) -> FALSE | AP16: =AND(NOT(AN16),NOT(AO16)) -> FALSE
C17: Ending Balance Sheet | D17: TRUE | I17: 7 | J17: Accumulated Depreciation | K17: 0 | M17: 7 | N17: Salaries & Wages Expense | O17: 3 | Q17: 5 | R17: Balance @ 12/31/20x4 | S17: 1.88 | T17: 2 | U17: Cash @ 12/31/20x4 | V17: 17.58 | X17: 7 | Y17: Accumulated Depreciation | Z17: -0.2 | AC17: =ISNUMBER(MATCH(N17&O17,FSData!$V$7:$V$95,0)) -> TRUE | AD17: =OR(ISNUMBER(SEARCH("Total",N17,1)),ISNUMBER(SEARCH("Net Income",N17,1))) -> FALSE | AE17: =AND(NOT(AC17),NOT(AD17)) -> FALSE | AF17: =ISNUMBER(MATCH(R17&S17,FSData!$X$7:$X$95,0)) -> FALSE | AG17: =OR(ISNUMBER(SEARCH("Total",R17,1)),ISNUMBER(SEARCH("Balance",R17,1))) -> TRUE | AH17: =AND(NOT(AF17),NOT(AG17)) -> FALSE | AJ17: =ISNUMBER(MATCH(U17&V17,FSData!$Z$7:$Z$95,0)) -> TRUE | AK17: =OR(ISNUMBER(SEARCH("Total",U17,1)),ISNUMBER(SEARCH("Increase (decrease)",U17,1)),ISNUMBER(SEARCH("Operating Activities",U17,1)),ISNUMBER(SEARCH("Investing Activities",U17,1)),ISNUMBER(SEARCH("Financing Activities",U17,1)),ISNUMBER(SEARCH("Cash @",U17,1)),ISNUMBER(SEARCH("Net Income",U17,1)),ISNUMBER(SEARCH("Cash Flow from Operations",U17,1))) -> TRUE | AL17: =AND(NOT(AJ17),NOT(AK17)) -> FALSE | AN17: =ISNUMBER(MATCH(Y17&Z17,FSData!$AB$7:$AB$95,0)) -> TRUE | AO17: =OR(ISNUMBER(SEARCH("Total",Y17,1))) -> FALSE | AP17: =AND(NOT(AN17),NOT(AO17)) -> FALSE
D18: FALSE | I18: 5 | J18: Total Noncurrent Assets | K18: 0 | M18: 5 | N18: Total Expenses | O18: 23.07 | Q18: 2 | R18: Total Shareholders' Equity @ 12/31/20x4 | S18: 4.88 | X18: 5 | Y18: Total Noncurrent Assets | Z18: 0.8 | AC18: =ISNUMBER(MATCH(N18&O18,FSData!$V$7:$V$95,0)) -> TRUE | AD18: =OR(ISNUMBER(SEARCH("Total",N18,1)),ISNUMBER(SEARCH("Net Income",N18,1))) -> TRUE | AE18: =AND(NOT(AC18),NOT(AD18)) -> FALSE | AF18: =ISNUMBER(MATCH(R18&S18,FSData!$X$7:$X$95,0)) -> FALSE | AG18: =OR(ISNUMBER(SEARCH("Total",R18,1)),ISNUMBER(SEARCH("Balance",R18,1))) -> TRUE | AH18: =AND(NOT(AF18),NOT(AG18)) -> FALSE | AJ18: =ISNUMBER(MATCH(U18&V18,FSData!$Z$7:$Z$95,0)) -> TRUE | AK18: =OR(ISNUMBER(SEARCH("Total",U18,1)),ISNUMBER(SEARCH("Increase (decrease)",U18,1)),ISNUMBER(SEARCH("Operating Activities",U18,1)),ISNUMBER(SEARCH("Investing Activities",U18,1)),ISNUMBER(SEARCH("Financing Activities",U18,1)),ISNUMBER(SEARCH("Cash @",U18,1)),ISNUMBER(SEARCH("Net Income",U18,1)),ISNUMBER(SEARCH("Cash Flow from Operations",U18,1))) -> FALSE | AL18: =AND(NOT(AJ18),NOT(AK18)) -> FALSE | AN18: =ISNUMBER(MATCH(Y18&Z18,FSData!$AB$7:$AB$95,0)) -> TRUE | AO18: =OR(ISNUMBER(SEARCH("Total",Y18,1))) -> TRUE | AP18: =AND(NOT(AN18),NOT(AO18)) -> FALSE
D19: FALSE | AC19: =ISNUMBER(MATCH(N19&O19,FSData!$V$7:$V$95,0)) -> TRUE | AD19: =OR(ISNUMBER(SEARCH("Total",N19,1)),ISNUMBER(SEARCH("Net Income",N19,1))) -> FALSE | AE19: =AND(NOT(AC19),NOT(AD19)) -> FALSE | AF19: =ISNUMBER(MATCH(R19&S19,FSData!$X$7:$X$95,0)) -> TRUE | AG19: =OR(ISNUMBER(SEARCH("Total",R19,1)),ISNUMBER(SEARCH("Balance",R19,1))) -> FALSE | AH19: =AND(NOT(AF19),NOT(AG19)) -> FALSE | AJ19: =ISNUMBER(MATCH(U19&V19,FSData!$Z$7:$Z$95,0)) -> TRUE | AK19: =OR(ISNUMBER(SEARCH("Total",U19,1)),ISNUMBER(SEARCH("Increase (decrease)",U19,1)),ISNUMBER(SEARCH("Operating Activities",U19,1)),ISNUMBER(SEARCH("Investing Activities",U19,1)),ISNUMBER(SEARCH("Financing Activities",U19,1)),ISNUMBER(SEARCH("Cash @",U19,1)),ISNUMBER(SEARCH("Net Income",U19,1)),ISNUMBER(SEARCH("Cash Flow from Operations",U19,1))) -> FALSE | AL19: =AND(NOT(AJ19),NOT(AK19)) -> FALSE | AN19: =ISNUMBER(MATCH(Y19&Z19,FSData!$AB$7:$AB$95,0)) -> TRUE | AO19: =OR(ISNUMBER(SEARCH("Total",Y19,1))) -> FALSE | AP19: =AND(NOT(AN19),NOT(AO19)) -> FALSE
D20: FALSE | I20: 3 | J20: Total Assets | K20: 0 | M20: 3 | N20: Net Income | O20: 1.93 | X20: 3 | Y20: Total Assets | Z20: 24.88 | AC20: =ISNUMBER(MATCH(N20&O20,FSData!$V$7:$V$95,0)) -> TRUE | AD20: =OR(ISNUMBER(SEARCH("Total",N20,1)),ISNUMBER(SEARCH("Net Income",N20,1))) -> TRUE | AE20: =AND(NOT(AC20),NOT(AD20)) -> FALSE | AF20: =ISNUMBER(MATCH(R20&S20,FSData!$X$7:$X$95,0)) -> TRUE | AG20: =OR(ISNUMBER(SEARCH("Total",R20,1)),ISNUMBER(SEARCH("Balance",R20,1))) -> FALSE | AH20: =AND(NOT(AF20),NOT(AG20)) -> FALSE | AJ20: =ISNUMBER(MATCH(U20&V20,FSData!$Z$7:$Z$95,0)) -> TRUE | AK20: =OR(ISNUMBER(SEARCH("Total",U20,1)),ISNUMBER(SEARCH("Increase (decrease)",U20,1)),ISNUMBER(SEARCH("Operating Activities",U20,1)),ISNUMBER(SEARCH("Investing Activities",U20,1)),ISNUMBER(SEARCH("Financing Activities",U20,1)),ISNUMBER(SEARCH("Cash @",U20,1)),ISNUMBER(SEARCH("Net Income",U20,1)),ISNUMBER(SEARCH("Cash Flow from Operations",U20,1))) -> FALSE | AL20: =AND(NOT(AJ20),NOT(AK20)) -> FALSE | AN20: =ISNUMBER(MATCH(Y20&Z20,FSData!$AB$7:$AB$95,0)) -> TRUE | AO20: =OR(ISNUMBER(SEARCH("Total",Y20,1))) -> TRUE | AP20: =AND(NOT(AN20),NOT(AO20)) -> FALSE
D21: FALSE | AC21: =ISNUMBER(MATCH(N21&O21,FSData!$V$7:$V$95,0)) -> TRUE | AD21: =OR(ISNUMBER(SEARCH("Total",N21,1)),ISNUMBER(SEARCH("Net Income",N21,1))) -> FALSE | AE21: =AND(NOT(AC21),NOT(AD21)) -> FALSE | AF21: =ISNUMBER(MATCH(R21&S21,FSData!$X$7:$X$95,0)) -> TRUE | AG21: =OR(ISNUMBER(SEARCH("Total",R21,1)),ISNUMBER(SEARCH("Balance",R21,1))) -> FALSE | AH21: =AND(NOT(AF21),NOT(AG21)) -> FALSE | AJ21: =ISNUMBER(MATCH(U21&V21,FSData!$Z$7:$Z$95,0)) -> TRUE | AK21: =OR(ISNUMBER(SEARCH("Total",U21,1)),ISNUMBER(SEARCH("Increase (decrease)",U21,1)),ISNUMBER(SEARCH("Operating Activities",U21,1)),ISNUMBER(SEARCH("Investing Activities",U21,1)),ISNUMBER(SEARCH("Financing Activities",U21,1)),ISNUMBER(SEARCH("Cash @",U21,1)),ISNUMBER(SEARCH("Net Income",U21,1)),ISNUMBER(SEARCH("Cash Flow from Operations",U21,1))) -> FALSE | AL21: =AND(NOT(AJ21),NOT(AK21)) -> FALSE | AN21: =ISNUMBER(MATCH(Y21&Z21,FSData!$AB$7:$AB$95,0)) -> TRUE | AO21: =OR(ISNUMBER(SEARCH("Total",Y21,1))) -> FALSE | AP21: =AND(NOT(AN21),NOT(AO21)) -> FALSE
I22: 2 | J22: Liabilities | X22: 2 | Y22: Liabilities | AC22: =ISNUMBER(MATCH(N22&O22,FSData!$V$7:$V$95,0)) -> TRUE | AD22: =OR(ISNUMBER(SEARCH("Total",N22,1)),ISNUMBER(SEARCH("Net Income",N22,1))) -> FALSE | AE22: =AND(NOT(AC22),NOT(AD22)) -> FALSE | AF22: =ISNUMBER(MATCH(R22&S22,FSData!$X$7:$X$95,0)) -> TRUE | AG22: =OR(ISNUMBER(SEARCH("Total",R22,1)),ISNUMBER(SEARCH("Balance",R22,1))) -> FALSE | AH22: =AND(NOT(AF22),NOT(AG22)) -> FALSE | AJ22: =ISNUMBER(MATCH(U22&V22,FSData!$Z$7:$Z$95,0)) -> TRUE | AK22: =OR(ISNUMBER(SEARCH("Total",U22,1)),ISNUMBER(SEARCH("Increase (decrease)",U22,1)),ISNUMBER(SEARCH("Operating Activities",U22,1)),ISNUMBER(SEARCH("Investing Activities",U22,1)),ISNUMBER(SEARCH("Financing Activities",U22,1)),ISNUMBER(SEARCH("Cash @",U22,1)),ISNUMBER(SEARCH("Net Income",U22,1)),ISNUMBER(SEARCH("Cash Flow from Operations",U22,1))) -> FALSE | AL22: =AND(NOT(AJ22),NOT(AK22)) -> FALSE | AN22: =ISNUMBER(MATCH(Y22&Z22,FSData!$AB$7:$AB$95,0)) -> TRUE | AO22: =OR(ISNUMBER(SEARCH("Total",Y22,1))) -> FALSE | AP22: =AND(NOT(AN22),NOT(AO22)) -> FALSE
AC23: =ISNUMBER(MATCH(N23&O23,FSData!$V$7:$V$95,0)) -> TRUE | AD23: =OR(ISNUMBER(SEARCH("Total",N23,1)),ISNUMBER(SEARCH("Net Income",N23,1))) -> FALSE | AE23: =AND(NOT(AC23),NOT(AD23)) -> FALSE | AF23: =ISNUMBER(MATCH(R23&S23,FSData!$X$7:$X$95,0)) -> TRUE | AG23: =OR(ISNUMBER(SEARCH("Total",R23,1)),ISNUMBER(SEARCH("Balance",R23,1))) -> FALSE | AH23: =AND(NOT(AF23),NOT(AG23)) -> FALSE | AJ23: =ISNUMBER(MATCH(U23&V23,FSData!$Z$7:$Z$95,0)) -> TRUE | AK23: =OR(ISNUMBER(SEARCH("Total",U23,1)),ISNUMBER(SEARCH("Increase (decrease)",U23,1)),ISNUMBER(SEARCH("Operating Activities",U23,1)),ISNUMBER(SEARCH("Investing Activities",U23,1)),ISNUMBER(SEARCH("Financing Activities",U23,1)),ISNUMBER(SEARCH("Cash @",U23,1)),ISNUMBER(SEARCH("Net Income",U23,1)),ISNUMBER(SEARCH("Cash Flow from Operations",U23,1))) -> FALSE | AL23: =AND(NOT(AJ23),NOT(AK23)) -> FALSE | AN23: =ISNUMBER(MATCH(Y23&Z23,FSData!$AB$7:$AB$95,0)) -> TRUE | AO23: =OR(ISNUMBER(SEARCH("Total",Y23,1))) -> FALSE | AP23: =AND(NOT(AN23),NOT(AO23)) -> FALSE | AR23: FSBuilder Menu construction
C24: Statement | D24: Category | E24: Account or Explanation | F24: Amount | I24: 4 | J24: Current Liabilities: | X24: 4 | Y24: Current Liabilities: | AC24: =ISNUMBER(MATCH(N24&O24,FSData!$V$7:$V$95,0)) -> TRUE | AD24: =OR(ISNUMBER(SEARCH("Total",N24,1)),ISNUMBER(SEARCH("Net Income",N24,1))) -> FALSE | AE24: =AND(NOT(AC24),NOT(AD24)) -> FALSE | AF24: =ISNUMBER(MATCH(R24&S24,FSData!$X$7:$X$95,0)) -> TRUE | AG24: =OR(ISNUMBER(SEARCH("Total",R24,1)),ISNUMBER(SEARCH("Balance",R24,1))) -> FALSE | AH24: =AND(NOT(AF24),NOT(AG24)) -> FALSE | AJ24: =ISNUMBER(MATCH(U24&V24,FSData!$Z$7:$Z$95,0)) -> TRUE | AK24: =OR(ISNUMBER(SEARCH("Total",U24,1)),ISNUMBER(SEARCH("Increase (decrease)",U24,1)),ISNUMBER(SEARCH("Operating Activities",U24,1)),ISNUMBER(SEARCH("Investing Activities",U24,1)),ISNUMBER(SEARCH("Financing Activities",U24,1)),ISNUMBER(SEARCH("Cash @",U24,1)),ISNUMBER(SEARCH("Net Income",U24,1)),ISNUMBER(SEARCH("Cash Flow from Operations",U24,1))) -> FALSE | AL24: =AND(NOT(AJ24),NOT(AK24)) -> FALSE | AN24: =ISNUMBER(MATCH(Y24&Z24,FSData!$AB$7:$AB$95,0)) -> TRUE | AO24: =OR(ISNUMBER(SEARCH("Total",Y24,1))) -> FALSE | AP24: =AND(NOT(AN24),NOT(AO24)) -> FALSE | AR24: Accnt | AS24: Category
C25: Beginning Balance Sheet | D25: Noncurrent Liabilities | E25: Notes Payable | F25: 0 | H25: =_xlfn.TEXTJOIN(6,1,FSBuilder[[#This Row],[Statement]:[Account or Explanation]]) -> Beginning Balance Sheet6 Noncurrent Liabilities6Notes Payable | I25: 6 | J25: Interest Payable | K25: 0 | X25: 6 | Y25: Interest Payable | Z25: 0 | AC25: =ISNUMBER(MATCH(N25&O25,FSData!$V$7:$V$95,0)) -> TRUE | AD25: =OR(ISNUMBER(SEARCH("Total",N25,1)),ISNUMBER(SEARCH("Net Income",N25,1))) -> FALSE | AE25: =AND(NOT(AC25),NOT(AD25)) -> FALSE | AF25: =ISNUMBER(MATCH(R25&S25,FSData!$X$7:$X$95,0)) -> TRUE | AG25: =OR(ISNUMBER(SEARCH("Total",R25,1)),ISNUMBER(SEARCH("Balance",R25,1))) -> FALSE | AH25: =AND(NOT(AF25),NOT(AG25)) -> FALSE | AJ25: =ISNUMBER(MATCH(U25&V25,FSData!$Z$7:$Z$95,0)) -> TRUE | AK25: =OR(ISNUMBER(SEARCH("Total",U25,1)),ISNUMBER(SEARCH("Increase (decrease)",U25,1)),ISNUMBER(SEARCH("Operating Activities",U25,1)),ISNUMBER(SEARCH("Investing Activities",U25,1)),ISNUMBER(SEARCH("Financing Activities",U25,1)),ISNUMBER(SEARCH("Cash @",U25,1)),ISNUMBER(SEARCH("Net Income",U25,1)),ISNUMBER(SEARCH("Cash Flow from Operations",U25,1))) -> FALSE | AL25: =AND(NOT(AJ25),NOT(AK25)) -> FALSE | AN25: =ISNUMBER(MATCH(Y25&Z25,FSData!$AB$7:$AB$95,0)) -> TRUE | AO25: =OR(ISNUMBER(SEARCH("Total",Y25,1))) -> FALSE | AP25: =AND(NOT(AN25),NOT(AO25)) -> FALSE | AR25: {=_xlfn.IFS(ISNUMBER(SEARCH("Balance",C25,1)),"MasterData!O56#",ISNUMBER(SEARCH("Income St",C25,1)),"MasterData!O116#",ISNUMBER(SEARCH("Shareholders",C25,1)),"D115#",ISNUMBER(SEARCH("Cash Flow",C25,1)),"E115#",ISNUMBER(SEARCH("Noncash",C25,1)),"C139#",ISNUMBER(SEARCH("Comprehensive",C25,1)),"E145",ISNUMBER(SEARCH("Reconciliation",C25,1)),"D137#")} -> MasterData!O56# | AS25: {=_xlfn.IFS(ISNUMBER(SEARCH("Balance",C25,1)),"AX25:AX29",ISNUMBER(SEARCH("Income St",C25,1)),"AY25:AY28",ISNUMBER(SEARCH("Shareholders",C25,1)),"EquityUsed",ISNUMBER(SEARCH("Cash Flow",C25,1)),"BA25:BA27",ISNUMBER(SEARCH("Noncash",C25,1)),"AZ25",ISNUMBER(SEARCH("Comprehensive",C25,1)),"AZ25",ISNUMBER(SEARCH("Reconciliation",C25,1)),"BB25:BB26")} -> AX25:AX29 | AU25: {=INDIRECT(AR25)} -> Accounts Receivable | AX25: Current Assets | AY25: Revenues | AZ25: None | BA25: Operating Activities | BB25: Adjustments
C26: Beginning Balance Sheet | D26: Current Assets | E26: Cash | F26: 0 | H26: =_xlfn.TEXTJOIN(6,1,FSBuilder[[#This Row],[Statement]:[Account or Explanation]]) -> Beginning Balance Sheet6 Current Assets6Cash | I26: 7 | J26: Dividends Payable | K26: 0 | X26: 7 | Y26: Dividends Payable | Z26: 0 | AC26: =ISNUMBER(MATCH(N26&O26,FSData!$V$7:$V$95,0)) -> TRUE | AD26: =OR(ISNUMBER(SEARCH("Total",N26,1)),ISNUMBER(SEARCH("Net Income",N26,1))) -> FALSE | AE26: =AND(NOT(AC26),NOT(AD26)) -> FALSE | AF26: =ISNUMBER(MATCH(R26&S26,FSData!$X$7:$X$95,0)) -> TRUE | AG26: =OR(ISNUMBER(SEARCH("Total",R26,1)),ISNUMBER(SEARCH("Balance",R26,1))) -> FALSE | AH26: =AND(NOT(AF26),NOT(AG26)) -> FALSE | AJ26: =ISNUMBER(MATCH(U26&V26,FSData!$Z$7:$Z$95,0)) -> TRUE | AK26: =OR(ISNUMBER(SEARCH("Total",U26,1)),ISNUMBER(SEARCH("Increase (decrease)",U26,1)),ISNUMBER(SEARCH("Operating Activities",U26,1)),ISNUMBER(SEARCH("Investing Activities",U26,1)),ISNUMBER(SEARCH("Financing Activities",U26,1)),ISNUMBER(SEARCH("Cash @",U26,1)),ISNUMBER(SEARCH("Net Income",U26,1)),ISNUMBER(SEARCH("Cash Flow from Operations",U26,1))) -> FALSE | AL26: =AND(NOT(AJ26),NOT(AK26)) -> FALSE | AN26: =ISNUMBER(MATCH(Y26&Z26,FSData!$AB$7:$AB$95,0)) -> TRUE | AO26: =OR(ISNUMBER(SEARCH("Total",Y26,1))) -> FALSE | AP26: =AND(NOT(AN26),NOT(AO26)) -> FALSE | AR26: {=_xlfn.IFS(ISNUMBER(SEARCH("Balance",C26,1)),"MasterData!O56#",ISNUMBER(SEARCH("Income St",C26,1)),"MasterData!O116#",ISNUMBER(SEARCH("Shareholders",C26,1)),"D115#",ISNUMBER(SEARCH("Cash Flow",C26,1)),"E115#",ISNUMBER(SEARCH("Noncash",C26,1)),"C139#",ISNUMBER(SEARCH("Comprehensive",C26,1)),"E145",ISNUMBER(SEARCH("Reconciliation",C26,1)),"D137#")} -> MasterData!O56# | AS26: {=_xlfn.IFS(ISNUMBER(SEARCH("Balance",C26,1)),"AX25:AX29",ISNUMBER(SEARCH("Income St",C26,1)),"AY25:AY28",ISNUMBER(SEARCH("Shareholders",C26,1)),"EquityUsed",ISNUMBER(SEARCH("Cash Flow",C26,1)),"BA25:BA27",ISNUMBER(SEARCH("Noncash",C26,1)),"AZ25",ISNUMBER(SEARCH("Comprehensive",C26,1)),"AZ25",ISNUMBER(SEARCH("Reconciliation",C26,1)),"BB25:BB26")} -> AX25:AX29 | AU26: Accumulated Depreciation | AX26: Current Liabilities | AY26: Expenses | BA26: Investing Activities | BB26: Changes in accounts due to operations
C27: Beginning Balance Sheet | D27: Current Assets | E27: Accounts Receivable | F27: 0 | H27: =_xlfn.TEXTJOIN(6,1,FSBuilder[[#This Row],[Statement]:[Account or Explanation]]) -> Beginning Balance Sheet6 Current Assets6Accounts Receivable | I27: 5 | J27: Total Current Liabilities | K27: 0 | X27: 5 | Y27: Total Current Liabilities | Z27: 0 | AC27: =ISNUMBER(MATCH(N27&O27,FSData!$V$7:$V$95,0)) -> TRUE | AD27: =OR(ISNUMBER(SEARCH("Total",N27,1)),ISNUMBER(SEARCH("Net Income",N27,1))) -> FALSE | AE27: =AND(NOT(AC27),NOT(AD27)) -> FALSE | AF27: =ISNUMBER(MATCH(R27&S27,FSData!$X$7:$X$95,0)) -> TRUE | AG27: =OR(ISNUMBER(SEARCH("Total",R27,1)),ISNUMBER(SEARCH("Balance",R27,1))) -> FALSE | AH27: =AND(NOT(AF27),NOT(AG27)) -> FALSE | AJ27: =ISNUMBER(MATCH(U27&V27,FSData!$Z$7:$Z$95,0)) -> TRUE | AK27: =OR(ISNUMBER(SEARCH("Total",U27,1)),ISNUMBER(SEARCH("Increase (decrease)",U27,1)),ISNUMBER(SEARCH("Operating Activities",U27,1)),ISNUMBER(SEARCH("Investing Activities",U27,1)),ISNUMBER(SEARCH("Financing Activities",U27,1)),ISNUMBER(SEARCH("Cash @",U27,1)),ISNUMBER(SEARCH("Net Income",U27,1)),ISNUMBER(SEARCH("Cash Flow from Operations",U27,1))) -> FALSE | AL27: =AND(NOT(AJ27),NOT(AK27)) -> FALSE | AN27: =ISNUMBER(MATCH(Y27&Z27,FSData!$AB$7:$AB$95,0)) -> TRUE | AO27: =OR(ISNUMBER(SEARCH("Total",Y27,1))) -> TRUE | AP27: =AND(NOT(AN27),NOT(AO27)) -> FALSE | AR27: {=_xlfn.IFS(ISNUMBER(SEARCH("Balance",C27,1)),"MasterData!O56#",ISNUMBER(SEARCH("Income St",C27,1)),"MasterData!O116#",ISNUMBER(SEARCH("Shareholders",C27,1)),"D115#",ISNUMBER(SEARCH("Cash Flow",C27,1)),"E115#",ISNUMBER(SEARCH("Noncash",C27,1)),"C139#",ISNUMBER(SEARCH("Comprehensive",C27,1)),"E145",ISNUMBER(SEARCH("Reconciliation",C27,1)),"D137#")} -> MasterData!O56# | AS27: {=_xlfn.IFS(ISNUMBER(SEARCH("Balance",C27,1)),"AX25:AX29",ISNUMBER(SEARCH("Income St",C27,1)),"AY25:AY28",ISNUMBER(SEARCH("Shareholders",C27,1)),"EquityUsed",ISNUMBER(SEARCH("Cash Flow",C27,1)),"BA25:BA27",ISNUMBER(SEARCH("Noncash",C27,1)),"AZ25",ISNUMBER(SEARCH("Comprehensive",C27,1)),"AZ25",ISNUMBER(SEARCH("Reconciliation",C27,1)),"BB25:BB26")} -> AX25:AX29 | AU27: Cash | AX27: Noncurrent Assets | AY27: =IF(MAX(FSConstruction!P36:P51)," Gains","") | BA27: Financing Activities
C28: Beginning Balance Sheet | D28: Current Assets | E28: Inventories | F28: 0 | H28: =_xlfn.TEXTJOIN(6,1,FSBuilder[[#This Row],[Statement]:[Account or Explanation]]) -> Beginning Balance Sheet6 Current Assets6Inventories | AC28: =ISNUMBER(MATCH(N28&O28,FSData!$V$7:$V$95,0)) -> TRUE | AD28: =OR(ISNUMBER(SEARCH("Total",N28,1)),ISNUMBER(SEARCH("Net Income",N28,1))) -> FALSE | AE28: =AND(NOT(AC28),NOT(AD28)) -> FALSE | AF28: =ISNUMBER(MATCH(R28&S28,FSData!$X$7:$X$95,0)) -> TRUE | AG28: =OR(ISNUMBER(SEARCH("Total",R28,1)),ISNUMBER(SEARCH("Balance",R28,1))) -> FALSE | AH28: =AND(NOT(AF28),NOT(AG28)) -> FALSE | AJ28: =ISNUMBER(MATCH(U28&V28,FSData!$Z$7:$Z$95,0)) -> TRUE | AK28: =OR(ISNUMBER(SEARCH("Total",U28,1)),ISNUMBER(SEARCH("Increase (decrease)",U28,1)),ISNUMBER(SEARCH("Operating Activities",U28,1)),ISNUMBER(SEARCH("Investing Activities",U28,1)),ISNUMBER(SEARCH("Financing Activities",U28,1)),ISNUMBER(SEARCH("Cash @",U28,1)),ISNUMBER(SEARCH("Net Income",U28,1)),ISNUMBER(SEARCH("Cash Flow from Operations",U28,1))) -> FALSE | AL28: =AND(NOT(AJ28),NOT(AK28)) -> FALSE | AN28: =ISNUMBER(MATCH(Y28&Z28,FSData!$AB$7:$AB$95,0)) -> TRUE | AO28: =OR(ISNUMBER(SEARCH("Total",Y28,1))) -> FALSE | AP28: =AND(NOT(AN28),NOT(AO28)) -> FALSE | AR28: {=_xlfn.IFS(ISNUMBER(SEARCH("Balance",C28,1)),"MasterData!O56#",ISNUMBER(SEARCH("Income St",C28,1)),"MasterData!O116#",ISNUMBER(SEARCH("Shareholders",C28,1)),"D115#",ISNUMBER(SEARCH("Cash Flow",C28,1)),"E115#",ISNUMBER(SEARCH("Noncash",C28,1)),"C139#",ISNUMBER(SEARCH("Comprehensive",C28,1)),"E145",ISNUMBER(SEARCH("Reconciliation",C28,1)),"D137#")} -> MasterData!O56# | AS28: {=_xlfn.IFS(ISNUMBER(SEARCH("Balance",C28,1)),"AX25:AX29",ISNUMBER(SEARCH("Income St",C28,1)),"AY25:AY28",ISNUMBER(SEARCH("Shareholders",C28,1)),"EquityUsed",ISNUMBER(SEARCH("Cash Flow",C28,1)),"BA25:BA27",ISNUMBER(SEARCH("Noncash",C28,1)),"AZ25",ISNUMBER(SEARCH("Comprehensive",C28,1)),"AZ25",ISNUMBER(SEARCH("Reconciliation",C28,1)),"BB25:BB26")} -> AX25:AX29 | AU28: Common Stock | AX28: Noncurrent Liabilities | AY28: =IF(MAX(FSConstruction!P36:P51)," Losses","")
C29: Beginning Balance Sheet | D29: Equities | E29: Common Stock | F29: 0 | H29: =_xlfn.TEXTJOIN(6,1,FSBuilder[[#This Row],[Statement]:[Account or Explanation]]) -> Beginning Balance Sheet6 Equities6Common Stock | I29: 4 | J29: Noncurrent Liabilities: | X29: 4 | Y29: Noncurrent Liabilities: | AC29: =ISNUMBER(MATCH(N29&O29,FSData!$V$7:$V$95,0)) -> TRUE | AD29: =OR(ISNUMBER(SEARCH("Total",N29,1)),ISNUMBER(SEARCH("Net Income",N29,1))) -> FALSE | AE29: =AND(NOT(AC29),NOT(AD29)) -> FALSE | AF29: =ISNUMBER(MATCH(R29&S29,FSData!$X$7:$X$95,0)) -> TRUE | AG29: =OR(ISNUMBER(SEARCH("Total",R29,1)),ISNUMBER(SEARCH("Balance",R29,1))) -> FALSE | AH29: =AND(NOT(AF29),NOT(AG29)) -> FALSE | AJ29: =ISNUMBER(MATCH(U29&V29,FSData!$Z$7:$Z$95,0)) -> TRUE | AK29: =OR(ISNUMBER(SEARCH("Total",U29,1)),ISNUMBER(SEARCH("Increase (decrease)",U29,1)),ISNUMBER(SEARCH("Operating Activities",U29,1)),ISNUMBER(SEARCH("Investing Activities",U29,1)),ISNUMBER(SEARCH("Financing Activities",U29,1)),ISNUMBER(SEARCH("Cash @",U29,1)),ISNUMBER(SEARCH("Net Income",U29,1)),ISNUMBER(SEARCH("Cash Flow from Operations",U29,1))) -> FALSE | AL29: =AND(NOT(AJ29),NOT(AK29)) -> FALSE | AN29: =ISNUMBER(MATCH(Y29&Z29,FSData!$AB$7:$AB$95,0)) -> TRUE | AO29: =OR(ISNUMBER(SEARCH("Total",Y29,1))) -> FALSE | AP29: =AND(NOT(AN29),NOT(AO29)) -> FALSE | AR29: {=_xlfn.IFS(ISNUMBER(SEARCH("Balance",C29,1)),"MasterData!O56#",ISNUMBER(SEARCH("Income St",C29,1)),"MasterData!O116#",ISNUMBER(SEARCH("Shareholders",C29,1)),"D115#",ISNUMBER(SEARCH("Cash Flow",C29,1)),"E115#",ISNUMBER(SEARCH("Noncash",C29,1)),"C139#",ISNUMBER(SEARCH("Comprehensive",C29,1)),"E145",ISNUMBER(SEARCH("Reconciliation",C29,1)),"D137#")} -> MasterData!O56# | AS29: {=_xlfn.IFS(ISNUMBER(SEARCH("Balance",C29,1)),"AX25:AX29",ISNUMBER(SEARCH("Income St",C29,1)),"AY25:AY28",ISNUMBER(SEARCH("Shareholders",C29,1)),"EquityUsed",ISNUMBER(SEARCH("Cash Flow",C29,1)),"BA25:BA27",ISNUMBER(SEARCH("Noncash",C29,1)),"AZ25",ISNUMBER(SEARCH("Comprehensive",C29,1)),"AZ25",ISNUMBER(SEARCH("Reconciliation",C29,1)),"BB25:BB26")} -> AX25:AX29 | AU29: Dividends Payable | AX29: Equities
C30: Beginning Balance Sheet | D30: Equities | E30: Retained Earnings | F30: 0 | H30: =_xlfn.TEXTJOIN(6,1,FSBuilder[[#This Row],[Statement]:[Account or Explanation]]) -> Beginning Balance Sheet6 Equities6Retained Earnings | I30: 6 | J30: Notes Payable | K30: 0 | X30: 6 | Y30: Notes Payable | Z30: 20 | AC30: =ISNUMBER(MATCH(N30&O30,FSData!$V$7:$V$95,0)) -> TRUE | AD30: =OR(ISNUMBER(SEARCH("Total",N30,1)),ISNUMBER(SEARCH("Net Income",N30,1))) -> FALSE | AE30: =AND(NOT(AC30),NOT(AD30)) -> FALSE | AF30: =ISNUMBER(MATCH(R30&S30,FSData!$X$7:$X$95,0)) -> TRUE | AG30: =OR(ISNUMBER(SEARCH("Total",R30,1)),ISNUMBER(SEARCH("Balance",R30,1))) -> FALSE | AH30: =AND(NOT(AF30),NOT(AG30)) -> FALSE | AJ30: =ISNUMBER(MATCH(U30&V30,FSData!$Z$7:$Z$95,0)) -> TRUE | AK30: =OR(ISNUMBER(SEARCH("Total",U30,1)),ISNUMBER(SEARCH("Increase (decrease)",U30,1)),ISNUMBER(SEARCH("Operating Activities",U30,1)),ISNUMBER(SEARCH("Investing Activities",U30,1)),ISNUMBER(SEARCH("Financing Activities",U30,1)),ISNUMBER(SEARCH("Cash @",U30,1)),ISNUMBER(SEARCH("Net Income",U30,1)),ISNUMBER(SEARCH("Cash Flow from Operations",U30,1))) -> FALSE | AL30: =AND(NOT(AJ30),NOT(AK30)) -> FALSE | AN30: =ISNUMBER(MATCH(Y30&Z30,FSData!$AB$7:$AB$95,0)) -> TRUE | AO30: =OR(ISNUMBER(SEARCH("Total",Y30,1))) -> FALSE | AP30: =AND(NOT(AN30),NOT(AO30)) -> FALSE | AR30: {=_xlfn.IFS(ISNUMBER(SEARCH("Balance",C30,1)),"MasterData!O56#",ISNUMBER(SEARCH("Income St",C30,1)),"MasterData!O116#",ISNUMBER(SEARCH("Shareholders",C30,1)),"D115#",ISNUMBER(SEARCH("Cash Flow",C30,1)),"E115#",ISNUMBER(SEARCH("Noncash",C30,1)),"C139#",ISNUMBER(SEARCH("Comprehensive",C30,1)),"E145",ISNUMBER(SEARCH("Reconciliation",C30,1)),"D137#")} -> MasterData!O56# | AS30: {=_xlfn.IFS(ISNUMBER(SEARCH("Balance",C30,1)),"AX25:AX29",ISNUMBER(SEARCH("Income St",C30,1)),"AY25:AY28",ISNUMBER(SEARCH("Shareholders",C30,1)),"EquityUsed",ISNUMBER(SEARCH("Cash Flow",C30,1)),"BA25:BA27",ISNUMBER(SEARCH("Noncash",C30,1)),"AZ25",ISNUMBER(SEARCH("Comprehensive",C30,1)),"AZ25",ISNUMBER(SEARCH("Reconciliation",C30,1)),"BB25:BB26")} -> AX25:AX29 | AU30: Interest Payable
C31: Beginning Balance Sheet | D31: Current Liabilities | E31: Interest Payable | F31: 0 | H31: =_xlfn.TEXTJOIN(6,1,FSBuilder[[#This Row],[Statement]:[Account or Explanation]]) -> Beginning Balance Sheet6 Current Liabilities6Interest Payable | I31: 5 | J31: Total Noncurrent Liabilities | K31: 0 | X31: 5 | Y31: Total Noncurrent Liabilities | Z31: 20 | AC31: =ISNUMBER(MATCH(N31&O31,FSData!$V$7:$V$95,0)) -> TRUE | AD31: =OR(ISNUMBER(SEARCH("Total",N31,1)),ISNUMBER(SEARCH("Net Income",N31,1))) -> FALSE | AE31: =AND(NOT(AC31),NOT(AD31)) -> FALSE | AF31: =ISNUMBER(MATCH(R31&S31,FSData!$X$7:$X$95,0)) -> TRUE | AG31: =OR(ISNUMBER(SEARCH("Total",R31,1)),ISNUMBER(SEARCH("Balance",R31,1))) -> FALSE | AH31: =AND(NOT(AF31),NOT(AG31)) -> FALSE | AJ31: =ISNUMBER(MATCH(U31&V31,FSData!$Z$7:$Z$95,0)) -> TRUE | AK31: =OR(ISNUMBER(SEARCH("Total",U31,1)),ISNUMBER(SEARCH("Increase (decrease)",U31,1)),ISNUMBER(SEARCH("Operating Activities",U31,1)),ISNUMBER(SEARCH("Investing Activities",U31,1)),ISNUMBER(SEARCH("Financing Activities",U31,1)),ISNUMBER(SEARCH("Cash @",U31,1)),ISNUMBER(SEARCH("Net Income",U31,1)),ISNUMBER(SEARCH("Cash Flow from Operations",U31,1))) -> FALSE | AL31: =AND(NOT(AJ31),NOT(AK31)) -> FALSE | AN31: =ISNUMBER(MATCH(Y31&Z31,FSData!$AB$7:$AB$95,0)) -> TRUE | AO31: =OR(ISNUMBER(SEARCH("Total",Y31,1))) -> TRUE | AP31: =AND(NOT(AN31),NOT(AO31)) -> FALSE | AR31: {=_xlfn.IFS(ISNUMBER(SEARCH("Balance",C31,1)),"MasterData!O56#",ISNUMBER(SEARCH("Income St",C31,1)),"MasterData!O116#",ISNUMBER(SEARCH("Shareholders",C31,1)),"D115#",ISNUMBER(SEARCH("Cash Flow",C31,1)),"E115#",ISNUMBER(SEARCH("Noncash",C31,1)),"C139#",ISNUMBER(SEARCH("Comprehensive",C31,1)),"E145",ISNUMBER(SEARCH("Reconciliation",C31,1)),"D137#")} -> MasterData!O56# | AS31: {=_xlfn.IFS(ISNUMBER(SEARCH("Balance",C31,1)),"AX25:AX29",ISNUMBER(SEARCH("Income St",C31,1)),"AY25:AY28",ISNUMBER(SEARCH("Shareholders",C31,1)),"EquityUsed",ISNUMBER(SEARCH("Cash Flow",C31,1)),"BA25:BA27",ISNUMBER(SEARCH("Noncash",C31,1)),"AZ25",ISNUMBER(SEARCH("Comprehensive",C31,1)),"AZ25",ISNUMBER(SEARCH("Reconciliation",C31,1)),"BB25:BB26")} -> AX25:AX29 | AU31: Inventories
C32: Beginning Balance Sheet | D32: Current Assets | E32: Dividends Payable | F32: 0 | H32: =_xlfn.TEXTJOIN(6,1,FSBuilder[[#This Row],[Statement]:[Account or Explanation]]) -> Beginning Balance Sheet6 Current Assets6Dividends Payable | AC32: =ISNUMBER(MATCH(N32&O32,FSData!$V$7:$V$95,0)) -> TRUE | AD32: =OR(ISNUMBER(SEARCH("Total",N32,1)),ISNUMBER(SEARCH("Net Income",N32,1))) -> FALSE | AE32: =AND(NOT(AC32),NOT(AD32)) -> FALSE | AF32: =ISNUMBER(MATCH(R32&S32,FSData!$X$7:$X$95,0)) -> TRUE | AG32: =OR(ISNUMBER(SEARCH("Total",R32,1)),ISNUMBER(SEARCH("Balance",R32,1))) -> FALSE | AH32: =AND(NOT(AF32),NOT(AG32)) -> FALSE | AJ32: =ISNUMBER(MATCH(U32&V32,FSData!$Z$7:$Z$95,0)) -> TRUE | AK32: =OR(ISNUMBER(SEARCH("Total",U32,1)),ISNUMBER(SEARCH("Increase (decrease)",U32,1)),ISNUMBER(SEARCH("Operating Activities",U32,1)),ISNUMBER(SEARCH("Investing Activities",U32,1)),ISNUMBER(SEARCH("Financing Activities",U32,1)),ISNUMBER(SEARCH("Cash @",U32,1)),ISNUMBER(SEARCH("Net Income",U32,1)),ISNUMBER(SEARCH("Cash Flow from Operations",U32,1))) -> FALSE | AL32: =AND(NOT(AJ32),NOT(AK32)) -> FALSE | AN32: =ISNUMBER(MATCH(Y32&Z32,FSData!$AB$7:$AB$95,0)) -> TRUE | AO32: =OR(ISNUMBER(SEARCH("Total",Y32,1))) -> FALSE | AP32: =AND(NOT(AN32),NOT(AO32)) -> FALSE | AR32: {=_xlfn.IFS(ISNUMBER(SEARCH("Balance",C32,1)),"MasterData!O56#",ISNUMBER(SEARCH("Income St",C32,1)),"MasterData!O116#",ISNUMBER(SEARCH("Shareholders",C32,1)),"D115#",ISNUMBER(SEARCH("Cash Flow",C32,1)),"E115#",ISNUMBER(SEARCH("Noncash",C32,1)),"C139#",ISNUMBER(SEARCH("Comprehensive",C32,1)),"E145",ISNUMBER(SEARCH("Reconciliation",C32,1)),"D137#")} -> MasterData!O56# | AS32: {=_xlfn.IFS(ISNUMBER(SEARCH("Balance",C32,1)),"AX25:AX29",ISNUMBER(SEARCH("Income St",C32,1)),"AY25:AY28",ISNUMBER(SEARCH("Shareholders",C32,1)),"EquityUsed",ISNUMBER(SEARCH("Cash Flow",C32,1)),"BA25:BA27",ISNUMBER(SEARCH("Noncash",C32,1)),"AZ25",ISNUMBER(SEARCH("Comprehensive",C32,1)),"AZ25",ISNUMBER(SEARCH("Reconciliation",C32,1)),"BB25:BB26")} -> AX25:AX29 | AU32: Notes Payable
C33: Beginning Balance Sheet | D33: Noncurrent Assets | E33: Property, Plant & Equipment | F33: 0 | H33: =_xlfn.TEXTJOIN(6,1,FSBuilder[[#This Row],[Statement]:[Account or Explanation]]) -> Beginning Balance Sheet6 Noncurrent Assets6Property, Plant & Equipment | I33: 3 | J33: Total Liabilities | K33: 0 | X33: 3 | Y33: Total Liabilities | Z33: 20 | AC33: =ISNUMBER(MATCH(N33&O33,FSData!$V$7:$V$95,0)) -> TRUE | AD33: =OR(ISNUMBER(SEARCH("Total",N33,1)),ISNUMBER(SEARCH("Net Income",N33,1))) -> FALSE | AE33: =AND(NOT(AC33),NOT(AD33)) -> FALSE | AF33: =ISNUMBER(MATCH(R33&S33,FSData!$X$7:$X$95,0)) -> TRUE | AG33: =OR(ISNUMBER(SEARCH("Total",R33,1)),ISNUMBER(SEARCH("Balance",R33,1))) -> FALSE | AH33: =AND(NOT(AF33),NOT(AG33)) -> FALSE | AJ33: =ISNUMBER(MATCH(U33&V33,FSData!$Z$7:$Z$95,0)) -> TRUE | AK33: =OR(ISNUMBER(SEARCH("Total",U33,1)),ISNUMBER(SEARCH("Increase (decrease)",U33,1)),ISNUMBER(SEARCH("Operating Activities",U33,1)),ISNUMBER(SEARCH("Investing Activities",U33,1)),ISNUMBER(SEARCH("Financing Activities",U33,1)),ISNUMBER(SEARCH("Cash @",U33,1)),ISNUMBER(SEARCH("Net Income",U33,1)),ISNUMBER(SEARCH("Cash Flow from Operations",U33,1))) -> FALSE | AL33: =AND(NOT(AJ33),NOT(AK33)) -> FALSE | AN33: =ISNUMBER(MATCH(Y33&Z33,FSData!$AB$7:$AB$95,0)) -> TRUE | AO33: =OR(ISNUMBER(SEARCH("Total",Y33,1))) -> TRUE | AP33: =AND(NOT(AN33),NOT(AO33)) -> FALSE | AR33: {=_xlfn.IFS(ISNUMBER(SEARCH("Balance",C33,1)),"MasterData!O56#",ISNUMBER(SEARCH("Income St",C33,1)),"MasterData!O116#",ISNUMBER(SEARCH("Shareholders",C33,1)),"D115#",ISNUMBER(SEARCH("Cash Flow",C33,1)),"E115#",ISNUMBER(SEARCH("Noncash",C33,1)),"C139#",ISNUMBER(SEARCH("Comprehensive",C33,1)),"E145",ISNUMBER(SEARCH("Reconciliation",C33,1)),"D137#")} -> MasterData!O56# | AS33: {=_xlfn.IFS(ISNUMBER(SEARCH("Balance",C33,1)),"AX25:AX29",ISNUMBER(SEARCH("Income St",C33,1)),"AY25:AY28",ISNUMBER(SEARCH("Shareholders",C33,1)),"EquityUsed",ISNUMBER(SEARCH("Cash Flow",C33,1)),"BA25:BA27",ISNUMBER(SEARCH("Noncash",C33,1)),"AZ25",ISNUMBER(SEARCH("Comprehensive",C33,1)),"AZ25",ISNUMBER(SEARCH("Reconciliation",C33,1)),"BB25:BB26")} -> AX25:AX29 | AU33: Property, Plant & Equipment
C34: Beginning Balance Sheet | D34: Noncurrent Assets | E34: Accumulated Depreciation | F34: 0 | H34: =_xlfn.TEXTJOIN(6,1,FSBuilder[[#This Row],[Statement]:[Account or Explanation]]) -> Beginning Balance Sheet6 Noncurrent Assets6Accumulated Depreciation | AC34: =ISNUMBER(MATCH(N34&O34,FSData!$V$7:$V$95,0)) -> TRUE | AD34: =OR(ISNUMBER(SEARCH("Total",N34,1)),ISNUMBER(SEARCH("Net Income",N34,1))) -> FALSE | AE34: =AND(NOT(AC34),NOT(AD34)) -> FALSE | AF34: =ISNUMBER(MATCH(R34&S34,FSData!$X$7:$X$95,0)) -> TRUE | AG34: =OR(ISNUMBER(SEARCH("Total",R34,1)),ISNUMBER(SEARCH("Balance",R34,1))) -> FALSE | AH34: =AND(NOT(AF34),NOT(AG34)) -> FALSE | AJ34: =ISNUMBER(MATCH(U34&V34,FSData!$Z$7:$Z$95,0)) -> TRUE | AK34: =OR(ISNUMBER(SEARCH("Total",U34,1)),ISNUMBER(SEARCH("Increase (decrease)",U34,1)),ISNUMBER(SEARCH("Operating Activities",U34,1)),ISNUMBER(SEARCH("Investing Activities",U34,1)),ISNUMBER(SEARCH("Financing Activities",U34,1)),ISNUMBER(SEARCH("Cash @",U34,1)),ISNUMBER(SEARCH("Net Income",U34,1)),ISNUMBER(SEARCH("Cash Flow from Operations",U34,1))) -> FALSE | AL34: =AND(NOT(AJ34),NOT(AK34)) -> FALSE | AN34: =ISNUMBER(MATCH(Y34&Z34,FSData!$AB$7:$AB$95,0)) -> TRUE | AO34: =OR(ISNUMBER(SEARCH("Total",Y34,1))) -> FALSE | AP34: =AND(NOT(AN34),NOT(AO34)) -> FALSE | AR34: {=_xlfn.IFS(ISNUMBER(SEARCH("Balance",C34,1)),"MasterData!O56#",ISNUMBER(SEARCH("Income St",C34,1)),"MasterData!O116#",ISNUMBER(SEARCH("Shareholders",C34,1)),"D115#",ISNUMBER(SEARCH("Cash Flow",C34,1)),"E115#",ISNUMBER(SEARCH("Noncash",C34,1)),"C139#",ISNUMBER(SEARCH("Comprehensive",C34,1)),"E145",ISNUMBER(SEARCH("Reconciliation",C34,1)),"D137#")} -> MasterData!O56# | AS34: {=_xlfn.IFS(ISNUMBER(SEARCH("Balance",C34,1)),"AX25:AX29",ISNUMBER(SEARCH("Income St",C34,1)),"AY25:AY28",ISNUMBER(SEARCH("Shareholders",C34,1)),"EquityUsed",ISNUMBER(SEARCH("Cash Flow",C34,1)),"BA25:BA27",ISNUMBER(SEARCH("Noncash",C34,1)),"AZ25",ISNUMBER(SEARCH("Comprehensive",C34,1)),"AZ25",ISNUMBER(SEARCH("Reconciliation",C34,1)),"BB25:BB26")} -> AX25:AX29 | AU34: Retained Earnings
E35: Cost of Goods Sold | H35: =_xlfn.TEXTJOIN(6,1,FSBuilder[[#This Row],[Statement]:[Account or Explanation]]) -> Cost of Goods Sold | I35: 2 | J35: Equities | X35: 2 | Y35: Equities | AC35: =ISNUMBER(MATCH(N35&O35,FSData!$V$7:$V$95,0)) -> TRUE | AD35: =OR(ISNUMBER(SEARCH("Total",N35,1)),ISNUMBER(SEARCH("Net Income",N35,1))) -> FALSE | AE35: =AND(NOT(AC35),NOT(AD35)) -> FALSE | AF35: =ISNUMBER(MATCH(R35&S35,FSData!$X$7:$X$95,0)) -> TRUE | AG35: =OR(ISNUMBER(SEARCH("Total",R35,1)),ISNUMBER(SEARCH("Balance",R35,1))) -> FALSE | AH35: =AND(NOT(AF35),NOT(AG35)) -> FALSE | AJ35: =ISNUMBER(MATCH(U35&V35,FSData!$Z$7:$Z$95,0)) -> TRUE | AK35: =OR(ISNUMBER(SEARCH("Total",U35,1)),ISNUMBER(SEARCH("Increase (decrease)",U35,1)),ISNUMBER(SEARCH("Operating Activities",U35,1)),ISNUMBER(SEARCH("Investing Activities",U35,1)),ISNUMBER(SEARCH("Financing Activities",U35,1)),ISNUMBER(SEARCH("Cash @",U35,1)),ISNUMBER(SEARCH("Net Income",U35,1)),ISNUMBER(SEARCH("Cash Flow from Operations",U35,1))) -> FALSE | AL35: =AND(NOT(AJ35),NOT(AK35)) -> FALSE | AN35: =ISNUMBER(MATCH(Y35&Z35,FSData!$AB$7:$AB$95,0)) -> TRUE | AO35: =OR(ISNUMBER(SEARCH("Total",Y35,1))) -> FALSE | AP35: =AND(NOT(AN35),NOT(AO35)) -> FALSE | AR35: {=_xlfn.IFS(ISNUMBER(SEARCH("Balance",C35,1)),"MasterData!O56#",ISNUMBER(SEARCH("Income St",C35,1)),"MasterData!O116#",ISNUMBER(SEARCH("Shareholders",C35,1)),"D115#",ISNUMBER(SEARCH("Cash Flow",C35,1)),"E115#",ISNUMBER(SEARCH("Noncash",C35,1)),"C139#",ISNUMBER(SEARCH("Comprehensive",C35,1)),"E145",ISNUMBER(SEARCH("Reconciliation",C35,1)),"D137#")} -> #N/A | AS35: {=_xlfn.IFS(ISNUMBER(SEARCH("Balance",C35,1)),"AX25:AX29",ISNUMBER(SEARCH("Income St",C35,1)),"AY25:AY28",ISNUMBER(SEARCH("Shareholders",C35,1)),"EquityUsed",ISNUMBER(SEARCH("Cash Flow",C35,1)),"BA25:BA27",ISNUMBER(SEARCH("Noncash",C35,1)),"AZ25",ISNUMBER(SEARCH("Comprehensive",C35,1)),"AZ25",ISNUMBER(SEARCH("Reconciliation",C35,1)),"BB25:BB26")} -> #N/A
E36: Interest Expense | H36: =_xlfn.TEXTJOIN(6,1,FSBuilder[[#This Row],[Statement]:[Account or Explanation]]) -> Interest Expense | AC36: =ISNUMBER(MATCH(N36&O36,FSData!$V$7:$V$95,0)) -> TRUE | AD36: =OR(ISNUMBER(SEARCH("Total",N36,1)),ISNUMBER(SEARCH("Net Income",N36,1))) -> FALSE | AE36: =AND(NOT(AC36),NOT(AD36)) -> FALSE | AF36: =ISNUMBER(MATCH(R36&S36,FSData!$X$7:$X$95,0)) -> TRUE | AG36: =OR(ISNUMBER(SEARCH("Total",R36,1)),ISNUMBER(SEARCH("Balance",R36,1))) -> FALSE | AH36: =AND(NOT(AF36),NOT(AG36)) -> FALSE | AJ36: =ISNUMBER(MATCH(U36&V36,FSData!$Z$7:$Z$95,0)) -> TRUE | AK36: =OR(ISNUMBER(SEARCH("Total",U36,1)),ISNUMBER(SEARCH("Increase (decrease)",U36,1)),ISNUMBER(SEARCH("Operating Activities",U36,1)),ISNUMBER(SEARCH("Investing Activities",U36,1)),ISNUMBER(SEARCH("Financing Activities",U36,1)),ISNUMBER(SEARCH("Cash @",U36,1)),ISNUMBER(SEARCH("Net Income",U36,1)),ISNUMBER(SEARCH("Cash Flow from Operations",U36,1))) -> FALSE | AL36: =AND(NOT(AJ36),NOT(AK36)) -> FALSE | AN36: =ISNUMBER(MATCH(Y36&Z36,FSData!$AB$7:$AB$95,0)) -> TRUE | AO36: =OR(ISNUMBER(SEARCH("Total",Y36,1))) -> FALSE | AP36: =AND(NOT(AN36),NOT(AO36)) -> FALSE | AR36: {=_xlfn.IFS(ISNUMBER(SEARCH("Balance",C36,1)),"MasterData!O56#",ISNUMBER(SEARCH("Income St",C36,1)),"MasterData!O116#",ISNUMBER(SEARCH("Shareholders",C36,1)),"D115#",ISNUMBER(SEARCH("Cash Flow",C36,1)),"E115#",ISNUMBER(SEARCH("Noncash",C36,1)),"C139#",ISNUMBER(SEARCH("Comprehensive",C36,1)),"E145",ISNUMBER(SEARCH("Reconciliation",C36,1)),"D137#")} -> #N/A | AS36: {=_xlfn.IFS(ISNUMBER(SEARCH("Balance",C36,1)),"AX25:AX29",ISNUMBER(SEARCH("Income St",C36,1)),"AY25:AY28",ISNUMBER(SEARCH("Shareholders",C36,1)),"EquityUsed",ISNUMBER(SEARCH("Cash Flow",C36,1)),"BA25:BA27",ISNUMBER(SEARCH("Noncash",C36,1)),"AZ25",ISNUMBER(SEARCH("Comprehensive",C36,1)),"AZ25",ISNUMBER(SEARCH("Reconciliation",C36,1)),"BB25:BB26")} -> #N/A
E37: Depreciation Expense | H37: =_xlfn.TEXTJOIN(6,1,FSBuilder[[#This Row],[Statement]:[Account or Explanation]]) -> Depreciation Expense | I37: 6 | J37: Common Stock | K37: 0 | X37: 6 | Y37: Common Stock | Z37: 3 | AC37: =ISNUMBER(MATCH(N37&O37,FSData!$V$7:$V$95,0)) -> TRUE | AD37: =OR(ISNUMBER(SEARCH("Total",N37,1)),ISNUMBER(SEARCH("Net Income",N37,1))) -> FALSE | AE37: =AND(NOT(AC37),NOT(AD37)) -> FALSE | AF37: =ISNUMBER(MATCH(R37&S37,FSData!$X$7:$X$95,0)) -> TRUE | AG37: =OR(ISNUMBER(SEARCH("Total",R37,1)),ISNUMBER(SEARCH("Balance",R37,1))) -> FALSE | AH37: =AND(NOT(AF37),NOT(AG37)) -> FALSE | AJ37: =ISNUMBER(MATCH(U37&V37,FSData!$Z$7:$Z$95,0)) -> TRUE | AK37: =OR(ISNUMBER(SEARCH("Total",U37,1)),ISNUMBER(SEARCH("Increase (decrease)",U37,1)),ISNUMBER(SEARCH("Operating Activities",U37,1)),ISNUMBER(SEARCH("Investing Activities",U37,1)),ISNUMBER(SEARCH("Financing Activities",U37,1)),ISNUMBER(SEARCH("Cash @",U37,1)),ISNUMBER(SEARCH("Net Income",U37,1)),ISNUMBER(SEARCH("Cash Flow from Operations",U37,1))) -> FALSE | AL37: =AND(NOT(AJ37),NOT(AK37)) -> FALSE | AN37: =ISNUMBER(MATCH(Y37&Z37,FSData!$AB$7:$AB$95,0)) -> TRUE | AO37: =OR(ISNUMBER(SEARCH("Total",Y37,1))) -> FALSE | AP37: =AND(NOT(AN37),NOT(AO37)) -> FALSE | AR37: {=_xlfn.IFS(ISNUMBER(SEARCH("Balance",C37,1)),"MasterData!O56#",ISNUMBER(SEARCH("Income St",C37,1)),"MasterData!O116#",ISNUMBER(SEARCH("Shareholders",C37,1)),"D115#",ISNUMBER(SEARCH("Cash Flow",C37,1)),"E115#",ISNUMBER(SEARCH("Noncash",C37,1)),"C139#",ISNUMBER(SEARCH("Comprehensive",C37,1)),"E145",ISNUMBER(SEARCH("Reconciliation",C37,1)),"D137#")} -> #N/A | AS37: {=_xlfn.IFS(ISNUMBER(SEARCH("Balance",C37,1)),"AX25:AX29",ISNUMBER(SEARCH("Income St",C37,1)),"AY25:AY28",ISNUMBER(SEARCH("Shareholders",C37,1)),"EquityUsed",ISNUMBER(SEARCH("Cash Flow",C37,1)),"BA25:BA27",ISNUMBER(SEARCH("Noncash",C37,1)),"AZ25",ISNUMBER(SEARCH("Comprehensive",C37,1)),"AZ25",ISNUMBER(SEARCH("Reconciliation",C37,1)),"BB25:BB26")} -> #N/A
E38: Salaries & Wages Expense | H38: =_xlfn.TEXTJOIN(6,1,FSBuilder[[#This Row],[Statement]:[Account or Explanation]]) -> Salaries & Wages Expense | I38: 7 | J38: Retained Earnings | K38: 0 | X38: 7 | Y38: Retained Earnings | Z38: 1.88 | AC38: =ISNUMBER(MATCH(N38&O38,FSData!$V$7:$V$95,0)) -> TRUE | AD38: =OR(ISNUMBER(SEARCH("Total",N38,1)),ISNUMBER(SEARCH("Net Income",N38,1))) -> FALSE | AE38: =AND(NOT(AC38),NOT(AD38)) -> FALSE | AF38: =ISNUMBER(MATCH(R38&S38,FSData!$X$7:$X$95,0)) -> TRUE | AG38: =OR(ISNUMBER(SEARCH("Total",R38,1)),ISNUMBER(SEARCH("Balance",R38,1))) -> FALSE | AH38: =AND(NOT(AF38),NOT(AG38)) -> FALSE | AJ38: =ISNUMBER(MATCH(U38&V38,FSData!$Z$7:$Z$95,0)) -> TRUE | AK38: =OR(ISNUMBER(SEARCH("Total",U38,1)),ISNUMBER(SEARCH("Increase (decrease)",U38,1)),ISNUMBER(SEARCH("Operating Activities",U38,1)),ISNUMBER(SEARCH("Investing Activities",U38,1)),ISNUMBER(SEARCH("Financing Activities",U38,1)),ISNUMBER(SEARCH("Cash @",U38,1)),ISNUMBER(SEARCH("Net Income",U38,1)),ISNUMBER(SEARCH("Cash Flow from Operations",U38,1))) -> FALSE | AL38: =AND(NOT(AJ38),NOT(AK38)) -> FALSE | AN38: =ISNUMBER(MATCH(Y38&Z38,FSData!$AB$7:$AB$95,0)) -> FALSE | AO38: =OR(ISNUMBER(SEARCH("Total",Y38,1))) -> FALSE | AP38: =AND(NOT(AN38),NOT(AO38)) -> TRUE | AR38: {=_xlfn.IFS(ISNUMBER(SEARCH("Balance",C38,1)),"MasterData!O56#",ISNUMBER(SEARCH("Income St",C38,1)),"MasterData!O116#",ISNUMBER(SEARCH("Shareholders",C38,1)),"D115#",ISNUMBER(SEARCH("Cash Flow",C38,1)),"E115#",ISNUMBER(SEARCH("Noncash",C38,1)),"C139#",ISNUMBER(SEARCH("Comprehensive",C38,1)),"E145",ISNUMBER(SEARCH("Reconciliation",C38,1)),"D137#")} -> #N/A | AS38: {=_xlfn.IFS(ISNUMBER(SEARCH("Balance",C38,1)),"AX25:AX29",ISNUMBER(SEARCH("Income St",C38,1)),"AY25:AY28",ISNUMBER(SEARCH("Shareholders",C38,1)),"EquityUsed",ISNUMBER(SEARCH("Cash Flow",C38,1)),"BA25:BA27",ISNUMBER(SEARCH("Noncash",C38,1)),"AZ25",ISNUMBER(SEARCH("Comprehensive",C38,1)),"AZ25",ISNUMBER(SEARCH("Reconciliation",C38,1)),"BB25:BB26")} -> #N/A
E39: Sales | H39: =_xlfn.TEXTJOIN(6,1,FSBuilder[[#This Row],[Statement]:[Account or Explanation]]) -> Sales | AC39: =ISNUMBER(MATCH(N39&O39,FSData!$V$7:$V$95,0)) -> TRUE | AD39: =OR(ISNUMBER(SEARCH("Total",N39,1)),ISNUMBER(SEARCH("Net Income",N39,1))) -> FALSE | AE39: =AND(NOT(AC39),NOT(AD39)) -> FALSE | AF39: =ISNUMBER(MATCH(R39&S39,FSData!$X$7:$X$95,0)) -> TRUE | AG39: =OR(ISNUMBER(SEARCH("Total",R39,1)),ISNUMBER(SEARCH("Balance",R39,1))) -> FALSE | AH39: =AND(NOT(AF39),NOT(AG39)) -> FALSE | AJ39: =ISNUMBER(MATCH(U39&V39,FSData!$Z$7:$Z$95,0)) -> TRUE | AK39: =OR(ISNUMBER(SEARCH("Total",U39,1)),ISNUMBER(SEARCH("Increase (decrease)",U39,1)),ISNUMBER(SEARCH("Operating Activities",U39,1)),ISNUMBER(SEARCH("Investing Activities",U39,1)),ISNUMBER(SEARCH("Financing Activities",U39,1)),ISNUMBER(SEARCH("Cash @",U39,1)),ISNUMBER(SEARCH("Net Income",U39,1)),ISNUMBER(SEARCH("Cash Flow from Operations",U39,1))) -> FALSE | AL39: =AND(NOT(AJ39),NOT(AK39)) -> FALSE | AN39: =ISNUMBER(MATCH(Y39&Z39,FSData!$AB$7:$AB$95,0)) -> TRUE | AO39: =OR(ISNUMBER(SEARCH("Total",Y39,1))) -> FALSE | AP39: =AND(NOT(AN39),NOT(AO39)) -> FALSE | AR39: {=_xlfn.IFS(ISNUMBER(SEARCH("Balance",C39,1)),"MasterData!O56#",ISNUMBER(SEARCH("Income St",C39,1)),"MasterData!O116#",ISNUMBER(SEARCH("Shareholders",C39,1)),"D115#",ISNUMBER(SEARCH("Cash Flow",C39,1)),"E115#",ISNUMBER(SEARCH("Noncash",C39,1)),"C139#",ISNUMBER(SEARCH("Comprehensive",C39,1)),"E145",ISNUMBER(SEARCH("Reconciliation",C39,1)),"D137#")} -> #N/A | AS39: {=_xlfn.IFS(ISNUMBER(SEARCH("Balance",C39,1)),"AX25:AX29",ISNUMBER(SEARCH("Income St",C39,1)),"AY25:AY28",ISNUMBER(SEARCH("Shareholders",C39,1)),"EquityUsed",ISNUMBER(SEARCH("Cash Flow",C39,1)),"BA25:BA27",ISNUMBER(SEARCH("Noncash",C39,1)),"AZ25",ISNUMBER(SEARCH("Comprehensive",C39,1)),"AZ25",ISNUMBER(SEARCH("Reconciliation",C39,1)),"BB25:BB26")} -> #N/A
E40: Notes Payable | H40: =_xlfn.TEXTJOIN(6,1,FSBuilder[[#This Row],[Statement]:[Account or Explanation]]) -> Notes Payable | I40: 3 | J40: Total Equities | K40: 0 | X40: 3 | Y40: Total Equities | Z40: 4.88 | AC40: =ISNUMBER(MATCH(N40&O40,FSData!$V$7:$V$95,0)) -> TRUE | AD40: =OR(ISNUMBER(SEARCH("Total",N40,1)),ISNUMBER(SEARCH("Net Income",N40,1))) -> FALSE | AE40: =AND(NOT(AC40),NOT(AD40)) -> FALSE | AF40: =ISNUMBER(MATCH(R40&S40,FSData!$X$7:$X$95,0)) -> TRUE | AG40: =OR(ISNUMBER(SEARCH("Total",R40,1)),ISNUMBER(SEARCH("Balance",R40,1))) -> FALSE | AH40: =AND(NOT(AF40),NOT(AG40)) -> FALSE | AJ40: =ISNUMBER(MATCH(U40&V40,FSData!$Z$7:$Z$95,0)) -> TRUE | AK40: =OR(ISNUMBER(SEARCH("Total",U40,1)),ISNUMBER(SEARCH("Increase (decrease)",U40,1)),ISNUMBER(SEARCH("Operating Activities",U40,1)),ISNUMBER(SEARCH("Investing Activities",U40,1)),ISNUMBER(SEARCH("Financing Activities",U40,1)),ISNUMBER(SEARCH("Cash @",U40,1)),ISNUMBER(SEARCH("Net Income",U40,1)),ISNUMBER(SEARCH("Cash Flow from Operations",U40,1))) -> FALSE | AL40: =AND(NOT(AJ40),NOT(AK40)) -> FALSE | AN40: =ISNUMBER(MATCH(Y40&Z40,FSData!$AB$7:$AB$95,0)) -> FALSE | AO40: =OR(ISNUMBER(SEARCH("Total",Y40,1))) -> TRUE | AP40: =AND(NOT(AN40),NOT(AO40)) -> FALSE | AR40: {=_xlfn.IFS(ISNUMBER(SEARCH("Balance",C40,1)),"MasterData!O56#",ISNUMBER(SEARCH("Income St",C40,1)),"MasterData!O116#",ISNUMBER(SEARCH("Shareholders",C40,1)),"D115#",ISNUMBER(SEARCH("Cash Flow",C40,1)),"E115#",ISNUMBER(SEARCH("Noncash",C40,1)),"C139#",ISNUMBER(SEARCH("Comprehensive",C40,1)),"E145",ISNUMBER(SEARCH("Reconciliation",C40,1)),"D137#")} -> #N/A | AS40: {=_xlfn.IFS(ISNUMBER(SEARCH("Balance",C40,1)),"AX25:AX29",ISNUMBER(SEARCH("Income St",C40,1)),"AY25:AY28",ISNUMBER(SEARCH("Shareholders",C40,1)),"EquityUsed",ISNUMBER(SEARCH("Cash Flow",C40,1)),"BA25:BA27",ISNUMBER(SEARCH("Noncash",C40,1)),"AZ25",ISNUMBER(SEARCH("Comprehensive",C40,1)),"AZ25",ISNUMBER(SEARCH("Reconciliation",C40,1)),"BB25:BB26")} -> #N/A
E41: Cash | H41: =_xlfn.TEXTJOIN(6,1,FSBuilder[[#This Row],[Statement]:[Account or Explanation]]) -> Cash | AC41: =ISNUMBER(MATCH(N41&O41,FSData!$V$7:$V$95,0)) -> TRUE | AD41: =OR(ISNUMBER(SEARCH("Total",N41,1)),ISNUMBER(SEARCH("Net Income",N41,1))) -> FALSE | AE41: =AND(NOT(AC41),NOT(AD41)) -> FALSE | AF41: =ISNUMBER(MATCH(R41&S41,FSData!$X$7:$X$95,0)) -> TRUE | AG41: =OR(ISNUMBER(SEARCH("Total",R41,1)),ISNUMBER(SEARCH("Balance",R41,1))) -> FALSE | AH41: =AND(NOT(AF41),NOT(AG41)) -> FALSE | AJ41: =ISNUMBER(MATCH(U41&V41,FSData!$Z$7:$Z$95,0)) -> TRUE | AK41: =OR(ISNUMBER(SEARCH("Total",U41,1)),ISNUMBER(SEARCH("Increase (decrease)",U41,1)),ISNUMBER(SEARCH("Operating Activities",U41,1)),ISNUMBER(SEARCH("Investing Activities",U41,1)),ISNUMBER(SEARCH("Financing Activities",U41,1)),ISNUMBER(SEARCH("Cash @",U41,1)),ISNUMBER(SEARCH("Net Income",U41,1)),ISNUMBER(SEARCH("Cash Flow from Operations",U41,1))) -> FALSE | AL41: =AND(NOT(AJ41),NOT(AK41)) -> FALSE | AN41: =ISNUMBER(MATCH(Y41&Z41,FSData!$AB$7:$AB$95,0)) -> TRUE | AO41: =OR(ISNUMBER(SEARCH("Total",Y41,1))) -> FALSE | AP41: =AND(NOT(AN41),NOT(AO41)) -> FALSE | AR41: {=_xlfn.IFS(ISNUMBER(SEARCH("Balance",C41,1)),"MasterData!O56#",ISNUMBER(SEARCH("Income St",C41,1)),"MasterData!O116#",ISNUMBER(SEARCH("Shareholders",C41,1)),"D115#",ISNUMBER(SEARCH("Cash Flow",C41,1)),"E115#",ISNUMBER(SEARCH("Noncash",C41,1)),"C139#",ISNUMBER(SEARCH("Comprehensive",C41,1)),"E145",ISNUMBER(SEARCH("Reconciliation",C41,1)),"D137#")} -> #N/A | AS41: {=_xlfn.IFS(ISNUMBER(SEARCH("Balance",C41,1)),"AX25:AX29",ISNUMBER(SEARCH("Income St",C41,1)),"AY25:AY28",ISNUMBER(SEARCH("Shareholders",C41,1)),"EquityUsed",ISNUMBER(SEARCH("Cash Flow",C41,1)),"BA25:BA27",ISNUMBER(SEARCH("Noncash",C41,1)),"AZ25",ISNUMBER(SEARCH("Comprehensive",C41,1)),"AZ25",ISNUMBER(SEARCH("Reconciliation",C41,1)),"BB25:BB26")} -> #N/A
E42: Accounts Receivable | H42: =_xlfn.TEXTJOIN(6,1,FSBuilder[[#This Row],[Statement]:[Account or Explanation]]) -> Accounts Receivable | I42: 3 | J42: Total Liabilities and Equities | K42: 0 | X42: 3 | Y42: Total Liabilities and Equities | Z42: 24.88 | AC42: =ISNUMBER(MATCH(N42&O42,FSData!$V$7:$V$95,0)) -> TRUE | AD42: =OR(ISNUMBER(SEARCH("Total",N42,1)),ISNUMBER(SEARCH("Net Income",N42,1))) -> FALSE | AE42: =AND(NOT(AC42),NOT(AD42)) -> FALSE | AF42: =ISNUMBER(MATCH(R42&S42,FSData!$X$7:$X$95,0)) -> TRUE | AG42: =OR(ISNUMBER(SEARCH("Total",R42,1)),ISNUMBER(SEARCH("Balance",R42,1))) -> FALSE | AH42: =AND(NOT(AF42),NOT(AG42)) -> FALSE | AJ42: =ISNUMBER(MATCH(U42&V42,FSData!$Z$7:$Z$95,0)) -> TRUE | AK42: =OR(ISNUMBER(SEARCH("Total",U42,1)),ISNUMBER(SEARCH("Increase (decrease)",U42,1)),ISNUMBER(SEARCH("Operating Activities",U42,1)),ISNUMBER(SEARCH("Investing Activities",U42,1)),ISNUMBER(SEARCH("Financing Activities",U42,1)),ISNUMBER(SEARCH("Cash @",U42,1)),ISNUMBER(SEARCH("Net Income",U42,1)),ISNUMBER(SEARCH("Cash Flow from Operations",U42,1))) -> FALSE | AL42: =AND(NOT(AJ42),NOT(AK42)) -> FALSE | AN42: =ISNUMBER(MATCH(Y42&Z42,FSData!$AB$7:$AB$95,0)) -> FALSE | AO42: =OR(ISNUMBER(SEARCH("Total",Y42,1))) -> TRUE | AP42: =AND(NOT(AN42),NOT(AO42)) -> FALSE | AR42: {=_xlfn.IFS(ISNUMBER(SEARCH("Balance",C42,1)),"MasterData!O56#",ISNUMBER(SEARCH("Income St",C42,1)),"MasterData!O116#",ISNUMBER(SEARCH("Shareholders",C42,1)),"D115#",ISNUMBER(SEARCH("Cash Flow",C42,1)),"E115#",ISNUMBER(SEARCH("Noncash",C42,1)),"C139#",ISNUMBER(SEARCH("Comprehensive",C42,1)),"E145",ISNUMBER(SEARCH("Reconciliation",C42,1)),"D137#")} -> #N/A | AS42: {=_xlfn.IFS(ISNUMBER(SEARCH("Balance",C42,1)),"AX25:AX29",ISNUMBER(SEARCH("Income St",C42,1)),"AY25:AY28",ISNUMBER(SEARCH("Shareholders",C42,1)),"EquityUsed",ISNUMBER(SEARCH("Cash Flow",C42,1)),"BA25:BA27",ISNUMBER(SEARCH("Noncash",C42,1)),"AZ25",ISNUMBER(SEARCH("Comprehensive",C42,1)),"AZ25",ISNUMBER(SEARCH("Reconciliation",C42,1)),"BB25:BB26")} -> #N/A
E43: Inventories | H43: =_xlfn.TEXTJOIN(6,1,FSBuilder[[#This Row],[Statement]:[Account or Explanation]]) -> Inventories | AC43: =ISNUMBER(MATCH(N43&O43,FSData!$V$7:$V$95,0)) -> TRUE | AD43: =OR(ISNUMBER(SEARCH("Total",N43,1)),ISNUMBER(SEARCH("Net Income",N43,1))) -> FALSE | AE43: =AND(NOT(AC43),NOT(AD43)) -> FALSE | AF43: =ISNUMBER(MATCH(R43&S43,FSData!$X$7:$X$95,0)) -> TRUE | AG43: =OR(ISNUMBER(SEARCH("Total",R43,1)),ISNUMBER(SEARCH("Balance",R43,1))) -> FALSE | AH43: =AND(NOT(AF43),NOT(AG43)) -> FALSE | AJ43: =ISNUMBER(MATCH(U43&V43,FSData!$Z$7:$Z$95,0)) -> TRUE | AK43: =OR(ISNUMBER(SEARCH("Total",U43,1)),ISNUMBER(SEARCH("Increase (decrease)",U43,1)),ISNUMBER(SEARCH("Operating Activities",U43,1)),ISNUMBER(SEARCH("Investing Activities",U43,1)),ISNUMBER(SEARCH("Financing Activities",U43,1)),ISNUMBER(SEARCH("Cash @",U43,1)),ISNUMBER(SEARCH("Net Income",U43,1)),ISNUMBER(SEARCH("Cash Flow from Operations",U43,1))) -> FALSE | AL43: =AND(NOT(AJ43),NOT(AK43)) -> FALSE | AN43: =ISNUMBER(MATCH(Y43&Z43,FSData!$AB$7:$AB$95,0)) -> TRUE | AO43: =OR(ISNUMBER(SEARCH("Total",Y43,1))) -> FALSE | AP43: =AND(NOT(AN43),NOT(AO43)) -> FALSE | AR43: {=_xlfn.IFS(ISNUMBER(SEARCH("Balance",C43,1)),"MasterData!O56#",ISNUMBER(SEARCH("Income St",C43,1)),"MasterData!O116#",ISNUMBER(SEARCH("Shareholders",C43,1)),"D115#",ISNUMBER(SEARCH("Cash Flow",C43,1)),"E115#",ISNUMBER(SEARCH("Noncash",C43,1)),"C139#",ISNUMBER(SEARCH("Comprehensive",C43,1)),"E145",ISNUMBER(SEARCH("Reconciliation",C43,1)),"D137#")} -> #N/A | AS43: {=_xlfn.IFS(ISNUMBER(SEARCH("Balance",C43,1)),"AX25:AX29",ISNUMBER(SEARCH("Income St",C43,1)),"AY25:AY28",ISNUMBER(SEARCH("Shareholders",C43,1)),"EquityUsed",ISNUMBER(SEARCH("Cash Flow",C43,1)),"BA25:BA27",ISNUMBER(SEARCH("Noncash",C43,1)),"AZ25",ISNUMBER(SEARCH("Comprehensive",C43,1)),"AZ25",ISNUMBER(SEARCH("Reconciliation",C43,1)),"BB25:BB26")} -> #N/A
E44: Common Stock | H44: =_xlfn.TEXTJOIN(6,1,FSBuilder[[#This Row],[Statement]:[Account or Explanation]]) -> Common Stock | AC44: =ISNUMBER(MATCH(N44&O44,FSData!$V$7:$V$95,0)) -> TRUE | AD44: =OR(ISNUMBER(SEARCH("Total",N44,1)),ISNUMBER(SEARCH("Net Income",N44,1))) -> FALSE | AE44: =AND(NOT(AC44),NOT(AD44)) -> FALSE | AF44: =ISNUMBER(MATCH(R44&S44,FSData!$X$7:$X$95,0)) -> TRUE | AG44: =OR(ISNUMBER(SEARCH("Total",R44,1)),ISNUMBER(SEARCH("Balance",R44,1))) -> FALSE | AH44: =AND(NOT(AF44),NOT(AG44)) -> FALSE | AJ44: =ISNUMBER(MATCH(U44&V44,FSData!$Z$7:$Z$95,0)) -> TRUE | AK44: =OR(ISNUMBER(SEARCH("Total",U44,1)),ISNUMBER(SEARCH("Increase (decrease)",U44,1)),ISNUMBER(SEARCH("Operating Activities",U44,1)),ISNUMBER(SEARCH("Investing Activities",U44,1)),ISNUMBER(SEARCH("Financing Activities",U44,1)),ISNUMBER(SEARCH("Cash @",U44,1)),ISNUMBER(SEARCH("Net Income",U44,1)),ISNUMBER(SEARCH("Cash Flow from Operations",U44,1))) -> FALSE | AL44: =AND(NOT(AJ44),NOT(AK44)) -> FALSE | AN44: =ISNUMBER(MATCH(Y44&Z44,FSData!$AB$7:$AB$95,0)) -> TRUE | AO44: =OR(ISNUMBER(SEARCH("Total",Y44,1))) -> FALSE | AP44: =AND(NOT(AN44),NOT(AO44)) -> FALSE | AR44: {=_xlfn.IFS(ISNUMBER(SEARCH("Balance",C44,1)),"MasterData!O56#",ISNUMBER(SEARCH("Income St",C44,1)),"MasterData!O116#",ISNUMBER(SEARCH("Shareholders",C44,1)),"D115#",ISNUMBER(SEARCH("Cash Flow",C44,1)),"E115#",ISNUMBER(SEARCH("Noncash",C44,1)),"C139#",ISNUMBER(SEARCH("Comprehensive",C44,1)),"E145",ISNUMBER(SEARCH("Reconciliation",C44,1)),"D137#")} -> #N/A | AS44: {=_xlfn.IFS(ISNUMBER(SEARCH("Balance",C44,1)),"AX25:AX29",ISNUMBER(SEARCH("Income St",C44,1)),"AY25:AY28",ISNUMBER(SEARCH("Shareholders",C44,1)),"EquityUsed",ISNUMBER(SEARCH("Cash Flow",C44,1)),"BA25:BA27",ISNUMBER(SEARCH("Noncash",C44,1)),"AZ25",ISNUMBER(SEARCH("Comprehensive",C44,1)),"AZ25",ISNUMBER(SEARCH("Reconciliation",C44,1)),"BB25:BB26")} -> #N/A
E45: Retained Earnings | H45: =_xlfn.TEXTJOIN(6,1,FSBuilder[[#This Row],[Statement]:[Account or Explanation]]) -> Retained Earnings | AC45: =ISNUMBER(MATCH(N45&O45,FSData!$V$7:$V$95,0)) -> TRUE | AD45: =OR(ISNUMBER(SEARCH("Total",N45,1)),ISNUMBER(SEARCH("Net Income",N45,1))) -> FALSE | AE45: =AND(NOT(AC45),NOT(AD45)) -> FALSE | AF45: =ISNUMBER(MATCH(R45&S45,FSData!$X$7:$X$95,0)) -> TRUE | AG45: =OR(ISNUMBER(SEARCH("Total",R45,1)),ISNUMBER(SEARCH("Balance",R45,1))) -> FALSE | AH45: =AND(NOT(AF45),NOT(AG45)) -> FALSE | AJ45: =ISNUMBER(MATCH(U45&V45,FSData!$Z$7:$Z$95,0)) -> TRUE | AK45: =OR(ISNUMBER(SEARCH("Total",U45,1)),ISNUMBER(SEARCH("Increase (decrease)",U45,1)),ISNUMBER(SEARCH("Operating Activities",U45,1)),ISNUMBER(SEARCH("Investing Activities",U45,1)),ISNUMBER(SEARCH("Financing Activities",U45,1)),ISNUMBER(SEARCH("Cash @",U45,1)),ISNUMBER(SEARCH("Net Income",U45,1)),ISNUMBER(SEARCH("Cash Flow from Operations",U45,1))) -> FALSE | AL45: =AND(NOT(AJ45),NOT(AK45)) -> FALSE | AN45: =ISNUMBER(MATCH(Y45&Z45,FSData!$AB$7:$AB$95,0)) -> TRUE | AO45: =OR(ISNUMBER(SEARCH("Total",Y45,1))) -> FALSE | AP45: =AND(NOT(AN45),NOT(AO45)) -> FALSE | AR45: {=_xlfn.IFS(ISNUMBER(SEARCH("Balance",C45,1)),"MasterData!O56#",ISNUMBER(SEARCH("Income St",C45,1)),"MasterData!O116#",ISNUMBER(SEARCH("Shareholders",C45,1)),"D115#",ISNUMBER(SEARCH("Cash Flow",C45,1)),"E115#",ISNUMBER(SEARCH("Noncash",C45,1)),"C139#",ISNUMBER(SEARCH("Comprehensive",C45,1)),"E145",ISNUMBER(SEARCH("Reconciliation",C45,1)),"D137#")} -> #N/A | AS45: {=_xlfn.IFS(ISNUMBER(SEARCH("Balance",C45,1)),"AX25:AX29",ISNUMBER(SEARCH("Income St",C45,1)),"AY25:AY28",ISNUMBER(SEARCH("Shareholders",C45,1)),"EquityUsed",ISNUMBER(SEARCH("Cash Flow",C45,1)),"BA25:BA27",ISNUMBER(SEARCH("Noncash",C45,1)),"AZ25",ISNUMBER(SEARCH("Comprehensive",C45,1)),"AZ25",ISNUMBER(SEARCH("Reconciliation",C45,1)),"BB25:BB26")} -> #N/A
E46: Interest Payable | H46: =_xlfn.TEXTJOIN(6,1,FSBuilder[[#This Row],[Statement]:[Account or Explanation]]) -> Interest Payable | AC46: =ISNUMBER(MATCH(N46&O46,FSData!$V$7:$V$95,0)) -> TRUE | AD46: =OR(ISNUMBER(SEARCH("Total",N46,1)),ISNUMBER(SEARCH("Net Income",N46,1))) -> FALSE | AE46: =AND(NOT(AC46),NOT(AD46)) -> FALSE | AF46: =ISNUMBER(MATCH(R46&S46,FSData!$X$7:$X$95,0)) -> TRUE | AG46: =OR(ISNUMBER(SEARCH("Total",R46,1)),ISNUMBER(SEARCH("Balance",R46,1))) -> FALSE | AH46: =AND(NOT(AF46),NOT(AG46)) -> FALSE | AJ46: =ISNUMBER(MATCH(U46&V46,FSData!$Z$7:$Z$95,0)) -> TRUE | AK46: =OR(ISNUMBER(SEARCH("Total",U46,1)),ISNUMBER(SEARCH("Increase (decrease)",U46,1)),ISNUMBER(SEARCH("Operating Activities",U46,1)),ISNUMBER(SEARCH("Investing Activities",U46,1)),ISNUMBER(SEARCH("Financing Activities",U46,1)),ISNUMBER(SEARCH("Cash @",U46,1)),ISNUMBER(SEARCH("Net Income",U46,1)),ISNUMBER(SEARCH("Cash Flow from Operations",U46,1))) -> FALSE | AL46: =AND(NOT(AJ46),NOT(AK46)) -> FALSE | AN46: =ISNUMBER(MATCH(Y46&Z46,FSData!$AB$7:$AB$95,0)) -> TRUE | AO46: =OR(ISNUMBER(SEARCH("Total",Y46,1))) -> FALSE | AP46: =AND(NOT(AN46),NOT(AO46)) -> FALSE | AR46: {=_xlfn.IFS(ISNUMBER(SEARCH("Balance",C46,1)),"MasterData!O56#",ISNUMBER(SEARCH("Income St",C46,1)),"MasterData!O116#",ISNUMBER(SEARCH("Shareholders",C46,1)),"D115#",ISNUMBER(SEARCH("Cash Flow",C46,1)),"E115#",ISNUMBER(SEARCH("Noncash",C46,1)),"C139#",ISNUMBER(SEARCH("Comprehensive",C46,1)),"E145",ISNUMBER(SEARCH("Reconciliation",C46,1)),"D137#")} -> #N/A | AS46: {=_xlfn.IFS(ISNUMBER(SEARCH("Balance",C46,1)),"AX25:AX29",ISNUMBER(SEARCH("Income St",C46,1)),"AY25:AY28",ISNUMBER(SEARCH("Shareholders",C46,1)),"EquityUsed",ISNUMBER(SEARCH("Cash Flow",C46,1)),"BA25:BA27",ISNUMBER(SEARCH("Noncash",C46,1)),"AZ25",ISNUMBER(SEARCH("Comprehensive",C46,1)),"AZ25",ISNUMBER(SEARCH("Reconciliation",C46,1)),"BB25:BB26")} -> #N/A
E47: Dividends Payable | H47: =_xlfn.TEXTJOIN(6,1,FSBuilder[[#This Row],[Statement]:[Account or Explanation]]) -> Dividends Payable | AC47: =ISNUMBER(MATCH(N47&O47,FSData!$V$7:$V$95,0)) -> TRUE | AD47: =OR(ISNUMBER(SEARCH("Total",N47,1)),ISNUMBER(SEARCH("Net Income",N47,1))) -> FALSE | AE47: =AND(NOT(AC47),NOT(AD47)) -> FALSE | AF47: =ISNUMBER(MATCH(R47&S47,FSData!$X$7:$X$95,0)) -> TRUE | AG47: =OR(ISNUMBER(SEARCH("Total",R47,1)),ISNUMBER(SEARCH("Balance",R47,1))) -> FALSE | AH47: =AND(NOT(AF47),NOT(AG47)) -> FALSE | AJ47: =ISNUMBER(MATCH(U47&V47,FSData!$Z$7:$Z$95,0)) -> TRUE | AK47: =OR(ISNUMBER(SEARCH("Total",U47,1)),ISNUMBER(SEARCH("Increase (decrease)",U47,1)),ISNUMBER(SEARCH("Operating Activities",U47,1)),ISNUMBER(SEARCH("Investing Activities",U47,1)),ISNUMBER(SEARCH("Financing Activities",U47,1)),ISNUMBER(SEARCH("Cash @",U47,1)),ISNUMBER(SEARCH("Net Income",U47,1)),ISNUMBER(SEARCH("Cash Flow from Operations",U47,1))) -> FALSE | AL47: =AND(NOT(AJ47),NOT(AK47)) -> FALSE | AN47: =ISNUMBER(MATCH(Y47&Z47,FSData!$AB$7:$AB$95,0)) -> TRUE | AO47: =OR(ISNUMBER(SEARCH("Total",Y47,1))) -> FALSE | AP47: =AND(NOT(AN47),NOT(AO47)) -> FALSE | AR47: {=_xlfn.IFS(ISNUMBER(SEARCH("Balance",C47,1)),"MasterData!O56#",ISNUMBER(SEARCH("Income St",C47,1)),"MasterData!O116#",ISNUMBER(SEARCH("Shareholders",C47,1)),"D115#",ISNUMBER(SEARCH("Cash Flow",C47,1)),"E115#",ISNUMBER(SEARCH("Noncash",C47,1)),"C139#",ISNUMBER(SEARCH("Comprehensive",C47,1)),"E145",ISNUMBER(SEARCH("Reconciliation",C47,1)),"D137#")} -> #N/A | AS47: {=_xlfn.IFS(ISNUMBER(SEARCH("Balance",C47,1)),"AX25:AX29",ISNUMBER(SEARCH("Income St",C47,1)),"AY25:AY28",ISNUMBER(SEARCH("Shareholders",C47,1)),"EquityUsed",ISNUMBER(SEARCH("Cash Flow",C47,1)),"BA25:BA27",ISNUMBER(SEARCH("Noncash",C47,1)),"AZ25",ISNUMBER(SEARCH("Comprehensive",C47,1)),"AZ25",ISNUMBER(SEARCH("Reconciliation",C47,1)),"BB25:BB26")} -> #N/A
E48: Property, Plant & Equipment | H48: =_xlfn.TEXTJOIN(6,1,FSBuilder[[#This Row],[Statement]:[Account or Explanation]]) -> Property, Plant & Equipment | AC48: =ISNUMBER(MATCH(N48&O48,FSData!$V$7:$V$95,0)) -> TRUE | AD48: =OR(ISNUMBER(SEARCH("Total",N48,1)),ISNUMBER(SEARCH("Net Income",N48,1))) -> FALSE | AE48: =AND(NOT(AC48),NOT(AD48)) -> FALSE | AF48: =ISNUMBER(MATCH(R48&S48,FSData!$X$7:$X$95,0)) -> TRUE | AG48: =OR(ISNUMBER(SEARCH("Total",R48,1)),ISNUMBER(SEARCH("Balance",R48,1))) -> FALSE | AH48: =AND(NOT(AF48),NOT(AG48)) -> FALSE | AJ48: =ISNUMBER(MATCH(U48&V48,FSData!$Z$7:$Z$95,0)) -> TRUE | AK48: =OR(ISNUMBER(SEARCH("Total",U48,1)),ISNUMBER(SEARCH("Increase (decrease)",U48,1)),ISNUMBER(SEARCH("Operating Activities",U48,1)),ISNUMBER(SEARCH("Investing Activities",U48,1)),ISNUMBER(SEARCH("Financing Activities",U48,1)),ISNUMBER(SEARCH("Cash @",U48,1)),ISNUMBER(SEARCH("Net Income",U48,1)),ISNUMBER(SEARCH("Cash Flow from Operations",U48,1))) -> FALSE | AL48: =AND(NOT(AJ48),NOT(AK48)) -> FALSE | AN48: =ISNUMBER(MATCH(Y48&Z48,FSData!$AB$7:$AB$95,0)) -> TRUE | AO48: =OR(ISNUMBER(SEARCH("Total",Y48,1))) -> FALSE | AP48: =AND(NOT(AN48),NOT(AO48)) -> FALSE | AR48: {=_xlfn.IFS(ISNUMBER(SEARCH("Balance",C48,1)),"MasterData!O56#",ISNUMBER(SEARCH("Income St",C48,1)),"MasterData!O116#",ISNUMBER(SEARCH("Shareholders",C48,1)),"D115#",ISNUMBER(SEARCH("Cash Flow",C48,1)),"E115#",ISNUMBER(SEARCH("Noncash",C48,1)),"C139#",ISNUMBER(SEARCH("Comprehensive",C48,1)),"E145",ISNUMBER(SEARCH("Reconciliation",C48,1)),"D137#")} -> #N/A | AS48: {=_xlfn.IFS(ISNUMBER(SEARCH("Balance",C48,1)),"AX25:AX29",ISNUMBER(SEARCH("Income St",C48,1)),"AY25:AY28",ISNUMBER(SEARCH("Shareholders",C48,1)),"EquityUsed",ISNUMBER(SEARCH("Cash Flow",C48,1)),"BA25:BA27",ISNUMBER(SEARCH("Noncash",C48,1)),"AZ25",ISNUMBER(SEARCH("Comprehensive",C48,1)),"AZ25",ISNUMBER(SEARCH("Reconciliation",C48,1)),"BB25:BB26")} -> #N/A
E49: Accumulated Depreciation | H49: =_xlfn.TEXTJOIN(6,1,FSBuilder[[#This Row],[Statement]:[Account or Explanation]]) -> Accumulated Depreciation | AC49: =ISNUMBER(MATCH(N49&O49,FSData!$V$7:$V$95,0)) -> TRUE | AD49: =OR(ISNUMBER(SEARCH("Total",N49,1)),ISNUMBER(SEARCH("Net Income",N49,1))) -> FALSE | AE49: =AND(NOT(AC49),NOT(AD49)) -> FALSE | AF49: =ISNUMBER(MATCH(R49&S49,FSData!$X$7:$X$95,0)) -> TRUE | AG49: =OR(ISNUMBER(SEARCH("Total",R49,1)),ISNUMBER(SEARCH("Balance",R49,1))) -> FALSE | AH49: =AND(NOT(AF49),NOT(AG49)) -> FALSE | AJ49: =ISNUMBER(MATCH(U49&V49,FSData!$Z$7:$Z$95,0)) -> TRUE | AK49: =OR(ISNUMBER(SEARCH("Total",U49,1)),ISNUMBER(SEARCH("Increase (decrease)",U49,1)),ISNUMBER(SEARCH("Operating Activities",U49,1)),ISNUMBER(SEARCH("Investing Activities",U49,1)),ISNUMBER(SEARCH("Financing Activities",U49,1)),ISNUMBER(SEARCH("Cash @",U49,1)),ISNUMBER(SEARCH("Net Income",U49,1)),ISNUMBER(SEARCH("Cash Flow from Operations",U49,1))) -> FALSE | AL49: =AND(NOT(AJ49),NOT(AK49)) -> FALSE | AN49: =ISNUMBER(MATCH(Y49&Z49,FSData!$AB$7:$AB$95,0)) -> TRUE | AO49: =OR(ISNUMBER(SEARCH("Total",Y49,1))) -> FALSE | AP49: =AND(NOT(AN49),NOT(AO49)) -> FALSE | AR49: {=_xlfn.IFS(ISNUMBER(SEARCH("Balance",C49,1)),"MasterData!O56#",ISNUMBER(SEARCH("Income St",C49,1)),"MasterData!O116#",ISNUMBER(SEARCH("Shareholders",C49,1)),"D115#",ISNUMBER(SEARCH("Cash Flow",C49,1)),"E115#",ISNUMBER(SEARCH("Noncash",C49,1)),"C139#",ISNUMBER(SEARCH("Comprehensive",C49,1)),"E145",ISNUMBER(SEARCH("Reconciliation",C49,1)),"D137#")} -> #N/A | AS49: {=_xlfn.IFS(ISNUMBER(SEARCH("Balance",C49,1)),"AX25:AX29",ISNUMBER(SEARCH("Income St",C49,1)),"AY25:AY28",ISNUMBER(SEARCH("Shareholders",C49,1)),"EquityUsed",ISNUMBER(SEARCH("Cash Flow",C49,1)),"BA25:BA27",ISNUMBER(SEARCH("Noncash",C49,1)),"AZ25",ISNUMBER(SEARCH("Comprehensive",C49,1)),"AZ25",ISNUMBER(SEARCH("Reconciliation",C49,1)),"BB25:BB26")} -> #N/A
E50: Issued common stock | H50: =_xlfn.TEXTJOIN(6,1,FSBuilder[[#This Row],[Statement]:[Account or Explanation]]) -> Issued common stock | AC50: =ISNUMBER(MATCH(N50&O50,FSData!$V$7:$V$95,0)) -> TRUE | AD50: =OR(ISNUMBER(SEARCH("Total",N50,1)),ISNUMBER(SEARCH("Net Income",N50,1))) -> FALSE | AE50: =AND(NOT(AC50),NOT(AD50)) -> FALSE | AF50: =ISNUMBER(MATCH(R50&S50,FSData!$X$7:$X$95,0)) -> TRUE | AG50: =OR(ISNUMBER(SEARCH("Total",R50,1)),ISNUMBER(SEARCH("Balance",R50,1))) -> FALSE | AH50: =AND(NOT(AF50),NOT(AG50)) -> FALSE | AJ50: =ISNUMBER(MATCH(U50&V50,FSData!$Z$7:$Z$95,0)) -> TRUE | AK50: =OR(ISNUMBER(SEARCH("Total",U50,1)),ISNUMBER(SEARCH("Increase (decrease)",U50,1)),ISNUMBER(SEARCH("Operating Activities",U50,1)),ISNUMBER(SEARCH("Investing Activities",U50,1)),ISNUMBER(SEARCH("Financing Activities",U50,1)),ISNUMBER(SEARCH("Cash @",U50,1)),ISNUMBER(SEARCH("Net Income",U50,1)),ISNUMBER(SEARCH("Cash Flow from Operations",U50,1))) -> FALSE | AL50: =AND(NOT(AJ50),NOT(AK50)) -> FALSE | AN50: =ISNUMBER(MATCH(Y50&Z50,FSData!$AB$7:$AB$95,0)) -> TRUE | AO50: =OR(ISNUMBER(SEARCH("Total",Y50,1))) -> FALSE | AP50: =AND(NOT(AN50),NOT(AO50)) -> FALSE | AR50: {=_xlfn.IFS(ISNUMBER(SEARCH("Balance",C50,1)),"MasterData!O56#",ISNUMBER(SEARCH("Income St",C50,1)),"MasterData!O116#",ISNUMBER(SEARCH("Shareholders",C50,1)),"D115#",ISNUMBER(SEARCH("Cash Flow",C50,1)),"E115#",ISNUMBER(SEARCH("Noncash",C50,1)),"C139#",ISNUMBER(SEARCH("Comprehensive",C50,1)),"E145",ISNUMBER(SEARCH("Reconciliation",C50,1)),"D137#")} -> #N/A | AS50: {=_xlfn.IFS(ISNUMBER(SEARCH("Balance",C50,1)),"AX25:AX29",ISNUMBER(SEARCH("Income St",C50,1)),"AY25:AY28",ISNUMBER(SEARCH("Shareholders",C50,1)),"EquityUsed",ISNUMBER(SEARCH("Cash Flow",C50,1)),"BA25:BA27",ISNUMBER(SEARCH("Noncash",C50,1)),"AZ25",ISNUMBER(SEARCH("Comprehensive",C50,1)),"AZ25",ISNUMBER(SEARCH("Reconciliation",C50,1)),"BB25:BB26")} -> #N/A
E51: Declared Dividends | H51: =_xlfn.TEXTJOIN(6,1,FSBuilder[[#This Row],[Statement]:[Account or Explanation]]) -> Declared Dividends | AC51: =ISNUMBER(MATCH(N51&O51,FSData!$V$7:$V$95,0)) -> TRUE | AD51: =OR(ISNUMBER(SEARCH("Total",N51,1)),ISNUMBER(SEARCH("Net Income",N51,1))) -> FALSE | AE51: =AND(NOT(AC51),NOT(AD51)) -> FALSE | AF51: =ISNUMBER(MATCH(R51&S51,FSData!$X$7:$X$95,0)) -> TRUE | AG51: =OR(ISNUMBER(SEARCH("Total",R51,1)),ISNUMBER(SEARCH("Balance",R51,1))) -> FALSE | AH51: =AND(NOT(AF51),NOT(AG51)) -> FALSE | AJ51: =ISNUMBER(MATCH(U51&V51,FSData!$Z$7:$Z$95,0)) -> TRUE | AK51: =OR(ISNUMBER(SEARCH("Total",U51,1)),ISNUMBER(SEARCH("Increase (decrease)",U51,1)),ISNUMBER(SEARCH("Operating Activities",U51,1)),ISNUMBER(SEARCH("Investing Activities",U51,1)),ISNUMBER(SEARCH("Financing Activities",U51,1)),ISNUMBER(SEARCH("Cash @",U51,1)),ISNUMBER(SEARCH("Net Income",U51,1)),ISNUMBER(SEARCH("Cash Flow from Operations",U51,1))) -> FALSE | AL51: =AND(NOT(AJ51),NOT(AK51)) -> FALSE | AN51: =ISNUMBER(MATCH(Y51&Z51,FSData!$AB$7:$AB$95,0)) -> TRUE | AO51: =OR(ISNUMBER(SEARCH("Total",Y51,1))) -> FALSE | AP51: =AND(NOT(AN51),NOT(AO51)) -> FALSE | AR51: {=_xlfn.IFS(ISNUMBER(SEARCH("Balance",C51,1)),"MasterData!O56#",ISNUMBER(SEARCH("Income St",C51,1)),"MasterData!O116#",ISNUMBER(SEARCH("Shareholders",C51,1)),"D115#",ISNUMBER(SEARCH("Cash Flow",C51,1)),"E115#",ISNUMBER(SEARCH("Noncash",C51,1)),"C139#",ISNUMBER(SEARCH("Comprehensive",C51,1)),"E145",ISNUMBER(SEARCH("Reconciliation",C51,1)),"D137#")} -> #N/A | AS51: {=_xlfn.IFS(ISNUMBER(SEARCH("Balance",C51,1)),"AX25:AX29",ISNUMBER(SEARCH("Income St",C51,1)),"AY25:AY28",ISNUMBER(SEARCH("Shareholders",C51,1)),"EquityUsed",ISNUMBER(SEARCH("Cash Flow",C51,1)),"BA25:BA27",ISNUMBER(SEARCH("Noncash",C51,1)),"AZ25",ISNUMBER(SEARCH("Comprehensive",C51,1)),"AZ25",ISNUMBER(SEARCH("Reconciliation",C51,1)),"BB25:BB26")} -> #N/A
E52: Net Income (Loss) | H52: =_xlfn.TEXTJOIN(6,1,FSBuilder[[#This Row],[Statement]:[Account or Explanation]]) -> Net Income (Loss) | AC52: =ISNUMBER(MATCH(N52&O52,FSData!$V$7:$V$95,0)) -> TRUE | AD52: =OR(ISNUMBER(SEARCH("Total",N52,1)),ISNUMBER(SEARCH("Net Income",N52,1))) -> FALSE | AE52: =AND(NOT(AC52),NOT(AD52)) -> FALSE | AF52: =ISNUMBER(MATCH(R52&S52,FSData!$X$7:$X$95,0)) -> TRUE | AG52: =OR(ISNUMBER(SEARCH("Total",R52,1)),ISNUMBER(SEARCH("Balance",R52,1))) -> FALSE | AH52: =AND(NOT(AF52),NOT(AG52)) -> FALSE | AJ52: =ISNUMBER(MATCH(U52&V52,FSData!$Z$7:$Z$95,0)) -> TRUE | AK52: =OR(ISNUMBER(SEARCH("Total",U52,1)),ISNUMBER(SEARCH("Increase (decrease)",U52,1)),ISNUMBER(SEARCH("Operating Activities",U52,1)),ISNUMBER(SEARCH("Investing Activities",U52,1)),ISNUMBER(SEARCH("Financing Activities",U52,1)),ISNUMBER(SEARCH("Cash @",U52,1)),ISNUMBER(SEARCH("Net Income",U52,1)),ISNUMBER(SEARCH("Cash Flow from Operations",U52,1))) -> FALSE | AL52: =AND(NOT(AJ52),NOT(AK52)) -> FALSE | AN52: =ISNUMBER(MATCH(Y52&Z52,FSData!$AB$7:$AB$95,0)) -> TRUE | AO52: =OR(ISNUMBER(SEARCH("Total",Y52,1))) -> FALSE | AP52: =AND(NOT(AN52),NOT(AO52)) -> FALSE | AR52: {=_xlfn.IFS(ISNUMBER(SEARCH("Balance",C52,1)),"MasterData!O56#",ISNUMBER(SEARCH("Income St",C52,1)),"MasterData!O116#",ISNUMBER(SEARCH("Shareholders",C52,1)),"D115#",ISNUMBER(SEARCH("Cash Flow",C52,1)),"E115#",ISNUMBER(SEARCH("Noncash",C52,1)),"C139#",ISNUMBER(SEARCH("Comprehensive",C52,1)),"E145",ISNUMBER(SEARCH("Reconciliation",C52,1)),"D137#")} -> #N/A | AS52: {=_xlfn.IFS(ISNUMBER(SEARCH("Balance",C52,1)),"AX25:AX29",ISNUMBER(SEARCH("Income St",C52,1)),"AY25:AY28",ISNUMBER(SEARCH("Shareholders",C52,1)),"EquityUsed",ISNUMBER(SEARCH("Cash Flow",C52,1)),"BA25:BA27",ISNUMBER(SEARCH("Noncash",C52,1)),"AZ25",ISNUMBER(SEARCH("Comprehensive",C52,1)),"AZ25",ISNUMBER(SEARCH("Reconciliation",C52,1)),"BB25:BB26")} -> #N/A
H53: =_xlfn.TEXTJOIN(6,1,FSBuilder[[#This Row],[Statement]:[Account or Explanation]]) | AC53: =ISNUMBER(MATCH(N53&O53,FSData!$V$7:$V$95,0)) -> TRUE | AD53: =OR(ISNUMBER(SEARCH("Total",N53,1)),ISNUMBER(SEARCH("Net Income",N53,1))) -> FALSE | AE53: =AND(NOT(AC53),NOT(AD53)) -> FALSE | AF53: =ISNUMBER(MATCH(R53&S53,FSData!$X$7:$X$95,0)) -> TRUE | AG53: =OR(ISNUMBER(SEARCH("Total",R53,1)),ISNUMBER(SEARCH("Balance",R53,1))) -> FALSE | AH53: =AND(NOT(AF53),NOT(AG53)) -> FALSE | AJ53: =ISNUMBER(MATCH(U53&V53,FSData!$Z$7:$Z$95,0)) -> TRUE | AK53: =OR(ISNUMBER(SEARCH("Total",U53,1)),ISNUMBER(SEARCH("Increase (decrease)",U53,1)),ISNUMBER(SEARCH("Operating Activities",U53,1)),ISNUMBER(SEARCH("Investing Activities",U53,1)),ISNUMBER(SEARCH("Financing Activities",U53,1)),ISNUMBER(SEARCH("Cash @",U53,1)),ISNUMBER(SEARCH("Net Income",U53,1)),ISNUMBER(SEARCH("Cash Flow from Operations",U53,1))) -> FALSE | AL53: =AND(NOT(AJ53),NOT(AK53)) -> FALSE | AN53: =ISNUMBER(MATCH(Y53&Z53,FSData!$AB$7:$AB$95,0)) -> TRUE | AO53: =OR(ISNUMBER(SEARCH("Total",Y53,1))) -> FALSE | AP53: =AND(NOT(AN53),NOT(AO53)) -> FALSE | AR53: {=_xlfn.IFS(ISNUMBER(SEARCH("Balance",C53,1)),"MasterData!O56#",ISNUMBER(SEARCH("Income St",C53,1)),"MasterData!O116#",ISNUMBER(SEARCH("Shareholders",C53,1)),"D115#",ISNUMBER(SEARCH("Cash Flow",C53,1)),"E115#",ISNUMBER(SEARCH("Noncash",C53,1)),"C139#",ISNUMBER(SEARCH("Comprehensive",C53,1)),"E145",ISNUMBER(SEARCH("Reconciliation",C53,1)),"D137#")} -> #N/A | AS53: {=_xlfn.IFS(ISNUMBER(SEARCH("Balance",C53,1)),"AX25:AX29",ISNUMBER(SEARCH("Income St",C53,1)),"AY25:AY28",ISNUMBER(SEARCH("Shareholders",C53,1)),"EquityUsed",ISNUMBER(SEARCH("Cash Flow",C53,1)),"BA25:BA27",ISNUMBER(SEARCH("Noncash",C53,1)),"AZ25",ISNUMBER(SEARCH("Comprehensive",C53,1)),"AZ25",ISNUMBER(SEARCH("Reconciliation",C53,1)),"BB25:BB26")} -> #N/A
H54: =_xlfn.TEXTJOIN(6,1,FSBuilder[[#This Row],[Statement]:[Account or Explanation]]) | AC54: =ISNUMBER(MATCH(N54&O54,FSData!$V$7:$V$95,0)) -> TRUE | AD54: =OR(ISNUMBER(SEARCH("Total",N54,1)),ISNUMBER(SEARCH("Net Income",N54,1))) -> FALSE | AE54: =AND(NOT(AC54),NOT(AD54)) -> FALSE | AF54: =ISNUMBER(MATCH(R54&S54,FSData!$X$7:$X$95,0)) -> TRUE | AG54: =OR(ISNUMBER(SEARCH("Total",R54,1)),ISNUMBER(SEARCH("Balance",R54,1))) -> FALSE | AH54: =AND(NOT(AF54),NOT(AG54)) -> FALSE | AJ54: =ISNUMBER(MATCH(U54&V54,FSData!$Z$7:$Z$95,0)) -> TRUE | AK54: =OR(ISNUMBER(SEARCH("Total",U54,1)),ISNUMBER(SEARCH("Increase (decrease)",U54,1)),ISNUMBER(SEARCH("Operating Activities",U54,1)),ISNUMBER(SEARCH("Investing Activities",U54,1)),ISNUMBER(SEARCH("Financing Activities",U54,1)),ISNUMBER(SEARCH("Cash @",U54,1)),ISNUMBER(SEARCH("Net Income",U54,1)),ISNUMBER(SEARCH("Cash Flow from Operations",U54,1))) -> FALSE | AL54: =AND(NOT(AJ54),NOT(AK54)) -> FALSE | AN54: =ISNUMBER(MATCH(Y54&Z54,FSData!$AB$7:$AB$95,0)) -> TRUE | AO54: =OR(ISNUMBER(SEARCH("Total",Y54,1))) -> FALSE | AP54: =AND(NOT(AN54),NOT(AO54)) -> FALSE | AR54: {=_xlfn.IFS(ISNUMBER(SEARCH("Balance",C54,1)),"MasterData!O56#",ISNUMBER(SEARCH("Income St",C54,1)),"MasterData!O116#",ISNUMBER(SEARCH("Shareholders",C54,1)),"D115#",ISNUMBER(SEARCH("Cash Flow",C54,1)),"E115#",ISNUMBER(SEARCH("Noncash",C54,1)),"C139#",ISNUMBER(SEARCH("Comprehensive",C54,1)),"E145",ISNUMBER(SEARCH("Reconciliation",C54,1)),"D137#")} -> #N/A | AS54: {=_xlfn.IFS(ISNUMBER(SEARCH("Balance",C54,1)),"AX25:AX29",ISNUMBER(SEARCH("Income St",C54,1)),"AY25:AY28",ISNUMBER(SEARCH("Shareholders",C54,1)),"EquityUsed",ISNUMBER(SEARCH("Cash Flow",C54,1)),"BA25:BA27",ISNUMBER(SEARCH("Noncash",C54,1)),"AZ25",ISNUMBER(SEARCH("Comprehensive",C54,1)),"AZ25",ISNUMBER(SEARCH("Reconciliation",C54,1)),"BB25:BB26")} -> #N/A
H55: =_xlfn.TEXTJOIN(6,1,FSBuilder[[#This Row],[Statement]:[Account or Explanation]]) | AC55: =ISNUMBER(MATCH(N55&O55,FSData!$V$7:$V$95,0)) -> TRUE | AD55: =OR(ISNUMBER(SEARCH("Total",N55,1)),ISNUMBER(SEARCH("Net Income",N55,1))) -> FALSE | AE55: =AND(NOT(AC55),NOT(AD55)) -> FALSE | AF55: =ISNUMBER(MATCH(R55&S55,FSData!$X$7:$X$95,0)) -> TRUE | AG55: =OR(ISNUMBER(SEARCH("Total",R55,1)),ISNUMBER(SEARCH("Balance",R55,1))) -> FALSE | AH55: =AND(NOT(AF55),NOT(AG55)) -> FALSE | AJ55: =ISNUMBER(MATCH(U55&V55,FSData!$Z$7:$Z$95,0)) -> TRUE | AK55: =OR(ISNUMBER(SEARCH("Total",U55,1)),ISNUMBER(SEARCH("Increase (decrease)",U55,1)),ISNUMBER(SEARCH("Operating Activities",U55,1)),ISNUMBER(SEARCH("Investing Activities",U55,1)),ISNUMBER(SEARCH("Financing Activities",U55,1)),ISNUMBER(SEARCH("Cash @",U55,1)),ISNUMBER(SEARCH("Net Income",U55,1)),ISNUMBER(SEARCH("Cash Flow from Operations",U55,1))) -> FALSE | AL55: =AND(NOT(AJ55),NOT(AK55)) -> FALSE | AN55: =ISNUMBER(MATCH(Y55&Z55,FSData!$AB$7:$AB$95,0)) -> TRUE | AO55: =OR(ISNUMBER(SEARCH("Total",Y55,1))) -> FALSE | AP55: =AND(NOT(AN55),NOT(AO55)) -> FALSE | AR55: {=_xlfn.IFS(ISNUMBER(SEARCH("Balance",C55,1)),"MasterData!O56#",ISNUMBER(SEARCH("Income St",C55,1)),"MasterData!O116#",ISNUMBER(SEARCH("Shareholders",C55,1)),"D115#",ISNUMBER(SEARCH("Cash Flow",C55,1)),"E115#",ISNUMBER(SEARCH("Noncash",C55,1)),"C139#",ISNUMBER(SEARCH("Comprehensive",C55,1)),"E145",ISNUMBER(SEARCH("Reconciliation",C55,1)),"D137#")} -> #N/A | AS55: {=_xlfn.IFS(ISNUMBER(SEARCH("Balance",C55,1)),"AX25:AX29",ISNUMBER(SEARCH("Income St",C55,1)),"AY25:AY28",ISNUMBER(SEARCH("Shareholders",C55,1)),"EquityUsed",ISNUMBER(SEARCH("Cash Flow",C55,1)),"BA25:BA27",ISNUMBER(SEARCH("Noncash",C55,1)),"AZ25",ISNUMBER(SEARCH("Comprehensive",C55,1)),"AZ25",ISNUMBER(SEARCH("Reconciliation",C55,1)),"BB25:BB26")} -> #N/A
H56: =_xlfn.TEXTJOIN(6,1,FSBuilder[[#This Row],[Statement]:[Account or Explanation]]) | AC56: =ISNUMBER(MATCH(N56&O56,FSData!$V$7:$V$95,0)) -> TRUE | AD56: =OR(ISNUMBER(SEARCH("Total",N56,1)),ISNUMBER(SEARCH("Net Income",N56,1))) -> FALSE | AE56: =AND(NOT(AC56),NOT(AD56)) -> FALSE | AF56: =ISNUMBER(MATCH(R56&S56,FSData!$X$7:$X$95,0)) -> TRUE | AG56: =OR(ISNUMBER(SEARCH("Total",R56,1)),ISNUMBER(SEARCH("Balance",R56,1))) -> FALSE | AH56: =AND(NOT(AF56),NOT(AG56)) -> FALSE | AJ56: =ISNUMBER(MATCH(U56&V56,FSData!$Z$7:$Z$95,0)) -> TRUE | AK56: =OR(ISNUMBER(SEARCH("Total",U56,1)),ISNUMBER(SEARCH("Increase (decrease)",U56,1)),ISNUMBER(SEARCH("Operating Activities",U56,1)),ISNUMBER(SEARCH("Investing Activities",U56,1)),ISNUMBER(SEARCH("Financing Activities",U56,1)),ISNUMBER(SEARCH("Cash @",U56,1)),ISNUMBER(SEARCH("Net Income",U56,1)),ISNUMBER(SEARCH("Cash Flow from Operations",U56,1))) -> FALSE | AL56: =AND(NOT(AJ56),NOT(AK56)) -> FALSE | AN56: =ISNUMBER(MATCH(Y56&Z56,FSData!$AB$7:$AB$95,0)) -> TRUE | AO56: =OR(ISNUMBER(SEARCH("Total",Y56,1))) -> FALSE | AP56: =AND(NOT(AN56),NOT(AO56)) -> FALSE | AR56: {=_xlfn.IFS(ISNUMBER(SEARCH("Balance",C56,1)),"MasterData!O56#",ISNUMBER(SEARCH("Income St",C56,1)),"MasterData!O116#",ISNUMBER(SEARCH("Shareholders",C56,1)),"D115#",ISNUMBER(SEARCH("Cash Flow",C56,1)),"E115#",ISNUMBER(SEARCH("Noncash",C56,1)),"C139#",ISNUMBER(SEARCH("Comprehensive",C56,1)),"E145",ISNUMBER(SEARCH("Reconciliation",C56,1)),"D137#")} -> #N/A | AS56: {=_xlfn.IFS(ISNUMBER(SEARCH("Balance",C56,1)),"AX25:AX29",ISNUMBER(SEARCH("Income St",C56,1)),"AY25:AY28",ISNUMBER(SEARCH("Shareholders",C56,1)),"EquityUsed",ISNUMBER(SEARCH("Cash Flow",C56,1)),"BA25:BA27",ISNUMBER(SEARCH("Noncash",C56,1)),"AZ25",ISNUMBER(SEARCH("Comprehensive",C56,1)),"AZ25",ISNUMBER(SEARCH("Reconciliation",C56,1)),"BB25:BB26")} -> #N/A
H57: =_xlfn.TEXTJOIN(6,1,FSBuilder[[#This Row],[Statement]:[Account or Explanation]]) | AC57: =ISNUMBER(MATCH(N57&O57,FSData!$V$7:$V$95,0)) -> TRUE | AD57: =OR(ISNUMBER(SEARCH("Total",N57,1)),ISNUMBER(SEARCH("Net Income",N57,1))) -> FALSE | AE57: =AND(NOT(AC57),NOT(AD57)) -> FALSE | AF57: =ISNUMBER(MATCH(R57&S57,FSData!$X$7:$X$95,0)) -> TRUE | AG57: =OR(ISNUMBER(SEARCH("Total",R57,1)),ISNUMBER(SEARCH("Balance",R57,1))) -> FALSE | AH57: =AND(NOT(AF57),NOT(AG57)) -> FALSE | AJ57: =ISNUMBER(MATCH(U57&V57,FSData!$Z$7:$Z$95,0)) -> TRUE | AK57: =OR(ISNUMBER(SEARCH("Total",U57,1)),ISNUMBER(SEARCH("Increase (decrease)",U57,1)),ISNUMBER(SEARCH("Operating Activities",U57,1)),ISNUMBER(SEARCH("Investing Activities",U57,1)),ISNUMBER(SEARCH("Financing Activities",U57,1)),ISNUMBER(SEARCH("Cash @",U57,1)),ISNUMBER(SEARCH("Net Income",U57,1)),ISNUMBER(SEARCH("Cash Flow from Operations",U57,1))) -> FALSE | AL57: =AND(NOT(AJ57),NOT(AK57)) -> FALSE | AN57: =ISNUMBER(MATCH(Y57&Z57,FSData!$AB$7:$AB$95,0)) -> TRUE | AO57: =OR(ISNUMBER(SEARCH("Total",Y57,1))) -> FALSE | AP57: =AND(NOT(AN57),NOT(AO57)) -> FALSE | AR57: {=_xlfn.IFS(ISNUMBER(SEARCH("Balance",C57,1)),"MasterData!O56#",ISNUMBER(SEARCH("Income St",C57,1)),"MasterData!O116#",ISNUMBER(SEARCH("Shareholders",C57,1)),"D115#",ISNUMBER(SEARCH("Cash Flow",C57,1)),"E115#",ISNUMBER(SEARCH("Noncash",C57,1)),"C139#",ISNUMBER(SEARCH("Comprehensive",C57,1)),"E145",ISNUMBER(SEARCH("Reconciliation",C57,1)),"D137#")} -> #N/A | AS57: {=_xlfn.IFS(ISNUMBER(SEARCH("Balance",C57,1)),"AX25:AX29",ISNUMBER(SEARCH("Income St",C57,1)),"AY25:AY28",ISNUMBER(SEARCH("Shareholders",C57,1)),"EquityUsed",ISNUMBER(SEARCH("Cash Flow",C57,1)),"BA25:BA27",ISNUMBER(SEARCH("Noncash",C57,1)),"AZ25",ISNUMBER(SEARCH("Comprehensive",C57,1)),"AZ25",ISNUMBER(SEARCH("Reconciliation",C57,1)),"BB25:BB26")} -> #N/A
H58: =_xlfn.TEXTJOIN(6,1,FSBuilder[[#This Row],[Statement]:[Account or Explanation]]) | AC58: =ISNUMBER(MATCH(N58&O58,FSData!$V$7:$V$95,0)) -> TRUE | AD58: =OR(ISNUMBER(SEARCH("Total",N58,1)),ISNUMBER(SEARCH("Net Income",N58,1))) -> FALSE | AE58: =AND(NOT(AC58),NOT(AD58)) -> FALSE | AF58: =ISNUMBER(MATCH(R58&S58,FSData!$X$7:$X$95,0)) -> TRUE | AG58: =OR(ISNUMBER(SEARCH("Total",R58,1)),ISNUMBER(SEARCH("Balance",R58,1))) -> FALSE | AH58: =AND(NOT(AF58),NOT(AG58)) -> FALSE | AJ58: =ISNUMBER(MATCH(U58&V58,FSData!$Z$7:$Z$95,0)) -> TRUE | AK58: =OR(ISNUMBER(SEARCH("Total",U58,1)),ISNUMBER(SEARCH("Increase (decrease)",U58,1)),ISNUMBER(SEARCH("Operating Activities",U58,1)),ISNUMBER(SEARCH("Investing Activities",U58,1)),ISNUMBER(SEARCH("Financing Activities",U58,1)),ISNUMBER(SEARCH("Cash @",U58,1)),ISNUMBER(SEARCH("Net Income",U58,1)),ISNUMBER(SEARCH("Cash Flow from Operations",U58,1))) -> FALSE | AL58: =AND(NOT(AJ58),NOT(AK58)) -> FALSE | AN58: =ISNUMBER(MATCH(Y58&Z58,FSData!$AB$7:$AB$95,0)) -> TRUE | AO58: =OR(ISNUMBER(SEARCH("Total",Y58,1))) -> FALSE | AP58: =AND(NOT(AN58),NOT(AO58)) -> FALSE | AR58: {=_xlfn.IFS(ISNUMBER(SEARCH("Balance",C58,1)),"MasterData!O56#",ISNUMBER(SEARCH("Income St",C58,1)),"MasterData!O116#",ISNUMBER(SEARCH("Shareholders",C58,1)),"D115#",ISNUMBER(SEARCH("Cash Flow",C58,1)),"E115#",ISNUMBER(SEARCH("Noncash",C58,1)),"C139#",ISNUMBER(SEARCH("Comprehensive",C58,1)),"E145",ISNUMBER(SEARCH("Reconciliation",C58,1)),"D137#")} -> #N/A | AS58: {=_xlfn.IFS(ISNUMBER(SEARCH("Balance",C58,1)),"AX25:AX29",ISNUMBER(SEARCH("Income St",C58,1)),"AY25:AY28",ISNUMBER(SEARCH("Shareholders",C58,1)),"EquityUsed",ISNUMBER(SEARCH("Cash Flow",C58,1)),"BA25:BA27",ISNUMBER(SEARCH("Noncash",C58,1)),"AZ25",ISNUMBER(SEARCH("Comprehensive",C58,1)),"AZ25",ISNUMBER(SEARCH("Reconciliation",C58,1)),"BB25:BB26")} -> #N/A
H59: =_xlfn.TEXTJOIN(6,1,FSBuilder[[#This Row],[Statement]:[Account or Explanation]]) | AC59: =ISNUMBER(MATCH(N59&O59,FSData!$V$7:$V$95,0)) -> TRUE | AD59: =OR(ISNUMBER(SEARCH("Total",N59,1)),ISNUMBER(SEARCH("Net Income",N59,1))) -> FALSE | AE59: =AND(NOT(AC59),NOT(AD59)) -> FALSE | AF59: =ISNUMBER(MATCH(R59&S59,FSData!$X$7:$X$95,0)) -> TRUE | AG59: =OR(ISNUMBER(SEARCH("Total",R59,1)),ISNUMBER(SEARCH("Balance",R59,1))) -> FALSE | AH59: =AND(NOT(AF59),NOT(AG59)) -> FALSE | AJ59: =ISNUMBER(MATCH(U59&V59,FSData!$Z$7:$Z$95,0)) -> TRUE | AK59: =OR(ISNUMBER(SEARCH("Total",U59,1)),ISNUMBER(SEARCH("Increase (decrease)",U59,1)),ISNUMBER(SEARCH("Operating Activities",U59,1)),ISNUMBER(SEARCH("Investing Activities",U59,1)),ISNUMBER(SEARCH("Financing Activities",U59,1)),ISNUMBER(SEARCH("Cash @",U59,1)),ISNUMBER(SEARCH("Net Income",U59,1)),ISNUMBER(SEARCH("Cash Flow from Operations",U59,1))) -> FALSE | AL59: =AND(NOT(AJ59),NOT(AK59)) -> FALSE | AN59: =ISNUMBER(MATCH(Y59&Z59,FSData!$AB$7:$AB$95,0)) -> TRUE | AO59: =OR(ISNUMBER(SEARCH("Total",Y59,1))) -> FALSE | AP59: =AND(NOT(AN59),NOT(AO59)) -> FALSE | AR59: {=_xlfn.IFS(ISNUMBER(SEARCH("Balance",C59,1)),"MasterData!O56#",ISNUMBER(SEARCH("Income St",C59,1)),"MasterData!O116#",ISNUMBER(SEARCH("Shareholders",C59,1)),"D115#",ISNUMBER(SEARCH("Cash Flow",C59,1)),"E115#",ISNUMBER(SEARCH("Noncash",C59,1)),"C139#",ISNUMBER(SEARCH("Comprehensive",C59,1)),"E145",ISNUMBER(SEARCH("Reconciliation",C59,1)),"D137#")} -> #N/A | AS59: {=_xlfn.IFS(ISNUMBER(SEARCH("Balance",C59,1)),"AX25:AX29",ISNUMBER(SEARCH("Income St",C59,1)),"AY25:AY28",ISNUMBER(SEARCH("Shareholders",C59,1)),"EquityUsed",ISNUMBER(SEARCH("Cash Flow",C59,1)),"BA25:BA27",ISNUMBER(SEARCH("Noncash",C59,1)),"AZ25",ISNUMBER(SEARCH("Comprehensive",C59,1)),"AZ25",ISNUMBER(SEARCH("Reconciliation",C59,1)),"BB25:BB26")} -> #N/A
H60: =_xlfn.TEXTJOIN(6,1,FSBuilder[[#This Row],[Statement]:[Account or Explanation]]) | AC60: =ISNUMBER(MATCH(N60&O60,FSData!$V$7:$V$95,0)) -> TRUE | AD60: =OR(ISNUMBER(SEARCH("Total",N60,1)),ISNUMBER(SEARCH("Net Income",N60,1))) -> FALSE | AE60: =AND(NOT(AC60),NOT(AD60)) -> FALSE | AF60: =ISNUMBER(MATCH(R60&S60,FSData!$X$7:$X$95,0)) -> TRUE | AG60: =OR(ISNUMBER(SEARCH("Total",R60,1)),ISNUMBER(SEARCH("Balance",R60,1))) -> FALSE | AH60: =AND(NOT(AF60),NOT(AG60)) -> FALSE | AJ60: =ISNUMBER(MATCH(U60&V60,FSData!$Z$7:$Z$95,0)) -> TRUE | AK60: =OR(ISNUMBER(SEARCH("Total",U60,1)),ISNUMBER(SEARCH("Increase (decrease)",U60,1)),ISNUMBER(SEARCH("Operating Activities",U60,1)),ISNUMBER(SEARCH("Investing Activities",U60,1)),ISNUMBER(SEARCH("Financing Activities",U60,1)),ISNUMBER(SEARCH("Cash @",U60,1)),ISNUMBER(SEARCH("Net Income",U60,1)),ISNUMBER(SEARCH("Cash Flow from Operations",U60,1))) -> FALSE | AL60: =AND(NOT(AJ60),NOT(AK60)) -> FALSE | AN60: =ISNUMBER(MATCH(Y60&Z60,FSData!$AB$7:$AB$95,0)) -> TRUE | AO60: =OR(ISNUMBER(SEARCH("Total",Y60,1))) -> FALSE | AP60: =AND(NOT(AN60),NOT(AO60)) -> FALSE | AR60: {=_xlfn.IFS(ISNUMBER(SEARCH("Balance",C60,1)),"MasterData!O56#",ISNUMBER(SEARCH("Income St",C60,1)),"MasterData!O116#",ISNUMBER(SEARCH("Shareholders",C60,1)),"D115#",ISNUMBER(SEARCH("Cash Flow",C60,1)),"E115#",ISNUMBER(SEARCH("Noncash",C60,1)),"C139#",ISNUMBER(SEARCH("Comprehensive",C60,1)),"E145",ISNUMBER(SEARCH("Reconciliation",C60,1)),"D137#")} -> #N/A | AS60: {=_xlfn.IFS(ISNUMBER(SEARCH("Balance",C60,1)),"AX25:AX29",ISNUMBER(SEARCH("Income St",C60,1)),"AY25:AY28",ISNUMBER(SEARCH("Shareholders",C60,1)),"EquityUsed",ISNUMBER(SEARCH("Cash Flow",C60,1)),"BA25:BA27",ISNUMBER(SEARCH("Noncash",C60,1)),"AZ25",ISNUMBER(SEARCH("Comprehensive",C60,1)),"AZ25",ISNUMBER(SEARCH("Reconciliation",C60,1)),"BB25:BB26")} -> #N/A
H61: =_xlfn.TEXTJOIN(6,1,FSBuilder[[#This Row],[Statement]:[Account or Explanation]]) | AC61: =ISNUMBER(MATCH(N61&O61,FSData!$V$7:$V$95,0)) -> TRUE | AD61: =OR(ISNUMBER(SEARCH("Total",N61,1)),ISNUMBER(SEARCH("Net Income",N61,1))) -> FALSE | AE61: =AND(NOT(AC61),NOT(AD61)) -> FALSE | AF61: =ISNUMBER(MATCH(R61&S61,FSData!$X$7:$X$95,0)) -> TRUE | AG61: =OR(ISNUMBER(SEARCH("Total",R61,1)),ISNUMBER(SEARCH("Balance",R61,1))) -> FALSE | AH61: =AND(NOT(AF61),NOT(AG61)) -> FALSE | AJ61: =ISNUMBER(MATCH(U61&V61,FSData!$Z$7:$Z$95,0)) -> TRUE | AK61: =OR(ISNUMBER(SEARCH("Total",U61,1)),ISNUMBER(SEARCH("Increase (decrease)",U61,1)),ISNUMBER(SEARCH("Operating Activities",U61,1)),ISNUMBER(SEARCH("Investing Activities",U61,1)),ISNUMBER(SEARCH("Financing Activities",U61,1)),ISNUMBER(SEARCH("Cash @",U61,1)),ISNUMBER(SEARCH("Net Income",U61,1)),ISNUMBER(SEARCH("Cash Flow from Operations",U61,1))) -> FALSE | AL61: =AND(NOT(AJ61),NOT(AK61)) -> FALSE | AN61: =ISNUMBER(MATCH(Y61&Z61,FSData!$AB$7:$AB$95,0)) -> TRUE | AO61: =OR(ISNUMBER(SEARCH("Total",Y61,1))) -> FALSE | AP61: =AND(NOT(AN61),NOT(AO61)) -> FALSE | AR61: {=_xlfn.IFS(ISNUMBER(SEARCH("Balance",C61,1)),"MasterData!O56#",ISNUMBER(SEARCH("Income St",C61,1)),"MasterData!O116#",ISNUMBER(SEARCH("Shareholders",C61,1)),"D115#",ISNUMBER(SEARCH("Cash Flow",C61,1)),"E115#",ISNUMBER(SEARCH("Noncash",C61,1)),"C139#",ISNUMBER(SEARCH("Comprehensive",C61,1)),"E145",ISNUMBER(SEARCH("Reconciliation",C61,1)),"D137#")} -> #N/A | AS61: {=_xlfn.IFS(ISNUMBER(SEARCH("Balance",C61,1)),"AX25:AX29",ISNUMBER(SEARCH("Income St",C61,1)),"AY25:AY28",ISNUMBER(SEARCH("Shareholders",C61,1)),"EquityUsed",ISNUMBER(SEARCH("Cash Flow",C61,1)),"BA25:BA27",ISNUMBER(SEARCH("Noncash",C61,1)),"AZ25",ISNUMBER(SEARCH("Comprehensive",C61,1)),"AZ25",ISNUMBER(SEARCH("Reconciliation",C61,1)),"BB25:BB26")} -> #N/A
H62: =_xlfn.TEXTJOIN(6,1,FSBuilder[[#This Row],[Statement]:[Account or Explanation]]) | AC62: =ISNUMBER(MATCH(N62&O62,FSData!$V$7:$V$95,0)) -> TRUE | AD62: =OR(ISNUMBER(SEARCH("Total",N62,1)),ISNUMBER(SEARCH("Net Income",N62,1))) -> FALSE | AE62: =AND(NOT(AC62),NOT(AD62)) -> FALSE | AF62: =ISNUMBER(MATCH(R62&S62,FSData!$X$7:$X$95,0)) -> TRUE | AG62: =OR(ISNUMBER(SEARCH("Total",R62,1)),ISNUMBER(SEARCH("Balance",R62,1))) -> FALSE | AH62: =AND(NOT(AF62),NOT(AG62)) -> FALSE | AJ62: =ISNUMBER(MATCH(U62&V62,FSData!$Z$7:$Z$95,0)) -> TRUE | AK62: =OR(ISNUMBER(SEARCH("Total",U62,1)),ISNUMBER(SEARCH("Increase (decrease)",U62,1)),ISNUMBER(SEARCH("Operating Activities",U62,1)),ISNUMBER(SEARCH("Investing Activities",U62,1)),ISNUMBER(SEARCH("Financing Activities",U62,1)),ISNUMBER(SEARCH("Cash @",U62,1)),ISNUMBER(SEARCH("Net Income",U62,1)),ISNUMBER(SEARCH("Cash Flow from Operations",U62,1))) -> FALSE | AL62: =AND(NOT(AJ62),NOT(AK62)) -> FALSE | AN62: =ISNUMBER(MATCH(Y62&Z62,FSData!$AB$7:$AB$95,0)) -> TRUE | AO62: =OR(ISNUMBER(SEARCH("Total",Y62,1))) -> FALSE | AP62: =AND(NOT(AN62),NOT(AO62)) -> FALSE | AR62: {=_xlfn.IFS(ISNUMBER(SEARCH("Balance",C62,1)),"MasterData!O56#",ISNUMBER(SEARCH("Income St",C62,1)),"MasterData!O116#",ISNUMBER(SEARCH("Shareholders",C62,1)),"D115#",ISNUMBER(SEARCH("Cash Flow",C62,1)),"E115#",ISNUMBER(SEARCH("Noncash",C62,1)),"C139#",ISNUMBER(SEARCH("Comprehensive",C62,1)),"E145",ISNUMBER(SEARCH("Reconciliation",C62,1)),"D137#")} -> #N/A | AS62: {=_xlfn.IFS(ISNUMBER(SEARCH("Balance",C62,1)),"AX25:AX29",ISNUMBER(SEARCH("Income St",C62,1)),"AY25:AY28",ISNUMBER(SEARCH("Shareholders",C62,1)),"EquityUsed",ISNUMBER(SEARCH("Cash Flow",C62,1)),"BA25:BA27",ISNUMBER(SEARCH("Noncash",C62,1)),"AZ25",ISNUMBER(SEARCH("Comprehensive",C62,1)),"AZ25",ISNUMBER(SEARCH("Reconciliation",C62,1)),"BB25:BB26")} -> #N/A
H63: =_xlfn.TEXTJOIN(6,1,FSBuilder[[#This Row],[Statement]:[Account or Explanation]]) | AC63: =ISNUMBER(MATCH(N63&O63,FSData!$V$7:$V$95,0)) -> TRUE | AD63: =OR(ISNUMBER(SEARCH("Total",N63,1)),ISNUMBER(SEARCH("Net Income",N63,1))) -> FALSE | AE63: =AND(NOT(AC63),NOT(AD63)) -> FALSE | AF63: =ISNUMBER(MATCH(R63&S63,FSData!$X$7:$X$95,0)) -> TRUE | AG63: =OR(ISNUMBER(SEARCH("Total",R63,1)),ISNUMBER(SEARCH("Balance",R63,1))) -> FALSE | AH63: =AND(NOT(AF63),NOT(AG63)) -> FALSE | AJ63: =ISNUMBER(MATCH(U63&V63,FSData!$Z$7:$Z$95,0)) -> TRUE | AK63: =OR(ISNUMBER(SEARCH("Total",U63,1)),ISNUMBER(SEARCH("Increase (decrease)",U63,1)),ISNUMBER(SEARCH("Operating Activities",U63,1)),ISNUMBER(SEARCH("Investing Activities",U63,1)),ISNUMBER(SEARCH("Financing Activities",U63,1)),ISNUMBER(SEARCH("Cash @",U63,1)),ISNUMBER(SEARCH("Net Income",U63,1)),ISNUMBER(SEARCH("Cash Flow from Operations",U63,1))) -> FALSE | AL63: =AND(NOT(AJ63),NOT(AK63)) -> FALSE | AN63: =ISNUMBER(MATCH(Y63&Z63,FSData!$AB$7:$AB$95,0)) -> TRUE | AO63: =OR(ISNUMBER(SEARCH("Total",Y63,1))) -> FALSE | AP63: =AND(NOT(AN63),NOT(AO63)) -> FALSE | AR63: {=_xlfn.IFS(ISNUMBER(SEARCH("Balance",C63,1)),"MasterData!O56#",ISNUMBER(SEARCH("Income St",C63,1)),"MasterData!O116#",ISNUMBER(SEARCH("Shareholders",C63,1)),"D115#",ISNUMBER(SEARCH("Cash Flow",C63,1)),"E115#",ISNUMBER(SEARCH("Noncash",C63,1)),"C139#",ISNUMBER(SEARCH("Comprehensive",C63,1)),"E145",ISNUMBER(SEARCH("Reconciliation",C63,1)),"D137#")} -> #N/A | AS63: {=_xlfn.IFS(ISNUMBER(SEARCH("Balance",C63,1)),"AX25:AX29",ISNUMBER(SEARCH("Income St",C63,1)),"AY25:AY28",ISNUMBER(SEARCH("Shareholders",C63,1)),"EquityUsed",ISNUMBER(SEARCH("Cash Flow",C63,1)),"BA25:BA27",ISNUMBER(SEARCH("Noncash",C63,1)),"AZ25",ISNUMBER(SEARCH("Comprehensive",C63,1)),"AZ25",ISNUMBER(SEARCH("Reconciliation",C63,1)),"BB25:BB26")} -> #N/A
H64: =_xlfn.TEXTJOIN(6,1,FSBuilder[[#This Row],[Statement]:[Account or Explanation]]) | AC64: =ISNUMBER(MATCH(N64&O64,FSData!$V$7:$V$95,0)) -> TRUE | AD64: =OR(ISNUMBER(SEARCH("Total",N64,1)),ISNUMBER(SEARCH("Net Income",N64,1))) -> FALSE | AE64: =AND(NOT(AC64),NOT(AD64)) -> FALSE | AF64: =ISNUMBER(MATCH(R64&S64,FSData!$X$7:$X$95,0)) -> TRUE | AG64: =OR(ISNUMBER(SEARCH("Total",R64,1)),ISNUMBER(SEARCH("Balance",R64,1))) -> FALSE | AH64: =AND(NOT(AF64),NOT(AG64)) -> FALSE | AJ64: =ISNUMBER(MATCH(U64&V64,FSData!$Z$7:$Z$95,0)) -> TRUE | AK64: =OR(ISNUMBER(SEARCH("Total",U64,1)),ISNUMBER(SEARCH("Increase (decrease)",U64,1)),ISNUMBER(SEARCH("Operating Activities",U64,1)),ISNUMBER(SEARCH("Investing Activities",U64,1)),ISNUMBER(SEARCH("Financing Activities",U64,1)),ISNUMBER(SEARCH("Cash @",U64,1)),ISNUMBER(SEARCH("Net Income",U64,1)),ISNUMBER(SEARCH("Cash Flow from Operations",U64,1))) -> FALSE | AL64: =AND(NOT(AJ64),NOT(AK64)) -> FALSE | AN64: =ISNUMBER(MATCH(Y64&Z64,FSData!$AB$7:$AB$95,0)) -> TRUE | AO64: =OR(ISNUMBER(SEARCH("Total",Y64,1))) -> FALSE | AP64: =AND(NOT(AN64),NOT(AO64)) -> FALSE | AR64: {=_xlfn.IFS(ISNUMBER(SEARCH("Balance",C64,1)),"MasterData!O56#",ISNUMBER(SEARCH("Income St",C64,1)),"MasterData!O116#",ISNUMBER(SEARCH("Shareholders",C64,1)),"D115#",ISNUMBER(SEARCH("Cash Flow",C64,1)),"E115#",ISNUMBER(SEARCH("Noncash",C64,1)),"C139#",ISNUMBER(SEARCH("Comprehensive",C64,1)),"E145",ISNUMBER(SEARCH("Reconciliation",C64,1)),"D137#")} -> #N/A | AS64: {=_xlfn.IFS(ISNUMBER(SEARCH("Balance",C64,1)),"AX25:AX29",ISNUMBER(SEARCH("Income St",C64,1)),"AY25:AY28",ISNUMBER(SEARCH("Shareholders",C64,1)),"EquityUsed",ISNUMBER(SEARCH("Cash Flow",C64,1)),"BA25:BA27",ISNUMBER(SEARCH("Noncash",C64,1)),"AZ25",ISNUMBER(SEARCH("Comprehensive",C64,1)),"AZ25",ISNUMBER(SEARCH("Reconciliation",C64,1)),"BB25:BB26")} -> #N/A
... H90: =_xlfn.TEXTJOIN(6,1,FSBuilder[[#This Row],[Statement]:[Account or Explanation]]) | AC90: =ISNUMBER(MATCH(N90&O90,FSData!$V$7:$V$95,0)) -> TRUE | AD90: =OR(ISNUMBER(SEARCH("Total",N90,1)),ISNUMBER(SEARCH("Net Income",N90,1))) -> FALSE | AE90: =AND(NOT(AC90),NOT(AD90)) -> FALSE | AF90: =ISNUMBER(MATCH(R90&S90,FSData!$X$7:$X$95,0)) -> TRUE | AG90: =OR(ISNUMBER(SEARCH("Total",R90,1)),ISNUMBER(SEARCH("Balance",R90,1))) -> FALSE | AH90: =AND(NOT(AF90),NOT(AG90)) -> FALSE | AJ90: =ISNUMBER(MATCH(U90&V90,FSData!$Z$7:$Z$95,0)) -> TRUE | AK90: =OR(ISNUMBER(SEARCH("Total",U90,1)),ISNUMBER(SEARCH("Increase (decrease)",U90,1)),ISNUMBER(SEARCH("Operating Activities",U90,1)),ISNUMBER(SEARCH("Investing Activities",U90,1)),ISNUMBER(SEARCH("Financing Activities",U90,1)),ISNUMBER(SEARCH("Cash @",U90,1)),ISNUMBER(SEARCH("Net Income",U90,1)),ISNUMBER(SEARCH("Cash Flow from Operations",U90,1))) -> FALSE | AL90: =AND(NOT(AJ90),NOT(AK90)) -> FALSE | AN90: =ISNUMBER(MATCH(Y90&Z90,FSData!$AB$7:$AB$95,0)) -> TRUE | AO90: =OR(ISNUMBER(SEARCH("Total",Y90,1))) -> FALSE | AP90: =AND(NOT(AN90),NOT(AO90)) -> FALSE | AR90: {=_xlfn.IFS(ISNUMBER(SEARCH("Balance",C90,1)),"MasterData!O56#",ISNUMBER(SEARCH("Income St",C90,1)),"MasterData!O116#",ISNUMBER(SEARCH("Shareholders",C90,1)),"D115#",ISNUMBER(SEARCH("Cash Flow",C90,1)),"E115#",ISNUMBER(SEARCH("Noncash",C90,1)),"C139#",ISNUMBER(SEARCH("Comprehensive",C90,1)),"E145",ISNUMBER(SEARCH("Reconciliation",C90,1)),"D137#")} -> #N/A | AS90: {=_xlfn.IFS(ISNUMBER(SEARCH("Balance",C90,1)),"AX25:AX29",ISNUMBER(SEARCH("Income St",C90,1)),"AY25:AY28",ISNUMBER(SEARCH("Shareholders",C90,1)),"EquityUsed",ISNUMBER(SEARCH("Cash Flow",C90,1)),"BA25:BA27",ISNUMBER(SEARCH("Noncash",C90,1)),"AZ25",ISNUMBER(SEARCH("Comprehensive",C90,1)),"AZ25",ISNUMBER(SEARCH("Reconciliation",C90,1)),"BB25:BB26")} -> #N/A
H91: =_xlfn.TEXTJOIN(6,1,FSBuilder[[#This Row],[Statement]:[Account or Explanation]]) | AR91: {=_xlfn.IFS(ISNUMBER(SEARCH("Balance",C91,1)),"MasterData!O56#",ISNUMBER(SEARCH("Income St",C91,1)),"MasterData!O116#",ISNUMBER(SEARCH("Shareholders",C91,1)),"D115#",ISNUMBER(SEARCH("Cash Flow",C91,1)),"E115#",ISNUMBER(SEARCH("Noncash",C91,1)),"C139#",ISNUMBER(SEARCH("Comprehensive",C91,1)),"E145",ISNUMBER(SEARCH("Reconciliation",C91,1)),"D137#")} -> #N/A | AS91: {=_xlfn.IFS(ISNUMBER(SEARCH("Balance",C91,1)),"AX25:AX29",ISNUMBER(SEARCH("Income St",C91,1)),"AY25:AY28",ISNUMBER(SEARCH("Shareholders",C91,1)),"EquityUsed",ISNUMBER(SEARCH("Cash Flow",C91,1)),"BA25:BA27",ISNUMBER(SEARCH("Noncash",C91,1)),"AZ25",ISNUMBER(SEARCH("Comprehensive",C91,1)),"AZ25",ISNUMBER(SEARCH("Reconciliation",C91,1)),"BB25:BB26")} -> #N/A
B95: Info for FS Builder
C96: Concatenated strings of items selected:
C97: Statement | D97: Category | E97: Statement&Category&Account | AC97: Cash Flow Statement | AF97: Noncash Investing/Financing Transactions
C98: =_xlfn.TEXTJOIN("6",TRUE,C25:C91) -> Beginning Balance Sheet6Beginning Balance Sheet6Beginning Balance Sheet6Beginning Balance Sheet6Beginning Balance Sheet6Beginning Balance Sheet6Beginning Balance Sheet6Beginning Balance Sheet6Beginning Balance Sheet6Beginning Balance Sheet | D98: =_xlfn.TEXTJOIN("6",TRUE,D25:D91) -> Noncurrent Liabilities6 Current Assets6 Current Assets6 Current Assets6 Equities6 Equities6 Current Liabilities6 Current Assets6 Noncurrent Assets6 Noncurrent Assets | E98: =_xlfn.TEXTJOIN(6,1,H25:H91) -> Beginning Balance Sheet6 Noncurrent Liabilities6Notes Payable6Beginning Balance Sheet6 Current Assets6Cash6Beginning Balance Sheet6 Current Assets6Accounts Receivable6Beginning Balance Sheet6 Current Assets6Inventories6Beginning Balance Sheet6 Equities6Common Stock6Beginning Balance Sheet6 Equities6Retained Earnings6Beginning Balance Sheet6 Current Liabilities6Interest Payable6Beginning Balance Sheet6 Current Assets6Dividends Payable6Beginning Balance Sheet6 Noncurrent Assets6Property, Plant & Equipment6Beginning Balance Sheet6 Noncurrent Assets6Accumulated Depreciation6Cost of Goods Sold6Interest Expense6Depreciation Expense6Salaries & Wages Expense6Sales6Notes Payable6Cash6Accounts Receivable6Inventories6Common Stock6Retained Earnings6Interest Payable6Dividends Payable6Property, Plant & Equipment6Accumulated Depreciation6Issued common stock6Declared Dividends6Net Income (Loss) | AC98: When Cash Flow Statement is shown | AF98: It is automated or selected | AG98: =OR(F107,E107) -> FALSE
AC99: Beginning Cash | AD99: =$S$126 -> TRUE
C100: Statement Names | D100: Problem Requirement | E100: Selected by Student? | F100: Automated | G100: In Balance? | H100: Disagree w Answer? | N100: Student Selection - Complex | O100: Selected by Student? | R100: Conditions under which statements are shown: | U100: Conditions under which parts of statements are shown: | AC100: Ending Cash | AD100: =$S$126 -> TRUE | AF100: NI CFO Reconciliation
C101: Beginning Balance Sheet | D101: =ProblemData!F37 -> Prepare | E101: =ISNUMBER(SEARCH(C101,$C$98)) -> TRUE | F101: =IF(ProblemData!E10,_xlfn.XLOOKUP(C101,$C$14:$C$21,$D$14:$D$21),"FALSE") -> TRUE | G101: =ABS(D555-D556-D557)<0.00001 -> TRUE | H101: =FSAnswers!D99 -> FALSE | N101: Beginning Balance Sheet6 Current Assets | O101: =ISNUMBER(SEARCH(N101,$E$98,1)) -> TRUE | AF101: It is automated or selected | AG101: =OR(F105,E105) -> FALSE
C102: Income Statement | D102: =ProblemData!F41 -> Prepare | E102: =ISNUMBER(SEARCH(C102,$C$98)) -> FALSE | F102: =IF(ProblemData!E11,_xlfn.XLOOKUP(C102,$C$14:$C$21,$D$14:$D$21),"FALSE") -> TRUE | H102: =FSAnswers!I99 -> FALSE | N102: Beginning Balance Sheet6 Noncurrent Assets | O102: =ISNUMBER(SEARCH(N102,$E$98,1)) -> TRUE | R102: Beginning Balance Sheet | U102: Beginning Balance Sheet | Y102: Income Statement | AC102: Operating activities
C103: Statement of Changes in Shareholders' Equity | D103: =ProblemData!F43 -> Prepare | E103: =ISNUMBER(SEARCH(C103,$C$98)) -> FALSE | F103: =IF(ProblemData!E13,_xlfn.XLOOKUP(C103,$C$14:$C$21,$D$14:$D$21),"FALSE") -> TRUE | H103: =FSAnswers!M99 -> FALSE | N103: Beginning Balance Sheet6 Current Liabilities | O103: =ISNUMBER(SEARCH(N103,$E$98,1)) -> TRUE | R103: It is automated | S103: =$F$101 -> TRUE | U103: Beginning Balance Sheet is shown | Y103: Income Statement is shown | AC103: CFS is automated | AD103: =$F$104 -> FALSE | AF103: Net Income (Loss)
C104: Cash Flow Statement | D104: =ProblemData!F45 -> Omit | E104: =ISNUMBER(SEARCH(C104,$C$98)) -> FALSE | F104: =IF(ProblemData!E14,_xlfn.XLOOKUP(C104,$C$14:$C$21,$D$14:$D$21),"FALSE") -> FALSE | N104: Beginning Balance Sheet6 Noncurrent Liabilities | O104: =ISNUMBER(SEARCH(N104,$E$98,1)) -> TRUE | R104: It is selected | S104: =$E$101 -> TRUE | U104: Assets | V104: =$S$105 -> TRUE | Y104: Revenues | Z104: =$S$111 -> TRUE | AC104: Cash Flow Statement is shown | AD104: =$S$126 -> TRUE | AF104: Adjustments
C105: Reconciliation of NI and CFO | D105: =ProblemData!F47 -> Omit | E105: =ISNUMBER(SEARCH(C105,$C$98)) -> FALSE | F105: =IF(ProblemData!E15,_xlfn.XLOOKUP(C105,$C$14:$C$21,$D$14:$D$21),"FALSE") -> FALSE | N105: Beginning Balance Sheet6 Equities | O105: =ISNUMBER(SEARCH(N105,$E$98,1)) -> TRUE | R105: Show it: | S105: =OR(S103,S104) -> TRUE | U105: Liabilities | V105: =$S$105 -> TRUE | Y105: Expenses | Z105: =$S$111 -> TRUE | AC105: Operating Activities are selected | AD105: =$K$125 -> FALSE | AF105: Changes in balance sheet accounts due to operations
C106: Ending Balance Sheet | D106: =ProblemData!F40 -> Prepare | E106: =ISNUMBER(SEARCH(C106,$C$98)) -> FALSE | F106: =IF(ProblemData!E17,_xlfn.XLOOKUP(C106,$C$14:$C$21,$D$14:$D$21),"FALSE") -> TRUE | G106: =ABS(AD555-AD556-AD557)<0.00001 -> TRUE | H106: =FSAnswers!U99 -> FALSE | N106: =$N$105&"6Preferred Stock" -> Beginning Balance Sheet6 Equities6Preferred Stock | O106: =ISNUMBER(SEARCH(N106,$E$98,1)) -> FALSE | U106: Equities | V106: =$S$105 -> TRUE | AC106: Investing Activities are selected | AD106: =$K$126 -> FALSE | AF106: Cash Flow from Operations
C107: Noncash Investing/Financing Transactions | D107: =ProblemData!F48 -> Omit | E107: =ISNUMBER(SEARCH(C107,$C$98)) -> FALSE | F107: =IF(ProblemData!E16,_xlfn.XLOOKUP(C107,$C$14:$C$21,$D$14:$D$21),"FALSE") -> FALSE | N107: =$N$105&"6Common Stock" -> Beginning Balance Sheet6 Equities6Common Stock | O107: =ISNUMBER(SEARCH(N107,$E$98,1)) -> TRUE | R107: Income Statement | Y107: Gains | AC107: Financing activities are selected | AD107: =$K$127 -> FALSE
C108: Statement of Comprehensive Income | D108: =ProblemData!F42 -> Omit | E108: =ISNUMBER(SEARCH(C108,$C$98)) -> FALSE | F108: =IF(ProblemData!E12,_xlfn.XLOOKUP(C108,$C$14:$C$21,$D$14:$D$21),"FALSE") -> FALSE | N108: =$N$105&"6Additional Paid-in Capital" -> Beginning Balance Sheet6 Equities6Additional Paid-in Capital | O108: =ISNUMBER(SEARCH(N108,$E$98,1)) -> FALSE | R108: It is automated | S108: =$F$102 -> TRUE | Y108: Income Statement is shown | Z108: =$S$111 -> TRUE | AC108: Show it: | AD108: =OR(AD103,AND(AD104,OR(AD105,AD106,AD107))) -> FALSE | AF108: Ending Balance Sheet
N109: =$N$105&"6Retained Earnings" -> Beginning Balance Sheet6 Equities6Retained Earnings | O109: =ISNUMBER(SEARCH(N109,$E$98,1)) -> TRUE | R109: It is selected | S109: =$E$102 -> FALSE | U109: Current Assets | Y109: Gains are active in the problem | Z109: =FSConstruction!$J$42=1 -> FALSE | AF109: Assets | AG109: =$S$146 -> TRUE
C110: ="as of "&EndDate -> as of 12/31/20x4 | N110: =$N$105&"6Accumulated Other Comprehensive Income" -> Beginning Balance Sheet6 Equities6Accumulated Other Comprehensive Income | O110: =ISNUMBER(SEARCH(N110,$E$98,1)) -> FALSE | R110: Both Beginning and Ending Balance Sheets appear. | S110: =AND($S$105,$S$146) -> TRUE | U110: Beginning balance sheet shown | V110: =$S$105 -> TRUE | Y110: Gains have been selected | Z110: =$K$123 -> FALSE | AC110: Investing activities | AF110: Liabilities | AG110: =$S$146 -> TRUE
C111: ="as of "&BegDate -> as of 12/31/20x3 | N111: =$N$105&"6Treasury Stock" -> Beginning Balance Sheet6 Equities6Treasury Stock | O111: =ISNUMBER(SEARCH(N111,$E$98,1)) -> FALSE | R111: Show it: | S111: =OR(S108,S109,S110) -> TRUE | U111: Current Assets selected | V111: =$K$116 -> TRUE | Y111: Losses are active in the problem | Z111: =FSConstruction!$J$52=1 -> FALSE | AC111: CFS is automated | AD111: =$F$104 -> FALSE | AF111: Equities | AG111: =$S$146 -> TRUE
C112: ="for the "&Period&" ended "&EndDate -> for the Year ended 12/31/20x4 | N112: Beginning Balance Sheet6 Current Assets6Cash | O112: =ISNUMBER(SEARCH(N112,$E$98,1)) -> TRUE | U112: Noncurrent Assets selected | V112: =$K$117 -> TRUE | Y112: Losses have been selected | Z112: =$K$124 -> FALSE | AC112: Cash Flow Statement is shown | AD112: =$S$126 -> TRUE
N113: Ending Balance Sheet6 Current Assets | O113: =ISNUMBER(SEARCH(N113,$E$98,1)) -> FALSE | U113: Show it: | V113: =AND(V110,OR(V111,V112)) -> TRUE | Y113: Show it: | Z113: =AND(Z108,OR(Z109,Z110,Z111,Z112)) -> FALSE | AC113: Operating Activities are selected | AD113: =$K$125 -> FALSE | AF113: Current Assets
D114: St changes | E114: CF statement | F114: CFS Adjs | N114: Ending Balance Sheet6 Noncurrent Assets | O114: =ISNUMBER(SEARCH(N114,$E$98,1)) -> FALSE | R114: Statement of Shareholders' Equity | AC114: Investing Activities are selected | AD114: =$K$126 -> FALSE | AF114: Ending balance sheet shown | AG114: =$S$146 -> TRUE
D115: {=_xlfn._xlws.FILTER(StChsSE[Item],ABS(StChsSE[AmtAnswer])>0,"")} -> Issued common stock | E115: {=_xlfn._xlws.SORT(_xlfn.VSTACK(_xlfn.ANCHORARRAY(C129),_xlfn.ANCHORARRAY(D129),_xlfn.ANCHORARRAY(E129)))} -> Acquired PP&E | F115: {=_xlfn._xlws.FILTER(NI_CFO_Recon_Adjs[Account],NI_CFO_Recon_Adjs[UsedAnswer]=1,"")} -> Depreciation expense | J115: Categories | K115: Selected by Student? | N115: Ending Balance Sheet6 Current Liabilities | O115: =ISNUMBER(SEARCH(N115,$E$98,1)) -> FALSE | R115: It is automated | S115: =$F$103 -> TRUE | Y115: Losses | AC115: Financing activities are selected | AD115: =$K$127 -> FALSE | AF115: Current Assets selected | AG115: =$O$113 -> FALSE
D116: Declared Dividends | E116: Collections from customers | J116: Current Assets | K116: =ISNUMBER(SEARCH(J116,$D$98)) -> TRUE | N116: Ending Balance Sheet6 Noncurrent Liabilities | O116: =ISNUMBER(SEARCH(N116,$E$98,1)) -> FALSE | R116: Both Beginning and Ending Balance Sheet Equity are selected | S116: =AND($O$105,$O$117) -> FALSE | U116: Noncurrent Assets | Y116: Income Statement is shown | Z116: =$S$111 -> TRUE | AC116: Show it: | AD116: =OR(AD111,AND(AD112,OR(AD113,AD114,AD115))) -> FALSE | AF116: Noncurrent Assets selected | AG116: =$O$114 -> FALSE
D117: Net Income (Loss) | E117: Issued common stock | J117: Noncurrent Assets | K117: =ISNUMBER(SEARCH(J117,$D$98)) -> TRUE | N117: Ending Balance Sheet6 Equities | O117: =ISNUMBER(SEARCH(N117,$E$98,1)) -> FALSE | R117: Both Beginning and Ending Balance Sheets appear. | S117: =AND($S$105,$S$146) -> TRUE | U117: Beginning balance sheet shown | V117: =$S$105 -> TRUE | Y117: Gains are active in the problem | Z117: =FSConstruction!$J$42=1 -> FALSE | AF117: Show it: | AG117: =AND(AG114,OR(AG115,AG116)) -> FALSE
E118: Issued notes | J118: Current Liabilities | K118: =ISNUMBER(SEARCH(J118,$D$98)) -> TRUE | N118: =$N$117&"6Preferred Stock" -> Ending Balance Sheet6 Equities6Preferred Stock | O118: =ISNUMBER(SEARCH(N118,$E$98,1)) -> FALSE | R118: Show it: | S118: =OR(S115,S116,S117) -> TRUE | U118: Current Assets selected | V118: =$K$116 -> TRUE | Y118: Gains have been selected | Z118: =$K$123 -> FALSE | AC118: Financing activities
E119: Paid dividends | J119: Noncurrent Liabilities | K119: =ISNUMBER(SEARCH(J119,$D$98)) -> TRUE | N119: =$N$117&"6Common Stock" -> Ending Balance Sheet6 Equities6Common Stock | O119: =ISNUMBER(SEARCH(N119,$E$98,1)) -> FALSE | U119: Noncurrent Assets selected | V119: =K117 -> TRUE | Y119: Losses are active in the problem | Z119: =FSConstruction!$J$52=1 -> FALSE | AC119: CFS is automated | AD119: =$F$104 -> FALSE
E120: Payments for interest | J120: Equities | K120: =ISNUMBER(SEARCH(J120,$D$98)) -> TRUE | N120: =$N$117&"6Additional Paid-in Capital" -> Ending Balance Sheet6 Equities6Additional Paid-in Capital | O120: =ISNUMBER(SEARCH(N120,$E$98,1)) -> FALSE | U120: Show it: | V120: =AND(V117,OR(V118,V119)) -> TRUE | Y120: Losses have been selected | Z120: =$K$124 -> FALSE | AC120: Cash Flow Statement is shown | AD120: =$S$126 -> TRUE | AF120: Noncurrent Assets
E121: Payments to employees | J121: Revenues | K121: =ISNUMBER(SEARCH(J121,$D$98)) -> FALSE | N121: =$N$117&"6Retained Earnings" -> Ending Balance Sheet6 Equities6Retained Earnings | O121: =ISNUMBER(SEARCH(N121,$E$98,1)) -> FALSE | R121: Cash Flow Statement | Y121: Show it: | Z121: =AND(Z116,OR(Z117,Z118,Z119,Z120)) -> FALSE | AC121: Operating Activities are selected | AD121: =$K$125 -> FALSE | AF121: Ending balance sheet shown | AG121: =$S$146 -> TRUE
E122: Payments to suppliers | J122: Expenses | K122: =ISNUMBER(SEARCH(J122,$D$98)) -> FALSE | N122: =$N$117&"6Accumulated Other Comprehensive Income" -> Ending Balance Sheet6 Equities6Accumulated Other Comprehensive Income | O122: =ISNUMBER(SEARCH(N122,$E$98,1)) -> FALSE | R122: It is automated | S122: =$F$104 -> FALSE | AC122: Investing Activities are selected | AD122: =$K$126 -> FALSE | AF122: Current Assets selected | AG122: =$O$113 -> FALSE
J123: Gains | K123: =ISNUMBER(SEARCH(J123,$D$98)) -> FALSE | N123: =$N$117&"6Treasury Stock" -> Ending Balance Sheet6 Equities6Treasury Stock | O123: =ISNUMBER(SEARCH(N123,$E$98,1)) -> FALSE | R123: Cash Flow Statement is selected | S123: =$E$104 -> FALSE | U123: Current Liabilities | Y123: Statement of Changes in Shareholders Equity | AC123: Financing activities are selected | AD123: =$K$127 -> FALSE | AF123: Noncurrent Assets selected | AG123: =$O$114 -> FALSE
F124: CFS Δs due to OPS | J124: Losses | K124: =ISNUMBER(SEARCH(J124,$D$98)) -> FALSE | N124: Ending Balance Sheet6 Current Assets6Cash | O124: =ISNUMBER(SEARCH(N124,$E$98,1)) -> FALSE | R124: Cash has been selected on both Beginning and Ending Balance Sheets | S124: =AND($O$112,$O$124) -> FALSE | U124: Beginning balance sheet shown | V124: =$S$105 -> TRUE | AC124: Show it: | AD124: =OR(AD119,AND(AD120,OR(AD121,AD122,AD123))) -> FALSE | AF124: Show it: | AG124: =AND(AG121,OR(AG122,AG123)) -> FALSE
F125: {=_xlfn._xlws.FILTER(NI_CFO_Recon_Chs_Ops[Account],NI_CFO_Recon_Chs_Ops[UsedAnswer]=1,"")} -> Accounts Receivable | J125: Operating Activities | K125: =ISNUMBER(SEARCH(J125,$D$98)) -> FALSE | R125: Both Beginning and Ending Balance Sheets appear. | S125: =AND($S$105,$S$146) -> TRUE | U125: Current Liabilities selected | V125: =$K$118 -> TRUE | Y125: When Statement of Shareholders' Equity is shown:
F126: Inventories | J126: Financing Activities | K126: =ISNUMBER(SEARCH(J126,$D$98)) -> FALSE | R126: Show it: | S126: =OR(S122,S123,S124,S125) -> TRUE | U126: Noncurrent Liabilities selected | V126: =$K$119 -> TRUE | Y126: Beginning Shareholders' Equity | Z126: =$S$118 -> TRUE | AC126: CFS Sections and Details
J127: Investing Activities | K127: =ISNUMBER(SEARCH(J127,$D$98)) -> FALSE | U127: Show it: | V127: =AND(V124,OR(V125,V126)) -> TRUE | Y127: Ending Shareholders' Equity | Z127: =$S$118 -> TRUE | AC127: Operating Activities | AF127: Current Liabilities
C128: CFO | D128: CFI | E128: CFF | J128: Other Comprehensive Income | K128: =ISNUMBER(SEARCH(J128,$D$98)) -> FALSE | R128: NI CFO Reconciliation | AC128: CFS is automated | AD128: =$F$104 -> FALSE | AF128: Ending balance sheet shown | AG128: =$S$146 -> TRUE
...

Sheet Notes_to_FSs
C1: =Entity -> Miloslav's Magazines
C2: =Units -> Dollars in Thousands
C4: Notes to the Financial Statements
B5: {=FSConstruction!B117:C135} -> 10 | C5: BUSINESS OPERATIONS
B6: 11 | C6: Miloslav's Magazines (the 'Company', 'we', 'us', 'our') is a For-profit corporation whose activity is Retail.
B7: 10 | C7: SUMMARY OF SIGNIFICANT ACCOUNTING POLICIES
B8: 10 | C8: Basis of Presentation and Use of Estimates
B9: 11 | C9: We prepare financial statements in conformity with accounting principles generally accepted in the United States (U.S. GAAP), with includes accounting standards set by the Financial Accounting Standards Board (FASB) and other bodies. U.S. GAAP requires us to make estimates and assumptions in reporting amounts on our balance sheets and income statements. Actual results may differ from the estimates used in preparing financial statements.
B10: 10 | C10: Cash
B11: 11 | C11: Cash includes demand deposits, money market accounts, …
B12: 10 | C12: Inventories
B13: 11 | C13: Our inventories are exclusively goods held for resale and stated on a First-in, first-out (FIFO) basis.
B14: 10 | C14: Property, Plant & Equipment
B15: 11 | C15: The Company calculates depreciation expense on a straight-line basis.
B16: 10 | C16: Revenue Recognition
B17: 11 | C17: We recognize revenue in accordance with FASB ASC 606, "Revenue from Contracts with Customers"..
... B23: 11 | C23: We have evaluated subsequent events through 3/31/20x5, the date we have issued these financial statements. As of that date, there were no material, reportable subsequent events.

Sheet Analysis_Help
B2: SELECT TRANSACTION TO ANALYZE
D3: select from drop down menu
C4: Transaction #
C6: Transaction Details
C7: {=INDEX(ProblemData!D78:AN79,2,D4+1)} -> Transaction Info
B13: Recognition Help
C15: Do you recognize the transaction?
I17: =_xlfn.IFNA(MATCH($D$4,ProblemData!E78:$AM$78,0),"")
C18: Explanation | I18: {=IFERROR(D15&INDEX(ProblemData!$E$78:$AM$83,3,I17),"")}
C19: =IF(ISBLANK(D15),"",_xlfn.XLOOKUP(I18,MD_RecognitionFeedback[Student&Answer],MD_RecognitionFeedback[Feedback],""))
C21: {=IF(NOT(ISBLANK(D15)),INDEX(ProblemData!$E$78:$AM$83,4,I17),"")}
C27: You have correctly decided to record the effects of this transaction or event. The Accounting Identity Calculator will help you figure out the details of what you will record by identifying all the effects on Assets, Liabilities and Equities.
B32: Accounting Identity Calculator
C34: Instructions Click Here
C36: Accounting Identity | G36: Asset Recognition Criteria:
C37: Assets | D37: Liabilities | E37: Equities | G37: A) Future Benefit
G38: B) Owned or controlled by the entity
G39: C) Sufficient Evidence
G42: Liability Recognition Criteria:
G43: A) Future Sacrifice
G44: B) Obligation to make the sacrifice
G45: C) Sufficient Evidence
C46: =SUM(C38:C45) -> 0 | D46: =SUM(D38:D45) -> 0 | E46: =C46-D46 -> 0
C48: Assets and Liabilities are all entered?
C51: {=_xlfn.IFS(AND(E46=0,D48="YES"),MasterData!C405,AND(E46<>0,D48="YES"),MasterData!C406,OR(D48="",D48="NO"),"")}
B58: Equity Analysis Help
C60: Equity has been: | G60: Examples
C61: because: | Q61: ="MD_Equity"&D60&"[Reasons]" -> MD_Equity[Reasons]
Q62: =ISNUMBER(MATCH(D61,INDIRECT(Q61),0)) -> FALSE
C64: then: | D64: {=_xlfn.IFNA(_xlfn.IFS(ISBLANK(D60),"",D60="Increased",_xlfn.XLOOKUP(D61,MD_EquityIncreased[Reasons],MD_EquityIncreased[Response]),D60="Decreased",_xlfn.XLOOKUP(D61,MD_EquityDecreased[Reasons],MD_EquityDecreased[Response])),"")}
B67: Account Name Help
C69: Account Type | D69: Account Name
E70: =C70&"Used" -> Used
C72: Definition
C73: {=IFERROR(_xlfn.XLOOKUP(D70,INDIRECT(I74),INDIRECT(I75)),"")}
I74: ="MD_"&C70&"[Account Name]" -> MD_[Account Name]
I75: ="MD_"&C70&"[Definition]" -> MD_[Definition]
I76: {=_xlfn.IFNA(_xlfn.XLOOKUP(D70,INDIRECT(I74),INDIRECT(I75)),"Not Found")} -> #REF!
B79: Debit/Credit Help
C81: Assets
C82: Title | D82: Amount | E82: Debit or Credit?
D83: =C38 -> 0 | E83: {=IFERROR(_xlfn.IFS(D83>0,"Debit",D83<0,"Credit",D83=0,""),"")}
D84: =C39 -> 0 | E84: {=IFERROR(_xlfn.IFS(D84>0,"Debit",D84<0,"Credit",D84=0,""),"")}
D85: =C40 -> 0
D86: =C41 -> 0
D87: =C42 -> 0
D88: =C43 -> 0
D89: =C44 -> 0 | L89: `
D90: =C45 -> 0
C92: Liabilities
C93: Title | D93: Amount | E93: Debit or Credit?
D94: =D38 -> 0 | E94: {=IFERROR(_xlfn.IFS(D94>0,"Credit",D94<0,"Debit",D94=0,""),"")}
D95: =D39 -> 0 | E95: {=IFERROR(_xlfn.IFS(D95>0,"Credit",D95<0,"Debit",D95=0,""),"")}
D96: =D40 -> 0 | E96: {=IFERROR(_xlfn.IFS(D96>0,"Credit",D96<0,"Debit",D96=0,""),"")}
D97: =D41 -> 0 | E97: {=IFERROR(_xlfn.IFS(D97>0,"Credit",D97<0,"Debit",D97=0,""),"")}
D98: =D42 -> 0 | E98: {=IFERROR(_xlfn.IFS(D98>0,"Credit",D98<0,"Debit",D98=0,""),"")}
D99: =D43 -> 0 | E99: {=IFERROR(_xlfn.IFS(D99>0,"Credit",D99<0,"Debit",D99=0,""),"")}
D100: =D44 -> 0 | E100: {=IFERROR(_xlfn.IFS(D100>0,"Credit",D100<0,"Debit",D100=0,""),"")}
D101: =D45 -> 0 | E101: {=IFERROR(_xlfn.IFS(D101>0,"Credit",D101<0,"Debit",D101=0,""),"")}
C103: Equities
C104: Title | D104: Amount | E104: Debit or Credit?
E105: {=IFERROR(_xlfn.IFS(D105>0,"Credit",D105<0,"Debit",D105=0,""),"")}
E106: {=IFERROR(_xlfn.IFS(D106>0,"Credit",D106<0,"Debit",D106=0,""),"")}
E107: {=IFERROR(_xlfn.IFS(D107>0,"Credit",D107<0,"Debit",D107=0,""),"")}
E108: {=IFERROR(_xlfn.IFS(D108>0,"Credit",D108<0,"Debit",D108=0,""),"")}
E109: {=IFERROR(_xlfn.IFS(D109>0,"Credit",D109<0,"Debit",D109=0,""),"")}
E110: {=IFERROR(_xlfn.IFS(D110>0,"Credit",D110<0,"Debit",D110=0,""),"")}
E111: {=IFERROR(_xlfn.IFS(D111>0,"Credit",D111<0,"Debit",D111=0,""),"")}
E112: {=IFERROR(_xlfn.IFS(D112>0,"Credit",D112<0,"Debit",D112=0,""),"")}
C113: Total | D113: =SUM(D105:D112) -> 0
C114: Per Identity Calculator | D114: =E46 -> 0
C115: Difference | D115: =D114-D113 -> 0
C117: Equities are all entered?
C119: =COUNTIF(C105:C112,"Retained Earnings") -> 0
C120: When Retained Earnings is affected, there are two possibilities: • Retained Earnings is debited directly • Temporary accounts are debited or credited and then closed into Retained Earnings. Only dividend declarations result in entries directly to Retained Earnings. All other changes in Retained Earnings result from closing the Revenue, Expense, Gain and Loss accounts.
C127: Are temporary accounts required?
C130: Revenue accounts are used to record inflows and they are increased by Credits.
C131: Expense accounts are used to record inflows and they are increased by Debits.
C132: Gain accounts are used to record the excess of consideration received over the book value of what is given up and they are increased by Credits.
C133: Loss accounts are used to record the excess of the book value of what is given up over the consideration received and they are increased by Debits.
B135: Journal Entry Help
C137: AccntType | D137: DrAccnt | E137: CrAccnt | F137: DrAmt | G137: CrAmt | I137: Debits - Credits
B138: {=_xlfn.IFS(C138="","",AND(C138<>"",$J138),"OK",AND(C138<>"",NOT($J138)),"?")} | I138: =SUM(F138:F153)-SUM(G138:G153) -> 0 | J138: {=_xlfn.IFNA(_xlfn.IFS(K138="----","",K138<>"----",ISNUMBER(MATCH(K138,MasterData!$AI$494:$AI$509,0))),"FALSE")} | K138: =_xlfn.TEXTJOIN("-",FALSE,C138:G138) -> ---- | M138: =C138&"Used" -> Used
B139: {=_xlfn.IFS(C139="","",AND(C139<>"",$J139),"OK",AND(C139<>"",NOT($J139)),"?")} | J139: {=_xlfn.IFNA(_xlfn.IFS(K139="----","",K139<>"----",ISNUMBER(MATCH(K139,MasterData!$AI$494:$AI$509,0))),"FALSE")} | K139: =_xlfn.TEXTJOIN("-",FALSE,C139:G139) -> ---- | M139: =C139&"Used" -> Used
B140: {=_xlfn.IFS(C140="","",AND(C140<>"",$J140),"OK",AND(C140<>"",NOT($J140)),"?")} | J140: {=_xlfn.IFNA(_xlfn.IFS(K140="----","",K140<>"----",ISNUMBER(MATCH(K140,MasterData!$AI$494:$AI$509,0))),"FALSE")} | K140: =_xlfn.TEXTJOIN("-",FALSE,C140:G140) -> ---- | M140: =C140&"Used" -> Used
B141: {=_xlfn.IFS(C141="","",AND(C141<>"",$J141),"OK",AND(C141<>"",NOT($J141)),"?")} | J141: {=_xlfn.IFNA(_xlfn.IFS(K141="----","",K141<>"----",ISNUMBER(MATCH(K141,MasterData!$AI$494:$AI$509,0))),"FALSE")} | K141: =_xlfn.TEXTJOIN("-",FALSE,C141:G141) -> ---- | M141: =C141&"Used" -> Used
B142: {=_xlfn.IFS(C142="","",AND(C142<>"",$J142),"OK",AND(C142<>"",NOT($J142)),"?")} | J142: {=_xlfn.IFNA(_xlfn.IFS(K142="----","",K142<>"----",ISNUMBER(MATCH(K142,MasterData!$AI$494:$AI$509,0))),"FALSE")} | K142: =_xlfn.TEXTJOIN("-",FALSE,C142:G142) -> ---- | M142: =C142&"Used" -> Used
B143: {=_xlfn.IFS(C143="","",AND(C143<>"",$J143),"OK",AND(C143<>"",NOT($J143)),"?")} | J143: {=_xlfn.IFNA(_xlfn.IFS(K143="----","",K143<>"----",ISNUMBER(MATCH(K143,MasterData!$AI$494:$AI$509,0))),"FALSE")} | K143: =_xlfn.TEXTJOIN("-",FALSE,C143:G143) -> ---- | M143: =C143&"Used" -> Used
B144: {=_xlfn.IFS(C144="","",AND(C144<>"",$J144),"OK",AND(C144<>"",NOT($J144)),"?")} | J144: {=_xlfn.IFNA(_xlfn.IFS(K144="----","",K144<>"----",ISNUMBER(MATCH(K144,MasterData!$AI$494:$AI$509,0))),"FALSE")} | K144: =_xlfn.TEXTJOIN("-",FALSE,C144:G144) -> ---- | M144: =C144&"Used" -> Used
B145: {=_xlfn.IFS(C145="","",AND(C145<>"",$J145),"OK",AND(C145<>"",NOT($J145)),"?")} | J145: {=_xlfn.IFNA(_xlfn.IFS(K145="----","",K145<>"----",ISNUMBER(MATCH(K145,MasterData!$AI$494:$AI$509,0))),"FALSE")} | K145: =_xlfn.TEXTJOIN("-",FALSE,C145:G145) -> ---- | M145: =C145&"Used" -> Used
B146: {=_xlfn.IFS(C146="","",AND(C146<>"",$J146),"OK",AND(C146<>"",NOT($J146)),"?")} | J146: {=_xlfn.IFNA(_xlfn.IFS(K146="----","",K146<>"----",ISNUMBER(MATCH(K146,MasterData!$AI$494:$AI$509,0))),"FALSE")} | K146: =_xlfn.TEXTJOIN("-",FALSE,C146:G146) -> ---- | M146: =C146&"Used" -> Used
B147: {=_xlfn.IFS(C147="","",AND(C147<>"",$J147),"OK",AND(C147<>"",NOT($J147)),"?")} | J147: {=_xlfn.IFNA(_xlfn.IFS(K147="----","",K147<>"----",ISNUMBER(MATCH(K147,MasterData!$AI$494:$AI$509,0))),"FALSE")} | K147: =_xlfn.TEXTJOIN("-",FALSE,C147:G147) -> ---- | M147: =C147&"Used" -> Used
B148: {=_xlfn.IFS(C148="","",AND(C148<>"",$J148),"OK",AND(C148<>"",NOT($J148)),"?")} | J148: {=_xlfn.IFNA(_xlfn.IFS(K148="----","",K148<>"----",ISNUMBER(MATCH(K148,MasterData!$AI$494:$AI$509,0))),"FALSE")} | K148: =_xlfn.TEXTJOIN("-",FALSE,C148:G148) -> ---- | M148: =C148&"Used" -> Used
B149: {=_xlfn.IFS(C149="","",AND(C149<>"",$J149),"OK",AND(C149<>"",NOT($J149)),"?")} | J149: {=_xlfn.IFNA(_xlfn.IFS(K149="----","",K149<>"----",ISNUMBER(MATCH(K149,MasterData!$AI$494:$AI$509,0))),"FALSE")} | K149: =_xlfn.TEXTJOIN("-",FALSE,C149:G149) -> ---- | M149: =C149&"Used" -> Used
B150: {=_xlfn.IFS(C150="","",AND(C150<>"",$J150),"OK",AND(C150<>"",NOT($J150)),"?")} | J150: {=_xlfn.IFNA(_xlfn.IFS(K150="----","",K150<>"----",ISNUMBER(MATCH(K150,MasterData!$AI$494:$AI$509,0))),"FALSE")} | K150: =_xlfn.TEXTJOIN("-",FALSE,C150:G150) -> ---- | M150: =C150&"Used" -> Used
B151: {=_xlfn.IFS(C151="","",AND(C151<>"",$J151),"OK",AND(C151<>"",NOT($J151)),"?")} | J151: {=_xlfn.IFNA(_xlfn.IFS(K151="----","",K151<>"----",ISNUMBER(MATCH(K151,MasterData!$AI$494:$AI$509,0))),"FALSE")} | K151: =_xlfn.TEXTJOIN("-",FALSE,C151:G151) -> ---- | M151: =C151&"Used" -> Used
B152: {=_xlfn.IFS(C152="","",AND(C152<>"",$J152),"OK",AND(C152<>"",NOT($J152)),"?")} | I152: Check it: | J152: {=_xlfn.IFNA(_xlfn.IFS(K152="----","",K152<>"----",ISNUMBER(MATCH(K152,MasterData!$AI$494:$AI$509,0))),"FALSE")} | K152: =_xlfn.TEXTJOIN("-",FALSE,C152:G152) -> ---- | M152: =C152&"Used" -> Used
B153: {=_xlfn.IFS(C153="","",AND(C153<>"",$J153),"OK",AND(C153<>"",NOT($J153)),"?")} | J153: {=_xlfn.IFNA(_xlfn.IFS(K153="----","",K153<>"----",ISNUMBER(MATCH(K153,MasterData!$AI$494:$AI$509,0))),"FALSE")} | K153: =_xlfn.TEXTJOIN("-",FALSE,C153:G153) -> ----
D155: #Accounts Debited | E155: #Accounts Credited | F155: Total Debits | G155: Total Credits
C156: You | D156: =COUNTA(D138:D153)-COUNTIF(D138:D153,0) -> 0 | E156: =COUNTA(E138:E153)-COUNTIF(E138:E153,0) -> 0 | F156: =SUM(F138:F153) -> 0 | G156: =SUM(G138:G153) -> 0
...

Sheet Tools
C3: Permanent Account | I3: 1 | J3: Select an entry to check | P3: ALL TEMPORARY ACCOUNTS ARE CLOSED
C4: Account Type: | D4: Asset | I4: Your Entry | P4: =IF(ABS(Q132)<0.00001,"Closing Entry Balances","Closing Entry Doesn't Balance") -> Closing Entry Balances | V4: ref | W4: ="Cash" -> Cash | Y4: ref | AG4: Checklist:
C5: Account Name: | D5: Inventories | I5: AccntType | J5: DrAccnt | K5: CrAccnt | L5: DrAmt | M5: CrAmt | P5: {=IFERROR(_xlfn.VSTACK("REVENUES:",_xlfn._xlws.FILTER(MD_Revenue[Account Name],MD_Revenue[Used]=1),"EXPENSES:",_xlfn._xlws.FILTER(MD_Expense[Account Name],MD_Expense[Used]=1),"GAINS:",_xlfn._xlws.FILTER(MD_Gain[Account Name],MD_Gain[Used]=1),"LOSSES:",_xlfn._xlws.FILTER(MD_Loss[Account Name],MD_Loss[Used]=1)),"")} | Q5: Amount | R5: Increased by: | V5: =BegDate -> 12/31/20x3 | W5: =IF(W108="Debit",ABS(X108),0) -> 0 | X5: =IF(W108="Credit",ABS(X108),0) -> 0 | Y5: =BegDate -> 12/31/20x3 | AC5: Investing | AD5: Financing | AE5: Other | AG5: Transaction # | AH5: Done?
H6: {=_xlfn.IFS(I6="","",AND(I6<>"",N101),"OK",AND(I6<>"",NOT(N101)),"?")} -> OK | I6: {=IF(I3<>"",_xlfn._xlws.FILTER(Journal[Accnt Type]:Journal[Cr Amt],Journal[Transaction '#]=$I$3,"No Entry Found"),"")} -> Asset | J6: Cash | K6: 0 | L6: 3 | M6: 0 | Q6: =_xlfn.XLOOKUP(P6,P101:P130,Q101:Q130,0) -> 0 | R6: {=IF(P6<>"",_xlfn.XLOOKUP(P6,P101:P130,R101:R130&"s",""),"")} | U6: {=_xlfn._xlws.FILTER(Journal[Cash Flow],Journal[Debit Account]=W4,"")} -> 0 | V6: {=_xlfn._xlws.FILTER(Journal[Transaction '#],Journal[Debit Account]=W4,"")} -> 1 | W6: {=_xlfn._xlws.FILTER(Journal[Dr Amt],Journal[Debit Account]=W4,0)} -> 3 | X6: {=_xlfn._xlws.FILTER(Journal[Cr Amt],Journal[Credit Account]=W4,0)} -> 1 | Y6: {=_xlfn._xlws.FILTER(Journal[Transaction '#],Journal[Credit Account]=W4,"")} -> 3 | Z6: {=_xlfn._xlws.FILTER(Journal[Cash Flow],Journal[Credit Account]=W4,"")} -> 0 | AC6: {=IFERROR(_xlfn._xlws.FILTER(JournalAnswer[Transaction '#],JournalAnswer[Cash Flow]="Investing"),"")} -> 3 | AD6: {=IFERROR(_xlfn._xlws.FILTER(JournalAnswer[Transaction '#],JournalAnswer[Cash Flow]="Financing"),"")} -> 1 | AE6: {=IFERROR(_xlfn.UNIQUE(_xlfn._xlws.FILTER(JournalAnswer[Transaction '#],(JournalAnswer[ref1]="OCI")+(JournalAnswer[ref1]="FVMS")+(JournalAnswer[ref1]="DD")+(JournalAnswer[ref1]="SBC")+(JournalAnswer[ref1]="PPEfCS")+(JournalAnswer[ref1]="PPEfTS"))),"")} -> 8 | AG6: {=_xlfn.VSTACK(_xlfn.ANCHORARRAY(AC6),_xlfn.ANCHORARRAY(AD6),_xlfn.ANCHORARRAY(AE6))} -> 3 | AH6: FALSE
B7: ref | C7: =D5 -> Inventories | E7: ref | H7: {=_xlfn.IFS(I7="","",AND(I7<>"",N102),"OK",AND(I7<>"",NOT(N102)),"?")} -> OK | I7: Equity | J7: 0 | K7: Common Stock | L7: 0 | M7: 3 | Q7: =_xlfn.XLOOKUP(P7,P102:P131,Q102:Q131,0) -> 0 | R7: {=IF(P7<>"",_xlfn.XLOOKUP(P7,P102:P131,R102:R131&"s",""),"")} | U7: 0 | V7: 2 | W7: 20 | X7: 20 | Y7: 4 | Z7: 0 | AD7: 2 | AG7: 1 | AH7: FALSE
B8: =BegDate -> 12/31/20x3 | C8: =IF(C108="Debit",ABS(D108),0) -> 0 | D8: =IF(C108="Credit",ABS(D108),0) -> 0 | E8: =BegDate -> 12/31/20x3 | H8: {=_xlfn.IFS(I8="","",AND(I8<>"",N103),"OK",AND(I8<>"",NOT(N103)),"?")} | Q8: =_xlfn.XLOOKUP(P8,P103:P132,Q103:Q132,0) -> 0 | R8: {=IF(P8<>"",_xlfn.XLOOKUP(P8,P103:P132,R103:R132&"s",""),"")} | U8: 0 | V8: 6 | W8: 20.5 | X8: 3 | Y8: 7 | Z8: 0 | AD8: 9 | AG8: 2 | AH8: FALSE
B9: {=_xlfn._xlws.FILTER(Journal[Transaction '#],Journal[Debit Account]=D5,"")} -> 4 | C9: {=_xlfn._xlws.FILTER(Journal[Dr Amt],Journal[Debit Account]=D5,0)} -> 20 | D9: {=_xlfn._xlws.FILTER(Journal[Cr Amt],Journal[Credit Account]=D5,0)} -> 18 | E9: {=_xlfn._xlws.FILTER(Journal[Transaction '#],Journal[Credit Account]=D5,"")} -> 12 | H9: {=_xlfn.IFS(I9="","",AND(I9<>"",N104),"OK",AND(I9<>"",NOT(N104)),"?")} | Q9: =_xlfn.XLOOKUP(P9,P104:P133,Q104:Q133,0) -> 0 | R9: {=IF(P9<>"",_xlfn.XLOOKUP(P9,P104:P133,R104:R133&"s",""),"")} | X9: 0.05 | Y9: 9 | Z9: 0 | AG9: 9 | AH9: FALSE
H10: {=_xlfn.IFS(I10="","",AND(I10<>"",N105),"OK",AND(I10<>"",NOT(N105)),"?")} | Q10: =_xlfn.XLOOKUP(P10,P105:P134,Q105:Q134,0) -> 0 | R10: {=IF(P10<>"",_xlfn.XLOOKUP(P10,P105:P134,R105:R134&"s",""),"")} | X10: 1.87 | Y10: 11 | Z10: 0 | AG10: 8 | AH10: FALSE
H11: {=_xlfn.IFS(I11="","",AND(I11<>"",N106),"OK",AND(I11<>"",NOT(N106)),"?")} | Q11: =_xlfn.XLOOKUP(P11,P106:P135,Q106:Q135,0) -> 0 | R11: {=IF(P11<>"",_xlfn.XLOOKUP(P11,P106:P135,R106:R135&"s",""),"")} | AH11: FALSE
H12: {=_xlfn.IFS(I12="","",AND(I12<>"",N107),"OK",AND(I12<>"",NOT(N107)),"?")} | Q12: =_xlfn.XLOOKUP(P12,P107:P136,Q107:Q136,0) -> 0 | R12: {=IF(P12<>"",_xlfn.XLOOKUP(P12,P107:P136,R107:R136&"s",""),"")} | AH12: FALSE
H13: {=_xlfn.IFS(I13="","",AND(I13<>"",N108),"OK",AND(I13<>"",NOT(N108)),"?")} | Q13: =_xlfn.XLOOKUP(P13,P108:P137,Q108:Q137,0) -> 0 | R13: {=IF(P13<>"",_xlfn.XLOOKUP(P13,P108:P137,R108:R137&"s",""),"")} | AH13: FALSE
H14: {=_xlfn.IFS(I14="","",AND(I14<>"",N109),"OK",AND(I14<>"",NOT(N109)),"?")} | Q14: =_xlfn.XLOOKUP(P14,P109:P138,Q109:Q138,0) -> 0 | R14: {=IF(P14<>"",_xlfn.XLOOKUP(P14,P109:P138,R109:R138&"s",""),"")} | AH14: FALSE
H15: {=_xlfn.IFS(I15="","",AND(I15<>"",N110),"OK",AND(I15<>"",NOT(N110)),"?")} | Q15: =_xlfn.XLOOKUP(P15,P110:P139,Q110:Q139,0) -> 0 | R15: {=IF(P15<>"",_xlfn.XLOOKUP(P15,P110:P139,R110:R139&"s",""),"")} | AH15: FALSE
H16: {=_xlfn.IFS(I16="","",AND(I16<>"",N111),"OK",AND(I16<>"",NOT(N111)),"?")} | Q16: =_xlfn.XLOOKUP(P16,P111:P140,Q111:Q140,0) -> 0 | R16: {=IF(P16<>"",_xlfn.XLOOKUP(P16,P111:P140,R111:R140&"s",""),"")} | AH16: FALSE
H17: {=_xlfn.IFS(I17="","",AND(I17<>"",N112),"OK",AND(I17<>"",NOT(N112)),"?")} | Q17: =_xlfn.XLOOKUP(P17,P112:P141,Q112:Q141,0) -> 0 | R17: {=IF(P17<>"",_xlfn.XLOOKUP(P17,P112:P141,R112:R141&"s",""),"")} | AH17: FALSE
H18: {=_xlfn.IFS(I18="","",AND(I18<>"",N113),"OK",AND(I18<>"",NOT(N113)),"?")} | Q18: =_xlfn.XLOOKUP(P18,P113:P142,Q113:Q142,0) -> 0 | R18: {=IF(P18<>"",_xlfn.XLOOKUP(P18,P113:P142,R113:R142&"s",""),"")} | V18: =EndDate -> 12/31/20x4 | W18: =MAX(SUM(W5:W17)-SUM(X5:X17),0) -> 17.58 | X18: =MAX(SUM(X5:X17)-SUM(W5:W17),0) -> 0 | Y18: =EndDate -> 12/31/20x4 | AH18: FALSE
H19: {=_xlfn.IFS(I19="","",AND(I19<>"",N114),"OK",AND(I19<>"",NOT(N114)),"?")} | Q19: =_xlfn.XLOOKUP(P19,P114:P143,Q114:Q143,0) -> 0 | R19: {=IF(P19<>"",_xlfn.XLOOKUP(P19,P114:P143,R114:R143&"s",""),"")} | AH19: FALSE
H20: {=_xlfn.IFS(I20="","",AND(I20<>"",N115),"OK",AND(I20<>"",NOT(N115)),"?")} | Q20: =_xlfn.XLOOKUP(P20,P115:P144,Q115:Q144,0) -> 0 | R20: {=IF(P20<>"",_xlfn.XLOOKUP(P20,P115:P144,R115:R144&"s",""),"")} | V20: Totals | AH20: FALSE
B21: =EndDate -> 12/31/20x4 | C21: =MAX(SUM(C8:C20)-SUM(D8:D20),0) -> 2 | D21: =MAX(SUM(D8:D20)-SUM(C8:C20),0) -> 0 | E21: =EndDate -> 12/31/20x4 | H21: {=_xlfn.IFS(I21="","",AND(I21<>"",N116),"OK",AND(I21<>"",NOT(N116)),"?")} | Q21: =_xlfn.XLOOKUP(P21,P116:P145,Q116:Q145,0) -> 0 | R21: {=IF(P21<>"",_xlfn.XLOOKUP(P21,P116:P145,R116:R145&"s",""),"")} | V21: Operating | W21: =SUMIF(U6:U17,"Operating",W6:W17)-SUMIF(Z6:Z17,"Operating",X6:X17) -> 0 | AH21: FALSE
H22: {=_xlfn.IFS(I22="","",AND(I22<>"",N117),"OK",AND(I22<>"",NOT(N117)),"?")} | Q22: =_xlfn.XLOOKUP(P22,P117:P146,Q117:Q146,0) -> 0 | R22: {=IF(P22<>"",_xlfn.XLOOKUP(P22,P117:P146,R117:R146&"s",""),"")} | V22: Investing | W22: =SUMIF(U6:U17,"Investing",W6:W17)-SUMIF(Z6:Z17,"Investing",X6:X17) -> 0 | AH22: FALSE
H23: {=_xlfn.IFS(I23="","",AND(I23<>"",N118),"OK",AND(I23<>"",NOT(N118)),"?")} | Q23: =_xlfn.XLOOKUP(P23,P118:P147,Q118:Q147,0) -> 0 | R23: {=IF(P23<>"",_xlfn.XLOOKUP(P23,P118:P147,R118:R147&"s",""),"")} | V23: Financing | W23: =SUMIF(U6:U17,"Financing",W6:W17)-SUMIF(Z6:Z17,"Financing",X6:X17) -> 0 | AH23: FALSE
C24: Temporary Account | H24: {=_xlfn.IFS(I24="","",AND(I24<>"",N119),"OK",AND(I24<>"",NOT(N119)),"?")} | Q24: =_xlfn.XLOOKUP(P24,P119:P148,Q119:Q148,0) -> 0 | R24: {=IF(P24<>"",_xlfn.XLOOKUP(P24,P119:P148,R119:R148&"s",""),"")} | AH24: FALSE
C25: Account Type: | D25: Revenue | H25: {=_xlfn.IFS(I25="","",AND(I25<>"",N120),"OK",AND(I25<>"",NOT(N120)),"?")} | Q25: =_xlfn.XLOOKUP(P25,P120:P149,Q120:Q149,0) -> 0 | R25: {=IF(P25<>"",_xlfn.XLOOKUP(P25,P120:P149,R120:R149&"s",""),"")} | AH25: FALSE
C26: Account Name: | D26: Sales | Q26: =_xlfn.XLOOKUP(P26,P121:P150,Q121:Q150,0) -> 0 | R26: {=IF(P26<>"",_xlfn.XLOOKUP(P26,P121:P150,R121:R150&"s",""),"")} | AH26: FALSE
Q27: =_xlfn.XLOOKUP(P27,P122:P151,Q122:Q151,0) -> 0 | R27: {=IF(P27<>"",_xlfn.XLOOKUP(P27,P122:P151,R122:R151&"s",""),"")} | AH27: FALSE
B28: ref | C28: =D26 -> Sales | E28: ref | Q28: =_xlfn.XLOOKUP(P28,P123:P152,Q123:Q152,0) -> 0 | R28: {=IF(P28<>"",_xlfn.XLOOKUP(P28,P123:P152,R123:R152&"s",""),"")} | AH28: FALSE
B29: {=_xlfn._xlws.FILTER(Journal[Transaction '#],Journal[Debit Account]=D26,"")} -> 14 | C29: {=_xlfn._xlws.FILTER(Journal[Dr Amt],Journal[Debit Account]=D26,0)} -> 25 | D29: {=_xlfn._xlws.FILTER(Journal[Cr Amt],Journal[Credit Account]=D26,0)} -> 25 | E29: {=_xlfn._xlws.FILTER(Journal[Transaction '#],Journal[Credit Account]=D26,"")} -> 5 | Q29: =_xlfn.XLOOKUP(P29,P124:P153,Q124:Q153,0) -> 0 | R29: {=IF(P29<>"",_xlfn.XLOOKUP(P29,P124:P153,R124:R153&"s",""),"")} | AH29: FALSE
Q30: =_xlfn.XLOOKUP(P30,P125:P154,Q125:Q154,0) -> 0 | R30: {=IF(P30<>"",_xlfn.XLOOKUP(P30,P125:P154,R125:R154&"s",""),"")}
Q31: =_xlfn.XLOOKUP(P31,P126:P155,Q126:Q155,0) -> 0 | R31: {=IF(P31<>"",_xlfn.XLOOKUP(P31,P126:P155,R126:R155&"s",""),"")}
Q32: =_xlfn.XLOOKUP(P32,P127:P156,Q127:Q156,0) -> 0 | R32: {=IF(P32<>"",_xlfn.XLOOKUP(P32,P127:P156,R127:R156&"s",""),"")}
Q33: =_xlfn.XLOOKUP(P33,P128:P157,Q128:Q157,0) -> 0 | R33: {=IF(P33<>"",_xlfn.XLOOKUP(P33,P128:P157,R128:R157&"s",""),"")}
Q34: =_xlfn.XLOOKUP(P34,P129:P158,Q129:Q158,0) -> 0 | R34: {=IF(P34<>"",_xlfn.XLOOKUP(P34,P129:P158,R129:R158&"s",""),"")}
Q35: =_xlfn.XLOOKUP(P35,P130:P159,Q130:Q159,0) -> 0 | R35: {=IF(P35<>"",_xlfn.XLOOKUP(P35,P130:P159,R130:R159&"s",""),"")}
Q36: =_xlfn.XLOOKUP(P36,P131:P160,Q131:Q160,0) -> 0 | R36: {=IF(P36<>"",_xlfn.XLOOKUP(P36,P131:P160,R131:R160&"s",""),"")}
Q37: =_xlfn.XLOOKUP(P37,P132:P161,Q132:Q161,0) -> 0 | R37: {=IF(P37<>"",_xlfn.XLOOKUP(P37,P132:P161,R132:R161&"s",""),"")}
B38: =EndDate -> 12/31/20x4 | C38: =MAX(SUM(C29:C37)-SUM(D29:D37),0) -> 0 | D38: =MAX(SUM(D29:D37)-SUM(C29:C37),0) -> 0 | E38: =EndDate -> 12/31/20x4 | Q38: =_xlfn.XLOOKUP(P38,P133:P162,Q133:Q162,0) -> 0 | R38: {=IF(P38<>"",_xlfn.XLOOKUP(P38,P133:P162,R133:R162&"s",""),"")}
C39: =IF(MAX(C38,D38)>0,"Balance must be brought to zero by "&EndDate,"") | Q39: =_xlfn.XLOOKUP(P39,P134:P163,Q134:Q163,0) -> 0 | R39: {=IF(P39<>"",_xlfn.XLOOKUP(P39,P134:P163,R134:R163&"s",""),"")}
Q40: =_xlfn.XLOOKUP(P40,P135:P164,Q135:Q164,0) -> 0 | R40: {=IF(P40<>"",_xlfn.XLOOKUP(P40,P135:P164,R135:R164&"s",""),"")}
Q41: =_xlfn.XLOOKUP(P41,P136:P165,Q136:Q165,0) -> 0 | R41: {=IF(P41<>"",_xlfn.XLOOKUP(P41,P136:P165,R136:R165&"s",""),"")}
Q42: =_xlfn.XLOOKUP(P42,P137:P166,Q137:Q166,0) -> 0 | R42: {=IF(P42<>"",_xlfn.XLOOKUP(P42,P137:P166,R137:R166&"s",""),"")}
Q43: =_xlfn.XLOOKUP(P43,P138:P167,Q138:Q167,0) -> 0 | R43: {=IF(P43<>"",_xlfn.XLOOKUP(P43,P138:P167,R138:R167&"s",""),"")}
Q44: =_xlfn.XLOOKUP(P44,P139:P168,Q139:Q168,0) -> 0 | R44: {=IF(P44<>"",_xlfn.XLOOKUP(P44,P139:P168,R139:R168&"s",""),"")}
Q45: =_xlfn.XLOOKUP(P45,P140:P169,Q140:Q169,0) -> 0 | R45: {=IF(P45<>"",_xlfn.XLOOKUP(P45,P140:P169,R140:R169&"s",""),"")}
Q46: =_xlfn.XLOOKUP(P46,P141:P170,Q141:Q170,0) -> 0 | R46: {=IF(P46<>"",_xlfn.XLOOKUP(P46,P141:P170,R141:R170&"s",""),"")}
Q47: =_xlfn.XLOOKUP(P47,P142:P171,Q142:Q171,0) -> 0 | R47: {=IF(P47<>"",_xlfn.XLOOKUP(P47,P142:P171,R142:R171&"s",""),"")}
Q48: =_xlfn.XLOOKUP(P48,P143:P172,Q143:Q172,0) -> 0 | R48: {=IF(P48<>"",_xlfn.XLOOKUP(P48,P143:P172,R143:R172&"s",""),"")}
Q49: =_xlfn.XLOOKUP(P49,P144:P173,Q144:Q173,0) -> 0 | R49: {=IF(P49<>"",_xlfn.XLOOKUP(P49,P144:P173,R144:R173&"s",""),"")}
Q50: =_xlfn.XLOOKUP(P50,P145:P174,Q145:Q174,0) -> 0 | R50: {=IF(P50<>"",_xlfn.XLOOKUP(P50,P145:P174,R145:R174&"s",""),"")}
C100: {=_xlfn.IFS(D4="Asset","MD_Asset",D4="Liability","MD_Liability",D4="Equity","MD_Equity")} -> MD_Asset | D100: {=_xlfn.IFS(D4="Asset","BegBalanceSheet_Assets",D4="Liability","BegBalanceSheet_Liabilities",D4="Equity","BegBalanceSheet_Equities")} -> BegBalanceSheet_Assets | I100: AccntType | J100: DrAccnt | K100: CrAccnt | L100: DrAmt | M100: CrAmt | P100: Revenues | Q100: Balance | W100: ="MD_Asset" -> MD_Asset | X100: ="BegBalanceSheet_Assets" -> BegBalanceSheet_Assets
